Workbook
Name __dol1: #REF!
Name __END1: #REF!
Name __kurs_dol__: #REF!
Name __stroka__: #REF!
Name _dol1: #REF!
Name _END1: #REF!
Name aned110: #REF!
Name aned111: #REF!
Name aned112: #REF!
Name aned113: #REF!
Name aned146: #REF!
Name aned158: #REF!
Name aned161: #REF!
Name aned162: #REF!
Name aned170: #REF!
Name aned184: #REF!
Name aned191: #REF!
Name aned194: #REF!
Name aned213: #REF!
Name aned224: #REF!
Name aned239: #REF!
Name aned34: #REF!
Name aned50: #REF!
Name aned60: #REF!
Name aned61: #REF!
Name aned62: #REF!
Name aned620: #REF!
Name aned624: #REF!
Name aned628: #REF!
Name aned629: #REF!
Name aned63: #REF!
Name aned632: #REF!
Name aned636: #REF!
Name aned637: #REF!
Name aned639: #REF!
Name aned64: #REF!
Name aned647: #REF!
Name aned65: #REF!
Name aned657: #REF!
Name aned662: #REF!
Name aned668: #REF!
Name aned680: #REF!
Name aned681: #REF!
Name aned682: #REF!
Name aned683: #REF!
Name aned716: #REF!
Name aned718: #REF!
Name aned719: #REF!
Name aned72: #REF!
Name aned728: #REF!
Name aned729: #REF!
Name aned731: #REF!
Name aned76: #REF!
Name aned77: #REF!
Name aned79: #REF!
Name aned812: #REF!
Name aned86: #REF!
Name aned87: #REF!
Name aned882: #REF!
Name aned900: #REF!

Sheet 0
A1: BaaS - параметры модели
D4: 46023 | E4: 46054 | F4: 46082 | G4: 46113 | H4: 46143 | I4: 46174 | J4: 46204 | K4: 46235 | L4: 46266 | M4: 46296 | N4: 46327 | O4: 46357 | P4: 46388 | Q4: 46419 | R4: 46447 | S4: 46478 | T4: 46508 | U4: 46539 | V4: 46569 | W4: 46600 | X4: 46631 | Y4: 46661 | Z4: 46692 | AA4: 46722 | AB4: 46753 | AC4: 46784 | AD4: 46813 | AE4: 46844 | AF4: 46874 | AG4: 46905 | AH4: 46935 | AI4: 46966 | AJ4: 46997 | AK4: 47027 | AL4: 47058 | AM4: 47088 | AO4: =YEAR(O4) -> 2026 | AP4: =YEAR(AA4) -> 2027 | AQ4: =YEAR(AM4) -> 2028
D5: m1 | E5: m2 | F5: m3 | G5: m4 | H5: m5 | I5: m6 | J5: m7 | K5: m8 | L5: m9 | M5: m10 | N5: m11 | O5: m12 | P5: m13 | Q5: m14 | R5: m15 | S5: m16 | T5: m17 | U5: m18 | V5: m19 | W5: m20 | X5: m21 | Y5: m22 | Z5: m23 | AA5: m24 | AB5: m25 | AC5: m26 | AD5: m27 | AE5: m28 | AF5: m29 | AG5: m30 | AH5: m31 | AI5: m32 | AJ5: m33 | AK5: m34 | AL5: m35 | AM5: m36 | AO5: Y1 | AP5: Y2 | AQ5: Y3
D6: 1 | E6: =D6+1 -> 2 | F6: =E6+1 -> 3 | G6: =F6+1 -> 4 | H6: =G6+1 -> 5 | I6: =H6+1 -> 6 | J6: =I6+1 -> 7 | K6: =J6+1 -> 8 | L6: =K6+1 -> 9 | ... AM6: =AL6+1 -> 36
A8: Показатель | B8: ЕИ | C8: Отв.исп.
A9: общее количество партнеров, в т.ч.: | D9: 15 | E9: =D9+1 -> 16 | F9: =E9+1 -> 17 | G9: =F9+1 -> 18 | H9: =G9+1 -> 19 | I9: =H9+1 -> 20 | J9: 20 | K9: =J9+2 -> 22 | L9: =K9+2 -> 24 | M9: =L9+2 -> 26 | N9: =M9+2 -> 28 | O9: 30 | P9: =O9 -> 30 | Q9: =P9 -> 30 | R9: =Q9 -> 30 | S9: =R9 -> 30 | T9: =S9 -> 30 | U9: =T9 -> 30 | V9: =U9 -> 30 | W9: =V9 -> 30 | ... AM9: =AL9 -> 30 | AO9: =O9 -> 30 | AP9: =AA9 -> 30 | AQ9: =AM9 -> 30
A10: кредитование (свои кредиты) | B10: шт | D10: 15 | E10: =D10+1 -> 16 | F10: =E10+1 -> 17 | G10: =F10+1 -> 18 | H10: =G10+1 -> 19 | I10: =H10+1 -> 20 | J10: 20 | K10: =J10+2 -> 22 | L10: =K10+2 -> 24 | M10: =L10+2 -> 26 | N10: =M10+2 -> 28 | O10: 30 | P10: =O10 -> 30 | Q10: =P10 -> 30 | R10: =Q10 -> 30 | S10: =R10 -> 30 | T10: =S10 -> 30 | U10: =T10 -> 30 | V10: =U10 -> 30 | W10: =V10 -> 30 | ... AM10: =AL10 -> 30 | AO10: =O10 -> 30 | AP10: =AA10 -> 30 | AQ10: =AM10 -> 30
A11: кредитование (чужие кредиты) | B11: шт | D11: 2 | E11: =D11+1 -> 3 | F11: =E11+1 -> 4 | G11: =F11+1 -> 5 | H11: =G11+1 -> 6 | I11: =H11+1 -> 7 | J11: =I11+1 -> 8 | K11: =J11+1 -> 9 | L11: =K11+1 -> 10 | ... AM11: =AL11+1 -> 37 | AO11: =O11 -> 13 | AP11: =AA11 -> 25 | AQ11: =AM11 -> 37
A12: депозиты | B12: шт | D12: 15 | E12: =D12+1 -> 16 | F12: =E12+1 -> 17 | G12: =F12+1 -> 18 | H12: =G12+1 -> 19 | I12: =H12+1 -> 20 | J12: 20 | K12: =J12+2 -> 22 | L12: =K12+2 -> 24 | M12: =L12+2 -> 26 | N12: =M12+2 -> 28 | O12: 30 | P12: =O12 -> 30 | Q12: =P12 -> 30 | R12: =Q12 -> 30 | S12: =R12 -> 30 | T12: =S12 -> 30 | U12: =T12 -> 30 | V12: =U12 -> 30 | W12: =V12 -> 30 | ... AM12: =AL12 -> 30 | AO12: =O12 -> 30 | AP12: =AA12 -> 30 | AQ12: =AM12 -> 30
A13: DCB ID / DCB BIO | B13: шт | D13: 15 | E13: =D13+1 -> 16 | F13: =E13+1 -> 17 | G13: =F13+1 -> 18 | H13: =G13+1 -> 19 | I13: =H13+1 -> 20 | J13: 20 | K13: =J13+2 -> 22 | L13: =K13+2 -> 24 | M13: =L13+2 -> 26 | N13: =M13+2 -> 28 | O13: 30 | P13: =O13 -> 30 | Q13: =P13 -> 30 | R13: =Q13 -> 30 | S13: =R13 -> 30 | T13: =S13 -> 30 | U13: =T13 -> 30 | V13: =U13 -> 30 | W13: =V13 -> 30 | ... AM13: =AL13 -> 30 | AO13: =O13 -> 30 | AP13: =AA13 -> 30 | AQ13: =AM13 -> 30
A14: QR прием | B14: шт | D14: 7 | E14: 7 | F14: 8 | G14: 8 | H14: 8 | I14: 9 | J14: 9 | K14: 9 | L14: 10 | M14: 10 | N14: 12 | O14: 14 | P14: 14 | Q14: 14 | R14: 14 | S14: 14 | T14: 14 | U14: 14 | V14: 14 | W14: 14 | X14: 14 | Y14: 14 | Z14: 14 | AA14: 14 | AB14: 14 | AC14: 14 | AD14: 14 | AE14: 14 | AF14: 14 | AG14: 14 | AH14: 14 | AI14: 14 | AJ14: 14 | AK14: 14 | AL14: 14 | AM14: 14 | AO14: =O14 -> 14 | AP14: =AA14 -> 14 | AQ14: =AM14 -> 14
A15: QR оплата | B15: шт | D15: 5 | E15: 5 | F15: 5 | G15: 6 | H15: 6 | I15: 6 | J15: 7 | K15: 7 | L15: 7 | M15: 8 | N15: 8 | O15: 9 | P15: 9 | Q15: 9 | R15: 9 | S15: 9 | T15: 9 | U15: 9 | V15: 9 | W15: 9 | X15: 9 | Y15: 9 | Z15: 9 | AA15: 9 | AB15: 9 | AC15: 9 | AD15: 9 | AE15: 9 | AF15: 9 | AG15: 9 | AH15: 9 | AI15: 9 | AJ15: 9 | AK15: 9 | AL15: 9 | AM15: 9 | AO15: =O15 -> 9 | AP15: =AA15 -> 9 | AQ15: =AM15 -> 9
A16: кошелек | B16: шт | D16: 2 | E16: 2 | F16: 2 | G16: 3 | H16: 3 | I16: 4 | J16: 4 | K16: 4 | L16: 5 | M16: 5 | N16: 5 | O16: 6 | P16: =O16 -> 6 | Q16: =P16 -> 6 | R16: =Q16 -> 6 | S16: =R16 -> 6 | T16: =S16 -> 6 | U16: =T16 -> 6 | V16: =U16 -> 6 | W16: =V16 -> 6 | ... AM16: =AL16 -> 6 | AO16: =O16 -> 6 | AP16: =AA16 -> 6 | AQ16: =AM16 -> 6
A17: расчетный счет | B17: шт | D17: 1 | E17: 1 | F17: 2 | G17: 2 | H17: 3 | I17: 3 | J17: 4 | K17: 5 | L17: 6 | M17: 7 | N17: 8 | O17: 8 | P17: =O17 -> 8 | Q17: =P17 -> 8 | R17: =Q17 -> 8 | S17: =R17 -> 8 | T17: =S17 -> 8 | U17: =T17 -> 8 | V17: =U17 -> 8 | W17: =V17 -> 8 | ... AM17: =AL17 -> 8 | AO17: =O17 -> 8 | AP17: =AA17 -> 8 | AQ17: =AM17 -> 8
A18: карта | B18: шт | D18: 1 | E18: =D18+1 -> 2 | F18: 2 | G18: 2 | H18: 2 | I18: 3 | J18: 3 | K18: 3 | L18: 3 | M18: 3 | N18: 4 | O18: 4 | P18: =O18 -> 4 | Q18: =P18 -> 4 | R18: =Q18 -> 4 | S18: =R18 -> 4 | T18: =S18 -> 4 | U18: =T18 -> 4 | V18: =U18 -> 4 | W18: =V18 -> 4 | ... AM18: =AL18 -> 4 | AO18: =O18 -> 4 | AP18: =AA18 -> 4 | AQ18: =AM18 -> 4
A19: онлайн конвертация | B19: шт | D19: 1 | E19: 1 | F19: 1 | G19: 2 | H19: 2 | I19: 2 | J19: 3 | K19: 3 | L19: 4 | M19: 5 | N19: 5 | O19: 6 | P19: =O19 -> 6 | Q19: =P19 -> 6 | R19: =Q19 -> 6 | S19: =R19 -> 6 | T19: =S19 -> 6 | U19: =T19 -> 6 | V19: =U19 -> 6 | W19: =V19 -> 6 | ... AM19: =AL19 -> 6 | AO19: =O19 -> 6 | AP19: =AA19 -> 6 | AQ19: =AM19 -> 6
A20: онлайн переводы | B20: шт | D20: 23 | E20: 23 | F20: =E20+1 -> 24 | G20: 24 | H20: =G20+1 -> 25 | I20: 25 | J20: 27 | K20: 28 | L20: 28 | M20: 29 | N20: 29 | O20: 30 | P20: =O20 -> 30 | Q20: =P20 -> 30 | R20: =Q20 -> 30 | S20: =R20 -> 30 | T20: =S20 -> 30 | U20: =T20 -> 30 | V20: =U20 -> 30 | W20: =V20 -> 30 | ... AM20: =AL20 -> 30 | AO20: =O20 -> 30 | AP20: =AA20 -> 30 | AQ20: =AM20 -> 30
A21: (ИЭ) Привязка карты и списания с карты | B21: шт | D21: 15 | E21: =D21+1 -> 16 | F21: =E21+1 -> 17 | G21: =F21+1 -> 18 | H21: =G21+1 -> 19 | I21: =H21+1 -> 20 | J21: 20 | K21: =J21+2 -> 22 | L21: =K21+2 -> 24 | M21: =L21+2 -> 26 | N21: =M21+2 -> 28 | O21: 30 | P21: =O21 -> 30 | Q21: =P21 -> 30 | R21: =Q21 -> 30 | S21: =R21 -> 30 | T21: =S21 -> 30 | U21: =T21 -> 30 | V21: =U21 -> 30 | W21: =V21 -> 30 | ... AM21: =AL21 -> 30 | AO21: =O21 -> 30 | AP21: =AA21 -> 30 | AQ21: =AM21 -> 30
A22: (ИЭ) QR-генерация | B22: шт | D22: 15 | E22: =D22+1 -> 16 | F22: =E22+1 -> 17 | G22: =F22+1 -> 18 | H22: =G22+1 -> 19 | I22: =H22+1 -> 20 | J22: 20 | K22: =J22+2 -> 22 | L22: =K22+2 -> 24 | M22: =L22+2 -> 26 | N22: =M22+2 -> 28 | O22: 30 | P22: =O22 -> 30 | Q22: =P22 -> 30 | R22: =Q22 -> 30 | S22: =R22 -> 30 | T22: =S22 -> 30 | U22: =T22 -> 30 | V22: =U22 -> 30 | W22: =V22 -> 30 | ... AM22: =AL22 -> 30 | AO22: =O22 -> 30 | AP22: =AA22 -> 30 | AQ22: =AM22 -> 30
A23: (ИЭ) Переход в МП DCB + платежи из него | B23: шт | D23: 15 | E23: =D23+1 -> 16 | F23: =E23+1 -> 17 | G23: =F23+1 -> 18 | H23: =G23+1 -> 19 | I23: =H23+1 -> 20 | J23: 20 | K23: =J23+2 -> 22 | L23: =K23+2 -> 24 | M23: =L23+2 -> 26 | N23: =M23+2 -> 28 | O23: 30 | P23: =O23 -> 30 | Q23: =P23 -> 30 | R23: =Q23 -> 30 | S23: =R23 -> 30 | T23: =S23 -> 30 | U23: =T23 -> 30 | V23: =U23 -> 30 | W23: =V23 -> 30 | ... AM23: =AL23 -> 30 | AO23: =O23 -> 30 | AP23: =AA23 -> 30 | AQ23: =AM23 -> 30
A24: продажа страховых полисов | B24: шт | D24: 2 | E24: 2 | F24: 3 | G24: 3 | H24: 3 | I24: 3 | J24: 4 | K24: 4 | L24: 5 | M24: 5 | N24: 5 | O24: 6 | P24: =O24 -> 6 | Q24: =P24 -> 6 | R24: =Q24 -> 6 | S24: =R24 -> 6 | T24: =S24 -> 6 | U24: =T24 -> 6 | V24: =U24 -> 6 | W24: =V24 -> 6 | ... AM24: =AL24 -> 6 | AO24: =O24 -> 6 | AP24: =AA24 -> 6 | AQ24: =AM24 -> 6
A25: курсы валют
A26: RUB | D26: 1.01 | E26: 1.01 | F26: 1.01 | G26: 1.01 | H26: 1.01 | I26: 1 | J26: 1 | K26: 1 | L26: 1 | M26: 1 | N26: 1 | O26: 1 | P26: 1 | Q26: 1 | R26: 0.97 | S26: 0.97 | T26: 0.97 | U26: 0.97 | V26: 0.97 | W26: 0.97 | X26: 0.97 | Y26: 0.97 | Z26: 0.97 | AA26: 0.97 | AB26: 0.97 | AC26: 0.97 | AD26: 0.97 | AE26: 0.97 | AF26: 0.97 | AG26: 0.97 | AH26: 0.97 | AI26: 0.97 | AJ26: 0.97 | AK26: 0.97 | AL26: 0.97 | AM26: 0.97
A27: USD | D27: 85 | E27: 85 | F27: 85 | G27: 85 | H27: 85 | I27: 85 | J27: 85 | K27: 85 | L27: 85 | M27: 85 | N27: 85 | O27: 85 | P27: 85 | Q27: 85 | R27: 85 | S27: 85 | T27: 85 | U27: 85 | V27: 85 | W27: 85 | X27: 85 | Y27: 85 | Z27: 85 | AA27: 85 | AB27: 85 | AC27: 85 | AD27: 85 | AE27: 85 | AF27: 85 | AG27: 85 | AH27: 85 | AI27: 85 | AJ27: 85 | AK27: 85 | AL27: 85 | AM27: 85

Sheet BaaS.1
A1: BaaS - Онлайн кредитование
D3: 46023 | E3: 46054 | F3: 46082 | G3: 46113 | H3: 46143 | I3: 46174 | J3: 46204 | K3: 46235 | L3: 46266 | M3: 46296 | N3: 46327 | O3: 46357 | P3: 46388 | Q3: 46419 | R3: 46447 | S3: 46478 | T3: 46508 | U3: 46539 | V3: 46569 | W3: 46600 | X3: 46631 | Y3: 46661 | Z3: 46692 | AA3: 46722 | AB3: 46753 | AC3: 46784 | AD3: 46813 | AE3: 46844 | AF3: 46874 | AG3: 46905 | AH3: 46935 | AI3: 46966 | AJ3: 46997 | AK3: 47027 | AL3: 47058 | AM3: 47088 | AO3: =YEAR(O3) -> 2026 | AP3: =YEAR(AA3) -> 2027 | AQ3: =YEAR(AM3) -> 2028
D4: m1 | E4: m2 | F4: m3 | G4: m4 | H4: m5 | I4: m6 | J4: m7 | K4: m8 | L4: m9 | M4: m10 | N4: m11 | O4: m12 | P4: m13 | Q4: m14 | R4: m15 | S4: m16 | T4: m17 | U4: m18 | V4: m19 | W4: m20 | X4: m21 | Y4: m22 | Z4: m23 | AA4: m24 | AB4: m25 | AC4: m26 | AD4: m27 | AE4: m28 | AF4: m29 | AG4: m30 | AH4: m31 | AI4: m32 | AJ4: m33 | AK4: m34 | AL4: m35 | AM4: m36 | AO4: Y1 | AP4: Y2 | AQ4: Y3
D5: 1 | E5: =D5+1 -> 2 | F5: =E5+1 -> 3 | G5: =F5+1 -> 4 | H5: =G5+1 -> 5 | I5: =H5+1 -> 6 | J5: =I5+1 -> 7 | K5: =J5+1 -> 8 | L5: =K5+1 -> 9 | ... AM5: =AL5+1 -> 36
A7: Итого | B7: ЕИ | C7: Отв.исп.
A8: чистый операционный доход | B8: тыс сом | D8: =D32+D54+D76+D102+D118+D129 -> -524.4951 | E8: =E32+E54+E76+E102+E118+E129 -> -252.67733 | F8: =F32+F54+F76+F102+F118+F129 -> -17.422927 | G8: =G32+G54+G76+G102+G118+G129 -> 202.48295 | H8: =H32+H54+H76+H102+H118+H129 -> 411.91642 | I8: =I32+I54+I76+I102+I118+I129 -> 614.18897 | J8: =J32+J54+J76+J102+J118+J129 -> 846.66095 | K8: =K32+K54+K76+K102+K118+K129 -> 985.20545 | ... AM8: =AM32+AM54+AM76+AM102+AM118+AM129 -> 5129.3657 | AO8: =SUM(D8:O8) -> 7974.2142 | AP8: =SUM(P8:AA8) -> 37528.639 | AQ8: =SUM(AB8:AM8) -> 55973.163
A9: операционные расходы | B9: тыс сом | D9: =D33+D55+D77+D103+D119+D130 -> -62.717173 | E9: =E33+E55+E77+E103+E119+E130 -> -52.432524 | F9: =F33+F55+F77+F103+F119+F130 -> -65.156034 | G9: =G33+G55+G77+G103+G119+G130 -> -77.338018 | H9: =H33+H55+H77+H103+H119+H130 -> -89.143119 | I9: =I33+I55+I77+I103+I119+I130 -> -100.67754 | J9: =J33+J55+J77+J103+J119+J130 -> -111.37862 | K9: =K33+K55+K77+K103+K119+K130 -> -122.37435 | ... AM9: =AM33+AM55+AM77+AM103+AM119+AM130 -> -315.89162 | AO9: =SUM(D9:O9) -> -1295.5684 | AP9: =SUM(P9:AA9) -> -2837.7126 | AQ9: =SUM(AB9:AM9) -> -3597.163
A10: прибыль | B10: тыс сом | D10: =D34+D56+D78+D104+D120+D131 -> -587.21227 | E10: =E34+E56+E78+E104+E120+E131 -> -305.10985 | F10: =F34+F56+F78+F104+F120+F131 -> -82.578961 | G10: =G34+G56+G78+G104+G120+G131 -> 125.14493 | H10: =H34+H56+H78+H104+H120+H131 -> 322.7733 | I10: =I34+I56+I78+I104+I120+I131 -> 513.51143 | J10: =J34+J56+J78+J104+J120+J131 -> 735.28233 | K10: =K34+K56+K78+K104+K120+K131 -> 862.8311 | ... AM10: =AM34+AM56+AM78+AM104+AM120+AM131 -> 4813.4741 | AO10: =SUM(D10:O10) -> 6678.6457 | AP10: =SUM(P10:AA10) -> 34690.927 | AQ10: =SUM(AB10:AM10) -> 52376
A12: Потребительский кредит | B12: ЕИ | C12: Отв.исп.
A13: количество партнеров | B13: шт | D13: ='0'!D10 -> 15 | E13: ='0'!E10 -> 16 | F13: ='0'!F10 -> 17 | G13: ='0'!G10 -> 18 | H13: ='0'!H10 -> 19 | I13: ='0'!I10 -> 20 | J13: ='0'!J10 -> 20 | K13: ='0'!K10 -> 22 | ... AM13: ='0'!AM10 -> 30 | AO13: =O13 -> 30 | AP13: =AA13 -> 30 | AQ13: =AM13 -> 30
A14: среднее количество выдач на 1 партнера | B14: шт | D14: 30 | E14: 30 | F14: 30 | G14: 30 | H14: 30 | I14: 30 | J14: 30 | K14: 30 | L14: 30 | M14: 30 | N14: 30 | O14: 30 | P14: 30 | Q14: 30 | R14: 30 | S14: 30 | T14: 30 | U14: 30 | V14: 30 | W14: 30 | X14: 30 | Y14: 30 | Z14: 30 | AA14: 30 | AB14: 30 | AC14: 30 | AD14: 30 | AE14: 30 | AF14: 30 | AG14: 30 | AH14: 30 | AI14: 30 | AJ14: 30 | AK14: 30 | AL14: 30 | AM14: 30 | AO14: =AVERAGE(D14:O14) -> 30 | AP14: =AVERAGE(P14:AA14) -> 30 | AQ14: =AVERAGE(AB14:AM14) -> 30
A15: количество выдач | B15: шт | D15: =D13*D14 -> 450 | E15: =E13*E14 -> 480 | F15: =F13*F14 -> 510 | G15: =G13*G14 -> 540 | H15: =H13*H14 -> 570 | I15: =I13*I14 -> 600 | J15: =J13*J14 -> 600 | K15: =K13*K14 -> 660 | ... AM15: =AM13*AM14 -> 900 | AO15: =SUM(D15:O15) -> 7650 | AP15: =SUM(P15:AA15) -> 10800 | AQ15: =SUM(AB15:AM15) -> 10800
A16: ср. сумма выдачи | B16: тыс сом | D16: 50 | E16: 50 | F16: 50 | G16: 50 | H16: 50 | I16: 50 | J16: 50 | K16: 50 | L16: 50 | M16: 50 | N16: 50 | O16: 50 | P16: 50 | Q16: 50 | R16: 50 | S16: 50 | T16: 50 | U16: 50 | V16: 50 | W16: 50 | X16: 50 | Y16: 50 | Z16: 50 | AA16: 50 | AB16: 50 | AC16: 50 | AD16: 50 | AE16: 50 | AF16: 50 | AG16: 50 | AH16: 50 | AI16: 50 | AJ16: 50 | AK16: 50 | AL16: 50 | AM16: 50 | AO16: =AVERAGE(D16:O16) -> 50 | AP16: =AVERAGE(P16:AA16) -> 50 | AQ16: =AVERAGE(AB16:AM16) -> 50
A17: выдачи | B17: тыс сом | D17: =D15*D16 -> 22500 | E17: =E15*E16 -> 24000 | F17: =F15*F16 -> 25500 | G17: =G15*G16 -> 27000 | H17: =H15*H16 -> 28500 | I17: =I15*I16 -> 30000 | J17: =J15*J16 -> 30000 | K17: =K15*K16 -> 33000 | ... AM17: =AM15*AM16 -> 45000 | AO17: =SUM(D17:O17) -> 382500 | AP17: =SUM(P17:AA17) -> 540000 | AQ17: =SUM(AB17:AM17) -> 540000
A18: cр. срок портфеля | B18: мес | D18: 12 | E18: 12 | F18: 12 | G18: 12 | H18: 12 | I18: 12 | J18: 12 | K18: 12 | L18: 12 | M18: 12 | N18: 12 | O18: 12 | P18: 12 | Q18: 12 | R18: 12 | S18: 12 | T18: 12 | U18: 12 | V18: 12 | W18: 12 | X18: 12 | Y18: 12 | Z18: 12 | AA18: 12 | AB18: 12 | AC18: 12 | AD18: 12 | AE18: 12 | AF18: 12 | AG18: 12 | AH18: 12 | AI18: 12 | AJ18: 12 | AK18: 12 | AL18: 12 | AM18: 12 | AO18: =AVERAGE(D18:O18) -> 12 | AP18: =AVERAGE(P18:AA18) -> 12 | AQ18: =AVERAGE(AB18:AM18) -> 12
A19: погашения | B19: тыс сом | D19: 0 | E19: =D20/E18 -> 1875 | F19: =E20/F18 -> 3718.75 | G19: =F20/G18 -> 5533.8542 | H19: =G20/H18 -> 7322.6997 | I19: =H20/I18 -> 9087.4747 | J19: =I20/J18 -> 10830.185 | K19: =J20/K18 -> 12427.67 | L19: =K20/L18 -> 14142.031 | ... AM19: =AL20/AM18 -> 41889.215 | AO19: =SUM(D19:O19) -> 118677.39 | AP19: =SUM(P19:AA19) -> 361035.84 | AQ19: =SUM(AB19:AM19) -> 477005.4
A20: кредитный портфель | B20: тыс сом | D20: =D17-D19 -> 22500 | E20: =D20+E17-E19 -> 44625 | F20: =E20+F17-F19 -> 66406.25 | G20: =F20+G17-G19 -> 87872.396 | H20: =G20+H17-H19 -> 109049.7 | I20: =H20+I17-I19 -> 129962.22 | J20: =I20+J17-J19 -> 149132.04 | K20: =J20+K17-K19 -> 169704.37 | L20: =K20+L17-L19 -> 191562.34 | ... AM20: =AL20+AM17-AM19 -> 505781.37 | AO20: =O20 -> 263822.61 | AP20: =AA20 -> 442786.77 | AQ20: =AM20 -> 505781.37
A21: доля просроченной задолженности, % | B21: % | D21: 0.04 | E21: 0.04 | F21: 0.04 | G21: 0.04 | H21: 0.04 | I21: 0.04 | J21: 0.04 | K21: 0.04 | L21: 0.04 | M21: 0.04 | N21: 0.04 | O21: 0.04 | P21: 0.04 | Q21: 0.04 | R21: 0.04 | S21: 0.04 | T21: 0.04 | U21: 0.04 | V21: 0.04 | W21: 0.04 | X21: 0.04 | Y21: 0.04 | Z21: 0.04 | AA21: 0.04 | AB21: 0.04 | AC21: 0.04 | AD21: 0.04 | AE21: 0.04 | AF21: 0.04 | AG21: 0.04 | AH21: 0.04 | AI21: 0.04 | AJ21: 0.04 | AK21: 0.04 | AL21: 0.04 | AM21: 0.04 | AO21: =O21 -> 0.04 | AP21: =AA21 -> 0.04 | AQ21: =AM21 -> 0.04
A22: просроченная задолженность | B22: тыс сом | D22: =D20*D21 -> 900 | E22: =E20*E21 -> 1785 | F22: =F20*F21 -> 2656.25 | G22: =G20*G21 -> 3514.8958 | H22: =H20*H21 -> 4361.9878 | I22: =I20*I21 -> 5198.4889 | J22: =J20*J21 -> 5965.2815 | K22: =K20*K21 -> 6788.1747 | ... AM22: =AM20*AM21 -> 20231.255 | AO22: =SUM(D22:O22) -> 67518.052 | AP22: =SUM(P22:AA22) -> 180455.77 | AQ22: =SUM(AB22:AM22) -> 231482.38
A23: комиссия партнеру | B23: % | D23: 0 | E23: 0 | F23: 0 | G23: 0 | H23: 0 | I23: 0 | J23: 0 | K23: 0 | L23: 0 | M23: 0 | N23: 0 | O23: 0 | P23: 0 | Q23: 0 | R23: 0 | S23: 0 | T23: 0 | U23: 0 | V23: 0 | W23: 0 | X23: 0 | Y23: 0 | Z23: 0 | AA23: 0 | AB23: 0 | AC23: 0 | AD23: 0 | AE23: 0 | AF23: 0 | AG23: 0 | AH23: 0 | AI23: 0 | AJ23: 0 | AK23: 0 | AL23: 0 | AM23: 0 | AO23: =AVERAGE(D23:O23) -> 0 | AP23: =AVERAGE(P23:AA23) -> 0 | AQ23: =AVERAGE(AB23:AM23) -> 0
A24: ср. % ставка портфеля | B24: % | D24: 0.24 | E24: 0.24 | F24: 0.24 | G24: 0.24 | H24: 0.24 | I24: 0.24 | J24: 0.24 | K24: 0.24 | L24: 0.24 | M24: 0.24 | N24: 0.24 | O24: 0.24 | P24: 0.24 | Q24: 0.24 | R24: 0.24 | S24: 0.24 | T24: 0.24 | U24: 0.24 | V24: 0.24 | W24: 0.24 | X24: 0.24 | Y24: 0.24 | Z24: 0.24 | AA24: 0.24 | AB24: 0.24 | AC24: 0.24 | AD24: 0.24 | AE24: 0.24 | AF24: 0.24 | AG24: 0.24 | AH24: 0.24 | AI24: 0.24 | AJ24: 0.24 | AK24: 0.24 | AL24: 0.24 | AM24: 0.24 | AO24: =AVERAGE(D24:O24) -> 0.24 | AP24: =AVERAGE(P24:AA24) -> 0.24 | AQ24: =AVERAGE(AB24:AM24) -> 0.24
A25: ср. % ставка фондирования | B25: % | D25: 0.15 | E25: 0.15 | F25: 0.15 | G25: 0.15 | H25: 0.15 | I25: 0.15 | J25: 0.15 | K25: 0.15 | L25: 0.15 | M25: 0.15 | N25: 0.15 | O25: 0.15 | P25: 0.15 | Q25: 0.15 | R25: 0.15 | S25: 0.15 | T25: 0.15 | U25: 0.15 | V25: 0.15 | W25: 0.15 | X25: 0.15 | Y25: 0.15 | Z25: 0.15 | AA25: 0.15 | AB25: 0.15 | AC25: 0.15 | AD25: 0.15 | AE25: 0.15 | AF25: 0.15 | AG25: 0.15 | AH25: 0.15 | AI25: 0.15 | AJ25: 0.15 | AK25: 0.15 | AL25: 0.15 | AM25: 0.15 | AO25: =AVERAGE(D25:O25) -> 0.15 | AP25: =AVERAGE(P25:AA25) -> 0.15 | AQ25: =AVERAGE(AB25:AM25) -> 0.15
A26: ср. % резервирования | B26: % | D26: 0.02 | E26: 0.02 | F26: 0.02 | G26: 0.02 | H26: 0.02 | I26: 0.02 | J26: 0.02 | K26: 0.02 | L26: 0.02 | M26: 0.02 | N26: 0.02 | O26: 0.02 | P26: 0.02 | Q26: 0.02 | R26: 0.02 | S26: 0.02 | T26: 0.02 | U26: 0.02 | V26: 0.02 | W26: 0.02 | X26: 0.02 | Y26: 0.02 | Z26: 0.02 | AA26: 0.02 | AB26: 0.02 | AC26: 0.02 | AD26: 0.02 | AE26: 0.02 | AF26: 0.02 | AG26: 0.02 | AH26: 0.02 | AI26: 0.02 | AJ26: 0.02 | AK26: 0.02 | AL26: 0.02 | AM26: 0.02 | AO26: =AVERAGE(D26:O26) -> 0.02 | AP26: =AVERAGE(P26:AA26) -> 0.02 | AQ26: =AVERAGE(AB26:AM26) -> 0.02
A27: РППУ на конец месяца | B27: тыс сом | D27: =-D20*D26 -> -450 | E27: =-E20*E26 -> -892.5 | F27: =-F20*F26 -> -1328.125 | G27: =-G20*G26 -> -1757.4479 | H27: =-H20*H26 -> -2180.9939 | I27: =-I20*I26 -> -2599.2444 | J27: =-J20*J26 -> -2982.6407 | K27: =-K20*K26 -> -3394.0873 | ... AM27: =-AM20*AM26 -> -10115.627 | AO27: =O27 -> -5276.4522 | AP27: =AA27 -> -8855.7353 | AQ27: =AM27 -> -10115.627
A28: % доход | B28: тыс сом | D28: =(C20+D20)/2*D24/12*(1-2/102) -> 220.58824 | E28: =(D20+E20)/2*E24/12*(1-2/102) -> 658.08824 | F28: =(E20+F20)/2*F24/12*(1-2/102) -> 1088.5417 | G28: =(F20+G20)/2*G24/12*(1-2/102) -> 1512.5357 | H28: =(G20+H20)/2*H24/12*(1-2/102) -> 1930.6087 | I28: =(H20+I20)/2*I24/12*(1-2/102) -> 2343.2541 | J28: =(I20+J20)/2*J24/12*(1-2/102) -> 2736.2182 | K28: =(J20+K20)/2*K24/12*(1-2/102) -> 3125.8471 | ... AM28: =(AL20+AM20)/2*AM24/12*(1-2/102) -> 9886.7838 | AO28: =SUM(D28:O28) -> 30510.588 | AP28: =SUM(P28:AA28) -> 86704.161 | AQ28: =SUM(AB28:AM28) -> 112854.16
A29: трансфертный расход | B29: тыс сом | D29: =-(C20+D20)/2*D25/12 -> -140.625 | E29: =-(D20+E20)/2*E25/12 -> -419.53125 | F29: =-(E20+F20)/2*F25/12 -> -693.94531 | G29: =-(F20+G20)/2*G25/12 -> -964.24154 | H29: =-(G20+H20)/2*H25/12 -> -1230.7631 | I29: =-(H20+I20)/2*I25/12 -> -1493.8245 | J29: =-(I20+J20)/2*J25/12 -> -1744.3391 | K29: =-(J20+K20)/2*K25/12 -> -1992.7275 | ... AM29: =-(AL20+AM20)/2*AM25/12 -> -6302.8247 | AO29: =SUM(D29:O29) -> -19450.5 | AP29: =SUM(P29:AA29) -> -55273.903 | AQ29: =SUM(AB29:AM29) -> -71944.526
A30: комиссия партнеру | B30: тыс сом | D30: =-D23*D17 -> 0 | E30: =-E23*E17 -> 0 | F30: =-F23*F17 -> 0 | G30: =-G23*G17 -> 0 | H30: =-H23*H17 -> 0 | I30: =-I23*I17 -> 0 | J30: =-J23*J17 -> 0 | K30: =-K23*K17 -> 0 | ... AM30: =-AM23*AM17 -> 0 | AO30: =SUM(D30:O30) -> 0 | AP30: =SUM(P30:AA30) -> 0 | AQ30: =SUM(AB30:AM30) -> 0
A31: расходы на провизии | B31: тыс сом | D31: =(D27-C27) -> -450 | E31: =(E27-D27) -> -442.5 | F31: =(F27-E27) -> -435.625 | G31: =(G27-F27) -> -429.32292 | H31: =(H27-G27) -> -423.54601 | I31: =(I27-H27) -> -418.25051 | J31: =(J27-I27) -> -383.3963 | K31: =(K27-J27) -> -411.44661 | ... AM31: =(AM27-AL27) -> -62.215697 | AO31: =SUM(D31:O31) -> -5276.4522 | AP31: =SUM(P31:AA31) -> -3579.2831 | AQ31: =SUM(AB31:AM31) -> -1259.892
A32: чистый операционный доход | B32: тыс сом | D32: =SUM(D28:D31) -> -370.03676 | E32: =SUM(E28:E31) -> -203.94301 | F32: =SUM(F28:F31) -> -41.028646 | G32: =SUM(G28:G31) -> 118.97129 | H32: =SUM(H28:H31) -> 276.29966 | I32: =SUM(I28:I31) -> 431.1791 | J32: =SUM(J28:J31) -> 608.48281 | K32: =SUM(K28:K31) -> 721.67296 | ... AM32: =SUM(AM28:AM31) -> 3521.7434 | AO32: =SUM(D32:O32) -> 5783.636 | AP32: =SUM(P32:AA32) -> 27850.975 | AQ32: =SUM(AB32:AM32) -> 39649.741
A33: операционные расходы | B33: тыс сом | D33: =-'OPEX+CAPEX'!E19 -> -11.41875 | E33: =-'OPEX+CAPEX'!F19 -> -22.647188 | F33: =-'OPEX+CAPEX'!G19 -> -33.701172 | G33: =-'OPEX+CAPEX'!H19 -> -44.595241 | H33: =-'OPEX+CAPEX'!I19 -> -55.342721 | I33: =-'OPEX+CAPEX'!J19 -> -65.955827 | J33: =-'OPEX+CAPEX'!K19 -> -75.684508 | K33: =-'OPEX+CAPEX'!L19 -> -86.124966 | ... AM33: =-'OPEX+CAPEX'!AN19 -> -256.68404 | AO33: =SUM(D33:O33) -> -856.63528 | AP33: =SUM(P33:AA33) -> -2289.5326 | AQ33: =SUM(AB33:AM33) -> -2936.9326
A34: прибыль | B34: тыс сом | D34: =D32+D33 -> -381.45551 | E34: =E32+E33 -> -226.5902 | F34: =F32+F33 -> -74.729818 | G34: =G32+G33 -> 74.376049 | H34: =H32+H33 -> 220.95694 | I34: =I32+I33 -> 365.22328 | J34: =J32+J33 -> 532.7983 | K34: =K32+K33 -> 635.548 | ... AM34: =AM32+AM33 -> 3265.0594 | AO34: =SUM(D34:O34) -> 4927.0007 | AP34: =SUM(P34:AA34) -> 25561.443 | AQ34: =SUM(AB34:AM34) -> 36712.808
A36: Рассрочка (BNPL) | B36: ЕИ | C36: Отв.исп.
A37: количество партнеров | B37: шт | D37: ='0'!D10 -> 15 | E37: ='0'!E10 -> 16 | F37: ='0'!F10 -> 17 | G37: ='0'!G10 -> 18 | H37: ='0'!H10 -> 19 | I37: ='0'!I10 -> 20 | J37: ='0'!J10 -> 20 | K37: ='0'!K10 -> 22 | ... AM37: ='0'!AM10 -> 30 | AO37: =O37 -> 30 | AP37: =AA37 -> 30 | AQ37: =AM37 -> 30
A38: среднее количество выдач на 1 партнера | B38: шт | D38: 1 | E38: 1 | F38: 1 | G38: 1 | H38: 1 | I38: 1 | J38: 1 | K38: 1 | L38: 1 | M38: 1 | N38: 1 | O38: 1 | P38: 1 | Q38: 1 | R38: 1 | S38: 1 | T38: 1 | U38: 1 | V38: 1 | W38: 1 | X38: 1 | Y38: 1 | Z38: 1 | AA38: 1 | AB38: 1 | AC38: 1 | AD38: 1 | AE38: 1 | AF38: 1 | AG38: 1 | AH38: 1 | AI38: 1 | AJ38: 1 | AK38: 1 | AL38: 1 | AM38: 1 | AO38: =AVERAGE(D38:O38) -> 1 | AP38: =AVERAGE(P38:AA38) -> 1 | AQ38: =AVERAGE(AB38:AM38) -> 1
A39: количество выдач | B39: шт | D39: =D37*D38 -> 15 | E39: =E37*E38 -> 16 | F39: =F37*F38 -> 17 | G39: =G37*G38 -> 18 | H39: =H37*H38 -> 19 | I39: =I37*I38 -> 20 | J39: =J37*J38 -> 20 | K39: =K37*K38 -> 22 | ... AM39: =AM37*AM38 -> 30 | AO39: =SUM(D39:O39) -> 255 | AP39: =SUM(P39:AA39) -> 360 | AQ39: =SUM(AB39:AM39) -> 360
A40: ср. сумма выдачи | B40: тыс сом | D40: 100 | E40: 100 | F40: 100 | G40: 100 | H40: 100 | I40: 100 | J40: 100 | K40: 100 | L40: 100 | M40: 100 | N40: 100 | O40: 100 | P40: 100 | Q40: 100 | R40: 100 | S40: 100 | T40: 100 | U40: 100 | V40: 100 | W40: 100 | X40: 100 | Y40: 100 | Z40: 100 | AA40: 100 | AB40: 100 | AC40: 100 | AD40: 100 | AE40: 100 | AF40: 100 | AG40: 100 | AH40: 100 | AI40: 100 | AJ40: 100 | AK40: 100 | AL40: 100 | AM40: 100 | AO40: =AVERAGE(D40:O40) -> 100 | AP40: =AVERAGE(P40:AA40) -> 100 | AQ40: =AVERAGE(AB40:AM40) -> 100
A41: выдачи | B41: тыс сом | D41: =D39*D40 -> 1500 | E41: =E39*E40 -> 1600 | F41: =F39*F40 -> 1700 | G41: =G39*G40 -> 1800 | H41: =H39*H40 -> 1900 | I41: =I39*I40 -> 2000 | J41: =J39*J40 -> 2000 | K41: =K39*K40 -> 2200 | ... AM41: =AM39*AM40 -> 3000 | AO41: =SUM(D41:O41) -> 25500 | AP41: =SUM(P41:AA41) -> 36000 | AQ41: =SUM(AB41:AM41) -> 36000
A42: cр. срок портфеля | B42: мес | D42: 3 | E42: 3 | F42: 3 | G42: 3 | H42: 3 | I42: 3 | J42: 3 | K42: 3 | L42: 3 | M42: 3 | N42: 3 | O42: 3 | P42: 3 | Q42: 3 | R42: 3 | S42: 3 | T42: 3 | U42: 3 | V42: 3 | W42: 3 | X42: 3 | Y42: 3 | Z42: 3 | AA42: 3 | AB42: 3 | AC42: 3 | AD42: 3 | AE42: 3 | AF42: 3 | AG42: 3 | AH42: 3 | AI42: 3 | AJ42: 3 | AK42: 3 | AL42: 3 | AM42: 3 | AO42: =AVERAGE(D42:O42) -> 3 | AP42: =AVERAGE(P42:AA42) -> 3 | AQ42: =AVERAGE(AB42:AM42) -> 3
A43: погашения | B43: тыс сом | D43: 0 | E43: =D44/E42 -> 500 | F43: =E44/F42 -> 866.66667 | G43: =F44/G42 -> 1144.4444 | H43: =G44/H42 -> 1362.963 | I43: =H44/I42 -> 1541.9753 | J43: =I44/J42 -> 1694.6502 | K43: =J44/K42 -> 1796.4335 | L43: =K44/L42 -> 1930.9556 | ... AM43: =AL44/AM42 -> 2999.9667 | AO43: =SUM(D43:O43) -> 17622.397 | AP43: =SUM(P43:AA43) -> 34886.254 | AQ43: =SUM(AB43:AM43) -> 35991.416
A44: кредитный портфель | B44: тыс сом | D44: =D41-D43 -> 1500 | E44: =D44+E41-E43 -> 2600 | F44: =E44+F41-F43 -> 3433.3333 | G44: =F44+G41-G43 -> 4088.8889 | H44: =G44+H41-H43 -> 4625.9259 | I44: =H44+I41-I43 -> 5083.9506 | J44: =I44+J41-J43 -> 5389.3004 | K44: =J44+K41-K43 -> 5792.8669 | L44: =K44+L41-L43 -> 6261.9113 | ... AM44: =AL44+AM41-AM43 -> 8999.9333 | AO44: =O44 -> 7877.6033 | AP44: =AA44 -> 8991.3493 | AQ44: =AM44 -> 8999.9333
A45: комиссия партнеру | B45: % | D45: 0.01 | E45: 0.01 | F45: 0.01 | G45: 0.01 | H45: 0.01 | I45: 0.01 | J45: 0.01 | K45: 0.01 | L45: 0.01 | M45: 0.01 | N45: 0.01 | O45: 0.01 | P45: 0.01 | Q45: 0.01 | R45: 0.01 | S45: 0.01 | T45: 0.01 | U45: 0.01 | V45: 0.01 | W45: 0.01 | X45: 0.01 | Y45: 0.01 | Z45: 0.01 | AA45: 0.01 | AB45: 0.01 | AC45: 0.01 | AD45: 0.01 | AE45: 0.01 | AF45: 0.01 | AG45: 0.01 | AH45: 0.01 | AI45: 0.01 | AJ45: 0.01 | AK45: 0.01 | AL45: 0.01 | AM45: 0.01 | AO45: =AVERAGE(D45:O45) -> 0.01 | AP45: =AVERAGE(P45:AA45) -> 0.01 | AQ45: =AVERAGE(AB45:AM45) -> 0.01
A46: комиссия мерчанта | B46: % | D46: 0.05 | E46: 0.05 | F46: 0.05 | G46: 0.05 | H46: 0.05 | I46: 0.05 | J46: 0.05 | K46: 0.05 | L46: 0.05 | M46: 0.05 | N46: 0.05 | O46: 0.05 | P46: 0.05 | Q46: 0.05 | R46: 0.05 | S46: 0.05 | T46: 0.05 | U46: 0.05 | V46: 0.05 | W46: 0.05 | X46: 0.05 | Y46: 0.05 | Z46: 0.05 | AA46: 0.05 | AB46: 0.05 | AC46: 0.05 | AD46: 0.05 | AE46: 0.05 | AF46: 0.05 | AG46: 0.05 | AH46: 0.05 | AI46: 0.05 | AJ46: 0.05 | AK46: 0.05 | AL46: 0.05 | AM46: 0.05 | AO46: =AVERAGE(D46:O46) -> 0.05 | AP46: =AVERAGE(P46:AA46) -> 0.05 | AQ46: =AVERAGE(AB46:AM46) -> 0.05
A47: ср. % ставка фондирования | B47: % | D47: 0.1 | E47: 0.1 | F47: 0.1 | G47: 0.1 | H47: 0.1 | I47: 0.1 | J47: 0.1 | K47: 0.1 | L47: 0.1 | M47: 0.1 | N47: 0.1 | O47: 0.1 | P47: 0.1 | Q47: 0.1 | R47: 0.1 | S47: 0.1 | T47: 0.1 | U47: 0.1 | V47: 0.1 | W47: 0.1 | X47: 0.1 | Y47: 0.1 | Z47: 0.1 | AA47: 0.1 | AB47: 0.1 | AC47: 0.1 | AD47: 0.1 | AE47: 0.1 | AF47: 0.1 | AG47: 0.1 | AH47: 0.1 | AI47: 0.1 | AJ47: 0.1 | AK47: 0.1 | AL47: 0.1 | AM47: 0.1 | AO47: =AVERAGE(D47:O47) -> 0.1 | AP47: =AVERAGE(P47:AA47) -> 0.1 | AQ47: =AVERAGE(AB47:AM47) -> 0.1
A48: ср. % резервирования | B48: % | D48: 0.05 | E48: 0.05 | F48: 0.05 | G48: 0.05 | H48: 0.05 | I48: 0.05 | J48: 0.05 | K48: 0.05 | L48: 0.05 | M48: 0.05 | N48: 0.05 | O48: 0.05 | P48: 0.05 | Q48: 0.05 | R48: 0.05 | S48: 0.05 | T48: 0.05 | U48: 0.05 | V48: 0.05 | W48: 0.05 | X48: 0.05 | Y48: 0.05 | Z48: 0.05 | AA48: 0.05 | AB48: 0.05 | AC48: 0.05 | AD48: 0.05 | AE48: 0.05 | AF48: 0.05 | AG48: 0.05 | AH48: 0.05 | AI48: 0.05 | AJ48: 0.05 | AK48: 0.05 | AL48: 0.05 | AM48: 0.05 | AO48: =AVERAGE(D48:O48) -> 0.05 | AP48: =AVERAGE(P48:AA48) -> 0.05 | AQ48: =AVERAGE(AB48:AM48) -> 0.05
A49: РППУ на конец месяца | B49: тыс сом | D49: =-D44*D48 -> -75 | E49: =-E44*E48 -> -130 | F49: =-F44*F48 -> -171.66667 | G49: =-G44*G48 -> -204.44444 | H49: =-H44*H48 -> -231.2963 | I49: =-I44*I48 -> -254.19753 | J49: =-J44*J48 -> -269.46502 | K49: =-K44*K48 -> -289.64335 | ... AM49: =-AM44*AM48 -> -449.99667 | AO49: =O49 -> -393.88017 | AP49: =AA49 -> -449.56746 | AQ49: =AM49 -> -449.99667
A50: комиссионный доход | B50: тыс сом | D50: =D41*D46*(1-2/102) -> 73.529412 | E50: =E41*E46*(1-2/102) -> 78.431373 | F50: =F41*F46*(1-2/102) -> 83.333333 | G50: =G41*G46*(1-2/102) -> 88.235294 | H50: =H41*H46*(1-2/102) -> 93.137255 | I50: =I41*I46*(1-2/102) -> 98.039216 | J50: =J41*J46*(1-2/102) -> 98.039216 | K50: =K41*K46*(1-2/102) -> 107.84314 | ... AM50: =AM41*AM46*(1-2/102) -> 147.05882 | AO50: =SUM(D50:O50) -> 1250 | AP50: =SUM(P50:AA50) -> 1764.7059 | AQ50: =SUM(AB50:AM50) -> 1764.7059
A51: трансфертный расход | B51: тыс сом | D51: =-(C44+D44)/2*D47/12 -> -6.25 | E51: =-(D44+E44)/2*E47/12 -> -17.083333 | F51: =-(E44+F44)/2*F47/12 -> -25.138889 | G51: =-(F44+G44)/2*G47/12 -> -31.342593 | H51: =-(G44+H44)/2*H47/12 -> -36.311728 | I51: =-(H44+I44)/2*I47/12 -> -40.457819 | J51: =-(I44+J44)/2*J47/12 -> -43.638546 | K51: =-(J44+K44)/2*K47/12 -> -46.592364 | ... AM51: =-(AL44+AM44)/2*AM47/12 -> -74.999305 | AO51: =SUM(D51:O51) -> -473.38326 | AP51: =SUM(P51:AA51) -> -876.79696 | AQ51: =SUM(AB51:AM51) -> -899.82117
A52: комиссия партнеру | B52: тыс сом | D52: =-D45*D41 -> -15 | E52: =-E45*E41 -> -16 | F52: =-F45*F41 -> -17 | G52: =-G45*G41 -> -18 | H52: =-H45*H41 -> -19 | I52: =-I45*I41 -> -20 | J52: =-J45*J41 -> -20 | K52: =-K45*K41 -> -22 | ... AM52: =-AM45*AM41 -> -30 | AO52: =SUM(D52:O52) -> -255 | AP52: =SUM(P52:AA52) -> -360 | AQ52: =SUM(AB52:AM52) -> -360
A53: расходы на провизии | B53: тыс сом | D53: =(D49-C49) -> -75 | E53: =(E49-D49) -> -55 | F53: =(F49-E49) -> -41.666667 | G53: =(G49-F49) -> -32.777778 | H53: =(H49-G49) -> -26.851852 | I53: =(I49-H49) -> -22.901235 | J53: =(J49-I49) -> -15.26749 | K53: =(K49-J49) -> -20.178326 | ... AM53: =(AM49-AL49) -> -0.0016668486 | AO53: =SUM(D53:O53) -> -393.88017 | AP53: =SUM(P53:AA53) -> -55.687298 | AQ53: =SUM(AB53:AM53) -> -0.42920131
A54: чистый операционный доход | B54: тыс сом | D54: =SUM(D50:D53) -> -22.720588 | E54: =SUM(E50:E53) -> -9.6519608 | F54: =SUM(F50:F53) -> -0.47222222 | G54: =SUM(G50:G53) -> 6.1149237 | H54: =SUM(H50:H53) -> 10.973675 | I54: =SUM(I50:I53) -> 14.680162 | J54: =SUM(J50:J53) -> 19.13318 | K54: =SUM(K50:K53) -> 19.072447 | ... AM54: =SUM(AM50:AM53) -> 42.057851 | AO54: =SUM(D54:O54) -> 127.73657 | AP54: =SUM(P54:AA54) -> 472.22163 | AQ54: =SUM(AB54:AM54) -> 504.45551
A55: операционные расходы | B55: тыс сом | D55: =-'OPEX+CAPEX'!E25 -> -2.5375 | E55: =-'OPEX+CAPEX'!F25 -> -4.1234375 | F55: =-'OPEX+CAPEX'!G25 -> -5.1247549 | G55: =-'OPEX+CAPEX'!H25 -> -5.7641975 | H55: =-'OPEX+CAPEX'!I25 -> -6.1780458 | I55: =-'OPEX+CAPEX'!J25 -> -6.4502623 | J55: =-'OPEX+CAPEX'!K25 -> -6.8376749 | K55: =-'OPEX+CAPEX'!L25 -> -6.6815454 | ... AM55: =-'OPEX+CAPEX'!AN25 -> -7.6124436 | AO55: =SUM(D55:O55) -> -70.223473 | AP55: =SUM(P55:AA55) -> -89.465913 | AQ55: =SUM(AB55:AM55) -> -91.335479
A56: прибыль | B56: тыс сом | D56: =D54+D55 -> -25.258088 | E56: =E54+E55 -> -13.775398 | F56: =F54+F55 -> -5.5969771 | G56: =G54+G55 -> 0.35072622 | H56: =H54+H55 -> 4.7956288 | I56: =I54+I55 -> 8.2298998 | J56: =J54+J55 -> 12.295505 | K56: =K54+K55 -> 12.390901 | ... AM56: =AM54+AM55 -> 34.445408 | AO56: =SUM(D56:O56) -> 57.513096 | AP56: =SUM(P56:AA56) -> 382.75571 | AQ56: =SUM(AB56:AM56) -> 413.12004
A58: Факторинг | B58: ЕИ | C58: Отв.исп.
A59: количество партнеров | B59: шт | D59: ='0'!D10 -> 15 | E59: ='0'!E10 -> 16 | F59: ='0'!F10 -> 17 | G59: ='0'!G10 -> 18 | H59: ='0'!H10 -> 19 | I59: ='0'!I10 -> 20 | J59: ='0'!J10 -> 20 | K59: ='0'!K10 -> 22 | ... AM59: ='0'!AM10 -> 30 | AO59: =O59 -> 30 | AP59: =AA59 -> 30 | AQ59: =AM59 -> 30
A60: среднее количество сделок на 1 партнера | B60: шт | D60: 1 | E60: 1 | F60: 1 | G60: 1 | H60: 1 | I60: 1 | J60: 1 | K60: 1 | L60: 1 | M60: 1 | N60: 1 | O60: 1 | P60: 1 | Q60: 1 | R60: 1 | S60: 1 | T60: 1 | U60: 1 | V60: 1 | W60: 1 | X60: 1 | Y60: 1 | Z60: 1 | AA60: 1 | AB60: 1 | AC60: 1 | AD60: 1 | AE60: 1 | AF60: 1 | AG60: 1 | AH60: 1 | AI60: 1 | AJ60: 1 | AK60: 1 | AL60: 1 | AM60: 1 | AO60: =AVERAGE(D60:O60) -> 1 | AP60: =AVERAGE(P60:AA60) -> 1 | AQ60: =AVERAGE(AB60:AM60) -> 1
A61: количество сделок | B61: шт | D61: =D59*D60 -> 15 | E61: =E59*E60 -> 16 | F61: =F59*F60 -> 17 | G61: =G59*G60 -> 18 | H61: =H59*H60 -> 19 | I61: =I59*I60 -> 20 | J61: =J59*J60 -> 20 | K61: =K59*K60 -> 22 | ... AM61: =AM59*AM60 -> 30 | AO61: =SUM(D61:O61) -> 255 | AP61: =SUM(P61:AA61) -> 360 | AQ61: =SUM(AB61:AM61) -> 360
A62: ср. сумма купленного долга | B62: тыс сом | D62: 100 | E62: 100 | F62: 100 | G62: 100 | H62: 100 | I62: 100 | J62: 100 | K62: 100 | L62: 100 | M62: 100 | N62: 100 | O62: 100 | P62: 100 | Q62: 100 | R62: 100 | S62: 100 | T62: 100 | U62: 100 | V62: 100 | W62: 100 | X62: 100 | Y62: 100 | Z62: 100 | AA62: 100 | AB62: 100 | AC62: 100 | AD62: 100 | AE62: 100 | AF62: 100 | AG62: 100 | AH62: 100 | AI62: 100 | AJ62: 100 | AK62: 100 | AL62: 100 | AM62: 100 | AO62: =AVERAGE(D62:O62) -> 100 | AP62: =AVERAGE(P62:AA62) -> 100 | AQ62: =AVERAGE(AB62:AM62) -> 100
A63: сумма купленного долга | B63: тыс сом | D63: =D61*D62 -> 1500 | E63: =E61*E62 -> 1600 | F63: =F61*F62 -> 1700 | G63: =G61*G62 -> 1800 | H63: =H61*H62 -> 1900 | I63: =I61*I62 -> 2000 | J63: =J61*J62 -> 2000 | K63: =K61*K62 -> 2200 | ... AM63: =AM61*AM62 -> 3000 | AO63: =SUM(D63:O63) -> 25500 | AP63: =SUM(P63:AA63) -> 36000 | AQ63: =SUM(AB63:AM63) -> 36000
A64: cр. срок портфеля | B64: мес | D64: 3 | E64: 3 | F64: 3 | G64: 3 | H64: 3 | I64: 3 | J64: 3 | K64: 3 | L64: 3 | M64: 3 | N64: 3 | O64: 3 | P64: 3 | Q64: 3 | R64: 3 | S64: 3 | T64: 3 | U64: 3 | V64: 3 | W64: 3 | X64: 3 | Y64: 3 | Z64: 3 | AA64: 3 | AB64: 3 | AC64: 3 | AD64: 3 | AE64: 3 | AF64: 3 | AG64: 3 | AH64: 3 | AI64: 3 | AJ64: 3 | AK64: 3 | AL64: 3 | AM64: 3 | AO64: =AVERAGE(D64:O64) -> 3 | AP64: =AVERAGE(P64:AA64) -> 3 | AQ64: =AVERAGE(AB64:AM64) -> 3
A65: погашения | B65: тыс сом | D65: 0 | E65: =D66/E64 -> 500 | F65: =E66/F64 -> 866.66667 | G65: =F66/G64 -> 1144.4444 | H65: =G66/H64 -> 1362.963 | I65: =H66/I64 -> 1541.9753 | J65: =I66/J64 -> 1694.6502 | K65: =J66/K64 -> 1796.4335 | L65: =K66/L64 -> 1930.9556 | ... AM65: =AL66/AM64 -> 2999.9667 | AO65: =SUM(D65:O65) -> 17622.397 | AP65: =SUM(P65:AA65) -> 34886.254 | AQ65: =SUM(AB65:AM65) -> 35991.416
A66: факторинговый портфель | B66: тыс сом | D66: =D63-D65 -> 1500 | E66: =D66+E63-E65 -> 2600 | F66: =E66+F63-F65 -> 3433.3333 | G66: =F66+G63-G65 -> 4088.8889 | H66: =G66+H63-H65 -> 4625.9259 | I66: =H66+I63-I65 -> 5083.9506 | J66: =I66+J63-J65 -> 5389.3004 | K66: =J66+K63-K65 -> 5792.8669 | L66: =K66+L63-L65 -> 6261.9113 | ... AM66: =AL66+AM63-AM65 -> 8999.9333 | AO66: =O66 -> 7877.6033 | AP66: =AA66 -> 8991.3493 | AQ66: =AM66 -> 8999.9333
A67: комиссия партнеру | B67: % | D67: 0.01 | E67: 0.01 | F67: 0.01 | G67: 0.01 | H67: 0.01 | I67: 0.01 | J67: 0.01 | K67: 0.01 | L67: 0.01 | M67: 0.01 | N67: 0.01 | O67: 0.01 | P67: 0.01 | Q67: 0.01 | R67: 0.01 | S67: 0.01 | T67: 0.01 | U67: 0.01 | V67: 0.01 | W67: 0.01 | X67: 0.01 | Y67: 0.01 | Z67: 0.01 | AA67: 0.01 | AB67: 0.01 | AC67: 0.01 | AD67: 0.01 | AE67: 0.01 | AF67: 0.01 | AG67: 0.01 | AH67: 0.01 | AI67: 0.01 | AJ67: 0.01 | AK67: 0.01 | AL67: 0.01 | AM67: 0.01 | AO67: =AVERAGE(D67:O67) -> 0.01 | AP67: =AVERAGE(P67:AA67) -> 0.01 | AQ67: =AVERAGE(AB67:AM67) -> 0.01
A68: ср. % комиссии | B68: % | D68: 0.1 | E68: 0.1 | F68: 0.1 | G68: 0.1 | H68: 0.1 | I68: 0.1 | J68: 0.1 | K68: 0.1 | L68: 0.1 | M68: 0.1 | N68: 0.1 | O68: 0.1 | P68: 0.1 | Q68: 0.1 | R68: 0.1 | S68: 0.1 | T68: 0.1 | U68: 0.1 | V68: 0.1 | W68: 0.1 | X68: 0.1 | Y68: 0.1 | Z68: 0.1 | AA68: 0.1 | AB68: 0.1 | AC68: 0.1 | AD68: 0.1 | AE68: 0.1 | AF68: 0.1 | AG68: 0.1 | AH68: 0.1 | AI68: 0.1 | AJ68: 0.1 | AK68: 0.1 | AL68: 0.1 | AM68: 0.1 | AO68: =AVERAGE(D68:O68) -> 0.1 | AP68: =AVERAGE(P68:AA68) -> 0.1 | AQ68: =AVERAGE(AB68:AM68) -> 0.1
A69: ср. % ставка фондирования | B69: % | D69: 0.1 | E69: 0.1 | F69: 0.1 | G69: 0.1 | H69: 0.1 | I69: 0.1 | J69: 0.1 | K69: 0.1 | L69: 0.1 | M69: 0.1 | N69: 0.1 | O69: 0.1 | P69: 0.1 | Q69: 0.1 | R69: 0.1 | S69: 0.1 | T69: 0.1 | U69: 0.1 | V69: 0.1 | W69: 0.1 | X69: 0.1 | Y69: 0.1 | Z69: 0.1 | AA69: 0.1 | AB69: 0.1 | AC69: 0.1 | AD69: 0.1 | AE69: 0.1 | AF69: 0.1 | AG69: 0.1 | AH69: 0.1 | AI69: 0.1 | AJ69: 0.1 | AK69: 0.1 | AL69: 0.1 | AM69: 0.1 | AO69: =AVERAGE(D69:O69) -> 0.1 | AP69: =AVERAGE(P69:AA69) -> 0.1 | AQ69: =AVERAGE(AB69:AM69) -> 0.1
A70: ср. % резервирования | B70: % | D70: 0.05 | E70: 0.05 | F70: 0.05 | G70: 0.05 | H70: 0.05 | I70: 0.05 | J70: 0.05 | K70: 0.05 | L70: 0.05 | M70: 0.05 | N70: 0.05 | O70: 0.05 | P70: 0.05 | Q70: 0.05 | R70: 0.05 | S70: 0.05 | T70: 0.05 | U70: 0.05 | V70: 0.05 | W70: 0.05 | X70: 0.05 | Y70: 0.05 | Z70: 0.05 | AA70: 0.05 | AB70: 0.05 | AC70: 0.05 | AD70: 0.05 | AE70: 0.05 | AF70: 0.05 | AG70: 0.05 | AH70: 0.05 | AI70: 0.05 | AJ70: 0.05 | AK70: 0.05 | AL70: 0.05 | AM70: 0.05 | AO70: =AVERAGE(D70:O70) -> 0.05 | AP70: =AVERAGE(P70:AA70) -> 0.05 | AQ70: =AVERAGE(AB70:AM70) -> 0.05
A71: РППУ на конец месяца | B71: тыс сом | D71: =-D66*D70 -> -75 | E71: =-E66*E70 -> -130 | F71: =-F66*F70 -> -171.66667 | G71: =-G66*G70 -> -204.44444 | H71: =-H66*H70 -> -231.2963 | I71: =-I66*I70 -> -254.19753 | J71: =-J66*J70 -> -269.46502 | K71: =-K66*K70 -> -289.64335 | ... AM71: =-AM66*AM70 -> -449.99667 | AO71: =O71 -> -393.88017 | AP71: =AA71 -> -449.56746 | AQ71: =AM71 -> -449.99667
A72: комиссионный доход | B72: тыс сом | D72: =D65*D68*(1-2/102) -> 0 | E72: =E65*E68*(1-2/102) -> 49.019608 | F72: =F65*F68*(1-2/102) -> 84.96732 | G72: =G65*G68*(1-2/102) -> 112.20044 | H72: =H65*H68*(1-2/102) -> 133.62382 | I72: =I65*I68*(1-2/102) -> 151.17405 | J72: =J65*J68*(1-2/102) -> 166.14218 | K72: =K65*K68*(1-2/102) -> 176.12093 | ... AM72: =AM65*AM68*(1-2/102) -> 294.11438 | AO72: =SUM(D72:O72) -> 1727.6859 | AP72: =SUM(P72:AA72) -> 3420.221 | AQ72: =SUM(AB72:AM72) -> 3528.5702
A73: трансфертный расход | B73: тыс сом | D73: =-(C66+D66)/2*D69/12 -> -6.25 | E73: =-(D66+E66)/2*E69/12 -> -17.083333 | F73: =-(E66+F66)/2*F69/12 -> -25.138889 | G73: =-(F66+G66)/2*G69/12 -> -31.342593 | H73: =-(G66+H66)/2*H69/12 -> -36.311728 | I73: =-(H66+I66)/2*I69/12 -> -40.457819 | J73: =-(I66+J66)/2*J69/12 -> -43.638546 | K73: =-(J66+K66)/2*K69/12 -> -46.592364 | ... AM73: =-(AL66+AM66)/2*AM69/12 -> -74.999305 | AO73: =SUM(D73:O73) -> -473.38326 | AP73: =SUM(P73:AA73) -> -876.79696 | AQ73: =SUM(AB73:AM73) -> -899.82117
A74: комиссия партнеру | B74: тыс сом | D74: =-D67*D63 -> -15 | E74: =-E67*E63 -> -16 | F74: =-F67*F63 -> -17 | G74: =-G67*G63 -> -18 | H74: =-H67*H63 -> -19 | I74: =-I67*I63 -> -20 | J74: =-J67*J63 -> -20 | K74: =-K67*K63 -> -22 | ... AM74: =-AM67*AM63 -> -30 | AO74: =SUM(D74:O74) -> -255 | AP74: =SUM(P74:AA74) -> -360 | AQ74: =SUM(AB74:AM74) -> -360
A75: расходы на провизии | B75: тыс сом | D75: =(D71-C71) -> -75 | E75: =(E71-D71) -> -55 | F75: =(F71-E71) -> -41.666667 | G75: =(G71-F71) -> -32.777778 | H75: =(H71-G71) -> -26.851852 | I75: =(I71-H71) -> -22.901235 | J75: =(J71-I71) -> -15.26749 | K75: =(K71-J71) -> -20.178326 | ... AM75: =(AM71-AL71) -> -0.0016668486 | AO75: =SUM(D75:O75) -> -393.88017 | AP75: =SUM(P75:AA75) -> -55.687298 | AQ75: =SUM(AB75:AM75) -> -0.42920131
A76: чистый операционный доход | B76: тыс сом | D76: =SUM(D72:D75) -> -96.25 | E76: =SUM(E72:E75) -> -39.063725 | F76: =SUM(F72:F75) -> 1.1617647 | G76: =SUM(G72:G75) -> 30.080065 | H76: =SUM(H72:H75) -> 51.46024 | I76: =SUM(I72:I75) -> 67.814996 | J76: =SUM(J72:J75) -> 87.236141 | K76: =SUM(K72:K75) -> 87.350238 | ... AM76: =SUM(AM72:AM75) -> 189.11341 | AO76: =SUM(D76:O76) -> 605.42252 | AP76: =SUM(P76:AA76) -> 2127.7367 | AQ76: =SUM(AB76:AM76) -> 2268.3198
A77: операционные расходы | B77: тыс сом | D77: =-'OPEX+CAPEX'!E27 -> -0.380625 | E77: =-'OPEX+CAPEX'!F27 -> -0.65975 | F77: =-'OPEX+CAPEX'!G27 -> -0.87120833 | G77: =-'OPEX+CAPEX'!H27 -> -1.0375556 | H77: =-'OPEX+CAPEX'!I27 -> -1.1738287 | I77: =-'OPEX+CAPEX'!J27 -> -1.2900525 | J77: =-'OPEX+CAPEX'!K27 -> -1.367535 | K77: =-'OPEX+CAPEX'!L27 -> -1.46994 | ... AM77: =-'OPEX+CAPEX'!AN27 -> -2.2837331 | AO77: =SUM(D77:O77) -> -15.413991 | AP77: =SUM(P77:AA77) -> -26.839774 | AQ77: =SUM(AB77:AM77) -> -27.400644
A78: прибыль | B78: тыс сом | D78: =D76+D77 -> -96.630625 | E78: =E76+E77 -> -39.723475 | F78: =F76+F77 -> 0.29055637 | G78: =G76+G77 -> 29.04251 | H78: =H76+H77 -> 50.286411 | I78: =I76+I77 -> 66.524944 | J78: =J76+J77 -> 85.868606 | K78: =K76+K77 -> 85.880298 | ... AM78: =AM76+AM77 -> 186.82967 | AO78: =SUM(D78:O78) -> 590.00852 | AP78: =SUM(P78:AA78) -> 2100.897 | AQ78: =SUM(AB78:AM78) -> 2240.9192
A80: Кредитная линия для ИП | B80: ЕИ | C80: Отв.исп.
A81: количество партнеров | B81: шт | D81: ='0'!D10 -> 15 | E81: ='0'!E10 -> 16 | F81: ='0'!F10 -> 17 | G81: ='0'!G10 -> 18 | H81: ='0'!H10 -> 19 | I81: ='0'!I10 -> 20 | J81: ='0'!J10 -> 20 | K81: ='0'!K10 -> 22 | ... AM81: ='0'!AM10 -> 30 | AO81: =O81 -> 30 | AP81: =AA81 -> 30 | AQ81: =AM81 -> 30
A82: среднее количество продаж на 1 партнера | B82: шт | D82: 1 | E82: 1 | F82: 1 | G82: 1 | H82: 1 | I82: 1 | J82: 1 | K82: 1 | L82: 1 | M82: 1 | N82: 1 | O82: 1 | P82: 1 | Q82: 1 | R82: 1 | S82: 1 | T82: 1 | U82: 1 | V82: 1 | W82: 1 | X82: 1 | Y82: 1 | Z82: 1 | AA82: 1 | AB82: 1 | AC82: 1 | AD82: 1 | AE82: 1 | AF82: 1 | AG82: 1 | AH82: 1 | AI82: 1 | AJ82: 1 | AK82: 1 | AL82: 1 | AM82: 1 | AO82: =AVERAGE(D82:O82) -> 1 | AP82: =AVERAGE(P82:AA82) -> 1 | AQ82: =AVERAGE(AB82:AM82) -> 1
A83: новые клиенты | B83: шт | D83: =D81*D82 -> 15 | E83: =E81*E82 -> 16 | F83: =F81*F82 -> 17 | G83: =G81*G82 -> 18 | H83: =H81*H82 -> 19 | I83: =I81*I82 -> 20 | J83: =J81*J82 -> 20 | K83: =K81*K82 -> 22 | ... AM83: =AM81*AM82 -> 30 | AO83: =SUM(D83:O83) -> 255 | AP83: =SUM(P83:AA83) -> 360 | AQ83: =SUM(AB83:AM83) -> 360
A84: ср. сумма КЛ | B84: тыс сом | D84: 100 | E84: 100 | F84: 100 | G84: 100 | H84: 100 | I84: 100 | J84: 100 | K84: 100 | L84: 100 | M84: 100 | N84: 100 | O84: 100 | P84: 100 | Q84: 100 | R84: 100 | S84: 100 | T84: 100 | U84: 100 | V84: 100 | W84: 100 | X84: 100 | Y84: 100 | Z84: 100 | AA84: 100 | AB84: 100 | AC84: 100 | AD84: 100 | AE84: 100 | AF84: 100 | AG84: 100 | AH84: 100 | AI84: 100 | AJ84: 100 | AK84: 100 | AL84: 100 | AM84: 100 | AO84: =AVERAGE(D84:O84) -> 100 | AP84: =AVERAGE(P84:AA84) -> 100 | AQ84: =AVERAGE(AB84:AM84) -> 100
A85: сумма новых КЛ | B85: тыс сом | D85: =D83*D84 -> 1500 | E85: =E83*E84 -> 1600 | F85: =F83*F84 -> 1700 | G85: =G83*G84 -> 1800 | H85: =H83*H84 -> 1900 | I85: =I83*I84 -> 2000 | J85: =J83*J84 -> 2000 | K85: =K83*K84 -> 2200 | ... AM85: =AM83*AM84 -> 3000 | AO85: =SUM(D85:O85) -> 25500 | AP85: =SUM(P85:AA85) -> 36000 | AQ85: =SUM(AB85:AM85) -> 36000
A86: портфель КЛ | B86: тыс сом | D86: =D85 -> 1500 | E86: =D86+E85 -> 3100 | F86: =E86+F85 -> 4800 | G86: =F86+G85 -> 6600 | H86: =G86+H85 -> 8500 | I86: =H86+I85 -> 10500 | J86: =I86+J85 -> 12500 | K86: =J86+K85 -> 14700 | L86: =K86+L85 -> 17100 | ... AM86: =AL86+AM85 -> 97500 | AO86: =SUM(D86:O86) -> 147000 | AP86: =SUM(P86:AA86) -> 540000 | AQ86: =SUM(AB86:AM86) -> 972000
A87: ср.использование КЛ | B87: % | D87: 0.3 | E87: 0.3 | F87: 0.3 | G87: 0.3 | H87: 0.3 | I87: 0.3 | J87: 0.3 | K87: 0.3 | L87: 0.3 | M87: 0.3 | N87: 0.3 | O87: 0.3 | P87: 0.3 | Q87: 0.3 | R87: 0.3 | S87: 0.3 | T87: 0.3 | U87: 0.3 | V87: 0.3 | W87: 0.3 | X87: 0.3 | Y87: 0.3 | Z87: 0.3 | AA87: 0.3 | AB87: 0.3 | AC87: 0.3 | AD87: 0.3 | AE87: 0.3 | AF87: 0.3 | AG87: 0.3 | AH87: 0.3 | AI87: 0.3 | AJ87: 0.3 | AK87: 0.3 | AL87: 0.3 | AM87: 0.3 | AO87: =AVERAGE(D87:O87) -> 0.3 | AP87: =AVERAGE(P87:AA87) -> 0.3 | AQ87: =AVERAGE(AB87:AM87) -> 0.3
A88: кредитный портфель | B88: тыс сом | D88: =D86*D87 -> 450 | E88: =E86*E87 -> 930 | F88: =F86*F87 -> 1440 | G88: =G86*G87 -> 1980 | H88: =H86*H87 -> 2550 | I88: =I86*I87 -> 3150 | J88: =J86*J87 -> 3750 | K88: =K86*K87 -> 4410 | ... AM88: =AM86*AM87 -> 29250 | AO88: =O88 -> 7650 | AP88: =AA88 -> 18450 | AQ88: =AM88 -> 29250
A89: доля просроченной задолженности, % | B89: % | D89: 0.01 | E89: 0.01 | F89: 0.01 | G89: 0.01 | H89: 0.01 | I89: 0.01 | J89: 0.01 | K89: 0.01 | L89: 0.01 | M89: 0.01 | N89: 0.01 | O89: 0.01 | P89: 0.01 | Q89: 0.01 | R89: 0.01 | S89: 0.01 | T89: 0.01 | U89: 0.01 | V89: 0.01 | W89: 0.01 | X89: 0.01 | Y89: 0.01 | Z89: 0.01 | AA89: 0.01 | AB89: 0.01 | AC89: 0.01 | AD89: 0.01 | AE89: 0.01 | AF89: 0.01 | AG89: 0.01 | AH89: 0.01 | AI89: 0.01 | AJ89: 0.01 | AK89: 0.01 | AL89: 0.01 | AM89: 0.01
A90: просроченная задолженность | B90: тыс сом | D90: =D88*D89 -> 4.5 | E90: =E88*E89 -> 9.3 | F90: =F88*F89 -> 14.4 | G90: =G88*G89 -> 19.8 | H90: =H88*H89 -> 25.5 | I90: =I88*I89 -> 31.5 | J90: =J88*J89 -> 37.5 | K90: =K88*K89 -> 44.1 | ... AM90: =AM88*AM89 -> 292.5 | AO90: =SUM(D90:O90) -> 441 | AP90: =SUM(P90:AA90) -> 1620 | AQ90: =SUM(AB90:AM90) -> 2916
A91: комиссия партнеру | B91: % | D91: 0.01 | E91: 0.01 | F91: 0.01 | G91: 0.01 | H91: 0.01 | I91: 0.01 | J91: 0.01 | K91: 0.01 | L91: 0.01 | M91: 0.01 | N91: 0.01 | O91: 0.01 | P91: 0.01 | Q91: 0.01 | R91: 0.01 | S91: 0.01 | T91: 0.01 | U91: 0.01 | V91: 0.01 | W91: 0.01 | X91: 0.01 | Y91: 0.01 | Z91: 0.01 | AA91: 0.01 | AB91: 0.01 | AC91: 0.01 | AD91: 0.01 | AE91: 0.01 | AF91: 0.01 | AG91: 0.01 | AH91: 0.01 | AI91: 0.01 | AJ91: 0.01 | AK91: 0.01 | AL91: 0.01 | AM91: 0.01 | AO91: =AVERAGE(D91:O91) -> 0.01 | AP91: =AVERAGE(P91:AA91) -> 0.01 | AQ91: =AVERAGE(AB91:AM91) -> 0.01
A92: ср. % ставка портфеля | B92: % | D92: 0.21 | E92: 0.21 | F92: 0.21 | G92: 0.21 | H92: 0.21 | I92: 0.21 | J92: 0.21 | K92: 0.21 | L92: 0.21 | M92: 0.21 | N92: 0.21 | O92: 0.21 | P92: 0.21 | Q92: 0.21 | R92: 0.21 | S92: 0.21 | T92: 0.21 | U92: 0.21 | V92: 0.21 | W92: 0.21 | X92: 0.21 | Y92: 0.21 | Z92: 0.21 | AA92: 0.21 | AB92: 0.21 | AC92: 0.21 | AD92: 0.21 | AE92: 0.21 | AF92: 0.21 | AG92: 0.21 | AH92: 0.21 | AI92: 0.21 | AJ92: 0.21 | AK92: 0.21 | AL92: 0.21 | AM92: 0.21 | AO92: =AVERAGE(D92:O92) -> 0.21 | AP92: =AVERAGE(P92:AA92) -> 0.21 | AQ92: =AVERAGE(AB92:AM92) -> 0.21
A93: ср. % ставка фондирования | B93: % | D93: 0.1 | E93: 0.1 | F93: 0.1 | G93: 0.1 | H93: 0.1 | I93: 0.1 | J93: 0.1 | K93: 0.1 | L93: 0.1 | M93: 0.1 | N93: 0.1 | O93: 0.1 | P93: 0.1 | Q93: 0.1 | R93: 0.1 | S93: 0.1 | T93: 0.1 | U93: 0.1 | V93: 0.1 | W93: 0.1 | X93: 0.1 | Y93: 0.1 | Z93: 0.1 | AA93: 0.1 | AB93: 0.1 | AC93: 0.1 | AD93: 0.1 | AE93: 0.1 | AF93: 0.1 | AG93: 0.1 | AH93: 0.1 | AI93: 0.1 | AJ93: 0.1 | AK93: 0.1 | AL93: 0.1 | AM93: 0.1 | AO93: =AVERAGE(D93:O93) -> 0.1 | AP93: =AVERAGE(P93:AA93) -> 0.1 | AQ93: =AVERAGE(AB93:AM93) -> 0.1
A94: ср. % резервирования (КП) | B94: % | D94: 0.05 | E94: 0.05 | F94: 0.05 | G94: 0.05 | H94: 0.05 | I94: 0.05 | J94: 0.05 | K94: 0.05 | L94: 0.05 | M94: 0.05 | N94: 0.05 | O94: 0.05 | P94: 0.05 | Q94: 0.05 | R94: 0.05 | S94: 0.05 | T94: 0.05 | U94: 0.05 | V94: 0.05 | W94: 0.05 | X94: 0.05 | Y94: 0.05 | Z94: 0.05 | AA94: 0.05 | AB94: 0.05 | AC94: 0.05 | AD94: 0.05 | AE94: 0.05 | AF94: 0.05 | AG94: 0.05 | AH94: 0.05 | AI94: 0.05 | AJ94: 0.05 | AK94: 0.05 | AL94: 0.05 | AM94: 0.05 | AO94: =AVERAGE(D94:O94) -> 0.05 | AP94: =AVERAGE(P94:AA94) -> 0.05 | AQ94: =AVERAGE(AB94:AM94) -> 0.05
A95: ср. % резервирования (УО) | B95: % | D95: 0.01 | E95: 0.01 | F95: 0.01 | G95: 0.01 | H95: 0.01 | I95: 0.01 | J95: 0.01 | K95: 0.01 | L95: 0.01 | M95: 0.01 | N95: 0.01 | O95: 0.01 | P95: 0.01 | Q95: 0.01 | R95: 0.01 | S95: 0.01 | T95: 0.01 | U95: 0.01 | V95: 0.01 | W95: 0.01 | X95: 0.01 | Y95: 0.01 | Z95: 0.01 | AA95: 0.01 | AB95: 0.01 | AC95: 0.01 | AD95: 0.01 | AE95: 0.01 | AF95: 0.01 | AG95: 0.01 | AH95: 0.01 | AI95: 0.01 | AJ95: 0.01 | AK95: 0.01 | AL95: 0.01 | AM95: 0.01 | AO95: =AVERAGE(D95:O95) -> 0.01 | AP95: =AVERAGE(P95:AA95) -> 0.01 | AQ95: =AVERAGE(AB95:AM95) -> 0.01
A96: РППУ (КП) | B96: тыс сом | D96: =-D88*D94 -> -22.5 | E96: =-E88*E94 -> -46.5 | F96: =-F88*F94 -> -72 | G96: =-G88*G94 -> -99 | H96: =-H88*H94 -> -127.5 | I96: =-I88*I94 -> -157.5 | J96: =-J88*J94 -> -187.5 | K96: =-K88*K94 -> -220.5 | ... AM96: =-AM88*AM94 -> -1462.5 | AO96: =O96 -> -382.5 | AP96: =AA96 -> -922.5 | AQ96: =AM96 -> -1462.5
A97: РППУ (УО) | B97: тыс сом | D97: =-D95*(D86-D88) -> -10.5 | E97: =-E95*(E86-E88) -> -21.7 | F97: =-F95*(F86-F88) -> -33.6 | G97: =-G95*(G86-G88) -> -46.2 | H97: =-H95*(H86-H88) -> -59.5 | I97: =-I95*(I86-I88) -> -73.5 | J97: =-J95*(J86-J88) -> -87.5 | K97: =-K95*(K86-K88) -> -102.9 | ... AM97: =-AM95*(AM86-AM88) -> -682.5 | AO97: =O97 -> -178.5 | AP97: =AA97 -> -430.5 | AQ97: =AM97 -> -682.5
A98: % доход | B98: тыс сом | D98: =(1-2/102)*(C86+D86)/2*D92/12 -> 12.867647 | E98: =(1-2/102)*(D86+E86)/2*E92/12 -> 39.460784 | F98: =(1-2/102)*(E86+F86)/2*F92/12 -> 67.769608 | G98: =(1-2/102)*(F86+G86)/2*G92/12 -> 97.794118 | H98: =(1-2/102)*(G86+H86)/2*H92/12 -> 129.53431 | I98: =(1-2/102)*(H86+I86)/2*I92/12 -> 162.9902 | J98: =(1-2/102)*(I86+J86)/2*J92/12 -> 197.30392 | K98: =(1-2/102)*(J86+K86)/2*K92/12 -> 233.33333 | ... AM98: =(1-2/102)*(AL86+AM86)/2*AM92/12 -> 1647.0588 | AO98: =SUM(D98:O98) -> 2303.3088 | AP98: =SUM(P98:AA98) -> 8955.8824 | AQ98: =SUM(AB98:AM98) -> 16367.647
A99: трансфертный расход | B99: тыс сом | D99: =-(C88+D88)/2*D93/12 -> -1.875 | E99: =-(D88+E88)/2*E93/12 -> -5.75 | F99: =-(E88+F88)/2*F93/12 -> -9.875 | G99: =-(F88+G88)/2*G93/12 -> -14.25 | H99: =-(G88+H88)/2*H93/12 -> -18.875 | I99: =-(H88+I88)/2*I93/12 -> -23.75 | J99: =-(I88+J88)/2*J93/12 -> -28.75 | K99: =-(J88+K88)/2*K93/12 -> -34 | ... AM99: =-(AL88+AM88)/2*AM93/12 -> -240 | AO99: =SUM(D99:O99) -> -335.625 | AP99: =SUM(P99:AA99) -> -1305 | AQ99: =SUM(AB99:AM99) -> -2385
A100: комиссия партнеру | B100: тыс сом | D100: =-D91*D85 -> -15 | E100: =-E91*E85 -> -16 | F100: =-F91*F85 -> -17 | G100: =-G91*G85 -> -18 | H100: =-H91*H85 -> -19 | I100: =-I91*I85 -> -20 | J100: =-J91*J85 -> -20 | K100: =-K91*K85 -> -22 | ... AM100: =-AM91*AM85 -> -30 | AO100: =SUM(D100:O100) -> -255 | AP100: =SUM(P100:AA100) -> -360 | AQ100: =SUM(AB100:AM100) -> -360
A101: расходы на провизии | B101: тыс сом | D101: =(D96-C96)+(D97-C97) -> -33 | E101: =(E96-D96)+(E97-D97) -> -35.2 | F101: =(F96-E96)+(F97-E97) -> -37.4 | G101: =(G96-F96)+(G97-F97) -> -39.6 | H101: =(H96-G96)+(H97-G97) -> -41.8 | I101: =(I96-H96)+(I97-H97) -> -44 | J101: =(J96-I96)+(J97-I97) -> -44 | K101: =(K96-J96)+(K97-J97) -> -48.4 | ... AM101: =(AM96-AL96)+(AM97-AL97) -> -66 | AO101: =SUM(D101:O101) -> -561 | AP101: =SUM(P101:AA101) -> -792 | AQ101: =SUM(AB101:AM101) -> -792
A102: чистый операционный доход | B102: тыс сом | D102: =SUM(D98:D101) -> -37.007353 | E102: =SUM(E98:E101) -> -17.489216 | F102: =SUM(F98:F101) -> 3.4946078 | G102: =SUM(G98:G101) -> 25.944118 | H102: =SUM(H98:H101) -> 49.859314 | I102: =SUM(I98:I101) -> 75.240196 | J102: =SUM(J98:J101) -> 104.55392 | K102: =SUM(K98:K101) -> 128.93333 | ... AM102: =SUM(AM98:AM101) -> 1311.0588 | AO102: =SUM(D102:O102) -> 1151.6838 | AP102: =SUM(P102:AA102) -> 6498.8824 | AQ102: =SUM(AB102:AM102) -> 12830.647
A103: операционные расходы | B103: тыс сом | D103: =-'OPEX+CAPEX'!E29 -> -0.380625 | E103: =-'OPEX+CAPEX'!F29 -> -0.786625 | F103: =-'OPEX+CAPEX'!G29 -> -1.218 | G103: =-'OPEX+CAPEX'!H29 -> -1.67475 | H103: =-'OPEX+CAPEX'!I29 -> -2.156875 | I103: =-'OPEX+CAPEX'!J29 -> -2.664375 | J103: =-'OPEX+CAPEX'!K29 -> -3.171875 | K103: =-'OPEX+CAPEX'!L29 -> -3.730125 | ... AM103: =-'OPEX+CAPEX'!AN29 -> -24.740625 | AO103: =SUM(D103:O103) -> -37.30125 | AP103: =SUM(P103:AA103) -> -137.025 | AQ103: =SUM(AB103:AM103) -> -246.645
A104: прибыль | B104: тыс сом | D104: =D102+D103 -> -37.387978 | E104: =E102+E103 -> -18.275841 | F104: =F102+F103 -> 2.2766078 | G104: =G102+G103 -> 24.269368 | H104: =H102+H103 -> 47.702439 | I104: =I102+I103 -> 72.575821 | J104: =J102+J103 -> 101.38205 | K104: =K102+K103 -> 125.20321 | ... AM104: =AM102+AM103 -> 1286.3182 | AO104: =SUM(D104:O104) -> 1114.3826 | AP104: =SUM(P104:AA104) -> 6361.8574 | AQ104: =SUM(AB104:AM104) -> 12584.002
A106: Гарантия | B106: ЕИ | C106: Отв.исп.
A107: количество партнеров | B107: шт | D107: ='0'!D10 -> 15 | E107: ='0'!E10 -> 16 | F107: ='0'!F10 -> 17 | G107: ='0'!G10 -> 18 | H107: ='0'!H10 -> 19 | I107: ='0'!I10 -> 20 | J107: ='0'!J10 -> 20 | K107: ='0'!K10 -> 22 | ... AM107: ='0'!AM10 -> 30 | AO107: =O107 -> 30 | AP107: =AA107 -> 30 | AQ107: =AM107 -> 30
...

Sheet BaaS.2
A1: BaaS - Онлайн депозит
D3: 46023 | E3: 46054 | F3: 46082 | G3: 46113 | H3: 46143 | I3: 46174 | J3: 46204 | K3: 46235 | L3: 46266 | M3: 46296 | N3: 46327 | O3: 46357 | P3: 46388 | Q3: 46419 | R3: 46447 | S3: 46478 | T3: 46508 | U3: 46539 | V3: 46569 | W3: 46600 | X3: 46631 | Y3: 46661 | Z3: 46692 | AA3: 46722 | AB3: 46753 | AC3: 46784 | AD3: 46813 | AE3: 46844 | AF3: 46874 | AG3: 46905 | AH3: 46935 | AI3: 46966 | AJ3: 46997 | AK3: 47027 | AL3: 47058 | AM3: 47088 | AO3: =YEAR(O3) -> 2026 | AP3: =YEAR(AA3) -> 2027 | AQ3: =YEAR(AM3) -> 2028
D4: m1 | E4: m2 | F4: m3 | G4: m4 | H4: m5 | I4: m6 | J4: m7 | K4: m8 | L4: m9 | M4: m10 | N4: m11 | O4: m12 | P4: m13 | Q4: m14 | R4: m15 | S4: m16 | T4: m17 | U4: m18 | V4: m19 | W4: m20 | X4: m21 | Y4: m22 | Z4: m23 | AA4: m24 | AB4: m25 | AC4: m26 | AD4: m27 | AE4: m28 | AF4: m29 | AG4: m30 | AH4: m31 | AI4: m32 | AJ4: m33 | AK4: m34 | AL4: m35 | AM4: m36 | AO4: Y1 | AP4: Y2 | AQ4: Y3
D5: 1 | E5: =D5+1 -> 2 | F5: =E5+1 -> 3 | G5: =F5+1 -> 4 | H5: =G5+1 -> 5 | I5: =H5+1 -> 6 | J5: =I5+1 -> 7 | K5: =J5+1 -> 8 | L5: =K5+1 -> 9 | ... AM5: =AL5+1 -> 36
A7: Итого | B7: ЕИ | C7: Отв.исп.
A8: количество депозитов | B8: шт | D8: =D27/D22+D45/D40+D70/D65 -> 1350 | E8: =E27/E22+E45/E40+E70/E65 -> 2681.4375 | F8: =F27/F22+F45/F40+F70/F65 -> 3999.7427 | G8: =G27/G22+G45/G40+G70/G65 -> 5305.9176 | H8: =H27/H22+H45/H40+H70/H65 -> 6600.8993 | I8: =I27/I22+I45/I40+I70/I65 -> 7885.5526 | J8: =J27/J22+J45/J40+J70/J65 -> 9070.6754 | K8: =K27/K22+K45/K40+K70/K65 -> 10344.241 | ... AM8: =AM27/AM22+AM45/AM40+AM70/AM65 -> 32130.82 | AO8: =O8 -> 16188.695 | AP8: =AA8 -> 27732.221 | AQ8: =AM8 -> 32130.82
A9: портфель | B9: тыс сом | D9: =D27+D55+D80 -> 64350 | E9: =E27+E55+E80 -> 127815.19 | F9: =F27+F55+F80 -> 190654.4 | G9: =G27+G55+G80 -> 252915.41 | H9: =H27+H55+H80 -> 314642.87 | I9: =I27+I55+I80 -> 374563.75 | J9: =J27+J55+J80 -> 430857.08 | K9: =K27+K55+K80 -> 491351.47 | ... AM9: =AM27+AM55+AM80 -> 1510148.5 | AO9: =O9 -> 768963.01 | AP9: =AA9 -> 1303414.4 | AQ9: =AM9 -> 1510148.5
A10: % расход | B10: тыс сом | D10: =D31+D56+D81 -> -375.375 | E10: =E31+E56+E81 -> -1120.9636 | F10: =F31+F56+F81 -> -1857.7393 | G10: =G31+G56+G81 -> -2587.4906 | H10: =H31+H56+H81 -> -3310.7566 | I10: =I31+I56+I81 -> -4013.9544 | J10: =J31+J56+J81 -> -4698.2882 | K10: =K31+K56+K81 -> -5379.5499 | ... AM10: =AM31+AM56+AM81 -> -17556.242 | AO10: =SUM(D10:O10) -> -52559.885 | AP10: =SUM(P10:AA10) -> -150677.19 | AQ10: =SUM(AB10:AM10) -> -199225.02
A11: трансфертный доход | B11: тыс сом | D11: =D32+D57+D82 -> 429 | E11: =E32+E57+E82 -> 1281.1012 | F11: =F32+F57+F82 -> 2123.1306 | G11: =G32+G57+G82 -> 2957.1321 | H11: =H32+H57+H82 -> 3783.7218 | I11: =I32+I57+I82 -> 4587.3764 | J11: =J32+J57+J82 -> 5369.4722 | K11: =K32+K57+K82 -> 6148.057 | ... AM11: =AM32+AM57+AM82 -> 20064.277 | AO11: =SUM(D11:O11) -> 60068.44 | AP11: =SUM(P11:AA11) -> 172202.51 | AQ11: =SUM(AB11:AM11) -> 227685.73
A12: комиссия партнеру | B12: тыс сом | D12: =D33+D58+D83 -> -643.5 | E12: =E33+E58+E83 -> -686.4 | F12: =F33+F58+F83 -> -729.3 | G12: =G33+G58+G83 -> -772.2 | H12: =H33+H58+H83 -> -815.1 | I12: =I33+I58+I83 -> -855 | J12: =J33+J58+J83 -> -855 | K12: =K33+K58+K83 -> -940.5 | ... AM12: =AM33+AM58+AM83 -> -1269 | AO12: =SUM(D12:O12) -> -10914 | AP12: =SUM(P12:AA12) -> -15255 | AQ12: =SUM(AB12:AM12) -> -15228
A13: начисление расходов в ФЗД | B13: тыс сом | E13: =-0.2%*D9/12 -> -10.725 | F13: =-0.2%*(D9+E9)/2/12 -> -16.013766 | G13: =-0.2%*(E9+F9)/2/12 -> -26.539133 | H13: =-0.2%*(F9+G9)/2/12 -> -36.964151 | I13: =-0.2%*(G9+H9)/2/12 -> -47.296523 | J13: =-0.2%*(H9+I9)/2/12 -> -57.433885 | K13: =-0.2%*(I9+J9)/2/12 -> -67.118402 | L13: =-0.2%*(J9+K9)/2/12 -> -76.850712 | M13: =-0.2%*(K9+L9)/2/12 -> -87.253896 | ... AM13: =-0.2%*(AK9+AL9)/2/12 -> -248.95318 | AO13: =SUM(D13:O13) -> -634.33235 | AP13: =SUM(P13:AA13) -> -2060.3932 | AQ13: =SUM(AB13:AM13) -> -2810.1736
A14: чистый операционный доход | B14: тыс сом | D14: =D34+D59+D84+D13 -> -589.875 | E14: =E34+E59+E84+E13 -> -536.98734 | F14: =F34+F59+F84+F13 -> -479.92244 | G14: =G34+G59+G84+G13 -> -429.09762 | H14: =H34+H59+H84+H13 -> -379.09892 | I14: =I34+I59+I84+I13 -> -328.87447 | J14: =J34+J59+J84+J13 -> -241.24986 | K14: =K34+K59+K84+K13 -> -239.11128 | ... AM14: =AM34+AM59+AM84+AM13 -> 990.08139 | AO14: =SUM(D14:O14) -> -4039.7774 | AP14: =SUM(P14:AA14) -> 4209.9201 | AQ14: =SUM(AB14:AM14) -> 10422.543
A15: операционные расходы | B15: тыс сом | D15: =-('OPEX+CAPEX'!E38+'OPEX+CAPEX'!E45+'OPEX+CAPEX'!E46) -> -103.93214 | E15: =-('OPEX+CAPEX'!F38+'OPEX+CAPEX'!F45+'OPEX+CAPEX'!F46) -> -107.81022 | F15: =-('OPEX+CAPEX'!G38+'OPEX+CAPEX'!G45+'OPEX+CAPEX'!G46) -> -111.65004 | G15: =-('OPEX+CAPEX'!H38+'OPEX+CAPEX'!H45+'OPEX+CAPEX'!H46) -> -115.45454 | H15: =-('OPEX+CAPEX'!I38+'OPEX+CAPEX'!I45+'OPEX+CAPEX'!I46) -> -144.0181 | I15: =-('OPEX+CAPEX'!J38+'OPEX+CAPEX'!J45+'OPEX+CAPEX'!J46) -> -147.7599 | J15: =-('OPEX+CAPEX'!K38+'OPEX+CAPEX'!K45+'OPEX+CAPEX'!K46) -> -151.21181 | K15: =-('OPEX+CAPEX'!L38+'OPEX+CAPEX'!L45+'OPEX+CAPEX'!L46) -> -154.92132 | ... AM15: =-('OPEX+CAPEX'!AN38+'OPEX+CAPEX'!AN45+'OPEX+CAPEX'!AN46) -> -232.54572 | AO15: =SUM(D15:O15) -> -1697.9943 | AP15: =SUM(P15:AA15) -> -2455.2712 | AQ15: =SUM(AB15:AM15) -> -2732.1716
A16: прибыль | B16: тыс сом | D16: =D14+D15 -> -693.80714 | E16: =E14+E15 -> -644.79756 | F16: =F14+F15 -> -591.57248 | G16: =G14+G15 -> -544.55216 | H16: =H14+H15 -> -523.11702 | I16: =I14+I15 -> -476.63437 | J16: =J14+J15 -> -392.46167 | K16: =K14+K15 -> -394.0326 | ... AM16: =AM14+AM15 -> 757.53567 | AO16: =SUM(D16:O16) -> -5737.7717 | AP16: =SUM(P16:AA16) -> 1754.6489 | AQ16: =SUM(AB16:AM16) -> 7690.3713
A18: Депозиты KGS | B18: ЕИ | C18: Отв.исп.
A19: количество партнеров | B19: шт | D19: ='0'!D12 -> 15 | E19: ='0'!E12 -> 16 | F19: ='0'!F12 -> 17 | G19: ='0'!G12 -> 18 | H19: ='0'!H12 -> 19 | I19: ='0'!I12 -> 20 | J19: ='0'!J12 -> 20 | K19: ='0'!K12 -> 22 | ... AM19: ='0'!AM12 -> 30 | AO19: =O19 -> 30 | AP19: =AA19 -> 30 | AQ19: =AM19 -> 30
A20: среднее количество депозитов на 1 партнера | B20: шт | D20: 30 | E20: 30 | F20: 30 | G20: 30 | H20: 30 | I20: 30 | J20: 30 | K20: 30 | L20: 30 | M20: 30 | N20: 30 | O20: 30 | P20: 30 | Q20: 30 | R20: 30 | S20: 30 | T20: 30 | U20: 30 | V20: 30 | W20: 30 | X20: 30 | Y20: 30 | Z20: 30 | AA20: 30 | AB20: 30 | AC20: 30 | AD20: 30 | AE20: 30 | AF20: 30 | AG20: 30 | AH20: 30 | AI20: 30 | AJ20: 30 | AK20: 30 | AL20: 30 | AM20: 30 | AO20: =AVERAGE(D20:O20) -> 30 | AP20: =AVERAGE(P20:AA20) -> 30 | AQ20: =AVERAGE(AB20:AM20) -> 30
A21: количество новых депозитов | B21: шт | D21: =D19*D20 -> 450 | E21: =E19*E20 -> 480 | F21: =F19*F20 -> 510 | G21: =G19*G20 -> 540 | H21: =H19*H20 -> 570 | I21: =I19*I20 -> 600 | J21: =J19*J20 -> 600 | K21: =K19*K20 -> 660 | ... AM21: =AM19*AM20 -> 900 | AO21: =SUM(D21:O21) -> 7650 | AP21: =SUM(P21:AA21) -> 10800 | AQ21: =SUM(AB21:AM21) -> 10800
A22: ср. сумма депозита | B22: тыс сом | D22: 50 | E22: 50 | F22: 50 | G22: 50 | H22: 50 | I22: 50 | J22: 50 | K22: 50 | L22: 50 | M22: 50 | N22: 50 | O22: 50 | P22: 50 | Q22: 50 | R22: 50 | S22: 50 | T22: 50 | U22: 50 | V22: 50 | W22: 50 | X22: 50 | Y22: 50 | Z22: 50 | AA22: 50 | AB22: 50 | AC22: 50 | AD22: 50 | AE22: 50 | AF22: 50 | AG22: 50 | AH22: 50 | AI22: 50 | AJ22: 50 | AK22: 50 | AL22: 50 | AM22: 50 | AO22: =AVERAGE(D22:O22) -> 50 | AP22: =AVERAGE(P22:AA22) -> 50 | AQ22: =AVERAGE(AB22:AM22) -> 50
A23: привлечение депозитов | B23: тыс сом | D23: =D21*D22 -> 22500 | E23: =E21*E22 -> 24000 | F23: =F21*F22 -> 25500 | G23: =G21*G22 -> 27000 | H23: =H21*H22 -> 28500 | I23: =I21*I22 -> 30000 | J23: =J21*J22 -> 30000 | K23: =K21*K22 -> 33000 | ... AM23: =AM21*AM22 -> 45000 | AO23: =SUM(D23:O23) -> 382500 | AP23: =SUM(P23:AA23) -> 540000 | AQ23: =SUM(AB23:AM23) -> 540000
A24: капитализация % | B24: тыс сом | E24: =-D31/2 -> 65.625 | F24: =-E31/2 -> 195.97266 | G24: =-F31/2 -> 324.77959 | H24: =-G31/2 -> 452.35849 | I24: =-H31/2 -> 578.8036 | J24: =-I31/2 -> 704.20252 | K24: =-J31/2 -> 824.26108 | L24: =-K31/2 -> 943.78068 | ... AM24: =-AL31/2 -> 3089.8444 | AO24: =SUM(D24:O24) -> 7717.3897 | AP24: =SUM(P24:AA24) -> 25510.106 | AQ24: =SUM(AB24:AM24) -> 34878.041
A25: cр. срок портфеля | B25: мес | D25: 12 | E25: 12 | F25: 12 | G25: 12 | H25: 12 | I25: 12 | J25: 12 | K25: 12 | L25: 12 | M25: 12 | N25: 12 | O25: 12 | P25: 12 | Q25: 12 | R25: 12 | S25: 12 | T25: 12 | U25: 12 | V25: 12 | W25: 12 | X25: 12 | Y25: 12 | Z25: 12 | AA25: 12 | AB25: 12 | AC25: 12 | AD25: 12 | AE25: 12 | AF25: 12 | AG25: 12 | AH25: 12 | AI25: 12 | AJ25: 12 | AK25: 12 | AL25: 12 | AM25: 12 | AO25: =AVERAGE(D25:O25) -> 12 | AP25: =AVERAGE(P25:AA25) -> 12 | AQ25: =AVERAGE(AB25:AM25) -> 12
A26: возвраты | B26: тыс сом | D26: 0 | E26: =D27/E25 -> 1875 | F26: =E27/F25 -> 3724.2188 | G26: =F27/G25 -> 5555.1982 | H26: =G27/H25 -> 7369.33 | I26: =H27/I25 -> 9167.9157 | J26: =I27/J25 -> 10952.156 | K26: =J27/K25 -> 12598.16 | L26: =K27/L25 -> 14367.002 | ... AM26: =AL27/AM25 -> 44311.257 | AO26: =SUM(D26:O26) -> 120405.81 | AP26: =SUM(P26:AA26) -> 373118.01 | AQ26: =SUM(AB26:AM26) -> 501568.05
A27: портфель | B27: тыс сом | D27: =D23-D26 -> 22500 | E27: =D27+E23-E26+E24 -> 44690.625 | F27: =E27+F23-F26+F24 -> 66662.379 | G27: =F27+G23-G26+G24 -> 88431.96 | H27: =G27+H23-H26+H24 -> 110014.99 | I27: =H27+I23-I26+I24 -> 131425.88 | J27: =I27+J23-J26+J24 -> 151177.92 | K27: =J27+K23-K26+K24 -> 172404.02 | L27: =K27+L23-L26+L24 -> 194980.8 | ... AM27: =AL27+AM23-AM26+AM24 -> 535513.67 | AO27: =O27 -> 269811.58 | AP27: =AA27 -> 462203.68 | AQ27: =AM27 -> 535513.67
A28: комиссия партнеру | B28: % | D28: 0.01 | E28: 0.01 | F28: 0.01 | G28: 0.01 | H28: 0.01 | I28: 0.01 | J28: 0.01 | K28: 0.01 | L28: 0.01 | M28: 0.01 | N28: 0.01 | O28: 0.01 | P28: 0.01 | Q28: 0.01 | R28: 0.01 | S28: 0.01 | T28: 0.01 | U28: 0.01 | V28: 0.01 | W28: 0.01 | X28: 0.01 | Y28: 0.01 | Z28: 0.01 | AA28: 0.01 | AB28: 0.01 | AC28: 0.01 | AD28: 0.01 | AE28: 0.01 | AF28: 0.01 | AG28: 0.01 | AH28: 0.01 | AI28: 0.01 | AJ28: 0.01 | AK28: 0.01 | AL28: 0.01 | AM28: 0.01 | AO28: =AVERAGE(D28:O28) -> 0.01 | AP28: =AVERAGE(P28:AA28) -> 0.01 | AQ28: =AVERAGE(AB28:AM28) -> 0.01
A29: ср. % ставка портфеля | B29: % | D29: 0.14 | E29: 0.14 | F29: 0.14 | G29: 0.14 | H29: 0.14 | I29: 0.14 | J29: 0.14 | K29: 0.14 | L29: 0.14 | M29: 0.14 | N29: 0.14 | O29: 0.14 | P29: 0.14 | Q29: 0.14 | R29: 0.14 | S29: 0.14 | T29: 0.14 | U29: 0.14 | V29: 0.14 | W29: 0.14 | X29: 0.14 | Y29: 0.14 | Z29: 0.14 | AA29: 0.14 | AB29: 0.14 | AC29: 0.14 | AD29: 0.14 | AE29: 0.14 | AF29: 0.14 | AG29: 0.14 | AH29: 0.14 | AI29: 0.14 | AJ29: 0.14 | AK29: 0.14 | AL29: 0.14 | AM29: 0.14 | AO29: =AVERAGE(D29:O29) -> 0.14 | AP29: =AVERAGE(P29:AA29) -> 0.14 | AQ29: =AVERAGE(AB29:AM29) -> 0.14
A30: ср. % ставка фондирования | B30: % | D30: 0.16 | E30: 0.16 | F30: 0.16 | G30: 0.16 | H30: 0.16 | I30: 0.16 | J30: 0.16 | K30: 0.16 | L30: 0.16 | M30: 0.16 | N30: 0.16 | O30: 0.16 | P30: 0.16 | Q30: 0.16 | R30: 0.16 | S30: 0.16 | T30: 0.16 | U30: 0.16 | V30: 0.16 | W30: 0.16 | X30: 0.16 | Y30: 0.16 | Z30: 0.16 | AA30: 0.16 | AB30: 0.16 | AC30: 0.16 | AD30: 0.16 | AE30: 0.16 | AF30: 0.16 | AG30: 0.16 | AH30: 0.16 | AI30: 0.16 | AJ30: 0.16 | AK30: 0.16 | AL30: 0.16 | AM30: 0.16 | AO30: =AVERAGE(D30:O30) -> 0.16 | AP30: =AVERAGE(P30:AA30) -> 0.16 | AQ30: =AVERAGE(AB30:AM30) -> 0.16
A31: % расход | B31: тыс сом | D31: =-(C27+D27)/2*D29/12 -> -131.25 | E31: =-(D27+E27)/2*E29/12 -> -391.94531 | F31: =-(E27+F27)/2*F29/12 -> -649.55919 | G31: =-(F27+G27)/2*G29/12 -> -904.71698 | H31: =-(G27+H27)/2*H29/12 -> -1157.6072 | I31: =-(H27+I27)/2*I29/12 -> -1408.405 | J31: =-(I27+J27)/2*J29/12 -> -1648.5222 | K31: =-(J27+K27)/2*K29/12 -> -1887.5614 | ... AM31: =-(AL27+AM27)/2*AM29/12 -> -6225.6177 | AO31: =SUM(D31:O31) -> -18430.714 | AP31: =SUM(P31:AA31) -> -53358.809 | AQ31: =SUM(AB31:AM31) -> -70647.169
A32: трансфертный доход | B32: тыс сом | D32: =(C27+D27)/2*D30/12 -> 150 | E32: =(D27+E27)/2*E30/12 -> 447.9375 | F32: =(E27+F27)/2*F30/12 -> 742.35336 | G32: =(F27+G27)/2*G30/12 -> 1033.9623 | H32: =(G27+H27)/2*H30/12 -> 1322.9797 | I32: =(H27+I27)/2*I30/12 -> 1609.6058 | J32: =(I27+J27)/2*J30/12 -> 1884.0253 | K32: =(J27+K27)/2*K30/12 -> 2157.213 | ... AM32: =(AL27+AM27)/2*AM30/12 -> 7114.9917 | AO32: =SUM(D32:O32) -> 21063.673 | AP32: =SUM(P32:AA32) -> 60981.496 | AQ32: =SUM(AB32:AM32) -> 80739.621
A33: комиссия партнеру | B33: тыс сом | D33: =-D28*D23 -> -225 | E33: =-E28*E23 -> -240 | F33: =-F28*F23 -> -255 | G33: =-G28*G23 -> -270 | H33: =-H28*H23 -> -285 | I33: =-I28*I23 -> -300 | J33: =-J28*J23 -> -300 | K33: =-K28*K23 -> -330 | ... AM33: =-AM28*AM23 -> -450 | AO33: =SUM(D33:O33) -> -3825 | AP33: =SUM(P33:AA33) -> -5400 | AQ33: =SUM(AB33:AM33) -> -5400
A34: чистый операционный доход | B34: тыс сом | D34: =SUM(D31:D33) -> -206.25 | E34: =SUM(E31:E33) -> -184.00781 | F34: =SUM(F31:F33) -> -162.20583 | G34: =SUM(G31:G33) -> -140.75472 | H34: =SUM(H31:H33) -> -119.62754 | I34: =SUM(I31:I33) -> -98.799279 | J34: =SUM(J31:J33) -> -64.496834 | K34: =SUM(K31:K33) -> -60.348378 | ... AM34: =SUM(AM31:AM33) -> 439.37396 | AO34: =SUM(D34:O34) -> -1192.0409 | AP34: =SUM(P34:AA34) -> 2222.687 | AQ34: =SUM(AB34:AM34) -> 4692.4527
A36: Депозиты RUB | B36: ЕИ | C36: Отв.исп.
A37: количество партнеров | B37: шт | D37: ='0'!D12 -> 15 | E37: ='0'!E12 -> 16 | F37: ='0'!F12 -> 17 | G37: ='0'!G12 -> 18 | H37: ='0'!H12 -> 19 | I37: ='0'!I12 -> 20 | J37: ='0'!J12 -> 20 | K37: ='0'!K12 -> 22 | ... AM37: ='0'!AM12 -> 30 | AO37: =O37 -> 30 | AP37: =AA37 -> 30 | AQ37: =AM37 -> 30
A38: среднее количество депозитов на 1 партнера | B38: шт | D38: 30 | E38: 30 | F38: 30 | G38: 30 | H38: 30 | I38: 30 | J38: 30 | K38: 30 | L38: 30 | M38: 30 | N38: 30 | O38: 30 | P38: 30 | Q38: 30 | R38: 30 | S38: 30 | T38: 30 | U38: 30 | V38: 30 | W38: 30 | X38: 30 | Y38: 30 | Z38: 30 | AA38: 30 | AB38: 30 | AC38: 30 | AD38: 30 | AE38: 30 | AF38: 30 | AG38: 30 | AH38: 30 | AI38: 30 | AJ38: 30 | AK38: 30 | AL38: 30 | AM38: 30 | AO38: =AVERAGE(D38:O38) -> 30 | AP38: =AVERAGE(P38:AA38) -> 30 | AQ38: =AVERAGE(AB38:AM38) -> 30
A39: количество новых депозитов | B39: шт | D39: =D37*D38 -> 450 | E39: =E37*E38 -> 480 | F39: =F37*F38 -> 510 | G39: =G37*G38 -> 540 | H39: =H37*H38 -> 570 | I39: =I37*I38 -> 600 | J39: =J37*J38 -> 600 | K39: =K37*K38 -> 660 | ... AM39: =AM37*AM38 -> 900 | AO39: =SUM(D39:O39) -> 7650 | AP39: =SUM(P39:AA39) -> 10800 | AQ39: =SUM(AB39:AM39) -> 10800
A40: ср. сумма депозита | B40: тыс руб | D40: 50 | E40: 50 | F40: 50 | G40: 50 | H40: 50 | I40: 50 | J40: 50 | K40: 50 | L40: 50 | M40: 50 | N40: 50 | O40: 50 | P40: 50 | Q40: 50 | R40: 50 | S40: 50 | T40: 50 | U40: 50 | V40: 50 | W40: 50 | X40: 50 | Y40: 50 | Z40: 50 | AA40: 50 | AB40: 50 | AC40: 50 | AD40: 50 | AE40: 50 | AF40: 50 | AG40: 50 | AH40: 50 | AI40: 50 | AJ40: 50 | AK40: 50 | AL40: 50 | AM40: 50 | AO40: =AVERAGE(D40:O40) -> 50 | AP40: =AVERAGE(P40:AA40) -> 50 | AQ40: =AVERAGE(AB40:AM40) -> 50
A41: привлечение депозитов | B41: тыс руб | D41: =D39*D40 -> 22500 | E41: =E39*E40 -> 24000 | F41: =F39*F40 -> 25500 | G41: =G39*G40 -> 27000 | H41: =H39*H40 -> 28500 | I41: =I39*I40 -> 30000 | J41: =J39*J40 -> 30000 | K41: =K39*K40 -> 33000 | ... AM41: =AM39*AM40 -> 45000 | AO41: =SUM(D41:O41) -> 382500 | AP41: =SUM(P41:AA41) -> 540000 | AQ41: =SUM(AB41:AM41) -> 540000
A42: капитализация % | B42: тыс руб | E42: =-D49/2 -> 65.625 | F42: =-E49/2 -> 195.97266 | G42: =-F49/2 -> 324.77959 | H42: =-G49/2 -> 452.35849 | I42: =-H49/2 -> 578.8036 | J42: =-I49/2 -> 704.20252 | K42: =-J49/2 -> 824.26108 | L42: =-K49/2 -> 943.78068 | ... AM42: =-AL49/2 -> 3089.8444 | AO42: =SUM(D42:O42) -> 7717.3897 | AP42: =SUM(P42:AA42) -> 25510.106 | AQ42: =SUM(AB42:AM42) -> 34878.041
A43: cр. срок портфеля | B43: мес | D43: 12 | E43: 12 | F43: 12 | G43: 12 | H43: 12 | I43: 12 | J43: 12 | K43: 12 | L43: 12 | M43: 12 | N43: 12 | O43: 12 | P43: 12 | Q43: 12 | R43: 12 | S43: 12 | T43: 12 | U43: 12 | V43: 12 | W43: 12 | X43: 12 | Y43: 12 | Z43: 12 | AA43: 12 | AB43: 12 | AC43: 12 | AD43: 12 | AE43: 12 | AF43: 12 | AG43: 12 | AH43: 12 | AI43: 12 | AJ43: 12 | AK43: 12 | AL43: 12 | AM43: 12 | AO43: =AVERAGE(D43:O43) -> 12 | AP43: =AVERAGE(P43:AA43) -> 12 | AQ43: =AVERAGE(AB43:AM43) -> 12
A44: возвраты | B44: тыс руб | D44: 0 | E44: =D45/E43 -> 1875 | F44: =E45/F43 -> 3724.2188 | G44: =F45/G43 -> 5555.1982 | H44: =G45/H43 -> 7369.33 | I44: =H45/I43 -> 9167.9157 | J44: =I45/J43 -> 10952.156 | K44: =J45/K43 -> 12598.16 | L44: =K45/L43 -> 14367.002 | ... AM44: =AL45/AM43 -> 44311.257 | AO44: =SUM(D44:O44) -> 120405.81 | AP44: =SUM(P44:AA44) -> 373118.01 | AQ44: =SUM(AB44:AM44) -> 501568.05
A45: портфель | B45: тыс руб | D45: =D41-D44 -> 22500 | E45: =D45+E41-E44+E42 -> 44690.625 | F45: =E45+F41-F44+F42 -> 66662.379 | G45: =F45+G41-G44+G42 -> 88431.96 | H45: =G45+H41-H44+H42 -> 110014.99 | I45: =H45+I41-I44+I42 -> 131425.88 | J45: =I45+J41-J44+J42 -> 151177.92 | K45: =J45+K41-K44+K42 -> 172404.02 | L45: =K45+L41-L44+L42 -> 194980.8 | ... AM45: =AL45+AM41-AM44+AM42 -> 535513.67 | AO45: =O45 -> 269811.58 | AP45: =AA45 -> 462203.68 | AQ45: =AM45 -> 535513.67
A46: комиссия партнеру | B46: % | D46: 0.01 | E46: 0.01 | F46: 0.01 | G46: 0.01 | H46: 0.01 | I46: 0.01 | J46: 0.01 | K46: 0.01 | L46: 0.01 | M46: 0.01 | N46: 0.01 | O46: 0.01 | P46: 0.01 | Q46: 0.01 | R46: 0.01 | S46: 0.01 | T46: 0.01 | U46: 0.01 | V46: 0.01 | W46: 0.01 | X46: 0.01 | Y46: 0.01 | Z46: 0.01 | AA46: 0.01 | AB46: 0.01 | AC46: 0.01 | AD46: 0.01 | AE46: 0.01 | AF46: 0.01 | AG46: 0.01 | AH46: 0.01 | AI46: 0.01 | AJ46: 0.01 | AK46: 0.01 | AL46: 0.01 | AM46: 0.01 | AO46: =AVERAGE(D46:O46) -> 0.01 | AP46: =AVERAGE(P46:AA46) -> 0.01 | AQ46: =AVERAGE(AB46:AM46) -> 0.01
A47: ср. % ставка портфеля | B47: % | D47: 0.14 | E47: 0.14 | F47: 0.14 | G47: 0.14 | H47: 0.14 | I47: 0.14 | J47: 0.14 | K47: 0.14 | L47: 0.14 | M47: 0.14 | N47: 0.14 | O47: 0.14 | P47: 0.14 | Q47: 0.14 | R47: 0.14 | S47: 0.14 | T47: 0.14 | U47: 0.14 | V47: 0.14 | W47: 0.14 | X47: 0.14 | Y47: 0.14 | Z47: 0.14 | AA47: 0.14 | AB47: 0.14 | AC47: 0.14 | AD47: 0.14 | AE47: 0.14 | AF47: 0.14 | AG47: 0.14 | AH47: 0.14 | AI47: 0.14 | AJ47: 0.14 | AK47: 0.14 | AL47: 0.14 | AM47: 0.14 | AO47: =AVERAGE(D47:O47) -> 0.14 | AP47: =AVERAGE(P47:AA47) -> 0.14 | AQ47: =AVERAGE(AB47:AM47) -> 0.14
A48: ср. % ставка фондирования | B48: % | D48: 0.16 | E48: 0.16 | F48: 0.16 | G48: 0.16 | H48: 0.16 | I48: 0.16 | J48: 0.16 | K48: 0.16 | L48: 0.16 | M48: 0.16 | N48: 0.16 | O48: 0.16 | P48: 0.16 | Q48: 0.16 | R48: 0.16 | S48: 0.16 | T48: 0.16 | U48: 0.16 | V48: 0.16 | W48: 0.16 | X48: 0.16 | Y48: 0.16 | Z48: 0.16 | AA48: 0.16 | AB48: 0.16 | AC48: 0.16 | AD48: 0.16 | AE48: 0.16 | AF48: 0.16 | AG48: 0.16 | AH48: 0.16 | AI48: 0.16 | AJ48: 0.16 | AK48: 0.16 | AL48: 0.16 | AM48: 0.16 | AO48: =AVERAGE(D48:O48) -> 0.16 | AP48: =AVERAGE(P48:AA48) -> 0.16 | AQ48: =AVERAGE(AB48:AM48) -> 0.16
A49: % расход | B49: тыс руб | D49: =-(C45+D45)/2*D47/12 -> -131.25 | E49: =-(D45+E45)/2*E47/12 -> -391.94531 | F49: =-(E45+F45)/2*F47/12 -> -649.55919 | G49: =-(F45+G45)/2*G47/12 -> -904.71698 | H49: =-(G45+H45)/2*H47/12 -> -1157.6072 | I49: =-(H45+I45)/2*I47/12 -> -1408.405 | J49: =-(I45+J45)/2*J47/12 -> -1648.5222 | K49: =-(J45+K45)/2*K47/12 -> -1887.5614 | ... AM49: =-(AL45+AM45)/2*AM47/12 -> -6225.6177 | AO49: =SUM(D49:O49) -> -18430.714 | AP49: =SUM(P49:AA49) -> -53358.809 | AQ49: =SUM(AB49:AM49) -> -70647.169
A50: трансфертный доход | B50: тыс руб | D50: =(C45+D45)/2*D48/12 -> 150 | E50: =(D45+E45)/2*E48/12 -> 447.9375 | F50: =(E45+F45)/2*F48/12 -> 742.35336 | G50: =(F45+G45)/2*G48/12 -> 1033.9623 | H50: =(G45+H45)/2*H48/12 -> 1322.9797 | I50: =(H45+I45)/2*I48/12 -> 1609.6058 | J50: =(I45+J45)/2*J48/12 -> 1884.0253 | K50: =(J45+K45)/2*K48/12 -> 2157.213 | ... AM50: =(AL45+AM45)/2*AM48/12 -> 7114.9917 | AO50: =SUM(D50:O50) -> 21063.673 | AP50: =SUM(P50:AA50) -> 60981.496 | AQ50: =SUM(AB50:AM50) -> 80739.621
A51: комиссия партнеру | B51: тыс руб | D51: =-D46*D41 -> -225 | E51: =-E46*E41 -> -240 | F51: =-F46*F41 -> -255 | G51: =-G46*G41 -> -270 | H51: =-H46*H41 -> -285 | I51: =-I46*I41 -> -300 | J51: =-J46*J41 -> -300 | K51: =-K46*K41 -> -330 | ... AM51: =-AM46*AM41 -> -450 | AO51: =SUM(D51:O51) -> -3825 | AP51: =SUM(P51:AA51) -> -5400 | AQ51: =SUM(AB51:AM51) -> -5400
A52: чистый операционный доход | B52: тыс руб | D52: =SUM(D49:D51) -> -206.25 | E52: =SUM(E49:E51) -> -184.00781 | F52: =SUM(F49:F51) -> -162.20583 | G52: =SUM(G49:G51) -> -140.75472 | H52: =SUM(H49:H51) -> -119.62754 | I52: =SUM(I49:I51) -> -98.799279 | J52: =SUM(J49:J51) -> -64.496834 | K52: =SUM(K49:K51) -> -60.348378 | ... AM52: =SUM(AM49:AM51) -> 439.37396 | AO52: =SUM(D52:O52) -> -1192.0409 | AP52: =SUM(P52:AA52) -> 2222.687 | AQ52: =SUM(AB52:AM52) -> 4692.4527
A53: эквивалент в сом
A54: курс RUB (сом за 1 RUB) | B54: сом | D54: ='0'!D26 -> 1.01 | E54: ='0'!E26 -> 1.01 | F54: ='0'!F26 -> 1.01 | G54: ='0'!G26 -> 1.01 | H54: ='0'!H26 -> 1.01 | I54: ='0'!I26 -> 1 | J54: ='0'!J26 -> 1 | K54: ='0'!K26 -> 1 | ... AM54: ='0'!AM26 -> 0.97
A55: портфель | B55: тыс сом | D55: =D45*D$54 -> 22725 | E55: =E45*E$54 -> 45137.531 | F55: =F45*F$54 -> 67329.003 | G55: =G45*G$54 -> 89316.28 | H55: =H45*H$54 -> 111115.14 | I55: =I45*I$54 -> 131425.88 | J55: =J45*J$54 -> 151177.92 | K55: =K45*K$54 -> 172404.02 | ... AM55: =AM45*AM$54 -> 519448.26 | AO55: =O55 -> 269811.58 | AP55: =AA55 -> 448337.57 | AQ55: =AM55 -> 519448.26
A56: % расход | B56: тыс сом | D56: =D49*D$54 -> -132.5625 | E56: =E49*E$54 -> -395.86477 | F56: =F49*F$54 -> -656.05478 | G56: =G49*G$54 -> -913.76415 | H56: =H49*H$54 -> -1169.1833 | I56: =I49*I$54 -> -1408.405 | J56: =J49*J$54 -> -1648.5222 | K56: =K49*K$54 -> -1887.5614 | ... AM56: =AM49*AM$54 -> -6038.8492 | AO56: =SUM(D56:O56) -> -18463.065 | AP56: =SUM(P56:AA56) -> -51963.397 | AQ56: =SUM(AB56:AM56) -> -68527.754
A57: трансфертный доход | B57: тыс сом | D57: =D50*D$54 -> 151.5 | E57: =E50*E$54 -> 452.41688 | F57: =F50*F$54 -> 749.77689 | G57: =G50*G$54 -> 1044.3019 | H57: =H50*H$54 -> 1336.2095 | I57: =I50*I$54 -> 1609.6058 | J57: =J50*J$54 -> 1884.0253 | K57: =K50*K$54 -> 2157.213 | ... AM57: =AM50*AM$54 -> 6901.5419 | AO57: =SUM(D57:O57) -> 21100.645 | AP57: =SUM(P57:AA57) -> 59386.74 | AQ57: =SUM(AB57:AM57) -> 78317.433
A58: комиссия партнеру | B58: тыс сом | D58: =D51*D$54 -> -227.25 | E58: =E51*E$54 -> -242.4 | F58: =F51*F$54 -> -257.55 | G58: =G51*G$54 -> -272.7 | H58: =H51*H$54 -> -287.85 | I58: =I51*I$54 -> -300 | J58: =J51*J$54 -> -300 | K58: =K51*K$54 -> -330 | ... AM58: =AM51*AM$54 -> -436.5 | AO58: =SUM(D58:O58) -> -3837.75 | AP58: =SUM(P58:AA58) -> -5265 | AQ58: =SUM(AB58:AM58) -> -5238
A59: чистый операционный доход | B59: тыс сом | D59: =D52*D$54 -> -208.3125 | E59: =E52*E$54 -> -185.84789 | F59: =F52*F$54 -> -163.82789 | G59: =G52*G$54 -> -142.16226 | H59: =H52*H$54 -> -120.82382 | I59: =I52*I$54 -> -98.799279 | J59: =J52*J$54 -> -64.496834 | K59: =K52*K$54 -> -60.348378 | ... AM59: =AM52*AM$54 -> 426.19274 | AO59: =SUM(D59:O59) -> -1200.1694 | AP59: =SUM(P59:AA59) -> 2158.3425 | AQ59: =SUM(AB59:AM59) -> 4551.6791
A61: Депозиты USD | B61: ЕИ | C61: Отв.исп.
A62: количество партнеров | B62: шт | D62: ='0'!D12 -> 15 | E62: ='0'!E12 -> 16 | F62: ='0'!F12 -> 17 | G62: ='0'!G12 -> 18 | H62: ='0'!H12 -> 19 | I62: ='0'!I12 -> 20 | J62: ='0'!J12 -> 20 | K62: ='0'!K12 -> 22 | ... AM62: ='0'!AM12 -> 30 | AO62: =O62 -> 30 | AP62: =AA62 -> 30 | AQ62: =AM62 -> 30
A63: среднее количество депозитов на 1 партнера | B63: шт | D63: 30 | E63: 30 | F63: 30 | G63: 30 | H63: 30 | I63: 30 | J63: 30 | K63: 30 | L63: 30 | M63: 30 | N63: 30 | O63: 30 | P63: 30 | Q63: 30 | R63: 30 | S63: 30 | T63: 30 | U63: 30 | V63: 30 | W63: 30 | X63: 30 | Y63: 30 | Z63: 30 | AA63: 30 | AB63: 30 | AC63: 30 | AD63: 30 | AE63: 30 | AF63: 30 | AG63: 30 | AH63: 30 | AI63: 30 | AJ63: 30 | AK63: 30 | AL63: 30 | AM63: 30 | AO63: =AVERAGE(D63:O63) -> 30 | AP63: =AVERAGE(P63:AA63) -> 30 | AQ63: =AVERAGE(AB63:AM63) -> 30
A64: количество новых депозитов | B64: шт | D64: =D62*D63 -> 450 | E64: =E62*E63 -> 480 | F64: =F62*F63 -> 510 | G64: =G62*G63 -> 540 | H64: =H62*H63 -> 570 | I64: =I62*I63 -> 600 | J64: =J62*J63 -> 600 | K64: =K62*K63 -> 660 | ... AM64: =AM62*AM63 -> 900 | AO64: =SUM(D64:O64) -> 7650 | AP64: =SUM(P64:AA64) -> 10800 | AQ64: =SUM(AB64:AM64) -> 10800
A65: ср. сумма депозита | B65: тыс. долл | D65: 0.5 | E65: 0.5 | F65: 0.5 | G65: 0.5 | H65: 0.5 | I65: 0.5 | J65: 0.5 | K65: 0.5 | L65: 0.5 | M65: 0.5 | N65: 0.5 | O65: 0.5 | P65: 0.5 | Q65: 0.5 | R65: 0.5 | S65: 0.5 | T65: 0.5 | U65: 0.5 | V65: 0.5 | W65: 0.5 | X65: 0.5 | Y65: 0.5 | Z65: 0.5 | AA65: 0.5 | AB65: 0.5 | AC65: 0.5 | AD65: 0.5 | AE65: 0.5 | AF65: 0.5 | AG65: 0.5 | AH65: 0.5 | AI65: 0.5 | AJ65: 0.5 | AK65: 0.5 | AL65: 0.5 | AM65: 0.5 | AO65: =AVERAGE(D65:O65) -> 0.5 | AP65: =AVERAGE(P65:AA65) -> 0.5 | AQ65: =AVERAGE(AB65:AM65) -> 0.5
A66: привлечение депозитов | B66: тыс. долл | D66: =D64*D65 -> 225 | E66: =E64*E65 -> 240 | F66: =F64*F65 -> 255 | G66: =G64*G65 -> 270 | H66: =H64*H65 -> 285 | I66: =I64*I65 -> 300 | J66: =J64*J65 -> 300 | K66: =K64*K65 -> 330 | ... AM66: =AM64*AM65 -> 450 | AO66: =SUM(D66:O66) -> 3825 | AP66: =SUM(P66:AA66) -> 5400 | AQ66: =SUM(AB66:AM66) -> 5400
A67: капитализация % | B67: тыс. долл | E67: =-D74/2 -> 0.65625 | F67: =-E74/2 -> 1.9597266 | G67: =-F74/2 -> 3.2477959 | H67: =-G74/2 -> 4.5235849 | I67: =-H74/2 -> 5.788036 | J67: =-I74/2 -> 7.0420252 | K67: =-J74/2 -> 8.2426108 | L67: =-K74/2 -> 9.4378068 | ... AM67: =-AL74/2 -> 30.898444 | AO67: =SUM(D67:O67) -> 77.173897 | AP67: =SUM(P67:AA67) -> 255.10106 | AQ67: =SUM(AB67:AM67) -> 348.78041
A68: cр. срок портфеля | B68: мес | D68: 12 | E68: 12 | F68: 12 | G68: 12 | H68: 12 | I68: 12 | J68: 12 | K68: 12 | L68: 12 | M68: 12 | N68: 12 | O68: 12 | P68: 12 | Q68: 12 | R68: 12 | S68: 12 | T68: 12 | U68: 12 | V68: 12 | W68: 12 | X68: 12 | Y68: 12 | Z68: 12 | AA68: 12 | AB68: 12 | AC68: 12 | AD68: 12 | AE68: 12 | AF68: 12 | AG68: 12 | AH68: 12 | AI68: 12 | AJ68: 12 | AK68: 12 | AL68: 12 | AM68: 12 | AO68: =AVERAGE(D68:O68) -> 12 | AP68: =AVERAGE(P68:AA68) -> 12 | AQ68: =AVERAGE(AB68:AM68) -> 12
A69: возвраты | B69: тыс. долл | D69: 0 | E69: =D70/E68 -> 18.75 | F69: =E70/F68 -> 37.242188 | G69: =F70/G68 -> 55.551982 | H69: =G70/H68 -> 73.6933 | I69: =H70/I68 -> 91.679157 | J69: =I70/J68 -> 109.52156 | K69: =J70/K68 -> 125.9816 | L69: =K70/L68 -> 143.67002 | ... AM69: =AL70/AM68 -> 443.11257 | AO69: =SUM(D69:O69) -> 1204.0581 | AP69: =SUM(P69:AA69) -> 3731.1801 | AQ69: =SUM(AB69:AM69) -> 5015.6805
A70: портфель | B70: тыс. долл | D70: =D66-D69 -> 225 | E70: =D70+E66-E69+E67 -> 446.90625 | F70: =E70+F66-F69+F67 -> 666.62379 | G70: =F70+G66-G69+G67 -> 884.3196 | H70: =G70+H66-H69+H67 -> 1100.1499 | I70: =H70+I66-I69+I67 -> 1314.2588 | J70: =I70+J66-J69+J67 -> 1511.7792 | K70: =J70+K66-K69+K67 -> 1724.0402 | L70: =K70+L66-L69+L67 -> 1949.808 | ... AM70: =AL70+AM66-AM69+AM67 -> 5355.1367 | AO70: =O70 -> 2698.1158 | AP70: =AA70 -> 4622.0368 | AQ70: =AM70 -> 5355.1367
A71: комиссия партнеру | B71: % | D71: 0.01 | E71: 0.01 | F71: 0.01 | G71: 0.01 | H71: 0.01 | I71: 0.01 | J71: 0.01 | K71: 0.01 | L71: 0.01 | M71: 0.01 | N71: 0.01 | O71: 0.01 | P71: 0.01 | Q71: 0.01 | R71: 0.01 | S71: 0.01 | T71: 0.01 | U71: 0.01 | V71: 0.01 | W71: 0.01 | X71: 0.01 | Y71: 0.01 | Z71: 0.01 | AA71: 0.01 | AB71: 0.01 | AC71: 0.01 | AD71: 0.01 | AE71: 0.01 | AF71: 0.01 | AG71: 0.01 | AH71: 0.01 | AI71: 0.01 | AJ71: 0.01 | AK71: 0.01 | AL71: 0.01 | AM71: 0.01 | AO71: =AVERAGE(D71:O71) -> 0.01 | AP71: =AVERAGE(P71:AA71) -> 0.01 | AQ71: =AVERAGE(AB71:AM71) -> 0.01
A72: ср. % ставка портфеля | B72: % | D72: 0.14 | E72: 0.14 | F72: 0.14 | G72: 0.14 | H72: 0.14 | I72: 0.14 | J72: 0.14 | K72: 0.14 | L72: 0.14 | M72: 0.14 | N72: 0.14 | O72: 0.14 | P72: 0.14 | Q72: 0.14 | R72: 0.14 | S72: 0.14 | T72: 0.14 | U72: 0.14 | V72: 0.14 | W72: 0.14 | X72: 0.14 | Y72: 0.14 | Z72: 0.14 | AA72: 0.14 | AB72: 0.14 | AC72: 0.14 | AD72: 0.14 | AE72: 0.14 | AF72: 0.14 | AG72: 0.14 | AH72: 0.14 | AI72: 0.14 | AJ72: 0.14 | AK72: 0.14 | AL72: 0.14 | AM72: 0.14 | AO72: =AVERAGE(D72:O72) -> 0.14 | AP72: =AVERAGE(P72:AA72) -> 0.14 | AQ72: =AVERAGE(AB72:AM72) -> 0.14
A73: ср. % ставка фондирования | B73: % | D73: 0.16 | E73: 0.16 | F73: 0.16 | G73: 0.16 | H73: 0.16 | I73: 0.16 | J73: 0.16 | K73: 0.16 | L73: 0.16 | M73: 0.16 | N73: 0.16 | O73: 0.16 | P73: 0.16 | Q73: 0.16 | R73: 0.16 | S73: 0.16 | T73: 0.16 | U73: 0.16 | V73: 0.16 | W73: 0.16 | X73: 0.16 | Y73: 0.16 | Z73: 0.16 | AA73: 0.16 | AB73: 0.16 | AC73: 0.16 | AD73: 0.16 | AE73: 0.16 | AF73: 0.16 | AG73: 0.16 | AH73: 0.16 | AI73: 0.16 | AJ73: 0.16 | AK73: 0.16 | AL73: 0.16 | AM73: 0.16 | AO73: =AVERAGE(D73:O73) -> 0.16 | AP73: =AVERAGE(P73:AA73) -> 0.16 | AQ73: =AVERAGE(AB73:AM73) -> 0.16
A74: % расход | B74: тыс. долл | D74: =-(C70+D70)/2*D72/12 -> -1.3125 | E74: =-(D70+E70)/2*E72/12 -> -3.9194531 | F74: =-(E70+F70)/2*F72/12 -> -6.4955919 | G74: =-(F70+G70)/2*G72/12 -> -9.0471698 | H74: =-(G70+H70)/2*H72/12 -> -11.576072 | I74: =-(H70+I70)/2*I72/12 -> -14.08405 | J74: =-(I70+J70)/2*J72/12 -> -16.485222 | K74: =-(J70+K70)/2*K72/12 -> -18.875614 | ... AM74: =-(AL70+AM70)/2*AM72/12 -> -62.256177 | AO74: =SUM(D74:O74) -> -184.30714 | AP74: =SUM(P74:AA74) -> -533.58809 | AQ74: =SUM(AB74:AM74) -> -706.47169
A75: трансфертный доход | B75: тыс. долл | D75: =(C70+D70)/2*D73/12 -> 1.5 | E75: =(D70+E70)/2*E73/12 -> 4.479375 | F75: =(E70+F70)/2*F73/12 -> 7.4235336 | G75: =(F70+G70)/2*G73/12 -> 10.339623 | H75: =(G70+H70)/2*H73/12 -> 13.229797 | I75: =(H70+I70)/2*I73/12 -> 16.096058 | J75: =(I70+J70)/2*J73/12 -> 18.840253 | K75: =(J70+K70)/2*K73/12 -> 21.57213 | ... AM75: =(AL70+AM70)/2*AM73/12 -> 71.149917 | AO75: =SUM(D75:O75) -> 210.63673 | AP75: =SUM(P75:AA75) -> 609.81496 | AQ75: =SUM(AB75:AM75) -> 807.39621
A76: комиссия партнеру | B76: тыс. долл | D76: =-D71*D66 -> -2.25 | E76: =-E71*E66 -> -2.4 | F76: =-F71*F66 -> -2.55 | G76: =-G71*G66 -> -2.7 | H76: =-H71*H66 -> -2.85 | I76: =-I71*I66 -> -3 | J76: =-J71*J66 -> -3 | K76: =-K71*K66 -> -3.3 | ... AM76: =-AM71*AM66 -> -4.5 | AO76: =SUM(D76:O76) -> -38.25 | AP76: =SUM(P76:AA76) -> -54 | AQ76: =SUM(AB76:AM76) -> -54
A77: чистый операционный доход | B77: тыс. долл | D77: =SUM(D74:D76) -> -2.0625 | E77: =SUM(E74:E76) -> -1.8400781 | F77: =SUM(F74:F76) -> -1.6220583 | G77: =SUM(G74:G76) -> -1.4075472 | H77: =SUM(H74:H76) -> -1.1962754 | I77: =SUM(I74:I76) -> -0.98799279 | J77: =SUM(J74:J76) -> -0.64496834 | K77: =SUM(K74:K76) -> -0.60348378 | ... AM77: =SUM(AM74:AM76) -> 4.3937396 | AO77: =SUM(D77:O77) -> -11.920409 | AP77: =SUM(P77:AA77) -> 22.22687 | AQ77: =SUM(AB77:AM77) -> 46.924527
A78: эквивалент в сом
A79: курс USD (сом за 1 USD) | B79: сом | D79: ='0'!D27 -> 85 | E79: ='0'!E27 -> 85 | F79: ='0'!F27 -> 85 | G79: ='0'!G27 -> 85 | H79: ='0'!H27 -> 85 | I79: ='0'!I27 -> 85 | J79: ='0'!J27 -> 85 | K79: ='0'!K27 -> 85 | ... AM79: ='0'!AM27 -> 85
A80: портфель | B80: тыс сом | D80: =D70*D$79 -> 19125 | E80: =E70*E$79 -> 37987.031 | F80: =F70*F$79 -> 56663.022 | G80: =G70*G$79 -> 75167.166 | H80: =H70*H$79 -> 93512.74 | I80: =I70*I$79 -> 111712 | J80: =J70*J$79 -> 128501.23 | K80: =K70*K$79 -> 146543.42 | ... AM80: =AM70*AM$79 -> 455186.62 | AO80: =O80 -> 229339.85 | AP80: =AA80 -> 392873.13 | AQ80: =AM80 -> 455186.62
A81: % расход | B81: тыс сом | D81: =D74*D$79 -> -111.5625 | E81: =E74*E$79 -> -333.15352 | F81: =F74*F$79 -> -552.12531 | G81: =G74*G$79 -> -769.00943 | H81: =H74*H$79 -> -983.96612 | I81: =I74*I$79 -> -1197.1443 | J81: =J74*J$79 -> -1401.2438 | K81: =K74*K$79 -> -1604.4272 | ... AM81: =AM74*AM$79 -> -5291.7751 | AO81: =SUM(D81:O81) -> -15666.107 | AP81: =SUM(P81:AA81) -> -45354.987 | AQ81: =SUM(AB81:AM81) -> -60050.093
A82: трансфертный доход | B82: тыс сом | D82: =D75*D$79 -> 127.5 | E82: =E75*E$79 -> 380.74687 | F82: =F75*F$79 -> 631.00036 | G82: =G75*G$79 -> 878.86792 | H82: =H75*H$79 -> 1124.5327 | I82: =I75*I$79 -> 1368.1649 | J82: =J75*J$79 -> 1601.4215 | K82: =K75*K$79 -> 1833.631 | ... AM82: =AM75*AM$79 -> 6047.7429 | AO82: =SUM(D82:O82) -> 17904.122 | AP82: =SUM(P82:AA82) -> 51834.271 | AQ82: =SUM(AB82:AM82) -> 68628.678
A83: комиссия партнеру | B83: тыс сом | D83: =D76*D$79 -> -191.25 | E83: =E76*E$79 -> -204 | F83: =F76*F$79 -> -216.75 | G83: =G76*G$79 -> -229.5 | H83: =H76*H$79 -> -242.25 | I83: =I76*I$79 -> -255 | J83: =J76*J$79 -> -255 | K83: =K76*K$79 -> -280.5 | ... AM83: =AM76*AM$79 -> -382.5 | AO83: =SUM(D83:O83) -> -3251.25 | AP83: =SUM(P83:AA83) -> -4590 | AQ83: =SUM(AB83:AM83) -> -4590
A84: чистый операционный доход | B84: тыс сом | D84: =D77*D$79 -> -175.3125 | E84: =E77*E$79 -> -156.40664 | F84: =F77*F$79 -> -137.87496 | G84: =G77*G$79 -> -119.64151 | H84: =H77*H$79 -> -101.68341 | I84: =I77*I$79 -> -83.979387 | J84: =J77*J$79 -> -54.822309 | K84: =K77*K$79 -> -51.296121 | ... AM84: =AM77*AM$79 -> 373.46787 | AO84: =SUM(D84:O84) -> -1013.2348 | AP84: =SUM(P84:AA84) -> 1889.2839 | AQ84: =SUM(AB84:AM84) -> 3988.5848

Sheet BaaS.3
A1: BaaS - Онлайн транзакционный бизнес
D3: 46023 | E3: 46054 | F3: 46082 | G3: 46113 | H3: 46143 | I3: 46174 | J3: 46204 | K3: 46235 | L3: 46266 | M3: 46296 | N3: 46327 | O3: 46357 | P3: 46388 | Q3: 46419 | R3: 46447 | S3: 46478 | T3: 46508 | U3: 46539 | V3: 46569 | W3: 46600 | X3: 46631 | Y3: 46661 | Z3: 46692 | AA3: 46722 | AB3: 46753 | AC3: 46784 | AD3: 46813 | AE3: 46844 | AF3: 46874 | AG3: 46905 | AH3: 46935 | AI3: 46966 | AJ3: 46997 | AK3: 47027 | AL3: 47058 | AM3: 47088 | AO3: =YEAR(O3) -> 2026 | AP3: =YEAR(AA3) -> 2027 | AQ3: =YEAR(AM3) -> 2028
D4: m1 | E4: m2 | F4: m3 | G4: m4 | H4: m5 | I4: m6 | J4: m7 | K4: m8 | L4: m9 | M4: m10 | N4: m11 | O4: m12 | P4: m13 | Q4: m14 | R4: m15 | S4: m16 | T4: m17 | U4: m18 | V4: m19 | W4: m20 | X4: m21 | Y4: m22 | Z4: m23 | AA4: m24 | AB4: m25 | AC4: m26 | AD4: m27 | AE4: m28 | AF4: m29 | AG4: m30 | AH4: m31 | AI4: m32 | AJ4: m33 | AK4: m34 | AL4: m35 | AM4: m36 | AO4: Y1 | AP4: Y2 | AQ4: Y3
D5: 1 | E5: =D5+1 -> 2 | F5: =E5+1 -> 3 | G5: =F5+1 -> 4 | H5: =G5+1 -> 5 | I5: =H5+1 -> 6 | J5: =I5+1 -> 7 | K5: =J5+1 -> 8 | L5: =K5+1 -> 9 | ... AM5: =AL5+1 -> 36
A7: DCB ID / DCB BIO
A8: количество партнеров | B8: шт | D8: ='0'!D13 -> 15 | E8: ='0'!E13 -> 16 | F8: ='0'!F13 -> 17 | G8: ='0'!G13 -> 18 | H8: ='0'!H13 -> 19 | I8: ='0'!I13 -> 20 | J8: ='0'!J13 -> 20 | K8: ='0'!K13 -> 22 | ... AM8: ='0'!AM13 -> 30 | AO8: =O8 -> 30 | AP8: =AA8 -> 30 | AQ8: =AM8 -> 30
A9: среднее кол-во клиентов на 1 партнера | B9: шт | D9: 100 | E9: 100 | F9: 100 | G9: 100 | H9: 100 | I9: 100 | J9: 100 | K9: 100 | L9: 100 | M9: 100 | N9: 100 | O9: 100 | P9: 100 | Q9: 100 | R9: 100 | S9: 100 | T9: 100 | U9: 100 | V9: 100 | W9: 100 | X9: 100 | Y9: 100 | Z9: 100 | AA9: 100 | AB9: 100 | AC9: 100 | AD9: 100 | AE9: 100 | AF9: 100 | AG9: 100 | AH9: 100 | AI9: 100 | AJ9: 100 | AK9: 100 | AL9: 100 | AM9: 100 | AO9: =AVERAGE(D9:O9) -> 100 | AP9: =AVERAGE(P9:AA9) -> 100 | AQ9: =AVERAGE(AB9:AM9) -> 100
A10: количество клиентов | B10: шт | D10: =D8*D9 -> 1500 | E10: =E8*E9 -> 1600 | F10: =F8*F9 -> 1700 | G10: =G8*G9 -> 1800 | H10: =H8*H9 -> 1900 | I10: =I8*I9 -> 2000 | J10: =J8*J9 -> 2000 | K10: =K8*K9 -> 2200 | ... AM10: =AM8*AM9 -> 3000 | AO10: =SUM(D10:O10) -> 25500 | AP10: =SUM(P10:AA10) -> 36000 | AQ10: =SUM(AB10:AM10) -> 36000
A11: ср.кол-во идентификаций в месяц 1 клиента | B11: шт | D11: 1 | E11: 1 | F11: 1 | G11: 1 | H11: 1 | I11: 1 | J11: 1 | K11: 1 | L11: 1 | M11: 1 | N11: 1 | O11: 1 | P11: 1 | Q11: 1 | R11: 1 | S11: 1 | T11: 1 | U11: 1 | V11: 1 | W11: 1 | X11: 1 | Y11: 1 | Z11: 1 | AA11: 1 | AB11: 1 | AC11: 1 | AD11: 1 | AE11: 1 | AF11: 1 | AG11: 1 | AH11: 1 | AI11: 1 | AJ11: 1 | AK11: 1 | AL11: 1 | AM11: 1 | AO11: =AVERAGE(D11:O11) -> 1 | AP11: =AVERAGE(P11:AA11) -> 1 | AQ11: =AVERAGE(AB11:AM11) -> 1
A12: общее кол-во идентификаций | B12: шт | D12: =D10*D11 -> 1500 | E12: =E10*E11 -> 1600 | F12: =F10*F11 -> 1700 | G12: =G10*G11 -> 1800 | H12: =H10*H11 -> 1900 | I12: =I10*I11 -> 2000 | J12: =J10*J11 -> 2000 | K12: =K10*K11 -> 2200 | ... AM12: =AM10*AM11 -> 3000 | AO12: =SUM(D12:O12) -> 25500 | AP12: =SUM(P12:AA12) -> 36000 | AQ12: =SUM(AB12:AM12) -> 36000
A13: ср.комиссия за идентификацию 1 клиента | B13: сом | D13: 50 | E13: 50 | F13: 50 | G13: 50 | H13: 50 | I13: 50 | J13: 50 | K13: 50 | L13: 50 | M13: 50 | N13: 50 | O13: 50 | P13: 50 | Q13: 50 | R13: 50 | S13: 50 | T13: 50 | U13: 50 | V13: 50 | W13: 50 | X13: 50 | Y13: 50 | Z13: 50 | AA13: 50 | AB13: 50 | AC13: 50 | AD13: 50 | AE13: 50 | AF13: 50 | AG13: 50 | AH13: 50 | AI13: 50 | AJ13: 50 | AK13: 50 | AL13: 50 | AM13: 50 | AO13: =AVERAGE(D13:O13) -> 50 | AP13: =AVERAGE(P13:AA13) -> 50 | AQ13: =AVERAGE(AB13:AM13) -> 50
A14: комиссионный доход | B14: тыс сом | D14: =D12*D13/1000*(1-2/102) -> 73.529412 | E14: =E12*E13/1000*(1-2/102) -> 78.431373 | F14: =F12*F13/1000*(1-2/102) -> 83.333333 | G14: =G12*G13/1000*(1-2/102) -> 88.235294 | H14: =H12*H13/1000*(1-2/102) -> 93.137255 | I14: =I12*I13/1000*(1-2/102) -> 98.039216 | J14: =J12*J13/1000*(1-2/102) -> 98.039216 | K14: =K12*K13/1000*(1-2/102) -> 107.84314 | ... AM14: =AM12*AM13/1000*(1-2/102) -> 147.05882 | AO14: =SUM(D14:O14) -> 1250 | AP14: =SUM(P14:AA14) -> 1764.7059 | AQ14: =SUM(AB14:AM14) -> 1764.7059
A15: себестоимость 1 идентификации (OzForenzics, 0,29usd за 1 запрос) | B15: сом | D15: =-0.29*'0'!D27 -> -24.65 | E15: =-0.29*'0'!E27 -> -24.65 | F15: =-0.29*'0'!F27 -> -24.65 | G15: =-0.29*'0'!G27 -> -24.65 | H15: =-0.29*'0'!H27 -> -24.65 | I15: =-0.29*'0'!I27 -> -24.65 | J15: =-0.29*'0'!J27 -> -24.65 | K15: =-0.29*'0'!K27 -> -24.65 | ... AM15: =-0.29*'0'!AM27 -> -24.65 | AO15: =SUM(D15:O15) -> -295.8 | AP15: =SUM(P15:AA15) -> -295.8 | AQ15: =SUM(AB15:AM15) -> -295.8
A16: операционные расходы (provider) | B16: тыс сом | D16: =D12*D15/1000 -> -36.975 | E16: =E12*E15/1000 -> -39.44 | F16: =F12*F15/1000 -> -41.905 | G16: =G12*G15/1000 -> -44.37 | H16: =H12*H15/1000 -> -46.835 | I16: =I12*I15/1000 -> -49.3 | J16: =J12*J15/1000 -> -49.3 | K16: =K12*K15/1000 -> -54.23 | ... AM16: =AM12*AM15/1000 -> -73.95 | AO16: =SUM(D16:O16) -> -628.575 | AP16: =SUM(P16:AA16) -> -887.4 | AQ16: =SUM(AB16:AM16) -> -887.4
A17: операционные расходы (банк) | B17: тыс сом | D17: =-('OPEX+CAPEX'!E50+'OPEX+CAPEX'!E52+'OPEX+CAPEX'!E53) -> -100 | E17: =-('OPEX+CAPEX'!F50+'OPEX+CAPEX'!F52+'OPEX+CAPEX'!F53) -> -142.5 | F17: =-('OPEX+CAPEX'!G50+'OPEX+CAPEX'!G52+'OPEX+CAPEX'!G53) -> -206.25 | G17: =-('OPEX+CAPEX'!H50+'OPEX+CAPEX'!H52+'OPEX+CAPEX'!H53) -> -270 | H17: =-('OPEX+CAPEX'!I50+'OPEX+CAPEX'!I52+'OPEX+CAPEX'!I53) -> -270 | I17: =-('OPEX+CAPEX'!J50+'OPEX+CAPEX'!J52+'OPEX+CAPEX'!J53) -> -270 | J17: =-('OPEX+CAPEX'!K50+'OPEX+CAPEX'!K52+'OPEX+CAPEX'!K53) -> -270 | K17: =-('OPEX+CAPEX'!L50+'OPEX+CAPEX'!L52+'OPEX+CAPEX'!L53) -> -270 | ... AM17: =-('OPEX+CAPEX'!AN50+'OPEX+CAPEX'!AN52+'OPEX+CAPEX'!AN53) -> -277.08333 | AO17: =SUM(D17:O17) -> -2878.75 | AP17: =SUM(P17:AA17) -> -3325 | AQ17: =SUM(AB17:AM17) -> -3325
A18: прибыль | B18: тыс сом | D18: =D14+D16+D17 -> -63.445588 | E18: =E14+E16+E17 -> -103.50863 | F18: =F14+F16+F17 -> -164.82167 | G18: =G14+G16+G17 -> -226.13471 | H18: =H14+H16+H17 -> -223.69775 | I18: =I14+I16+I17 -> -221.26078 | J18: =J14+J16+J17 -> -221.26078 | K18: =K14+K16+K17 -> -216.38686 | ... AM18: =AM14+AM16+AM17 -> -203.97451 | AO18: =SUM(D18:O18) -> -2257.325 | AP18: =SUM(P18:AA18) -> -2447.6941 | AQ18: =SUM(AB18:AM18) -> -2447.6941
A20: QR прием / оплата
A21: количество партнеров QR-приход | B21: шт | D21: ='0'!D14 -> 7 | E21: ='0'!E14 -> 7 | F21: ='0'!F14 -> 8 | G21: ='0'!G14 -> 8 | H21: ='0'!H14 -> 8 | I21: ='0'!I14 -> 9 | J21: ='0'!J14 -> 9 | K21: ='0'!K14 -> 9 | ... AM21: ='0'!AM14 -> 14 | AO21: =O21 -> 14 | AP21: =AA21 -> 14 | AQ21: =AM21 -> 14
A22: количество партнеров QR-оплата | B22: шт | D22: ='0'!D15 -> 5 | E22: ='0'!E15 -> 5 | F22: ='0'!F15 -> 5 | G22: ='0'!G15 -> 6 | H22: ='0'!H15 -> 6 | I22: ='0'!I15 -> 6 | J22: ='0'!J15 -> 7 | K22: ='0'!K15 -> 7 | ... AM22: ='0'!AM15 -> 9 | AO22: =O22 -> 9 | AP22: =AA22 -> 9 | AQ22: =AM22 -> 9
A23: среднемесячная сумма Предварительного возмещения на 1 партнера (на транзитных счета) | B23: тыс сом | D23: =(270000+50000)/2 -> 160000 | E23: =(270000+50000)/2 -> 160000 | F23: =(270000+50000)/2 -> 160000 | G23: =(270000+50000)/2 -> 160000 | H23: =(270000+50000)/2 -> 160000 | I23: =(270000+50000)/2 -> 160000 | J23: =(270000+50000)/2 -> 160000 | K23: =(270000+50000)/2 -> 160000 | ... AM23: =(270000+50000)/2 -> 160000 | AO23: =AVERAGE(D23:O23) -> 160000 | AP23: =AVERAGE(P23:AA23) -> 160000 | AQ23: =AVERAGE(AB23:AM23) -> 160000
A24: общая сумма Предварительного возмещения (для исходящих платежей Партнеров) | B24: тыс сом | D24: =D22*D23 -> 800000 | E24: =E22*E23 -> 800000 | F24: =F22*F23 -> 800000 | G24: =G22*G23 -> 960000 | H24: =H22*H23 -> 960000 | I24: =I22*I23 -> 960000 | J24: =J22*J23 -> 1120000 | K24: =K22*K23 -> 1120000 | ... AM24: =AM22*AM23 -> 1440000 | AO24: =AVERAGE(D24:O24) -> 1053333.3 | AP24: =AVERAGE(P24:AA24) -> 1440000 | AQ24: =AVERAGE(AB24:AM24) -> 1440000
A25: ср.сумма остатка на р/с 1 Партнера по входящим платежам | B25: тыс сом | D25: 10000 | E25: 10000 | F25: 10000 | G25: 10000 | H25: 10000 | I25: 10000 | J25: 10000 | K25: 10000 | L25: 10000 | M25: 10000 | N25: 10000 | O25: 10000 | P25: 10000 | Q25: 10000 | R25: 10000 | S25: 10000 | T25: 10000 | U25: 10000 | V25: 10000 | W25: 10000 | X25: 10000 | Y25: 10000 | Z25: 10000 | AA25: 10000 | AB25: 10000 | AC25: 10000 | AD25: 10000 | AE25: 10000 | AF25: 10000 | AG25: 10000 | AH25: 10000 | AI25: 10000 | AJ25: 10000 | AK25: 10000 | AL25: 10000 | AM25: 10000 | AO25: =AVERAGE(D25:O25) -> 10000 | AP25: =AVERAGE(P25:AA25) -> 10000 | AQ25: =AVERAGE(AB25:AM25) -> 10000
A26: общая сумма остатков на р/с Партнеров по входящим платежам | B26: тыс сом | D26: =D21*D25 -> 70000 | E26: =E21*E25 -> 70000 | F26: =F21*F25 -> 80000 | G26: =G21*G25 -> 80000 | H26: =H21*H25 -> 80000 | I26: =I21*I25 -> 90000 | J26: =J21*J25 -> 90000 | K26: =K21*K25 -> 90000 | ... AM26: =AM21*AM25 -> 140000 | AO26: =O26 -> 140000 | AP26: =AA26 -> 140000 | AQ26: =AM26 -> 140000
A27: ср. % ставка фондирования | B27: % | D27: 0.04 | E27: 0.04 | F27: 0.04 | G27: 0.04 | H27: 0.04 | I27: 0.04 | J27: 0.04 | K27: 0.04 | L27: 0.04 | M27: 0.04 | N27: 0.04 | O27: 0.04 | P27: 0.04 | Q27: 0.04 | R27: 0.04 | S27: 0.04 | T27: 0.04 | U27: 0.04 | V27: 0.04 | W27: 0.04 | X27: 0.04 | Y27: 0.04 | Z27: 0.04 | AA27: 0.04 | AB27: 0.04 | AC27: 0.04 | AD27: 0.04 | AE27: 0.04 | AF27: 0.04 | AG27: 0.04 | AH27: 0.04 | AI27: 0.04 | AJ27: 0.04 | AK27: 0.04 | AL27: 0.04 | AM27: 0.04 | AO27: =AVERAGE(D27:O27) -> 0.04 | AP27: =AVERAGE(P27:AA27) -> 0.04 | AQ27: =AVERAGE(AB27:AM27) -> 0.04
A28: трансфертный доход | B28: тыс сом | D28: =(C24+D24+C26+D26)/2*D27/12 -> 1450 | E28: =(D24+E24+D26+E26)/2*E27/12 -> 2900 | F28: =(E24+F24+E26+F26)/2*F27/12 -> 2916.6667 | G28: =(F24+G24+F26+G26)/2*G27/12 -> 3200 | H28: =(G24+H24+G26+H26)/2*H27/12 -> 3466.6667 | I28: =(H24+I24+H26+I26)/2*I27/12 -> 3483.3333 | J28: =(I24+J24+I26+J26)/2*J27/12 -> 3766.6667 | K28: =(J24+K24+J26+K26)/2*K27/12 -> 4033.3333 | ... AM28: =(AL24+AM24+AL26+AM26)/2*AM27/12 -> 5266.6667 | AO28: =SUM(D28:O28) -> 43200 | AP28: =SUM(P28:AA28) -> 63200 | AQ28: =SUM(AB28:AM28) -> 63200
A29: ср.сумма исходящих переводов на 1 Партнера | B29: тыс сом | D29: 150000 | E29: 150000 | F29: 150000 | G29: 150000 | H29: 150000 | I29: 150000 | J29: 150000 | K29: 150000 | L29: 150000 | M29: 150000 | N29: 150000 | O29: 150000 | P29: 150000 | Q29: 150000 | R29: 150000 | S29: 150000 | T29: 150000 | U29: 150000 | V29: 150000 | W29: 150000 | X29: 150000 | Y29: 150000 | Z29: 150000 | AA29: 150000 | AB29: 150000 | AC29: 150000 | AD29: 150000 | AE29: 150000 | AF29: 150000 | AG29: 150000 | AH29: 150000 | AI29: 150000 | AJ29: 150000 | AK29: 150000 | AL29: 150000 | AM29: 150000 | AO29: =AVERAGE(D29:O29) -> 150000 | AP29: =AVERAGE(P29:AA29) -> 150000 | AQ29: =AVERAGE(AB29:AM29) -> 150000
A30: ср.сумма входящих переводов на 1 Партнера | B30: тыс сом | D30: =1250000/4 -> 312500 | E30: =1250000/4 -> 312500 | F30: =1250000/4 -> 312500 | G30: =1250000/4 -> 312500 | H30: =1250000/4 -> 312500 | I30: =1250000/4 -> 312500 | J30: =1250000/4 -> 312500 | K30: =1250000/4 -> 312500 | ... AM30: =1250000/4 -> 312500 | AO30: =AVERAGE(D30:O30) -> 312500 | AP30: =AVERAGE(P30:AA30) -> 312500 | AQ30: =AVERAGE(AB30:AM30) -> 312500
A31: общая сумма исходящих переводов | B31: тыс сом | D31: =D29*D22 -> 750000 | E31: =E29*E22 -> 750000 | F31: =F29*F22 -> 750000 | G31: =G29*G22 -> 900000 | H31: =H29*H22 -> 900000 | I31: =I29*I22 -> 900000 | J31: =J29*J22 -> 1050000 | K31: =K29*K22 -> 1050000 | ... AM31: =AM29*AM22 -> 1350000 | AO31: =SUM(D31:O31) -> 11850000 | AP31: =SUM(P31:AA31) -> 16200000 | AQ31: =SUM(AB31:AM31) -> 16200000
A32: общая сумма входящих переводов | B32: тыс сом | D32: =D30*D21 -> 2187500 | E32: =E30*E21 -> 2187500 | F32: =F30*F21 -> 2500000 | G32: =G30*G21 -> 2500000 | H32: =H30*H21 -> 2500000 | I32: =I30*I21 -> 2812500 | J32: =J30*J21 -> 2812500 | K32: =K30*K21 -> 2812500 | ... AM32: =AM30*AM21 -> 4375000 | AO32: =SUM(D32:O32) -> 34687500 | AP32: =SUM(P32:AA32) -> 52500000 | AQ32: =SUM(AB32:AM32) -> 52500000
A33: ср.комиссия за исходящие платежи партнера | B33: % | D33: 0.005 | E33: 0.005 | F33: 0.005 | G33: 0.005 | H33: 0.005 | I33: 0.005 | J33: 0.005 | K33: 0.005 | L33: 0.005 | M33: 0.005 | N33: 0.005 | O33: 0.005 | P33: 0.005 | Q33: 0.005 | R33: 0.005 | S33: 0.005 | T33: 0.005 | U33: 0.005 | V33: 0.005 | W33: 0.005 | X33: 0.005 | Y33: 0.005 | Z33: 0.005 | AA33: 0.005 | AB33: 0.005 | AC33: 0.005 | AD33: 0.005 | AE33: 0.005 | AF33: 0.005 | AG33: 0.005 | AH33: 0.005 | AI33: 0.005 | AJ33: 0.005 | AK33: 0.005 | AL33: 0.005 | AM33: 0.005 | AO33: =AVERAGE(D33:O33) -> 0.005 | AP33: =AVERAGE(P33:AA33) -> 0.005 | AQ33: =AVERAGE(AB33:AM33) -> 0.005
A34: ср.комиссия за исходящие платежи (Interchange) | B34: % | D34: 0.002 | E34: 0.002 | F34: 0.002 | G34: 0.002 | H34: 0.002 | I34: 0.002 | J34: 0.002 | K34: 0.002 | L34: 0.002 | M34: 0.002 | N34: 0.002 | O34: 0.002 | P34: 0.002 | Q34: 0.002 | R34: 0.002 | S34: 0.002 | T34: 0.002 | U34: 0.002 | V34: 0.002 | W34: 0.002 | X34: 0.002 | Y34: 0.002 | Z34: 0.002 | AA34: 0.002 | AB34: 0.002 | AC34: 0.002 | AD34: 0.002 | AE34: 0.002 | AF34: 0.002 | AG34: 0.002 | AH34: 0.002 | AI34: 0.002 | AJ34: 0.002 | AK34: 0.002 | AL34: 0.002 | AM34: 0.002 | AO34: =AVERAGE(D34:O34) -> 0.002 | AP34: =AVERAGE(P34:AA34) -> 0.002 | AQ34: =AVERAGE(AB34:AM34) -> 0.002
A35: ср.комиссия за входящие платежи партнера | B35: % | D35: 0.005 | E35: 0.005 | F35: 0.005 | G35: 0.005 | H35: 0.005 | I35: 0.005 | J35: 0.005 | K35: 0.005 | L35: 0.005 | M35: 0.005 | N35: 0.005 | O35: 0.005 | P35: 0.005 | Q35: 0.005 | R35: 0.005 | S35: 0.005 | T35: 0.005 | U35: 0.005 | V35: 0.005 | W35: 0.005 | X35: 0.005 | Y35: 0.005 | Z35: 0.005 | AA35: 0.005 | AB35: 0.005 | AC35: 0.005 | AD35: 0.005 | AE35: 0.005 | AF35: 0.005 | AG35: 0.005 | AH35: 0.005 | AI35: 0.005 | AJ35: 0.005 | AK35: 0.005 | AL35: 0.005 | AM35: 0.005 | AO35: =AVERAGE(D35:O35) -> 0.005 | AP35: =AVERAGE(P35:AA35) -> 0.005 | AQ35: =AVERAGE(AB35:AM35) -> 0.005
A36: комиссионный доход | B36: тыс сом | D36: =(D31*D33+D32*D35+D31*D34)*(1-2/102) -> 15870.098 | E36: =(E31*E33+E32*E35+E31*E34)*(1-2/102) -> 15870.098 | F36: =(F31*F33+F32*F35+F31*F34)*(1-2/102) -> 17401.961 | G36: =(G31*G33+G32*G35+G31*G34)*(1-2/102) -> 18431.373 | H36: =(H31*H33+H32*H35+H31*H34)*(1-2/102) -> 18431.373 | I36: =(I31*I33+I32*I35+I31*I34)*(1-2/102) -> 19963.235 | J36: =(J31*J33+J32*J35+J31*J34)*(1-2/102) -> 20992.647 | K36: =(K31*K33+K32*K35+K31*K34)*(1-2/102) -> 20992.647 | ... AM36: =(AM31*AM33+AM32*AM35+AM31*AM34)*(1-2/102) -> 30710.784 | AO36: =SUM(D36:O36) -> 251360.29 | AP36: =SUM(P36:AA36) -> 368529.41 | AQ36: =SUM(AB36:AM36) -> 368529.41
A37: ср.комиссия возмещения Процессингу за входящие платежи | B37: % | D37: 0.001 | E37: 0.001 | F37: 0.001 | G37: 0.001 | H37: 0.001 | I37: 0.001 | J37: 0.001 | K37: 0.001 | L37: 0.001 | M37: 0.001 | N37: 0.001 | O37: 0.001 | P37: 0.001 | Q37: 0.001 | R37: 0.001 | S37: 0.001 | T37: 0.001 | U37: 0.001 | V37: 0.001 | W37: 0.001 | X37: 0.001 | Y37: 0.001 | Z37: 0.001 | AA37: 0.001 | AB37: 0.001 | AC37: 0.001 | AD37: 0.001 | AE37: 0.001 | AF37: 0.001 | AG37: 0.001 | AH37: 0.001 | AI37: 0.001 | AJ37: 0.001 | AK37: 0.001 | AL37: 0.001 | AM37: 0.001 | AO37: =AVERAGE(D37:O37) -> 0.001 | AP37: =AVERAGE(P37:AA37) -> 0.001 | AQ37: =AVERAGE(AB37:AM37) -> 0.001
A38: сумма возмещения Процессингу за входящие платежи | B38: тыс сом | D38: =-D32*D37 -> -2187.5 | E38: =-E32*E37 -> -2187.5 | F38: =-F32*F37 -> -2500 | G38: =-G32*G37 -> -2500 | H38: =-H32*H37 -> -2500 | I38: =-I32*I37 -> -2812.5 | J38: =-J32*J37 -> -2812.5 | K38: =-K32*K37 -> -2812.5 | ... AM38: =-AM32*AM37 -> -4375 | AO38: =SUM(D38:O38) -> -34687.5 | AP38: =SUM(P38:AA38) -> -52500 | AQ38: =SUM(AB38:AM38) -> -52500
A39: ср.комиссия за входящие платежи (Interchange) | B39: % | D39: 0.002 | E39: 0.002 | F39: 0.002 | G39: 0.002 | H39: 0.002 | I39: 0.002 | J39: 0.002 | K39: 0.002 | L39: 0.002 | M39: 0.002 | N39: 0.002 | O39: 0.002 | P39: 0.002 | Q39: 0.002 | R39: 0.002 | S39: 0.002 | T39: 0.002 | U39: 0.002 | V39: 0.002 | W39: 0.002 | X39: 0.002 | Y39: 0.002 | Z39: 0.002 | AA39: 0.002 | AB39: 0.002 | AC39: 0.002 | AD39: 0.002 | AE39: 0.002 | AF39: 0.002 | AG39: 0.002 | AH39: 0.002 | AI39: 0.002 | AJ39: 0.002 | AK39: 0.002 | AL39: 0.002 | AM39: 0.002 | AO39: =AVERAGE(D39:O39) -> 0.002 | AP39: =AVERAGE(P39:AA39) -> 0.002 | AQ39: =AVERAGE(AB39:AM39) -> 0.002
A40: сумма возмещения за входящие платежи (Interchange) | B40: тыс сом | D40: =-D32*D39 -> -4375 | E40: =-E32*E39 -> -4375 | F40: =-F32*F39 -> -5000 | G40: =-G32*G39 -> -5000 | H40: =-H32*H39 -> -5000 | I40: =-I32*I39 -> -5625 | J40: =-J32*J39 -> -5625 | K40: =-K32*K39 -> -5625 | ... AM40: =-AM32*AM39 -> -8750 | AO40: =SUM(D40:O40) -> -69375 | AP40: =SUM(P40:AA40) -> -105000 | AQ40: =SUM(AB40:AM40) -> -105000
A41: ср.комиссия за исходящие платежи Партнера (Interchange) | B41: % | D41: 0.001 | E41: 0.001 | F41: 0.001 | G41: 0.001 | H41: 0.001 | I41: 0.001 | J41: 0.001 | K41: 0.001 | L41: 0.001 | M41: 0.001 | N41: 0.001 | O41: 0.001 | P41: 0.001 | Q41: 0.001 | R41: 0.001 | S41: 0.001 | T41: 0.001 | U41: 0.001 | V41: 0.001 | W41: 0.001 | X41: 0.001 | Y41: 0.001 | Z41: 0.001 | AA41: 0.001 | AB41: 0.001 | AC41: 0.001 | AD41: 0.001 | AE41: 0.001 | AF41: 0.001 | AG41: 0.001 | AH41: 0.001 | AI41: 0.001 | AJ41: 0.001 | AK41: 0.001 | AL41: 0.001 | AM41: 0.001 | AO41: =AVERAGE(D41:O41) -> 0.001 | AP41: =AVERAGE(P41:AA41) -> 0.001 | AQ41: =AVERAGE(AB41:AM41) -> 0.001
A42: сумма возмещения Партнеру за исходящие платежи (Interchange) | B42: тыс сом | D42: =-(D41*D31) -> -750 | E42: =-(E41*E31) -> -750 | F42: =-(F41*F31) -> -750 | G42: =-(G41*G31) -> -900 | H42: =-(H41*H31) -> -900 | I42: =-(I41*I31) -> -900 | J42: =-(J41*J31) -> -1050 | K42: =-(K41*K31) -> -1050 | ... AM42: =-(AM41*AM31) -> -1350 | AO42: =SUM(D42:O42) -> -11850 | AP42: =SUM(P42:AA42) -> -16200 | AQ42: =SUM(AB42:AM42) -> -16200
A43: комиссионный расход | B43: тыс сом | D43: =D38+D40+D42 -> -7312.5 | E43: =E38+E40+E42 -> -7312.5 | F43: =F38+F40+F42 -> -8250 | G43: =G38+G40+G42 -> -8400 | H43: =H38+H40+H42 -> -8400 | I43: =I38+I40+I42 -> -9337.5 | J43: =J38+J40+J42 -> -9487.5 | K43: =K38+K40+K42 -> -9487.5 | ... AM43: =AM38+AM40+AM42 -> -14475 | AO43: =SUM(D43:O43) -> -115912.5 | AP43: =SUM(P43:AA43) -> -173700 | AQ43: =SUM(AB43:AM43) -> -173700
A44: операционные расходы (банк) | B44: тыс сом | D44: =-('OPEX+CAPEX'!E60+'OPEX+CAPEX'!E64+'OPEX+CAPEX'!E65) -> -342.14286 | E44: =-('OPEX+CAPEX'!F60+'OPEX+CAPEX'!F64+'OPEX+CAPEX'!F65) -> -207.14286 | F44: =-('OPEX+CAPEX'!G60+'OPEX+CAPEX'!G64+'OPEX+CAPEX'!G65) -> -239.01786 | G44: =-('OPEX+CAPEX'!H60+'OPEX+CAPEX'!H64+'OPEX+CAPEX'!H65) -> -239.01786 | H44: =-('OPEX+CAPEX'!I60+'OPEX+CAPEX'!I64+'OPEX+CAPEX'!I65) -> -239.01786 | I44: =-('OPEX+CAPEX'!J60+'OPEX+CAPEX'!J64+'OPEX+CAPEX'!J65) -> -239.01786 | J44: =-('OPEX+CAPEX'!K60+'OPEX+CAPEX'!K64+'OPEX+CAPEX'!K65) -> -239.01786 | K44: =-('OPEX+CAPEX'!L60+'OPEX+CAPEX'!L64+'OPEX+CAPEX'!L65) -> -239.01786 | ... AM44: =-('OPEX+CAPEX'!AN60+'OPEX+CAPEX'!AN64+'OPEX+CAPEX'!AN65) -> -239.01786 | AO44: =SUM(D44:O44) -> -2939.4643 | AP44: =SUM(P44:AA44) -> -2868.2143 | AQ44: =SUM(AB44:AM44) -> -2868.2143
A45: прибыль | B45: тыс сом | D45: =D28+D36+D43+D44 -> 9665.4552 | E45: =E28+E36+E43+E44 -> 11250.455 | F45: =F28+F36+F43+F44 -> 11829.61 | G45: =G28+G36+G43+G44 -> 12992.355 | H45: =H28+H36+H43+H44 -> 13259.021 | I45: =I28+I36+I43+I44 -> 13870.051 | J45: =J28+J36+J43+J44 -> 15032.796 | K45: =K28+K36+K43+K44 -> 15299.463 | ... AM45: =AM28+AM36+AM43+AM44 -> 21263.433 | AO45: =SUM(D45:O45) -> 175708.33 | AP45: =SUM(P45:AA45) -> 255161.2 | AQ45: =SUM(AB45:AM45) -> 255161.2
A47: Кошельки
A48: количество партнеров | B48: шт | D48: ='0'!D16 -> 2 | E48: ='0'!E16 -> 2 | F48: ='0'!F16 -> 2 | G48: ='0'!G16 -> 3 | H48: ='0'!H16 -> 3 | I48: ='0'!I16 -> 4 | J48: ='0'!J16 -> 4 | K48: ='0'!K16 -> 4 | ... AM48: ='0'!AM16 -> 6 | AO48: =O48 -> 6 | AP48: =AA48 -> 6 | AQ48: =AM48 -> 6
A49: среднее количество кошельков на 1 партнера | B49: шт | D49: 20 | E49: 20 | F49: 20 | G49: 20 | H49: 20 | I49: 20 | J49: 20 | K49: 20 | L49: 20 | M49: 20 | N49: 20 | O49: 20 | P49: 20 | Q49: 20 | R49: 20 | S49: 20 | T49: 20 | U49: 20 | V49: 20 | W49: 20 | X49: 20 | Y49: 20 | Z49: 20 | AA49: 20 | AB49: 20 | AC49: 20 | AD49: 20 | AE49: 20 | AF49: 20 | AG49: 20 | AH49: 20 | AI49: 20 | AJ49: 20 | AK49: 20 | AL49: 20 | AM49: 20 | AO49: =AVERAGE(D49:O49) -> 20 | AP49: =AVERAGE(P49:AA49) -> 20 | AQ49: =AVERAGE(AB49:AM49) -> 20
A50: количество кошельков | B50: шт | D50: =D48*D49 -> 40 | E50: =E48*E49 -> 40 | F50: =F48*F49 -> 40 | G50: =G48*G49 -> 60 | H50: =H48*H49 -> 60 | I50: =I48*I49 -> 80 | J50: =J48*J49 -> 80 | K50: =K48*K49 -> 80 | ... AM50: =AM48*AM49 -> 120 | AO50: =SUM(D50:O50) -> 900 | AP50: =SUM(P50:AA50) -> 1440 | AQ50: =SUM(AB50:AM50) -> 1440
A51: ср. остаток в 1 кошельке | B51: тыс. сом | D51: 5 | E51: 5 | F51: 5 | G51: 5 | H51: 5 | I51: 5 | J51: 5 | K51: 5 | L51: 5 | M51: 5 | N51: 5 | O51: 5 | P51: 5 | Q51: 5 | R51: 5 | S51: 5 | T51: 5 | U51: 5 | V51: 5 | W51: 5 | X51: 5 | Y51: 5 | Z51: 5 | AA51: 5 | AB51: 5 | AC51: 5 | AD51: 5 | AE51: 5 | AF51: 5 | AG51: 5 | AH51: 5 | AI51: 5 | AJ51: 5 | AK51: 5 | AL51: 5 | AM51: 5 | AO51: =AVERAGE(D51:O51) -> 5 | AP51: =AVERAGE(P51:AA51) -> 5 | AQ51: =AVERAGE(AB51:AM51) -> 5
A52: портфель | B52: тыс. сом | D52: =D50*D51 -> 200 | E52: =E50*E51 -> 200 | F52: =F50*F51 -> 200 | G52: =G50*G51 -> 300 | H52: =H50*H51 -> 300 | I52: =I50*I51 -> 400 | J52: =J50*J51 -> 400 | K52: =K50*K51 -> 400 | ... AM52: =AM50*AM51 -> 600 | AO52: =O52 -> 600 | AP52: =AA52 -> 600 | AQ52: =AM52 -> 600
A53: ср. % ставка фондирования | B53: % | D53: 0.04 | E53: 0.04 | F53: 0.04 | G53: 0.04 | H53: 0.04 | I53: 0.04 | J53: 0.04 | K53: 0.04 | L53: 0.04 | M53: 0.04 | N53: 0.04 | O53: 0.04 | P53: 0.04 | Q53: 0.04 | R53: 0.04 | S53: 0.04 | T53: 0.04 | U53: 0.04 | V53: 0.04 | W53: 0.04 | X53: 0.04 | Y53: 0.04 | Z53: 0.04 | AA53: 0.04 | AB53: 0.04 | AC53: 0.04 | AD53: 0.04 | AE53: 0.04 | AF53: 0.04 | AG53: 0.04 | AH53: 0.04 | AI53: 0.04 | AJ53: 0.04 | AK53: 0.04 | AL53: 0.04 | AM53: 0.04 | AO53: =AVERAGE(D53:O53) -> 0.04 | AP53: =AVERAGE(P53:AA53) -> 0.04 | AQ53: =AVERAGE(AB53:AM53) -> 0.04
A54: трансфертный доход | B54: тыс. сом | D54: =(C52+D52)/2*D53/12 -> 0.33333333 | E54: =(D52+E52)/2*E53/12 -> 0.66666667 | F54: =(E52+F52)/2*F53/12 -> 0.66666667 | G54: =(F52+G52)/2*G53/12 -> 0.83333333 | H54: =(G52+H52)/2*H53/12 -> 1 | I54: =(H52+I52)/2*I53/12 -> 1.1666667 | J54: =(I52+J52)/2*J53/12 -> 1.3333333 | K54: =(J52+K52)/2*K53/12 -> 1.3333333 | ... AM54: =(AL52+AM52)/2*AM53/12 -> 2 | AO54: =SUM(D54:O54) -> 14 | AP54: =SUM(P54:AA54) -> 24 | AQ54: =SUM(AB54:AM54) -> 24
A55: операционные расходы на 1 кошелек | B55: сом
A56: операционные расходы (provider) | B56: тыс сом | D56: =D55*D50 -> 0 | E56: =E55*E50 -> 0 | F56: =F55*F50 -> 0 | G56: =G55*G50 -> 0 | H56: =H55*H50 -> 0 | I56: =I55*I50 -> 0 | J56: =J55*J50 -> 0 | K56: =K55*K50 -> 0 | ... AM56: =AM55*AM50 -> 0 | AO56: =SUM(D56:O56) -> 0 | AP56: =SUM(P56:AA56) -> 0 | AQ56: =SUM(AB56:AM56) -> 0
A57: начисление расходов в ФЗД | B57: тыс сом | E57: =-0.2%*D52/12 -> -0.033333333 | F57: =-0.2%*(D52+E52)/2/12 -> -0.033333333 | G57: =-0.2%*(E52+F52)/2/12 -> -0.033333333 | H57: =-0.2%*(F52+G52)/2/12 -> -0.041666667 | I57: =-0.2%*(G52+H52)/2/12 -> -0.05 | J57: =-0.2%*(H52+I52)/2/12 -> -0.058333333 | K57: =-0.2%*(I52+J52)/2/12 -> -0.066666667 | L57: =-0.2%*(J52+K52)/2/12 -> -0.066666667 | M57: =-0.2%*(K52+L52)/2/12 -> -0.075 | ... AM57: =-0.2%*(AK52+AL52)/2/12 -> -0.1 | AO57: =SUM(D57:O57) -> -0.625 | AP57: =SUM(P57:AA57) -> -1.1916667 | AQ57: =SUM(AB57:AM57) -> -1.2
A58: операционные расходы (постоянные) | B58: тыс сом | D58: =-('OPEX+CAPEX'!E69+'OPEX+CAPEX'!E72) -> -107.14286 | E58: =-('OPEX+CAPEX'!F69+'OPEX+CAPEX'!F72) -> -107.14286 | F58: =-('OPEX+CAPEX'!G69+'OPEX+CAPEX'!G72) -> -107.14286 | G58: =-('OPEX+CAPEX'!H69+'OPEX+CAPEX'!H72) -> -107.14286 | H58: =-('OPEX+CAPEX'!I69+'OPEX+CAPEX'!I72) -> -107.14286 | I58: =-('OPEX+CAPEX'!J69+'OPEX+CAPEX'!J72) -> -107.14286 | J58: =-('OPEX+CAPEX'!K69+'OPEX+CAPEX'!K72) -> -107.14286 | K58: =-('OPEX+CAPEX'!L69+'OPEX+CAPEX'!L72) -> -107.14286 | ... AM58: =-('OPEX+CAPEX'!AN69+'OPEX+CAPEX'!AN72) -> -156.72619 | AO58: =SUM(D58:O58) -> -1484.0476 | AP58: =SUM(P58:AA58) -> -1880.7143 | AQ58: =SUM(AB58:AM58) -> -1880.7143
A59: прибыль | B59: тыс сом | D59: =D56+D54+D58+D57 -> -106.80952 | E59: =E56+E54+E58+E57 -> -106.50952 | F59: =F56+F54+F58+F57 -> -106.50952 | G59: =G56+G54+G58+G57 -> -106.34286 | H59: =H56+H54+H58+H57 -> -106.18452 | I59: =I56+I54+I58+I57 -> -106.02619 | J59: =J56+J54+J58+J57 -> -105.86786 | K59: =K56+K54+K58+K57 -> -105.87619 | ... AM59: =AM56+AM54+AM58+AM57 -> -154.82619 | AO59: =SUM(D59:O59) -> -1470.6726 | AP59: =SUM(P59:AA59) -> -1857.906 | AQ59: =SUM(AB59:AM59) -> -1857.9143
A61: Расчетный счет (ФЛ)
A62: количество партнеров | B62: шт | D62: ='0'!D17 -> 1 | E62: ='0'!E17 -> 1 | F62: ='0'!F17 -> 2 | G62: ='0'!G17 -> 2 | H62: ='0'!H17 -> 3 | I62: ='0'!I17 -> 3 | J62: ='0'!J17 -> 4 | K62: ='0'!K17 -> 5 | ... AM62: ='0'!AM17 -> 8 | AO62: =O62 -> 8 | AP62: =AA62 -> 8 | AQ62: =AM62 -> 8
A63: среднее количество счетов на 1 партнера | B63: шт | D63: 40 | E63: 40 | F63: 40 | G63: 40 | H63: 40 | I63: 40 | J63: 40 | K63: 40 | L63: 40 | M63: 40 | N63: 40 | O63: 40 | P63: 40 | Q63: 40 | R63: 40 | S63: 40 | T63: 40 | U63: 40 | V63: 40 | W63: 40 | X63: 40 | Y63: 40 | Z63: 40 | AA63: 40 | AB63: 40 | AC63: 40 | AD63: 40 | AE63: 40 | AF63: 40 | AG63: 40 | AH63: 40 | AI63: 40 | AJ63: 40 | AK63: 40 | AL63: 40 | AM63: 40 | AO63: =AVERAGE(D63:O63) -> 40 | AP63: =AVERAGE(P63:AA63) -> 40 | AQ63: =AVERAGE(AB63:AM63) -> 40
A64: количество счетов | B64: шт | D64: =D62*D63 -> 40 | E64: =E62*E63 -> 40 | F64: =F62*F63 -> 80 | G64: =G62*G63 -> 80 | H64: =H62*H63 -> 120 | I64: =I62*I63 -> 120 | J64: =J62*J63 -> 160 | K64: =K62*K63 -> 200 | ... AM64: =AM62*AM63 -> 320 | AO64: =SUM(D64:O64) -> 2000 | AP64: =SUM(P64:AA64) -> 3840 | AQ64: =SUM(AB64:AM64) -> 3840
A65: ср. остаток на 1 счете | B65: тыс. сом | D65: 5 | E65: 5 | F65: 5 | G65: 5 | H65: 5 | I65: 5 | J65: 5 | K65: 5 | L65: 5 | M65: 5 | N65: 5 | O65: 5 | P65: 5 | Q65: 5 | R65: 5 | S65: 5 | T65: 5 | U65: 5 | V65: 5 | W65: 5 | X65: 5 | Y65: 5 | Z65: 5 | AA65: 5 | AB65: 5 | AC65: 5 | AD65: 5 | AE65: 5 | AF65: 5 | AG65: 5 | AH65: 5 | AI65: 5 | AJ65: 5 | AK65: 5 | AL65: 5 | AM65: 5 | AO65: =AVERAGE(D65:O65) -> 5 | AP65: =AVERAGE(P65:AA65) -> 5 | AQ65: =AVERAGE(AB65:AM65) -> 5
A66: портфель | B66: тыс. сом | D66: =D64*D65 -> 200 | E66: =E64*E65 -> 200 | F66: =F64*F65 -> 400 | G66: =G64*G65 -> 400 | H66: =H64*H65 -> 600 | I66: =I64*I65 -> 600 | J66: =J64*J65 -> 800 | K66: =K64*K65 -> 1000 | ... AM66: =AM64*AM65 -> 1600 | AO66: =O66 -> 1600 | AP66: =AA66 -> 1600 | AQ66: =AM66 -> 1600
A67: ср. % ставка фондирования | B67: % | D67: 0.04 | E67: 0.04 | F67: 0.04 | G67: 0.04 | H67: 0.04 | I67: 0.04 | J67: 0.04 | K67: 0.04 | L67: 0.04 | M67: 0.04 | N67: 0.04 | O67: 0.04 | P67: 0.04 | Q67: 0.04 | R67: 0.04 | S67: 0.04 | T67: 0.04 | U67: 0.04 | V67: 0.04 | W67: 0.04 | X67: 0.04 | Y67: 0.04 | Z67: 0.04 | AA67: 0.04 | AB67: 0.04 | AC67: 0.04 | AD67: 0.04 | AE67: 0.04 | AF67: 0.04 | AG67: 0.04 | AH67: 0.04 | AI67: 0.04 | AJ67: 0.04 | AK67: 0.04 | AL67: 0.04 | AM67: 0.04 | AO67: =AVERAGE(D67:O67) -> 0.04 | AP67: =AVERAGE(P67:AA67) -> 0.04 | AQ67: =AVERAGE(AB67:AM67) -> 0.04
A68: трансфертный доход | B68: тыс. сом | D68: =(C66+D66)/2*D67/12 -> 0.33333333 | E68: =(D66+E66)/2*E67/12 -> 0.66666667 | F68: =(E66+F66)/2*F67/12 -> 1 | G68: =(F66+G66)/2*G67/12 -> 1.3333333 | H68: =(G66+H66)/2*H67/12 -> 1.6666667 | I68: =(H66+I66)/2*I67/12 -> 2 | J68: =(I66+J66)/2*J67/12 -> 2.3333333 | K68: =(J66+K66)/2*K67/12 -> 3 | ... AM68: =(AL66+AM66)/2*AM67/12 -> 5.3333333 | AO68: =SUM(D68:O68) -> 30.666667 | AP68: =SUM(P68:AA68) -> 64 | AQ68: =SUM(AB68:AM68) -> 64
A69: ср.комиссия за ослуживание 1 расчетного счета | B69: тыс. сом | D69: 0 | E69: 0 | F69: 0 | G69: 0 | H69: 0 | I69: 0 | J69: 0 | K69: 0 | L69: 0 | M69: 0 | N69: 0 | O69: 0 | P69: 0 | Q69: 0 | R69: 0 | S69: 0 | T69: 0 | U69: 0 | V69: 0 | W69: 0 | X69: 0 | Y69: 0 | Z69: 0 | AA69: 0 | AB69: 0 | AC69: 0 | AD69: 0 | AE69: 0 | AF69: 0 | AG69: 0 | AH69: 0 | AI69: 0 | AJ69: 0 | AK69: 0 | AL69: 0 | AM69: 0 | AO69: =AVERAGE(D69:O69) -> 0 | AP69: =AVERAGE(P69:AA69) -> 0 | AQ69: =AVERAGE(AB69:AM69) -> 0
A70: комиссионный доход | B70: тыс сом | D70: =D69*D64*(1-2/102) -> 0 | E70: =E69*E64*(1-2/102) -> 0 | F70: =F69*F64*(1-2/102) -> 0 | G70: =G69*G64*(1-2/102) -> 0 | H70: =H69*H64*(1-2/102) -> 0 | I70: =I69*I64*(1-2/102) -> 0 | J70: =J69*J64*(1-2/102) -> 0 | K70: =K69*K64*(1-2/102) -> 0 | ... AM70: =AM69*AM64*(1-2/102) -> 0 | AO70: =SUM(D70:O70) -> 0 | AP70: =SUM(P70:AA70) -> 0 | AQ70: =SUM(AB70:AM70) -> 0
A71: чистый операционный доход | B71: тыс сом | D71: =D68+D70 -> 0.33333333 | E71: =E68+E70 -> 0.66666667 | F71: =F68+F70 -> 1 | G71: =G68+G70 -> 1.3333333 | H71: =H68+H70 -> 1.6666667 | I71: =I68+I70 -> 2 | J71: =J68+J70 -> 2.3333333 | K71: =K68+K70 -> 3 | ... AM71: =AM68+AM70 -> 5.3333333 | AO71: =SUM(D71:O71) -> 30.666667 | AP71: =SUM(P71:AA71) -> 64 | AQ71: =SUM(AB71:AM71) -> 64
A72: начисление расходов в ФЗД | B72: тыс сом | E72: =-0.2%*D66/12 -> -0.033333333 | F72: =-0.2%*(D66+E66)/2/12 -> -0.033333333 | G72: =-0.2%*(E66+F66)/2/12 -> -0.05 | H72: =-0.2%*(F66+G66)/2/12 -> -0.066666667 | I72: =-0.2%*(G66+H66)/2/12 -> -0.083333333 | J72: =-0.2%*(H66+I66)/2/12 -> -0.1 | K72: =-0.2%*(I66+J66)/2/12 -> -0.11666667 | L72: =-0.2%*(J66+K66)/2/12 -> -0.15 | M72: =-0.2%*(K66+L66)/2/12 -> -0.18333333 | ... AM72: =-0.2%*(AK66+AL66)/2/12 -> -0.26666667 | AO72: =SUM(D72:O72) -> -1.2833333 | AP72: =SUM(P72:AA72) -> -3.2 | AQ72: =SUM(AB72:AM72) -> -3.2
A73: операционные расходы (постоянные) | B73: тыс сом | D73: =-('OPEX+CAPEX'!E75+'OPEX+CAPEX'!E82+'OPEX+CAPEX'!E83) -> -100.09111 | E73: =-('OPEX+CAPEX'!F75+'OPEX+CAPEX'!F82+'OPEX+CAPEX'!F83) -> -100.09111 | F73: =-('OPEX+CAPEX'!G75+'OPEX+CAPEX'!G82+'OPEX+CAPEX'!G83) -> -100.18222 | G73: =-('OPEX+CAPEX'!H75+'OPEX+CAPEX'!H82+'OPEX+CAPEX'!H83) -> -100.18222 | H73: =-('OPEX+CAPEX'!I75+'OPEX+CAPEX'!I82+'OPEX+CAPEX'!I83) -> -125.065 | I73: =-('OPEX+CAPEX'!J75+'OPEX+CAPEX'!J82+'OPEX+CAPEX'!J83) -> -125.065 | J73: =-('OPEX+CAPEX'!K75+'OPEX+CAPEX'!K82+'OPEX+CAPEX'!K83) -> -125.15611 | K73: =-('OPEX+CAPEX'!L75+'OPEX+CAPEX'!L82+'OPEX+CAPEX'!L83) -> -125.24722 | ... AM73: =-('OPEX+CAPEX'!AN75+'OPEX+CAPEX'!AN82+'OPEX+CAPEX'!AN83) -> -139.68722 | AO73: =SUM(D73:O73) -> -1402.8889 | AP73: =SUM(P73:AA73) -> -1647.9133 | AQ73: =SUM(AB73:AM73) -> -1676.2467
A74: прибыль | B74: тыс сом | D74: =D71+D73+D72 -> -99.757778 | E74: =E71+E73+E72 -> -99.457778 | F74: =F71+F73+F72 -> -99.215556 | G74: =G71+G73+G72 -> -98.898889 | H74: =H71+H73+H72 -> -123.465 | I74: =I71+I73+I72 -> -123.14833 | J74: =J71+J73+J72 -> -122.92278 | K74: =K71+K73+K72 -> -122.36389 | ... AM74: =AM71+AM73+AM72 -> -134.62056 | AO74: =SUM(D74:O74) -> -1373.5056 | AP74: =SUM(P74:AA74) -> -1587.1133 | AQ74: =SUM(AB74:AM74) -> -1615.4467
A76: Виртуальные карты
A77: количество партнеров | B77: шт | D77: ='0'!D18 -> 1 | E77: ='0'!E18 -> 2 | F77: ='0'!F18 -> 2 | G77: ='0'!G18 -> 2 | H77: ='0'!H18 -> 2 | I77: ='0'!I18 -> 3 | J77: ='0'!J18 -> 3 | K77: ='0'!K18 -> 3 | ... AM77: ='0'!AM18 -> 4 | AO77: =O77 -> 4 | AP77: =AA77 -> 4 | AQ77: =AM77 -> 4
A78: среднее количество вирт.карт на 1 партнера | B78: шт | D78: 30 | E78: 30 | F78: 30 | G78: 30 | H78: 30 | I78: 30 | J78: 30 | K78: 30 | L78: 30 | M78: 30 | N78: 30 | O78: 30 | P78: 30 | Q78: 30 | R78: 30 | S78: 30 | T78: 30 | U78: 30 | V78: 30 | W78: 30 | X78: 30 | Y78: 30 | Z78: 30 | AA78: 30 | AB78: 30 | AC78: 30 | AD78: 30 | AE78: 30 | AF78: 30 | AG78: 30 | AH78: 30 | AI78: 30 | AJ78: 30 | AK78: 30 | AL78: 30 | AM78: 30 | AO78: =AVERAGE(D78:O78) -> 30 | AP78: =AVERAGE(P78:AA78) -> 30 | AQ78: =AVERAGE(AB78:AM78) -> 30
A79: количество вирт.карт | B79: шт | D79: =D77*D78 -> 30 | E79: =E77*E78 -> 60 | F79: =F77*F78 -> 60 | G79: =G77*G78 -> 60 | H79: =H77*H78 -> 60 | I79: =I77*I78 -> 90 | J79: =J77*J78 -> 90 | K79: =K77*K78 -> 90 | ... AM79: =AM77*AM78 -> 120 | AO79: =SUM(D79:O79) -> 960 | AP79: =SUM(P79:AA79) -> 1440 | AQ79: =SUM(AB79:AM79) -> 1440
A80: ср. остаток на 1 карте | B80: тыс. сом | D80: 5 | E80: 5 | F80: 5 | G80: 5 | H80: 5 | I80: 5 | J80: 5 | K80: 5 | L80: 5 | M80: 5 | N80: 5 | O80: 5 | P80: 5 | Q80: 5 | R80: 5 | S80: 5 | T80: 5 | U80: 5 | V80: 5 | W80: 5 | X80: 5 | Y80: 5 | Z80: 5 | AA80: 5 | AB80: 5 | AC80: 5 | AD80: 5 | AE80: 5 | AF80: 5 | AG80: 5 | AH80: 5 | AI80: 5 | AJ80: 5 | AK80: 5 | AL80: 5 | AM80: 5 | AO80: =AVERAGE(D80:O80) -> 5 | AP80: =AVERAGE(P80:AA80) -> 5 | AQ80: =AVERAGE(AB80:AM80) -> 5
A81: портфель | B81: тыс. сом | D81: =D79*D80 -> 150 | E81: =E79*E80 -> 300 | F81: =F79*F80 -> 300 | G81: =G79*G80 -> 300 | H81: =H79*H80 -> 300 | I81: =I79*I80 -> 450 | J81: =J79*J80 -> 450 | K81: =K79*K80 -> 450 | ... AM81: =AM79*AM80 -> 600 | AO81: =O81 -> 600 | AP81: =AA81 -> 600 | AQ81: =AM81 -> 600
A82: ср. Дт оборот по 1 карте | B82: тыс. сом | D82: 10 | E82: 10 | F82: 10 | G82: 10 | H82: 10 | I82: 10 | J82: 10 | K82: 10 | L82: 10 | M82: 10 | N82: 10 | O82: 10 | P82: 10 | Q82: 10 | R82: 10 | S82: 10 | T82: 10 | U82: 10 | V82: 10 | W82: 10 | X82: 10 | Y82: 10 | Z82: 10 | AA82: 10 | AB82: 10 | AC82: 10 | AD82: 10 | AE82: 10 | AF82: 10 | AG82: 10 | AH82: 10 | AI82: 10 | AJ82: 10 | AK82: 10 | AL82: 10 | AM82: 10 | AO82: =AVERAGE(D82:O82) -> 10 | AP82: =AVERAGE(P82:AA82) -> 10 | AQ82: =AVERAGE(AB82:AM82) -> 10
A83: ср.% cashback | B83: % | D83: 0.02 | E83: 0.02 | F83: 0.02 | G83: 0.02 | H83: 0.02 | I83: 0.02 | J83: 0.02 | K83: 0.02 | L83: 0.02 | M83: 0.02 | N83: 0.02 | O83: 0.02 | P83: 0.02 | Q83: 0.02 | R83: 0.02 | S83: 0.02 | T83: 0.02 | U83: 0.02 | V83: 0.02 | W83: 0.02 | X83: 0.02 | Y83: 0.02 | Z83: 0.02 | AA83: 0.02 | AB83: 0.02 | AC83: 0.02 | AD83: 0.02 | AE83: 0.02 | AF83: 0.02 | AG83: 0.02 | AH83: 0.02 | AI83: 0.02 | AJ83: 0.02 | AK83: 0.02 | AL83: 0.02 | AM83: 0.02
A84: ср. % ставка фондирования | B84: % | D84: 0.04 | E84: 0.04 | F84: 0.04 | G84: 0.04 | H84: 0.04 | I84: 0.04 | J84: 0.04 | K84: 0.04 | L84: 0.04 | M84: 0.04 | N84: 0.04 | O84: 0.04 | P84: 0.04 | Q84: 0.04 | R84: 0.04 | S84: 0.04 | T84: 0.04 | U84: 0.04 | V84: 0.04 | W84: 0.04 | X84: 0.04 | Y84: 0.04 | Z84: 0.04 | AA84: 0.04 | AB84: 0.04 | AC84: 0.04 | AD84: 0.04 | AE84: 0.04 | AF84: 0.04 | AG84: 0.04 | AH84: 0.04 | AI84: 0.04 | AJ84: 0.04 | AK84: 0.04 | AL84: 0.04 | AM84: 0.04 | AO84: =AVERAGE(D84:O84) -> 0.04 | AP84: =AVERAGE(P84:AA84) -> 0.04 | AQ84: =AVERAGE(AB84:AM84) -> 0.04
A85: трансфертный доход | B85: тыс. сом | D85: =(C81+D81)/2*D84/12 -> 0.25 | E85: =(D81+E81)/2*E84/12 -> 0.75 | F85: =(E81+F81)/2*F84/12 -> 1 | G85: =(F81+G81)/2*G84/12 -> 1 | H85: =(G81+H81)/2*H84/12 -> 1 | I85: =(H81+I81)/2*I84/12 -> 1.25 | J85: =(I81+J81)/2*J84/12 -> 1.5 | K85: =(J81+K81)/2*K84/12 -> 1.5 | ... AM85: =(AL81+AM81)/2*AM84/12 -> 2 | AO85: =SUM(D85:O85) -> 15 | AP85: =SUM(P85:AA85) -> 24 | AQ85: =SUM(AB85:AM85) -> 24
A86: ср.комиссионный доход на 1 карту | B86: тыс. сом | D86: =480/20000 -> 0.024 | E86: =480/20000 -> 0.024 | F86: =480/20000 -> 0.024 | G86: =480/20000 -> 0.024 | H86: =480/20000 -> 0.024 | I86: =480/20000 -> 0.024 | J86: =480/20000 -> 0.024 | K86: =480/20000 -> 0.024 | ... AM86: =480/20000 -> 0.024
A87: комиссионный доход | B87: тыс сом | D87: =D86*D79*(1-2/102) -> 0.70588235 | E87: =E86*E79*(1-2/102) -> 1.4117647 | F87: =F86*F79*(1-2/102) -> 1.4117647 | G87: =G86*G79*(1-2/102) -> 1.4117647 | H87: =H86*H79*(1-2/102) -> 1.4117647 | I87: =I86*I79*(1-2/102) -> 2.1176471 | J87: =J86*J79*(1-2/102) -> 2.1176471 | K87: =K86*K79*(1-2/102) -> 2.1176471 | ... AM87: =AM86*AM79*(1-2/102) -> 2.8235294 | AO87: =SUM(D87:O87) -> 22.588235 | AP87: =SUM(P87:AA87) -> 33.882353 | AQ87: =SUM(AB87:AM87) -> 33.882353
A88: cashback | B88: тыс сом | D88: =-D82*D79*D83 -> -6 | E88: =-(E82*E79+D79*D82)/2*E83 -> -9 | F88: =-(F82*F79+E79*E82)/2*F83 -> -12 | G88: =-(G82*G79+F79*F82)/2*G83 -> -12 | H88: =-(H82*H79+G79*G82)/2*H83 -> -12 | I88: =-(I82*I79+H79*H82)/2*I83 -> -15 | J88: =-(J82*J79+I79*I82)/2*J83 -> -18 | K88: =-(K82*K79+J79*J82)/2*K83 -> -18 | L88: =-(L82*L79+K79*K82)/2*L83 -> -18 | ... AM88: =-(AM82*AM79+AL79*AL82)/2*AM83 -> -24 | AO88: =SUM(D88:O88) -> -183 | AP88: =SUM(P88:AA88) -> -288 | AQ88: =SUM(AB88:AM88) -> -288
A89: ср.операционный расход на 1 карту | B89: тыс. сом | D89: =-0.02 -> -0.02 | E89: =-0.02 -> -0.02 | F89: =-0.02 -> -0.02 | G89: =-0.02 -> -0.02 | H89: =-0.02 -> -0.02 | I89: =-0.02 -> -0.02 | J89: =-0.02 -> -0.02 | K89: =-0.02 -> -0.02 | ... AM89: =-0.02 -> -0.02
A90: операционные расходы (переменные) | B90: тыс сом | D90: =D89*D79 -> -0.6 | E90: =E89*E79 -> -1.2 | F90: =F89*F79 -> -1.2 | G90: =G89*G79 -> -1.2 | H90: =H89*H79 -> -1.2 | I90: =I89*I79 -> -1.8 | J90: =J89*J79 -> -1.8 | K90: =K89*K79 -> -1.8 | ... AM90: =AM89*AM79 -> -2.4 | AO90: =SUM(D90:O90) -> -19.2 | AP90: =SUM(P90:AA90) -> -28.8 | AQ90: =SUM(AB90:AM90) -> -28.8
A91: начисление расходов в ФЗД | B91: тыс сом | E91: =-0.2%*D81/12 -> -0.025 | F91: =-0.2%*(D81+E81)/2/12 -> -0.0375 | G91: =-0.2%*(E81+F81)/2/12 -> -0.05 | H91: =-0.2%*(F81+G81)/2/12 -> -0.05 | I91: =-0.2%*(G81+H81)/2/12 -> -0.05 | J91: =-0.2%*(H81+I81)/2/12 -> -0.0625 | K91: =-0.2%*(I81+J81)/2/12 -> -0.075 | L91: =-0.2%*(J81+K81)/2/12 -> -0.075 | M91: =-0.2%*(K81+L81)/2/12 -> -0.075 | ... AM91: =-0.2%*(AK81+AL81)/2/12 -> -0.1 | AO91: =SUM(D91:O91) -> -0.6625 | AP91: =SUM(P91:AA91) -> -1.2 | AQ91: =SUM(AB91:AM91) -> -1.2
A92: операционные расходы (постоянные) | B92: тыс сом | D92: =-'OPEX+CAPEX'!E87 -> -107.21119 | E92: =-'OPEX+CAPEX'!F87 -> -107.27952 | F92: =-'OPEX+CAPEX'!G87 -> -107.27952 | G92: =-'OPEX+CAPEX'!H87 -> -107.27952 | H92: =-'OPEX+CAPEX'!I87 -> -107.27952 | I92: =-'OPEX+CAPEX'!J87 -> -107.34786 | J92: =-'OPEX+CAPEX'!K87 -> -107.34786 | K92: =-'OPEX+CAPEX'!L87 -> -107.34786 | ... AM92: =-'OPEX+CAPEX'!AN87 -> -107.41619 | AO92: =SUM(D92:O92) -> -1287.901 | AP92: =SUM(P92:AA92) -> -1288.9943 | AQ92: =SUM(AB92:AM92) -> -1288.9943
A93: прибыль | B93: тыс сом | D93: =D85+D87+D88+D90+D92+D91 -> -112.85531 | E93: =E85+E87+E88+E90+E92+E91 -> -115.34276 | F93: =F85+F87+F88+F90+F92+F91 -> -118.10526 | G93: =G85+G87+G88+G90+G92+G91 -> -118.11776 | H93: =H85+H87+H88+H90+H92+H91 -> -118.11776 | I93: =I85+I87+I88+I90+I92+I91 -> -120.83021 | J93: =J85+J87+J88+J90+J92+J91 -> -123.59271 | K93: =K85+K87+K88+K90+K92+K91 -> -123.60521 | ... AM93: =AM85+AM87+AM88+AM90+AM92+AM91 -> -129.09266 | AO93: =SUM(D93:O93) -> -1453.1752 | AP93: =SUM(P93:AA93) -> -1549.1119 | AQ93: =SUM(AB93:AM93) -> -1549.1119
A95: Онлайн конвертация
A96: количество партнеров | B96: шт | D96: ='0'!D19 -> 1 | E96: ='0'!E19 -> 1 | F96: ='0'!F19 -> 1 | G96: ='0'!G19 -> 2 | H96: ='0'!H19 -> 2 | I96: ='0'!I19 -> 2 | J96: ='0'!J19 -> 3 | K96: ='0'!K19 -> 3 | ... AM96: ='0'!AM19 -> 6 | AO96: =O96 -> 6 | AP96: =AA96 -> 6 | AQ96: =AM96 -> 6
A97: среднее объем конвертаций на 1 партнера | B97: тыс сом | D97: 10000 | E97: 10000 | F97: 10000 | G97: 10000 | H97: 10000 | I97: 10000 | J97: 10000 | K97: 10000 | L97: 10000 | M97: 10000 | N97: 10000 | O97: 10000 | P97: 10000 | Q97: 10000 | R97: 10000 | S97: 10000 | T97: 10000 | U97: 10000 | V97: 10000 | W97: 10000 | X97: 10000 | Y97: 10000 | Z97: 10000 | AA97: 10000 | AB97: 10000 | AC97: 10000 | AD97: 10000 | AE97: 10000 | AF97: 10000 | AG97: 10000 | AH97: 10000 | AI97: 10000 | AJ97: 10000 | AK97: 10000 | AL97: 10000 | AM97: 10000 | AO97: =AVERAGE(D97:O97) -> 10000 | AP97: =AVERAGE(P97:AA97) -> 10000 | AQ97: =AVERAGE(AB97:AM97) -> 10000
A98: объем конвертации | B98: тыс сом | D98: =D97*D96 -> 10000 | E98: =E97*E96 -> 10000 | F98: =F97*F96 -> 10000 | G98: =G97*G96 -> 20000 | H98: =H97*H96 -> 20000 | I98: =I97*I96 -> 20000 | J98: =J97*J96 -> 30000 | K98: =K97*K96 -> 30000 | ... AM98: =AM97*AM96 -> 60000 | AO98: =SUM(D98:O98) -> 350000 | AP98: =SUM(P98:AA98) -> 720000 | AQ98: =SUM(AB98:AM98) -> 720000
A99: % маржи | B99: % | D99: 0.0017 | E99: 0.0017 | F99: 0.0017 | G99: 0.0017 | H99: 0.0017 | I99: 0.0017 | J99: 0.0017 | K99: 0.0017 | L99: 0.0017 | M99: 0.0017 | N99: 0.0017 | O99: 0.0017 | P99: 0.0017 | Q99: 0.0017 | R99: 0.0017 | S99: 0.0017 | T99: 0.0017 | U99: 0.0017 | V99: 0.0017 | W99: 0.0017 | X99: 0.0017 | Y99: 0.0017 | Z99: 0.0017 | AA99: 0.0017 | AB99: 0.0017 | AC99: 0.0017 | AD99: 0.0017 | AE99: 0.0017 | AF99: 0.0017 | AG99: 0.0017 | AH99: 0.0017 | AI99: 0.0017 | AJ99: 0.0017 | AK99: 0.0017 | AL99: 0.0017 | AM99: 0.0017 | AO99: =AVERAGE(D99:O99) -> 0.0017 | AP99: =AVERAGE(P99:AA99) -> 0.0017 | AQ99: =AVERAGE(AB99:AM99) -> 0.0017
A100: доход от конвертации | B100: тыс сом | D100: =D98*D99 -> 17 | E100: =E98*E99 -> 17 | F100: =F98*F99 -> 17 | G100: =G98*G99 -> 34 | H100: =H98*H99 -> 34 | I100: =I98*I99 -> 34 | J100: =J98*J99 -> 51 | K100: =K98*K99 -> 51 | ... AM100: =AM98*AM99 -> 102 | AO100: =SUM(D100:O100) -> 595 | AP100: =SUM(P100:AA100) -> 1224 | AQ100: =SUM(AB100:AM100) -> 1224
A101: % партнеру | B101: % | D101: 0.3 | E101: 0.3 | F101: 0.3 | G101: 0.3 | H101: 0.3 | I101: 0.3 | J101: 0.3 | K101: 0.3 | L101: 0.3 | M101: 0.3 | N101: 0.3 | O101: 0.3 | P101: 0.3 | Q101: 0.3 | R101: 0.3 | S101: 0.3 | T101: 0.3 | U101: 0.3 | V101: 0.3 | W101: 0.3 | X101: 0.3 | Y101: 0.3 | Z101: 0.3 | AA101: 0.3 | AB101: 0.3 | AC101: 0.3 | AD101: 0.3 | AE101: 0.3 | AF101: 0.3 | AG101: 0.3 | AH101: 0.3 | AI101: 0.3 | AJ101: 0.3 | AK101: 0.3 | AL101: 0.3 | AM101: 0.3 | AO101: =AVERAGE(D101:O101) -> 0.3 | AP101: =AVERAGE(P101:AA101) -> 0.3 | AQ101: =AVERAGE(AB101:AM101) -> 0.3
A102: расход на партнера | B102: тыс сом | D102: =-D100*D101 -> -5.1 | E102: =-E100*E101 -> -5.1 | F102: =-F100*F101 -> -5.1 | G102: =-G100*G101 -> -10.2 | H102: =-H100*H101 -> -10.2 | I102: =-I100*I101 -> -10.2 | J102: =-J100*J101 -> -15.3 | K102: =-K100*K101 -> -15.3 | ... AM102: =-AM100*AM101 -> -30.6 | AO102: =SUM(D102:O102) -> -178.5 | AP102: =SUM(P102:AA102) -> -367.2 | AQ102: =SUM(AB102:AM102) -> -367.2
A103: операционные расходы (постоянные) | B103: тыс сом | D103: =-'OPEX+CAPEX'!E95 -> -107.14286 | E103: =-'OPEX+CAPEX'!F95 -> -107.14286 | F103: =-'OPEX+CAPEX'!G95 -> -107.14286 | G103: =-'OPEX+CAPEX'!H95 -> -107.14286 | H103: =-'OPEX+CAPEX'!I95 -> -107.14286 | I103: =-'OPEX+CAPEX'!J95 -> -107.14286 | J103: =-'OPEX+CAPEX'!K95 -> -107.14286 | K103: =-'OPEX+CAPEX'!L95 -> -107.14286 | ... AM103: =-'OPEX+CAPEX'!AN95 -> -107.14286 | AO103: =SUM(D103:O103) -> -1285.7143 | AP103: =SUM(P103:AA103) -> -1285.7143 | AQ103: =SUM(AB103:AM103) -> -1285.7143
A104: прибыль | B104: тыс сом | D104: =D100+D102+D103 -> -95.242857 | E104: =E100+E102+E103 -> -95.242857 | F104: =F100+F102+F103 -> -95.242857 | G104: =G100+G102+G103 -> -83.342857 | H104: =H100+H102+H103 -> -83.342857 | I104: =I100+I102+I103 -> -83.342857 | J104: =J100+J102+J103 -> -71.442857 | K104: =K100+K102+K103 -> -71.442857 | ... AM104: =AM100+AM102+AM103 -> -35.742857 | AO104: =SUM(D104:O104) -> -869.21429 | AP104: =SUM(P104:AA104) -> -428.91429 | AQ104: =SUM(AB104:AM104) -> -428.91429
A106: Онлайн переводы
A107: количество партнеров | B107: шт | D107: ='0'!D20 -> 23 | E107: ='0'!E20 -> 23 | F107: ='0'!F20 -> 24 | G107: ='0'!G20 -> 24 | H107: ='0'!H20 -> 25 | I107: ='0'!I20 -> 25 | J107: ='0'!J20 -> 27 | K107: ='0'!K20 -> 28 | ... AM107: ='0'!AM20 -> 30 | AO107: =O107 -> 30 | AP107: =AA107 -> 30 | AQ107: =AM107 -> 30
A108: среднее объем переводов на 1 партнера | B108: тыс сом | D108: 100000 | E108: 100000 | F108: 100000 | G108: 100000 | H108: 100000 | I108: 100000 | J108: 100000 | K108: 100000 | L108: 100000 | M108: 100000 | N108: 100000 | O108: 100000 | P108: 100000 | Q108: 100000 | R108: 100000 | S108: 100000 | T108: 100000 | U108: 100000 | V108: 100000 | W108: 100000 | X108: 100000 | Y108: 100000 | Z108: 100000 | AA108: 100000 | AB108: 100000 | AC108: 100000 | AD108: 100000 | AE108: 100000 | AF108: 100000 | AG108: 100000 | AH108: 100000 | AI108: 100000 | AJ108: 100000 | AK108: 100000 | AL108: 100000 | AM108: 100000 | AO108: =AVERAGE(D108:O108) -> 100000 | AP108: =AVERAGE(P108:AA108) -> 100000 | AQ108: =AVERAGE(AB108:AM108) -> 100000
...

Sheet BS
B1: Баланс BaaS
B2: (тыс. сом)
C4: 46023 | D4: =C4+31 -> 46054 | E4: =D4+31 -> 46085 | F4: =E4+31 -> 46116 | G4: =F4+31 -> 46147 | H4: =G4+31 -> 46178 | I4: =H4+31 -> 46209 | J4: =I4+31 -> 46240 | K4: =J4+31 -> 46271 | ... AL4: =AK4+31 -> 47108 | AN4: =YEAR(N4) -> 2026 | AO4: =YEAR(Z4) -> 2027 | AP4: =YEAR(AL4) -> 2028
C5: m1 | D5: m2 | E5: m3 | F5: m4 | G5: m5 | H5: m6 | I5: m7 | J5: m8 | K5: m9 | L5: m10 | M5: m11 | N5: m12 | O5: m13 | P5: m14 | Q5: m15 | R5: m16 | S5: m17 | T5: m18 | U5: m19 | V5: m20 | W5: m21 | X5: m22 | Y5: m23 | Z5: m24 | AA5: m25 | AB5: m26 | AC5: m27 | AD5: m28 | AE5: m29 | AF5: m30 | AG5: m31 | AH5: m32 | AI5: m33 | AJ5: m34 | AK5: m35 | AL5: m36 | AN5: Y1 | AO5: Y2 | AP5: Y3
B6: АКТИВЫ
B7: Кредиты клиентам | C7: =SUM(C8:C11) -> 25950 | D7: =SUM(D8:D11) -> 50755 | E7: =SUM(E8:E11) -> 74712.917 | F7: =SUM(F8:F11) -> 98030.174 | G7: =SUM(G8:G11) -> 120851.55 | H7: =SUM(H8:H11) -> 143280.12 | I7: =SUM(I8:I11) -> 163660.64 | J7: =SUM(J8:J11) -> 185700.1 | ... AL7: =SUM(AL8:AL11) -> 553031.23 | AN7: =N7 -> 287227.82 | AO7: =Z7 -> 479219.46 | AP7: =AL7 -> 553031.23
B8: Потребительский кредит | C8: =BaaS.1!D20 -> 22500 | D8: =BaaS.1!E20 -> 44625 | E8: =BaaS.1!F20 -> 66406.25 | F8: =BaaS.1!G20 -> 87872.396 | G8: =BaaS.1!H20 -> 109049.7 | H8: =BaaS.1!I20 -> 129962.22 | I8: =BaaS.1!J20 -> 149132.04 | J8: =BaaS.1!K20 -> 169704.37 | ... AL8: =BaaS.1!AM20 -> 505781.37 | AN8: =N8 -> 263822.61 | AO8: =Z8 -> 442786.77 | AP8: =AL8 -> 505781.37
B9: Рассрочка (BNPL) | C9: =BaaS.1!D44 -> 1500 | D9: =BaaS.1!E44 -> 2600 | E9: =BaaS.1!F44 -> 3433.3333 | F9: =BaaS.1!G44 -> 4088.8889 | G9: =BaaS.1!H44 -> 4625.9259 | H9: =BaaS.1!I44 -> 5083.9506 | I9: =BaaS.1!J44 -> 5389.3004 | J9: =BaaS.1!K44 -> 5792.8669 | ... AL9: =BaaS.1!AM44 -> 8999.9333 | AN9: =N9 -> 7877.6033 | AO9: =Z9 -> 8991.3493 | AP9: =AL9 -> 8999.9333
B10: Факторинг | C10: =BaaS.1!D66 -> 1500 | D10: =BaaS.1!E66 -> 2600 | E10: =BaaS.1!F66 -> 3433.3333 | F10: =BaaS.1!G66 -> 4088.8889 | G10: =BaaS.1!H66 -> 4625.9259 | H10: =BaaS.1!I66 -> 5083.9506 | I10: =BaaS.1!J66 -> 5389.3004 | J10: =BaaS.1!K66 -> 5792.8669 | ... AL10: =BaaS.1!AM66 -> 8999.9333 | AN10: =N10 -> 7877.6033 | AO10: =Z10 -> 8991.3493 | AP10: =AL10 -> 8999.9333
B11: Кредитная линия для ИП | C11: =BaaS.1!D88 -> 450 | D11: =BaaS.1!E88 -> 930 | E11: =BaaS.1!F88 -> 1440 | F11: =BaaS.1!G88 -> 1980 | G11: =BaaS.1!H88 -> 2550 | H11: =BaaS.1!I88 -> 3150 | I11: =BaaS.1!J88 -> 3750 | J11: =BaaS.1!K88 -> 4410 | ... AL11: =BaaS.1!AM88 -> 29250 | AN11: =N11 -> 7650 | AO11: =Z11 -> 18450 | AP11: =AL11 -> 29250
B12: Резервы под обесценение | C12: =SUM(C13:C16) -> -633 | D12: =SUM(D13:D16) -> -1220.7 | E12: =SUM(E13:E16) -> -1777.0583 | F12: =SUM(F13:F16) -> -2311.5368 | G12: =SUM(G13:G16) -> -2830.5865 | H12: =SUM(H13:H16) -> -3338.6395 | I12: =SUM(I13:I16) -> -3796.5708 | J12: =SUM(J13:J16) -> -4296.774 | ... AL12: =SUM(AL13:AL16) -> -13160.621 | AN12: =N12 -> -6625.2125 | AO12: =Z12 -> -11107.87 | AP12: =AL12 -> -13160.621
B13: Потребительский кредит | C13: =BaaS.1!D27 -> -450 | D13: =BaaS.1!E27 -> -892.5 | E13: =BaaS.1!F27 -> -1328.125 | F13: =BaaS.1!G27 -> -1757.4479 | G13: =BaaS.1!H27 -> -2180.9939 | H13: =BaaS.1!I27 -> -2599.2444 | I13: =BaaS.1!J27 -> -2982.6407 | J13: =BaaS.1!K27 -> -3394.0873 | ... AL13: =BaaS.1!AM27 -> -10115.627 | AN13: =N13 -> -5276.4522 | AO13: =Z13 -> -8855.7353 | AP13: =AL13 -> -10115.627
B14: Рассрочка (BNPL) | C14: =BaaS.1!D49 -> -75 | D14: =BaaS.1!E49 -> -130 | E14: =BaaS.1!F49 -> -171.66667 | F14: =BaaS.1!G49 -> -204.44444 | G14: =BaaS.1!H49 -> -231.2963 | H14: =BaaS.1!I49 -> -254.19753 | I14: =BaaS.1!J49 -> -269.46502 | J14: =BaaS.1!K49 -> -289.64335 | ... AL14: =BaaS.1!AM49 -> -449.99667 | AN14: =N14 -> -393.88017 | AO14: =Z14 -> -449.56746 | AP14: =AL14 -> -449.99667
B15: Факторинг | C15: =BaaS.1!D71 -> -75 | D15: =BaaS.1!E71 -> -130 | E15: =BaaS.1!F71 -> -171.66667 | F15: =BaaS.1!G71 -> -204.44444 | G15: =BaaS.1!H71 -> -231.2963 | H15: =BaaS.1!I71 -> -254.19753 | I15: =BaaS.1!J71 -> -269.46502 | J15: =BaaS.1!K71 -> -289.64335 | ... AL15: =BaaS.1!AM71 -> -449.99667 | AN15: =N15 -> -393.88017 | AO15: =Z15 -> -449.56746 | AP15: =AL15 -> -449.99667
B16: Кредитная линия для ИП | C16: =BaaS.1!D96+BaaS.1!D97 -> -33 | D16: =BaaS.1!E96+BaaS.1!E97 -> -68.2 | E16: =BaaS.1!F96+BaaS.1!F97 -> -105.6 | F16: =BaaS.1!G96+BaaS.1!G97 -> -145.2 | G16: =BaaS.1!H96+BaaS.1!H97 -> -187 | H16: =BaaS.1!I96+BaaS.1!I97 -> -231 | I16: =BaaS.1!J96+BaaS.1!J97 -> -275 | J16: =BaaS.1!K96+BaaS.1!K97 -> -323.4 | ... AL16: =BaaS.1!AM96+BaaS.1!AM97 -> -2145 | AN16: =N16 -> -561 | AO16: =Z16 -> -1353 | AP16: =AL16 -> -2145
B17: Чистые кредиты клиентам | C17: =C7+C12 -> 25317 | D17: =D7+D12 -> 49534.3 | E17: =E7+E12 -> 72935.858 | F17: =F7+F12 -> 95718.637 | G17: =G7+G12 -> 118020.96 | H17: =H7+H12 -> 139941.48 | I17: =I7+I12 -> 159864.07 | J17: =J7+J12 -> 181403.33 | ... AL17: =AL7+AL12 -> 539870.61 | AN17: =N17 -> 280602.6 | AO17: =Z17 -> 468111.59 | AP17: =AL17 -> 539870.61
B18: Основные средства и НМА | C18: =SUM(C19:C20) -> 2550 | D18: =SUM(D19:D20) -> 10157.5 | E18: =SUM(E19:E20) -> 13812.5 | F18: =SUM(F19:F20) -> 16553.75 | G18: =SUM(G19:G20) -> 16270.417 | H18: =SUM(H19:H20) -> 15987.083 | I18: =SUM(I19:I20) -> 15703.75 | J18: =SUM(J19:J20) -> 18395.417 | ... AL18: =SUM(AL19:AL20) -> 9073.75 | AN18: =N18 -> 17063.75 | AO18: =Z18 -> 13068.75 | AP18: =AL18 -> 9073.75
B19: Первоначальная стоимость | C19: ='OPEX+CAPEX'!E17 -> 2550 | D19: =C19+'OPEX+CAPEX'!F17 -> 10200 | E19: =D19+'OPEX+CAPEX'!G17 -> 14025 | F19: =E19+'OPEX+CAPEX'!H17 -> 17000 | G19: =F19+'OPEX+CAPEX'!I17 -> 17000 | H19: =G19+'OPEX+CAPEX'!J17 -> 17000 | I19: =H19+'OPEX+CAPEX'!K17 -> 17000 | J19: =I19+'OPEX+CAPEX'!L17 -> 19975 | K19: =J19+'OPEX+CAPEX'!M17 -> 19975 | ... AL19: =AK19+'OPEX+CAPEX'!AN17 -> 19975 | AN19: =N19 -> 19975 | AO19: =Z19 -> 19975 | AP19: =AL19 -> 19975
B20: (Амортизация) | C20: =-'OPEX+CAPEX'!E8 -> 0 | D20: =C20-'OPEX+CAPEX'!F8 -> -42.5 | E20: =D20-'OPEX+CAPEX'!G8 -> -212.5 | F20: =E20-'OPEX+CAPEX'!H8 -> -446.25 | G20: =F20-'OPEX+CAPEX'!I8 -> -729.58333 | H20: =G20-'OPEX+CAPEX'!J8 -> -1012.9167 | I20: =H20-'OPEX+CAPEX'!K8 -> -1296.25 | J20: =I20-'OPEX+CAPEX'!L8 -> -1579.5833 | K20: =J20-'OPEX+CAPEX'!M8 -> -1912.5 | ... AL20: =AK20-'OPEX+CAPEX'!AN8 -> -10901.25 | AN20: =N20 -> -2911.25 | AO20: =Z20 -> -6906.25 | AP20: =AL20 -> -10901.25
B21: ВСЕГО АКТИВЫ | C21: =C7+C12 -> 25317 | D21: =D7+D12 -> 49534.3 | E21: =E7+E12 -> 72935.858 | F21: =F7+F12 -> 95718.637 | G21: =G7+G12 -> 118020.96 | H21: =H7+H12 -> 139941.48 | I21: =I7+I12 -> 159864.07 | J21: =J7+J12 -> 181403.33 | ... AL21: =AL7+AL12 -> 539870.61 | AN21: =N21 -> 280602.6 | AO21: =Z21 -> 468111.59 | AP21: =AL21 -> 539870.61
B23: ОБЯЗАТЕЛЬСТВА
B24: Средства клиентов | C24: =C25+C27+C31+C33 -> 134900 | D24: =D25+D27+D31+D33 -> 198515.19 | E24: =E25+E27+E31+E33 -> 271554.4 | F24: =F25+F27+F31+F33 -> 333915.41 | G24: =G25+G27+G31+G33 -> 395842.87 | H24: =H25+H27+H31+H33 -> 466013.75 | I24: =I25+I27+I31+I33 -> 522507.08 | J24: =J25+J27+J31+J33 -> 583201.47 | ... AL24: =AL25+AL27+AL31+AL33 -> 1652948.5 | AN24: =N24 -> 911763.01 | AO24: =Z24 -> 1446214.4 | AP24: =AL24 -> 1652948.5
B25: Текущие счета юр лиц | C25: =C26 -> 70000 | D25: =D26 -> 70000 | E25: =E26 -> 80000 | F25: =F26 -> 80000 | G25: =G26 -> 80000 | H25: =H26 -> 90000 | I25: =I26 -> 90000 | J25: =J26 -> 90000 | ... AL25: =AL26 -> 140000 | AN25: =N25 -> 140000 | AO25: =Z25 -> 140000 | AP25: =AL25 -> 140000
B26: QR прием / оплата | C26: =BaaS.3!D26 -> 70000 | D26: =BaaS.3!E26 -> 70000 | E26: =BaaS.3!F26 -> 80000 | F26: =BaaS.3!G26 -> 80000 | G26: =BaaS.3!H26 -> 80000 | H26: =BaaS.3!I26 -> 90000 | I26: =BaaS.3!J26 -> 90000 | J26: =BaaS.3!K26 -> 90000 | ... AL26: =BaaS.3!AM26 -> 140000 | AN26: =N26 -> 140000 | AO26: =Z26 -> 140000 | AP26: =AL26 -> 140000
B27: Депозиты до востребования физ лиц | C27: =SUM(C28:C30) -> 550 | D27: =SUM(D28:D30) -> 700 | E27: =SUM(E28:E30) -> 900 | F27: =SUM(F28:F30) -> 1000 | G27: =SUM(G28:G30) -> 1200 | H27: =SUM(H28:H30) -> 1450 | I27: =SUM(I28:I30) -> 1650 | J27: =SUM(J28:J30) -> 1850 | ... AL27: =SUM(AL28:AL30) -> 2800 | AN27: =N27 -> 2800 | AO27: =Z27 -> 2800 | AP27: =AL27 -> 2800
B28: Кошельки | C28: =BaaS.3!D52 -> 200 | D28: =BaaS.3!E52 -> 200 | E28: =BaaS.3!F52 -> 200 | F28: =BaaS.3!G52 -> 300 | G28: =BaaS.3!H52 -> 300 | H28: =BaaS.3!I52 -> 400 | I28: =BaaS.3!J52 -> 400 | J28: =BaaS.3!K52 -> 400 | ... AL28: =BaaS.3!AM52 -> 600 | AN28: =N28 -> 600 | AO28: =Z28 -> 600 | AP28: =AL28 -> 600
B29: Расчетный счет (ФЛ) | C29: =BaaS.3!D66 -> 200 | D29: =BaaS.3!E66 -> 200 | E29: =BaaS.3!F66 -> 400 | F29: =BaaS.3!G66 -> 400 | G29: =BaaS.3!H66 -> 600 | H29: =BaaS.3!I66 -> 600 | I29: =BaaS.3!J66 -> 800 | J29: =BaaS.3!K66 -> 1000 | ... AL29: =BaaS.3!AM66 -> 1600 | AN29: =N29 -> 1600 | AO29: =Z29 -> 1600 | AP29: =AL29 -> 1600
B30: Виртуальная карта | C30: =BaaS.3!D81 -> 150 | D30: =BaaS.3!E81 -> 300 | E30: =BaaS.3!F81 -> 300 | F30: =BaaS.3!G81 -> 300 | G30: =BaaS.3!H81 -> 300 | H30: =BaaS.3!I81 -> 450 | I30: =BaaS.3!J81 -> 450 | J30: =BaaS.3!K81 -> 450 | ... AL30: =BaaS.3!AM81 -> 600 | AN30: =N30 -> 600 | AO30: =Z30 -> 600 | AP30: =AL30 -> 600
B31: Срочные депозиты физ лиц | C31: =SUM(C32) -> 64350 | D31: =SUM(D32) -> 127815.19 | E31: =SUM(E32) -> 190654.4 | F31: =SUM(F32) -> 252915.41 | G31: =SUM(G32) -> 314642.87 | H31: =SUM(H32) -> 374563.75 | I31: =SUM(I32) -> 430857.08 | J31: =SUM(J32) -> 491351.47 | ... AL31: =SUM(AL32) -> 1510148.5 | AN31: =N31 -> 768963.01 | AO31: =Z31 -> 1303414.4 | AP31: =AL31 -> 1510148.5
B32: Онлайн депозит | C32: =BaaS.2!D9 -> 64350 | D32: =BaaS.2!E9 -> 127815.19 | E32: =BaaS.2!F9 -> 190654.4 | F32: =BaaS.2!G9 -> 252915.41 | G32: =BaaS.2!H9 -> 314642.87 | H32: =BaaS.2!I9 -> 374563.75 | I32: =BaaS.2!J9 -> 430857.08 | J32: =BaaS.2!K9 -> 491351.47 | ... AL32: =BaaS.2!AM9 -> 1510148.5 | AN32: =N32 -> 768963.01 | AO32: =Z32 -> 1303414.4 | AP32: =AL32 -> 1510148.5
B33: Срочные депозиты юр лиц | AN33: =N33 -> 0 | AO33: =Z33 -> 0 | AP33: =AL33 -> 0
B34: ИТОГО ОБЯЗАТЕЛЬСТВА | C34: =C24 -> 134900 | D34: =D24 -> 198515.19 | E34: =E24 -> 271554.4 | F34: =F24 -> 333915.41 | G34: =G24 -> 395842.87 | H34: =H24 -> 466013.75 | I34: =I24 -> 522507.08 | J34: =J24 -> 583201.47 | ... AL34: =AL24 -> 1652948.5 | AN34: =N34 -> 911763.01 | AO34: =Z34 -> 1446214.4 | AP34: =AL34 -> 1652948.5
B36: КАПИТАЛ
B37: Нераспределенная прибыль | O37: =N38 -> 417423.99 | P37: =O37 -> 417423.99 | Q37: =P37 -> 417423.99 | R37: =Q37 -> 417423.99 | S37: =R37 -> 417423.99 | T37: =S37 -> 417423.99 | U37: =T37 -> 417423.99 | V37: =U37 -> 417423.99 | W37: =V37 -> 417423.99 | ... Z37: =Y37 -> 417423.99 | AA37: =Z37+Z38 -> 1041254.6 | AB37: =AA37 -> 1041254.6 | AC37: =AB37 -> 1041254.6 | AD37: =AC37 -> 1041254.6 | AE37: =AD37 -> 1041254.6 | AF37: =AE37 -> 1041254.6 | AG37: =AF37 -> 1041254.6 | AH37: =AG37 -> 1041254.6 | AI37: =AH37 -> 1041254.6 | ... AL37: =AK37 -> 1041254.6 | AN37: =N37 -> 0 | AO37: =Z37 -> 417423.99 | AP37: =AL37 -> 1041254.6
B38: Текущая прибыль | C38: =PL!C148 -> 23055.21 | D38: =PL!D148 -> 48793.582 | E38: =PL!E148 -> 76259.956 | F38: =PL!F148 -> 105903.88 | G38: =PL!G148 -> 136970.56 | H38: =PL!H148 -> 169694.69 | I38: =PL!I148 -> 204206.83 | J38: =PL!J148 -> 240885.03 | ... AL38: =PL!AL148 -> 647423.02 | AN38: =N38 -> 417423.99 | AO38: =Z38 -> 623830.56 | AP38: =AL38 -> 647423.02
B39: ИТОГО КАПИТАЛ | C39: =C37+C38 -> 23055.21 | D39: =D37+D38 -> 48793.582 | E39: =E37+E38 -> 76259.956 | F39: =F37+F38 -> 105903.88 | G39: =G37+G38 -> 136970.56 | H39: =H37+H38 -> 169694.69 | I39: =I37+I38 -> 204206.83 | J39: =J37+J38 -> 240885.03 | ... AL39: =AL37+AL38 -> 1688677.6 | AN39: =N39 -> 417423.99 | AO39: =Z39 -> 1041254.6 | AP39: =AL39 -> 1688677.6
B40: ВСЕГО ОБЯЗАТЕЛЬСТВА И КАПИТАЛ | C40: =SUM(C34,C39) -> 157955.21 | D40: =SUM(D34,D39) -> 247308.77 | E40: =SUM(E34,E39) -> 347814.36 | F40: =SUM(F34,F39) -> 439819.28 | G40: =SUM(G34,G39) -> 532813.43 | H40: =SUM(H34,H39) -> 635708.44 | I40: =SUM(I34,I39) -> 726713.91 | J40: =SUM(J34,J39) -> 824086.49 | ... AL40: =SUM(AL34,AL39) -> 3341626.1 | AN40: =N40 -> 1329187 | AO40: =Z40 -> 2487468.9 | AP40: =AL40 -> 3341626.1

Sheet PL
B1: Финансовый результат BaaS
B2: (тыс. сом)
C4: 46023 | D4: =C4+31 -> 46054 | E4: =D4+31 -> 46085 | F4: =E4+31 -> 46116 | G4: =F4+31 -> 46147 | H4: =G4+31 -> 46178 | I4: =H4+31 -> 46209 | J4: =I4+31 -> 46240 | K4: =J4+31 -> 46271 | ... AL4: =AK4+31 -> 47108 | AN4: =YEAR(N4) -> 2026 | AO4: =YEAR(Z4) -> 2027 | AP4: =YEAR(AL4) -> 2028
C5: m1 | D5: m2 | E5: m3 | F5: m4 | G5: m5 | H5: m6 | I5: m7 | J5: m8 | K5: m9 | L5: m10 | M5: m11 | N5: m12 | O5: m13 | P5: m14 | Q5: m15 | R5: m16 | S5: m17 | T5: m18 | U5: m19 | V5: m20 | W5: m21 | X5: m22 | Y5: m23 | Z5: m24 | AA5: m25 | AB5: m26 | AC5: m27 | AD5: m28 | AE5: m29 | AF5: m30 | AG5: m31 | AH5: m32 | AI5: m33 | AJ5: m34 | AK5: m35 | AL5: m36 | AN5: Y1 | AO5: Y2 | AP5: Y3
B7: Маржа по размещению | C7: =C8+C11 -> 78.455882 | D7: =D8+D11 -> 238.1011 | E7: =E8+E11 -> 402.21318 | F7: =F8+F11 -> 569.15314 | G7: =G8+G11 -> 737.88153 | H7: =H8+H11 -> 907.75417 | I7: =I8+I11 -> 1073.1559 | J7: =J8+J11 -> 1239.2682 | ... AL7: =AL8+AL11 -> 4841.0193 | AN7: =SUM(C7:N7) -> 12081.005 | AO7: =SUM(O7:Z7) -> 37327.547 | AP7: =SUM(AA7:AL7) -> 53092.637
B8: Процентные доходы | C8: =SUM(C9:C10) -> 233.45588 | D8: =SUM(D9:D10) -> 697.54902 | E8: =SUM(E9:E10) -> 1156.3113 | F8: =SUM(F9:F10) -> 1610.3299 | G8: =SUM(G9:G10) -> 2060.1431 | H8: =SUM(H9:H10) -> 2506.2443 | I8: =SUM(I9:I10) -> 2933.5221 | J8: =SUM(J9:J10) -> 3359.1804 | ... AL8: =SUM(AL9:AL10) -> 11533.843 | AN8: =SUM(C8:N8) -> 32813.897 | AO8: =SUM(O8:Z8) -> 95660.043 | AP8: =SUM(AA8:AL8) -> 129221.81
B9: Потребительский кредит | C9: =BaaS.1!D28 -> 220.58824 | D9: =BaaS.1!E28 -> 658.08824 | E9: =BaaS.1!F28 -> 1088.5417 | F9: =BaaS.1!G28 -> 1512.5357 | G9: =BaaS.1!H28 -> 1930.6087 | H9: =BaaS.1!I28 -> 2343.2541 | I9: =BaaS.1!J28 -> 2736.2182 | J9: =BaaS.1!K28 -> 3125.8471 | ... AL9: =BaaS.1!AM28 -> 9886.7838 | AN9: =SUM(C9:N9) -> 30510.588 | AO9: =SUM(O9:Z9) -> 86704.161 | AP9: =SUM(AA9:AL9) -> 112854.16
B10: Кредитная линия для ИП | C10: =BaaS.1!D98 -> 12.867647 | D10: =BaaS.1!E98 -> 39.460784 | E10: =BaaS.1!F98 -> 67.769608 | F10: =BaaS.1!G98 -> 97.794118 | G10: =BaaS.1!H98 -> 129.53431 | H10: =BaaS.1!I98 -> 162.9902 | I10: =BaaS.1!J98 -> 197.30392 | J10: =BaaS.1!K98 -> 233.33333 | ... AL10: =BaaS.1!AM98 -> 1647.0588 | AN10: =SUM(C10:N10) -> 2303.3088 | AO10: =SUM(O10:Z10) -> 8955.8824 | AP10: =SUM(AA10:AL10) -> 16367.647
B11: Расходы на фондирование | C11: =SUM(C12:C15) -> -155 | D11: =SUM(D12:D15) -> -459.44792 | E11: =SUM(E12:E15) -> -754.09809 | F11: =SUM(F12:F15) -> -1041.1767 | G11: =SUM(G12:G15) -> -1322.2615 | H11: =SUM(H12:H15) -> -1598.4901 | I11: =SUM(I12:I15) -> -1860.3662 | J11: =SUM(J12:J15) -> -2119.9122 | ... AL11: =SUM(AL12:AL15) -> -6692.8233 | AN11: =SUM(C11:N11) -> -20732.891 | AO11: =SUM(O11:Z11) -> -58332.496 | AP11: =SUM(AA11:AL11) -> -76129.168
B12: Потребительский кредит | C12: =BaaS.1!D29 -> -140.625 | D12: =BaaS.1!E29 -> -419.53125 | E12: =BaaS.1!F29 -> -693.94531 | F12: =BaaS.1!G29 -> -964.24154 | G12: =BaaS.1!H29 -> -1230.7631 | H12: =BaaS.1!I29 -> -1493.8245 | I12: =BaaS.1!J29 -> -1744.3391 | J12: =BaaS.1!K29 -> -1992.7275 | ... AL12: =BaaS.1!AM29 -> -6302.8247 | AN12: =SUM(C12:N12) -> -19450.5 | AO12: =SUM(O12:Z12) -> -55273.903 | AP12: =SUM(AA12:AL12) -> -71944.526
B13: Рассрочка (BNPL) | C13: =BaaS.1!D51 -> -6.25 | D13: =BaaS.1!E51 -> -17.083333 | E13: =BaaS.1!F51 -> -25.138889 | F13: =BaaS.1!G51 -> -31.342593 | G13: =BaaS.1!H51 -> -36.311728 | H13: =BaaS.1!I51 -> -40.457819 | I13: =BaaS.1!J51 -> -43.638546 | J13: =BaaS.1!K51 -> -46.592364 | ... AL13: =BaaS.1!AM51 -> -74.999305 | AN13: =SUM(C13:N13) -> -473.38326 | AO13: =SUM(O13:Z13) -> -876.79696 | AP13: =SUM(AA13:AL13) -> -899.82117
B14: Факторинг | C14: =BaaS.1!D73 -> -6.25 | D14: =BaaS.1!E73 -> -17.083333 | E14: =BaaS.1!F73 -> -25.138889 | F14: =BaaS.1!G73 -> -31.342593 | G14: =BaaS.1!H73 -> -36.311728 | H14: =BaaS.1!I73 -> -40.457819 | I14: =BaaS.1!J73 -> -43.638546 | J14: =BaaS.1!K73 -> -46.592364 | ... AL14: =BaaS.1!AM73 -> -74.999305 | AN14: =SUM(C14:N14) -> -473.38326 | AO14: =SUM(O14:Z14) -> -876.79696 | AP14: =SUM(AA14:AL14) -> -899.82117
B15: Кредитная линия для ИП | C15: =BaaS.1!D99 -> -1.875 | D15: =BaaS.1!E99 -> -5.75 | E15: =BaaS.1!F99 -> -9.875 | F15: =BaaS.1!G99 -> -14.25 | G15: =BaaS.1!H99 -> -18.875 | H15: =BaaS.1!I99 -> -23.75 | I15: =BaaS.1!J99 -> -28.75 | J15: =BaaS.1!K99 -> -34 | ... AL15: =BaaS.1!AM99 -> -240 | AN15: =SUM(C15:N15) -> -335.625 | AO15: =SUM(O15:Z15) -> -1305 | AP15: =SUM(AA15:AL15) -> -2385
B16: Маржа по привлечению | C16: =C17+C21 -> 1498.5417 | D16: =D17+D21 -> 3053.221 | E16: =E17+E21 -> 3172.7247 | F16: =F17+F21 -> 3560.8082 | G16: =G17+G21 -> 3931.2986 | H16: =H17+H21 -> 4046.1721 | I16: =I17+I21 -> 4425.0174 | J16: =J17+J21 -> 4789.6738 | ... AL16: =AL17+AL21 -> 7760.0346 | AN16: =SUM(C16:N16) -> 50585.222 | AO16: =SUM(O16:Z16) -> 84549.313 | AP16: =SUM(AA16:AL16) -> 91484.717
B17: Процентные расходы | C17: =SUM(C18:C20) -> -381.375 | D17: =SUM(D18:D20) -> -1129.9636 | E17: =SUM(E18:E20) -> -1869.7393 | F17: =SUM(F18:F20) -> -2599.4906 | G17: =SUM(G18:G20) -> -3322.7566 | H17: =SUM(H18:H20) -> -4028.9544 | I17: =SUM(I18:I20) -> -4716.2882 | J17: =SUM(J18:J20) -> -5397.5499 | ... AL17: =SUM(AL18:AL20) -> -17580.242 | AN17: =SUM(C17:N17) -> -52742.885 | AO17: =SUM(O17:Z17) -> -150965.19 | AP17: =SUM(AA17:AL17) -> -199513.02
B18: Онлайн депозит | C18: =BaaS.2!D10 -> -375.375 | D18: =BaaS.2!E10 -> -1120.9636 | E18: =BaaS.2!F10 -> -1857.7393 | F18: =BaaS.2!G10 -> -2587.4906 | G18: =BaaS.2!H10 -> -3310.7566 | H18: =BaaS.2!I10 -> -4013.9544 | I18: =BaaS.2!J10 -> -4698.2882 | J18: =BaaS.2!K10 -> -5379.5499 | ... AL18: =BaaS.2!AM10 -> -17556.242 | AN18: =SUM(C18:N18) -> -52559.885 | AO18: =SUM(O18:Z18) -> -150677.19 | AP18: =SUM(AA18:AL18) -> -199225.02
B19: Виртуальные карты (cashback) | C19: =BaaS.3!D88 -> -6 | D19: =BaaS.3!E88 -> -9 | E19: =BaaS.3!F88 -> -12 | F19: =BaaS.3!G88 -> -12 | G19: =BaaS.3!H88 -> -12 | H19: =BaaS.3!I88 -> -15 | I19: =BaaS.3!J88 -> -18 | J19: =BaaS.3!K88 -> -18 | ... AL19: =BaaS.3!AM88 -> -24 | AN19: =SUM(C19:N19) -> -183 | AO19: =SUM(O19:Z19) -> -288 | AP19: =SUM(AA19:AL19) -> -288
B21: Доходы от фондирования | C21: =SUM(C22:C27) -> 1879.9167 | D21: =SUM(D22:D27) -> 4183.1846 | E21: =SUM(E22:E27) -> 5042.4639 | F21: =SUM(F22:F27) -> 6160.2987 | G21: =SUM(G22:G27) -> 7254.0552 | H21: =SUM(H22:H27) -> 8075.1264 | I21: =SUM(I22:I27) -> 9141.3055 | J21: =SUM(J22:J27) -> 10187.224 | ... AL21: =SUM(AL22:AL27) -> 25340.277 | AN21: =SUM(C21:N21) -> 103328.11 | AO21: =SUM(O21:Z21) -> 235514.51 | AP21: =SUM(AA21:AL21) -> 290997.73
B22: Онлайн депозит | C22: =BaaS.2!D11 -> 429 | D22: =BaaS.2!E11 -> 1281.1012 | E22: =BaaS.2!F11 -> 2123.1306 | F22: =BaaS.2!G11 -> 2957.1321 | G22: =BaaS.2!H11 -> 3783.7218 | H22: =BaaS.2!I11 -> 4587.3764 | I22: =BaaS.2!J11 -> 5369.4722 | J22: =BaaS.2!K11 -> 6148.057 | ... AL22: =BaaS.2!AM11 -> 20064.277 | AN22: =SUM(C22:N22) -> 60068.44 | AO22: =SUM(O22:Z22) -> 172202.51 | AP22: =SUM(AA22:AL22) -> 227685.73
B23: QR прием / оплата | C23: =BaaS.3!D28 -> 1450 | D23: =BaaS.3!E28 -> 2900 | E23: =BaaS.3!F28 -> 2916.6667 | F23: =BaaS.3!G28 -> 3200 | G23: =BaaS.3!H28 -> 3466.6667 | H23: =BaaS.3!I28 -> 3483.3333 | I23: =BaaS.3!J28 -> 3766.6667 | J23: =BaaS.3!K28 -> 4033.3333 | ... AL23: =BaaS.3!AM28 -> 5266.6667 | AN23: =SUM(C23:N23) -> 43200 | AO23: =SUM(O23:Z23) -> 63200 | AP23: =SUM(AA23:AL23) -> 63200
B24: Кошельки | C24: =BaaS.3!D54 -> 0.33333333 | D24: =BaaS.3!E54 -> 0.66666667 | E24: =BaaS.3!F54 -> 0.66666667 | F24: =BaaS.3!G54 -> 0.83333333 | G24: =BaaS.3!H54 -> 1 | H24: =BaaS.3!I54 -> 1.1666667 | I24: =BaaS.3!J54 -> 1.3333333 | J24: =BaaS.3!K54 -> 1.3333333 | ... AL24: =BaaS.3!AM54 -> 2 | AN24: =SUM(C24:N24) -> 14 | AO24: =SUM(O24:Z24) -> 24 | AP24: =SUM(AA24:AL24) -> 24
B25: Расчетный счет (ФЛ) | C25: =BaaS.3!D68 -> 0.33333333 | D25: =BaaS.3!E68 -> 0.66666667 | E25: =BaaS.3!F68 -> 1 | F25: =BaaS.3!G68 -> 1.3333333 | G25: =BaaS.3!H68 -> 1.6666667 | H25: =BaaS.3!I68 -> 2 | I25: =BaaS.3!J68 -> 2.3333333 | J25: =BaaS.3!K68 -> 3 | ... AL25: =BaaS.3!AM68 -> 5.3333333 | AN25: =SUM(C25:N25) -> 30.666667 | AO25: =SUM(O25:Z25) -> 64 | AP25: =SUM(AA25:AL25) -> 64
B26: Виртуальные карты | C26: =BaaS.3!D85 -> 0.25 | D26: =BaaS.3!E85 -> 0.75 | E26: =BaaS.3!F85 -> 1 | F26: =BaaS.3!G85 -> 1 | G26: =BaaS.3!H85 -> 1 | H26: =BaaS.3!I85 -> 1.25 | I26: =BaaS.3!J85 -> 1.5 | J26: =BaaS.3!K85 -> 1.5 | ... AL26: =BaaS.3!AM85 -> 2 | AN26: =SUM(C26:N26) -> 15 | AO26: =SUM(O26:Z26) -> 24 | AP26: =SUM(AA26:AL26) -> 24
B28: Чистый процентный доход до формирования резервов | C28: =C7+C16 -> 1576.9975 | D28: =D7+D16 -> 3291.3221 | E28: =E7+E16 -> 3574.9378 | F28: =F7+F16 -> 4129.9613 | G28: =G7+G16 -> 4669.1801 | H28: =H7+H16 -> 4953.9262 | I28: =I7+I16 -> 5498.1733 | J28: =J7+J16 -> 6028.942 | ... AL28: =AL7+AL16 -> 12601.054 | AN28: =SUM(C28:N28) -> 62666.227 | AO28: =SUM(O28:Z28) -> 121876.86 | AP28: =SUM(AA28:AL28) -> 144577.35
B29: Формирование резерва под обесценение процентных активов | C29: =SUM(C30:C34) -> -648 | D29: =SUM(D30:D34) -> -588.7 | E29: =SUM(E30:E34) -> -557.35833 | F29: =SUM(F30:F34) -> -535.47847 | G29: =SUM(G30:G34) -> -520.04971 | H29: =SUM(H30:H34) -> -509.05298 | I29: =SUM(I30:I34) -> -457.93128 | J29: =SUM(J30:J34) -> -502.20326 | ... AL29: =SUM(AL30:AL34) -> -128.21903 | AN29: =SUM(C29:N29) -> -6655.2125 | AO29: =SUM(O29:Z29) -> -4482.6577 | AP29: =SUM(AA29:AL29) -> -2052.7504
B30: Потребительский кредит | C30: =BaaS.1!D31 -> -450 | D30: =BaaS.1!E31 -> -442.5 | E30: =BaaS.1!F31 -> -435.625 | F30: =BaaS.1!G31 -> -429.32292 | G30: =BaaS.1!H31 -> -423.54601 | H30: =BaaS.1!I31 -> -418.25051 | I30: =BaaS.1!J31 -> -383.3963 | J30: =BaaS.1!K31 -> -411.44661 | ... AL30: =BaaS.1!AM31 -> -62.215697 | AN30: =SUM(C30:N30) -> -5276.4522 | AO30: =SUM(O30:Z30) -> -3579.2831 | AP30: =SUM(AA30:AL30) -> -1259.892
B31: Рассрочка (BNPL) | C31: =BaaS.1!D53 -> -75 | D31: =BaaS.1!E53 -> -55 | E31: =BaaS.1!F53 -> -41.666667 | F31: =BaaS.1!G53 -> -32.777778 | G31: =BaaS.1!H53 -> -26.851852 | H31: =BaaS.1!I53 -> -22.901235 | I31: =BaaS.1!J53 -> -15.26749 | J31: =BaaS.1!K53 -> -20.178326 | ... AL31: =BaaS.1!AM53 -> -0.0016668486 | AN31: =SUM(C31:N31) -> -393.88017 | AO31: =SUM(O31:Z31) -> -55.687298 | AP31: =SUM(AA31:AL31) -> -0.42920131
B32: Факторинг | C32: =BaaS.1!D75 -> -75 | D32: =BaaS.1!E75 -> -55 | E32: =BaaS.1!F75 -> -41.666667 | F32: =BaaS.1!G75 -> -32.777778 | G32: =BaaS.1!H75 -> -26.851852 | H32: =BaaS.1!I75 -> -22.901235 | I32: =BaaS.1!J75 -> -15.26749 | J32: =BaaS.1!K75 -> -20.178326 | ... AL32: =BaaS.1!AM75 -> -0.0016668486 | AN32: =SUM(C32:N32) -> -393.88017 | AO32: =SUM(O32:Z32) -> -55.687298 | AP32: =SUM(AA32:AL32) -> -0.42920131
B33: Кредитная линия для ИП | C33: =BaaS.1!D101 -> -33 | D33: =BaaS.1!E101 -> -35.2 | E33: =BaaS.1!F101 -> -37.4 | F33: =BaaS.1!G101 -> -39.6 | G33: =BaaS.1!H101 -> -41.8 | H33: =BaaS.1!I101 -> -44 | I33: =BaaS.1!J101 -> -44 | J33: =BaaS.1!K101 -> -48.4 | ... AL33: =BaaS.1!AM101 -> -66 | AN33: =SUM(C33:N33) -> -561 | AO33: =SUM(O33:Z33) -> -792 | AP33: =SUM(AA33:AL33) -> -792
B34: Гарантии | C34: =BaaS.1!D115 -> -15 | D34: =BaaS.1!E115 -> -1 | E34: =BaaS.1!F115 -> -1 | F34: =BaaS.1!G115 -> -1 | G34: =BaaS.1!H115 -> -1 | H34: =BaaS.1!I115 -> -1 | I34: =BaaS.1!J115 -> 0 | J34: =BaaS.1!K115 -> -2 | ... AL34: =BaaS.1!AM115 -> 0 | AN34: =SUM(C34:N34) -> -30 | AO34: =SUM(O34:Z34) -> 0 | AP34: =SUM(AA34:AL34) -> 0
B35: ЧИСТЫЙ ПРОЦЕНТНЫЙ ДОХОД | C35: =C28+C29 -> 928.99755 | D35: =D28+D29 -> 2702.6221 | E35: =E28+E29 -> 3017.5795 | F35: =F28+F29 -> 3594.4828 | G35: =G28+G29 -> 4149.1304 | H35: =H28+H29 -> 4444.8732 | I35: =I28+I29 -> 5040.242 | J35: =J28+J29 -> 5526.7387 | ... AL35: =AL28+AL29 -> 12472.835 | AN35: =SUM(C35:N35) -> 56011.015 | AO35: =SUM(O35:Z35) -> 117394.2 | AP35: =SUM(AA35:AL35) -> 142524.6
AN36: =SUM(C36:N36) -> 0 | AO36: =SUM(O36:Z36) -> 0 | AP36: =SUM(AA36:AL36) -> 0
B37: Чистый доход от операций с ин валютой | C37: =SUM(C38:C39) -> 17 | D37: =SUM(D38:D39) -> 17 | E37: =SUM(E38:E39) -> 17 | F37: =SUM(F38:F39) -> 34 | G37: =SUM(G38:G39) -> 34 | H37: =SUM(H38:H39) -> 34 | I37: =SUM(I38:I39) -> 51 | J37: =SUM(J38:J39) -> 51 | ... AL37: =SUM(AL38:AL39) -> 102 | AN37: =SUM(C37:N37) -> 595 | AO37: =SUM(O37:Z37) -> 1224 | AP37: =SUM(AA37:AL37) -> 1224
B38: Онлайн конвертация | C38: =BaaS.3!D100 -> 17 | D38: =BaaS.3!E100 -> 17 | E38: =BaaS.3!F100 -> 17 | F38: =BaaS.3!G100 -> 34 | G38: =BaaS.3!H100 -> 34 | H38: =BaaS.3!I100 -> 34 | I38: =BaaS.3!J100 -> 51 | J38: =BaaS.3!K100 -> 51 | ... AL38: =BaaS.3!AM100 -> 102 | AN38: =SUM(C38:N38) -> 595 | AO38: =SUM(O38:Z38) -> 1224 | AP38: =SUM(AA38:AL38) -> 1224
B40: Комиссионные доходы | C40: =C41+C45+C57 -> 35850.029 | D40: =D41+D45+D57 -> 36924.02 | E40: =E41+E45+E57 -> 39730.095 | F40: =F41+F45+F57 -> 41811.004 | G40: =G41+G45+G57 -> 43056.692 | H40: =H41+H45+H57 -> 45631.076 | I40: =I41+I45+I57 -> 47090.436 | J40: =J41+J45+J57 -> 49347.964 | ... AL40: =AL41+AL45+AL57 -> 67826.526 | AN40: =SUM(C40:N40) -> 577766.3 | AO40: =SUM(O40:Z40) -> 813603.28 | AP40: =SUM(AA40:AL40) -> 813852.81
B41: от партнеров BaaS | C41: =SUM(C42:C44) -> 75.490196 | D41: =SUM(D42:D44) -> 81.372549 | E41: =SUM(E42:E44) -> 87.254902 | F41: =SUM(F42:F44) -> 93.137255 | G41: =SUM(G42:G44) -> 99.019608 | H41: =SUM(H42:H44) -> 104.90196 | I41: =SUM(I42:I44) -> 105.88235 | J41: =SUM(J42:J44) -> 116.66667 | ... AL41: =SUM(AL42:AL44) -> 183.33333 | AN41: =SUM(C41:N41) -> 1338.2353 | AO41: =SUM(O41:Z41) -> 1994.1176 | AP41: =SUM(AA41:AL41) -> 2135.2941
B42: Продажа чужих кредитов | C42: =BaaS.1!D129 -> 1.9607843 | D42: =BaaS.1!E129 -> 2.9411765 | E42: =BaaS.1!F129 -> 3.9215686 | F42: =BaaS.1!G129 -> 4.9019608 | G42: =BaaS.1!H129 -> 5.8823529 | H42: =BaaS.1!I129 -> 6.8627451 | I42: =BaaS.1!J129 -> 7.8431373 | J42: =BaaS.1!K129 -> 8.8235294 | ... AL42: =BaaS.1!AM129 -> 36.27451 | AN42: =SUM(C42:N42) -> 88.235294 | AO42: =SUM(O42:Z42) -> 229.41176 | AP42: =SUM(AA42:AL42) -> 370.58824
B43: DCB ID / DCB BIO | C43: =BaaS.3!D14 -> 73.529412 | D43: =BaaS.3!E14 -> 78.431373 | E43: =BaaS.3!F14 -> 83.333333 | F43: =BaaS.3!G14 -> 88.235294 | G43: =BaaS.3!H14 -> 93.137255 | H43: =BaaS.3!I14 -> 98.039216 | I43: =BaaS.3!J14 -> 98.039216 | J43: =BaaS.3!K14 -> 107.84314 | ... AL43: =BaaS.3!AM14 -> 147.05882 | AN43: =SUM(C43:N43) -> 1250 | AO43: =SUM(O43:Z43) -> 1764.7059 | AP43: =SUM(AA43:AL43) -> 1764.7059
AN44: =SUM(C44:N44) -> 0 | AO44: =SUM(O44:Z44) -> 0 | AP44: =SUM(AA44:AL44) -> 0
B45: от клиентов | C45: =SUM(C46:C56) -> 19904.441 | D45: =SUM(D46:D56) -> 20972.549 | E45: =SUM(E46:E56) -> 22240.879 | F45: =SUM(F46:F56) -> 23286.495 | G45: =SUM(G46:G56) -> 24526.3 | H45: =SUM(H46:H56) -> 25562.939 | I45: =SUM(I46:I56) -> 25991.907 | J45: =SUM(J46:J56) -> 28238.65 | ... AL45: =SUM(AL46:AL56) -> 36932.408 | AN45: =SUM(C45:N45) -> 325067.77 | AO45: =SUM(O45:Z45) -> 443079.75 | AP45: =SUM(AA45:AL45) -> 443188.1
B46: Рассрочка (BNPL) | C46: =BaaS.1!D50 -> 73.529412 | D46: =BaaS.1!E50 -> 78.431373 | E46: =BaaS.1!F50 -> 83.333333 | F46: =BaaS.1!G50 -> 88.235294 | G46: =BaaS.1!H50 -> 93.137255 | H46: =BaaS.1!I50 -> 98.039216 | I46: =BaaS.1!J50 -> 98.039216 | J46: =BaaS.1!K50 -> 107.84314 | ... AL46: =BaaS.1!AM50 -> 147.05882 | AN46: =SUM(C46:N46) -> 1250 | AO46: =SUM(O46:Z46) -> 1764.7059 | AP46: =SUM(AA46:AL46) -> 1764.7059
B47: Факторинг | C47: =BaaS.1!D72 -> 0 | D47: =BaaS.1!E72 -> 49.019608 | E47: =BaaS.1!F72 -> 84.96732 | F47: =BaaS.1!G72 -> 112.20044 | G47: =BaaS.1!H72 -> 133.62382 | H47: =BaaS.1!I72 -> 151.17405 | I47: =BaaS.1!J72 -> 166.14218 | J47: =BaaS.1!K72 -> 176.12093 | ... AL47: =BaaS.1!AM72 -> 294.11438 | AN47: =SUM(C47:N47) -> 1727.6859 | AO47: =SUM(O47:Z47) -> 3420.221 | AP47: =SUM(AA47:AL47) -> 3528.5702
B48: Гарантии | C48: =BaaS.1!D116 -> 14.705882 | D48: =BaaS.1!E116 -> 15.686275 | E48: =BaaS.1!F116 -> 16.666667 | F48: =BaaS.1!G116 -> 17.647059 | G48: =BaaS.1!H116 -> 18.627451 | H48: =BaaS.1!I116 -> 19.607843 | I48: =BaaS.1!J116 -> 19.607843 | J48: =BaaS.1!K116 -> 21.568627 | ... AL48: =BaaS.1!AM116 -> 29.411765 | AN48: =SUM(C48:N48) -> 250 | AO48: =SUM(O48:Z48) -> 352.94118 | AP48: =SUM(AA48:AL48) -> 352.94118
B49: Расчетный счет (ФЛ) | C49: =BaaS.3!D70 -> 0 | D49: =BaaS.3!E70 -> 0 | E49: =BaaS.3!F70 -> 0 | F49: =BaaS.3!G70 -> 0 | G49: =BaaS.3!H70 -> 0 | H49: =BaaS.3!I70 -> 0 | I49: =BaaS.3!J70 -> 0 | J49: =BaaS.3!K70 -> 0 | ... AL49: =BaaS.3!AM70 -> 0 | AN49: =SUM(C49:N49) -> 0 | AO49: =SUM(O49:Z49) -> 0 | AP49: =SUM(AA49:AL49) -> 0
B50: Виртуальные карты | C50: =BaaS.3!D87 -> 0.70588235 | D50: =BaaS.3!E87 -> 1.4117647 | E50: =BaaS.3!F87 -> 1.4117647 | F50: =BaaS.3!G87 -> 1.4117647 | G50: =BaaS.3!H87 -> 1.4117647 | H50: =BaaS.3!I87 -> 2.1176471 | I50: =BaaS.3!J87 -> 2.1176471 | J50: =BaaS.3!K87 -> 2.1176471 | ... AL50: =BaaS.3!AM87 -> 2.8235294 | AN50: =SUM(C50:N50) -> 22.588235 | AO50: =SUM(O50:Z50) -> 33.882353 | AP50: =SUM(AA50:AL50) -> 33.882353
B51: Онлайн переводы | C51: =BaaS.3!D111 -> 4600 | D51: =BaaS.3!E111 -> 4600 | E51: =BaaS.3!F111 -> 4800 | F51: =BaaS.3!G111 -> 4800 | G51: =BaaS.3!H111 -> 5000 | H51: =BaaS.3!I111 -> 5000 | I51: =BaaS.3!J111 -> 5400 | J51: =BaaS.3!K111 -> 5600 | ... AL51: =BaaS.3!AM111 -> 6000 | AN51: =SUM(C51:N51) -> 63000 | AO51: =SUM(O51:Z51) -> 72000 | AP51: =SUM(AA51:AL51) -> 72000
B52: (ИЭ) Привязка карты и списания с карты | C52: =BaaS.3!D123 -> 15000 | D52: =BaaS.3!E123 -> 16000 | E52: =BaaS.3!F123 -> 17000 | F52: =BaaS.3!G123 -> 18000 | G52: =BaaS.3!H123 -> 19000 | H52: =BaaS.3!I123 -> 20000 | I52: =BaaS.3!J123 -> 20000 | J52: =BaaS.3!K123 -> 22000 | ... AL52: =BaaS.3!AM123 -> 30000 | AN52: =SUM(C52:N52) -> 255000 | AO52: =SUM(O52:Z52) -> 360000 | AP52: =SUM(AA52:AL52) -> 360000
B53: (ИЭ) QR-генерация | C53: =BaaS.3!D136 -> 150 | D53: =BaaS.3!E136 -> 160 | E53: =BaaS.3!F136 -> 170 | F53: =BaaS.3!G136 -> 180 | G53: =BaaS.3!H136 -> 190 | H53: =BaaS.3!I136 -> 200 | I53: =BaaS.3!J136 -> 200 | J53: =BaaS.3!K136 -> 220 | ... AL53: =BaaS.3!AM136 -> 300 | AN53: =SUM(C53:N53) -> 2550 | AO53: =SUM(O53:Z53) -> 3600 | AP53: =SUM(AA53:AL53) -> 3600
B54: (ИЭ) Переход в МП DCB + платежи из него | C54: =BaaS.3!D150 -> 37.5 | D54: =BaaS.3!E150 -> 40 | E54: =BaaS.3!F150 -> 42.5 | F54: =BaaS.3!G150 -> 45 | G54: =BaaS.3!H150 -> 47.5 | H54: =BaaS.3!I150 -> 50 | I54: =BaaS.3!J150 -> 50 | J54: =BaaS.3!K150 -> 55 | ... AL54: =BaaS.3!AM150 -> 75 | AN54: =SUM(C54:N54) -> 637.5 | AO54: =SUM(O54:Z54) -> 900 | AP54: =SUM(AA54:AL54) -> 900
B55: Продажа страховых полисов | C55: =BaaS.3!D161 -> 28 | D55: =BaaS.3!E161 -> 28 | E55: =BaaS.3!F161 -> 42 | F55: =BaaS.3!G161 -> 42 | G55: =BaaS.3!H161 -> 42 | H55: =BaaS.3!I161 -> 42 | I55: =BaaS.3!J161 -> 56 | J55: =BaaS.3!K161 -> 56 | ... AL55: =BaaS.3!AM161 -> 84 | AN55: =SUM(C55:N55) -> 630 | AO55: =SUM(O55:Z55) -> 1008 | AP55: =SUM(AA55:AL55) -> 1008
AN56: =SUM(C56:N56) -> 0 | AO56: =SUM(O56:Z56) -> 0 | AP56: =SUM(AA56:AL56) -> 0
B57: от поставщиков услуг | C57: =SUM(C58:C60) -> 15870.098 | D57: =SUM(D58:D60) -> 15870.098 | E57: =SUM(E58:E60) -> 17401.961 | F57: =SUM(F58:F60) -> 18431.373 | G57: =SUM(G58:G60) -> 18431.373 | H57: =SUM(H58:H60) -> 19963.235 | I57: =SUM(I58:I60) -> 20992.647 | J57: =SUM(J58:J60) -> 20992.647 | ... AL57: =SUM(AL58:AL60) -> 30710.784 | AN57: =SUM(C57:N57) -> 251360.29 | AO57: =SUM(O57:Z57) -> 368529.41 | AP57: =SUM(AA57:AL57) -> 368529.41
B58: QR прием / оплата | C58: =BaaS.3!D36 -> 15870.098 | D58: =BaaS.3!E36 -> 15870.098 | E58: =BaaS.3!F36 -> 17401.961 | F58: =BaaS.3!G36 -> 18431.373 | G58: =BaaS.3!H36 -> 18431.373 | H58: =BaaS.3!I36 -> 19963.235 | I58: =BaaS.3!J36 -> 20992.647 | J58: =BaaS.3!K36 -> 20992.647 | ... AL58: =BaaS.3!AM36 -> 30710.784
B61: Комиссионные расходы | C61: =C62+C73 -> -12254.722 | D61: =D62+D73 -> -12507.197 | E61: =E62+E73 -> -13750.772 | F61: =F62+F73 -> -14157.746 | G61: =G62+G73 -> -14459.621 | H61: =H62+H73 -> -15646.596 | I61: =I62+I73 -> -15905.896 | J61: =J62+J73 -> -16459.346 | ... AL61: =AL62+AL73 -> -23571.444 | AN61: =SUM(C61:N61) -> -196251.77 | AO61: =SUM(O61:Z61) -> -282884.33 | AP61: =SUM(AA61:AL61) -> -282857.33
B62: партнерам BaaS | C62: =SUM(C63:C72) -> -1452.1471 | D62: =SUM(D63:D72) -> -1498.0569 | E62: =SUM(E63:E72) -> -1548.1667 | F62: =SUM(F63:F72) -> -1749.1765 | G62: =SUM(G63:G72) -> -1795.0863 | H62: =SUM(H63:H72) -> -1837.9961 | I62: =SUM(I63:I72) -> -1997.2961 | J62: =SUM(J63:J72) -> -2088.8157 | ... AL62: =SUM(AL63:AL72) -> -2765.0941 | AN62: =SUM(C62:N62) -> -23899 | AO62: =SUM(O62:Z62) -> -33208.129 | AP62: =SUM(AA62:AL62) -> -33181.129
B63: Потребительский кредит | C63: =BaaS.1!D30 -> 0 | D63: =BaaS.1!E30 -> 0 | E63: =BaaS.1!F30 -> 0 | F63: =BaaS.1!G30 -> 0 | G63: =BaaS.1!H30 -> 0 | H63: =BaaS.1!I30 -> 0 | I63: =BaaS.1!J30 -> 0 | J63: =BaaS.1!K30 -> 0 | ... AL63: =BaaS.1!AM30 -> 0 | AN63: =SUM(C63:N63) -> 0 | AO63: =SUM(O63:Z63) -> 0 | AP63: =SUM(AA63:AL63) -> 0
B64: Рассрочка (BNPL) | C64: =BaaS.1!D52 -> -15 | D64: =BaaS.1!E52 -> -16 | E64: =BaaS.1!F52 -> -17 | F64: =BaaS.1!G52 -> -18 | G64: =BaaS.1!H52 -> -19 | H64: =BaaS.1!I52 -> -20 | I64: =BaaS.1!J52 -> -20 | J64: =BaaS.1!K52 -> -22 | ... AL64: =BaaS.1!AM52 -> -30 | AN64: =SUM(C64:N64) -> -255 | AO64: =SUM(O64:Z64) -> -360 | AP64: =SUM(AA64:AL64) -> -360
B65: Факторинг | C65: =BaaS.1!D74 -> -15 | D65: =BaaS.1!E74 -> -16 | E65: =BaaS.1!F74 -> -17 | F65: =BaaS.1!G74 -> -18 | G65: =BaaS.1!H74 -> -19 | H65: =BaaS.1!I74 -> -20 | I65: =BaaS.1!J74 -> -20 | J65: =BaaS.1!K74 -> -22 | ... AL65: =BaaS.1!AM74 -> -30 | AN65: =SUM(C65:N65) -> -255 | AO65: =SUM(O65:Z65) -> -360 | AP65: =SUM(AA65:AL65) -> -360
B66: Кредитная линия для ИП | C66: =BaaS.1!D100 -> -15 | D66: =BaaS.1!E100 -> -16 | E66: =BaaS.1!F100 -> -17 | F66: =BaaS.1!G100 -> -18 | G66: =BaaS.1!H100 -> -19 | H66: =BaaS.1!I100 -> -20 | I66: =BaaS.1!J100 -> -20 | J66: =BaaS.1!K100 -> -22 | ... AL66: =BaaS.1!AM100 -> -30 | AN66: =SUM(C66:N66) -> -255 | AO66: =SUM(O66:Z66) -> -360 | AP66: =SUM(AA66:AL66) -> -360
B67: Гарантии | C67: =BaaS.1!D117 -> -0.14705882 | D67: =BaaS.1!E117 -> -0.15686275 | E67: =BaaS.1!F117 -> -0.16666667 | F67: =BaaS.1!G117 -> -0.17647059 | G67: =BaaS.1!H117 -> -0.18627451 | H67: =BaaS.1!I117 -> -0.19607843 | I67: =BaaS.1!J117 -> -0.19607843 | J67: =BaaS.1!K117 -> -0.21568627 | ... AL67: =BaaS.1!AM117 -> -0.29411765 | AN67: =SUM(C67:N67) -> -2.5 | AO67: =SUM(O67:Z67) -> -3.5294118 | AP67: =SUM(AA67:AL67) -> -3.5294118
B68: Онлайн депозиты | C68: =BaaS.2!D12 -> -643.5 | D68: =BaaS.2!E12 -> -686.4 | E68: =BaaS.2!F12 -> -729.3 | F68: =BaaS.2!G12 -> -772.2 | G68: =BaaS.2!H12 -> -815.1 | H68: =BaaS.2!I12 -> -855 | I68: =BaaS.2!J12 -> -855 | J68: =BaaS.2!K12 -> -940.5 | ... AL68: =BaaS.2!AM12 -> -1269 | AN68: =SUM(C68:N68) -> -10914 | AO68: =SUM(O68:Z68) -> -15255 | AP68: =SUM(AA68:AL68) -> -15228
B69: QR прием / оплата | C69: =BaaS.3!D42 -> -750 | D69: =BaaS.3!E42 -> -750 | E69: =BaaS.3!F42 -> -750 | F69: =BaaS.3!G42 -> -900 | G69: =BaaS.3!H42 -> -900 | H69: =BaaS.3!I42 -> -900 | I69: =BaaS.3!J42 -> -1050 | J69: =BaaS.3!K42 -> -1050 | ... AL69: =BaaS.3!AM42 -> -1350
B70: Онлайн конвертация | C70: =BaaS.3!D102 -> -5.1 | D70: =BaaS.3!E102 -> -5.1 | E70: =BaaS.3!F102 -> -5.1 | F70: =BaaS.3!G102 -> -10.2 | G70: =BaaS.3!H102 -> -10.2 | H70: =BaaS.3!I102 -> -10.2 | I70: =BaaS.3!J102 -> -15.3 | J70: =BaaS.3!K102 -> -15.3 | ... AL70: =BaaS.3!AM102 -> -30.6 | AN70: =SUM(C70:N70) -> -178.5 | AO70: =SUM(O70:Z70) -> -367.2 | AP70: =SUM(AA70:AL70) -> -367.2
B71: Продажа страховых полисов | C71: =BaaS.3!D163 -> -8.4 | D71: =BaaS.3!E163 -> -8.4 | E71: =BaaS.3!F163 -> -12.6 | F71: =BaaS.3!G163 -> -12.6 | G71: =BaaS.3!H163 -> -12.6 | H71: =BaaS.3!I163 -> -12.6 | I71: =BaaS.3!J163 -> -16.8 | J71: =BaaS.3!K163 -> -16.8 | ... AL71: =BaaS.3!AM163 -> -25.2 | AN71: =SUM(C71:N71) -> -189 | AO71: =SUM(O71:Z71) -> -302.4 | AP71: =SUM(AA71:AL71) -> -302.4
AN72: =SUM(C72:N72) -> 0 | AO72: =SUM(O72:Z72) -> 0 | AP72: =SUM(AA72:AL72) -> 0
B73: поставщикам услуг | C73: =SUM(C74:C81) -> -10802.575 | D73: =SUM(D74:D81) -> -11009.14 | E73: =SUM(E74:E81) -> -12202.605 | F73: =SUM(F74:F81) -> -12408.57 | G73: =SUM(G74:G81) -> -12664.535 | H73: =SUM(H74:H81) -> -13808.6 | I73: =SUM(I74:I81) -> -13908.6 | J73: =SUM(J74:J81) -> -14370.53 | ... AL73: =SUM(AL74:AL81) -> -20806.35 | AN73: =SUM(C73:N73) -> -172352.77 | AO73: =SUM(O73:Z73) -> -249676.2 | AP73: =SUM(AA73:AL73) -> -249676.2
B74: DCB ID / DCB BIO | C74: =BaaS.3!D16 -> -36.975 | D74: =BaaS.3!E16 -> -39.44 | E74: =BaaS.3!F16 -> -41.905 | F74: =BaaS.3!G16 -> -44.37 | G74: =BaaS.3!H16 -> -46.835 | H74: =BaaS.3!I16 -> -49.3 | I74: =BaaS.3!J16 -> -49.3 | J74: =BaaS.3!K16 -> -54.23 | ... AL74: =BaaS.3!AM16 -> -73.95 | AN74: =SUM(C74:N74) -> -628.575 | AO74: =SUM(O74:Z74) -> -887.4 | AP74: =SUM(AA74:AL74) -> -887.4
B75: QR прием / оплата | C75: =BaaS.3!D38+BaaS.3!D40 -> -6562.5 | D75: =BaaS.3!E38+BaaS.3!E40 -> -6562.5 | E75: =BaaS.3!F38+BaaS.3!F40 -> -7500 | F75: =BaaS.3!G38+BaaS.3!G40 -> -7500 | G75: =BaaS.3!H38+BaaS.3!H40 -> -7500 | H75: =BaaS.3!I38+BaaS.3!I40 -> -8437.5 | I75: =BaaS.3!J38+BaaS.3!J40 -> -8437.5 | J75: =BaaS.3!K38+BaaS.3!K40 -> -8437.5 | ... AL75: =BaaS.3!AM38+BaaS.3!AM40 -> -13125
B76: Кошельки | C76: =BaaS.3!D56 -> 0 | D76: =BaaS.3!E56 -> 0 | E76: =BaaS.3!F56 -> 0 | F76: =BaaS.3!G56 -> 0 | G76: =BaaS.3!H56 -> 0 | H76: =BaaS.3!I56 -> 0 | I76: =BaaS.3!J56 -> 0 | J76: =BaaS.3!K56 -> 0 | ... AL76: =BaaS.3!AM56 -> 0
B77: Виртуальные карты | C77: =BaaS.3!D90 -> -0.6 | D77: =BaaS.3!E90 -> -1.2 | E77: =BaaS.3!F90 -> -1.2 | F77: =BaaS.3!G90 -> -1.2 | G77: =BaaS.3!H90 -> -1.2 | H77: =BaaS.3!I90 -> -1.8 | I77: =BaaS.3!J90 -> -1.8 | J77: =BaaS.3!K90 -> -1.8 | ... AL77: =BaaS.3!AM90 -> -2.4
B78: Онлайн переводы | C78: =BaaS.3!D113 -> -1150 | D78: =BaaS.3!E113 -> -1150 | E78: =BaaS.3!F113 -> -1200 | F78: =BaaS.3!G113 -> -1200 | G78: =BaaS.3!H113 -> -1250 | H78: =BaaS.3!I113 -> -1250 | I78: =BaaS.3!J113 -> -1350 | J78: =BaaS.3!K113 -> -1400 | ... AL78: =BaaS.3!AM113 -> -1500
B79: (ИЭ) Привязка карты и списания с карты | C79: =BaaS.3!D125+BaaS.3!D127 -> -3007.5 | D79: =BaaS.3!E125+BaaS.3!E127 -> -3208 | E79: =BaaS.3!F125+BaaS.3!F127 -> -3408.5 | F79: =BaaS.3!G125+BaaS.3!G127 -> -3609 | G79: =BaaS.3!H125+BaaS.3!H127 -> -3809.5 | H79: =BaaS.3!I125+BaaS.3!I127 -> -4010 | I79: =BaaS.3!J125+BaaS.3!J127 -> -4010 | J79: =BaaS.3!K125+BaaS.3!K127 -> -4411 | ... AL79: =BaaS.3!AM125+BaaS.3!AM127 -> -6015 | AN79: =SUM(C79:N79) -> -51127.5 | AO79: =SUM(O79:Z79) -> -72180 | AP79: =SUM(AA79:AL79) -> -72180
B80: (ИЭ) QR-генерация | C80: =BaaS.3!D141 -> -45 | D80: =BaaS.3!E141 -> -48 | E80: =BaaS.3!F141 -> -51 | F80: =BaaS.3!G141 -> -54 | G80: =BaaS.3!H141 -> -57 | H80: =BaaS.3!I141 -> -60 | I80: =BaaS.3!J141 -> -60 | J80: =BaaS.3!K141 -> -66 | ... AL80: =BaaS.3!AM141 -> -90 | AN80: =SUM(C80:N80) -> -765 | AO80: =SUM(O80:Z80) -> -1080 | AP80: =SUM(AA80:AL80) -> -1080
B82: Прочие доходы | AN82: =SUM(C82:N82) -> 0 | AO82: =SUM(O82:Z82) -> 0 | AP82: =SUM(AA82:AL82) -> 0
B83: ЧИСТЫЙ НЕПРОЦЕНТНЫЙ ДОХОД | C83: =C37+C40+C61+C82 -> 23612.307 | D83: =D37+D40+D61+D82 -> 24433.823 | E83: =E37+E40+E61+E82 -> 25996.323 | F83: =F37+F40+F61+F82 -> 27687.258 | G83: =G37+G40+G61+G82 -> 28631.071 | H83: =H37+H40+H61+H82 -> 30018.48 | I83: =I37+I40+I61+I82 -> 31235.54 | J83: =J37+J40+J61+J82 -> 32939.618 | ... AL83: =AL37+AL40+AL61+AL82 -> 44357.082 | AN83: =SUM(C83:N83) -> 382109.53 | AO83: =SUM(O83:Z83) -> 531942.95 | AP83: =SUM(AA83:AL83) -> 532219.48
AN84: =SUM(C84:N84) -> 0 | AO84: =SUM(O84:Z84) -> 0 | AP84: =SUM(AA84:AL84) -> 0
B85: Операционные расходы | C85: =C86+C106+C113+C114 -> -1486.0945 | D85: =D86+D106+D113+D114 -> -1398.0729 | E85: =E86+E106+E113+E114 -> -1547.5286 | F85: =F86+F106+F113+F114 -> -1637.8196 | G85: =G86+G106+G113+G114 -> -1713.5211 | H85: =H86+H106+H113+H114 -> -1739.223 | I85: =I86+I106+I113+I114 -> -1763.642 | J85: =J86+J106+J113+J114 -> -1788.1603 | ... AL85: =AL86+AL106+AL113+AL114 -> -2312.5201 | AN85: =SUM(C85:N85) -> -20696.553 | AO85: =SUM(O85:Z85) -> -25506.591 | AP85: =SUM(AA85:AL85) -> -27321.064
B86: Расходы на персонал | C86: =SUM(C87:C105) -> -1351.0945 | D86: =SUM(D87:D105) -> -1344.7562 | E86: =SUM(E87:E105) -> -1361.4107 | F86: =SUM(F87:F105) -> -1377.3972 | G86: =SUM(G87:G105) -> -1393.0653 | H86: =SUM(H87:H105) -> -1408.4098 | I86: =SUM(I87:I105) -> -1422.6539 | J86: =SUM(J87:J105) -> -1437.4503 | ... AL86: =SUM(AL87:AL105) -> -1694.7669 | AN86: =SUM(C86:N86) -> -17013.4 | AO86: =SUM(O86:Z86) -> -19077.272 | AP86: =SUM(AA86:AL86) -> -20085.29
B87: Потребительский кредит | C87: =-'OPEX+CAPEX'!E19 -> -11.41875 | D87: =-'OPEX+CAPEX'!F19 -> -22.647188 | E87: =-'OPEX+CAPEX'!G19 -> -33.701172 | F87: =-'OPEX+CAPEX'!H19 -> -44.595241 | G87: =-'OPEX+CAPEX'!I19 -> -55.342721 | H87: =-'OPEX+CAPEX'!J19 -> -65.955827 | I87: =-'OPEX+CAPEX'!K19 -> -75.684508 | J87: =-'OPEX+CAPEX'!L19 -> -86.124966 | ... AL87: =-'OPEX+CAPEX'!AN19 -> -256.68404 | AN87: =SUM(C87:N87) -> -856.63528 | AO87: =SUM(O87:Z87) -> -2289.5326 | AP87: =SUM(AA87:AL87) -> -2936.9326
B88: Рассрочка (BNPL) | C88: =-'OPEX+CAPEX'!E25 -> -2.5375 | D88: =-'OPEX+CAPEX'!F25 -> -4.1234375 | E88: =-'OPEX+CAPEX'!G25 -> -5.1247549 | F88: =-'OPEX+CAPEX'!H25 -> -5.7641975 | G88: =-'OPEX+CAPEX'!I25 -> -6.1780458 | H88: =-'OPEX+CAPEX'!J25 -> -6.4502623 | I88: =-'OPEX+CAPEX'!K25 -> -6.8376749 | J88: =-'OPEX+CAPEX'!L25 -> -6.6815454 | ... AL88: =-'OPEX+CAPEX'!AN25 -> -7.6124436 | AN88: =SUM(C88:N88) -> -70.223473 | AO88: =SUM(O88:Z88) -> -89.465913 | AP88: =SUM(AA88:AL88) -> -91.335479
B89: Факторинг | C89: =-'OPEX+CAPEX'!E27 -> -0.380625 | D89: =-'OPEX+CAPEX'!F27 -> -0.65975 | E89: =-'OPEX+CAPEX'!G27 -> -0.87120833 | F89: =-'OPEX+CAPEX'!H27 -> -1.0375556 | G89: =-'OPEX+CAPEX'!I27 -> -1.1738287 | H89: =-'OPEX+CAPEX'!J27 -> -1.2900525 | I89: =-'OPEX+CAPEX'!K27 -> -1.367535 | J89: =-'OPEX+CAPEX'!L27 -> -1.46994 | ... AL89: =-'OPEX+CAPEX'!AN27 -> -2.2837331 | AN89: =SUM(C89:N89) -> -15.413991 | AO89: =SUM(O89:Z89) -> -26.839774 | AP89: =SUM(AA89:AL89) -> -27.400644
B90: Кредитная линия для ИП | C90: =-'OPEX+CAPEX'!E29 -> -0.380625 | D90: =-'OPEX+CAPEX'!F29 -> -0.786625 | E90: =-'OPEX+CAPEX'!G29 -> -1.218 | F90: =-'OPEX+CAPEX'!H29 -> -1.67475 | G90: =-'OPEX+CAPEX'!I29 -> -2.156875 | H90: =-'OPEX+CAPEX'!J29 -> -2.664375 | I90: =-'OPEX+CAPEX'!K29 -> -3.171875 | J90: =-'OPEX+CAPEX'!L29 -> -3.730125 | ... AL90: =-'OPEX+CAPEX'!AN29 -> -24.740625 | AN90: =SUM(C90:N90) -> -37.30125 | AO90: =SUM(O90:Z90) -> -137.025 | AP90: =SUM(AA90:AL90) -> -246.645
B91: Гарантии | C91: =-'OPEX+CAPEX'!E31 -> -0.380625 | D91: =-'OPEX+CAPEX'!F31 -> -0.406 | E91: =-'OPEX+CAPEX'!G31 -> -0.431375 | F91: =-'OPEX+CAPEX'!H31 -> -0.45675 | G91: =-'OPEX+CAPEX'!I31 -> -0.482125 | H91: =-'OPEX+CAPEX'!J31 -> -0.5075 | I91: =-'OPEX+CAPEX'!K31 -> -0.5075 | J91: =-'OPEX+CAPEX'!L31 -> -0.55825 | ... AL91: =-'OPEX+CAPEX'!AN31 -> -0.76125 | AN91: =SUM(C91:N91) -> -6.470625 | AO91: =SUM(O91:Z91) -> -9.135 | AP91: =SUM(AA91:AL91) -> -9.135
B92: Продажа чужих кредитов | C92: =-'OPEX+CAPEX'!E33 -> -47.619048 | D92: =-'OPEX+CAPEX'!F33 -> -23.809524 | E92: =-'OPEX+CAPEX'!G33 -> -23.809524 | F92: =-'OPEX+CAPEX'!H33 -> -23.809524 | G92: =-'OPEX+CAPEX'!I33 -> -23.809524 | H92: =-'OPEX+CAPEX'!J33 -> -23.809524 | I92: =-'OPEX+CAPEX'!K33 -> -23.809524 | J92: =-'OPEX+CAPEX'!L33 -> -23.809524 | ... AL92: =-'OPEX+CAPEX'!AN33 -> -23.809524 | AN92: =SUM(C92:N92) -> -309.52381 | AO92: =SUM(O92:Z92) -> -285.71429 | AP92: =SUM(AA92:AL92) -> -285.71429
B93: Онлайн депозиты | C93: =-'OPEX+CAPEX'!E38 -> -103.93214 | D93: =-'OPEX+CAPEX'!F38 -> -107.81022 | E93: =-'OPEX+CAPEX'!G38 -> -111.65004 | F93: =-'OPEX+CAPEX'!H38 -> -115.45454 | G93: =-'OPEX+CAPEX'!I38 -> -119.22643 | H93: =-'OPEX+CAPEX'!J38 -> -122.96824 | I93: =-'OPEX+CAPEX'!K38 -> -126.42014 | J93: =-'OPEX+CAPEX'!L38 -> -130.12966 | ... AL93: =-'OPEX+CAPEX'!AN38 -> -193.58739 | AN93: =SUM(C93:N93) -> -1499.661 | AO93: =SUM(O93:Z93) -> -2016.1046 | AP93: =SUM(AA93:AL93) -> -2264.6716
B94: DCB ID / DCB BIO | C94: =-'OPEX+CAPEX'!E50 -> -100 | D94: =-'OPEX+CAPEX'!F50 -> -100 | E94: =-'OPEX+CAPEX'!G50 -> -100 | F94: =-'OPEX+CAPEX'!H50 -> -100 | G94: =-'OPEX+CAPEX'!I50 -> -100 | H94: =-'OPEX+CAPEX'!J50 -> -100 | I94: =-'OPEX+CAPEX'!K50 -> -100 | J94: =-'OPEX+CAPEX'!L50 -> -100 | ... AL94: =-'OPEX+CAPEX'!AN50 -> -100 | AN94: =SUM(C94:N94) -> -1200 | AO94: =SUM(O94:Z94) -> -1200 | AP94: =SUM(AA94:AL94) -> -1200
B95: QR прием / оплата | C95: =-'OPEX+CAPEX'!E60 -> -207.14286 | D95: =-'OPEX+CAPEX'!F60 -> -207.14286 | E95: =-'OPEX+CAPEX'!G60 -> -207.14286 | F95: =-'OPEX+CAPEX'!H60 -> -207.14286 | G95: =-'OPEX+CAPEX'!I60 -> -207.14286 | H95: =-'OPEX+CAPEX'!J60 -> -207.14286 | I95: =-'OPEX+CAPEX'!K60 -> -207.14286 | J95: =-'OPEX+CAPEX'!L60 -> -207.14286 | ... AL95: =-'OPEX+CAPEX'!AN60 -> -207.14286 | AN95: =SUM(C95:N95) -> -2485.7143 | AO95: =SUM(O95:Z95) -> -2485.7143 | AP95: =SUM(AA95:AL95) -> -2485.7143
B96: Кошельки | C96: =-'OPEX+CAPEX'!E69 -> -107.14286 | D96: =-'OPEX+CAPEX'!F69 -> -107.14286 | E96: =-'OPEX+CAPEX'!G69 -> -107.14286 | F96: =-'OPEX+CAPEX'!H69 -> -107.14286 | G96: =-'OPEX+CAPEX'!I69 -> -107.14286 | H96: =-'OPEX+CAPEX'!J69 -> -107.14286 | I96: =-'OPEX+CAPEX'!K69 -> -107.14286 | J96: =-'OPEX+CAPEX'!L69 -> -107.14286 | ... AL96: =-'OPEX+CAPEX'!AN69 -> -107.14286 | AN96: =SUM(C96:N96) -> -1285.7143 | AO96: =SUM(O96:Z96) -> -1285.7143 | AP96: =SUM(AA96:AL96) -> -1285.7143
B97: Расчетный счет (ФЛ) | C97: =-'OPEX+CAPEX'!E75 -> -100.09111 | D97: =-'OPEX+CAPEX'!F75 -> -100.09111 | E97: =-'OPEX+CAPEX'!G75 -> -100.18222 | F97: =-'OPEX+CAPEX'!H75 -> -100.18222 | G97: =-'OPEX+CAPEX'!I75 -> -100.27333 | H97: =-'OPEX+CAPEX'!J75 -> -100.27333 | I97: =-'OPEX+CAPEX'!K75 -> -100.36444 | J97: =-'OPEX+CAPEX'!L75 -> -100.45556 | ... AL97: =-'OPEX+CAPEX'!AN75 -> -100.72889 | AN97: =SUM(C97:N97) -> -1204.5556 | AO97: =SUM(O97:Z97) -> -1208.7467 | AP97: =SUM(AA97:AL97) -> -1208.7467
B98: Виртуальные карты | C98: =-'OPEX+CAPEX'!E87 -> -107.21119 | D98: =-'OPEX+CAPEX'!F87 -> -107.27952 | E98: =-'OPEX+CAPEX'!G87 -> -107.27952 | F98: =-'OPEX+CAPEX'!H87 -> -107.27952 | G98: =-'OPEX+CAPEX'!I87 -> -107.27952 | H98: =-'OPEX+CAPEX'!J87 -> -107.34786 | I98: =-'OPEX+CAPEX'!K87 -> -107.34786 | J98: =-'OPEX+CAPEX'!L87 -> -107.34786 | ... AL98: =-'OPEX+CAPEX'!AN87 -> -107.41619 | AN98: =SUM(C98:N98) -> -1287.901 | AO98: =SUM(O98:Z98) -> -1288.9943 | AP98: =SUM(AA98:AL98) -> -1288.9943
B99: Онлайн конвертация | C99: =-'OPEX+CAPEX'!E95 -> -107.14286 | D99: =-'OPEX+CAPEX'!F95 -> -107.14286 | E99: =-'OPEX+CAPEX'!G95 -> -107.14286 | F99: =-'OPEX+CAPEX'!H95 -> -107.14286 | G99: =-'OPEX+CAPEX'!I95 -> -107.14286 | H99: =-'OPEX+CAPEX'!J95 -> -107.14286 | I99: =-'OPEX+CAPEX'!K95 -> -107.14286 | J99: =-'OPEX+CAPEX'!L95 -> -107.14286 | ... AL99: =-'OPEX+CAPEX'!AN95 -> -107.14286 | AN99: =SUM(C99:N99) -> -1285.7143 | AO99: =SUM(O99:Z99) -> -1285.7143 | AP99: =SUM(AA99:AL99) -> -1285.7143
B100: Онлайн переводы | C100: =-'OPEX+CAPEX'!E98 -> -107.14286 | D100: =-'OPEX+CAPEX'!F98 -> -107.14286 | E100: =-'OPEX+CAPEX'!G98 -> -107.14286 | F100: =-'OPEX+CAPEX'!H98 -> -107.14286 | G100: =-'OPEX+CAPEX'!I98 -> -107.14286 | H100: =-'OPEX+CAPEX'!J98 -> -107.14286 | I100: =-'OPEX+CAPEX'!K98 -> -107.14286 | J100: =-'OPEX+CAPEX'!L98 -> -107.14286 | ... AL100: =-'OPEX+CAPEX'!AN98 -> -107.14286 | AN100: =SUM(C100:N100) -> -1285.7143 | AO100: =SUM(O100:Z100) -> -1285.7143 | AP100: =SUM(AA100:AL100) -> -1285.7143
B101: (ИЭ) Привязка карты и списания с карты | C101: =-'OPEX+CAPEX'!E104 -> -27.142857 | D101: =-'OPEX+CAPEX'!F104 -> -27.142857 | E101: =-'OPEX+CAPEX'!G104 -> -27.142857 | F101: =-'OPEX+CAPEX'!H104 -> -27.142857 | G101: =-'OPEX+CAPEX'!I104 -> -27.142857 | H101: =-'OPEX+CAPEX'!J104 -> -27.142857 | I101: =-'OPEX+CAPEX'!K104 -> -27.142857 | J101: =-'OPEX+CAPEX'!L104 -> -27.142857 | ... AL101: =-'OPEX+CAPEX'!AN104 -> -27.142857 | AN101: =SUM(C101:N101) -> -325.71429 | AO101: =SUM(O101:Z101) -> -325.71429 | AP101: =SUM(AA101:AL101) -> -325.71429
B102: (ИЭ) QR-генерация | C102: =-'OPEX+CAPEX'!E107 -> -107.14286 | D102: =-'OPEX+CAPEX'!F107 -> -107.14286 | E102: =-'OPEX+CAPEX'!G107 -> -107.14286 | F102: =-'OPEX+CAPEX'!H107 -> -107.14286 | G102: =-'OPEX+CAPEX'!I107 -> -107.14286 | H102: =-'OPEX+CAPEX'!J107 -> -107.14286 | I102: =-'OPEX+CAPEX'!K107 -> -107.14286 | J102: =-'OPEX+CAPEX'!L107 -> -107.14286 | ... AL102: =-'OPEX+CAPEX'!AN107 -> -107.14286 | AN102: =SUM(C102:N102) -> -1285.7143 | AO102: =SUM(O102:Z102) -> -1285.7143 | AP102: =SUM(AA102:AL102) -> -1285.7143
B103: (ИЭ) Переход в МП DCB + платежи из него | C103: =-'OPEX+CAPEX'!E110 -> -107.14286 | D103: =-'OPEX+CAPEX'!F110 -> -107.14286 | E103: =-'OPEX+CAPEX'!G110 -> -107.14286 | F103: =-'OPEX+CAPEX'!H110 -> -107.14286 | G103: =-'OPEX+CAPEX'!I110 -> -107.14286 | H103: =-'OPEX+CAPEX'!J110 -> -107.14286 | I103: =-'OPEX+CAPEX'!K110 -> -107.14286 | J103: =-'OPEX+CAPEX'!L110 -> -107.14286 | ... AL103: =-'OPEX+CAPEX'!AN110 -> -107.14286 | AN103: =SUM(C103:N103) -> -1285.7143 | AO103: =SUM(O103:Z103) -> -1285.7143 | AP103: =SUM(AA103:AL103) -> -1285.7143
B104: Продажа страховых полисов | C104: =-'OPEX+CAPEX'!E113 -> -107.14286 | D104: =-'OPEX+CAPEX'!F113 -> -107.14286 | E104: =-'OPEX+CAPEX'!G113 -> -107.14286 | F104: =-'OPEX+CAPEX'!H113 -> -107.14286 | G104: =-'OPEX+CAPEX'!I113 -> -107.14286 | H104: =-'OPEX+CAPEX'!J113 -> -107.14286 | I104: =-'OPEX+CAPEX'!K113 -> -107.14286 | J104: =-'OPEX+CAPEX'!L113 -> -107.14286 | ... AL104: =-'OPEX+CAPEX'!AN113 -> -107.14286 | AN104: =SUM(C104:N104) -> -1285.7143 | AO104: =SUM(O104:Z104) -> -1285.7143 | AP104: =SUM(AA104:AL104) -> -1285.7143
AN105: =SUM(C105:N105) -> 0 | AO105: =SUM(O105:Z105) -> 0 | AP105: =SUM(AA105:AL105) -> 0
B106: Амортизационные отчисления | C106: =SUM(C107:C112) -> 0 | D106: =SUM(D107:D112) -> -42.5 | E106: =SUM(E107:E112) -> -170 | F106: =SUM(F107:F112) -> -233.75 | G106: =SUM(G107:G112) -> -283.33333 | H106: =SUM(H107:H112) -> -283.33333 | I106: =SUM(I107:I112) -> -283.33333 | J106: =SUM(J107:J112) -> -283.33333 | ... AL106: =SUM(AL107:AL112) -> -332.91667 | AN106: =SUM(C106:N106) -> -2911.25 | AO106: =SUM(O106:Z106) -> -3995 | AP106: =SUM(AA106:AL106) -> -3995
B107: Онлайн депозиты | C107: =-'OPEX+CAPEX'!E45 -> 0 | D107: =-'OPEX+CAPEX'!F45 -> 0 | E107: =-'OPEX+CAPEX'!G45 -> 0 | F107: =-'OPEX+CAPEX'!H45 -> 0 | G107: =-'OPEX+CAPEX'!I45 -> -24.791667 | H107: =-'OPEX+CAPEX'!J45 -> -24.791667 | I107: =-'OPEX+CAPEX'!K45 -> -24.791667 | J107: =-'OPEX+CAPEX'!L45 -> -24.791667 | ... AL107: =-'OPEX+CAPEX'!AN45 -> -24.791667 | AN107: =SUM(C107:N107) -> -198.33333 | AO107: =SUM(O107:Z107) -> -297.5 | AP107: =SUM(AA107:AL107) -> -297.5
B108: DCB ID / DCB BIO | C108: =-'OPEX+CAPEX'!E52 -> 0 | D108: =-'OPEX+CAPEX'!F52 -> -42.5 | E108: =-'OPEX+CAPEX'!G52 -> -106.25 | F108: =-'OPEX+CAPEX'!H52 -> -170 | G108: =-'OPEX+CAPEX'!I52 -> -170 | H108: =-'OPEX+CAPEX'!J52 -> -170 | I108: =-'OPEX+CAPEX'!K52 -> -170 | J108: =-'OPEX+CAPEX'!L52 -> -170 | ... AL108: =-'OPEX+CAPEX'!AN52 -> -170 | AN108: =SUM(C108:N108) -> -1678.75 | AO108: =SUM(O108:Z108) -> -2040 | AP108: =SUM(AA108:AL108) -> -2040
...

Sheet OPEX+CAPEX
A1: Операционные расходы и Инвестиции в BaaS
A2: (тыс. сом)
E4: 46023 | F4: =E4+31 -> 46054 | G4: =F4+31 -> 46085 | H4: =G4+31 -> 46116 | I4: =H4+31 -> 46147 | J4: =I4+31 -> 46178 | K4: =J4+31 -> 46209 | L4: =K4+31 -> 46240 | M4: =L4+31 -> 46271 | ... AN4: =AM4+31 -> 47108 | AP4: =YEAR(P4) -> 2026 | AQ4: =YEAR(AB4) -> 2027 | AR4: =YEAR(AN4) -> 2028
A5: Продукт BaaS | B5: Вид расхода | C5: Статья расходов | E5: m1 | F5: m2 | G5: m3 | H5: m4 | I5: m5 | J5: m6 | K5: m7 | L5: m8 | M5: m9 | N5: m10 | O5: m11 | P5: m12 | Q5: m13 | R5: m14 | S5: m15 | T5: m16 | U5: m17 | V5: m18 | W5: m19 | X5: m20 | Y5: m21 | Z5: m22 | AA5: m23 | AB5: m24 | AC5: m25 | AD5: m26 | AE5: m27 | AF5: m28 | AG5: m29 | AH5: m30 | AI5: m31 | AJ5: m32 | AK5: m33 | AL5: m34 | AM5: m35 | AN5: m36 | AP5: Y1 | AQ5: Y2 | AR5: Y3
B7: OPEX | C7: Расходы на персонал | D7: тыс.сом | E7: =E19+E25+E27+E29+E31+E33+E38+E50+E60+E69+E75+E87+E95+E98+E113+E104+E107+E110 -> 1351.0945 | F7: =F19+F25+F27+F29+F31+F33+F38+F50+F60+F69+F75+F87+F95+F98+F113+F104+F107+F110 -> 1344.7562 | G7: =G19+G25+G27+G29+G31+G33+G38+G50+G60+G69+G75+G87+G95+G98+G113+G104+G107+G110 -> 1361.4107 | H7: =H19+H25+H27+H29+H31+H33+H38+H50+H60+H69+H75+H87+H95+H98+H113+H104+H107+H110 -> 1377.3972 | I7: =I19+I25+I27+I29+I31+I33+I38+I50+I60+I69+I75+I87+I95+I98+I113+I104+I107+I110 -> 1393.0653 | J7: =J19+J25+J27+J29+J31+J33+J38+J50+J60+J69+J75+J87+J95+J98+J113+J104+J107+J110 -> 1408.4098 | K7: =K19+K25+K27+K29+K31+K33+K38+K50+K60+K69+K75+K87+K95+K98+K113+K104+K107+K110 -> 1422.6539 | L7: =L19+L25+L27+L29+L31+L33+L38+L50+L60+L69+L75+L87+L95+L98+L113+L104+L107+L110 -> 1437.4503 | ... AN7: =AN19+AN25+AN27+AN29+AN31+AN33+AN38+AN50+AN60+AN69+AN75+AN87+AN95+AN98+AN113+AN104+AN107+AN110 -> 1694.7669 | AP7: =SUM(E7:P7) -> 17013.4 | AQ7: =SUM(Q7:AB7) -> 19077.272 | AR7: =SUM(AC7:AN7) -> 20085.29
B8: OPEX | C8: Амортизационные отчисления | D8: тыс сом | E8: =E45+E52+E64+E72+E82+E101 -> 0 | F8: =F45+F52+F64+F72+F82+F101 -> 42.5 | G8: =G45+G52+G64+G72+G82+G101 -> 170 | H8: =H45+H52+H64+H72+H82+H101 -> 233.75 | I8: =I45+I52+I64+I72+I82+I101 -> 283.33333 | J8: =J45+J52+J64+J72+J82+J101 -> 283.33333 | K8: =K45+K52+K64+K72+K82+K101 -> 283.33333 | L8: =L45+L52+L64+L72+L82+L101 -> 283.33333 | ... AN8: =AN45+AN52+AN64+AN72+AN82+AN101 -> 332.91667 | AP8: =SUM(E8:P8) -> 2911.25 | AQ8: =SUM(Q8:AB8) -> 3995 | AR8: =SUM(AC8:AN8) -> 3995
B9: OPEX | C9: Административные расходы | D9: тыс сом | E9: =E46+E53+E65+E83 -> 135 | F9: =F46+F53+F65+F83 -> 0 | G9: =G46+G53+G65+G83 -> 0 | H9: =H46+H53+H65+H83 -> 0 | I9: =I46+I53+I65+I83 -> 0 | J9: =J46+J53+J65+J83 -> 0 | K9: =K46+K53+K65+K83 -> 0 | L9: =L46+L53+L65+L83 -> 0 | ... AN9: =AN46+AN53+AN65+AN83 -> 35.416667 | AP9: =SUM(E9:P9) -> 135 | AQ9: =SUM(Q9:AB9) -> 368.33333 | AR9: =SUM(AC9:AN9) -> 425
B10: OPEX | C10: Итого | D10: тыс сом | E10: =SUM(E7:E9) -> 1486.0945 | F10: =SUM(F7:F9) -> 1387.2562 | G10: =SUM(G7:G9) -> 1531.4107 | H10: =SUM(H7:H9) -> 1611.1472 | I10: =SUM(I7:I9) -> 1676.3986 | J10: =SUM(J7:J9) -> 1691.7432 | K10: =SUM(K7:K9) -> 1705.9873 | L10: =SUM(L7:L9) -> 1720.7836 | ... AN10: =SUM(AN7:AN9) -> 2063.1003 | AP10: =SUM(E10:P10) -> 20059.65 | AQ10: =SUM(Q10:AB10) -> 23440.606 | AR10: =SUM(AC10:AN10) -> 24505.29
B12: CAPEX | C12: Лицензии ПО | D12: тыс сом | E12: =E13*'0'!D27/1000 -> 0 | F12: =F13*'0'!E27/1000 -> 0 | G12: =G13*'0'!F27/1000 -> 3825 | H12: =H13*'0'!G27/1000 -> 0 | I12: =I13*'0'!H27/1000 -> 0 | J12: =J13*'0'!I27/1000 -> 0 | K12: =K13*'0'!J27/1000 -> 0 | L12: =L13*'0'!K27/1000 -> 0 | ... AN12: =AN13*'0'!AM27/1000 -> 0 | AP12: =SUM(E12:P12) -> 3825 | AQ12: =SUM(Q12:AB12) -> 0 | AR12: =SUM(AC12:AN12) -> 0
B13: CAPEX | C13: MinIO * 50% | D13: usd | E13: =E56 -> 0 | F13: =F56 -> 0 | G13: =G56 -> 45000 | H13: =H56 -> 0 | I13: =I56 -> 0 | J13: =J56 -> 0 | K13: =K56 -> 0 | L13: =L56 -> 0 | ... AN13: =AN56 -> 0 | AP13: =SUM(E13:P13) -> 45000 | AQ13: =SUM(Q13:AB13) -> 0 | AR13: =SUM(AC13:AN13) -> 0
B14: CAPEX | C14: Оборудование | D14: тыс сом | E14: =SUM(E15:E16)*'0'!D27/1000 -> 2550 | F14: =SUM(F15:F16)*'0'!E27/1000 -> 7650 | G14: =SUM(G15:G16)*'0'!F27/1000 -> 0 | H14: =SUM(H15:H16)*'0'!G27/1000 -> 2975 | I14: =SUM(I15:I16)*'0'!H27/1000 -> 0 | J14: =SUM(J15:J16)*'0'!I27/1000 -> 0 | K14: =SUM(K15:K16)*'0'!J27/1000 -> 0 | L14: =SUM(L15:L16)*'0'!K27/1000 -> 2975 | ... AN14: =SUM(AN15:AN16)*'0'!AM27/1000 -> 0 | AP14: =SUM(E14:P14) -> 16150 | AQ14: =SUM(Q14:AB14) -> 0 | AR14: =SUM(AC14:AN14) -> 0
B15: CAPEX | C15: Система хранения данных | D15: usd | E15: =E49+E58+E74+E86 -> 30000 | F15: =F49+F58+F74+F86 -> 0 | G15: =G49+G58+G74+G86 -> 0 | H15: =H49+H58+H74+H86 -> 35000 | I15: =I49+I58+I74+I86 -> 0 | J15: =J49+J58+J74+J86 -> 0 | K15: =K49+K58+K74+K86 -> 0 | L15: =L49+L58+L74+L86 -> 35000 | ... AN15: =AN49+AN58+AN74+AN86 -> 0 | AP15: =SUM(E15:P15) -> 100000 | AQ15: =SUM(Q15:AB15) -> 0 | AR15: =SUM(AC15:AN15) -> 0
B16: CAPEX | C16: Сервер | D16: usd | E16: =E59+E68+E103 -> 0 | F16: =F59+F68+F103 -> 90000 | G16: =G59+G68+G103 -> 0 | H16: =H59+H68+H103 -> 0 | I16: =I59+I68+I103 -> 0 | J16: =J59+J68+J103 -> 0 | K16: =K59+K68+K103 -> 0 | L16: =L59+L68+L103 -> 0 | ... AN16: =AN59+AN68+AN103 -> 0 | AP16: =SUM(E16:P16) -> 90000 | AQ16: =SUM(Q16:AB16) -> 0 | AR16: =SUM(AC16:AN16) -> 0
B17: CAPEX | C17: Итого | D17: тыс сом | E17: =E12+E14 -> 2550 | F17: =F12+F14 -> 7650 | G17: =G12+G14 -> 3825 | H17: =H12+H14 -> 2975 | I17: =I12+I14 -> 0 | J17: =J12+J14 -> 0 | K17: =K12+K14 -> 0 | L17: =L12+L14 -> 2975 | ... AN17: =AN12+AN14 -> 0 | AP17: =SUM(E17:P17) -> 19975 | AQ17: =SUM(Q17:AB17) -> 0 | AR17: =SUM(AC17:AN17) -> 0
A19: Потребительский кредит | B19: OPEX | C19: Расходы на персонал | D19: тыс.сом | E19: =E20*E21/1000 -> 11.41875 | F19: =F20*F21/1000 -> 22.647188 | G19: =G20*G21/1000 -> 33.701172 | H19: =H20*H21/1000 -> 44.595241 | I19: =I20*I21/1000 -> 55.342721 | J19: =J20*J21/1000 -> 65.955827 | K19: =K20*K21/1000 -> 75.684508 | L19: =L20*L21/1000 -> 86.124966 | ... AN19: =AN20*AN21/1000 -> 256.68404 | AP19: =SUM(E19:P19) -> 856.63528 | AQ19: =SUM(Q19:AB19) -> 2289.5326 | AR19: =SUM(AC19:AN19) -> 2936.9326
A20: Потребительский кредит | C20: количество кредитов в портфеле | D20: шт | E20: =BaaS.1!D20/BaaS.1!D16 -> 450 | F20: =BaaS.1!E20/BaaS.1!E16 -> 892.5 | G20: =BaaS.1!F20/BaaS.1!F16 -> 1328.125 | H20: =BaaS.1!G20/BaaS.1!G16 -> 1757.4479 | I20: =BaaS.1!H20/BaaS.1!H16 -> 2180.9939 | J20: =BaaS.1!I20/BaaS.1!I16 -> 2599.2444 | K20: =BaaS.1!J20/BaaS.1!J16 -> 2982.6407 | L20: =BaaS.1!K20/BaaS.1!K16 -> 3394.0873 | ... AN20: =BaaS.1!AM20/BaaS.1!AM16 -> 10115.627
A21: Потребительский кредит | C21: нормирование (сопровождение 1 кредита) | D21: сом | E21: =SUM(E22:E24) -> 25.375 | F21: =SUM(F22:F24) -> 25.375 | G21: =SUM(G22:G24) -> 25.375 | H21: =SUM(H22:H24) -> 25.375 | I21: =SUM(I22:I24) -> 25.375 | J21: =SUM(J22:J24) -> 25.375 | K21: =SUM(K22:K24) -> 25.375 | L21: =SUM(L22:L24) -> 25.375 | ... AN21: =SUM(AN22:AN24) -> 25.375
A22: Потребительский кредит | C22: кред.администраторы | D22: сом | E22: =15*35000/40000 -> 13.125 | F22: =15*35000/40000 -> 13.125 | G22: =15*35000/40000 -> 13.125 | H22: =15*35000/40000 -> 13.125 | I22: =15*35000/40000 -> 13.125 | J22: =15*35000/40000 -> 13.125 | K22: =15*35000/40000 -> 13.125 | L22: =15*35000/40000 -> 13.125 | ... AN22: =15*35000/40000 -> 13.125
A23: Потребительский кредит | C23: бухгалтеры | D23: сом | E23: =10*35000/40000 -> 8.75 | F23: =10*35000/40000 -> 8.75 | G23: =10*35000/40000 -> 8.75 | H23: =10*35000/40000 -> 8.75 | I23: =10*35000/40000 -> 8.75 | J23: =10*35000/40000 -> 8.75 | K23: =10*35000/40000 -> 8.75 | L23: =10*35000/40000 -> 8.75 | ... AN23: =10*35000/40000 -> 8.75
A24: Потребительский кредит | C24: collection | D24: сом | E24: =4*35000/40000 -> 3.5 | F24: =4*35000/40000 -> 3.5 | G24: =4*35000/40000 -> 3.5 | H24: =4*35000/40000 -> 3.5 | I24: =4*35000/40000 -> 3.5 | J24: =4*35000/40000 -> 3.5 | K24: =4*35000/40000 -> 3.5 | L24: =4*35000/40000 -> 3.5 | ... AN24: =4*35000/40000 -> 3.5
A25: Рассрочка (BNPL) | B25: OPEX | C25: Расходы на персонал | D25: тыс.сом | E25: =E$21*E26/1000 -> 2.5375 | F25: =F$21*F26/1000 -> 4.1234375 | G25: =G$21*G26/1000 -> 5.1247549 | H25: =H$21*H26/1000 -> 5.7641975 | I25: =I$21*I26/1000 -> 6.1780458 | J25: =J$21*J26/1000 -> 6.4502623 | K25: =K$21*K26/1000 -> 6.8376749 | L25: =L$21*L26/1000 -> 6.6815454 | ... AN25: =AN$21*AN26/1000 -> 7.6124436 | AP25: =SUM(E25:P25) -> 70.223473 | AQ25: =SUM(Q25:AB25) -> 89.465913 | AR25: =SUM(AC25:AN25) -> 91.335479
A26: Рассрочка (BNPL) | C26: количество кредитов в портфеле | D26: шт | E26: =BaaS.1!D44/BaaS.1!D39 -> 100 | F26: =BaaS.1!E44/BaaS.1!E39 -> 162.5 | G26: =BaaS.1!F44/BaaS.1!F39 -> 201.96078 | H26: =BaaS.1!G44/BaaS.1!G39 -> 227.16049 | I26: =BaaS.1!H44/BaaS.1!H39 -> 243.46979 | J26: =BaaS.1!I44/BaaS.1!I39 -> 254.19753 | K26: =BaaS.1!J44/BaaS.1!J39 -> 269.46502 | L26: =BaaS.1!K44/BaaS.1!K39 -> 263.31213 | ... AN26: =BaaS.1!AM44/BaaS.1!AM39 -> 299.99778
A27: Факторинг | B27: OPEX | C27: Расходы на персонал | D27: тыс.сом | E27: =E$21*E28/1000 -> 0.380625 | F27: =F$21*F28/1000 -> 0.65975 | G27: =G$21*G28/1000 -> 0.87120833 | H27: =H$21*H28/1000 -> 1.0375556 | I27: =I$21*I28/1000 -> 1.1738287 | J27: =J$21*J28/1000 -> 1.2900525 | K27: =K$21*K28/1000 -> 1.367535 | L27: =L$21*L28/1000 -> 1.46994 | ... AN27: =AN$21*AN28/1000 -> 2.2837331 | AP27: =SUM(E27:P27) -> 15.413991 | AQ27: =SUM(Q27:AB27) -> 26.839774 | AR27: =SUM(AC27:AN27) -> 27.400644
A28: Факторинг | C28: количество кредитов в портфеле | D28: шт | E28: =BaaS.1!D66/BaaS.1!D62 -> 15 | F28: =BaaS.1!E66/BaaS.1!E62 -> 26 | G28: =BaaS.1!F66/BaaS.1!F62 -> 34.333333 | H28: =BaaS.1!G66/BaaS.1!G62 -> 40.888889 | I28: =BaaS.1!H66/BaaS.1!H62 -> 46.259259 | J28: =BaaS.1!I66/BaaS.1!I62 -> 50.839506 | K28: =BaaS.1!J66/BaaS.1!J62 -> 53.893004 | L28: =BaaS.1!K66/BaaS.1!K62 -> 57.928669 | ... AN28: =BaaS.1!AM66/BaaS.1!AM62 -> 89.999333
A29: Кредитная линия для ИП | B29: OPEX | C29: Расходы на персонал | D29: тыс.сом | E29: =E$21*E30/1000 -> 0.380625 | F29: =F$21*F30/1000 -> 0.786625 | G29: =G$21*G30/1000 -> 1.218 | H29: =H$21*H30/1000 -> 1.67475 | I29: =I$21*I30/1000 -> 2.156875 | J29: =J$21*J30/1000 -> 2.664375 | K29: =K$21*K30/1000 -> 3.171875 | L29: =L$21*L30/1000 -> 3.730125 | ... AN29: =AN$21*AN30/1000 -> 24.740625 | AP29: =SUM(E29:P29) -> 37.30125 | AQ29: =SUM(Q29:AB29) -> 137.025 | AR29: =SUM(AC29:AN29) -> 246.645
A30: Кредитная линия для ИП | C30: количество кредитов в портфеле | D30: шт | E30: =BaaS.1!D86/BaaS.1!D84 -> 15 | F30: =BaaS.1!E86/BaaS.1!E84 -> 31 | G30: =BaaS.1!F86/BaaS.1!F84 -> 48 | H30: =BaaS.1!G86/BaaS.1!G84 -> 66 | I30: =BaaS.1!H86/BaaS.1!H84 -> 85 | J30: =BaaS.1!I86/BaaS.1!I84 -> 105 | K30: =BaaS.1!J86/BaaS.1!J84 -> 125 | L30: =BaaS.1!K86/BaaS.1!K84 -> 147 | ... AN30: =BaaS.1!AM86/BaaS.1!AM84 -> 975
A31: Гарантия | B31: OPEX | C31: Расходы на персонал | D31: тыс.сом | E31: =E$21*E32/1000 -> 0.380625 | F31: =F$21*F32/1000 -> 0.406 | G31: =G$21*G32/1000 -> 0.431375 | H31: =H$21*H32/1000 -> 0.45675 | I31: =I$21*I32/1000 -> 0.482125 | J31: =J$21*J32/1000 -> 0.5075 | K31: =K$21*K32/1000 -> 0.5075 | L31: =L$21*L32/1000 -> 0.55825 | ... AN31: =AN$21*AN32/1000 -> 0.76125 | AP31: =SUM(E31:P31) -> 6.470625 | AQ31: =SUM(Q31:AB31) -> 9.135 | AR31: =SUM(AC31:AN31) -> 9.135
A32: Гарантия | C32: количество кредитов в портфеле | D32: шт | E32: =BaaS.1!D109 -> 15 | F32: =BaaS.1!E109 -> 16 | G32: =BaaS.1!F109 -> 17 | H32: =BaaS.1!G109 -> 18 | I32: =BaaS.1!H109 -> 19 | J32: =BaaS.1!I109 -> 20 | K32: =BaaS.1!J109 -> 20 | L32: =BaaS.1!K109 -> 22 | ... AN32: =BaaS.1!AM109 -> 30
A33: Продажа чужих кредитов | B33: OPEX | C33: Расходы на персонал | D33: тыс сом | E33: =E34*E35/1000 -> 47.619048 | F33: =F34*F35/1000 -> 23.809524 | G33: =G34*G35/1000 -> 23.809524 | H33: =H34*H35/1000 -> 23.809524 | I33: =I34*I35/1000 -> 23.809524 | J33: =J34*J35/1000 -> 23.809524 | K33: =K34*K35/1000 -> 23.809524 | L33: =L34*L35/1000 -> 23.809524 | ... AN33: =AN34*AN35/1000 -> 23.809524 | AP33: =SUM(E33:P33) -> 309.52381 | AQ33: =SUM(Q33:AB33) -> 285.71429 | AR33: =SUM(AC33:AN33) -> 285.71429
A34: Продажа чужих кредитов | C34: количество новых партнеров | D34: шт | E34: ='0'!D11-'0'!C11 -> 2 | F34: ='0'!E11-'0'!D11 -> 1 | G34: ='0'!F11-'0'!E11 -> 1 | H34: ='0'!G11-'0'!F11 -> 1 | I34: ='0'!H11-'0'!G11 -> 1 | J34: ='0'!I11-'0'!H11 -> 1 | K34: ='0'!J11-'0'!I11 -> 1 | L34: ='0'!K11-'0'!J11 -> 1 | ... AN34: ='0'!AM11-'0'!AL11 -> 1
A35: Продажа чужих кредитов | C35: нормирование (подключение 1 нового партнера) | D35: сом | E35: =SUM(E36:E37) -> 23809.524 | F35: =SUM(F36:F37) -> 23809.524 | G35: =SUM(G36:G37) -> 23809.524 | H35: =SUM(H36:H37) -> 23809.524 | I35: =SUM(I36:I37) -> 23809.524 | J35: =SUM(J36:J37) -> 23809.524 | K35: =SUM(K36:K37) -> 23809.524 | L35: =SUM(L36:L37) -> 23809.524 | ... AN35: =SUM(AN36:AN37) -> 23809.524
A36: Продажа чужих кредитов | C36: специалист по hub | D36: сом | E36: =50000*5/21 -> 11904.762 | F36: =50000*5/21 -> 11904.762 | G36: =50000*5/21 -> 11904.762 | H36: =50000*5/21 -> 11904.762 | I36: =50000*5/21 -> 11904.762 | J36: =50000*5/21 -> 11904.762 | K36: =50000*5/21 -> 11904.762 | L36: =50000*5/21 -> 11904.762 | ... AN36: =50000*5/21 -> 11904.762
A37: Продажа чужих кредитов | C37: it-разработчик | D37: сом | E37: =50000*5/21 -> 11904.762 | F37: =50000*5/21 -> 11904.762 | G37: =50000*5/21 -> 11904.762 | H37: =50000*5/21 -> 11904.762 | I37: =50000*5/21 -> 11904.762 | J37: =50000*5/21 -> 11904.762 | K37: =50000*5/21 -> 11904.762 | L37: =50000*5/21 -> 11904.762 | ... AN37: =50000*5/21 -> 11904.762
A38: Депозиты | B38: OPEX | C38: Расходы на персонал | E38: =(E39+E40*E41)/1000 -> 103.93214 | F38: =(F39+F40*F41)/1000 -> 107.81022 | G38: =(G39+G40*G41)/1000 -> 111.65004 | H38: =(H39+H40*H41)/1000 -> 115.45454 | I38: =(I39+I40*I41)/1000 -> 119.22643 | J38: =(J39+J40*J41)/1000 -> 122.96824 | K38: =(K39+K40*K41)/1000 -> 126.42014 | L38: =(L39+L40*L41)/1000 -> 130.12966 | ... AN38: =(AN39+AN40*AN41)/1000 -> 193.58739 | AP38: =SUM(E38:P38) -> 1499.661 | AQ38: =SUM(Q38:AB38) -> 2016.1046 | AR38: =SUM(AC38:AN38) -> 2264.6716
A39: Депозиты | C39: it-разработчики + аналитики + DevOps | D39: сом | E39: 100000 | F39: 100000 | G39: 100000 | H39: 100000 | I39: 100000 | J39: 100000 | K39: 100000 | L39: 100000 | M39: 100000 | N39: 100000 | O39: 100000 | P39: 100000 | Q39: 100000 | R39: 100000 | S39: 100000 | T39: 100000 | U39: 100000 | V39: 100000 | W39: 100000 | X39: 100000 | Y39: 100000 | Z39: 100000 | AA39: 100000 | AB39: 100000 | AC39: 100000 | AD39: 100000 | AE39: 100000 | AF39: 100000 | AG39: 100000 | AH39: 100000 | AI39: 100000 | AJ39: 100000 | AK39: 100000 | AL39: 100000 | AM39: 100000 | AN39: 100000
A40: Депозиты | C40: количество депозитов в портфеле | D40: шт | E40: =BaaS.2!D8 -> 1350 | F40: =BaaS.2!E8 -> 2681.4375 | G40: =BaaS.2!F8 -> 3999.7427 | H40: =BaaS.2!G8 -> 5305.9176 | I40: =BaaS.2!H8 -> 6600.8993 | J40: =BaaS.2!I8 -> 7885.5526 | K40: =BaaS.2!J8 -> 9070.6754 | L40: =BaaS.2!K8 -> 10344.241 | ... AN40: =BaaS.2!AM8 -> 32130.82
A41: Депозиты | C41: нормирование (сопровождение 1 депозита) | D41: сом | E41: =SUM(E42:E44) -> 2.9126984 | F41: =SUM(F42:F44) -> 2.9126984 | G41: =SUM(G42:G44) -> 2.9126984 | H41: =SUM(H42:H44) -> 2.9126984 | I41: =SUM(I42:I44) -> 2.9126984 | J41: =SUM(J42:J44) -> 2.9126984 | K41: =SUM(K42:K44) -> 2.9126984 | L41: =SUM(L42:L44) -> 2.9126984 | ... AN41: =SUM(AN42:AN44) -> 2.9126984
A42: Депозиты | C42: отчетность | D42: сом | E42: =2*(2/21)*40000/30000 -> 0.25396825 | F42: =2*(2/21)*40000/30000 -> 0.25396825 | G42: =2*(2/21)*40000/30000 -> 0.25396825 | H42: =2*(2/21)*40000/30000 -> 0.25396825 | I42: =2*(2/21)*40000/30000 -> 0.25396825 | J42: =2*(2/21)*40000/30000 -> 0.25396825 | K42: =2*(2/21)*40000/30000 -> 0.25396825 | L42: =2*(2/21)*40000/30000 -> 0.25396825 | ... AN42: =2*(2/21)*40000/30000 -> 0.25396825
A43: Депозиты | C43: опер.департамент | D43: сом | E43: =2*(10/21)*40000/30000 -> 1.2698413 | F43: =2*(10/21)*40000/30000 -> 1.2698413 | G43: =2*(10/21)*40000/30000 -> 1.2698413 | H43: =2*(10/21)*40000/30000 -> 1.2698413 | I43: =2*(10/21)*40000/30000 -> 1.2698413 | J43: =2*(10/21)*40000/30000 -> 1.2698413 | K43: =2*(10/21)*40000/30000 -> 1.2698413 | L43: =2*(10/21)*40000/30000 -> 1.2698413 | ... AN43: =2*(10/21)*40000/30000 -> 1.2698413
A44: Депозиты | C44: кол центр | D44: сом | E44: =10*2.5/21*35000/30000 -> 1.3888889 | F44: =10*2.5/21*35000/30000 -> 1.3888889 | G44: =10*2.5/21*35000/30000 -> 1.3888889 | H44: =10*2.5/21*35000/30000 -> 1.3888889 | I44: =10*2.5/21*35000/30000 -> 1.3888889 | J44: =10*2.5/21*35000/30000 -> 1.3888889 | K44: =10*2.5/21*35000/30000 -> 1.3888889 | L44: =10*2.5/21*35000/30000 -> 1.3888889 | ... AN44: =10*2.5/21*35000/30000 -> 1.3888889
A45: Депозиты | B45: OPEX | C45: Амортизационные отчисления | D45: тыс сом | I45: =H49*'0'!G27/1000/(5*12) -> 24.791667 | J45: =I45 -> 24.791667 | K45: =J45 -> 24.791667 | L45: =K45 -> 24.791667 | M45: =L45 -> 24.791667 | N45: =M45 -> 24.791667 | O45: =N45 -> 24.791667 | P45: =O45 -> 24.791667 | Q45: =P45 -> 24.791667 | ... AN45: =AM45 -> 24.791667 | AP45: =SUM(E45:P45) -> 198.33333 | AQ45: =SUM(Q45:AB45) -> 297.5 | AR45: =SUM(AC45:AN45) -> 297.5
A46: Депозиты | B46: OPEX | C46: Административные расходы | D46: тыс сом | S46: =S47*'0'!R27/1000/12 -> 14.166667 | T46: =S46 -> 14.166667 | U46: =T46 -> 14.166667 | V46: =U46 -> 14.166667 | W46: =V46 -> 14.166667 | X46: =W46 -> 14.166667 | Y46: =X46 -> 14.166667 | Z46: =Y46 -> 14.166667 | AA46: =Z46 -> 14.166667 | ... AD46: =AC46 -> 14.166667 | AE46: =AE47*'0'!AD27/1000/12 -> 14.166667 | AF46: =AE46 -> 14.166667 | AG46: =AF46 -> 14.166667 | AH46: =AG46 -> 14.166667 | AI46: =AH46 -> 14.166667 | AJ46: =AI46 -> 14.166667 | AK46: =AJ46 -> 14.166667 | AL46: =AK46 -> 14.166667 | AM46: =AL46 -> 14.166667 | AN46: =AM46 -> 14.166667 | AP46: =SUM(E46:P46) -> 0 | AQ46: =SUM(Q46:AB46) -> 141.66667 | AR46: =SUM(AC46:AN46) -> 170
A47: Депозиты | C47: Система хранения данных (сопровождение) | D47: usd | S47: =50%*4000 -> 2000 | AE47: =S47 -> 2000
A48: Депозиты | B48: CAPEX | C48: Оборудование | D48: тыс сом | H48: =H49*'0'!G27/1000 -> 1487.5 | AP48: =SUM(E48:P48) -> 1487.5 | AQ48: =SUM(Q48:AB48) -> 0 | AR48: =SUM(AC48:AN48) -> 0
A49: Депозиты | C49: Система хранения данных | D49: usd | H49: =50%*35000 -> 17500
A50: DCB ID / DCB BIO | B50: OPEX | C50: Расходы на персонал | D50: тыс сом | E50: =E51/1000 -> 100 | F50: =F51/1000 -> 100 | G50: =G51/1000 -> 100 | H50: =H51/1000 -> 100 | I50: =I51/1000 -> 100 | J50: =J51/1000 -> 100 | K50: =K51/1000 -> 100 | L50: =L51/1000 -> 100 | ... AN50: =AN51/1000 -> 100 | AP50: =SUM(E50:P50) -> 1200 | AQ50: =SUM(Q50:AB50) -> 1200 | AR50: =SUM(AC50:AN50) -> 1200
