Workbook
Name __dol1: '[1]Д&Р'!$C$45
Name __END1: [2]Лист1!$A$293
Name __kurs_dol__: [3]Свод!$M$5
Name _dol1: '[1]Д&Р'!$C$45
Name _END1: [2]Лист1!$A$293
Name aned110: [4]неделя!$Q$81
Name aned111: [4]неделя!$Q$82
Name aned112: [4]неделя!$Q$83
Name aned113: [4]неделя!$Q$84
Name aned146: [4]неделя!$Q$93
Name aned158: [4]неделя!$Q$100
Name aned161: [4]неделя!$Q$169
Name aned162: [4]неделя!$Q$170
Name aned170: [4]неделя!$Q$178
Name aned184: [4]неделя!$Q$208
Name aned191: [4]неделя!$Q$220
Name aned194: [4]неделя!$Q$223
Name aned213: [4]неделя!$Q$229
Name aned224: [4]неделя!$Q$104
Name aned239: [4]неделя!$Q$109
Name aned34: [4]неделя!$Q$214
Name aned50: [4]неделя!$Q$38
Name aned60: [4]неделя!$Q$50
Name aned61: [4]неделя!$Q$51
Name aned62: [4]неделя!$Q$52
Name aned620: [4]неделя!$Q$416
Name aned624: [4]неделя!$Q$180
Name aned628: [4]неделя!$Q$184
Name aned629: [4]неделя!$Q$417
Name aned63: [4]неделя!$Q$53
Name aned632: [4]неделя!$Q$118
Name aned636: [4]неделя!$Q$121
Name aned637: [4]неделя!$Q$122
Name aned639: [4]неделя!$Q$124
Name aned64: [4]неделя!$Q$54
Name aned647: [4]неделя!$Q$185
Name aned65: [4]неделя!$Q$55
Name aned657: [4]неделя!$Q$187
Name aned662: [4]неделя!$Q$127
Name aned668: [4]неделя!$Q$132
Name aned680: [4]неделя!$Q$134
Name aned681: [4]неделя!$Q$135
Name aned682: [4]неделя!$Q$136
Name aned683: [4]неделя!$Q$137
Name aned716: [4]неделя!$Q$484
Name aned718: [4]неделя!$Q$486
Name aned719: [4]неделя!$Q$487
Name aned72: [4]неделя!$Q$62
Name aned728: [4]неделя!$Q$501
Name aned729: [4]неделя!$Q$502
Name aned731: [4]неделя!$Q$189
Name aned76: [4]неделя!$Q$66
Name aned77: [4]неделя!$Q$67
Name aned79: [4]неделя!$Q$69
Name aned812: [4]неделя!$Q$195
Name aned86: [4]неделя!$Q$70
Name aned87: [4]неделя!$Q$71
Name aned882: [4]неделя!$Q$561
Name aned900: [4]неделя!$Q$562
Name aned902: [4]неделя!$Q$547

Sheet Лист3
C1: 1 мес | D1: 2 мес | E1: 3 мес | F1: 4 мес | G1: 5 мес | H1: 6 мес | I1: 7 мес | J1: 8 мес | K1: 9 мес | L1: 10 мес | M1: 11 мес | N1: 12 мес | O1: 1 год | P1: 1 мес | Q1: 2 мес | R1: 3 мес | S1: 4 мес | T1: 5 мес | U1: 6 мес | V1: 7 мес | W1: 8 мес | X1: 9 мес | Y1: 10 мес | Z1: 11 мес | AA1: 12 мес | AB1: 2 год | AC1: 1 мес | AD1: 2 мес | AE1: 3 мес | AF1: 4 мес | AG1: 5 мес | AH1: 6 мес | AI1: 7 мес | AJ1: 8 мес | AK1: 9 мес | AL1: 10 мес | AM1: 11 мес | AN1: 12 мес | AO1: 3 год | AP1: 1 мес | AQ1: 2 мес | AR1: 3 мес | AS1: 4 мес | AT1: 5 мес | AU1: 6 мес | AV1: 7 мес | AW1: 8 мес | AX1: 9 мес | AY1: 10 мес | AZ1: 11 мес | BA1: 12 мес | BB1: 4 год | BC1: 1 мес | BD1: 2 мес | BE1: 3 мес | BF1: 4 мес | BG1: 5 мес | BH1: 6 мес | BI1: 7 мес | BJ1: 8 мес | BK1: 9 мес | BL1: 10 мес | BM1: 11 мес | BN1: 12 мес | BO1: 5 год
A3: Оформленные заявки | C3: =O3*C4 -> #REF! | D3: =O3*D4 -> #REF! | E3: =O3*E4 -> #REF! | F3: =O3*F4 -> #REF! | G3: =O3*G4 -> #REF! | H3: =O3*H4 -> #REF! | I3: =O3*I4 -> #REF! | J3: =O3*J4 -> #REF! | K3: =O3*K4 -> #REF! | L3: =O3*L4 -> #REF! | M3: =O3*M4 -> #REF! | N3: =O3*N4 -> #REF! | O3: =#REF! -> #REF! | P3: =AB3*P4 -> #REF! | Q3: =AB3*Q4 -> #REF! | R3: =AB3*R4 -> #REF! | S3: =AB3*S4 -> #REF! | T3: =AB3*T4 -> #REF! | U3: =AB3*U4 -> #REF! | V3: =AB3*V4 -> #REF! | W3: =AB3*W4 -> #REF! | X3: =AB3*X4 -> #REF! | Y3: =AB3*Y4 -> #REF! | Z3: =AB3*Z4 -> #REF! | AA3: =AB3*AA4 -> #REF! | AB3: =#REF! -> #REF! | AC3: =AO3*AC4 -> #REF! | AD3: =AO3*AD4 -> #REF! | AE3: =AO3*AE4 -> #REF! | AF3: =AO3*AF4 -> #REF! | AG3: =AO3*AG4 -> #REF! | AH3: =AO3*AH4 -> #REF! | AI3: =AO3*AI4 -> #REF! | AJ3: =AO3*AJ4 -> #REF! | AK3: =AO3*AK4 -> #REF! | AL3: =AO3*AL4 -> #REF! | AM3: =AO3*AM4 -> #REF! | AN3: =AO3*AN4 -> #REF! | AO3: =#REF! -> #REF! | AP3: =BB3*AP4 -> #REF! | AQ3: =BB3*AQ4 -> #REF! | AR3: =BB3*AR4 -> #REF! | AS3: =BB3*AS4 -> #REF! | AT3: =BB3*AT4 -> #REF! | AU3: =BB3*AU4 -> #REF! | AV3: =BB3*AV4 -> #REF! | AW3: =BB3*AW4 -> #REF! | AX3: =BB3*AX4 -> #REF! | AY3: =BB3*AY4 -> #REF! | AZ3: =BB3*AZ4 -> #REF! | BA3: =BB3*BA4 -> #REF! | BB3: =#REF! -> #REF! | BC3: =BO3*BC4 -> #REF! | BD3: =BO3*BD4 -> #REF! | BE3: =BO3*BE4 -> #REF! | BF3: =BO3*BF4 -> #REF! | BG3: =BO3*BG4 -> #REF! | BH3: =BO3*BH4 -> #REF! | BI3: =BO3*BI4 -> #REF! | BJ3: =BO3*BJ4 -> #REF! | BK3: =BO3*BK4 -> #REF! | BL3: =BO3*BL4 -> #REF! | BM3: =BO3*BM4 -> #REF! | BN3: =BO3*BN4 -> #REF! | BO3: =#REF! -> #REF!
A4: сезонность | C4: =100%/12 -> 0.083333333 | D4: =100%/12 -> 0.083333333 | E4: =100%/12 -> 0.083333333 | F4: =100%/12 -> 0.083333333 | G4: =100%/12 -> 0.083333333 | H4: =100%/12 -> 0.083333333 | I4: =100%/12 -> 0.083333333 | J4: =100%/12 -> 0.083333333 | ... M4: =100%/12 -> 0.083333333 | N4: =100%-SUM(C4:M4) -> 0.083333333 | O4: =SUM(C4:N4) -> 1 | P4: =100%/12 -> 0.083333333 | Q4: =100%/12 -> 0.083333333 | R4: =100%/12 -> 0.083333333 | S4: =100%/12 -> 0.083333333 | T4: =100%/12 -> 0.083333333 | U4: =100%/12 -> 0.083333333 | V4: =100%/12 -> 0.083333333 | W4: =100%/12 -> 0.083333333 | ... Z4: =100%/12 -> 0.083333333 | AA4: =100%-SUM(P4:Z4) -> 0.083333333 | AB4: =SUM(P4:AA4) -> 1 | AC4: =100%/12 -> 0.083333333 | AD4: =100%/12 -> 0.083333333 | AE4: =100%/12 -> 0.083333333 | AF4: =100%/12 -> 0.083333333 | AG4: =100%/12 -> 0.083333333 | AH4: =100%/12 -> 0.083333333 | AI4: =100%/12 -> 0.083333333 | AJ4: =100%/12 -> 0.083333333 | ... AM4: =100%/12 -> 0.083333333 | AN4: =100%-SUM(AC4:AM4) -> 0.083333333 | AO4: =SUM(AC4:AN4) -> 1 | AP4: =100%/12 -> 0.083333333 | AQ4: =100%/12 -> 0.083333333 | AR4: =100%/12 -> 0.083333333 | AS4: =100%/12 -> 0.083333333 | AT4: =100%/12 -> 0.083333333 | AU4: =100%/12 -> 0.083333333 | AV4: =100%/12 -> 0.083333333 | AW4: =100%/12 -> 0.083333333 | ... AZ4: =100%/12 -> 0.083333333 | BA4: =100%-SUM(AP4:AZ4) -> 0.083333333 | BB4: =SUM(AP4:BA4) -> 1 | BC4: =100%/12 -> 0.083333333 | BD4: =100%/12 -> 0.083333333 | BE4: =100%/12 -> 0.083333333 | BF4: =100%/12 -> 0.083333333 | BG4: =100%/12 -> 0.083333333 | BH4: =100%/12 -> 0.083333333 | BI4: =100%/12 -> 0.083333333 | BJ4: =100%/12 -> 0.083333333 | ... BM4: =100%/12 -> 0.083333333 | BN4: =100%-SUM(BC4:BM4) -> 0.083333333 | BO4: =SUM(BC4:BN4) -> 1
A5: AR, % | C5: =O5 -> #REF! | D5: =O5 -> #REF! | E5: =O5 -> #REF! | F5: =O5 -> #REF! | G5: =O5 -> #REF! | H5: =O5 -> #REF! | I5: =O5 -> #REF! | J5: =O5 -> #REF! | K5: =O5 -> #REF! | L5: =O5 -> #REF! | M5: =O5 -> #REF! | N5: =O5 -> #REF! | O5: =#REF! -> #REF! | P5: =AB5 -> #REF! | Q5: =AB5 -> #REF! | R5: =AB5 -> #REF! | S5: =AB5 -> #REF! | T5: =AB5 -> #REF! | U5: =AB5 -> #REF! | V5: =AB5 -> #REF! | W5: =AB5 -> #REF! | X5: =AB5 -> #REF! | Y5: =AB5 -> #REF! | Z5: =AB5 -> #REF! | AA5: =AB5 -> #REF! | AB5: =#REF! -> #REF! | AC5: =AO5 -> #REF! | AD5: =AO5 -> #REF! | AE5: =AO5 -> #REF! | AF5: =AO5 -> #REF! | AG5: =AO5 -> #REF! | AH5: =AO5 -> #REF! | AI5: =AO5 -> #REF! | AJ5: =AO5 -> #REF! | AK5: =AO5 -> #REF! | AL5: =AO5 -> #REF! | AM5: =AO5 -> #REF! | AN5: =AO5 -> #REF! | AO5: =#REF! -> #REF! | AP5: =BB5 -> #REF! | AQ5: =BB5 -> #REF! | AR5: =BB5 -> #REF! | AS5: =BB5 -> #REF! | AT5: =BB5 -> #REF! | AU5: =BB5 -> #REF! | AV5: =BB5 -> #REF! | AW5: =BB5 -> #REF! | AX5: =BB5 -> #REF! | AY5: =BB5 -> #REF! | AZ5: =BB5 -> #REF! | BA5: =BB5 -> #REF! | BB5: =#REF! -> #REF! | BC5: =BO5 -> #REF! | BD5: =BO5 -> #REF! | BE5: =BO5 -> #REF! | BF5: =BO5 -> #REF! | BG5: =BO5 -> #REF! | BH5: =BO5 -> #REF! | BI5: =BO5 -> #REF! | BJ5: =BO5 -> #REF! | BK5: =BO5 -> #REF! | BL5: =BO5 -> #REF! | BM5: =BO5 -> #REF! | BN5: =BO5 -> #REF! | BO5: =#REF! -> #REF!
A6: Кол-во одобренных клиентов | C6: =C3*C5 -> #REF! | D6: =D3*D5 -> #REF! | E6: =E3*E5 -> #REF! | F6: =F3*F5 -> #REF! | G6: =G3*G5 -> #REF! | H6: =H3*H5 -> #REF! | I6: =I3*I5 -> #REF! | J6: =J3*J5 -> #REF! | ... N6: =N3*N5 -> #REF! | O6: =SUM(C6:N6) -> #REF! | P6: =P3*P5 -> #REF! | Q6: =Q3*Q5 -> #REF! | R6: =R3*R5 -> #REF! | S6: =S3*S5 -> #REF! | T6: =T3*T5 -> #REF! | U6: =U3*U5 -> #REF! | V6: =V3*V5 -> #REF! | W6: =W3*W5 -> #REF! | ... AA6: =AA3*AA5 -> #REF! | AB6: =SUM(P6:AA6) -> #REF! | AC6: =AC3*AC5 -> #REF! | AD6: =AD3*AD5 -> #REF! | AE6: =AE3*AE5 -> #REF! | AF6: =AF3*AF5 -> #REF! | AG6: =AG3*AG5 -> #REF! | AH6: =AH3*AH5 -> #REF! | AI6: =AI3*AI5 -> #REF! | AJ6: =AJ3*AJ5 -> #REF! | ... AN6: =AN3*AN5 -> #REF! | AO6: =SUM(AC6:AN6) -> #REF! | AP6: =AP3*AP5 -> #REF! | AQ6: =AQ3*AQ5 -> #REF! | AR6: =AR3*AR5 -> #REF! | AS6: =AS3*AS5 -> #REF! | AT6: =AT3*AT5 -> #REF! | AU6: =AU3*AU5 -> #REF! | AV6: =AV3*AV5 -> #REF! | AW6: =AW3*AW5 -> #REF! | ... BA6: =BA3*BA5 -> #REF! | BB6: =SUM(AP6:BA6) -> #REF! | BC6: =BC3*BC5 -> #REF! | BD6: =BD3*BD5 -> #REF! | BE6: =BE3*BE5 -> #REF! | BF6: =BF3*BF5 -> #REF! | BG6: =BG3*BG5 -> #REF! | BH6: =BH3*BH5 -> #REF! | BI6: =BI3*BI5 -> #REF! | BJ6: =BJ3*BJ5 -> #REF! | ... BN6: =BN3*BN5 -> #REF! | BO6: =SUM(BC6:BN6) -> #REF!
A7: Take up, % | C7: =O7 -> #REF! | D7: =O7 -> #REF! | E7: =O7 -> #REF! | F7: =O7 -> #REF! | G7: =O7 -> #REF! | H7: =O7 -> #REF! | I7: =O7 -> #REF! | J7: =O7 -> #REF! | K7: =O7 -> #REF! | L7: =O7 -> #REF! | M7: =O7 -> #REF! | N7: =O7 -> #REF! | O7: =#REF! -> #REF! | P7: =AB7 -> #REF! | Q7: =AB7 -> #REF! | R7: =AB7 -> #REF! | S7: =AB7 -> #REF! | T7: =AB7 -> #REF! | U7: =AB7 -> #REF! | V7: =AB7 -> #REF! | W7: =AB7 -> #REF! | X7: =AB7 -> #REF! | Y7: =AB7 -> #REF! | Z7: =AB7 -> #REF! | AA7: =AB7 -> #REF! | AB7: =#REF! -> #REF! | AC7: =AO7 -> #REF! | AD7: =AO7 -> #REF! | AE7: =AO7 -> #REF! | AF7: =AO7 -> #REF! | AG7: =AO7 -> #REF! | AH7: =AO7 -> #REF! | AI7: =AO7 -> #REF! | AJ7: =AO7 -> #REF! | AK7: =AO7 -> #REF! | AL7: =AO7 -> #REF! | AM7: =AO7 -> #REF! | AN7: =AO7 -> #REF! | AO7: =#REF! -> #REF! | AP7: =BB7 -> #REF! | AQ7: =BB7 -> #REF! | AR7: =BB7 -> #REF! | AS7: =BB7 -> #REF! | AT7: =BB7 -> #REF! | AU7: =BB7 -> #REF! | AV7: =BB7 -> #REF! | AW7: =BB7 -> #REF! | AX7: =BB7 -> #REF! | AY7: =BB7 -> #REF! | AZ7: =BB7 -> #REF! | BA7: =BB7 -> #REF! | BB7: =#REF! -> #REF! | BC7: =BO7 -> #REF! | BD7: =BO7 -> #REF! | BE7: =BO7 -> #REF! | BF7: =BO7 -> #REF! | BG7: =BO7 -> #REF! | BH7: =BO7 -> #REF! | BI7: =BO7 -> #REF! | BJ7: =BO7 -> #REF! | BK7: =BO7 -> #REF! | BL7: =BO7 -> #REF! | BM7: =BO7 -> #REF! | BN7: =BO7 -> #REF! | BO7: =#REF! -> #REF!
A8: Кол-во клиентов, согласившихся на кредит | C8: =C6*C7 -> #REF! | D8: =D6*D7 -> #REF! | E8: =E6*E7 -> #REF! | F8: =F6*F7 -> #REF! | G8: =G6*G7 -> #REF! | H8: =H6*H7 -> #REF! | I8: =I6*I7 -> #REF! | J8: =J6*J7 -> #REF! | ... N8: =N6*N7 -> #REF! | O8: =SUM(C8:N8) -> #REF! | P8: =P6*P7 -> #REF! | Q8: =Q6*Q7 -> #REF! | R8: =R6*R7 -> #REF! | S8: =S6*S7 -> #REF! | T8: =T6*T7 -> #REF! | U8: =U6*U7 -> #REF! | V8: =V6*V7 -> #REF! | W8: =W6*W7 -> #REF! | ... AA8: =AA6*AA7 -> #REF! | AB8: =SUM(P8:AA8) -> #REF! | AC8: =AC6*AC7 -> #REF! | AD8: =AD6*AD7 -> #REF! | AE8: =AE6*AE7 -> #REF! | AF8: =AF6*AF7 -> #REF! | AG8: =AG6*AG7 -> #REF! | AH8: =AH6*AH7 -> #REF! | AI8: =AI6*AI7 -> #REF! | AJ8: =AJ6*AJ7 -> #REF! | ... AN8: =AN6*AN7 -> #REF! | AO8: =SUM(AC8:AN8) -> #REF! | AP8: =AP6*AP7 -> #REF! | AQ8: =AQ6*AQ7 -> #REF! | AR8: =AR6*AR7 -> #REF! | AS8: =AS6*AS7 -> #REF! | AT8: =AT6*AT7 -> #REF! | AU8: =AU6*AU7 -> #REF! | AV8: =AV6*AV7 -> #REF! | AW8: =AW6*AW7 -> #REF! | ... BA8: =BA6*BA7 -> #REF! | BB8: =SUM(AP8:BA8) -> #REF! | BC8: =BC6*BC7 -> #REF! | BD8: =BD6*BD7 -> #REF! | BE8: =BE6*BE7 -> #REF! | BF8: =BF6*BF7 -> #REF! | BG8: =BG6*BG7 -> #REF! | BH8: =BH6*BH7 -> #REF! | BI8: =BI6*BI7 -> #REF! | BJ8: =BJ6*BJ7 -> #REF! | ... BN8: =BN6*BN7 -> #REF! | BO8: =SUM(BC8:BN8) -> #REF!
A9: Средний чек займа, тенге | C9: =O9 -> #REF! | D9: =O9 -> #REF! | E9: =O9 -> #REF! | F9: =O9 -> #REF! | G9: =O9 -> #REF! | H9: =O9 -> #REF! | I9: =O9 -> #REF! | J9: =O9 -> #REF! | K9: =O9 -> #REF! | L9: =O9 -> #REF! | M9: =O9 -> #REF! | N9: =O9 -> #REF! | O9: =#REF! -> #REF! | P9: =AB9 -> #REF! | Q9: =AB9 -> #REF! | R9: =AB9 -> #REF! | S9: =AB9 -> #REF! | T9: =AB9 -> #REF! | U9: =AB9 -> #REF! | V9: =AB9 -> #REF! | W9: =AB9 -> #REF! | X9: =AB9 -> #REF! | Y9: =AB9 -> #REF! | Z9: =AB9 -> #REF! | AA9: =AB9 -> #REF! | AB9: =#REF! -> #REF! | AC9: =AO9 -> #REF! | AD9: =AO9 -> #REF! | AE9: =AO9 -> #REF! | AF9: =AO9 -> #REF! | AG9: =AO9 -> #REF! | AH9: =AO9 -> #REF! | AI9: =AO9 -> #REF! | AJ9: =AO9 -> #REF! | AK9: =AO9 -> #REF! | AL9: =AO9 -> #REF! | AM9: =AO9 -> #REF! | AN9: =AO9 -> #REF! | AO9: =#REF! -> #REF! | AP9: =BB9 -> #REF! | AQ9: =BB9 -> #REF! | AR9: =BB9 -> #REF! | AS9: =BB9 -> #REF! | AT9: =BB9 -> #REF! | AU9: =BB9 -> #REF! | AV9: =BB9 -> #REF! | AW9: =BB9 -> #REF! | AX9: =BB9 -> #REF! | AY9: =BB9 -> #REF! | AZ9: =BB9 -> #REF! | BA9: =BB9 -> #REF! | BB9: =#REF! -> #REF! | BC9: =BO9 -> #REF! | BD9: =BO9 -> #REF! | BE9: =BO9 -> #REF! | BF9: =BO9 -> #REF! | BG9: =BO9 -> #REF! | BH9: =BO9 -> #REF! | BI9: =BO9 -> #REF! | BJ9: =BO9 -> #REF! | BK9: =BO9 -> #REF! | BL9: =BO9 -> #REF! | BM9: =BO9 -> #REF! | BN9: =BO9 -> #REF! | BO9: =#REF! -> #REF!
A10: Выдачи, млн тенге | C10: =C8*C9/1000000 -> #REF! | D10: =D8*D9/1000000 -> #REF! | E10: =E8*E9/1000000 -> #REF! | F10: =F8*F9/1000000 -> #REF! | G10: =G8*G9/1000000 -> #REF! | H10: =H8*H9/1000000 -> #REF! | I10: =I8*I9/1000000 -> #REF! | J10: =J8*J9/1000000 -> #REF! | ... N10: =N8*N9/1000000 -> #REF! | O10: =SUM(C10:N10) -> #REF! | P10: =P8*P9/1000000 -> #REF! | Q10: =Q8*Q9/1000000 -> #REF! | R10: =R8*R9/1000000 -> #REF! | S10: =S8*S9/1000000 -> #REF! | T10: =T8*T9/1000000 -> #REF! | U10: =U8*U9/1000000 -> #REF! | V10: =V8*V9/1000000 -> #REF! | W10: =W8*W9/1000000 -> #REF! | ... AA10: =AA8*AA9/1000000 -> #REF! | AB10: =SUM(P10:AA10) -> #REF! | AC10: =AC8*AC9/1000000 -> #REF! | AD10: =AD8*AD9/1000000 -> #REF! | AE10: =AE8*AE9/1000000 -> #REF! | AF10: =AF8*AF9/1000000 -> #REF! | AG10: =AG8*AG9/1000000 -> #REF! | AH10: =AH8*AH9/1000000 -> #REF! | AI10: =AI8*AI9/1000000 -> #REF! | AJ10: =AJ8*AJ9/1000000 -> #REF! | ... AN10: =AN8*AN9/1000000 -> #REF! | AO10: =SUM(AC10:AN10) -> #REF! | AP10: =AP8*AP9/1000000 -> #REF! | AQ10: =AQ8*AQ9/1000000 -> #REF! | AR10: =AR8*AR9/1000000 -> #REF! | AS10: =AS8*AS9/1000000 -> #REF! | AT10: =AT8*AT9/1000000 -> #REF! | AU10: =AU8*AU9/1000000 -> #REF! | AV10: =AV8*AV9/1000000 -> #REF! | AW10: =AW8*AW9/1000000 -> #REF! | ... BA10: =BA8*BA9/1000000 -> #REF! | BB10: =SUM(AP10:BA10) -> #REF! | BC10: =BC8*BC9/1000000 -> #REF! | BD10: =BD8*BD9/1000000 -> #REF! | BE10: =BE8*BE9/1000000 -> #REF! | BF10: =BF8*BF9/1000000 -> #REF! | BG10: =BG8*BG9/1000000 -> #REF! | BH10: =BH8*BH9/1000000 -> #REF! | BI10: =BI8*BI9/1000000 -> #REF! | BJ10: =BJ8*BJ9/1000000 -> #REF! | ... BN10: =BN8*BN9/1000000 -> #REF! | BO10: =SUM(BC10:BN10) -> #REF!
A11: Коэффициент погашения | C11: =O11 -> -0.04 | D11: =O11 -> -0.04 | E11: =O11 -> -0.04 | F11: =O11 -> -0.04 | G11: =O11 -> -0.04 | H11: =O11 -> -0.04 | I11: =O11 -> -0.04 | J11: =O11 -> -0.04 | K11: =O11 -> -0.04 | L11: =O11 -> -0.04 | M11: =O11 -> -0.04 | N11: =O11 -> -0.04 | O11: -0.04 | P11: =AB11 -> -0.04 | Q11: =AB11 -> -0.04 | R11: =AB11 -> -0.04 | S11: =AB11 -> -0.04 | T11: =AB11 -> -0.04 | U11: =AB11 -> -0.04 | V11: =AB11 -> -0.04 | W11: =AB11 -> -0.04 | X11: =AB11 -> -0.04 | Y11: =AB11 -> -0.04 | Z11: =AB11 -> -0.04 | AA11: =AB11 -> -0.04 | AB11: -0.04 | AC11: =AO11 -> -0.04 | AD11: =AO11 -> -0.04 | AE11: =AO11 -> -0.04 | AF11: =AO11 -> -0.04 | AG11: =AO11 -> -0.04 | AH11: =AO11 -> -0.04 | AI11: =AO11 -> -0.04 | AJ11: =AO11 -> -0.04 | AK11: =AO11 -> -0.04 | AL11: =AO11 -> -0.04 | AM11: =AO11 -> -0.04 | AN11: =AO11 -> -0.04 | AO11: -0.04 | AP11: =BB11 -> -0.04 | AQ11: =BB11 -> -0.04 | AR11: =BB11 -> -0.04 | AS11: =BB11 -> -0.04 | AT11: =BB11 -> -0.04 | AU11: =BB11 -> -0.04 | AV11: =BB11 -> -0.04 | AW11: =BB11 -> -0.04 | AX11: =BB11 -> -0.04 | AY11: =BB11 -> -0.04 | AZ11: =BB11 -> -0.04 | BA11: =BB11 -> -0.04 | BB11: -0.04 | BC11: =BO11 -> -0.04 | BD11: =BO11 -> -0.04 | BE11: =BO11 -> -0.04 | BF11: =BO11 -> -0.04 | BG11: =BO11 -> -0.04 | BH11: =BO11 -> -0.04 | BI11: =BO11 -> -0.04 | BJ11: =BO11 -> -0.04 | BK11: =BO11 -> -0.04 | BL11: =BO11 -> -0.04 | BM11: =BO11 -> -0.04 | BN11: =BO11 -> -0.04 | BO11: -0.04
A12: Погашения | D12: =C14*D11 -> #REF! | E12: =D14*E11 -> #REF! | F12: =E14*F11 -> #REF! | G12: =F14*G11 -> #REF! | H12: =G14*H11 -> #REF! | I12: =H14*I11 -> #REF! | J12: =I14*J11 -> #REF! | K12: =J14*K11 -> #REF! | ... N12: =M14*N11 -> #REF! | O12: =SUM(C12:N12) -> #REF! | Q12: =P14*Q11 -> #REF! | R12: =Q14*R11 -> #REF! | S12: =R14*S11 -> #REF! | T12: =S14*T11 -> #REF! | U12: =T14*U11 -> #REF! | V12: =U14*V11 -> #REF! | W12: =V14*W11 -> #REF! | X12: =W14*X11 -> #REF! | ... AA12: =Z14*AA11 -> #REF! | AB12: =SUM(P12:AA12) -> #REF! | AD12: =AC14*AD11 -> #REF! | AE12: =AD14*AE11 -> #REF! | AF12: =AE14*AF11 -> #REF! | AG12: =AF14*AG11 -> #REF! | AH12: =AG14*AH11 -> #REF! | AI12: =AH14*AI11 -> #REF! | AJ12: =AI14*AJ11 -> #REF! | AK12: =AJ14*AK11 -> #REF! | ... AN12: =AM14*AN11 -> #REF! | AO12: =SUM(AC12:AN12) -> #REF! | AQ12: =AP14*AQ11 -> #REF! | AR12: =AQ14*AR11 -> #REF! | AS12: =AR14*AS11 -> #REF! | AT12: =AS14*AT11 -> #REF! | AU12: =AT14*AU11 -> #REF! | AV12: =AU14*AV11 -> #REF! | AW12: =AV14*AW11 -> #REF! | AX12: =AW14*AX11 -> #REF! | ... BA12: =AZ14*BA11 -> #REF! | BB12: =SUM(AP12:BA12) -> #REF! | BD12: =BC14*BD11 -> #REF! | BE12: =BD14*BE11 -> #REF! | BF12: =BE14*BF11 -> #REF! | BG12: =BF14*BG11 -> #REF! | BH12: =BG14*BH11 -> #REF! | BI12: =BH14*BI11 -> #REF! | BJ12: =BI14*BJ11 -> #REF! | BK12: =BJ14*BK11 -> #REF! | ... BN12: =BM14*BN11 -> #REF! | BO12: =SUM(BC12:BN12) -> #REF!
A13: Списания | O13: =N13 -> 0 | AB13: =AA13 -> 0 | AO13: =AN13 -> 0 | BB13: =BA13 -> 0 | BO13: =BN13 -> 0
A14: Кредитный порфтель | C14: =C10+C12+C13 -> #REF! | D14: =C14+D10+D12+D13 -> #REF! | E14: =D14+E10+E12+E13 -> #REF! | F14: =E14+F10+F12+F13 -> #REF! | G14: =F14+G10+G12+G13 -> #REF! | H14: =G14+H10+H12+H13 -> #REF! | I14: =H14+I10+I12+I13 -> #REF! | J14: =I14+J10+J12+J13 -> #REF! | K14: =J14+K10+K12+K13 -> #REF! | ... N14: =M14+N10+N12+N13 -> #REF! | O14: =N14 -> #REF! | P14: =P10+P12+P13 -> #REF! | Q14: =P14+Q10+Q12+Q13 -> #REF! | R14: =Q14+R10+R12+R13 -> #REF! | S14: =R14+S10+S12+S13 -> #REF! | T14: =S14+T10+T12+T13 -> #REF! | U14: =T14+U10+U12+U13 -> #REF! | V14: =U14+V10+V12+V13 -> #REF! | W14: =V14+W10+W12+W13 -> #REF! | X14: =W14+X10+X12+X13 -> #REF! | ... AA14: =Z14+AA10+AA12+AA13 -> #REF! | AB14: =AA14 -> #REF! | AC14: =AC10+AC12+AC13 -> #REF! | AD14: =AC14+AD10+AD12+AD13 -> #REF! | AE14: =AD14+AE10+AE12+AE13 -> #REF! | AF14: =AE14+AF10+AF12+AF13 -> #REF! | AG14: =AF14+AG10+AG12+AG13 -> #REF! | AH14: =AG14+AH10+AH12+AH13 -> #REF! | AI14: =AH14+AI10+AI12+AI13 -> #REF! | AJ14: =AI14+AJ10+AJ12+AJ13 -> #REF! | AK14: =AJ14+AK10+AK12+AK13 -> #REF! | ... AN14: =AM14+AN10+AN12+AN13 -> #REF! | AO14: =AN14 -> #REF! | AP14: =AP10+AP12+AP13 -> #REF! | AQ14: =AP14+AQ10+AQ12+AQ13 -> #REF! | AR14: =AQ14+AR10+AR12+AR13 -> #REF! | AS14: =AR14+AS10+AS12+AS13 -> #REF! | AT14: =AS14+AT10+AT12+AT13 -> #REF! | AU14: =AT14+AU10+AU12+AU13 -> #REF! | AV14: =AU14+AV10+AV12+AV13 -> #REF! | AW14: =AV14+AW10+AW12+AW13 -> #REF! | AX14: =AW14+AX10+AX12+AX13 -> #REF! | ... BA14: =AZ14+BA10+BA12+BA13 -> #REF! | BB14: =BA14 -> #REF! | BC14: =BC10+BC12+BC13 -> #REF! | BD14: =BC14+BD10+BD12+BD13 -> #REF! | BE14: =BD14+BE10+BE12+BE13 -> #REF! | BF14: =BE14+BF10+BF12+BF13 -> #REF! | BG14: =BF14+BG10+BG12+BG13 -> #REF! | BH14: =BG14+BH10+BH12+BH13 -> #REF! | BI14: =BH14+BI10+BI12+BI13 -> #REF! | BJ14: =BI14+BJ10+BJ12+BJ13 -> #REF! | BK14: =BJ14+BK10+BK12+BK13 -> #REF! | ... BN14: =BM14+BN10+BN12+BN13 -> #REF! | BO14: =BN14 -> #REF!
A15: Процентная ставка
A18: Уровень PD
A19: CoR
A20: Стоимость ресурсов

Sheet Лист4
C1: 1 мес | D1: 2 мес | E1: 3 мес | F1: 4 мес | G1: 5 мес | H1: 6 мес | I1: 7 мес | J1: 8 мес | K1: 9 мес | L1: 10 мес | M1: 11 мес | N1: 12 мес | O1: 1 год | P1: 1 мес | Q1: 2 мес | R1: 3 мес | S1: 4 мес | T1: 5 мес | U1: 6 мес | V1: 7 мес | W1: 8 мес | X1: 9 мес | Y1: 10 мес | Z1: 11 мес | AA1: 12 мес | AB1: 2 год | AC1: 1 мес | AD1: 2 мес | AE1: 3 мес | AF1: 4 мес | AG1: 5 мес | AH1: 6 мес | AI1: 7 мес | AJ1: 8 мес | AK1: 9 мес | AL1: 10 мес | AM1: 11 мес | AN1: 12 мес | AO1: 3 год | AP1: 1 мес | AQ1: 2 мес | AR1: 3 мес | AS1: 4 мес | AT1: 5 мес | AU1: 6 мес | AV1: 7 мес | AW1: 8 мес | AX1: 9 мес | AY1: 10 мес | AZ1: 11 мес | BA1: 12 мес | BB1: 4 год | BC1: 1 мес | BD1: 2 мес | BE1: 3 мес | BF1: 4 мес | BG1: 5 мес | BH1: 6 мес | BI1: 7 мес | BJ1: 8 мес | BK1: 9 мес | BL1: 10 мес | BM1: 11 мес | BN1: 12 мес | BO1: 5 год
A3: Кол-во клиентов, согласившихся на пакет | C3: =B3+C4 -> #REF! | D3: =C3+D4 -> #REF! | E3: =D3+E4 -> #REF! | F3: =E3+F4 -> #REF! | G3: =F3+G4 -> #REF! | H3: =G3+H4 -> #REF! | I3: =H3+I4 -> #REF! | J3: =I3+J4 -> #REF! | ... N3: =M3+N4 -> #REF! | O3: =#REF! -> #REF! | P3: =O3+P4 -> #REF! | Q3: =P3+Q4 -> #REF! | R3: =Q3+R4 -> #REF! | S3: =R3+S4 -> #REF! | T3: =S3+T4 -> #REF! | U3: =T3+U4 -> #REF! | V3: =U3+V4 -> #REF! | W3: =V3+W4 -> #REF! | ... AA3: =Z3+AA4 -> #REF! | AB3: =#REF! -> #REF! | AC3: =AB3+AC4 -> #REF! | AD3: =AC3+AD4 -> #REF! | AE3: =AD3+AE4 -> #REF! | AF3: =AE3+AF4 -> #REF! | AG3: =AF3+AG4 -> #REF! | AH3: =AG3+AH4 -> #REF! | AI3: =AH3+AI4 -> #REF! | AJ3: =AI3+AJ4 -> #REF! | ... AN3: =AM3+AN4 -> #REF! | AO3: =#REF! -> #REF! | AP3: =AO3+AP4 -> #REF! | AQ3: =AP3+AQ4 -> #REF! | AR3: =AQ3+AR4 -> #REF! | AS3: =AR3+AS4 -> #REF! | AT3: =AS3+AT4 -> #REF! | AU3: =AT3+AU4 -> #REF! | AV3: =AU3+AV4 -> #REF! | AW3: =AV3+AW4 -> #REF! | ... BA3: =AZ3+BA4 -> #REF! | BB3: =#REF! -> #REF! | BC3: =BB3+BC4 -> #REF! | BD3: =BC3+BD4 -> #REF! | BE3: =BD3+BE4 -> #REF! | BF3: =BE3+BF4 -> #REF! | BG3: =BF3+BG4 -> #REF! | BH3: =BG3+BH4 -> #REF! | BI3: =BH3+BI4 -> #REF! | BJ3: =BI3+BJ4 -> #REF! | ... BN3: =BM3+BN4 -> #REF! | BO3: =#REF! -> #REF!
A4: Прирост клиентов | C4: =O4*C5 -> #REF! | D4: =O4*D5 -> #REF! | E4: =O4*E5 -> #REF! | F4: =O4*F5 -> #REF! | G4: =O4*G5 -> #REF! | H4: =O4*H5 -> #REF! | I4: =O4*I5 -> #REF! | J4: =O4*J5 -> #REF! | K4: =O4*K5 -> #REF! | L4: =O4*L5 -> #REF! | M4: =O4*M5 -> #REF! | N4: =O4*N5 -> #REF! | O4: =O3-B3 -> #REF! | P4: =AB4*P5 -> #REF! | Q4: =AB4*Q5 -> #REF! | R4: =AB4*R5 -> #REF! | S4: =AB4*S5 -> #REF! | T4: =AB4*T5 -> #REF! | U4: =AB4*U5 -> #REF! | V4: =AB4*V5 -> #REF! | W4: =AB4*W5 -> #REF! | X4: =AB4*X5 -> #REF! | Y4: =AB4*Y5 -> #REF! | Z4: =AB4*Z5 -> #REF! | AA4: =AB4*AA5 -> #REF! | AB4: =AB3-O3 -> #REF! | AC4: =AO4*AC5 -> #REF! | AD4: =AO4*AD5 -> #REF! | AE4: =AO4*AE5 -> #REF! | AF4: =AO4*AF5 -> #REF! | AG4: =AO4*AG5 -> #REF! | AH4: =AO4*AH5 -> #REF! | AI4: =AO4*AI5 -> #REF! | AJ4: =AO4*AJ5 -> #REF! | AK4: =AO4*AK5 -> #REF! | AL4: =AO4*AL5 -> #REF! | AM4: =AO4*AM5 -> #REF! | AN4: =AO4*AN5 -> #REF! | AO4: =AO3-AB3 -> #REF! | AP4: =BB4*AP5 -> #REF! | AQ4: =BB4*AQ5 -> #REF! | AR4: =BB4*AR5 -> #REF! | AS4: =BB4*AS5 -> #REF! | AT4: =BB4*AT5 -> #REF! | AU4: =BB4*AU5 -> #REF! | AV4: =BB4*AV5 -> #REF! | AW4: =BB4*AW5 -> #REF! | AX4: =BB4*AX5 -> #REF! | AY4: =BB4*AY5 -> #REF! | AZ4: =BB4*AZ5 -> #REF! | BA4: =BB4*BA5 -> #REF! | BB4: =BB3-AO3 -> #REF! | BC4: =BO4*BC5 -> #REF! | BD4: =BO4*BD5 -> #REF! | BE4: =BO4*BE5 -> #REF! | BF4: =BO4*BF5 -> #REF! | BG4: =BO4*BG5 -> #REF! | BH4: =BO4*BH5 -> #REF! | BI4: =BO4*BI5 -> #REF! | BJ4: =BO4*BJ5 -> #REF! | BK4: =BO4*BK5 -> #REF! | BL4: =BO4*BL5 -> #REF! | BM4: =BO4*BM5 -> #REF! | BN4: =BO4*BN5 -> #REF! | BO4: =BO3-BB3 -> #REF!
A5: сезонность | C5: =100%/12 -> 0.083333333 | D5: =100%/12 -> 0.083333333 | E5: =100%/12 -> 0.083333333 | F5: =100%/12 -> 0.083333333 | G5: =100%/12 -> 0.083333333 | H5: =100%/12 -> 0.083333333 | I5: =100%/12 -> 0.083333333 | J5: =100%/12 -> 0.083333333 | ... M5: =100%/12 -> 0.083333333 | N5: =100%-SUM(C5:M5) -> 0.083333333 | O5: =SUM(C5:N5) -> 1 | P5: =100%/12 -> 0.083333333 | Q5: =100%/12 -> 0.083333333 | R5: =100%/12 -> 0.083333333 | S5: =100%/12 -> 0.083333333 | T5: =100%/12 -> 0.083333333 | U5: =100%/12 -> 0.083333333 | V5: =100%/12 -> 0.083333333 | W5: =100%/12 -> 0.083333333 | ... Z5: =100%/12 -> 0.083333333 | AA5: =100%-SUM(P5:Z5) -> 0.083333333 | AB5: =SUM(P5:AA5) -> 1 | AC5: =100%/12 -> 0.083333333 | AD5: =100%/12 -> 0.083333333 | AE5: =100%/12 -> 0.083333333 | AF5: =100%/12 -> 0.083333333 | AG5: =100%/12 -> 0.083333333 | AH5: =100%/12 -> 0.083333333 | AI5: =100%/12 -> 0.083333333 | AJ5: =100%/12 -> 0.083333333 | ... AM5: =100%/12 -> 0.083333333 | AN5: =100%-SUM(AC5:AM5) -> 0.083333333 | AO5: =SUM(AC5:AN5) -> 1 | AP5: =100%/12 -> 0.083333333 | AQ5: =100%/12 -> 0.083333333 | AR5: =100%/12 -> 0.083333333 | AS5: =100%/12 -> 0.083333333 | AT5: =100%/12 -> 0.083333333 | AU5: =100%/12 -> 0.083333333 | AV5: =100%/12 -> 0.083333333 | AW5: =100%/12 -> 0.083333333 | ... AZ5: =100%/12 -> 0.083333333 | BA5: =100%-SUM(AP5:AZ5) -> 0.083333333 | BB5: =SUM(AP5:BA5) -> 1 | BC5: =100%/12 -> 0.083333333 | BD5: =100%/12 -> 0.083333333 | BE5: =100%/12 -> 0.083333333 | BF5: =100%/12 -> 0.083333333 | BG5: =100%/12 -> 0.083333333 | BH5: =100%/12 -> 0.083333333 | BI5: =100%/12 -> 0.083333333 | BJ5: =100%/12 -> 0.083333333 | ... BM5: =100%/12 -> 0.083333333 | BN5: =100%-SUM(BC5:BM5) -> 0.083333333 | BO5: =SUM(BC5:BN5) -> 1
A6: Средний чек лимита для пакета, тенге | C6: =O6 -> #REF! | D6: =O6 -> #REF! | E6: =O6 -> #REF! | F6: =O6 -> #REF! | G6: =O6 -> #REF! | H6: =O6 -> #REF! | I6: =O6 -> #REF! | J6: =O6 -> #REF! | K6: =O6 -> #REF! | L6: =O6 -> #REF! | M6: =O6 -> #REF! | N6: =O6 -> #REF! | O6: =#REF! -> #REF! | P6: =AB6 -> #REF! | Q6: =AB6 -> #REF! | R6: =AB6 -> #REF! | S6: =AB6 -> #REF! | T6: =AB6 -> #REF! | U6: =AB6 -> #REF! | V6: =AB6 -> #REF! | W6: =AB6 -> #REF! | X6: =AB6 -> #REF! | Y6: =AB6 -> #REF! | Z6: =AB6 -> #REF! | AA6: =AB6 -> #REF! | AB6: =#REF! -> #REF! | AC6: =AO6 -> #REF! | AD6: =AO6 -> #REF! | AE6: =AO6 -> #REF! | AF6: =AO6 -> #REF! | AG6: =AO6 -> #REF! | AH6: =AO6 -> #REF! | AI6: =AO6 -> #REF! | AJ6: =AO6 -> #REF! | AK6: =AO6 -> #REF! | AL6: =AO6 -> #REF! | AM6: =AO6 -> #REF! | AN6: =AO6 -> #REF! | AO6: =#REF! -> #REF! | AP6: =BB6 -> #REF! | AQ6: =BB6 -> #REF! | AR6: =BB6 -> #REF! | AS6: =BB6 -> #REF! | AT6: =BB6 -> #REF! | AU6: =BB6 -> #REF! | AV6: =BB6 -> #REF! | AW6: =BB6 -> #REF! | AX6: =BB6 -> #REF! | AY6: =BB6 -> #REF! | AZ6: =BB6 -> #REF! | BA6: =BB6 -> #REF! | BB6: =#REF! -> #REF! | BC6: =BO6 -> #REF! | BD6: =BO6 -> #REF! | BE6: =BO6 -> #REF! | BF6: =BO6 -> #REF! | BG6: =BO6 -> #REF! | BH6: =BO6 -> #REF! | BI6: =BO6 -> #REF! | BJ6: =BO6 -> #REF! | BK6: =BO6 -> #REF! | BL6: =BO6 -> #REF! | BM6: =BO6 -> #REF! | BN6: =BO6 -> #REF! | BO6: =#REF! -> #REF!
A7: Сумма установленного кредитного лимита, млн.тенге | C7: =C3*C6/1000000 -> #REF! | D7: =D3*D6/1000000 -> #REF! | E7: =E3*E6/1000000 -> #REF! | F7: =F3*F6/1000000 -> #REF! | G7: =G3*G6/1000000 -> #REF! | H7: =H3*H6/1000000 -> #REF! | I7: =I3*I6/1000000 -> #REF! | J7: =J3*J6/1000000 -> #REF! | ... BO7: =BO3*BO6/1000000 -> #REF!
A8: % клиентов, которые пользуются пакетом | C8: =O8 -> #REF! | D8: =O8 -> #REF! | E8: =O8 -> #REF! | F8: =O8 -> #REF! | G8: =O8 -> #REF! | H8: =O8 -> #REF! | I8: =O8 -> #REF! | J8: =O8 -> #REF! | K8: =O8 -> #REF! | L8: =O8 -> #REF! | M8: =O8 -> #REF! | N8: =O8 -> #REF! | O8: =#REF! -> #REF! | P8: =AB8 -> #REF! | Q8: =AB8 -> #REF! | R8: =AB8 -> #REF! | S8: =AB8 -> #REF! | T8: =AB8 -> #REF! | U8: =AB8 -> #REF! | V8: =AB8 -> #REF! | W8: =AB8 -> #REF! | X8: =AB8 -> #REF! | Y8: =AB8 -> #REF! | Z8: =AB8 -> #REF! | AA8: =AB8 -> #REF! | AB8: =#REF! -> #REF! | AC8: =AO8 -> #REF! | AD8: =AO8 -> #REF! | AE8: =AO8 -> #REF! | AF8: =AO8 -> #REF! | AG8: =AO8 -> #REF! | AH8: =AO8 -> #REF! | AI8: =AO8 -> #REF! | AJ8: =AO8 -> #REF! | AK8: =AO8 -> #REF! | AL8: =AO8 -> #REF! | AM8: =AO8 -> #REF! | AN8: =AO8 -> #REF! | AO8: =#REF! -> #REF! | AP8: =BB8 -> #REF! | AQ8: =BB8 -> #REF! | AR8: =BB8 -> #REF! | AS8: =BB8 -> #REF! | AT8: =BB8 -> #REF! | AU8: =BB8 -> #REF! | AV8: =BB8 -> #REF! | AW8: =BB8 -> #REF! | AX8: =BB8 -> #REF! | AY8: =BB8 -> #REF! | AZ8: =BB8 -> #REF! | BA8: =BB8 -> #REF! | BB8: =#REF! -> #REF! | BC8: =BO8 -> #REF! | BD8: =BO8 -> #REF! | BE8: =BO8 -> #REF! | BF8: =BO8 -> #REF! | BG8: =BO8 -> #REF! | BH8: =BO8 -> #REF! | BI8: =BO8 -> #REF! | BJ8: =BO8 -> #REF! | BK8: =BO8 -> #REF! | BL8: =BO8 -> #REF! | BM8: =BO8 -> #REF! | BN8: =BO8 -> #REF! | BO8: =#REF! -> #REF!
A9: Кол-во клиентов, использующих пакет (с загрузкой лимита и оплачивающих пакет) | C9: =C3*C8 -> #REF! | D9: =D3*D8 -> #REF! | E9: =E3*E8 -> #REF! | F9: =F3*F8 -> #REF! | G9: =G3*G8 -> #REF! | H9: =H3*H8 -> #REF! | I9: =I3*I8 -> #REF! | J9: =J3*J8 -> #REF! | ... BO9: =BO3*BO8 -> #REF!
A10: % загрузки лимита у клиентов, которые используют пакет (важна в связи с резервами) | C10: =O10 -> #REF! | D10: =O10 -> #REF! | E10: =O10 -> #REF! | F10: =O10 -> #REF! | G10: =O10 -> #REF! | H10: =O10 -> #REF! | I10: =O10 -> #REF! | J10: =O10 -> #REF! | K10: =O10 -> #REF! | L10: =O10 -> #REF! | M10: =O10 -> #REF! | N10: =O10 -> #REF! | O10: =#REF! -> #REF! | P10: =AB10 -> #REF! | Q10: =AB10 -> #REF! | R10: =AB10 -> #REF! | S10: =AB10 -> #REF! | T10: =AB10 -> #REF! | U10: =AB10 -> #REF! | V10: =AB10 -> #REF! | W10: =AB10 -> #REF! | X10: =AB10 -> #REF! | Y10: =AB10 -> #REF! | Z10: =AB10 -> #REF! | AA10: =AB10 -> #REF! | AB10: =#REF! -> #REF! | AC10: =AO10 -> #REF! | AD10: =AO10 -> #REF! | AE10: =AO10 -> #REF! | AF10: =AO10 -> #REF! | AG10: =AO10 -> #REF! | AH10: =AO10 -> #REF! | AI10: =AO10 -> #REF! | AJ10: =AO10 -> #REF! | AK10: =AO10 -> #REF! | AL10: =AO10 -> #REF! | AM10: =AO10 -> #REF! | AN10: =AO10 -> #REF! | AO10: =#REF! -> #REF! | AP10: =BB10 -> #REF! | AQ10: =BB10 -> #REF! | AR10: =BB10 -> #REF! | AS10: =BB10 -> #REF! | AT10: =BB10 -> #REF! | AU10: =BB10 -> #REF! | AV10: =BB10 -> #REF! | AW10: =BB10 -> #REF! | AX10: =BB10 -> #REF! | AY10: =BB10 -> #REF! | AZ10: =BB10 -> #REF! | BA10: =BB10 -> #REF! | BB10: =#REF! -> #REF! | BC10: =BO10 -> #REF! | BD10: =BO10 -> #REF! | BE10: =BO10 -> #REF! | BF10: =BO10 -> #REF! | BG10: =BO10 -> #REF! | BH10: =BO10 -> #REF! | BI10: =BO10 -> #REF! | BJ10: =BO10 -> #REF! | BK10: =BO10 -> #REF! | BL10: =BO10 -> #REF! | BM10: =BO10 -> #REF! | BN10: =BO10 -> #REF! | BO10: =#REF! -> #REF!
A11: Сумма загруженного кредитного лимита, млн тенге (это кредитный портфель на дату - по годам не складывать) | C11: =C7*C10 -> #REF! | D11: =D7*D10 -> #REF! | E11: =E7*E10 -> #REF! | F11: =F7*F10 -> #REF! | G11: =G7*G10 -> #REF! | H11: =H7*H10 -> #REF! | I11: =I7*I10 -> #REF! | J11: =J7*J10 -> #REF! | ... BO11: =BO7*BO10 -> #REF!
A12: Средний чек загрузки лимита, тенге | C12: =C11*1000000/C9 -> #REF! | D12: =D11*1000000/D9 -> #REF! | E12: =E11*1000000/E9 -> #REF! | F12: =F11*1000000/F9 -> #REF! | G12: =G11*1000000/G9 -> #REF! | H12: =H11*1000000/H9 -> #REF! | I12: =I11*1000000/I9 -> #REF! | J12: =J11*1000000/J9 -> #REF! | ... BO12: =BO11*1000000/BO9 -> #REF!
A13: Обороты использования лимитов за период, млн тенге | C13: =C7*C8 -> #REF! | D13: =D7*D8 -> #REF! | E13: =E7*E8 -> #REF! | F13: =F7*F8 -> #REF! | G13: =G7*G8 -> #REF! | H13: =H7*H8 -> #REF! | I13: =I7*I8 -> #REF! | J13: =J7*J8 -> #REF! | ... N13: =N7*N8 -> #REF! | O13: =SUM(C13:N13) -> #REF! | P13: =P7*P8 -> #REF! | Q13: =Q7*Q8 -> #REF! | R13: =R7*R8 -> #REF! | S13: =S7*S8 -> #REF! | T13: =T7*T8 -> #REF! | U13: =U7*U8 -> #REF! | V13: =V7*V8 -> #REF! | W13: =W7*W8 -> #REF! | ... AA13: =AA7*AA8 -> #REF! | AB13: =SUM(P13:AA13) -> #REF! | AC13: =AC7*AC8 -> #REF! | AD13: =AD7*AD8 -> #REF! | AE13: =AE7*AE8 -> #REF! | AF13: =AF7*AF8 -> #REF! | AG13: =AG7*AG8 -> #REF! | AH13: =AH7*AH8 -> #REF! | AI13: =AI7*AI8 -> #REF! | AJ13: =AJ7*AJ8 -> #REF! | ... AN13: =AN7*AN8 -> #REF! | AO13: =SUM(AC13:AN13) -> #REF! | AP13: =AP7*AP8 -> #REF! | AQ13: =AQ7*AQ8 -> #REF! | AR13: =AR7*AR8 -> #REF! | AS13: =AS7*AS8 -> #REF! | AT13: =AT7*AT8 -> #REF! | AU13: =AU7*AU8 -> #REF! | AV13: =AV7*AV8 -> #REF! | AW13: =AW7*AW8 -> #REF! | ... BA13: =BA7*BA8 -> #REF! | BB13: =SUM(AP13:BA13) -> #REF! | BC13: =BC7*BC8 -> #REF! | BD13: =BD7*BD8 -> #REF! | BE13: =BE7*BE8 -> #REF! | BF13: =BF7*BF8 -> #REF! | BG13: =BG7*BG8 -> #REF! | BH13: =BH7*BH8 -> #REF! | BI13: =BI7*BI8 -> #REF! | BJ13: =BJ7*BJ8 -> #REF! | ... BN13: =BN7*BN8 -> #REF! | BO13: =SUM(BC13:BN13) -> #REF!
A14: Погашение лимита за период, млн тенге | C14: =C11-B11-C13 -> #REF! | D14: =D11-C11-D13 -> #REF! | E14: =E11-D11-E13 -> #REF! | F14: =F11-E11-F13 -> #REF! | G14: =G11-F11-G13 -> #REF! | H14: =H11-G11-H13 -> #REF! | I14: =I11-H11-I13 -> #REF! | J14: =J11-I11-J13 -> #REF! | ... N14: =N11-M11-N13 -> #REF! | O14: =SUM(C14:N14) -> #REF! | P14: =P11-O11-P13 -> #REF! | Q14: =Q11-P11-Q13 -> #REF! | R14: =R11-Q11-R13 -> #REF! | S14: =S11-R11-S13 -> #REF! | T14: =T11-S11-T13 -> #REF! | U14: =U11-T11-U13 -> #REF! | V14: =V11-U11-V13 -> #REF! | W14: =W11-V11-W13 -> #REF! | ... AA14: =AA11-Z11-AA13 -> #REF! | AB14: =SUM(P14:AA14) -> #REF! | AC14: =AC11-AB11-AC13 -> #REF! | AD14: =AD11-AC11-AD13 -> #REF! | AE14: =AE11-AD11-AE13 -> #REF! | AF14: =AF11-AE11-AF13 -> #REF! | AG14: =AG11-AF11-AG13 -> #REF! | AH14: =AH11-AG11-AH13 -> #REF! | AI14: =AI11-AH11-AI13 -> #REF! | AJ14: =AJ11-AI11-AJ13 -> #REF! | ... AN14: =AN11-AM11-AN13 -> #REF! | AO14: =SUM(AC14:AN14) -> #REF! | AP14: =AP11-AO11-AP13 -> #REF! | AQ14: =AQ11-AP11-AQ13 -> #REF! | AR14: =AR11-AQ11-AR13 -> #REF! | AS14: =AS11-AR11-AS13 -> #REF! | AT14: =AT11-AS11-AT13 -> #REF! | AU14: =AU11-AT11-AU13 -> #REF! | AV14: =AV11-AU11-AV13 -> #REF! | AW14: =AW11-AV11-AW13 -> #REF! | ... BA14: =BA11-AZ11-BA13 -> #REF! | BB14: =SUM(AP14:BA14) -> #REF! | BC14: =BC11-BB11-BC13 -> #REF! | BD14: =BD11-BC11-BD13 -> #REF! | BE14: =BE11-BD11-BE13 -> #REF! | BF14: =BF11-BE11-BF13 -> #REF! | BG14: =BG11-BF11-BG13 -> #REF! | BH14: =BH11-BG11-BH13 -> #REF! | BI14: =BI11-BH11-BI13 -> #REF! | BJ14: =BJ11-BI11-BJ13 -> #REF! | ... BN14: =BN11-BM11-BN13 -> #REF! | BO14: =SUM(BC14:BN14) -> #REF!

Sheet Лист2
D1: юр лицо | E1: механика
A2: 1 | B2: 1 | C2: Кошельки симпли обороты до 330 дол | D2: Симпли | F2: ограничение по обороту и типу транзакции
A3: от 1.3 млн | B3: 1.1 | C3: Доверительный платеж | D3: Симпли | E3: пределожение- ответ | F3: отсечения?
A4: от 5 млн | B4: 1.2 | C4: лимит кредитной транзакции 30 дол ( включая снятие нал) | D4: Симпли? Доссым?
A5: из 30 дол | B5: 1.2.1 | C5: БНПЛ 150 ( только рассрочка, любого мерчанта через QR Каспия) | D5: Досссым
B6: 2.2.1 | C6: БНПЛ 1000 (( только рассрочка, любого мерчанта через QR Каспия) | D6: Досссым
J8: Механика
A9: 2 | B9: 1 | C9: Кошельки симпли | D9: Симпли
B10: 2 | C10: кеш 2000 | D10: Доссым | I10: от 5000000 клиентов | J10: от Доверительный платежа и от Кошелька
I11: отсечение | J11: лимит кредитной транзакции 30 дол в месяц (с обязат закрытием в месяц)
I12: DPD 2-3% | J12: погашение нанолендинга | AA12: симпли
I13: сколько их? | J13: наличие семейного пакета Билайна с использованием более чем 2 мес | W13: симпли кошелек | AA13: передает в Доссым ежедневно через инструемнт факторинга и собранные деньги по пакетам и кредитную задолженность
I14: 0.7 | J14: по внутренним проверкам Билайна ( бесплатные), корпо пакеты, анлимитед, семейный, аванс платеж | T14: клиент
D15: из 5 000 000 | E15: из 5 000 000 | F15: из 5 000 000 | W15: кошелек и доверительный плтеж | AB15: камиссия и пакеты
D16: Пакет 1 | E16: Пакет 2 | F16: Пакет 3 | J16: установлен лимит 30 дол | AB16: фандиг
D17: 30 дол | E17: 30 дол | F17: 30 дол | I17: DPD на кеше 3% | W17: от лица Доссыма | AA17: досым | AB17: 10 % комисия
E18: БНПЛ 150 | F18: БНПЛ 1000 | J18: снятие кеша как опция через 90 дней ( только транзакции) | W18: кеш 30 и БНПЛ 150 или 1000
I19: 0.9 | J19: загрузка | AB19: оплата 450 дол
AB20: курсы 500 дол
D21: стоимость пакета | I21: от 5000000 клиентов | J21: от Доверительный платежа и от Кошелька | W21: курсы | AA21: чп иванов
D22: 1000 | E22: 2000 | F22: 3000 | J22: БНПЛ 150 и 1000 ( только рассрочка, любого мерчанта через QR Каспия)
I23: хочешь перейти на следующий стадию дай согласие
I24: 0.5 | J24: согласие клиента
I25: отсечение | J25: установленный лимит
I26: 0.03 | J26: просрочка на 30 дол
I27: 0.6 | J27: проверки в КБ +все необх запросы
C28: симпли кошелек | J28: устанановленный лимит на 6 мес | AD28: >
C30: кошелек и доверительный плтеж | I30: 37% осталось для двух продуктов
I32: 0.1 | J32: на 1000 долларов на 3 и 6мес
I33: для 20% | J33: увеличение лимита до 2000
I35: 0.27 | J35: на 150 долл на 3 и 6 мес
I36: для30% | J36: увеличение лимита до 1000 дол

Sheet Product
B2: курс | D2: 500 | E2: =D2 -> 500 | F2: =E2 -> 500 | G2: =F2 -> 500 | H2: =G2 -> 500 | I2: =H2 -> 500
D3: 2024 | E3: 2025 | F3: 2026 | G3: 2027 | H3: 2028 | I3: 2029
B4: Кол-во клиентов Билайн | D4: 5000000 | E4: =D4*117% -> 5850000 | F4: =E4*117% -> 6844500 | G4: =F4*117% -> 8008065 | H4: =G4*117% -> 9369436 | I4: =H4*117% -> 10962240
B5: доля клиентов со смартфонами (конверсия в кол-во клиентов Билайн), % | D5: 0.83 | E5: 0.83 | F5: 0.83 | G5: 0.83 | H5: 0.83 | I5: 0.83
B7: Кол-во эл кошельков Simply | D7: =D8+D12 -> 5153552 | E7: =E8+E12 -> 6009584.8 | F7: =F8+F12 -> 7008132.5 | G7: =G8+G12 -> 8172971.1 | H7: =H8+H12 -> 9531850.6 | I7: =I8+I12 -> 11117161
B8: Билайн | D8: =D4*D5 -> 4150000 | E8: =E4*E5 -> 4855500 | F8: =F4*F5 -> 5680935 | G8: =G4*G5 -> 6646693.9 | H8: =H4*H5 -> 7776631.9 | I8: =I4*I5 -> 9098659.3
B9: доля идентифицированных, % | D9: =D10/D8 -> 0.032315181 | E9: =E10/E8 -> 0.027619813 | F9: =F10/F8 -> 0.023606677 | G9: =G10/G8 -> 0.020176647 | H9: =H10/H8 -> 0.017244998 | I9: =I10/I8 -> 0.014739314
B10: идентифицированные | D10: 134108 | E10: 134108 | F10: 134108 | G10: 134108 | H10: 134108 | I10: 134108
B11: неидентифицированные | D11: =D8-D10 -> 4015892 | E11: =E8-E10 -> 4721392 | F11: =F8-F10 -> 5546827 | G11: =G8-G10 -> 6512585.9 | H11: =H8-H10 -> 7642523.9 | I11: =I8-I10 -> 8964551.3
B12: неБилайн | D12: 1003552 | E12: =D12*115% -> 1154084.8 | F12: =E12*115% -> 1327197.5 | G12: =F12*115% -> 1526277.1 | H12: =G12*115% -> 1755218.7 | I12: =H12*115% -> 2018501.5
B13: доля идентифицированных, % | D13: =D14/D12 -> 0.13363333 | E13: =E14/E12 -> 0.1162029 | F13: =F14/F12 -> 0.101046 | G13: =G14/G12 -> 0.087866087 | H13: =H14/H12 -> 0.076405293 | I13: =I14/I12 -> 0.066439385
B14: идентифицированные | D14: 134108 | E14: 134108 | F14: 134108 | G14: 134108 | H14: 134108 | I14: 134108
B15: неидентифицированные | D15: =D12-D14 -> 869444 | E15: =E12-E14 -> 1019976.8 | F15: =F12-F14 -> 1193089.5 | G15: =G12-G14 -> 1392169.1 | H15: =H12-H14 -> 1621110.7 | I15: =I12-I14 -> 1884393.5
B16: Доля активных кошельков Simply, % | D16: 0.5 | E16: 0.5 | F16: 0.5 | G16: 0.5 | H16: 0.5 | I16: 0.5
B17: Количество активных кошельков Simply | D17: =ROUND(D7*D16,0) -> 2576776 | E17: =ROUND(E7*E16,0) -> 3004792 | F17: =ROUND(F7*F16,0) -> 3504066 | G17: =ROUND(G7*G16,0) -> 4086486 | H17: =ROUND(H7*H16,0) -> 4765925 | I17: =ROUND(I7*I16,0) -> 5558580
B18: Current Accounts | C18: Forte
B19: Debit Card | C19: Forte | D19: Модель Simply
B20: Доля активных карт от количество активных кошельков Simply,% | D20: 0.1 | E20: 0.1 | F20: 0.1 | G20: 0.1 | H20: 0.1 | I20: 0.1
B21: Количество активных карт | D21: =D17*D20 -> 257677.6 | E21: =E17*E20 -> 300479.2 | F21: =F17*F20 -> 350406.6 | G21: =G17*G20 -> 408648.6 | H21: =H17*H20 -> 476592.5 | I21: =I17*I20 -> 555858
B22: Средний остаток на карте, KZT | D22: 5000 | E22: 5000 | F22: 5000 | G22: 5000 | H22: 5000 | I22: 5000
B23: Ср.остатки на картах, KZT | D23: =D22*D21 -> 1288388000 | E23: =E22*E21 -> 1502396000 | F23: =F22*F21 -> 1.752033e+09 | G23: =G22*G21 -> 2.043243e+09 | H23: =H22*H21 -> 2382962500 | I23: =I22*I21 -> 2779290000
B24: ср.ставка, % | D24: 0.05 | E24: 0.05 | F24: 0.05 | G24: 0.05 | H24: 0.05 | I24: 0.05
B25: трансф.ставка, % (дв) | D25: 0.1 | E25: 0.1 | F25: 0.1 | G25: 0.1 | H25: 0.1 | I25: 0.1
B26: комиссии:
B27: снятие наличных
B28: переводы (внутри KZ, заграничные)
B29: конверсионные
B30: добавить UE
B31: Nano-Lending | C31: Finco
B32: доля кошельков, участвующих в продукте, % | D32: 0.15844679 | E32: 0.15498951 | F32: 0.17129783 | G32: 0.18693162 | H32: 0.20801123 | I32: 0.23340524
B33: количество кошельков, участвующих в продукте, шт | D33: =ROUND(D17*D32,0) -> 408282 | E33: =ROUND(E17*E32,0) -> 465711 | F33: =ROUND(F17*F32,0) -> 600239 | G33: =ROUND(G17*G32,0) -> 763893 | H33: =ROUND(H17*H32,0) -> 991366 | I33: =ROUND(I17*I32,0) -> 1297402
B34: Кол-во платежей на 1 клиента | D34: 1.7964564 | E34: 1.6483669 | F34: 1.4518882 | G34: 1.2951236 | H34: 1.1476457 | I34: 1.0084752
B35: количество выдач | D35: =D17*D32*D34 -> 733460.63 | E35: =E17*E32*E34 -> 767663.01 | F35: =F17*F32*F34 -> 871479.76 | G35: =G17*G32*G34 -> 989336.42 | H35: =H17*H32*H34 -> 1137736.9 | I35: =I17*I32*I34 -> 1308397.4
B37: сред чек, долл | D37: 3 | E37: 3 | F37: 3 | G37: 3 | H37: 3 | I37: 3
B38: Сред чек, тенге | D38: =D37*D2 -> 1500 | E38: =E37*E2 -> 1500 | F38: =F37*F2 -> 1500 | G38: =G37*G2 -> 1500 | H38: =H37*H2 -> 1500 | I38: =I37*I2 -> 1500
B39: Сумма выдачи, тенге | E39: =E38*E35 -> 1.1514945e+09 | F39: =F38*F35 -> 1.3072196e+09 | G39: =G38*G35 -> 1.4840046e+09 | H39: =H38*H35 -> 1.7066053e+09 | I39: =I38*I35 -> 1.9625961e+09
B40: Сумма погашений (1 неделя)
B41: Cost of risk | D41: 0.02
B42: Резервы
B43: Комиссионный доход 1 долл за 1 неделю
B44: трансф.ставка, % (1 неделя)
B46: Микро Займ по подписке ( 30 дол c возможностью снятия кеша) | C46: Forte
B47: аналогично Nano
B48: 30 долларов за месяц
B49: трансф.ставка, % (месяц)
B54: Карта рассрочки ( BNPL. 150 дол) новая клиентская база из кошельков Simply | C54: Forte
B55: BNPL 1000 дол Fortebank:Выращиваем клиентов до 1000 дол | C55: Forte
B56: Cash Credit Dossym ( от 300 до 2000 дол, от 6 до 60 мес) - новая клиентская база | C56: Finco
B57: Обновление кредитной истории | C57: Finco

Sheet Воронка (2)
D1: этим цветом выделены ячейки, которые требуют уточнений
B5: курс | D5: 500 | E5: =D5 -> 500 | F5: =E5 -> 500 | G5: =F5 -> 500 | H5: =G5 -> 500 | I5: =H5 -> 500 | K5: 2025-2029 г.
D6: 2024 | E6: 2025 | F6: 2026 | G6: 2027 | H6: 2028 | I6: 2029 | K6: тенге | L6: USD
B7: Кол-во клиентов Билайн | D7: 5000000 | E7: =D7*117% -> 5850000 | F7: =E7*117% -> 6844500 | G7: =F7*117% -> 8008065 | H7: =G7*117% -> 9369436 | I7: =H7*117% -> 10962240 | K7: уточнить данные по клеинтам Билайна
B8: Кол-во эл кошельков Simply | D8: 4100000 | E8: 5000000 | F8: 5560000 | G8: 6220000 | H8: 7000000 | I8: 8000000 | K8: настаивают , что это все клеиенты
B9: Билайн | D9: 4136295 | E9: =E7*E12 -> 4851165.1 | F9: =F7*F12 -> 5689552.2 | G9: =G7*G12 -> 6672792.2 | H9: =H7*H12 -> 7825905.8 | I9: =I7*I12 -> 9178234.2
B10: идентифицированные | D10: 134108
B11: неидентифицированные | D11: 869444
B12: конверсия в кол-во клиентов Билайн | D12: =D9/D7 -> 0.827259 | E12: =D12+0.2% -> 0.829259 | F12: =E12+0.2% -> 0.831259 | G12: =F12+0.2% -> 0.833259 | H12: =G12+0.2% -> 0.835259 | I12: =H12+0.2% -> 0.837259
B13: неБилайн | D13: 1003552 | E13: =D13*115% -> 1154084.8 | F13: =E13*115% -> 1327197.5 | G13: =F13*115% -> 1526277.1 | H13: =G13*115% -> 1755218.7 | I13: =H13*115% -> 2018501.5 | K13: не будет статитсти Билайна, Нужно выводить в отдельную ветку ( деделасть с Дианой воронку)
B14: идентифицированные | D14: 237217 | P14: ДОДЕЛАТЬ:
B15: неидентифицированные | D15: 3899077 | P15: 1. затраты на идентификацию и онбординг - Оксана
P16: 2. портфель _ Александр
A17: 1 | B17: Debit Card | P17: 3. затраты на коллекш - сколько и в какой момент списываем, стоимость возвращенного доллара ( уточнить у Оксана) софт и хард,
B18: Кол-во активных кошельков | D18: 956516 | E18: =E8*E19 -> 1000000 | F18: =F8*F19 -> 1112000 | G18: =G8*G19 -> 1244000 | H18: =H8*H19 -> 1400000 | I18: =I8*I19 -> 1600000 | P18: 4. резервы - Диана
B19: конверсия в кол-ве эл кошельков | D19: =D18/D8 -> 0.23329659 | E19: 0.2 | F19: 0.2 | G19: 0.2 | H19: 0.2 | I19: 0.2 | P19: 5. стоимость сервиса - предположить
B20: Кол-во активных карт | D20: 129307.44 | E20: 106852.5 | F20: 191162.5 | G20: 233951.02 | H20: 286317.02 | I20: 350404.28 | P20: 6. Пакеты подписки - Марина и Ко
B21: доля активных карт | D21: =D20/D18 -> 0.13518587 | E21: =E20/E18 -> 0.1068525 | F21: =F20/F18 -> 0.17190872 | G21: =G20/G18 -> 0.18806352 | H21: =H20/H18 -> 0.20451216 | I21: =I20/I18 -> 0.21900267
A23: 2 | B23: Nano-Lending
B24: Nano-Lending MAU | D24: 733460.63 | E24: 767663.01 | F24: 871479.76 | G24: 989336.42 | H24: 1137736.9 | I24: 1308397.4 | K24: проверить, это уникальный клиент или это выдача?
B25: конверсия в кол-ве эл кошельков | D25: =D24/D8 -> 0.17889284 | E25: =D25+1% -> 0.18889284 | F25: =E25+1% -> 0.19889284 | G25: =F25+1% -> 0.20889284 | H25: =G25+1% -> 0.21889284 | I25: =H25+1% -> 0.22889284
B26: Кол-во платежей на 1 клиента | D26: 1.7964564 | E26: 1.6483669 | F26: 1.4518882 | G26: 1.2951236 | H26: 1.1476457 | I26: 1.0084752
B27: Сред чек, тенге | D27: =D28*D5 -> 1500 | E27: =E28*E5 -> 1500 | F27: =F28*F5 -> 1500 | G27: =G28*G5 -> 1500 | H27: =H28*H5 -> 1500 | I27: =I28*I5 -> 1500
B28: сред чек, долл | D28: 3 | E28: 3 | F28: 3 | G28: 3 | H28: 3 | I28: 3
B29: Сумма выдачи, тенге | E29: =E27*E24 -> 1.1514945e+09 | F29: =F27*F24 -> 1.3072196e+09 | G29: =G27*G24 -> 1.4840046e+09 | H29: =H27*H24 -> 1.7066053e+09 | I29: =I27*I24 -> 1.9625961e+09 | K29: =E29+F29+G29+H29+I29 -> 7.6119202e+09 | L29: =E29/$E$5+F29/$F$5+G29/$G$5+H29/$H$5+I29/$I$5 -> 15223840
A31: 3 | B31: Микро Займ по подписке ( 30 дол c возможностью снятия кеша)
B32: % клиентов после внутренних проверок и отсечений внутри Билайна ( бесплатно) | E32: 0.7 | F32: 0.7 | G32: 0.7 | H32: 0.7 | I32: 0.7
B33: База после комплайнеса в банке | E33: =E8*E32 -> 3500000 | F33: =F8*F32 -> 3892000 | G33: =G8*G32 -> 4354000 | H33: =H8*H32 -> 4900000 | I33: =I8*I32 -> 5600000
B34: % клиентов,прошедших комплайнес в Банке | E34: 0.8 | F34: 0.8 | G34: 0.8 | H34: 0.8 | I34: 0.8
B35: База после внешних , платных проверок ( КБ, доходы, налоги, аресты) - действует 30 дней | E35: =E33*E34 -> 2800000 | F35: =F33*F34 -> 3113600 | G35: =G33*G34 -> 3483200 | H35: =H33*H34 -> 3920000 | I35: =I33*I34 -> 4480000
B36: % клиентов,после платных проверок | E36: 0.6 | F36: 0.6 | G36: 0.6 | H36: 0.6 | I36: 0.6
B37: Клиенты , которым сделаи оффер в приложении после всех проверок | E37: =E35*E36 -> 1680000 | F37: =F35*F36 -> 1868160 | G37: =G35*G36 -> 2089920 | H37: =H35*H36 -> 2352000 | I37: =I35*I36 -> 2688000
B38: % клиентов, которые откликнулись | E38: 0.3 | F38: 0.35 | G38: 0.4 | H38: 0.45 | I38: 0.5
B39: Клиенты с продуктом | E39: =E37*E38 -> 504000 | F39: =F37*F38 -> 653856 | G39: =G37*G38 -> 835968 | H39: =H37*H38 -> 1058400 | I39: =I37*I38 -> 1344000
B40: Take up, % | E40: 0.95 | F40: 0.95 | G40: 0.95 | H40: 0.95 | I40: 0.95
B41: Кол-во клиентов, согласившихся на пакет | E41: =E39*E40 -> 478800 | F41: =F39*F40 -> 621163.2 | G41: =G39*G40 -> 794169.6 | H41: =H39*H40 -> 1005480 | I41: =I39*I40 -> 1276800
B42: Средний чек лимита для пакета, тенге | E42: =E43*D5 -> 15000 | F42: =F43*E5 -> 15000 | G42: =G43*F5 -> 15000 | H42: =H43*G5 -> 15000 | I42: =I43*H5 -> 15000
B43: сред чек лимита на пакет, долл | E43: 30 | F43: 30 | G43: 30 | H43: 30 | I43: 30
B44: Сумма установленного кредитного лимита, тенге | E44: =E42*E41 -> 7182000000 | F44: =F42*F41 -> 9317448000 | G44: =G42*G41 -> 11912544000 | H44: =H42*H41 -> 15082200000 | I44: =I42*I41 -> 19152000000
B45: % клиентов, которые пользуются пакетом | E45: 0.8 | F45: 0.8 | G45: 0.8 | H45: 0.8 | I45: 0.8
B46: Кол-во клиентов, использующих пакет (с загрузкой лимита и оплачивающих пакет) | E46: =E41*E45 -> 383040 | F46: =F41*F45 -> 496930.56 | G46: =G41*G45 -> 635335.68 | H46: =H41*H45 -> 804384 | I46: =I41*I45 -> 1021440
B47: % загрузки лимита у клиентов, которые используют пакет (важна в связи с резервами) | E47: 0.05 | F47: 0.05 | G47: 0.05 | H47: 0.05 | I47: 0.05
B48: Сумма загруженного кредитного лимита, тенге (это кредитный портфель на дату - по годам не складывать) | E48: =E44*E47 -> 359100000 | F48: =F44*F47 -> 465872400 | G48: =G44*G47 -> 595627200 | H48: =H44*H47 -> 754110000 | I48: =I44*I47 -> 957600000 | K48: =I48 -> 957600000 | L48: =K48/I5 -> 1915200 | M48: с учетом среднего срока займа 1 мес (взяла 5% как просрочники и переходящие займы)
B49: Средний чек загрузки лимита, тенге | E49: =E51/E46 -> 97500 | F49: =F51/F46 -> 161091.98 | G49: =G51/G46 -> 162027.73 | H49: =H51/H46 -> 162661.9 | I49: =I51/I46 -> 162468.75
B50: сред чек загрузки лимита, долл | E50: =E49/E5 -> 195 | F50: =F49/F5 -> 322.18397 | G50: =G49/G5 -> 324.05547 | H50: =H49/H5 -> 325.32381 | I50: =I49/I5 -> 324.9375
B51: Оборот по выдаче, тенге - нужно будет рассчитать | E51: =[10]Лист4!O13*1000000 -> 37346400000 | F51: =[10]Лист4!AB13*1000000 -> 8.005153e+10 | G51: =[10]Лист4!AO13*1000000 -> 1.02942e+11 | H51: =[10]Лист4!BB13*1000000 -> 1.3084263e+11 | I51: =[10]Лист4!BO13*1000000 -> 1.6595208e+11 | K51: =E51+F51+G51+H51+I51 -> 5.1713464e+11 | L51: =E51/$E$5+F51/$F$5+G51/$G$5+H51/$H$5+I51/$I$5 -> 1.0342693e+09
B52: процесс онбординга???
A53: 4 | B53: Карта рассрочки ( BNPL. 150 дол) новая клиентская база из кошельков Simply
A54: 4.1. | B54: % клиентов после внутренних проверок и отсечений внутри Билайна ( бесплатно) | E54: 0.7 | F54: 0.7 | G54: 0.7 | H54: 0.7 | I54: 0.7
B55: База после комплайнеса в банке | E55: =E8*E54 -> 3500000 | F55: =F8*F54 -> 3892000 | G55: =G8*G54 -> 4354000 | H55: =H8*H54 -> 4900000 | I55: =I8*I54 -> 5600000
B56: % клиентов,прошедших комплайнес в Банке | E56: 0.8 | F56: 0.8 | G56: 0.8 | H56: 0.8 | I56: 0.8
B57: База после внешних , платных проверок ( КБ, доходы, налоги, аресты) - действует 30 дней | E57: =E55*E56 -> 2800000 | F57: =F55*F56 -> 3113600 | G57: =G55*G56 -> 3483200 | H57: =H55*H56 -> 3920000 | I57: =I55*I56 -> 4480000
B58: % клиентов,после платных проверок | E58: 0.7 | F58: 0.7 | G58: 0.7 | H58: 0.7 | I58: 0.7
B59: Клиенты , которым сделаи оффер в приложении после всех проверок | E59: =E57*E58 -> 1960000 | F59: =F57*F58 -> 2179520 | G59: =G57*G58 -> 2438240 | H59: =H57*H58 -> 2744000 | I59: =I57*I58 -> 3136000
B60: % клиентов, которые откликнулись | E60: 0.2 | F60: 0.25 | G60: 0.3 | H60: 0.35 | I60: 0.4
B61: Клиенты с продуктом | E61: =E59*E60 -> 392000 | F61: =F59*F60 -> 544880 | G61: =G59*G60 -> 731472 | H61: =H59*H60 -> 960400 | I61: =I59*I60 -> 1254400
B62: Take up, % | E62: 0.7 | F62: 0.7 | G62: 0.7 | H62: 0.7 | I62: 0.7
B63: Кол-во клиентов, согласившихся на карту рассрочки | E63: =E59*E60 -> 392000 | F63: =F59*F60 -> 544880 | G63: =G59*G60 -> 731472 | H63: =H59*H60 -> 960400 | I63: =I59*I60 -> 1254400
B64: Средний чек лимита для карты, тенге | E64: =E65*E5 -> 40000 | F64: =F65*F5 -> 44000 | G64: =G65*G5 -> 48400 | H64: =H65*H5 -> 53240 | I64: =I65*I5 -> 58564
B65: Средний чек лимита для карты, долл | E65: 80 | F65: =E65*110% -> 88 | G65: =F65*110% -> 96.8 | H65: =G65*110% -> 106.48 | I65: =H65*110% -> 117.128
B66: Сумма установленного кредитного лимита, тенге | E66: =E63*E64 -> 15680000000 | F66: =F63*F64 -> 23974720000 | G66: =G63*G64 -> 3.5403245e+10 | H66: =H63*H64 -> 51131696000 | I66: =I63*I64 -> 7.3462682e+10
B67: % клиентов, которые используют карту | E67: 0.99 | F67: =E67-0.5% -> 0.985 | G67: =F67-0.5% -> 0.98 | H67: =G67-0.5% -> 0.975 | I67: =H67-0.5% -> 0.97
B68: Кол-во клиентов, использующих карту (с загрузкой лимита) | E68: =E63*E67 -> 388080 | F68: =F63*F67 -> 536706.8 | G68: =G63*G67 -> 716842.56 | H68: =H63*H67 -> 936390 | I68: =I63*I67 -> 1216768
B69: % загрузки лимита у клиентов, которые используют карту (важна я связи с резервами) | E69: 0.7 | F69: =E69+2% -> 0.72 | G69: =F69+2% -> 0.74 | H69: =G69+2% -> 0.76 | I69: =H69+2% -> 0.78
B70: Сумма загруженного кредитного лимита, тенге (это кредитный портфель на дату - по годам не складывать) | E70: =E66*E69 -> 10976000000 | F70: =F66*F69 -> 17261798400 | G70: =G66*G69 -> 2.6198401e+10 | H70: =H66*H69 -> 38860088960 | I70: =I66*I69 -> 5.7300892e+10 | K70: =I70 -> 5.7300892e+10 | L70: =K70/I5 -> 1.1460178e+08
B71: Средний чек загрузки лимита, тенге | E71: =E70/E68 -> 28282.828 | F71: =F70/F68 -> 32162.437 | G71: =G70/G68 -> 36546.939 | H71: =H70/H68 -> 41499.897 | I71: =I70/I68 -> 47092.701
B72: сред чек загрузки лимита, долл | E72: =E71/E5 -> 56.565657 | F72: =F71/F5 -> 64.324873 | G72: =G71/G5 -> 73.093878 | H72: =H71/H5 -> 82.999795 | I72: =I71/I5 -> 94.185402
B73: Оборот по выдаче, тенге - нужно будет рассчитать | K73: =E73+F73+G73+H73+I73 -> 0 | L73: =E73/$E$5+F73/$F$5+G73/$G$5+H73/$H$5+I73/$I$5 -> 0 | M73: будет зависеть от среднего срока рассрочки и кэшовой части
A75: 4.2. | B75: BNPL 1000 дол Fortebank:Выращиваем клиентов до 1000 дол
B76: % клиентов после внутренних проверок и отсечений внутри Билайна ( бесплатно) | E76: 0.7 | F76: 0.7 | G76: 0.7 | H76: 0.7 | I76: 0.7
B77: База после комплайнеса в банке | E77: =E7*E76 -> 4095000 | F77: =F7*F76 -> 4791150 | G77: =G7*G76 -> 5605645.5 | H77: =H7*H76 -> 6558605.2 | I77: =I7*I76 -> 7673568.1
B78: % клиентов,прошедших комплайнес в Банке | E78: 0.8 | F78: 0.8 | G78: 0.8 | H78: 0.8 | I78: 0.8
B79: База после внешних , платных проверок ( КБ, доходы, налоги, аресты) - действует 30 дней | E79: =(E18-E20)*E78 -> 714518 | F79: =(F18-F20)*F78 -> 736670 | G79: =(G18-G20)*G78 -> 808039.19 | H79: =(H18-H20)*H78 -> 890946.38 | I79: =(I18-I20)*I78 -> 999676.58
B80: % клиентов,после платных проверок | E80: 0.2 | F80: 0.22 | G80: 0.25 | H80: 0.27 | I80: 0.3
B81: Клиенты , которым сделаи оффер в приложении после всех проверок | E81: =(E77+E79)*E80 -> 961903.6 | F81: =(F77+F79)*F80 -> 1216120.4 | G81: =(G77+G79)*G80 -> 1603421.2 | H81: =(H77+H79)*H80 -> 2011378.9 | I81: =(I77+I79)*I80 -> 2601973.4
B82: % клиентов, которые откликнулись | E82: 0.1 | F82: 0.15 | G82: 0.15 | H82: 0.15 | I82: 0.15
B83: Клиенты с продуктом | E83: =E81*E82 -> 96190.36 | F83: =F81*F82 -> 182418.06 | G83: =G81*G82 -> 240513.18 | H83: =H81*H82 -> 301706.84 | I83: =I81*I82 -> 390296.01
B84: Take up, % | E84: 0.6 | F84: 0.6 | G84: 0.6 | H84: 0.6 | I84: 0.6
B85: Кол-во клиентов, согласившихся на карту рассрочки | E85: =E81*E82 -> 96190.36 | F85: =F81*F82 -> 182418.06 | G85: =G81*G82 -> 240513.18 | H85: =H81*H82 -> 301706.84 | I85: =I81*I82 -> 390296.01
B86: Средний чек лимита для карты, тенге | E86: =E87*E5 -> 200000 | F86: =F87*F5 -> 210000 | G86: =G87*G5 -> 220500 | H86: =H87*H5 -> 231525 | I86: =I87*I5 -> 243101.25
B87: Средний чек лимита для карты, долл | E87: 400 | F87: =E87*105% -> 420 | G87: =F87*105% -> 441 | H87: =G87*105% -> 463.05 | I87: =H87*105% -> 486.2025
B88: Сумма установленного кредитного лимита, тенге | E88: =E85*E86 -> 1.9238072e+10 | F88: =F85*F86 -> 3.8307793e+10 | G88: =G85*G86 -> 5.3033155e+10 | H88: =H85*H86 -> 6.9852676e+10 | I88: =I85*I86 -> 9.4881448e+10
B89: % клиентов, которые используют карту | E89: 0.95 | F89: =E89-1% -> 0.94 | G89: =F89-1% -> 0.93 | H89: =G89-1% -> 0.92 | I89: =H89-1% -> 0.91
B90: Кол-во клиентов, использующих карту (с загрузкой лимита) | E90: =E85*E89 -> 91380.842 | F90: =F85*F89 -> 171472.98 | G90: =G85*G89 -> 223677.25 | H90: =H85*H89 -> 277570.29 | I90: =I85*I89 -> 355169.37
B91: % загрузки лимита у клиентов, которые используют карту (важна я связи с резервами) | E91: 0.5 | F91: 0.5 | G91: 0.5 | H91: 0.5 | I91: 0.5
B92: Сумма загруженного кредитного лимита, тенге (это кредитный портфель на дату - по годам не складывать) | E92: =E88*E91 -> 9.619036e+09 | F92: =F88*F91 -> 1.9153896e+10 | G92: =G88*G91 -> 2.6516578e+10 | H92: =H88*H91 -> 3.4926338e+10 | I92: =I88*I91 -> 4.7440724e+10 | K92: =I92 -> 4.7440724e+10 | L92: =K92/I5 -> 94881448
B93: Средний чек загрузки лимита, тенге | E93: =E92/E90 -> 105263.16 | F93: =F92/F90 -> 111702.13 | G93: =G92/G90 -> 118548.39 | H93: =H92/H90 -> 125828.8 | I93: =I92/I90 -> 133572.12
B94: сред чек загрузки лимита, долл | E94: =E93/E5 -> 210.52632 | F94: =F93/F5 -> 223.40426 | G94: =G93/G5 -> 237.09677 | H94: =H93/H5 -> 251.65761 | I94: =I93/I5 -> 267.14423
B95: Оборот по выдаче, тенге - нужно будет рассчитать | K95: =E95+F95+G95+H95+I95 -> 0 | L95: =E95/$E$5+F95/$F$5+G95/$G$5+H95/$H$5+I95/$I$5 -> 0 | M95: будет зависеть от среднего срока рассрочки и кэшовой части
A97: 5 | B97: Cash Credit Dossym ( от 300 до 2000 дол, от 6 до 60 мес) - новая клиентская база
B98: База клиентов для внутренних проверок | D98: =D8-D24 -> 3366539.4 | E98: =E8-E24 -> 4232337 | F98: =F8-F24 -> 4688520.2 | G98: =G8-G24 -> 5230663.6 | H98: =H8-H24 -> 5862263.1 | I98: =I8-I24 -> 6691602.6
B99: внутренние проверки (конверсия их базы для внутренних проверок) | E99: 0.5 | F99: 0.5 | G99: 0.5 | H99: 0.5 | I99: 0.5
B100: Клиенты, прошедшие внут проверки | E100: =E98*E99 -> 2116168.5 | F100: =F98*F99 -> 2344260.1 | G100: =G98*G99 -> 2615331.8 | H100: =H98*H99 -> 2931131.6 | I100: =I98*I99 -> 3345801.3
B101: % клиентов, которым будет предоставлен оффер | E101: 0.9 | F101: 0.9 | G101: 0.9 | H101: 0.9 | I101: 0.9
B102: Клиенты, которым отправлен оффер | E102: =E100*E101 -> 1904551.6 | F102: =F100*F101 -> 2109834.1 | G102: =G100*G101 -> 2353798.6 | H102: =H100*H101 -> 2638018.4 | I102: =I100*I101 -> 3011221.2
B103: % отклика | E103: 0.2 | F103: 0.2 | G103: 0.2 | H103: 0.2 | I103: 0.2
B104: Оформленные заявки | E104: =E102*E103 -> 380910.33 | F104: =F102*F103 -> 421966.82 | G104: =G102*G103 -> 470759.72 | H104: =H102*H103 -> 527603.68 | I104: =I102*I103 -> 602244.23
B105: AR, % ( внешнние полатные проверки) | E105: 0.3 | F105: 0.32 | G105: 0.35 | H105: 0.35 | I105: 0.35
B106: Кол-во одобренных клиентов | E106: =E104*E105 -> 114273.1 | F106: =F104*F105 -> 135029.38 | G106: =G104*G105 -> 164765.9 | H106: =H104*H105 -> 184661.29 | I106: =I104*I105 -> 210785.48
B107: Take up, % | E107: 0.8 | F107: 0.8 | G107: 0.8 | H107: 0.8 | I107: 0.8
...

Sheet Goals
A1: Goals
D3: 45657 | E3: 45747 | F3: 45838 | G3: 45930 | H3: 46022
D4: 2024 | E4: 2025 | F4: 2025 | G4: 2025 | H4: 2025 | I4: 2026 | J4: 2026 | K4: 2027 | L4: 2027 | M4: 2028 | N4: 2028 | O4: 2029 | P4: 2029 | R4: 2024 | S4: 2025 | T4: 2026 | U4: 2027 | V4: 2028 | W4: 2029
D5: Y0 | E5: Q1 | F5: Q2 | G5: Q3 | H5: Q4 | I5: H1 | J5: H2 | K5: H1 | L5: H2 | M5: H1 | N5: H2 | O5: H1 | P5: H2 | R5: Y0 | S5: Y1 | T5: Y2 | U5: Y3 | V5: Y4 | W5: Y5
D6: 0 | E6: 1 | F6: 2 | G6: 3 | H6: 4 | I6: 5 | J6: 6 | K6: 7 | L6: 8 | M6: 9 | N6: 10 | O6: 11 | P6: 12
A7: Параметры | B7: ЕИ | C7: Отв.исп.
A8: The clients of Beeline | B8: person | D8: ='Funnel QH'!D8 -> 5000000 | E8: ='Funnel QH'!E8 -> 5295890.4 | F8: ='Funnel QH'!F8 -> 5595068.5 | G8: ='Funnel QH'!G8 -> 5897534.2 | H8: ='Funnel QH'!H8 -> 6200000 | I8: ='Funnel QH'!I8 -> 6497500 | J8: ='Funnel QH'!J8 -> 6795000 | K8: ='Funnel QH'!K8 -> 7147500 | ... P8: ='Funnel QH'!P8 -> 9510000 | R8: =D8 -> 5000000 | S8: =H8 -> 6200000 | T8: =J8 -> 6795000 | U8: =L8 -> 7500000 | V8: =N8 -> 8365000 | W8: =P8 -> 9510000
A9: El. Wallet Simply | B9: unit | D9: ='Funnel QH'!D11 -> 4100000 | E9: ='Funnel QH'!E11 -> 4320359.5 | F9: ='Funnel QH'!F11 -> 4543167.5 | G9: ='Funnel QH'!G11 -> 4768423.9 | H9: ='Funnel QH'!H11 -> 5006080.3 | I9: ='Funnel QH'!I11 -> 5264475.3 | J9: ='Funnel QH'!J11 -> 5562450.4 | K9: ='Funnel QH'!K11 -> 5881699.8 | ... P9: ='Funnel QH'!P11 -> 8003045.6 | R9: =D9 -> 4100000 | S9: =H9 -> 5006080.3 | T9: =J9 -> 5562450.4 | U9: =L9 -> 6215949.1 | V9: =N9 -> 7002496.2 | W9: =P9 -> 8003045.6
A10: Client of ecosystem with el.wallet Simply | B10: person | D10: ='Funnel QH'!D24 -> 3280000 | E10: ='Funnel QH'!E24 -> 3456287.6 | F10: ='Funnel QH'!F24 -> 3634534 | G10: ='Funnel QH'!G24 -> 3814739.1 | H10: ='Funnel QH'!H24 -> 4004864.3 | I10: ='Funnel QH'!I24 -> 4211580.3 | J10: ='Funnel QH'!J24 -> 4449960.3 | K10: ='Funnel QH'!K24 -> 4705359.8 | ... P10: ='Funnel QH'!P24 -> 6402436.5 | R10: =D10 -> 3280000 | S10: =H10 -> 4004864.3 | T10: =J10 -> 4449960.3 | U10: =L10 -> 4972759.3 | V10: =N10 -> 5601997 | W10: =P10 -> 6402436.5
A11: Active clients with credit limit | B11: person | R11: =Funnel!D117 -> 0 | S11: =Funnel!E117 -> 55590.32 | T11: =Funnel!F117 -> 399794.5 | U11: =Funnel!G117 -> 851814.28 | V11: =Funnel!H117 -> 1224673.5 | W11: =Funnel!I117 -> 1507002.9
A12: Active clients with credit | B12: person | R12: =Funnel!D119 -> 0 | S12: =Funnel!E119 -> 62782.218 | T12: =Funnel!F119 -> 380630.58 | U12: =Funnel!G119 -> 786819.94 | V12: =Funnel!H119 -> 1127530.8 | W12: =Funnel!I119 -> 1374307.5
A13: Merchants (legal entities and individual entrepreneurs) | B13: unit | D13: ='Funnel QH'!D25 -> 0 | E13: ='Funnel QH'!E25 -> 0 | F13: ='Funnel QH'!F25 -> 0 | G13: ='Funnel QH'!G25 -> 0 | H13: ='Funnel QH'!H25 -> 0 | I13: ='Funnel QH'!I25 -> 0 | J13: ='Funnel QH'!J25 -> 30000 | K13: ='Funnel QH'!K25 -> 49833.333 | ... P13: ='Funnel QH'!P25 -> 149000 | R13: =D13 -> 0 | S13: =H13 -> 0 | T13: =J13 -> 30000 | U13: =L13 -> 69666.667 | V13: =N13 -> 109333.33 | W13: =P13 -> 149000
A14: Active merchants | B14: unit | D14: ='Merchants(corp)'!D164 -> 0 | E14: ='Merchants(corp)'!E164 -> 0 | F14: ='Merchants(corp)'!F164 -> 0 | G14: ='Merchants(corp)'!G164 -> 0 | H14: ='Merchants(corp)'!H164 -> 0 | I14: ='Merchants(corp)'!I164 -> 0 | J14: ='Merchants(corp)'!J164 -> 15000 | K14: ='Merchants(corp)'!K164 -> 26162.5 | ... P14: ='Merchants(corp)'!P164 -> 99837.125 | R14: =D14 -> 0 | S14: =H14 -> 0 | T14: =J14 -> 15000 | U14: =L14 -> 38403.75 | V14: =N14 -> 66447.675 | W14: =P14 -> 99837.125
A15: Дебетовые карты Simply | C15: Forte
A16: % от кол-ва клиентов экосистемы | B16: % | E16: =E17/E10 -> 0.02498924 | F16: =F17/F10 -> 0.025296228 | G16: =G17/G10 -> 0.026384504 | H16: =H17/H10 -> 0.027534017 | I16: =I17/I10 -> 0.038618521 | J16: =J17/J10 -> 0.048319532 | K16: =K17/K10 -> 0.051579308 | L16: =L17/L10 -> 0.054371907 | ... P16: =P17/P10 -> 0.051788416 | R16: =D16 -> 0 | S16: =H16 -> 0.027534017 | T16: =J16 -> 0.048319532 | U16: =L16 -> 0.054371907 | V16: =N16 -> 0.054521175 | W16: =P16 -> 0.051788416
A17: Количество карт на конец периода | B17: шт | C17: Finmodel SIMPLY | D17: 81000 | E17: 86370 | F17: 91940 | G17: 100650 | H17: 110270 | I17: =AVERAGE(J17,H17) -> 162645 | J17: 215020 | K17: =AVERAGE(L17,J17) -> 242699.2 | L17: 270378.41 | M17: =AVERAGE(N17,L17) -> 287902.93 | N17: 305427.46 | O17: =AVERAGE(P17,N17) -> 318499.75 | P17: 331572.05 | R17: =D17 -> 81000 | S17: =H17 -> 110270 | T17: =J17 -> 215020 | U17: =L17 -> 270378.41 | V17: =N17 -> 305427.46 | W17: =P17 -> 331572.05
A18: Остатки (на конец периода) | B18: 000 USD | C18: Факторный анализ для FPA | E18: =326966.90169915/500 -> 653.9338 | F18: =F17*$E18/$E17 -> 696.10598 | G18: =G17*$E18/$E17 -> 762.05207 | H18: =502521.813794505/500 -> 1005.0436 | I18: =I17*H18/H17 -> 1482.4097 | J18: =943978.77954158/500 -> 1887.9576 | K18: =K17*J18/J17 -> 2130.9915 | L18: =1213036.20494188/500 -> 2426.0724 | M18: =M17*L18/L17 -> 2583.3178 | N18: =1558781.68703578/500 -> 3117.5634 | O18: =O17*N18/N17 -> 3250.9951 | P18: =2003073.22892685/500 -> 4006.1465 | R18: =D18 -> 0 | S18: =H18 -> 1005.0436 | T18: =J18 -> 1887.9576 | U18: =L18 -> 2426.0724 | V18: =N18 -> 3117.5634 | W18: =P18 -> 4006.1465
A19: Комиссионные доходы | B19: 000 USD | C19: Факторный анализ для FPA | E19: =1472388.52797171/4/500 -> 736.19426 | F19: =1472388.52797171/4/500 -> 736.19426 | G19: =1472388.52797171/4/500 -> 736.19426 | H19: =1472388.52797171/4/500 -> 736.19426 | I19: =2810288.92365012/2/500 -> 2810.2889 | J19: =2810288.92365012/2/500 -> 2810.2889 | K19: =3595873.85026496/2/500 -> 3595.8739 | L19: =3595873.85026496/2/500 -> 3595.8739 | M19: =4604802.75037225/2/500 -> 4604.8028 | N19: =4604802.75037225/2/500 -> 4604.8028 | O19: =5900639.34576269/2/500 -> 5900.6393 | P19: =5900639.34576269/2/500 -> 5900.6393
A20: Операционные расходы | B20: 000 USD | C20: Факторный анализ для FPA | E20: =-1204077.19822955/4/500 -> -602.0386 | F20: =-1204077.19822955/4/500 -> -602.0386 | G20: =-1204077.19822955/4/500 -> -602.0386 | H20: =-1204077.19822955/4/500 -> -602.0386 | I20: =-1399194.37543398/2/500 -> -1399.1944 | J20: =-1399194.37543398/2/500 -> -1399.1944 | K20: =-1624610.29352731/2/500 -> -1624.6103 | L20: =-1624610.29352731/2/500 -> -1624.6103 | M20: =-1859998.82599472/2/500 -> -1859.9988 | N20: =-1859998.82599472/2/500 -> -1859.9988 | O20: =-2333382.96480478/2/500 -> -2333.383 | P20: =-2333382.96480478/2/500 -> -2333.383
A21: Среднемесячная прибыль на 1 карту | B21: USD | C21: PL продуктов 2024 Act | D21: 2.0747097 | E21: 2.0747097 | F21: 2.0747097 | G21: 2.0747097 | H21: 2.0747097 | I21: 2.0747097 | J21: 2.0747097 | K21: 2.0747097 | L21: 2.0747097 | M21: 2.0747097 | N21: 2.0747097 | O21: 2.0747097 | P21: 2.0747097 | R21: =D21 -> 2.0747097 | S21: =H21 -> 2.0747097 | T21: =J21 -> 2.0747097 | U21: =L21 -> 2.0747097 | V21: =N21 -> 2.0747097 | W21: =P21 -> 2.0747097
A22: Прибыль (до уплаты налогов) | B22: 000 USD | D22: =73000*D21/1000*12 -> 1817.4457 | E22: =(D17+E17)/2*E21*3/1000 -> 520.86625 | F22: =(E17+F17)/2*F21*3/1000 -> 554.91224 | G22: =(F17+G17)/2*G21*3/1000 -> 599.35252 | H22: =(G17+H17)/2*H21*3/1000 -> 656.39667 | I22: =(H17+I17)/2*I21*6/1000 -> 1698.6582 | J22: =(I17+J17)/2*J21*6/1000 -> 2350.6358 | K22: =(J17+K17)/2*K21*6/1000 -> 2848.9035 | L22: =(K17+L17)/2*L21*6/1000 -> 3193.4613 | M22: =(L17+M17)/2*M21*6/1000 -> 3474.8152 | N22: =(M17+N17)/2*N21*6/1000 -> 3692.965 | O22: =(N17+O17)/2*O21*6/1000 -> 3883.4036 | P22: =(O17+P17)/2*P21*6/1000 -> 4046.1309 | R22: =D22 -> 1817.4457 | S22: =E22+F22+G22+H22 -> 2331.5277 | T22: =I22+J22 -> 4049.294 | U22: =K22+L22 -> 6042.3648 | V22: =M22+N22 -> 7167.7802 | W22: =O22+P22 -> 7929.5345 | Y22: =W22/$W$124 -> 0.048852549
A24: Nano-Lending | C24: Finco
A25: % от кол-ва клиентов экосистемы | B25: % | E25: =E26/E10 -> 0.091528139 | F25: =F26/F10 -> 0.087039377 | G25: =G26/G10 -> 0.082927708 | H25: =H26/H10 -> 0.078990836 | I25: =I26/I10 -> 0.15021572 | J25: =J26/J10 -> 0.14216881 | K25: =K26/K10 -> 0.13615462 | L25: =L26/L10 -> 0.12883319 | ... P25: =P26/P10 -> 0.10304564 | R25: =D25 -> 0 | S25: =H25 -> 0.078990836 | T25: =J25 -> 0.14216881 | U25: =L25 -> 0.12883319 | V25: =N25 -> 0.11654048 | W25: =P25 -> 0.10304564
A26: Количество выданных займов | B26: шт | C26: Finmodel SIMPLY | D26: 1098025.1 | E26: =1265390.29514024/4 -> 316347.57 | F26: =1265390.29514024/4 -> 316347.57 | G26: =1265390.29514024/4 -> 316347.57 | H26: =1265390.29514024/4 -> 316347.57 | I26: =1265291.14780088/2 -> 632645.57 | J26: =1265291.14780088/2 -> 632645.57 | K26: 640656.46 | L26: 640656.46 | M26: 652859.44 | N26: 652859.44 | O26: 659743.15 | P26: 659743.15 | R26: =D26 -> 1098025.1 | S26: =E26+F26+G26+H26 -> 1265390.3 | T26: =I26+J26 -> 1265291.1 | U26: =K26+L26 -> 1281312.9 | V26: =M26+N26 -> 1305718.9 | W26: =O26+P26 -> 1319486.3
A27: Комиссионные доходы | B27: 000 USD | C27: Факторный анализ для FPA | E27: =2120216.51288896/500/4 -> 1060.1083 | F27: =2120216.51288896/500/4 -> 1060.1083 | G27: =2120216.51288896/500/4 -> 1060.1083 | H27: =2120216.51288896/500/4 -> 1060.1083 | I27: =2226052.90656702/500/2 -> 2226.0529 | J27: =2226052.90656702/500/2 -> 2226.0529 | K27: =2366952.37582407/500/2 -> 2366.9524 | L27: =2366952.37582407/500/2 -> 2366.9524 | M27: =2532639.04213175/500/2 -> 2532.639 | N27: =2532639.04213175/500/2 -> 2532.639 | O27: =2687310.16254222/500/2 -> 2687.3102 | P27: =2687310.16254222/500/2 -> 2687.3102 | S27: =E27+F27+G27+H27 -> 4240.433 | T27: =I27+J27 -> 4452.1058 | U27: =K27+L27 -> 4733.9048 | V27: =M27+N27 -> 5065.2781 | W27: =O27+P27 -> 5374.6203
A28: Операционные расходы | B28: 000 USD | C28: Факторный анализ для FPA | E28: =-754108.020657356/500/4 -> -377.05401 | F28: =-754108.020657356/500/4 -> -377.05401 | G28: =-754108.020657356/500/4 -> -377.05401 | H28: =-754108.020657356/500/4 -> -377.05401 | I28: =-664573.031479807/500/2 -> -664.57303 | J28: =-664573.031479807/500/2 -> -664.57303 | K28: =-645823.790682006/500/2 -> -645.82379 | L28: =-645823.790682006/500/2 -> -645.82379 | M28: =-650458.881388264/500/2 -> -650.45888 | N28: =-650458.881388264/500/2 -> -650.45888 | O28: =-711365.338718628/500/2 -> -711.36534 | P28: =-711365.338718628/500/2 -> -711.36534 | S28: =H28+J28+L28+N28 -> -2337.9097 | T28: =P28+#REF! -> #REF! | U28: =#REF!+#REF! -> #REF! | V28: =#REF!+#REF! -> #REF! | W28: =#REF!+#REF! -> #REF!
A29: Прибыль с 1 займа | B29: USD | C29: PL продуктов 2024 Act | D29: 3 | E29: 3 | F29: 3 | G29: 3 | H29: 3 | I29: 3 | J29: 3 | K29: 3 | L29: 3 | M29: 3 | N29: 3 | O29: 3 | P29: 3 | R29: =D29 -> 3 | S29: =H29 -> 3 | T29: =J29 -> 3 | U29: =L29 -> 3 | V29: =N29 -> 3 | W29: =P29 -> 3
A30: Прибыль (до уплаты налогов) | B30: 000 USD | D30: =D26*D29/1000 -> 3294.0752 | E30: =E26*E29/1000*3 -> 2847.1282 | F30: =F26*F29/1000*3 -> 2847.1282 | G30: =G26*G29/1000*3 -> 2847.1282 | H30: =H26*H29/1000*3 -> 2847.1282 | I30: =I26*I29/1000 -> 1897.9367 | J30: =J26*J29/1000 -> 1897.9367 | K30: =K26*K29/1000 -> 1921.9694 | L30: =L26*L29/1000 -> 1921.9694 | M30: =M26*M29/1000 -> 1958.5783 | N30: =N26*N29/1000 -> 1958.5783 | O30: =O26*O29/1000 -> 1979.2294 | P30: =P26*P29/1000 -> 1979.2294 | R30: =D30 -> 3294.0752 | S30: =E30+F30+G30+H30 -> 11388.513 | T30: =I30+J30 -> 3795.8734 | U30: =K30+L30 -> 3843.9388 | V30: =M30+N30 -> 3917.1567 | W30: =O30+P30 -> 3958.4589 | Y30: =W30/$W$124 -> 0.02438741
A32: Платные подписки на пакеты услуг | C32: Forte
A33: Прибыль (до уплаты налогов) | B33: 000 USD | G33: ='packages (indiv)'!BT$95 -> -719.73813 | H33: ='packages (indiv)'!BU$95 -> -872.68316 | I33: ='packages (indiv)'!BV$95 -> -3031.5865 | J33: ='packages (indiv)'!BW$95 -> -3852.4112 | K33: ='packages (indiv)'!BX$95 -> 1263.7236 | L33: ='packages (indiv)'!BY$95 -> 2599.2777 | M33: ='packages (indiv)'!BZ$95 -> 9636.2258 | N33: ='packages (indiv)'!CA$95 -> 11479.161 | ... Q33: ='packages (indiv)'!CD$95 -> 0 | T33: =I33+J33 -> -6883.9977 | U33: =K33+L33 -> 3863.0013 | V33: =M33+N33 -> 21115.387 | W33: =O33+P33 -> 39385.325 | Y33: =W33/$W$124 -> 0.24264647
A35: в т.ч. Дебетовые карты (план)
A36: Прибыль (до уплаты налогов) | E36: ='Debit card (indiv)'!BR$95 -> 0 | F36: ='Debit card (indiv)'!BS$95 -> 0 | G36: ='Debit card (indiv)'!BT$95 -> -92.821072 | H36: ='Debit card (indiv)'!BU$95 -> -241.53794 | I36: ='Debit card (indiv)'!BV$95 -> -690.44226 | J36: ='Debit card (indiv)'!BW$95 -> -1525.4348 | K36: ='Debit card (indiv)'!BX$95 -> -297.57002 | L36: ='Debit card (indiv)'!BY$95 -> -377.23838 | ... P36: ='Debit card (indiv)'!CC$95 -> 6979.3543 | S36: =E36+F36+G36+H36 -> -334.35901 | T36: =I36+J36 -> -2215.877 | U36: =K36+L36 -> -674.8084 | V36: =M36+N36 -> 5554.5244 | W36: =O36+P36 -> 13114.874 | Y36: =W36/$W$124 -> 0.080798568
A38: в т.ч. Микро Займ по подписке ( 30 дол c возможностью снятия кеша) | C38: Forte
A39: Прибыль (до уплаты налогов) | B39: 000 USD | E39: ='Micro_30 (indiv)'!BR$73 -> 0 | F39: ='Micro_30 (indiv)'!BS$73 -> 0 | G39: ='Micro_30 (indiv)'!BT$73 -> -12.008725 | H39: ='Micro_30 (indiv)'!BU$73 -> -37.942127 | I39: ='Micro_30 (indiv)'!BV$73 -> -221.19214 | J39: ='Micro_30 (indiv)'!BW$73 -> -523.8303 | K39: ='Micro_30 (indiv)'!BX$73 -> -788.11334 | L39: ='Micro_30 (indiv)'!BY$73 -> -1165.9014 | ... P39: ='Micro_30 (indiv)'!CC$73 -> -1933.8642 | S39: =E39+F39+G39+H39 -> -49.950852 | T39: =I39+J39 -> -745.02245 | U39: =K39+L39 -> -1954.0148 | V39: =M39+N39 -> -3018.5422 | W39: =O39+P39 -> -3645.8402 | Y39: =W39/$W$124 -> -0.022461418
A41: в т.ч. Карта рассрочки ( BNPL 150 дол) новая клиентская база из кошельков Simply - 4 мес | C41: Forte
A42: Прибыль (до уплаты налогов) | B42: 000 USD | E42: ='Installment card_150 (indiv)'!BR$133 -> 0 | F42: ='Installment card_150 (indiv)'!BS$133 -> 0 | G42: ='Installment card_150 (indiv)'!BT$133 -> -2.4993212 | H42: ='Installment card_150 (indiv)'!BU$133 -> -20.972351 | I42: ='Installment card_150 (indiv)'!BV$133 -> -420.11766 | J42: ='Installment card_150 (indiv)'!BW$133 -> -1090.1332 | K42: ='Installment card_150 (indiv)'!BX$133 -> -1808.2952 | L42: ='Installment card_150 (indiv)'!BY$133 -> -2547.1333 | ... P42: ='Installment card_150 (indiv)'!CC$133 -> -3700.8175 | S42: =E42+F42+G42+H42 -> -23.471672 | T42: =I42+J42 -> -1510.2508 | U42: =K42+L42 -> -4355.4285 | V42: =M42+N42 -> -6570.9912 | W42: =O42+P42 -> -7337.5865 | Y42: =W42/$W$124 -> -0.045205656
A44: в т.ч. Карта рассрочки ( BNPL 1000 дол) - 12 мес | C44: Forte
A45: Прибыль (до уплаты налогов) | B45: 000 USD | E45: ='Installment card_1000 (indiv)'!BR$133 -> 0 | F45: ='Installment card_1000 (indiv)'!BS$133 -> 0 | G45: ='Installment card_1000 (indiv)'!BT$133 -> 0 | H45: ='Installment card_1000 (indiv)'!BU$133 -> 0 | I45: ='Installment card_1000 (indiv)'!BV$133 -> 0 | J45: ='Installment card_1000 (indiv)'!BW$133 -> -783.23182 | K45: ='Installment card_1000 (indiv)'!BX$133 -> -2033.7016 | L45: ='Installment card_1000 (indiv)'!BY$133 -> -3415.5142 | ... P45: ='Installment card_1000 (indiv)'!CC$133 -> -5836.9682 | S45: =E45+F45+G45+H45 -> 0 | T45: =I45+J45 -> -783.23182 | U45: =K45+L45 -> -5449.2158 | V45: =M45+N45 -> -9501.9972 | W45: =O45+P45 -> -11295.325 | Y45: =W45/$W$124 -> -0.069588626
A47: Вклады и сбережения | C47: Forte
A48: % от кол-ва клиентов экосистемы | B48: % | G48: =G49/G10 -> 0.01 | H48: =H49/H10 -> 0.0119395 | I48: =I49/I10 -> 0.01431288 | J48: =J49/J10 -> 0.017154547 | K48: =K49/K10 -> 0.023650044 | L48: =L49/L10 -> 0.032481392 | M48: =M49/M10 -> 0.04477591 | N48: =N49/N10 -> 0.061744285 | ... P48: =P49/P10 -> 0.063472623 | S48: =H48 -> 0.0119395 | T48: =J48 -> 0.017154547 | U48: =L48 -> 0.032481392 | V48: =N48 -> 0.061744285 | W48: =P48 -> 0.063472623
A49: Количество счетов | B49: шт | G49: ='Deposits (indiv)'!G11 -> 38147.391 | H49: ='Deposits (indiv)'!H11 -> 47816.077 | I49: ='Deposits (indiv)'!I11 -> 60279.843 | J49: ='Deposits (indiv)'!J11 -> 76337.054 | K49: ='Deposits (indiv)'!K11 -> 111281.97 | L49: ='Deposits (indiv)'!L11 -> 161522.15 | M49: ='Deposits (indiv)'!M11 -> 236447.53 | N49: ='Deposits (indiv)'!N11 -> 345891.3 | ... P49: ='Deposits (indiv)'!P11 -> 406379.44 | S49: =H49 -> 47816.077 | T49: =J49 -> 76337.054 | U49: =L49 -> 161522.15 | V49: =N49 -> 345891.3 | W49: =P49 -> 406379.44
A50: Портфель (средние остатки) | B50: 000 USD | G50: ='Deposits (indiv)'!G15 -> 23475.905 | H50: ='Deposits (indiv)'!H15 -> 26455.909 | I50: ='Deposits (indiv)'!I15 -> 33366.955 | J50: ='Deposits (indiv)'!J15 -> 42409.835 | K50: ='Deposits (indiv)'!K15 -> 79792.834 | L50: ='Deposits (indiv)'!L15 -> 137388.13 | M50: ='Deposits (indiv)'!M15 -> 202314.68 | N50: ='Deposits (indiv)'!N15 -> 297559.69 | ... P50: ='Deposits (indiv)'!P15 -> 414860.44 | S50: =H50 -> 26455.909 | T50: =J50 -> 42409.835 | U50: =L50 -> 137388.13 | V50: =N50 -> 297559.69 | W50: =P50 -> 414860.44
A51: Маржинальность | B51: % годовых | G51: ='Deposits (indiv)'!G23 -> 0.012 | H51: ='Deposits (indiv)'!H23 -> 0.018197754 | I51: ='Deposits (indiv)'!I23 -> 0.0190575 | J51: ='Deposits (indiv)'!J23 -> 0.019035726 | K51: ='Deposits (indiv)'!K23 -> 0.0071527913 | L51: ='Deposits (indiv)'!L23 -> 0.0088686579 | M51: ='Deposits (indiv)'!M23 -> 0.0039273576 | N51: ='Deposits (indiv)'!N23 -> 0.0039525704 | ... P51: ='Deposits (indiv)'!P23 -> 0.005204851 | S51: ='Deposits (indiv)'!S23 -> 0.0076419112 | T51: ='Deposits (indiv)'!T23 -> 0.019045314 | U51: ='Deposits (indiv)'!U23 -> 0.0082382442 | V51: ='Deposits (indiv)'!V23 -> 0.003942366 | W51: ='Deposits (indiv)'!W23 -> 0.0051215124
A52: Прибыль (до уплаты налогов) | B52: 000 USD | G52: ='Deposits (indiv)'!G24 -> 70.427714 | H52: ='Deposits (indiv)'!H24 -> 120.35953 | I52: ='Deposits (indiv)'!I24 -> 317.94538 | J52: ='Deposits (indiv)'!J24 -> 403.651 | K52: ='Deposits (indiv)'!K24 -> 285.37075 | L52: ='Deposits (indiv)'!L24 -> 609.22417 | M52: ='Deposits (indiv)'!M24 -> 397.28105 | N52: ='Deposits (indiv)'!N24 -> 588.06282 | ... P52: ='Deposits (indiv)'!P24 -> 1079.6434 | S52: =E52+F52+G52+H52 -> 190.78724 | T52: =I52+J52 -> 721.59638 | U52: =K52+L52 -> 894.59491 | V52: =M52+N52 -> 985.34387 | W52: =O52+P52 -> 2020.7216 | Y52: =W52/$W$124 -> 0.012449332
A54: Cash Loans Dossym ( от 300 до 10000 дол, от 6 до 60 мес) - ср.срок погашения - 24 мес | C54: Finco
A55: Прибыль (до уплаты налогов) | B55: 000 USD | E55: ='CashCredit_dossym (indiv)'!BR$61 -> 0 | F55: ='CashCredit_dossym (indiv)'!BS$61 -> 0 | G55: ='CashCredit_dossym (indiv)'!BT$61 -> -30.575732 | H55: ='CashCredit_dossym (indiv)'!BU$61 -> -79.240873 | I55: ='CashCredit_dossym (indiv)'!BV$61 -> 429.49412 | J55: ='CashCredit_dossym (indiv)'!BW$61 -> 1818.9046 | K55: ='CashCredit_dossym (indiv)'!BX$61 -> 1238.0982 | L55: ='CashCredit_dossym (indiv)'!BY$61 -> 4019.1345 | ... P55: ='CashCredit_dossym (indiv)'!CC$61 -> 9549.7485 | S55: =E55+F55+G55+H55 -> -109.81661 | T55: =I55+J55 -> 2248.3988 | U55: =K55+L55 -> 5257.2327 | V55: =M55+N55 -> 9272.1522 | W55: =O55+P55 -> 13135.87 | Y55: =W55/$W$124 -> 0.080927921
A57: Восстановление кредитной истории | C57: Finco
A58: % от кол-ва клиентов экосистемы | B58: % | I58: 0.01 | J58: =I58*(1+30%) -> 0.013 | K58: =J58*(1+30%) -> 0.0169 | L58: =K58*(1+30%) -> 0.02197 | M58: =L58*(1+30%) -> 0.028561 | N58: =M58*(1+30%) -> 0.0371293 | O58: =N58*(1+30%) -> 0.04826809 | P58: =O58*(1+30%) -> 0.062748517 | S58: =H58 -> 0 | T58: =J58 -> 0.013 | U58: =L58 -> 0.02197 | V58: =N58 -> 0.0371293 | W58: =P58 -> 0.062748517
A59: Количество активных клиентов | B59: шт | I59: =I58*I10 -> 42115.803 | J59: =J58*J10 -> 57849.484 | K59: =K58*K10 -> 79520.581 | L59: =L58*L10 -> 109251.52 | M59: =M58*M10 -> 150821.68 | N59: =N58*N10 -> 207998.23 | O59: =O58*O10 -> 289348.31 | P59: =P58*P10 -> 401743.4 | S59: =H59 -> 0 | T59: =J59 -> 57849.484 | U59: =L59 -> 109251.52 | V59: =N59 -> 207998.23 | W59: =P59 -> 401743.4
A60: из них: доля клиентов Freemium | B60: % | I60: 0.7 | J60: 0.7 | K60: 0.7 | L60: 0.7 | M60: 0.7 | N60: 0.7 | O60: 0.7 | P60: 0.7 | S60: =H60 -> 0 | T60: =J60 -> 0.7 | U60: =L60 -> 0.7 | V60: =N60 -> 0.7 | W60: =P60 -> 0.7
A61: из них: кол-во клиентов Freemium | B61: чел | I61: =I59*I60 -> 29481.062 | J61: =J59*J60 -> 40494.639 | K61: =K59*K60 -> 55664.406 | L61: =L59*L60 -> 76476.066 | M61: =M59*M60 -> 105575.17 | N61: =N59*N60 -> 145598.76 | O61: =O59*O60 -> 202543.82 | P61: =P59*P60 -> 281220.38 | S61: =H61 -> 0 | T61: =J61 -> 40494.639 | U61: =L61 -> 76476.066 | V61: =N61 -> 145598.76 | W61: =P61 -> 281220.38
A62: Прибыль с 1 клиента (месяц) | B62: USD | I62: 3 | J62: 3 | K62: 3 | L62: 3 | M62: 3 | N62: 3 | O62: 3 | P62: 3 | S62: =H62 -> 0 | T62: =J62 -> 3 | U62: =L62 -> 3 | V62: =N62 -> 3 | W62: =P62 -> 3
A63: Прибыль (до уплаты налогов) | B63: 000 USD | I63: =I61*I62/1000*6 -> 530.65911 | J63: =J61*J62/1000*6 -> 728.90349 | K63: =K61*K62/1000*6 -> 1001.9593 | L63: =L61*L62/1000*6 -> 1376.5692 | M63: =M61*M62/1000*6 -> 1900.3531 | N63: =N61*N62/1000*6 -> 2620.7777 | O63: =O61*O62/1000*6 -> 3645.7888 | P63: =P61*P62/1000*6 -> 5061.9668 | S63: =E63+F63+G63+H63 -> 0 | T63: =I63+J63 -> 1259.5626 | U63: =K63+L63 -> 2378.5285 | V63: =M63+N63 -> 4521.1308 | W63: =O63+P63 -> 8707.7555 | Y63: =W63/$W$124 -> 0.053647041
A65: Микроинвестиции (StarGaze) | C65: Forte
A66: % от кол-ва клиентов экосистемы | B66: % | H66: =H67/H$10 -> 0.0063733393 | J66: =J67/J$10 -> 0.015022994 | L66: =L67/L$10 -> 0.029213407 | N66: =N67/N$10 -> 0.049437575 | P66: =P67/P$10 -> 0.072083421 | S66: =H66 -> 0.0063733393 | T66: =J66 -> 0.015022994 | U66: =L66 -> 0.029213407 | V66: =N66 -> 0.049437575 | W66: =P66 -> 0.072083421
A67: Количество клиентов | B67: шт | C67: Stargaze Finmodel | H67: 25524.359 | J67: 66851.725 | L67: 145271.24 | N67: 276949.14 | P67: 461509.53 | S67: =E67+F67+G67+H67 -> 25524.359 | T67: =I67+J67 -> 66851.725 | U67: =K67+L67 -> 145271.24 | V67: =M67+N67 -> 276949.14 | W67: =O67+P67 -> 461509.53
A68: Прибыль с 1 клиента | B68: USD | C68: Stargaze Finmodel | H68: -0.67696698 | J68: 15.353217 | L68: 27.985306 | N68: 36.127207 | P68: 37.498 | S68: =H68 -> -0.67696698 | T68: =J68 -> 15.353217 | U68: =L68 -> 27.985306 | V68: =N68 -> 36.127207 | W68: =P68 -> 37.498
A69: Прибыль (до уплаты налогов) | B69: 000 USD | H69: =H67*H68/1000 -> -17.279148 | I69: =I67*I68/1000 -> 0 | J69: =J67*J68/1000 -> 1026.389 | K69: =K67*K68/1000 -> 0 | L69: =L67*L68/1000 -> 4065.4602 | M69: =M67*M68/1000 -> 0 | N69: =N67*N68/1000 -> 10005.399 | O69: =O67*O68/1000 -> 0 | P69: =P67*P68/1000 -> 17305.684 | S69: =E69+F69+G69+H69 -> -17.279148 | T69: =I69+J69 -> 1026.389 | U69: =K69+L69 -> 4065.4602 | V69: =M69+N69 -> 10005.399 | W69: =O69+P69 -> 17305.684 | Y69: =W69/$W$124 -> 0.10661746
A71: Бизнес-кредит мерчантам ( от 100 до 50'000 дол, оборачиваемость 12 мес) - БЕЗЗАЛОГОВЫЙ | C71: Finco?
A72: % от кол-ва клиентов экосистемы | B72: % | J72: =J73/J10 -> 0.0002426988 | K72: =K73/K10 -> 0.00050041338 | L72: =L73/L10 -> 0.0008321738 | M72: =M73/M10 -> 0.0010525053 | N72: =N73/N10 -> 0.0012646919 | O72: =O73/O10 -> 0.0014544319 | P72: =P73/P10 -> 0.0016337218 | T72: =J72 -> 0.0002426988 | U72: =L72 -> 0.0008321738 | V72: =N72 -> 0.0012646919 | W72: =P72 -> 0.0016337218
A73: Количество выдач | B73: шт | J73: ='Merchants(corp)'!J14 -> 1080 | K73: ='Merchants(corp)'!K14 -> 2354.625 | L73: ='Merchants(corp)'!L14 -> 4138.2 | M73: ='Merchants(corp)'!M14 -> 5557.95 | N73: ='Merchants(corp)'!N14 -> 7084.8 | O73: ='Merchants(corp)'!O14 -> 8718.75 | P73: ='Merchants(corp)'!P14 -> 10459.8 | T73: =I73+J73 -> 1080 | U73: =K73+L73 -> 6492.825 | V73: =M73+N73 -> 12642.75 | W73: =O73+P73 -> 19178.55 | Y73: =(W73+W91+W101+W106+W113+W118)/149000 -> 2.2735205
A74: Портфель (средние остатки) | B74: 000 USD | J74: ='Merchants(corp)'!J27 -> 8835.75 | K74: ='Merchants(corp)'!K27 -> 14049.763 | L74: ='Merchants(corp)'!L27 -> 26559.712 | M74: ='Merchants(corp)'!M27 -> 39663.314 | N74: ='Merchants(corp)'!N27 -> 51716.749 | O74: ='Merchants(corp)'!O27 -> 64646.397 | P74: ='Merchants(corp)'!P27 -> 78452.256 | T74: =J74 -> 8835.75 | U74: =L74 -> 26559.712 | V74: =N74 -> 51716.749 | W74: =P74 -> 78452.256
A75: Маржинальность | B75: % годовых | J75: ='Merchants(corp)'!J58 -> -0.088579068 | K75: ='Merchants(corp)'!K58 -> -0.0028378078 | L75: ='Merchants(corp)'!L58 -> 0.062212 | M75: ='Merchants(corp)'!M58 -> 0.14876107 | N75: ='Merchants(corp)'!N58 -> 0.16607103 | O75: ='Merchants(corp)'!O58 -> 0.17779586 | P75: ='Merchants(corp)'!P58 -> 0.18630415 | T75: =J75 -> -0.088579068 | U75: =L75 -> 0.062212 | V75: =N75 -> 0.16607103 | W75: =P75 -> 0.18630415
A76: Прибыль (до уплаты налогов) | B76: 000 USD | J76: ='Merchants(corp)'!J57 -> -391.33125 | K76: ='Merchants(corp)'!K57 -> -19.935264 | L76: ='Merchants(corp)'!L57 -> 826.16641 | M76: ='Merchants(corp)'!M57 -> 2950.1784 | N76: ='Merchants(corp)'!N57 -> 4294.3269 | O76: ='Merchants(corp)'!O57 -> 5746.9308 | P76: ='Merchants(corp)'!P57 -> 7307.9903 | T76: =I76+J76 -> -391.33125 | U76: =K76+L76 -> 806.23114 | V76: =M76+N76 -> 7244.5054 | W76: =O76+P76 -> 13054.921 | Y76: =W76/$W$124 -> 0.080429208
A78: BNPL через криейтеров | C78: Forte
A79: % от кол-ва клиентов экосистемы | B79: % | I79: =I80/I10 -> 0 | J79: =J80/J10 -> 0 | K79: =K80/K10 -> 0 | L79: =L80/L10 -> 0 | M79: =M80/M10 -> 0 | N79: =N80/N10 -> 0 | O79: =O80/O10 -> 0 | P79: =P80/P10 -> 0 | T79: =J79 -> 0 | U79: =L79 -> 0 | V79: =N79 -> 0 | W79: =P79 -> 0
A80: Количество выдач | B80: шт | I80: ='Криейтеры (ЮЛ)'!I18 -> 0 | J80: ='Криейтеры (ЮЛ)'!J18 -> 0 | K80: ='Криейтеры (ЮЛ)'!K18 -> 0 | L80: ='Криейтеры (ЮЛ)'!L18 -> 0 | M80: ='Криейтеры (ЮЛ)'!M18 -> 0 | N80: ='Криейтеры (ЮЛ)'!N18 -> 0 | O80: ='Криейтеры (ЮЛ)'!O18 -> 0 | P80: ='Криейтеры (ЮЛ)'!P18 -> 0 | T80: =I80+J80 -> 0 | U80: =K80+L80 -> 0 | V80: =M80+N80 -> 0 | W80: =O80+P80 -> 0
A81: Портфель (средние остатки) | B81: 000 USD | I81: ='Криейтеры (ЮЛ)'!I31 -> 0 | J81: ='Криейтеры (ЮЛ)'!J31 -> 0 | K81: ='Криейтеры (ЮЛ)'!K31 -> 0 | L81: ='Криейтеры (ЮЛ)'!L31 -> 0 | M81: ='Криейтеры (ЮЛ)'!M31 -> 0 | N81: ='Криейтеры (ЮЛ)'!N31 -> 0 | O81: ='Криейтеры (ЮЛ)'!O31 -> 0 | P81: ='Криейтеры (ЮЛ)'!P31 -> 0 | T81: =J81 -> 0 | U81: =L81 -> 0 | V81: =N81 -> 0 | W81: =P81 -> 0
A82: Маржинальность | B82: % годовых | I82: ='Криейтеры (ЮЛ)'!I60 -> #DIV/0! | J82: ='Криейтеры (ЮЛ)'!J60 -> #DIV/0! | K82: ='Криейтеры (ЮЛ)'!K60 -> #DIV/0! | L82: ='Криейтеры (ЮЛ)'!L60 -> #DIV/0! | M82: ='Криейтеры (ЮЛ)'!M60 -> #DIV/0! | N82: ='Криейтеры (ЮЛ)'!N60 -> #DIV/0! | O82: ='Криейтеры (ЮЛ)'!O60 -> #DIV/0! | P82: ='Криейтеры (ЮЛ)'!P60 -> #DIV/0! | T82: =J82 -> #DIV/0! | U82: =L82 -> #DIV/0! | V82: =N82 -> #DIV/0! | W82: =P82 -> #DIV/0!
A83: Прибыль (до уплаты налогов) | B83: 000 USD | I83: ='Криейтеры (ЮЛ)'!I59 -> 0 | J83: ='Криейтеры (ЮЛ)'!J59 -> 0 | K83: ='Криейтеры (ЮЛ)'!K59 -> 0 | L83: ='Криейтеры (ЮЛ)'!L59 -> 0 | M83: ='Криейтеры (ЮЛ)'!M59 -> 0 | N83: ='Криейтеры (ЮЛ)'!N59 -> 0 | O83: ='Криейтеры (ЮЛ)'!O59 -> 0 | P83: ='Криейтеры (ЮЛ)'!P59 -> 0 | T83: =I83+J83 -> 0 | U83: =K83+L83 -> 0 | V83: =M83+N83 -> 0 | W83: =O83+P83 -> 0 | Y83: =W83/$W$124 -> 0
A85: Расчеты мерчантов с криейтерами | C85: Forte
A86: Оборот ЮЛ-партнеров | B86: 000 USD | I86: ='Криейтеры (ЮЛ)'!I12/'Funnel QH'!I30 -> 0 | J86: ='Криейтеры (ЮЛ)'!J12/'Funnel QH'!J30 -> 0 | K86: ='Криейтеры (ЮЛ)'!K12/'Funnel QH'!K30 -> 0 | L86: ='Криейтеры (ЮЛ)'!L12/'Funnel QH'!L30 -> 0 | M86: ='Криейтеры (ЮЛ)'!M12/'Funnel QH'!M30 -> 0 | N86: ='Криейтеры (ЮЛ)'!N12/'Funnel QH'!N30 -> 0 | O86: ='Криейтеры (ЮЛ)'!O12/'Funnel QH'!O30 -> 0 | P86: ='Криейтеры (ЮЛ)'!P12/'Funnel QH'!P30 -> 0 | T86: =I86+J86 -> 0 | U86: =K86+L86 -> 0 | V86: =M86+N86 -> 0 | W86: =O86+P86 -> 0
A87: Прибыль (до уплаты налогов) | B87: 000 USD | I87: ='Криейтеры (ЮЛ)'!I65 -> 0 | J87: ='Криейтеры (ЮЛ)'!J65 -> 0 | K87: ='Криейтеры (ЮЛ)'!K65 -> 0 | L87: ='Криейтеры (ЮЛ)'!L65 -> 0 | M87: ='Криейтеры (ЮЛ)'!M65 -> 0 | N87: ='Криейтеры (ЮЛ)'!N65 -> 0 | O87: ='Криейтеры (ЮЛ)'!O65 -> 0 | P87: ='Криейтеры (ЮЛ)'!P65 -> 0 | T87: =I87+J87 -> 0 | U87: =K87+L87 -> 0 | V87: =M87+N87 -> 0 | W87: =O87+P87 -> 0 | Y87: =W87/$W$124 -> 0
A89: Остатки мерчантов | C89: Forte
A90: % от кол-ва клиентов экосистемы | B90: %
A91: Количество счетов | B91: шт
A92: Портфель (средние остатки) | B92: 000 USD | J92: ='Merchants(corp)'!J130/'Funnel QH'!J30 -> 111000 | K92: ='Merchants(corp)'!K130/'Funnel QH'!K30 -> 147691.67 | L92: ='Merchants(corp)'!L130/'Funnel QH'!L30 -> 221075 | M92: ='Merchants(corp)'!M130/'Funnel QH'!M30 -> 294458.33 | N92: ='Merchants(corp)'!N130/'Funnel QH'!N30 -> 367841.67 | O92: ='Merchants(corp)'!O130/'Funnel QH'!O30 -> 441225 | P92: ='Merchants(corp)'!P130/'Funnel QH'!P30 -> 514608.33 | T92: =J92 -> 111000 | U92: =L92 -> 221075 | V92: =N92 -> 367841.67 | W92: =P92 -> 514608.33
A93: Маржинальность | B93: % годовых | J93: ='Merchants(corp)'!J157 -> 0.02 | K93: ='Merchants(corp)'!K157 -> 0.02283671 | L93: ='Merchants(corp)'!L157 -> 0.023979933 | M93: ='Merchants(corp)'!M157 -> 0.02284689 | N93: ='Merchants(corp)'!N157 -> 0.022216015 | O93: ='Merchants(corp)'!O157 -> 0.021814024 | P93: ='Merchants(corp)'!P157 -> 0.021535484 | T93: ='Deposits (indiv)'!T92 -> 0 | U93: ='Deposits (indiv)'!U92 -> 0 | V93: ='Deposits (indiv)'!V92 -> 0 | W93: ='Deposits (indiv)'!W92 -> 0
A94: Прибыль (до уплаты налогов) | B94: 000 USD | J94: ='Merchants(corp)'!J159 -> 1110 | K94: ='Merchants(corp)'!K159 -> 1476.9167 | L94: ='Merchants(corp)'!L159 -> 3687.6667 | M94: ='Merchants(corp)'!M159 -> 2944.5833 | N94: ='Merchants(corp)'!N159 -> 6623 | O94: ='Merchants(corp)'!O159 -> 4412.25 | P94: ='Merchants(corp)'!P159 -> 9558.3333 | T94: =I94+J94 -> 1110 | U94: =K94+L94 -> 5164.5833 | V94: =M94+N94 -> 9567.5833 | W94: =O94+P94 -> 13970.583 | Y94: =W94/$W$124 -> 0.086070451
A96: BNPL комиссии | C96: Forte
A97: Прибыль (до уплаты налогов) | B97: 000 USD | G97: ='Merchants(corp)'!G197 -> 0.9894053 | H97: ='Merchants(corp)'!H197 -> 3.7224467 | I97: ='Merchants(corp)'!I197 -> 73.866034 | J97: ='Merchants(corp)'!J197 -> 286.10781 | K97: ='Merchants(corp)'!K197 -> 507.73783 | L97: ='Merchants(corp)'!L197 -> 756.13146 | M97: ='Merchants(corp)'!M197 -> 940.75529 | N97: ='Merchants(corp)'!N197 -> 1050.674 | ... P97: ='Merchants(corp)'!P197 -> 1251.8252 | S97: =E97+F97+G97+H97 -> 4.711852 | T97: =I97+J97 -> 359.97385 | U97: =K97+L97 -> 1263.8693 | V97: =M97+N97 -> 1991.4293 | W97: =O97+P97 -> 2459.5052 | Y97: =W97/$W$124 -> 0.015152604
A99: FX | C99: Forte
A100: % от кол-ва клиентов экосистемы | B100: % | K100: =K101/K10 -> 0.0010590759 | L100: =L101/L10 -> 0.001400966 | M100: =M101/M10 -> 0.0016948555 | N100: =N101/N10 -> 0.001951685 | O100: =O101/O10 -> 0.0021547139 | P100: =P101/P10 -> 0.002327239 | U100: =L100 -> 0.001400966 | V100: =N100 -> 0.001951685 | W100: =P100 -> 0.002327239
A101: Количество клиентов (на конец периода) | B101: шт | K101: ='Merchants(corp)'!K184 -> 4983.3333 | L101: ='Merchants(corp)'!L184 -> 6966.6667 | M101: ='Merchants(corp)'!M184 -> 8950 | N101: ='Merchants(corp)'!N184 -> 10933.333 | O101: ='Merchants(corp)'!O184 -> 12916.667 | P101: ='Merchants(corp)'!P184 -> 14900 | U101: =L101 -> 6966.6667 | V101: =N101 -> 10933.333 | W101: =P101 -> 14900
A102: Прибыль (до уплаты налогов) | B102: 000 USD | K102: ='Merchants(corp)'!K194 -> 478.4 | L102: ='Merchants(corp)'!L194 -> 668.8 | M102: ='Merchants(corp)'!M194 -> 859.2 | N102: ='Merchants(corp)'!N194 -> 1049.6 | O102: ='Merchants(corp)'!O194 -> 1240 | P102: ='Merchants(corp)'!P194 -> 1430.4 | U102: =K102+L102 -> 1147.2 | V102: =M102+N102 -> 1908.8 | W102: =O102+P102 -> 2670.4 | Y102: =W102/$W$124 -> 0.016451892
A104: Залоговый бизнес-кредит (до 100 000 USD) - до 48 мес | C104: Forte
A105: % от кол-ва клиентов экосистемы | B105: % | J105: =J106/J10 -> 0.0001617992 | K105: =K106/K10 -> 0.00025417822 | L105: =L106/L10 -> 0.00033623184 | M105: =M106/M10 -> 0.00040676532 | N105: =N106/N10 -> 0.00046840439 | O105: =O106/O10 -> 0.00051713133 | P105: =P106/P10 -> 0.00055853736 | T105: =J105 -> 0.0001617992 | U105: =L105 -> 0.00033623184 | V105: =N105 -> 0.00046840439 | W105: =P105 -> 0.00055853736
A106: Количество выдач | B106: шт | J106: ='Merchants(corp)'!J67 -> 720 | K106: ='Merchants(corp)'!K67 -> 1196 | L106: ='Merchants(corp)'!L67 -> 1672 | M106: ='Merchants(corp)'!M67 -> 2148 | N106: ='Merchants(corp)'!N67 -> 2624 | O106: ='Merchants(corp)'!O67 -> 3100 | P106: ='Merchants(corp)'!P67 -> 3576 | T106: =I106+J106 -> 720 | U106: =K106+L106 -> 2868 | V106: =M106+N106 -> 4772 | W106: =O106+P106 -> 6676
A107: Портфель (средние остатки) | B107: 000 USD | J107: ='Merchants(corp)'!J83 -> 30600 | K107: ='Merchants(corp)'!K83 -> 55551.75 | L107: ='Merchants(corp)'!L83 -> 108548.24 | M107: ='Merchants(corp)'!M83 -> 166609.5 | N107: ='Merchants(corp)'!N83 -> 227899.56 | O107: ='Merchants(corp)'!O83 -> 291247.97 | P107: ='Merchants(corp)'!P83 -> 355908.58 | T107: =J107 -> 30600 | U107: =L107 -> 108548.24 | V107: =N107 -> 227899.56 | W107: =P107 -> 355908.58
A108: Маржинальность | B108: % годовых | J108: ='Merchants(corp)'!J114 -> -0.12576471 | K108: ='Merchants(corp)'!K114 -> -0.10355371 | L108: ='Merchants(corp)'!L114 -> -0.015444442 | M108: ='Merchants(corp)'!M114 -> 0.01949073 | N108: ='Merchants(corp)'!N114 -> 0.037709002 | O108: ='Merchants(corp)'!O114 -> 0.048381777 | P108: ='Merchants(corp)'!P114 -> 0.054971696 | T108: =J108 -> -0.12576471 | U108: =L108 -> -0.015444442 | V108: =N108 -> 0.037709002 | W108: =P108 -> 0.054971696
A109: Прибыль (до уплаты налогов) | B109: 000 USD | J109: ='Merchants(corp)'!J113 -> -1924.2 | K109: ='Merchants(corp)'!K113 -> -2876.2948 | L109: ='Merchants(corp)'!L113 -> -838.23352 | M109: ='Merchants(corp)'!M113 -> 1623.6704 | N109: ='Merchants(corp)'!N113 -> 4296.9325 | O109: ='Merchants(corp)'!O113 -> 7045.5471 | P109: ='Merchants(corp)'!P113 -> 9782.4491 | T109: =I109+J109 -> -1924.2 | U109: =K109+L109 -> -3714.5283 | V109: =M109+N109 -> 5920.6029 | W109: =O109+P109 -> 16827.996 | Y109: =W109/$W$124 -> 0.1036745
A111: РКО и Бизнес-карта | C111: Forte
A112: % от кол-ва клиентов экосистемы | B112: % | J112: =J113/J10 -> 0.0067416332 | K112: =K113/K10 -> 0.010590759 | L112: =L113/L10 -> 0.01400966 | M112: =M113/M10 -> 0.016948555 | N112: =N113/N10 -> 0.01951685 | O112: =O113/O10 -> 0.021547139 | P112: =P113/P10 -> 0.02327239 | T112: =J112 -> 0.0067416332 | U112: =L112 -> 0.01400966 | V112: =N112 -> 0.01951685 | W112: =P112 -> 0.02327239
A113: Количество клиентов (на конец периода) | B113: шт | J113: ='Merchants(corp)'!J162 -> 30000 | K113: ='Merchants(corp)'!K162 -> 49833.333 | L113: ='Merchants(corp)'!L162 -> 69666.667 | M113: ='Merchants(corp)'!M162 -> 89500 | N113: ='Merchants(corp)'!N162 -> 109333.33 | O113: ='Merchants(corp)'!O162 -> 129166.67 | P113: ='Merchants(corp)'!P162 -> 149000 | T113: =J113 -> 30000 | U113: =L113 -> 69666.667 | V113: =N113 -> 109333.33 | W113: =P113 -> 149000
A114: Прибыль (до уплаты налогов) | B114: 000 USD | J114: ='Merchants(corp)'!J167+'Merchants(corp)'!J281 -> 651.168 | K114: ='Merchants(corp)'!K167+'Merchants(corp)'!K281 -> 1094.4118 | L114: ='Merchants(corp)'!L167+'Merchants(corp)'!L281 -> 1540.0274 | M114: ='Merchants(corp)'!M167+'Merchants(corp)'!M281 -> 5087.4265 | N114: ='Merchants(corp)'!N167+'Merchants(corp)'!N281 -> 6387.627 | O114: ='Merchants(corp)'!O167+'Merchants(corp)'!O281 -> 7736.2945 | P114: ='Merchants(corp)'!P167+'Merchants(corp)'!P281 -> 9121.8228 | T114: =I114+J114 -> 651.168 | U114: =K114+L114 -> 2634.4391 | V114: =M114+N114 -> 11475.054 | W114: =O114+P114 -> 16858.117 | Y114: =W114/$W$124 -> 0.10386007
A116: Интернет-эквайринг | C116: Forte
A117: % от кол-ва клиентов экосистемы | B117: % | J117: =J118/J10 -> 0.0067416332 | K117: =K118/K10 -> 0.010590759 | L117: =L118/L10 -> 0.01400966 | M117: =M118/M10 -> 0.016948555 | N117: =N118/N10 -> 0.01951685 | O117: =O118/O10 -> 0.021547139 | P117: =P118/P10 -> 0.02327239 | T117: =J117 -> 0.0067416332 | U117: =L117 -> 0.01400966 | V117: =N117 -> 0.01951685 | W117: =P117 -> 0.02327239
A118: Количество клиентов (на конец периода) | B118: шт | J118: ='Merchants(corp)'!J170 -> 30000 | K118: ='Merchants(corp)'!K170 -> 49833.333 | L118: ='Merchants(corp)'!L170 -> 69666.667 | M118: ='Merchants(corp)'!M170 -> 89500 | N118: ='Merchants(corp)'!N170 -> 109333.33 | O118: ='Merchants(corp)'!O170 -> 129166.67 | P118: ='Merchants(corp)'!P170 -> 149000 | T118: =J118 -> 30000 | U118: =L118 -> 69666.667 | V118: =N118 -> 109333.33 | W118: =P118 -> 149000
A119: Прибыль (до уплаты налогов) | B119: 000 USD | J119: ='Merchants(corp)'!J179 -> -180 | K119: ='Merchants(corp)'!K179 -> -134.55 | L119: ='Merchants(corp)'!L179 -> 53.295 | M119: ='Merchants(corp)'!M179 -> 394.09088 | N119: ='Merchants(corp)'!N179 -> 899.0931 | O119: ='Merchants(corp)'!O179 -> 1580.3003 | P119: ='Merchants(corp)'!P179 -> 2450.5005 | T119: =I119+J119 -> -180 | U119: =K119+L119 -> -81.255 | V119: =M119+N119 -> 1293.184 | W119: =O119+P119 -> 4030.8009 | Y119: =W119/$W$124 -> 0.024833097
A124: Итого прибыль по продуктам | B124: 000 USD | E124: =E33+E22+E52+E30+E55+E63+E69+E76+E83+E87+E94+E97+E102+E109+E114+E119 -> 3367.9944 | F124: =F33+F22+F52+F30+F55+F63+F69+F76+F83+F87+F94+F97+F102+F109+F114+F119 -> 3402.0404 | G124: =G33+G22+G52+G30+G55+G63+G69+G76+G83+G87+G94+G97+G102+G109+G114+G119 -> 2767.5839 | H124: =H33+H22+H52+H30+H55+H63+H69+H76+H83+H87+H94+H97+H102+H109+H114+H119 -> 2658.4036 | I124: =I33+I22+I52+I30+I55+I63+I69+I76+I83+I87+I94+I97+I102+I109+I114+I119 -> 1916.9731 | J124: =J33+J22+J52+J30+J55+J63+J69+J76+J83+J87+J94+J97+J102+J109+J114+J119 -> 3925.754 | K124: =K33+K22+K52+K30+K55+K63+K69+K76+K83+K87+K94+K97+K102+K109+K114+K119 -> 9086.7109 | L124: =L33+L22+L52+L30+L55+L63+L69+L76+L83+L87+L94+L97+L102+L109+L114+L119 -> 24478.95 | ... P124: =P33+P22+P52+P30+P55+P63+P69+P76+P83+P87+P94+P97+P102+P109+P114+P119 -> 100466.18 | R124: =D124 -> 0 | S124: =E124+F124+G124+H124 -> 12196.022 | T124: =I124+J124 -> 5842.7271 | U124: =K124+L124 -> 33565.661 | V124: =M124+N124 -> 96385.508 | W124: =O124+P124 -> 162315.67
...

Sheet Funnel
D1: этим цветом выделены ячейки для ввода
B5: курс | D5: 500 | E5: =D5 -> 500 | F5: =E5 -> 500 | G5: =F5 -> 500 | H5: =G5 -> 500 | I5: =H5 -> 500 | K5: 2025-2029 г.
D6: 2024 | E6: 2025 | F6: 2026 | G6: 2027 | H6: 2028 | I6: 2029 | K6: тенге | L6: USD
B7: Кол-во клиентов Билайн | D7: 5000000 | E7: 6200000 | F7: 6795000 | G7: 7500000 | H7: 8365000 | I7: 9510000 | O7: Beeline clients
B8: Кол-во эл кошельков | D8: 4100000 | E8: =E9+E13 -> 5006080.3 | F8: =F9+F13 -> 5562450.4 | G8: =G9+G13 -> 6215949.1 | H8: =H9+H13 -> 7002496.2 | I8: =I9+I13 -> 8003045.6 | O8: e-Wallet
B9: Билайн | D9: =D8-D13 -> 3096448 | E9: =E7*E12 -> 3851995.5 | F9: =F7*F12 -> 4235252.8 | G9: =G7*G12 -> 4689672 | H9: =H7*H12 -> 5247277.5 | I9: =I7*I12 -> 5984544.1 | O9: Билайн
B10: идентифицированные | D10: 237217 | O10: identified
B11: неидентифицированные | D11: =D9-D10 -> 2859231 | O11: unidentified
B12: конверсия в кол-во клиентов Билайн | D12: =D9/D7 -> 0.6192896 | E12: =D12+0.2% -> 0.6212896 | F12: =E12+0.2% -> 0.6232896 | G12: =F12+0.2% -> 0.6252896 | H12: =G12+0.2% -> 0.6272896 | I12: =H12+0.2% -> 0.6292896 | O12: conversion in Beeline clients
B13: неБилайн | D13: 1003552 | E13: =D13*115% -> 1154084.8 | F13: =E13*115% -> 1327197.5 | G13: =F13*115% -> 1526277.1 | H13: =G13*115% -> 1755218.7 | I13: =H13*115% -> 2018501.5 | O13: not Beeline
B14: идентифицированные | D14: 134108 | O14: identified
B15: неидентифицированные | D15: 869444 | O15: unidentified
B16: Кол-во эл кошельков Simply | D16: =D17*D8 -> 0 | E16: =E17*E8 -> 0 | F16: =F17*F8 -> 0 | G16: =G17*G8 -> 0 | H16: =H17*H8 -> 0 | I16: =I17*I8 -> 0
B17: доля активных эл кошельков Simply
A19: 1 | B19: Debit Card | O19: Debit Card
B20: Кол-во выпущенных карт | D20: 956516 | E20: =E8*E21 -> 1001216.1 | F20: =F8*F21 -> 1112490.1 | G20: =G8*G21 -> 1243189.8 | H20: =H8*H21 -> 1400499.2 | I20: =I8*I21 -> 1600609.1 | O20: Кол-во выпущенных карт
B21: конверсия в кол-ве эл кошельков | D21: =D20/D8 -> 0.23329659 | E21: 0.2 | F21: 0.2 | G21: 0.2 | H21: 0.2 | I21: 0.2 | O21: конверсия в кол-ве эл кошельков
B22: Кол-во активных карт | D22: 129307.44 | E22: 106852.5 | F22: 191162.5 | G22: 233951.02 | H22: 286317.02 | I22: 350404.28 | O22: Кол-во активных карт
B23: доля активных карт | D23: =D22/D20 -> 0.13518587 | E23: =E22/E20 -> 0.10672272 | F23: =F22/F20 -> 0.17183299 | G23: =G22/G20 -> 0.18818608 | H23: =H22/H20 -> 0.20443925 | I23: =I22/I20 -> 0.21891933 | O23: доля активных карт
A25: 2 | B25: Nano-Lending | O25: Nano-Lending
B26: Nano-Lending MAU | D26: 733460.63 | E26: 767663.01 | F26: 871479.76 | G26: 989336.42 | H26: 1137736.9 | I26: 1308397.4 | O26: Nano-Lending MAU
B27: конверсия в кол-ве эл кошельков | D27: =D26/D8 -> 0.17889284 | E27: =D27+1% -> 0.18889284 | F27: =E27+1% -> 0.19889284 | G27: =F27+1% -> 0.20889284 | H27: =G27+1% -> 0.21889284 | I27: =H27+1% -> 0.22889284 | O27: конверсия в кол-ве эл кошельков
B28: Кол-во платежей на 1 клиента | D28: 1.7964564 | E28: 1.6483669 | F28: 1.4518882 | G28: 1.2951236 | H28: 1.1476457 | I28: 1.0084752 | O28: Кол-во платежей на 1 клиента
B29: Сред чек, тенге | D29: =D30*D5 -> 1500 | E29: =E30*E5 -> 1500 | F29: =F30*F5 -> 1500 | G29: =G30*G5 -> 1500 | H29: =H30*H5 -> 1500 | I29: =I30*I5 -> 1500 | O29: Сред чек, тенге
B30: сред чек, долл | D30: 3 | E30: 3 | F30: 3 | G30: 3 | H30: 3 | I30: 3 | O30: сред чек, долл
B31: Сумма выдачи, тенге | E31: =E29*E26 -> 1.1514945e+09 | F31: =F29*F26 -> 1.3072196e+09 | G31: =G29*G26 -> 1.4840046e+09 | H31: =H29*H26 -> 1.7066053e+09 | I31: =I29*I26 -> 1.9625961e+09 | K31: =E31+F31+G31+H31+I31 -> 7.6119202e+09 | L31: =E31/$E$5+F31/$F$5+G31/$G$5+H31/$H$5+I31/$I$5 -> 15223840 | O31: Сумма выдачи, тенге
A33: 3 | B33: Микро Займ по подписке ( 30 дол c возможностью снятия кеша) | O33: Microloan 30 USD
B34: % клиентов после внутренних проверок и отсечений внутри Билайна ( бесплатно) | E34: 0.35 | F34: 0.5 | G34: 0.6 | H34: =G34 -> 0.6 | I34: =H34 -> 0.6 | O34: % of clients after internal checks and cuts within Beeline (free)
B35: база после внутренних проверок Билайна | E35: =E8*E34/2 -> 876064.06 | F35: =F8*F34 -> 2781225.2 | G35: =G8*G34 -> 3729569.5 | H35: =H8*H34 -> 4201497.7 | I35: =I8*I34 -> 4801827.4 | O35: base after internal checks of Beeline
B36: % клиентов,прошедших комплайнес в Банке | E36: 0.8 | F36: 0.8 | G36: 0.8 | H36: 0.8 | I36: 0.8 | O36: % of clients who have passed compliance at the Bank
B37: База клиентов после комплайенса | E37: =E35*E36 -> 700851.24 | F37: =F35*F36 -> 2224980.1 | G37: =G35*G36 -> 2983655.6 | H37: =H35*H36 -> 3361198.2 | I37: =I35*I36 -> 3841461.9 | O37: Paid Base (Post-Compliance Base)
B38: AR | E38: 0.5 | F38: 0.5 | G38: 0.5 | H38: 0.5 | I38: 0.5 | O38: AR
B39: База после внешних , платных проверок ( КБ, доходы, налоги, аресты) - действует 30 дней | E39: =E37*E38 -> 350425.62 | F39: =F37*F38 -> 1112490.1 | G39: =G37*G38 -> 1491827.8 | H39: =H37*H38 -> 1680599.1 | I39: =I37*I38 -> 1920730.9 | O39: Approved clients
B40: Take up | E40: 0.3 | F40: =E40+5% -> 0.35 | G40: =F40+5% -> 0.4 | H40: =G40 -> 0.4 | I40: =H40 -> 0.4 | O40: % of responded clients
B41: Клиенты, согласившиеся на карту с лимитом 30 долл - эмиссия за период | E41: =E39*E40 -> 105127.69 | F41: =F39*F40 -> 389371.52 | G41: =G39*G40 -> 596731.12 | H41: =H39*H40 -> 672239.64 | I41: =I39*I40 -> 768292.38 | O41: Clients who agreed to a card with a limit of $30 - issue cards
B42: % активации | E42: 0.95 | F42: 0.95 | G42: 0.95 | H42: 0.95 | I42: 0.95 | O42: % activation
B43: Кол-во клиентов, по которым установлен КЛ | E43: ='Micro_30 (indiv)'!P18 -> 55590.32 | F43: ='Micro_30 (indiv)'!AC18 -> 399794.5 | G43: ='Micro_30 (indiv)'!AP18 -> 851814.28 | H43: ='Micro_30 (indiv)'!BC18 -> 1224673.5 | I43: ='Micro_30 (indiv)'!BP18 -> 1507002.9 | O43: Сards with established Credit Limit
B44: Средний чек лимита для пакета, тенге | E44: =E45*D5 -> 15000 | F44: =F45*E5 -> 15000 | G44: =G45*F5 -> 15000 | H44: =H45*G5 -> 15000 | I44: =I45*H5 -> 15000 | O44: average check of the established credit limit, tenge
B45: сред чек лимита на пакет, долл | E45: 30 | F45: =E45 -> 30 | G45: =F45 -> 30 | H45: =G45 -> 30 | I45: =H45 -> 30 | O45: average check of the established credit limit, USD
B46: Сумма установленного кредитного лимита, тенге | E46: =E44*E43 -> 8.3385479e+08 | F46: =F44*F43 -> 5.9969176e+09 | G46: =G44*G43 -> 1.2777214e+10 | H46: =H44*H43 -> 1.8370103e+10 | I46: =I44*I43 -> 2.2605044e+10 | O46: Amount of established credit limit, tenge
B47: % клиентов, которые пользуются займом | E47: 0.8 | F47: 0.8 | G47: 0.8 | H47: 0.8 | I47: 0.8 | O47: % of customers who use the package
B48: Кол-во клиентов, использующих пакет (с загрузкой лимита и оплачивающих пакет) | E48: ='Micro_30 (indiv)'!P22 -> 44472.256 | F48: ='Micro_30 (indiv)'!AC22 -> 319835.6 | G48: ='Micro_30 (indiv)'!AP22 -> 681451.42 | H48: ='Micro_30 (indiv)'!BC22 -> 979738.83 | I48: ='Micro_30 (indiv)'!BP22 -> 1205602.3 | O48: Сlients using the card (with limit loading and paying for the package)
B49: % загрузки лимита у клиентов, которые используют пакет | E49: 0.05 | F49: 0.05 | G49: 0.05 | H49: 0.05 | I49: 0.05 | O49: % of limit utilisation for clients who use the package by the end of the month (overdue + rolling over limits)
B50: Сумма загруженного кредитного лимита, тенге | E50: =E46*E49 -> 41692740 | F50: =F46*F49 -> 2.9984588e+08 | G50: =G46*G49 -> 6.3886071e+08 | H50: =H46*H49 -> 9.1850515e+08 | I50: =I46*I49 -> 1.1302522e+09 | K50: =I50 -> 1.1302522e+09 | L50: =K50/I5 -> 2260504.4 | O50: Amount of loaded credit limit at the end of the month, tenge
B51: Средний чек загрузки лимита, тенге | E51: =E50/E48 -> 937.5 | F51: =F50/F48 -> 937.5 | G51: =G50/G48 -> 937.5 | H51: =H50/H48 -> 937.5 | I51: =I50/I48 -> 937.5 | O51: Average check for loading the limit by the end of the month, tenge
B52: сред чек загрузки лимита, долл | E52: =E51/E5 -> 1.875 | F52: =F51/F5 -> 1.875 | G52: =G51/G5 -> 1.875 | H52: =H51/H5 -> 1.875 | I52: =I51/I5 -> 1.875 | O52: Average check for loading the limit by the end of the month, USD
B53: Оборот по выдаче, тенге | E53: ='Micro_30 (indiv)'!P26*1000000 -> 2.2822954e+09 | F53: ='Micro_30 (indiv)'!AC26*1000000 -> 3.3259778e+10 | G53: ='Micro_30 (indiv)'!AP26*1000000 -> 9.0910754e+10 | H53: ='Micro_30 (indiv)'!BC26*1000000 -> 1.4988872e+11 | I53: ='Micro_30 (indiv)'!BP26*1000000 -> 1.9620391e+11 | K53: =E53+F53+G53+H53+I53 -> 4.7254546e+11 | L53: =E53/$E$5+F53/$F$5+G53/$G$5+H53/$H$5+I53/$I$5 -> 9.4509092e+08 | O53: Turnover of using limits for the period, tenge
A55: 4 | B55: Карта рассрочки | O55: Installment card
A56: 4.1. | B56: Карта рассрочки ( BNPL. 150 дол) | O56: Installment card ( BNPL. 150 дол)
B57: % клиентов после внутренних проверок и отсечений внутри Билайна ( бесплатно) | E57: 0.35 | F57: 0.5 | G57: 0.6 | H57: =G57 -> 0.6 | I57: =H57 -> 0.6 | O57: % of clients after internal checks and cuts within Beeline (free)
B58: База после внутренних проверок | E58: =E8*E57/4 -> 438032.03 | F58: =F8*F57 -> 2781225.2 | G58: =G8*G57 -> 3729569.5 | H58: =H8*H57 -> 4201497.7 | I58: =I8*I57 -> 4801827.4 | O58: base after internal checks of Beeline
B59: % клиентов,прошедших комплайнес в Банке | E59: 0.8 | F59: 0.8 | G59: 0.8 | H59: 0.8 | I59: 0.8 | O59: % of clients who have passed compliance at the Bank
B60: База после комплайнеса в банке | E60: =E58*E59 -> 350425.62 | F60: =F58*F59 -> 2224980.1 | G60: =G58*G59 -> 2983655.6 | H60: =H58*H59 -> 3361198.2 | I60: =I58*I59 -> 3841461.9 | O60: Paid Base (Post-Compliance Base)
B61: AR | E61: =E38-35% -> 0.15 | F61: =F38-35% -> 0.15 | G61: =G38-35% -> 0.15 | H61: =H38-35% -> 0.15 | I61: =I38-35% -> 0.15 | O61: AR
B62: База после внешних , платных проверок ( КБ, доходы, налоги, аресты) - действует 30 дней | E62: =E60*E61 -> 52563.843 | F62: =F60*F61 -> 333747.02 | G62: =G60*G61 -> 447548.34 | H62: =H60*H61 -> 504179.73 | I62: =I60*I61 -> 576219.28 | O62: Approved clients
B63: Take up | E63: =E40 -> 0.3 | F63: =F40 -> 0.35 | G63: =G40 -> 0.4 | H63: =H40 -> 0.4 | I63: =I40 -> 0.4 | O63: % of responded clients
B64: Клиенты, согласившиеся на карту - эмиссия за период | E64: =E62*E63 -> 15769.153 | F64: =F62*F63 -> 116811.46 | G64: =G62*G63 -> 179019.34 | H64: =H62*H63 -> 201671.89 | I64: =I62*I63 -> 230487.71 | O64: Clients who agreed to a card with a limit of $30 - issue cards
B65: % активации | E65: =E42 -> 0.95 | F65: =F42 -> 0.95 | G65: =G42 -> 0.95 | H65: =H42 -> 0.95 | I65: =I42 -> 0.95 | O65: % activation
B66: Кол-во клиентов, по которым установлен КЛ | E66: ='Installment card_150 (indiv)'!P18 -> 4248.2898 | F66: ='Installment card_150 (indiv)'!AC18 -> 114420.6 | G66: ='Installment card_150 (indiv)'!AP18 -> 259215.92 | H66: ='Installment card_150 (indiv)'!BC18 -> 379228.96 | I66: ='Installment card_150 (indiv)'!BP18 -> 470538.06 | O66: Сards with established Credit Limit
B67: Средний чек лимита для карты, тенге | E67: =E68*E5 -> 75000 | F67: =F68*F5 -> 82500 | G67: =G68*G5 -> 90750 | H67: =H68*H5 -> 99825 | I67: =I68*I5 -> 109807.5 | O67: average check of the established credit limit, tenge
B68: Средний чек лимита для карты, долл | E68: 150 | F68: =E68*110% -> 165 | G68: =F68*110% -> 181.5 | H68: =G68*110% -> 199.65 | I68: =H68*110% -> 219.615 | O68: average check of the established credit limit, USD
B69: Сумма установленного кредитного лимита, тенге | E69: =E66*E67 -> 3.1862174e+08 | F69: =F66*F67 -> 9.4396993e+09 | G69: =G66*G67 -> 2.3523845e+10 | H69: =H66*H67 -> 3.7856531e+10 | I69: =I66*I67 -> 5.1668609e+10 | O69: Amount of established credit limit, tenge
B70: % клиентов, которые используют карту | E70: 0.99 | F70: =E70-0.5% -> 0.985 | G70: =F70-0.5% -> 0.98 | H70: =G70-0.5% -> 0.975 | I70: =H70-0.5% -> 0.97 | O70: % of customers who use the package
B71: Кол-во клиентов, использующих карту (с загрузкой лимита) | E71: ='Installment card_150 (indiv)'!P22 -> 4205.8069 | F71: ='Installment card_150 (indiv)'!AC22 -> 112704.29 | G71: ='Installment card_150 (indiv)'!AP22 -> 254031.6 | H71: ='Installment card_150 (indiv)'!BC22 -> 369748.23 | I71: ='Installment card_150 (indiv)'!BP22 -> 456421.92 | O71: Сlients using the card (with limit loading and paying for the package)
B72: % загрузки лимита у клиентов, которые используют карту | E72: 0.7 | F72: 0.7 | G72: 0.7 | H72: 0.7 | I72: 0.7 | O72: % of limit utilisation for clients who use the package by the end of the month (overdue + rolling over limits)
B73: Сумма загруженного кредитного лимита, тенге | E73: =E69*E72 -> 2.2303522e+08 | F73: =F69*F72 -> 6.6077895e+09 | G73: =G69*G72 -> 1.6466691e+10 | H73: =H69*H72 -> 2.6499572e+10 | I73: =I69*I72 -> 3.6168026e+10 | K73: =I73 -> 3.6168026e+10 | L73: =K73/I5 -> 72336052 | O73: Amount of loaded credit limit at the end of the month, tenge
B74: Средний чек загрузки лимита, тенге | E74: =E73/E71 -> 53030.303 | F74: =F73/F71 -> 58629.442 | G74: =G73/G71 -> 64821.429 | H74: =H73/H71 -> 71669.231 | I74: =I73/I71 -> 79242.526 | O74: Average check for loading the limit by the end of the month, tenge
B75: сред чек загрузки лимита, долл | E75: =E74/E5 -> 106.06061 | F75: =F74/F5 -> 117.25888 | G75: =G74/G5 -> 129.64286 | H75: =H74/H5 -> 143.33846 | I75: =I74/I5 -> 158.48505 | O75: Average check for loading the limit by the end of the month, USD
B76: Оборот по выдаче, тенге | E76: ='Installment card_150 (indiv)'!P52*1000000 -> 2.4909613e+08 | F76: ='Installment card_150 (indiv)'!AC52*1000000 -> 9.2262672e+09 | G76: ='Installment card_150 (indiv)'!AP52*1000000 -> 2.0605956e+10 | H76: ='Installment card_150 (indiv)'!BC52*1000000 -> 3.0798067e+10 | I76: ='Installment card_150 (indiv)'!BP52*1000000 -> 4.0353953e+10 | K76: =E76+F76+G76+H76+I76 -> 1.0123334e+11 | L76: =E76/$E$5+F76/$F$5+G76/$G$5+H76/$H$5+I76/$I$5 -> 2.0246668e+08 | O76: Turnover of using limits for the period, tenge
A78: 4.2. | B78: Карта рассрочки (BNPL 1000 дол) | O78: Installment card ( BNPL. 1000 дол)
B79: % клиентов после внутренних проверок и отсечений внутри Билайна ( бесплатно) | E79: 0.35 | F79: 0.5 | G79: 0.6 | H79: =G79 -> 0.6 | I79: =H79 -> 0.6 | O79: % of clients after internal checks and cuts within Beeline (free)
B80: База после внутренних проверок | E80: =E8*E79/4 -> 438032.03 | F80: =F8*F79 -> 2781225.2 | G80: =G8*G79 -> 3729569.5 | H80: =H8*H79 -> 4201497.7 | I80: =I8*I79 -> 4801827.4 | O80: base after internal checks of Beeline
B81: % клиентов,прошедших комплайнес в Банке | E81: 0.8 | F81: 0.8 | G81: 0.8 | H81: 0.8 | I81: 0.8 | O81: % of clients who have passed compliance at the Bank
B82: База после комплайнеса в банке | E82: =E80*E81 -> 350425.62 | F82: =F80*F81 -> 2224980.1 | G82: =G80*G81 -> 2983655.6 | H82: =H80*H81 -> 3361198.2 | I82: =I80*I81 -> 3841461.9 | O82: Paid Base (Post-Compliance Base)
B83: AR | E83: 0.05 | F83: 0.05 | G83: 0.05 | H83: 0.05 | I83: 0.05 | O83: AR
B84: База после внешних , платных проверок ( КБ, доходы, налоги, аресты) - действует 30 дней | E84: =E82*E83 -> 17521.281 | F84: =F82*F83 -> 111249.01 | G84: =G82*G83 -> 149182.78 | H84: =H82*H83 -> 168059.91 | I84: =I82*I83 -> 192073.09 | O84: Approved clients
B85: Take up | E85: =E40 -> 0.3 | F85: =F40 -> 0.35 | G85: =G40 -> 0.4 | H85: =H40 -> 0.4 | I85: =I40 -> 0.4 | O85: % of responded clients
B86: Клиенты, согласившиеся на карту - эмиссия за период | E86: =E84*E85 -> 5256.3843 | F86: =F84*F85 -> 38937.152 | G86: =G84*G85 -> 59673.112 | H86: =H84*H85 -> 67223.964 | I86: =I84*I85 -> 76829.238 | O86: Clients who agreed to a card with a limit of $30 - issue cards
B87: % активации | E87: =E42 -> 0.95 | F87: =F42 -> 0.95 | G87: =G42 -> 0.95 | H87: =H42 -> 0.95 | I87: =I42 -> 0.95 | O87: % activation
B88: Кол-во клиентов, по которым установлен КЛ | E88: ='Installment card_1000 (indiv)'!P18 -> 0 | F88: ='Installment card_1000 (indiv)'!AC18 -> 21363.26 | G88: ='Installment card_1000 (indiv)'!AP18 -> 72538.713 | H88: ='Installment card_1000 (indiv)'!BC18 -> 115759.4 | I88: ='Installment card_1000 (indiv)'!BP18 -> 149248.23 | O88: Сards with established Credit Limit
B89: Средний чек лимита для карты, тенге | E89: =E90*E5 -> 500000 | F89: =F90*F5 -> 525000 | G89: =G90*G5 -> 551250 | H89: =H90*H5 -> 578812.5 | I89: =I90*I5 -> 607753.13 | O89: average check of the established credit limit, tenge
B90: Средний чек лимита для карты, долл | E90: 1000 | F90: =E90*105% -> 1050 | G90: =F90*105% -> 1102.5 | H90: =G90*105% -> 1157.625 | I90: =H90*105% -> 1215.5063 | O90: average check of the established credit limit, USD
B91: Сумма установленного кредитного лимита, тенге | E91: =E88*E89 -> 0 | F91: =F88*F89 -> 1.1215712e+10 | G91: =G88*G89 -> 3.9986966e+10 | H91: =H88*H89 -> 6.7002987e+10 | I91: =I88*I89 -> 9.070608e+10 | O91: Amount of established credit limit, tenge
B92: % клиентов, которые используют карту | E92: 0.95 | F92: =E92-1% -> 0.94 | G92: =F92-1% -> 0.93 | H92: =G92-1% -> 0.92 | I92: =H92-1% -> 0.91 | O92: % of customers who use the package
B93: Кол-во клиентов, использующих карту (с загрузкой лимита) | E93: ='Installment card_1000 (indiv)'!P22 -> 0 | F93: ='Installment card_1000 (indiv)'!AC22 -> 20081.464 | G93: ='Installment card_1000 (indiv)'!AP22 -> 67461.003 | H93: ='Installment card_1000 (indiv)'!BC22 -> 106498.65 | I93: ='Installment card_1000 (indiv)'!BP22 -> 135815.89 | O93: Сlients using the card (with limit loading and paying for the package)
B94: % загрузки лимита у клиентов, которые используют карту | E94: 0.5 | F94: 0.5 | G94: 0.5 | H94: 0.5 | I94: 0.5 | O94: % of limit utilisation for clients who use the package by the end of the month (overdue + rolling over limits)
B95: Сумма загруженного кредитного лимита, тенге | E95: =E91*E94 -> 0 | F95: =F91*F94 -> 5.6078558e+09 | G95: =G91*G94 -> 1.9993483e+10 | H95: =H91*H94 -> 3.3501493e+10 | I95: =I91*I94 -> 4.535304e+10 | K95: =I95 -> 4.535304e+10 | L95: =K95/I5 -> 90706080 | O95: Amount of loaded credit limit at the end of the month, tenge
B96: Средний чек загрузки лимита, тенге | F96: =F95/F93 -> 279255.32 | G96: =G95/G93 -> 296370.97 | H96: =H95/H93 -> 314572.01 | I96: =I95/I93 -> 333930.29 | O96: Average check for loading the limit by the end of the month, tenge
B97: сред чек загрузки лимита, долл | F97: =F96/F5 -> 558.51064 | G97: =G96/G5 -> 592.74194 | H97: =H96/H5 -> 629.14402 | I97: =I96/I5 -> 667.86058 | O97: Average check for loading the limit by the end of the month, USD
B98: Оборот по выдаче, тенге | E98: ='Installment card_1000 (indiv)'!P52*1000000 -> 0 | F98: ='Installment card_1000 (indiv)'!AC52*1000000 -> 6.7036544e+09 | G98: ='Installment card_1000 (indiv)'!AP52*1000000 -> 2.5872126e+10 | H98: ='Installment card_1000 (indiv)'!BC52*1000000 -> 3.8818347e+10 | I98: ='Installment card_1000 (indiv)'!BP52*1000000 -> 4.9729241e+10 | K98: =E98+F98+G98+H98+I98 -> 1.2112337e+11 | L98: =E98/$E$5+F98/$F$5+G98/$G$5+H98/$H$5+I98/$I$5 -> 2.4224674e+08 | O98: Turnover of using limits for the period, tenge
B99: проверка | E99: =E43-E66-E88 -> 51342.03 | F99: =F43-F66-F88 -> 264010.65 | G99: =G43-G66-G88 -> 520059.65 | H99: =H43-H66-H88 -> 729685.18 | I99: =I43-I66-I88 -> 887216.63 | O99: check
A100: 5 | B100: Cash Credit Dossym ( от 300 до 2000 дол, от 6 до 60 мес) - новая клиентская база | O100: Cash Credit Dossym (from 300 to 2000 USD, from 6 to 60 months) - new client base
B101: База клиентов для внутренних проверок | D101: =D8-D26 -> 3366539.4 | E101: =E8-E26 -> 4238417.3 | F101: =F8-F26 -> 4690970.6 | G101: =G8-G26 -> 5226612.7 | H101: =H8-H26 -> 5864759.3 | I101: =I8-I26 -> 6694648.2 | O101: Clients for internal audits
B102: внутренние проверки (конверсия их базы для внутренних проверок) | E102: 0.3 | F102: 0.3 | G102: 0.4 | H102: 0.5 | I102: 0.5 | O102: % of clients after internal checks and cuts within Beeline (free)
B103: Клиенты, прошедшие внутренние проверки | E103: =E101*E102/2 -> 635762.6 | F103: =F101*F102 -> 1407291.2 | G103: =G101*G102 -> 2090645.1 | H103: =H101*H102 -> 2932379.7 | I103: =I101*I102 -> 3347324.1 | O103: base after internal checks of Beeline
B104: % клиентов, которым будет предоставлен оффер | E104: 0.9 | F104: 0.9 | G104: 0.9 | H104: 0.9 | I104: 0.9 | O104: % of clients who will be provided with an offer
B105: Клиенты, которым отправлен оффер | E105: =E103*E104 -> 572186.34 | F105: =F103*F104 -> 1266562.1 | G105: =G103*G104 -> 1881580.6 | H105: =H103*H104 -> 2639141.7 | I105: =I103*I104 -> 3012591.7 | O105: Clients who received an offer
B106: % отклика | E106: 0.2 | F106: 0.2 | G106: 0.2 | H106: 0.2 | I106: 0.2 | O106: % response
B107: Оформленные заявки | E107: =E105*E106 -> 114437.27 | F107: =F105*F106 -> 253312.41 | G107: =G105*G106 -> 376316.12 | H107: =H105*H106 -> 527828.34 | I107: =I105*I106 -> 602518.34 | O107: Completed applications
B108: AR, % | E108: 0.2 | F108: 0.3 | G108: 0.35 | H108: 0.35 | I108: 0.35 | O108: AR, %
...

Sheet Funnel QH
A1: Funnel
D3: 45657 | E3: 45747 | F3: 45838 | G3: 45930 | H3: 46022
D4: 2024 | E4: 2025 | F4: 2025 | G4: 2025 | H4: 2025 | I4: 2026 | J4: 2026 | K4: 2027 | L4: 2027 | M4: 2028 | N4: 2028 | O4: 2029 | P4: 2029 | R4: 2024 | S4: 2025 | T4: 2026 | U4: 2027 | V4: 2028 | W4: 2029
D5: Y0 | E5: Q1 | F5: Q2 | G5: Q3 | H5: Q4 | I5: H1 | J5: H2 | K5: H1 | L5: H2 | M5: H1 | N5: H2 | O5: H1 | P5: H2 | R5: Y0 | S5: Y1 | T5: Y2 | U5: Y3 | V5: Y4 | W5: Y5
D6: 0 | E6: 1 | F6: 2 | G6: 3 | H6: 4 | I6: 5 | J6: 6 | K6: 7 | L6: 8 | M6: 9 | N6: 10 | O6: 11 | P6: 12
A7: Customers and Simply wallets | B7: ЕИ
A8: The clients of Beeline | B8: person | D8: =Funnel!D7 -> 5000000 | E8: =$D8+(E3-$D3)/($H3-$D3)*($H8-$D8) -> 5295890.4 | F8: =$D8+(F3-$D3)/($H3-$D3)*($H8-$D8) -> 5595068.5 | G8: =$D8+(G3-$D3)/($H3-$D3)*($H8-$D8) -> 5897534.2 | H8: =Funnel!E7 -> 6200000 | I8: =AVERAGE(H8,J8) -> 6497500 | J8: =Funnel!F7 -> 6795000 | K8: =AVERAGE(J8,L8) -> 7147500 | L8: =Funnel!G7 -> 7500000 | M8: =AVERAGE(L8,N8) -> 7932500 | N8: =Funnel!H7 -> 8365000 | O8: =AVERAGE(N8,P8) -> 8937500 | P8: =Funnel!I7 -> 9510000 | R8: =D8 -> 5000000 | S8: =H8 -> 6200000 | T8: =J8 -> 6795000 | U8: =L8 -> 7500000 | V8: =N8 -> 8365000 | W8: =P8 -> 9510000
A9: The growth rate of Beeline's customer base (year-on-year, YoY) | B9: % | H9: =H8/D8-1 -> 0.24 | J9: =J8/H8-1 -> 0.095967742 | L9: =L8/J8-1 -> 0.10375276 | N9: =N8/L8-1 -> 0.11533333 | P9: =P8/N8-1 -> 0.13687986 | S9: =S8/R8 -> 1.24 | T9: =T8/S8 -> 1.0959677 | U9: =U8/T8 -> 1.1037528 | V9: =V8/U8 -> 1.1153333 | W9: =W8/V8 -> 1.1368799
A10: The share of customers with smartphones (conversion to the number of Beeline customers), % | B10: % | D10: =D12/D8 -> 0.6192896 | E10: =D10 -> 0.6192896 | F10: =E10 -> 0.6192896 | G10: =F10 -> 0.6192896 | H10: =G10 -> 0.6192896 | I10: =H10 -> 0.6192896 | J10: =J12/J8 -> 0.6232896 | K10: =J10 -> 0.6232896 | L10: =L12/L8 -> 0.6252896 | M10: =L10 -> 0.6252896 | N10: =N12/N8 -> 0.6272896 | O10: =N10 -> 0.6272896 | P10: =P12/P8 -> 0.6292896 | R10: =D10 -> 0.6192896 | S10: =H10 -> 0.6192896 | T10: =J10 -> 0.6232896 | U10: =L10 -> 0.6252896 | V10: =N10 -> 0.6272896 | W10: =P10 -> 0.6292896
A11: The number of Simply e-wallets | B11: unit | D11: =Funnel!D8 -> 4100000 | E11: =E12+E16 -> 4320359.5 | F11: =F12+F16 -> 4543167.5 | G11: =G12+G16 -> 4768423.9 | H11: =Funnel!E8 -> 5006080.3 | I11: =I12+I16 -> 5264475.3 | J11: =Funnel!F8 -> 5562450.4 | K11: =K12+K16 -> 5881699.8 | L11: =Funnel!G8 -> 6215949.1 | M11: =M12+M16 -> 6600857.7 | N11: =Funnel!H8 -> 7002496.2 | O11: =O12+O16 -> 7493260.9 | P11: =Funnel!I8 -> 8003045.6 | R11: =D11 -> 4100000 | S11: =H11 -> 5006080.3 | T11: =J11 -> 5562450.4 | U11: =L11 -> 6215949.1 | V11: =N11 -> 7002496.2 | W11: =P11 -> 8003045.6
A12: Beeline | B12: unit | D12: =Funnel!D9 -> 3096448 | E12: =E8*E10 -> 3279689.9 | F12: =F8*F10 -> 3464967.7 | G12: =G8*G10 -> 3652281.6 | H12: =Funnel!E9 -> 3851995.5 | I12: =I8*I10 -> 4023834.2 | J12: =Funnel!F9 -> 4235252.8 | K12: =K8*K10 -> 4454962.4 | L12: =Funnel!G9 -> 4689672 | M12: =M8*M10 -> 4960109.8 | N12: =Funnel!H9 -> 5247277.5 | O12: =O8*O10 -> 5606400.8 | P12: =Funnel!I9 -> 5984544.1 | R12: =D12 -> 3096448 | S12: =H12 -> 3851995.5 | T12: =J12 -> 4235252.8 | U12: =L12 -> 4689672 | V12: =N12 -> 5247277.5 | W12: =P12 -> 5984544.1
A13: The share of identified customers | B13: % | D13: 0.03 | E13: 0.03 | F13: 0.03 | G13: 0.03 | H13: 0.03 | I13: 0.03 | J13: 0.03 | K13: 0.03 | L13: 0.03 | M13: 0.03 | N13: 0.03 | O13: 0.03 | P13: 0.03 | R13: =D13 -> 0.03 | S13: =H13 -> 0.03 | T13: =J13 -> 0.03 | U13: =L13 -> 0.03 | V13: =N13 -> 0.03 | W13: =P13 -> 0.03
A14: Identified | B14: unit | D14: =D12*D13 -> 92893.44 | E14: =E12*E13 -> 98390.696 | F14: =F12*F13 -> 103949.03 | G14: =G12*G13 -> 109568.45 | H14: =H12*H13 -> 115559.87 | I14: =I12*I13 -> 120715.03 | J14: =J12*J13 -> 127057.58 | K14: =K12*K13 -> 133648.87 | ... P14: =P12*P13 -> 179536.32 | R14: =D14 -> 92893.44 | S14: =H14 -> 115559.87 | T14: =J14 -> 127057.58 | U14: =L14 -> 140690.16 | V14: =N14 -> 157418.33 | W14: =P14 -> 179536.32
A15: Non-Identified | B15: unit | D15: =D12-D14 -> 3003554.6 | E15: =E12-E14 -> 3181299.2 | F15: =F12-F14 -> 3361018.7 | G15: =G12-G14 -> 3542713.2 | H15: =H12-H14 -> 3736435.7 | I15: =I12-I14 -> 3903119.2 | J15: =J12-J14 -> 4108195.2 | K15: =K12-K14 -> 4321313.5 | ... P15: =P12-P14 -> 5805007.8 | R15: =D15 -> 3003554.6 | S15: =H15 -> 3736435.7 | T15: =J15 -> 4108195.2 | U15: =L15 -> 4548981.8 | V15: =N15 -> 5089859.2 | W15: =P15 -> 5805007.8
A16: Non-Beeline | B16: unit | D16: =Funnel!D13 -> 1003552 | E16: =$D16+(E3-$D3)/($H3-$D3)*($H16-$D16) -> 1040669.7 | F16: =$D16+(F3-$D3)/($H3-$D3)*($H16-$D16) -> 1078199.8 | G16: =$D16+(G3-$D3)/($H3-$D3)*($H16-$D16) -> 1116142.3 | H16: =Funnel!E13 -> 1154084.8 | I16: =AVERAGE(H16,J16) -> 1240641.2 | J16: =Funnel!F13 -> 1327197.5 | K16: =AVERAGE(J16,L16) -> 1426737.3 | L16: =Funnel!G13 -> 1526277.1 | M16: =AVERAGE(L16,N16) -> 1640747.9 | N16: =Funnel!H13 -> 1755218.7 | O16: =AVERAGE(N16,P16) -> 1886860.1 | P16: =Funnel!I13 -> 2018501.5 | R16: =D16 -> 1003552 | S16: =H16 -> 1154084.8 | T16: =J16 -> 1327197.5 | U16: =L16 -> 1526277.1 | V16: =N16 -> 1755218.7 | W16: =P16 -> 2018501.5
A17: Customer base growth rate (year-on-year, YoY) | B17: % | H17: =H16/D16-1 -> 0.15 | J17: =J16/H16-1 -> 0.15 | L17: =L16/J16-1 -> 0.15 | N17: =N16/L16-1 -> 0.15 | P17: =P16/N16-1 -> 0.15 | S17: =S16/R16 -> 1.15 | T17: =T16/S16 -> 1.15 | U17: =U16/T16 -> 1.15 | V17: =V16/U16 -> 1.15 | W17: =W16/V16 -> 1.15
A18: The share of identified customers | B18: % | D18: 0.13 | E18: 0.12 | F18: 0.12 | G18: 0.12 | H18: 0.12 | I18: 0.1 | J18: 0.1 | K18: 0.09 | L18: 0.09 | M18: 0.08 | N18: 0.08 | O18: 0.07 | P18: 0.07 | R18: =D18 -> 0.13 | S18: =H18 -> 0.12 | T18: =J18 -> 0.1 | U18: =L18 -> 0.09 | V18: =N18 -> 0.08 | W18: =P18 -> 0.07
A19: Identified | B19: unit | D19: =D16*D18 -> 130461.76 | E19: =E16*E18 -> 124880.36 | F19: =F16*F18 -> 129383.97 | G19: =G16*G18 -> 133937.07 | H19: =H16*H18 -> 138490.18 | I19: =I16*I18 -> 124064.12 | J19: =J16*J18 -> 132719.75 | K19: =K16*K18 -> 128406.36 | ... P19: =P16*P18 -> 141295.11 | R19: =D19 -> 130461.76 | S19: =H19 -> 138490.18 | T19: =J19 -> 132719.75 | U19: =L19 -> 137364.94 | V19: =N19 -> 140417.5 | W19: =P19 -> 141295.11
A20: Non-Identified | B20: unit | D20: =D16-D19 -> 873090.24 | E20: =E16-E19 -> 915789.32 | F20: =F16-F19 -> 948815.8 | G20: =G16-G19 -> 982205.21 | H20: =H16-H19 -> 1015594.6 | I20: =I16-I19 -> 1116577 | J20: =J16-J19 -> 1194477.8 | K20: =K16-K19 -> 1298331 | ... P20: =P16-P19 -> 1877206.4 | R20: =D20 -> 873090.24 | S20: =H20 -> 1015594.6 | T20: =J20 -> 1194477.8 | U20: =L20 -> 1388912.2 | V20: =N20 -> 1614801.2 | W20: =P20 -> 1877206.4
A21: The share of active Simply wallets | B21: % | D21: 0.23329659 | E21: 0.2 | F21: 0.2 | G21: 0.2 | H21: 0.2 | I21: 0.2 | J21: 0.2 | K21: 0.2 | L21: 0.2 | M21: 0.2 | N21: 0.2 | O21: 0.2 | P21: 0.2 | R21: =D21 -> 0.23329659 | S21: =H21 -> 0.2 | T21: =J21 -> 0.2 | U21: =L21 -> 0.2 | V21: =N21 -> 0.2 | W21: =P21 -> 0.2
A22: Active Simply wallets | B22: unit | D22: =ROUND(D21*D11,0) -> 956516 | E22: =ROUND(E21*E11,0) -> 864072 | F22: =ROUND(F21*F11,0) -> 908634 | G22: =ROUND(G21*G11,0) -> 953685 | H22: =ROUND(H21*H11,0) -> 1001216 | I22: =ROUND(I21*I11,0) -> 1052895 | J22: =ROUND(J21*J11,0) -> 1112490 | K22: =ROUND(K21*K11,0) -> 1176340 | ... P22: =ROUND(P21*P11,0) -> 1600609 | R22: =D22 -> 956516 | S22: =H22 -> 1001216 | T22: =J22 -> 1112490 | U22: =L22 -> 1243190 | V22: =N22 -> 1400499 | W22: =P22 -> 1600609
A23: The share of Auto AML passed (from active Simply wallets) | B23: % | D23: 0.8 | E23: 0.8 | F23: 0.8 | G23: 0.8 | H23: 0.8 | I23: 0.8 | J23: 0.8 | K23: 0.8 | L23: 0.8 | M23: 0.8 | N23: 0.8 | O23: 0.8 | P23: 0.8 | R23: =D23 -> 0.8 | S23: =H23 -> 0.8 | T23: =J23 -> 0.8 | U23: =L23 -> 0.8 | V23: =N23 -> 0.8 | W23: =P23 -> 0.8
A24: Ecosystem clients (individuals) | B24: unit | D24: ='Funnel QH'!D11*'Funnel QH'!D23 -> 3280000 | E24: ='Funnel QH'!E11*'Funnel QH'!E23 -> 3456287.6 | F24: ='Funnel QH'!F11*'Funnel QH'!F23 -> 3634534 | G24: ='Funnel QH'!G11*'Funnel QH'!G23 -> 3814739.1 | H24: ='Funnel QH'!H11*'Funnel QH'!H23 -> 4004864.3 | I24: ='Funnel QH'!I11*'Funnel QH'!I23 -> 4211580.3 | J24: ='Funnel QH'!J11*'Funnel QH'!J23 -> 4449960.3 | K24: ='Funnel QH'!K11*'Funnel QH'!K23 -> 4705359.8 | ... P24: ='Funnel QH'!P11*'Funnel QH'!P23 -> 6402436.5 | R24: =D24 -> 3280000 | S24: =H24 -> 4004864.3 | T24: =J24 -> 4449960.3 | U24: =L24 -> 4972759.3 | V24: =N24 -> 5601997 | W24: =P24 -> 6402436.5
A25: Merchants, including: | B25: unit | J25: =SUM(J26:J27) -> 30000 | K25: =SUM(K26:K27) -> 49833.333 | L25: =SUM(L26:L27) -> 69666.667 | M25: =SUM(M26:M27) -> 89500 | N25: =SUM(N26:N27) -> 109333.33 | O25: =SUM(O26:O27) -> 129166.67 | P25: 149000 | R25: =D25 -> 0 | S25: =H25 -> 0 | T25: =J25 -> 30000 | U25: =L25 -> 69666.667 | V25: =N25 -> 109333.33 | W25: =P25 -> 149000
A26: Individual entrepreneurs (IE) | B26: unit | J26: 21000 | K26: =J26+($P26-$J26)/6 -> 34883.333 | L26: =K26+($P26-$J26)/6 -> 48766.667 | M26: =L26+($P26-$J26)/6 -> 62650 | N26: =M26+($P26-$J26)/6 -> 76533.333 | O26: =N26+($P26-$J26)/6 -> 90416.667 | P26: =$P$25*J26/$J$25 -> 104300 | R26: =D26 -> 0 | S26: =H26 -> 0 | T26: =J26 -> 21000 | U26: =L26 -> 48766.667 | V26: =N26 -> 76533.333 | W26: =P26 -> 104300
A27: Legal entities (LE) | B27: unit | J27: 9000 | K27: =J27+($P27-$J27)/6 -> 14950 | L27: =K27+($P27-$J27)/6 -> 20900 | M27: =L27+($P27-$J27)/6 -> 26850 | N27: =M27+($P27-$J27)/6 -> 32800 | O27: =N27+($P27-$J27)/6 -> 38750 | P27: =$P$25*J27/$J$25 -> 44700 | R27: =D27 -> 0 | S27: =H27 -> 0 | T27: =J27 -> 9000 | U27: =L27 -> 20900 | V27: =N27 -> 32800 | W27: =P27 -> 44700
A29: Параметры | B29: ЕИ
A30: Курс USD/KZT | B30: тенге | D30: =Funnel!D5 -> 500 | E30: 500 | F30: 500 | G30: 500 | H30: =Funnel!E5 -> 500 | I30: 500 | J30: =Funnel!F5 -> 500 | K30: 500 | L30: =Funnel!G5 -> 500 | M30: 500 | N30: =Funnel!H5 -> 500 | O30: 500 | P30: =Funnel!I5 -> 500
A31: Инфляция | B31: %

Sheet packages (indiv)
D1: 31 | E1: 28 | F1: 31 | G1: 30 | H1: 31 | I1: 30 | J1: 31 | K1: 31 | L1: 30 | M1: 31 | N1: 30 | O1: 31 | P1: =SUM(D1:O1) -> 365 | Q1: 31 | R1: 28 | S1: 31 | T1: 30 | U1: 31 | V1: 30 | W1: 31 | X1: 31 | Y1: 30 | Z1: 31 | AA1: 30 | AB1: 31 | AC1: =SUM(Q1:AB1) -> 365 | AD1: 31 | AE1: 28 | AF1: 31 | AG1: 30 | AH1: 31 | AI1: 30 | AJ1: 31 | AK1: 31 | AL1: 30 | AM1: 31 | AN1: 30 | AO1: 31 | AP1: =SUM(AD1:AO1) -> 365 | AQ1: 31 | AR1: 28 | AS1: 31 | AT1: 30 | AU1: 31 | AV1: 30 | AW1: 31 | AX1: 31 | AY1: 30 | AZ1: 31 | BA1: 30 | BB1: 31 | BC1: =SUM(AQ1:BB1) -> 365 | BD1: 31 | BE1: 28 | BF1: 31 | BG1: 30 | BH1: 31 | BI1: 30 | BJ1: 31 | BK1: 31 | BL1: 30 | BM1: 31 | BN1: 30 | BO1: 31 | BP1: =SUM(BD1:BO1) -> 365
B2: ед изм | D2: 1 мес | E2: 2 мес | F2: 3 мес | G2: 4 мес | H2: 5 мес | I2: 6 мес | J2: 7 мес | K2: 8 мес | L2: 9 мес | M2: 10 мес | N2: 11 мес | O2: 12 мес | P2: 1 год | Q2: 1 мес | R2: 2 мес | S2: 3 мес | T2: 4 мес | U2: 5 мес | V2: 6 мес | W2: 7 мес | X2: 8 мес | Y2: 9 мес | Z2: 10 мес | AA2: 11 мес | AB2: 12 мес | AC2: 2 год | AD2: 1 мес | AE2: 2 мес | AF2: 3 мес | AG2: 4 мес | AH2: 5 мес | AI2: 6 мес | AJ2: 7 мес | AK2: 8 мес | AL2: 9 мес | AM2: 10 мес | AN2: 11 мес | AO2: 12 мес | AP2: 3 год | AQ2: 1 мес | AR2: 2 мес | AS2: 3 мес | AT2: 4 мес | AU2: 5 мес | AV2: 6 мес | AW2: 7 мес | AX2: 8 мес | AY2: 9 мес | AZ2: 10 мес | BA2: 11 мес | BB2: 12 мес | BC2: 4 год | BD2: 1 мес | BE2: 2 мес | BF2: 3 мес | BG2: 4 мес | BH2: 5 мес | BI2: 6 мес | BJ2: 7 мес | BK2: 8 мес | BL2: 9 мес | BM2: 10 мес | BN2: 11 мес | BO2: 12 мес | BP2: 5 год
A4: База для платных проверок (база после комплаенса) | B4: штук | I4: ='Micro_30 (indiv)'!I4 -> 57352.994 | J4: ='Micro_30 (indiv)'!J4 -> 59946.143 | K4: ='Micro_30 (indiv)'!K4 -> 62539.293 | L4: ='Micro_30 (indiv)'!L4 -> 65132.442 | M4: ='Micro_30 (indiv)'!M4 -> 67725.592 | N4: ='Micro_30 (indiv)'!N4 -> 70318.742 | O4: ='Micro_30 (indiv)'!O4 -> 69968.316 | P4: ='Micro_30 (indiv)'!P4 -> 700851.24 | ... BP4: ='Micro_30 (indiv)'!BP4 -> 3841461.9 | CE4: Paid Base (Post-Compliance Base) | CF4: unit
A5: AR, % | B5: % | D5: 0 | E5: ='Micro_30 (indiv)'!E6 -> 0 | F5: ='Micro_30 (indiv)'!F6 -> 0 | G5: ='Micro_30 (indiv)'!G6 -> 0 | H5: ='Micro_30 (indiv)'!H6 -> 0 | I5: ='Micro_30 (indiv)'!I6 -> 0 | J5: ='Micro_30 (indiv)'!J6 -> 0.5 | K5: ='Micro_30 (indiv)'!K6 -> 0.5 | L5: ='Micro_30 (indiv)'!L6 -> 0.5 | ... BP5: ='Micro_30 (indiv)'!BP6 -> 0.5 | CE5: AR, % | CF5: %
A6: Кол-во одобренных клиентов | B6: штук | D6: =D4*D5 -> 0 | E6: =E4*E5 -> 0 | F6: =F4*F5 -> 0 | G6: =G4*G5 -> 0 | H6: =H4*H5 -> 0 | I6: =I4*I5 -> 0 | J6: =J4*J5 -> 29973.072 | K6: =K4*K5 -> 31269.646 | ... BP6: =BP4*BP5 -> 1920730.9 | CE6: Approved clients | CF6: unit
A7: % клиентов, которые откликнулись | B7: % | D7: ='Micro_30 (indiv)'!D8 -> 0.3 | E7: ='Micro_30 (indiv)'!E8 -> 0.3 | F7: ='Micro_30 (indiv)'!F8 -> 0.3 | G7: ='Micro_30 (indiv)'!G8 -> 0.3 | H7: ='Micro_30 (indiv)'!H8 -> 0.3 | I7: ='Micro_30 (indiv)'!I8 -> 0.3 | J7: ='Micro_30 (indiv)'!J8 -> 0.3 | K7: ='Micro_30 (indiv)'!K8 -> 0.3 | ... BP7: ='Micro_30 (indiv)'!BP8 -> 0.4 | CE7: % of responded clients | CF7: %
A8: Клиенты, согласившиеся на карту с лимитом 30 долл - эмиссия | B8: штук | D8: =D6*D7 -> 0 | E8: =E6*E7 -> 0 | F8: =F6*F7 -> 0 | G8: =G6*G7 -> 0 | H8: =H6*H7 -> 0 | I8: =I6*I7 -> 0 | J8: =J6*J7 -> 8991.9215 | K8: =K6*K7 -> 9380.8939 | ... BP8: =BP6*BP7 -> 768292.38 | CE8: Clients who agreed to a card with a limit of $30 - issue cards | CF8: unit
A9: % эмиссии с пластиком | B9: % | D9: ='Micro_30 (indiv)'!D10 -> 0.7 | E9: ='Micro_30 (indiv)'!E10 -> 0.7 | F9: ='Micro_30 (indiv)'!F10 -> 0.7 | G9: ='Micro_30 (indiv)'!G10 -> 0.7 | H9: ='Micro_30 (indiv)'!H10 -> 0.7 | I9: ='Micro_30 (indiv)'!I10 -> 0.7 | J9: ='Micro_30 (indiv)'!J10 -> 0.7 | K9: ='Micro_30 (indiv)'!K10 -> 0.7 | ... BP9: ='Micro_30 (indiv)'!BP10 -> 0.7 | CE9: % emissions with plastic | CF9: %
A10: Эмиссия пластика | B10: штук | D10: =D8*D9 -> 0 | E10: =E8*E9 -> 0 | F10: =F8*F9 -> 0 | G10: =G8*G9 -> 0 | H10: =H8*H9 -> 0 | I10: =I8*I9 -> 0 | J10: =J8*J9 -> 6294.345 | K10: =K8*K9 -> 6566.6257 | ... BP10: =BP8*BP9 -> 537804.67 | CE10: Issuance of plastic cards | CF10: unit
A11: % доставки карт | B11: % | D11: ='Micro_30 (indiv)'!D12 -> 1 | E11: ='Micro_30 (indiv)'!E12 -> 1 | F11: ='Micro_30 (indiv)'!F12 -> 1 | G11: ='Micro_30 (indiv)'!G12 -> 1 | H11: ='Micro_30 (indiv)'!H12 -> 1 | I11: ='Micro_30 (indiv)'!I12 -> 1 | J11: ='Micro_30 (indiv)'!J12 -> 1 | K11: ='Micro_30 (indiv)'!K12 -> 1 | ... BP11: ='Micro_30 (indiv)'!BP12 -> 1 | CE11: % of card delivery | CF11: %
A12: Кол-во карт к доставке | B12: штук | D12: =D10*D11 -> 0 | E12: =E10*E11 -> 0 | F12: =F10*F11 -> 0 | G12: =G10*G11 -> 0 | H12: =H10*H11 -> 0 | I12: =I10*I11 -> 0 | J12: =J10*J11 -> 6294.345 | K12: =K10*K11 -> 6566.6257 | ... BP12: =BP10*BP11 -> 537804.67 | CE12: Cards to be delivered | CF12: unit
A13: % активации | B13: % | D13: ='Micro_30 (indiv)'!D14 -> 0.95 | E13: ='Micro_30 (indiv)'!E14 -> 0.95 | F13: ='Micro_30 (indiv)'!F14 -> 0.95 | G13: ='Micro_30 (indiv)'!G14 -> 0.95 | H13: ='Micro_30 (indiv)'!H14 -> 0.95 | I13: ='Micro_30 (indiv)'!I14 -> 0.95 | J13: ='Micro_30 (indiv)'!J14 -> 0.95 | K13: ='Micro_30 (indiv)'!K14 -> 0.95 | ... BP13: ='Micro_30 (indiv)'!BP14 -> 0.95 | CE13: % activation | CF13: %
A14: Активировано карт за период | B14: штук | D14: =D8*D13 -> 0 | E14: =E8*E13 -> 0 | F14: =F8*F13 -> 0 | G14: =G8*G13 -> 0 | H14: =H8*H13 -> 0 | I14: =I8*I13 -> 0 | J14: =J8*J13 -> 8542.3254 | K14: =K8*K13 -> 8911.8492 | ... BP14: =BP8*BP13 -> 729877.76 | CE14: Cards activated during the period | CF14: unit
A15: % отмирания активированных карт | B15: % | D15: ='Micro_30 (indiv)'!D16 -> -0.001 | E15: ='Micro_30 (indiv)'!E16 -> -0.0015 | F15: ='Micro_30 (indiv)'!F16 -> -0.002 | G15: ='Micro_30 (indiv)'!G16 -> -0.0025 | H15: ='Micro_30 (indiv)'!H16 -> -0.003 | I15: ='Micro_30 (indiv)'!I16 -> -0.0035 | J15: ='Micro_30 (indiv)'!J16 -> -0.004 | K15: ='Micro_30 (indiv)'!K16 -> -0.0045 | ... BP15: ='Micro_30 (indiv)'!BP16 -> 0 | CE15: % of activated cards closed | CF15: %
A16: Закрыто карт (отмирание) | B16: штук | D16: =C17*D15 -> 0 | E16: =D17*E15 -> 0 | F16: =E17*F15 -> 0 | G16: =F17*G15 -> 0 | H16: =G17*H15 -> 0 | I16: =H17*I15 -> 0 | J16: =I17*J15 -> 0 | K16: =J17*K15 -> -38.440464 | ... BP16: =BO17*BP15 -> 0 | CE16: Сlosed cards | CF16: unit
A17: Кол-во пакетов = кол-во карт, с установленным КЛ (по микрозайму 30) | B17: штук | C17: 0 | D17: ='Micro_30 (indiv)'!D18 -> 0 | E17: ='Micro_30 (indiv)'!E18 -> 0 | F17: ='Micro_30 (indiv)'!F18 -> 0 | G17: ='Micro_30 (indiv)'!G18 -> 0 | H17: ='Micro_30 (indiv)'!H18 -> 0 | I17: ='Micro_30 (indiv)'!I18 -> 0 | J17: ='Micro_30 (indiv)'!J18 -> 8542.3254 | K17: ='Micro_30 (indiv)'!K18 -> 17415.734 | ... AB17: ='Micro_30 (indiv)'!AB18 -> 399794.5 | AC17: =AB17 -> 399794.5 | AD17: ='Micro_30 (indiv)'!AD18 -> 430500.5 | AE17: ='Micro_30 (indiv)'!AE18 -> 462689.57 | AF17: ='Micro_30 (indiv)'!AF18 -> 496310.26 | AG17: ='Micro_30 (indiv)'!AG18 -> 531309.62 | AH17: ='Micro_30 (indiv)'!AH18 -> 567633.33 | AI17: ='Micro_30 (indiv)'!AI18 -> 605225.89 | AJ17: ='Micro_30 (indiv)'!AJ18 -> 644030.66 | AK17: ='Micro_30 (indiv)'!AK18 -> 683990.04 | ... AO17: ='Micro_30 (indiv)'!AO18 -> 851814.28 | AP17: =AO17 -> 851814.28 | AQ17: ='Micro_30 (indiv)'!AQ18 -> 876076.23 | AR17: ='Micro_30 (indiv)'!AR18 -> 901802.08 | AS17: ='Micro_30 (indiv)'!AS18 -> 928938.3 | AT17: ='Micro_30 (indiv)'!AT18 -> 957430.25 | AU17: ='Micro_30 (indiv)'!AU18 -> 987222.32 | AV17: ='Micro_30 (indiv)'!AV18 -> 1018258.1 | AW17: ='Micro_30 (indiv)'!AW18 -> 1050480.3 | AX17: ='Micro_30 (indiv)'!AX18 -> 1083831.4 | ... BB17: ='Micro_30 (indiv)'!BB18 -> 1224673.5 | BC17: =BB17 -> 1224673.5 | BD17: ='Micro_30 (indiv)'!BD18 -> 1240282.3 | BE17: ='Micro_30 (indiv)'!BE18 -> 1257581.2 | BF17: ='Micro_30 (indiv)'!BF18 -> 1276510.8 | BG17: ='Micro_30 (indiv)'!BG18 -> 1297010.5 | BH17: ='Micro_30 (indiv)'!BH18 -> 1319019 | BI17: ='Micro_30 (indiv)'!BI18 -> 1342474.3 | BJ17: ='Micro_30 (indiv)'!BJ18 -> 1367313.9 | BK17: ='Micro_30 (indiv)'!BK18 -> 1393474.9 | ... BO17: ='Micro_30 (indiv)'!BO18 -> 1507002.9 | BP17: =BO17 -> 1507002.9 | CE17: Number of packages = number of cards with established CL (for microloan 30) | CF17: unit
A18: пакет - бесплатный (микрозайм + дебетная карта) | B18: штук | C18: 0 | D18: =D17-D19-D20 -> 0 | E18: =E17-E19-E20 -> 0 | F18: =F17-F19-F20 -> 0 | G18: =G17-G19-G20 -> 0 | H18: =H17-H19-H20 -> 0 | I18: =I17-I19-I20 -> 0 | J18: =J17-J19-J20 -> 8542.3254 | K18: =K17-K19-K20 -> 17415.734 | ... BP18: =BP17-BP19-BP20 -> 887216.63 | CE18: Package - "freemeum" (microloan + debit card) | CF18: unit
A19: пакет 1й категории (микрозайм + карта рассрочки 150 + дебетная карта) | B19: штук | C19: 0 | D19: ='Installment card_150 (indiv)'!D18 -> 0 | E19: ='Installment card_150 (indiv)'!E18 -> 0 | F19: ='Installment card_150 (indiv)'!F18 -> 0 | G19: ='Installment card_150 (indiv)'!G18 -> 0 | H19: ='Installment card_150 (indiv)'!H18 -> 0 | I19: ='Installment card_150 (indiv)'!I18 -> 0 | J19: ='Installment card_150 (indiv)'!J18 -> 0 | K19: ='Installment card_150 (indiv)'!K18 -> 0 | ... BP19: ='Installment card_150 (indiv)'!BP18 -> 470538.06 | CE19: "White" package (microloan + 150 installment card + debit card) | CF19: unit
A20: пакет 2й категории (микрозайм + карта рассрочки 1000 + дебетная карта) | B20: штук | C20: 0 | D20: ='Installment card_1000 (indiv)'!D18 -> 0 | E20: ='Installment card_1000 (indiv)'!E18 -> 0 | F20: ='Installment card_1000 (indiv)'!F18 -> 0 | G20: ='Installment card_1000 (indiv)'!G18 -> 0 | H20: ='Installment card_1000 (indiv)'!H18 -> 0 | I20: ='Installment card_1000 (indiv)'!I18 -> 0 | J20: ='Installment card_1000 (indiv)'!J18 -> 0 | K20: ='Installment card_1000 (indiv)'!K18 -> 0 | ... BP20: ='Installment card_1000 (indiv)'!BP18 -> 149248.23 | CE20: "Black" package (microloan + 1000 installment card + debit card) | CF20: unit
A21: Структура пакетов | CE21: Package structure
A22: пакет - бесплатный (микрозайм + дебетная карта) | B22: % | J22: =J18/J17 -> 1 | K22: =K18/K17 -> 1 | L22: =L18/L17 -> 0.96246855 | M22: =M18/M17 -> 0.94322848 | N22: =N18/N17 -> 0.93132625 | O22: =O18/O17 -> 0.9235786 | P22: =P18/P17 -> 0.9235786 | Q22: =Q18/Q17 -> 0.8522593 | ... BP22: =BP18/BP17 -> 0.5887292 | CE22: Package - "freemeum" (microloan + debit card) | CF22: %
A23: пакет 1й категории (микрозайм + карта рассрочки 150 + дебетная карта) | B23: % | J23: =J19/J17 -> 0 | K23: =K19/K17 -> 0 | L23: =L19/L17 -> 0.037531453 | M23: =M19/M17 -> 0.056771519 | N23: =N19/N17 -> 0.06867375 | O23: =O19/O17 -> 0.076421396 | P23: =P19/P17 -> 0.076421396 | Q23: =Q19/Q17 -> 0.1477407 | ... BP23: =BP19/BP17 -> 0.31223434 | CE23: "White" package (microloan + 150 installment card + debit card) | CF23: %
A24: пакет 2й категории (микрозайм + карта рассрочки 1000 + дебетная карта) | B24: % | J24: =J20/J17 -> 0 | K24: =K20/K17 -> 0 | L24: =L20/L17 -> 0 | M24: =M20/M17 -> 0 | N24: =N20/N17 -> 0 | O24: =O20/O17 -> 0 | P24: =P20/P17 -> 0 | Q24: =Q20/Q17 -> 0 | ... BP24: =BP20/BP17 -> 0.099036459 | CE24: "Black" package (microloan + 1000 installment card + debit card) | CF24: %
A25: Кол-во активных пакетов = кол-во карт, которые используют карту | B25: штук | C25: 0 | D25: ='Micro_30 (indiv)'!D22 -> 0 | E25: ='Micro_30 (indiv)'!E22 -> 0 | F25: ='Micro_30 (indiv)'!F22 -> 0 | G25: ='Micro_30 (indiv)'!G22 -> 0 | H25: ='Micro_30 (indiv)'!H22 -> 0 | I25: ='Micro_30 (indiv)'!I22 -> 0 | J25: ='Micro_30 (indiv)'!J22 -> 6833.8603 | K25: ='Micro_30 (indiv)'!K22 -> 13932.587 | ... BP25: ='Micro_30 (indiv)'!BP22 -> 1205602.3 | CE25: Number of active packages = number of cards that use the card | CF25: unit
A26: пакет - бесплатный (микрозайм + дебетная карта) | B26: штук | C26: 0 | D26: =D25-D27-D28 -> 0 | E26: =E25-E27-E28 -> 0 | F26: =F25-F27-F28 -> 0 | G26: =G25-G27-G28 -> 0 | H26: =H25-H27-H28 -> 0 | I26: =I25-I27-I28 -> 0 | J26: =J25-J27-J28 -> 6833.8603 | K26: =K25-K27-K28 -> 13932.587 | ... BP26: =BP25-BP27-BP28 -> 613364.53 | CE26: Package - "freemeum" (microloan + debit card) | CF26: unit
A27: пакет 1й категории (микрозайм + карта рассрочки 150 + дебетная карта) | B27: штук | C27: 0 | D27: ='Installment card_150 (indiv)'!D22 -> 0 | E27: ='Installment card_150 (indiv)'!E22 -> 0 | F27: ='Installment card_150 (indiv)'!F22 -> 0 | G27: ='Installment card_150 (indiv)'!G22 -> 0 | H27: ='Installment card_150 (indiv)'!H22 -> 0 | I27: ='Installment card_150 (indiv)'!I22 -> 0 | J27: ='Installment card_150 (indiv)'!J22 -> 0 | K27: ='Installment card_150 (indiv)'!K22 -> 0 | ... BP27: ='Installment card_150 (indiv)'!BP22 -> 456421.92 | CE27: "White" package (microloan + 150 installment card + debit card) | CF27: unit
A28: пакет 2й категории (микрозайм + карта рассрочки 1000 + дебетная карта) | B28: штук | C28: 0 | D28: ='Installment card_1000 (indiv)'!D22 -> 0 | E28: ='Installment card_1000 (indiv)'!E22 -> 0 | F28: ='Installment card_1000 (indiv)'!F22 -> 0 | G28: ='Installment card_1000 (indiv)'!G22 -> 0 | H28: ='Installment card_1000 (indiv)'!H22 -> 0 | I28: ='Installment card_1000 (indiv)'!I22 -> 0 | J28: ='Installment card_1000 (indiv)'!J22 -> 0 | K28: ='Installment card_1000 (indiv)'!K22 -> 0 | ... BP28: ='Installment card_1000 (indiv)'!BP22 -> 135815.89 | CE28: "Black" package (microloan + 1000 installment card + debit card) | CF28: unit
A29: Структура пакетов | CE29: Active Packages structure
A30: пакет - бесплатный (микрозайм + дебетная карта) | B30: % | J30: =J26/J25 -> 1 | K30: =K26/K25 -> 1 | L30: =L26/L25 -> 0.95355483 | M30: =M26/M25 -> 0.92974525 | N30: =N26/N25 -> 0.91501623 | O30: =O26/O25 -> 0.90542852 | P30: =P26/P25 -> 0.90542852 | Q30: =Q26/Q25 -> 0.81809427 | ... BP30: =BP26/BP25 -> 0.50876189 | CE30: Package - "freemeum" (microloan + debit card) | CF30: %
A31: пакет 1й категории (микрозайм + карта рассрочки 150 + дебетная карта) | B31: % | J31: =J27/J25 -> 0 | K31: =K27/K25 -> 0 | L31: =L27/L25 -> 0.046445173 | M31: =M27/M25 -> 0.070254754 | N31: =N27/N25 -> 0.084983765 | O31: =O27/O25 -> 0.094571478 | P31: =P27/P25 -> 0.094571478 | Q31: =Q27/Q25 -> 0.18190573 | ... BP31: =BP27/BP25 -> 0.37858414 | CE31: "White" package (microloan + 150 installment card + debit card) | CF31: %
A32: пакет 2й категории (микрозайм + карта рассрочки 1000 + дебетная карта) | B32: % | J32: =J28/J25 -> 0 | K32: =K28/K25 -> 0 | L32: =L28/L25 -> 0 | M32: =M28/M25 -> 0 | N32: =N28/N25 -> 0 | O32: =O28/O25 -> 0 | P32: =P28/P25 -> 0 | Q32: =Q28/Q25 -> 0 | ... BP32: =BP28/BP25 -> 0.11265397 | CE32: "Black" package (microloan + 1000 installment card + debit card) | CF32: %
A33: Выдачи по займам | B33: млн тенге | D33: =SUM(D34:D36) -> 0 | E33: =SUM(E34:E36) -> 0 | F33: =SUM(F34:F36) -> 0 | G33: =SUM(G34:G36) -> 0 | H33: =SUM(H34:H36) -> 0 | I33: =SUM(I34:I36) -> 0 | J33: =SUM(J34:J36) -> 102.5079 | K33: =SUM(K34:K36) -> 208.98881 | ... O33: =SUM(O34:O36) -> 737.81951 | P33: =SUM(D33:O33) -> 2531.3915 | Q33: =SUM(Q34:Q36) -> 1409.2259 | R33: =SUM(R34:R36) -> 1734.9107 | S33: =SUM(S34:S36) -> 2095.8838 | T33: =SUM(T34:T36) -> 2471.1469 | U33: =SUM(U34:U36) -> 2860.2012 | V33: =SUM(V34:V36) -> 3262.5318 | W33: =SUM(W34:W36) -> 4551.8447 | X33: =SUM(X34:X36) -> 5077.8281 | ... AB33: =SUM(AB34:AB36) -> 7212.5494 | AC33: =SUM(Q33:AB33) -> 49189.7 | AD33: =SUM(AD34:AD36) -> 8677.6404 | AE33: =SUM(AE34:AE36) -> 8400.7967 | AF33: =SUM(AF34:AF36) -> 9010.2254 | AG33: =SUM(AG34:AG36) -> 9639.3099 | AH33: =SUM(AH34:AH36) -> 10287.115 | AI33: =SUM(AI34:AI36) -> 10952.692 | AJ33: =SUM(AJ34:AJ36) -> 11635.081 | AK33: =SUM(AK34:AK36) -> 12333.311 | ... AO33: =SUM(AO34:AO36) -> 15119.621 | AP33: =SUM(AD33:AO33) -> 137388.84 | AQ33: =SUM(AQ34:AQ36) -> 17468.652 | AR33: =SUM(AR34:AR36) -> 15532.462 | AS33: =SUM(AS34:AS36) -> 16050.364 | AT33: =SUM(AT34:AT36) -> 16587.57 | AU33: =SUM(AU34:AU36) -> 17143.127 | AV33: =SUM(AV34:AV36) -> 17716.071 | AW33: =SUM(AW34:AW36) -> 18305.437 | AX33: =SUM(AX34:AX36) -> 18910.254 | ... BB33: =SUM(BB34:BB36) -> 21291.566 | BC33: =SUM(AQ33:BB33) -> 219505.13 | BD33: =SUM(BD34:BD36) -> 25025.516 | BE33: =SUM(BE34:BE36) -> 21430.697 | BF33: =SUM(BF34:BF36) -> 21836.875 | BG33: =SUM(BG34:BG36) -> 22265.737 | BH33: =SUM(BH34:BH36) -> 22716.225 | BI33: =SUM(BI34:BI36) -> 23187.278 | BJ33: =SUM(BJ34:BJ36) -> 23677.836 | BK33: =SUM(BK34:BK36) -> 24186.837 | ... BO33: =SUM(BO34:BO36) -> 26176.974 | BP33: =SUM(BD33:BO33) -> 286287.11 | CE33: Volume of loans issued | CF33: mln tenge
A34: микрозайм 30 | B34: млн тенге | D34: ='Micro_30 (indiv)'!D26 -> 0 | E34: ='Micro_30 (indiv)'!E26 -> 0 | F34: ='Micro_30 (indiv)'!F26 -> 0 | G34: ='Micro_30 (indiv)'!G26 -> 0 | H34: ='Micro_30 (indiv)'!H26 -> 0 | I34: ='Micro_30 (indiv)'!I26 -> 0 | J34: ='Micro_30 (indiv)'!J26 -> 102.5079 | K34: ='Micro_30 (indiv)'!K26 -> 208.98881 | ... O34: ='Micro_30 (indiv)'!O26 -> 667.08383 | P34: =SUM(D34:O34) -> 2282.2954 | Q34: ='Micro_30 (indiv)'!Q26 -> 943.54049 | R34: ='Micro_30 (indiv)'!R26 -> 1234.0139 | S34: ='Micro_30 (indiv)'!S26 -> 1538.1154 | T34: ='Micro_30 (indiv)'!T26 -> 1855.4387 | U34: ='Micro_30 (indiv)'!U26 -> 2185.5608 | V34: ='Micro_30 (indiv)'!V26 -> 2528.0426 | W34: ='Micro_30 (indiv)'!W26 -> 2882.4306 | X34: ='Micro_30 (indiv)'!X26 -> 3248.2572 | ... AB34: ='Micro_30 (indiv)'!AB26 -> 4797.5341 | AC34: =SUM(Q34:AB34) -> 33259.778 | AD34: ='Micro_30 (indiv)'!AD26 -> 5166.006 | AE34: ='Micro_30 (indiv)'!AE26 -> 5552.2749 | AF34: ='Micro_30 (indiv)'!AF26 -> 5955.7231 | AG34: ='Micro_30 (indiv)'!AG26 -> 6375.7154 | AH34: ='Micro_30 (indiv)'!AH26 -> 6811.6 | AI34: ='Micro_30 (indiv)'!AI26 -> 7262.7107 | AJ34: ='Micro_30 (indiv)'!AJ26 -> 7728.3679 | AK34: ='Micro_30 (indiv)'!AK26 -> 8207.8805 | ... AO34: ='Micro_30 (indiv)'!AO26 -> 10221.771 | AP34: =SUM(AD34:AO34) -> 90910.754 | AQ34: ='Micro_30 (indiv)'!AQ26 -> 10512.915 | AR34: ='Micro_30 (indiv)'!AR26 -> 10821.625 | AS34: ='Micro_30 (indiv)'!AS26 -> 11147.26 | AT34: ='Micro_30 (indiv)'!AT26 -> 11489.163 | AU34: ='Micro_30 (indiv)'!AU26 -> 11846.668 | AV34: ='Micro_30 (indiv)'!AV26 -> 12219.097 | AW34: ='Micro_30 (indiv)'!AW26 -> 12605.764 | AX34: ='Micro_30 (indiv)'!AX26 -> 13005.977 | ... BB34: ='Micro_30 (indiv)'!BB26 -> 14696.082 | BC34: =SUM(AQ34:BB34) -> 149888.72 | BD34: ='Micro_30 (indiv)'!BD26 -> 14883.387 | BE34: ='Micro_30 (indiv)'!BE26 -> 15090.975 | BF34: ='Micro_30 (indiv)'!BF26 -> 15318.13 | BG34: ='Micro_30 (indiv)'!BG26 -> 15564.126 | BH34: ='Micro_30 (indiv)'!BH26 -> 15828.228 | BI34: ='Micro_30 (indiv)'!BI26 -> 16109.692 | BJ34: ='Micro_30 (indiv)'!BJ26 -> 16407.767 | BK34: ='Micro_30 (indiv)'!BK26 -> 16721.699 | ... BO34: ='Micro_30 (indiv)'!BO26 -> 18084.035 | BP34: =SUM(BD34:BO34) -> 196203.91 | CE34: microloan 30 | CF34: mln tenge
A35: карта рассрочки 150 | B35: млн тенге | D35: ='Installment card_150 (indiv)'!D52 -> 0 | E35: ='Installment card_150 (indiv)'!E52 -> 0 | F35: ='Installment card_150 (indiv)'!F52 -> 0 | G35: ='Installment card_150 (indiv)'!G52 -> 0 | H35: ='Installment card_150 (indiv)'!H52 -> 0 | I35: ='Installment card_150 (indiv)'!I52 -> 0 | J35: ='Installment card_150 (indiv)'!J52 -> 0 | K35: ='Installment card_150 (indiv)'!K52 -> 0 | ... O35: ='Installment card_150 (indiv)'!O52 -> 70.735677 | P35: =SUM(D35:O35) -> 249.09613 | Q35: ='Installment card_150 (indiv)'!Q52 -> 465.68546 | R35: ='Installment card_150 (indiv)'!R52 -> 500.89685 | S35: ='Installment card_150 (indiv)'!S52 -> 557.76847 | T35: ='Installment card_150 (indiv)'!T52 -> 615.70817 | U35: ='Installment card_150 (indiv)'!U52 -> 674.64043 | V35: ='Installment card_150 (indiv)'!V52 -> 734.48913 | W35: ='Installment card_150 (indiv)'!W52 -> 795.1777 | X35: ='Installment card_150 (indiv)'!X52 -> 856.62931 | ... AB35: ='Installment card_150 (indiv)'!AB52 -> 1080.197 | AC35: =SUM(Q35:AB35) -> 9226.2672 | AD35: ='Installment card_150 (indiv)'!AD52 -> 1816.4168 | AE35: ='Installment card_150 (indiv)'!AE52 -> 1288.8731 | AF35: ='Installment card_150 (indiv)'!AF52 -> 1370.4909 | AG35: ='Installment card_150 (indiv)'!AG52 -> 1453.3674 | AH35: ='Installment card_150 (indiv)'!AH52 -> 1537.3897 | AI35: ='Installment card_150 (indiv)'!AI52 -> 1622.4454 | AJ35: ='Installment card_150 (indiv)'!AJ52 -> 1708.4226 | AK35: ='Installment card_150 (indiv)'!AK52 -> 1795.2103 | ... AO35: ='Installment card_150 (indiv)'!AO52 -> 2100.5211 | AP35: =SUM(AD35:AO35) -> 20605.956 | AQ35: ='Installment card_150 (indiv)'!AQ52 -> 3517.3047 | AR35: ='Installment card_150 (indiv)'!AR52 -> 2079.4568 | AS35: ='Installment card_150 (indiv)'!AS52 -> 2157.4659 | AT35: ='Installment card_150 (indiv)'!AT52 -> 2236.771 | AU35: ='Installment card_150 (indiv)'!AU52 -> 2317.2539 | AV35: ='Installment card_150 (indiv)'!AV52 -> 2398.7973 | AW35: ='Installment card_150 (indiv)'!AW52 -> 2481.2854 | AX35: ='Installment card_150 (indiv)'!AX52 -> 2564.6039 | ... BB35: ='Installment card_150 (indiv)'!BB52 -> 2844.7762 | BC35: =SUM(AQ35:BB35) -> 30798.067 | BD35: ='Installment card_150 (indiv)'!BD52 -> 5174.05 | BE35: ='Installment card_150 (indiv)'!BE52 -> 2810.0103 | BF35: ='Installment card_150 (indiv)'!BF52 -> 2884.6915 | BG35: ='Installment card_150 (indiv)'!BG52 -> 2961.0761 | BH35: ='Installment card_150 (indiv)'!BH52 -> 3039.0269 | BI35: ='Installment card_150 (indiv)'!BI52 -> 3118.4084 | BJ35: ='Installment card_150 (indiv)'!BJ52 -> 3199.0873 | BK35: ='Installment card_150 (indiv)'!BK52 -> 3280.9327 | ... BO35: ='Installment card_150 (indiv)'!BO52 -> 3543.0436 | BP35: =SUM(BD35:BO35) -> 40353.953 | CE35: Installment card 150 | CF35: mln tenge
A36: карта рассрочки 1000 | B36: млн тенге | D36: ='Installment card_1000 (indiv)'!D52 -> 0 | E36: ='Installment card_1000 (indiv)'!E52 -> 0 | F36: ='Installment card_1000 (indiv)'!F52 -> 0 | G36: ='Installment card_1000 (indiv)'!G52 -> 0 | H36: ='Installment card_1000 (indiv)'!H52 -> 0 | I36: ='Installment card_1000 (indiv)'!I52 -> 0 | J36: ='Installment card_1000 (indiv)'!J52 -> 0 | K36: ='Installment card_1000 (indiv)'!K52 -> 0 | ... O36: ='Installment card_1000 (indiv)'!O52 -> 0 | P36: =SUM(D36:O36) -> 0 | Q36: ='Installment card_1000 (indiv)'!Q52 -> 0 | R36: ='Installment card_1000 (indiv)'!R52 -> 0 | S36: ='Installment card_1000 (indiv)'!S52 -> 0 | T36: ='Installment card_1000 (indiv)'!T52 -> 0 | U36: ='Installment card_1000 (indiv)'!U52 -> 0 | V36: ='Installment card_1000 (indiv)'!V52 -> 0 | W36: ='Installment card_1000 (indiv)'!W52 -> 874.23642 | X36: ='Installment card_1000 (indiv)'!X52 -> 972.94166 | ... AB36: ='Installment card_1000 (indiv)'!AB52 -> 1334.8184 | AC36: =SUM(Q36:AB36) -> 6703.6544 | AD36: ='Installment card_1000 (indiv)'!AD52 -> 1695.2176 | AE36: ='Installment card_1000 (indiv)'!AE52 -> 1559.6487 | AF36: ='Installment card_1000 (indiv)'!AF52 -> 1684.0113 | AG36: ='Installment card_1000 (indiv)'!AG52 -> 1810.2271 | AH36: ='Installment card_1000 (indiv)'!AH52 -> 1938.1253 | AI36: ='Installment card_1000 (indiv)'!AI52 -> 2067.5361 | AJ36: ='Installment card_1000 (indiv)'!AJ52 -> 2198.2905 | AK36: ='Installment card_1000 (indiv)'!AK52 -> 2330.2206 | ... AO36: ='Installment card_1000 (indiv)'!AO52 -> 2797.3285 | AP36: =SUM(AD36:AO36) -> 25872.126 | AQ36: ='Installment card_1000 (indiv)'!AQ52 -> 3438.4331 | AR36: ='Installment card_1000 (indiv)'!AR52 -> 2631.3804 | AS36: ='Installment card_1000 (indiv)'!AS52 -> 2745.6385 | AT36: ='Installment card_1000 (indiv)'!AT52 -> 2861.6364 | AU36: ='Installment card_1000 (indiv)'!AU52 -> 2979.205 | AV36: ='Installment card_1000 (indiv)'!AV52 -> 3098.1771 | AW36: ='Installment card_1000 (indiv)'!AW52 -> 3218.3874 | AX36: ='Installment card_1000 (indiv)'!AX52 -> 3339.6732 | ... BB36: ='Installment card_1000 (indiv)'!BB52 -> 3750.7071 | BC36: =SUM(AQ36:BB36) -> 38818.347 | BD36: ='Installment card_1000 (indiv)'!BD52 -> 4968.078 | BE36: ='Installment card_1000 (indiv)'!BE52 -> 3529.7117 | BF36: ='Installment card_1000 (indiv)'!BF52 -> 3634.0544 | BG36: ='Installment card_1000 (indiv)'!BG52 -> 3740.5351 | BH36: ='Installment card_1000 (indiv)'!BH52 -> 3848.97 | BI36: ='Installment card_1000 (indiv)'!BI52 -> 3959.1782 | BJ36: ='Installment card_1000 (indiv)'!BJ52 -> 4070.9818 | BK36: ='Installment card_1000 (indiv)'!BK52 -> 4184.2062 | ... BO36: ='Installment card_1000 (indiv)'!BO52 -> 4549.8949 | BP36: =SUM(BD36:BO36) -> 49729.241 | CE36: Installment card 1000 | CF36: mln tenge
A37: Погашения по займам | B37: млн тенге | D37: =SUM(D38:D40) -> 0 | E37: =SUM(E38:E40) -> 0 | F37: =SUM(F38:F40) -> 0 | G37: =SUM(G38:G40) -> 0 | H37: =SUM(H38:H40) -> 0 | I37: =SUM(I38:I40) -> 0 | J37: =SUM(J38:J40) -> -96.101161 | K37: =SUM(K38:K40) -> -202.33375 | ... O37: =SUM(O38:O40) -> -673.08284 | P37: =SUM(D37:O37) -> -2266.6635 | Q37: =SUM(Q38:Q40) -> -944.12335 | R37: =SUM(R38:R40) -> -1269.59 | S37: =SUM(S38:S40) -> -1608.6644 | T37: =SUM(T38:T40) -> -1962.6802 | U37: =SUM(U38:U40) -> -2331.1658 | V37: =SUM(V38:V40) -> -2713.6314 | W37: =SUM(W38:W40) -> -3109.5707 | X37: =SUM(X38:X40) -> -3588.5285 | ... AB37: =SUM(AB38:AB40) -> -5627.6264 | AC37: =SUM(Q37:AB37) -> -36938.937 | AD37: =SUM(AD38:AD40) -> -6122.5694 | AE37: =SUM(AE38:AE40) -> -6710.9078 | AF37: =SUM(AF38:AF40) -> -7247.0246 | AG37: =SUM(AG38:AG40) -> -7805.55 | AH37: =SUM(AH38:AH40) -> -8385.6178 | AI37: =SUM(AI38:AI40) -> -8986.3412 | AJ37: =SUM(AJ38:AJ40) -> -9606.8153 | AK37: =SUM(AK38:AK40) -> -10246.119 | ... AO37: =SUM(AO38:AO40) -> -12945.971 | AP37: =SUM(AD37:AO37) -> -112805.29 | AQ37: =SUM(AQ38:AQ40) -> -13422.47 | AR37: =SUM(AR38:AR40) -> -14053.895 | AS37: =SUM(AS38:AS40) -> -14496.044 | AT37: =SUM(AT38:AT40) -> -14960.528 | AU37: =SUM(AU38:AU40) -> -15446.444 | AV37: =SUM(AV38:AV40) -> -15952.872 | AW37: =SUM(AW38:AW40) -> -16478.882 | AX37: =SUM(AX38:AX40) -> -17023.532 | ... BB37: =SUM(BB38:BB40) -> -19339.302 | BC37: =SUM(AQ37:BB37) -> -195684.6 | BD37: =SUM(BD38:BD40) -> -19696.266 | BE37: =SUM(BE38:BE40) -> -20330.751 | BF37: =SUM(BF38:BF40) -> -20644.693 | BG37: =SUM(BG38:BG40) -> -20984.863 | BH37: =SUM(BH38:BH40) -> -21350.246 | BI37: =SUM(BI38:BI40) -> -21739.816 | BJ37: =SUM(BJ38:BJ40) -> -22152.538 | BK37: =SUM(BK38:BK40) -> -22587.369 | ... BO37: =SUM(BO38:BO40) -> -24492.342 | BP37: =SUM(BD37:BO37) -> -264555.36 | CE37: Volume of loan repayments | CF37: mln tenge
A38: микрозайм 30 | B38: млн тенге | D38: ='Micro_30 (indiv)'!D27 -> 0 | E38: ='Micro_30 (indiv)'!E27 -> 0 | F38: ='Micro_30 (indiv)'!F27 -> 0 | G38: ='Micro_30 (indiv)'!G27 -> 0 | H38: ='Micro_30 (indiv)'!H27 -> 0 | I38: ='Micro_30 (indiv)'!I27 -> 0 | J38: ='Micro_30 (indiv)'!J27 -> -96.101161 | K38: ='Micro_30 (indiv)'!K27 -> -202.33375 | ... O38: ='Micro_30 (indiv)'!O27 -> -659.82982 | P38: =SUM(D38:O38) -> -2240.6026 | Q38: ='Micro_30 (indiv)'!Q27 -> -926.26195 | R38: ='Micro_30 (indiv)'!R27 -> -1215.8593 | S38: ='Micro_30 (indiv)'!S27 -> -1519.109 | T38: ='Micro_30 (indiv)'!T27 -> -1835.606 | U38: ='Micro_30 (indiv)'!U27 -> -2164.9281 | V38: ='Micro_30 (indiv)'!V27 -> -2506.6375 | W38: ='Micro_30 (indiv)'!W27 -> -2860.2813 | X38: ='Micro_30 (indiv)'!X27 -> -3225.393 | ... AB38: ='Micro_30 (indiv)'!AB27 -> -4773.2825 | AC38: =SUM(Q38:AB38) -> -33001.625 | AD38: ='Micro_30 (indiv)'!AD27 -> -5142.9765 | AE38: ='Micro_30 (indiv)'!AE27 -> -5528.1331 | AF38: ='Micro_30 (indiv)'!AF27 -> -5930.5076 | AG38: ='Micro_30 (indiv)'!AG27 -> -6349.4659 | AH38: ='Micro_30 (indiv)'!AH27 -> -6784.3572 | AI38: ='Micro_30 (indiv)'!AI27 -> -7234.5162 | AJ38: ='Micro_30 (indiv)'!AJ27 -> -7699.2643 | AK38: ='Micro_30 (indiv)'!AK27 -> -8177.911 | ... AO38: ='Micro_30 (indiv)'!AO27 -> -10190.567 | AP38: =SUM(AD38:AO38) -> -90571.739 | AQ38: ='Micro_30 (indiv)'!AQ27 -> -10494.718 | AR38: ='Micro_30 (indiv)'!AR27 -> -10802.331 | AS38: ='Micro_30 (indiv)'!AS27 -> -11126.907 | AT38: ='Micro_30 (indiv)'!AT27 -> -11467.794 | AU38: ='Micro_30 (indiv)'!AU27 -> -11824.324 | AV38: ='Micro_30 (indiv)'!AV27 -> -12195.82 | AW38: ='Micro_30 (indiv)'!AW27 -> -12581.597 | AX38: ='Micro_30 (indiv)'!AX27 -> -12980.964 | ... BB38: ='Micro_30 (indiv)'!BB27 -> -14670.133 | BC38: =SUM(AQ38:BB38) -> -149609.07 | BD38: ='Micro_30 (indiv)'!BD27 -> -14871.681 | BE38: ='Micro_30 (indiv)'!BE27 -> -15078.001 | BF38: ='Micro_30 (indiv)'!BF27 -> -15303.932 | BG38: ='Micro_30 (indiv)'!BG27 -> -15548.751 | BH38: ='Micro_30 (indiv)'!BH27 -> -15811.722 | BI38: ='Micro_30 (indiv)'!BI27 -> -16092.1 | BJ38: ='Micro_30 (indiv)'!BJ27 -> -16389.137 | BK38: ='Micro_30 (indiv)'!BK27 -> -16702.078 | ... BO38: ='Micro_30 (indiv)'!BO27 -> -18063.224 | BP38: =SUM(BD38:BO38) -> -195992.17 | CE38: microloan 30 | CF38: mln tenge
A39: карта рассрочки 150 | B39: млн тенге | D39: ='Installment card_150 (indiv)'!D59 -> 0 | E39: ='Installment card_150 (indiv)'!E59 -> 0 | F39: ='Installment card_150 (indiv)'!F59 -> 0 | G39: ='Installment card_150 (indiv)'!G59 -> 0 | H39: ='Installment card_150 (indiv)'!H59 -> 0 | I39: ='Installment card_150 (indiv)'!I59 -> 0 | J39: ='Installment card_150 (indiv)'!J59 -> 0 | K39: ='Installment card_150 (indiv)'!K59 -> 0 | ... O39: ='Installment card_150 (indiv)'!O59 -> -13.253019 | P39: =SUM(D39:O39) -> -26.060913 | Q39: ='Installment card_150 (indiv)'!Q59 -> -17.861404 | R39: ='Installment card_150 (indiv)'!R59 -> -53.730703 | S39: ='Installment card_150 (indiv)'!S59 -> -89.555389 | T39: ='Installment card_150 (indiv)'!T59 -> -127.07423 | U39: ='Installment card_150 (indiv)'!U59 -> -166.23763 | V39: ='Installment card_150 (indiv)'!V59 -> -206.9939 | W39: ='Installment card_150 (indiv)'!W59 -> -249.28937 | X39: ='Installment card_150 (indiv)'!X59 -> -293.06851 | ... AB39: ='Installment card_150 (indiv)'!AB59 -> -481.85322 | AC39: =SUM(Q39:AB39) -> -2841.5129 | AD39: ='Installment card_150 (indiv)'!AD59 -> -529.88966 | AE39: ='Installment card_150 (indiv)'!AE59 -> -633.12968 | AF39: ='Installment card_150 (indiv)'!AF59 -> -685.79794 | AG39: ='Installment card_150 (indiv)'!AG59 -> -740.80035 | AH39: ='Installment card_150 (indiv)'!AH59 -> -798.05139 | AI39: ='Installment card_150 (indiv)'!AI59 -> -857.46334 | AJ39: ='Installment card_150 (indiv)'!AJ59 -> -918.94644 | AK39: ='Installment card_150 (indiv)'!AK59 -> -982.40913 | ... AO39: ='Installment card_150 (indiv)'!AO59 -> -1254.1725 | AP39: =SUM(AD39:AO39) -> -10747.054 | AQ39: ='Installment card_150 (indiv)'!AQ59 -> -1322.2753 | AR39: ='Installment card_150 (indiv)'!AR59 -> -1498.7047 | AS39: ='Installment card_150 (indiv)'!AS59 -> -1545.518 | AT39: ='Installment card_150 (indiv)'!AT59 -> -1594.8477 | AU39: ='Installment card_150 (indiv)'!AU59 -> -1646.5966 | AV39: ='Installment card_150 (indiv)'!AV59 -> -1700.6657 | AW39: ='Installment card_150 (indiv)'!AW59 -> -1756.9545 | AX39: ='Installment card_150 (indiv)'!AX59 -> -1815.3615 | ... BB39: ='Installment card_150 (indiv)'!BB59 -> -2068.1032 | BC39: =SUM(AQ39:BB39) -> -20765.187 | BD39: ='Installment card_150 (indiv)'!BD59 -> -2130.7864 | BE39: ='Installment card_150 (indiv)'!BE59 -> -2375.7568 | BF39: ='Installment card_150 (indiv)'!BF59 -> -2410.949 | BG39: ='Installment card_150 (indiv)'!BG59 -> -2449.3253 | BH39: ='Installment card_150 (indiv)'!BH59 -> -2490.7677 | BI39: ='Installment card_150 (indiv)'!BI59 -> -2535.1566 | BJ39: ='Installment card_150 (indiv)'!BJ59 -> -2582.371 | BK39: ='Installment card_150 (indiv)'!BK59 -> -2632.2888 | ... BO39: ='Installment card_150 (indiv)'!BO59 -> -2856.533 | BP39: =SUM(BD39:BO39) -> -30685.498 | CE39: Installment card 150 | CF39: mln tenge
A40: карта рассрочки 1000 | B40: млн тенге | D40: ='Installment card_1000 (indiv)'!D59 -> 0 | E40: ='Installment card_1000 (indiv)'!E59 -> 0 | F40: ='Installment card_1000 (indiv)'!F59 -> 0 | G40: ='Installment card_1000 (indiv)'!G59 -> 0 | H40: ='Installment card_1000 (indiv)'!H59 -> 0 | I40: ='Installment card_1000 (indiv)'!I59 -> 0 | J40: ='Installment card_1000 (indiv)'!J59 -> 0 | K40: ='Installment card_1000 (indiv)'!K59 -> 0 | ... O40: ='Installment card_1000 (indiv)'!O59 -> 0 | P40: =SUM(D40:O40) -> 0 | Q40: ='Installment card_1000 (indiv)'!Q59 -> 0 | R40: ='Installment card_1000 (indiv)'!R59 -> 0 | S40: ='Installment card_1000 (indiv)'!S59 -> 0 | T40: ='Installment card_1000 (indiv)'!T59 -> 0 | U40: ='Installment card_1000 (indiv)'!U59 -> 0 | V40: ='Installment card_1000 (indiv)'!V59 -> 0 | W40: ='Installment card_1000 (indiv)'!W59 -> 0 | X40: ='Installment card_1000 (indiv)'!X59 -> -70.067013 | ... AB40: ='Installment card_1000 (indiv)'!AB59 -> -372.4907 | AC40: =SUM(Q40:AB40) -> -1095.7986 | AD40: ='Installment card_1000 (indiv)'!AD59 -> -449.7033 | AE40: ='Installment card_1000 (indiv)'!AE59 -> -549.64504 | AF40: ='Installment card_1000 (indiv)'!AF59 -> -630.71902 | AG40: ='Installment card_1000 (indiv)'!AG59 -> -715.2838 | AH40: ='Installment card_1000 (indiv)'!AH59 -> -803.20916 | AI40: ='Installment card_1000 (indiv)'!AI59 -> -894.36159 | AJ40: ='Installment card_1000 (indiv)'!AJ59 -> -988.60459 | AK40: ='Installment card_1000 (indiv)'!AK59 -> -1085.799 | ... AO40: ='Installment card_1000 (indiv)'!AO59 -> -1501.2313 | AP40: =SUM(AD40:AO40) -> -11486.499 | AQ40: ='Installment card_1000 (indiv)'!AQ59 -> -1605.4767 | AR40: ='Installment card_1000 (indiv)'!AR59 -> -1752.8601 | AS40: ='Installment card_1000 (indiv)'!AS59 -> -1823.6182 | AT40: ='Installment card_1000 (indiv)'!AT59 -> -1897.8864 | AU40: ='Installment card_1000 (indiv)'!AU59 -> -1975.5236 | AV40: ='Installment card_1000 (indiv)'!AV59 -> -2056.3865 | AW40: ='Installment card_1000 (indiv)'!AW59 -> -2140.3298 | AX40: ='Installment card_1000 (indiv)'!AX59 -> -2227.2064 | ... BB40: ='Installment card_1000 (indiv)'!BB59 -> -2601.0665 | BC40: =SUM(AQ40:BB40) -> -25310.336 | BD40: ='Installment card_1000 (indiv)'!BD59 -> -2693.7993 | BE40: ='Installment card_1000 (indiv)'!BE59 -> -2876.9932 | BF40: ='Installment card_1000 (indiv)'!BF59 -> -2929.812 | BG40: ='Installment card_1000 (indiv)'!BG59 -> -2986.7869 | BH40: ='Installment card_1000 (indiv)'!BH59 -> -3047.7569 | BI40: ='Installment card_1000 (indiv)'!BI59 -> -3112.5594 | BJ40: ='Installment card_1000 (indiv)'!BJ59 -> -3181.0297 | BK40: ='Installment card_1000 (indiv)'!BK59 -> -3253.0024 | ... BO40: ='Installment card_1000 (indiv)'!BO59 -> -3572.5853 | BP40: =SUM(BD40:BO40) -> -37877.695 | CE40: Installment card 1000 | CF40: mln tenge
A41: Кредитный портфель | B41: млн тенге | C41: 0 | D41: =SUM(D42:D44) -> 0 | E41: =SUM(E42:E44) -> 0 | F41: =SUM(F42:F44) -> 0 | G41: =SUM(G42:G44) -> 0 | H41: =SUM(H42:H44) -> 0 | I41: =SUM(I42:I44) -> 0 | J41: =SUM(J42:J44) -> 6.406744 | K41: =SUM(K42:K44) -> 13.061801 | ... BP41: =SUM(BP42:BP44) -> 82651.318 | CE41: Loan portfolio | CF41: mln tenge
A42: микрозайм 30 | B42: млн тенге | C42: 0 | D42: ='Micro_30 (indiv)'!D24 -> 0 | E42: ='Micro_30 (indiv)'!E24 -> 0 | F42: ='Micro_30 (indiv)'!F24 -> 0 | G42: ='Micro_30 (indiv)'!G24 -> 0 | H42: ='Micro_30 (indiv)'!H24 -> 0 | I42: ='Micro_30 (indiv)'!I24 -> 0 | J42: ='Micro_30 (indiv)'!J24 -> 6.406744 | K42: ='Micro_30 (indiv)'!K24 -> 13.061801 | ... O42: ='Micro_30 (indiv)'!O24 -> 41.69274 | P42: =O42 -> 41.69274 | Q42: ='Micro_30 (indiv)'!Q24 -> 58.971281 | R42: ='Micro_30 (indiv)'!R24 -> 77.125867 | S42: ='Micro_30 (indiv)'!S24 -> 96.132211 | T42: ='Micro_30 (indiv)'!T24 -> 115.96492 | U42: ='Micro_30 (indiv)'!U24 -> 136.59755 | V42: ='Micro_30 (indiv)'!V24 -> 158.00266 | W42: ='Micro_30 (indiv)'!W24 -> 180.15191 | X42: ='Micro_30 (indiv)'!X24 -> 203.01607 | ... AB42: ='Micro_30 (indiv)'!AB24 -> 299.84588 | AC42: =AB42 -> 299.84588 | AD42: ='Micro_30 (indiv)'!AD24 -> 322.87537 | AE42: ='Micro_30 (indiv)'!AE24 -> 347.01718 | AF42: ='Micro_30 (indiv)'!AF24 -> 372.2327 | AG42: ='Micro_30 (indiv)'!AG24 -> 398.48221 | AH42: ='Micro_30 (indiv)'!AH24 -> 425.725 | AI42: ='Micro_30 (indiv)'!AI24 -> 453.91942 | AJ42: ='Micro_30 (indiv)'!AJ24 -> 483.02299 | AK42: ='Micro_30 (indiv)'!AK24 -> 512.99253 | ... AO42: ='Micro_30 (indiv)'!AO24 -> 638.86071 | AP42: =AO42 -> 638.86071 | AQ42: ='Micro_30 (indiv)'!AQ24 -> 657.05717 | AR42: ='Micro_30 (indiv)'!AR24 -> 676.35156 | AS42: ='Micro_30 (indiv)'!AS24 -> 696.70373 | AT42: ='Micro_30 (indiv)'!AT24 -> 718.07269 | AU42: ='Micro_30 (indiv)'!AU24 -> 740.41674 | AV42: ='Micro_30 (indiv)'!AV24 -> 763.69356 | AW42: ='Micro_30 (indiv)'!AW24 -> 787.86026 | AX42: ='Micro_30 (indiv)'!AX24 -> 812.87356 | ... BB42: ='Micro_30 (indiv)'!BB24 -> 918.50515 | BC42: =BB42 -> 918.50515 | BD42: ='Micro_30 (indiv)'!BD24 -> 930.21171 | BE42: ='Micro_30 (indiv)'!BE24 -> 943.18592 | BF42: ='Micro_30 (indiv)'!BF24 -> 957.3831 | BG42: ='Micro_30 (indiv)'!BG24 -> 972.75788 | BH42: ='Micro_30 (indiv)'!BH24 -> 989.26425 | BI42: ='Micro_30 (indiv)'!BI24 -> 1006.8557 | BJ42: ='Micro_30 (indiv)'!BJ24 -> 1025.4854 | BK42: ='Micro_30 (indiv)'!BK24 -> 1045.1062 | ... BO42: ='Micro_30 (indiv)'!BO24 -> 1130.2522 | BP42: =BO42 -> 1130.2522 | BR42: =F42/500*1000 -> 0 | BS42: =I42/500*1000 -> 0 | BT42: =L42/500*1000 -> 39.915043 | BU42: =O42/500*1000 -> 83.385479 | BV42: =V42/500*1000 -> 316.00533 | BW42: =AB42/500*1000 -> 599.69176 | BX42: =AI42/500*1000 -> 907.83883 | BY42: =AO42/500*1000 -> 1277.7214 | BZ42: =AV42/500*1000 -> 1527.3871 | CA42: =BB42/500*1000 -> 1837.0103 | CB42: =BI42/500*1000 -> 2013.7115 | CC42: =BO42/500*1000 -> 2260.5044 | CE42: microloan 30 | CF42: mln tenge
A43: карта рассрочки 150 | B43: млн тенге | C43: 0 | D43: ='Installment card_150 (indiv)'!D36 -> 0 | E43: ='Installment card_150 (indiv)'!E36 -> 0 | F43: ='Installment card_150 (indiv)'!F36 -> 0 | G43: ='Installment card_150 (indiv)'!G36 -> 0 | H43: ='Installment card_150 (indiv)'!H36 -> 0 | I43: ='Installment card_150 (indiv)'!I36 -> 0 | J43: ='Installment card_150 (indiv)'!J36 -> 0 | K43: ='Installment card_150 (indiv)'!K36 -> 0 | ... O43: ='Installment card_150 (indiv)'!O36 -> 223.03522 | P43: =O43 -> 223.03522 | Q43: ='Installment card_150 (indiv)'!Q36 -> 670.85927 | R43: ='Installment card_150 (indiv)'!R36 -> 1118.0254 | S43: ='Installment card_150 (indiv)'!S36 -> 1586.2385 | T43: ='Installment card_150 (indiv)'!T36 -> 2074.8724 | U43: ='Installment card_150 (indiv)'!U36 -> 2583.2752 | V43: ='Installment card_150 (indiv)'!V36 -> 3110.7705 | W43: ='Installment card_150 (indiv)'!W36 -> 3656.6588 | X43: ='Installment card_150 (indiv)'!X36 -> 4220.2196 | ... AB43: ='Installment card_150 (indiv)'!AB36 -> 6607.7895 | AC43: =AB43 -> 6607.7895 | AD43: ='Installment card_150 (indiv)'!AD36 -> 7894.3166 | AE43: ='Installment card_150 (indiv)'!AE36 -> 8550.0601 | AF43: ='Installment card_150 (indiv)'!AF36 -> 9234.7531 | AG43: ='Installment card_150 (indiv)'!AG36 -> 9947.3201 | AH43: ='Installment card_150 (indiv)'!AH36 -> 10686.658 | AI43: ='Installment card_150 (indiv)'!AI36 -> 11451.641 | AJ43: ='Installment card_150 (indiv)'!AJ36 -> 12241.117 | AK43: ='Installment card_150 (indiv)'!AK36 -> 13053.918 | ... AO43: ='Installment card_150 (indiv)'!AO36 -> 16466.691 | AP43: =AO43 -> 16466.691 | AQ43: ='Installment card_150 (indiv)'!AQ36 -> 18661.721 | AR43: ='Installment card_150 (indiv)'!AR36 -> 19242.473 | AS43: ='Installment card_150 (indiv)'!AS36 -> 19854.421 | AT43: ='Installment card_150 (indiv)'!AT36 -> 20496.344 | AU43: ='Installment card_150 (indiv)'!AU36 -> 21167.001 | AV43: ='Installment card_150 (indiv)'!AV36 -> 21865.133 | AW43: ='Installment card_150 (indiv)'!AW36 -> 22589.464 | AX43: ='Installment card_150 (indiv)'!AX36 -> 23338.706 | ... BB43: ='Installment card_150 (indiv)'!BB36 -> 26499.572 | BC43: =BB43 -> 26499.572 | BD43: ='Installment card_150 (indiv)'!BD36 -> 29542.835 | BE43: ='Installment card_150 (indiv)'!BE36 -> 29977.089 | BF43: ='Installment card_150 (indiv)'!BF36 -> 30450.831 | BG43: ='Installment card_150 (indiv)'!BG36 -> 30962.582 | BH43: ='Installment card_150 (indiv)'!BH36 -> 31510.841 | BI43: ='Installment card_150 (indiv)'!BI36 -> 32094.093 | BJ43: ='Installment card_150 (indiv)'!BJ36 -> 32710.809 | BK43: ='Installment card_150 (indiv)'!BK36 -> 33359.453 | ... BO43: ='Installment card_150 (indiv)'!BO36 -> 36168.026 | BP43: =BO43 -> 36168.026 | BR43: =F43/500*1000 -> 0 | BS43: =I43/500*1000 -> 0 | BT43: =L43/500*1000 -> 104.86487 | BU43: =O43/500*1000 -> 446.07043 | BV43: =V43/500*1000 -> 6221.541 | BW43: =AB43/500*1000 -> 13215.579 | BX43: =AI43/500*1000 -> 22903.281 | BY43: =AO43/500*1000 -> 32933.383 | BZ43: =AV43/500*1000 -> 43730.266 | CA43: =BB43/500*1000 -> 52999.143 | CB43: =BI43/500*1000 -> 64188.186 | CC43: =BO43/500*1000 -> 72336.052 | CE43: Installment card 150 | CF43: mln tenge
A44: карта рассрочки 1000 | B44: млн тенге | C44: 0 | D44: ='Installment card_1000 (indiv)'!D36 -> 0 | E44: ='Installment card_1000 (indiv)'!E36 -> 0 | F44: ='Installment card_1000 (indiv)'!F36 -> 0 | G44: ='Installment card_1000 (indiv)'!G36 -> 0 | H44: ='Installment card_1000 (indiv)'!H36 -> 0 | I44: ='Installment card_1000 (indiv)'!I36 -> 0 | J44: ='Installment card_1000 (indiv)'!J36 -> 0 | K44: ='Installment card_1000 (indiv)'!K36 -> 0 | ... O44: ='Installment card_1000 (indiv)'!O36 -> 0 | P44: =O44 -> 0 | Q44: ='Installment card_1000 (indiv)'!Q36 -> 0 | R44: ='Installment card_1000 (indiv)'!R36 -> 0 | S44: ='Installment card_1000 (indiv)'!S36 -> 0 | T44: ='Installment card_1000 (indiv)'!T36 -> 0 | U44: ='Installment card_1000 (indiv)'!U36 -> 0 | V44: ='Installment card_1000 (indiv)'!V36 -> 0 | W44: ='Installment card_1000 (indiv)'!W36 -> 874.23642 | X44: ='Installment card_1000 (indiv)'!X36 -> 1777.1111 | ... AB44: ='Installment card_1000 (indiv)'!AB36 -> 5607.8558 | AC44: =AB44 -> 5607.8558 | AD44: ='Installment card_1000 (indiv)'!AD36 -> 6853.3701 | AE44: ='Installment card_1000 (indiv)'!AE36 -> 7863.3737 | AF44: ='Installment card_1000 (indiv)'!AF36 -> 8916.666 | AG44: ='Installment card_1000 (indiv)'!AG36 -> 10011.609 | AH44: ='Installment card_1000 (indiv)'!AH36 -> 11146.525 | AI44: ='Installment card_1000 (indiv)'!AI36 -> 12319.7 | AJ44: ='Installment card_1000 (indiv)'!AJ36 -> 13529.386 | AK44: ='Installment card_1000 (indiv)'!AK36 -> 14773.807 | ... AO44: ='Installment card_1000 (indiv)'!AO36 -> 19993.483 | AP44: =AO44 -> 19993.483 | AQ44: ='Installment card_1000 (indiv)'!AQ36 -> 21826.439 | AR44: ='Installment card_1000 (indiv)'!AR36 -> 22704.96 | AS44: ='Installment card_1000 (indiv)'!AS36 -> 23626.98 | AT44: ='Installment card_1000 (indiv)'!AT36 -> 24590.73 | AU44: ='Installment card_1000 (indiv)'!AU36 -> 25594.411 | AV44: ='Installment card_1000 (indiv)'!AV36 -> 26636.202 | AW44: ='Installment card_1000 (indiv)'!AW36 -> 27714.259 | AX44: ='Installment card_1000 (indiv)'!AX36 -> 28826.726 | ... BB44: ='Installment card_1000 (indiv)'!BB36 -> 33501.493 | BC44: =BB44 -> 33501.493 | BD44: ='Installment card_1000 (indiv)'!BD36 -> 35775.772 | BE44: ='Installment card_1000 (indiv)'!BE36 -> 36428.491 | BF44: ='Installment card_1000 (indiv)'!BF36 -> 37132.733 | BG44: ='Installment card_1000 (indiv)'!BG36 -> 37886.481 | BH44: ='Installment card_1000 (indiv)'!BH36 -> 38687.694 | BI44: ='Installment card_1000 (indiv)'!BI36 -> 39534.313 | BJ44: ='Installment card_1000 (indiv)'!BJ36 -> 40424.266 | BK44: ='Installment card_1000 (indiv)'!BK36 -> 41355.469 | ... BO44: ='Installment card_1000 (indiv)'!BO36 -> 45353.04 | BP44: =BO44 -> 45353.04 | BR44: =F44/500*1000 -> 0 | BS44: =I44/500*1000 -> 0 | BT44: =L44/500*1000 -> 0 | BU44: =O44/500*1000 -> 0 | BV44: =V44/500*1000 -> 0 | BW44: =AB44/500*1000 -> 11215.712 | BX44: =AI44/500*1000 -> 24639.4 | BY44: =AO44/500*1000 -> 39986.966 | BZ44: =AV44/500*1000 -> 53272.404 | CA44: =BB44/500*1000 -> 67002.987 | CB44: =BI44/500*1000 -> 79068.627 | CC44: =BO44/500*1000 -> 90706.08 | CE44: Installment card 1000 | CF44: mln tenge
A45: Итого ЧОД по всем продуктам | B45: млн тенге | D45: =SUM(D46:D49) -> 0 | E45: =SUM(E46:E49) -> 0 | F45: =SUM(F46:F49) -> 0 | G45: =SUM(G46:G49) -> 0 | H45: =SUM(H46:H49) -> 0 | I45: =SUM(I46:I49) -> 0 | J45: =SUM(J46:J49) -> -8.2769943 | K45: =SUM(K46:K49) -> -17.389884 | ... O45: =SUM(O46:O49) -> -61.26245 | P45: =SUM(D45:O45) -> -203.89077 | Q45: =SUM(Q46:Q49) -> -56.647495 | R45: =SUM(R46:R49) -> -74.751556 | S45: =SUM(S46:S49) -> -99.142649 | T45: =SUM(T46:T49) -> -120.78929 | U45: =SUM(U46:U49) -> -146.00042 | V45: =SUM(V46:V49) -> -168.54463 | W45: =SUM(W46:W49) -> -216.31007 | X45: =SUM(X46:X49) -> -260.20714 | ... AB45: =SUM(AB46:AB49) -> -442.31272 | AC45: =SUM(Q45:AB45) -> -2627.1911 | AD45: =SUM(AD46:AD49) -> -347.69147 | AE45: =SUM(AE46:AE49) -> -339.63096 | AF45: =SUM(AF46:AF49) -> -397.62631 | AG45: =SUM(AG46:AG49) -> -421.81326 | AH45: =SUM(AH46:AH49) -> -466.58138 | AI45: =SUM(AI46:AI49) -> -490.49669 | AJ45: =SUM(AJ46:AJ49) -> -538.25454 | AK45: =SUM(AK46:AK49) -> -574.88894 | ... AO45: =SUM(AO46:AO49) -> -721.92792 | AP45: =SUM(AD45:AO45) -> -6216.7337 | AQ45: =SUM(AQ46:AQ49) -> -543.63985 | AR45: =SUM(AR46:AR49) -> -461.63897 | AS45: =SUM(AS46:AS49) -> -522.57223 | AT45: =SUM(AT46:AT49) -> -518.90244 | AU45: =SUM(AU46:AU49) -> -549.16633 | AV45: =SUM(AV46:AV49) -> -545.21054 | AW45: =SUM(AW46:AW49) -> -576.66846 | AX45: =SUM(AX46:AX49) -> -590.58955 | ... BB45: =SUM(BB46:BB49) -> -643.47772 | BC45: =SUM(AQ45:BB45) -> -6768.5031 | BD45: =SUM(BD46:BD49) -> -465.22438 | BE45: =SUM(BE46:BE49) -> -342.08683 | BF45: =SUM(BF46:BF49) -> -393.87741 | BG45: =SUM(BG46:BG49) -> -374.06973 | BH45: =SUM(BH46:BH49) -> -390.13794 | BI45: =SUM(BI46:BI49) -> -370.39467 | BJ45: =SUM(BJ46:BJ49) -> -386.41321 | BK45: =SUM(BK46:BK49) -> -384.40837 | ... BO45: =SUM(BO46:BO49) -> -372.01107 | BP45: =SUM(BD45:BO45) -> -4581.9387 | CE45: Total Net Operating Income for all products | CF45: mln tenge
A46: ЧОД дебетная карта | B46: млн тенге | D46: ='Debit card (indiv)'!D79 -> 0 | E46: ='Debit card (indiv)'!E79 -> 0 | F46: ='Debit card (indiv)'!F79 -> 0 | G46: ='Debit card (indiv)'!G79 -> 0 | H46: ='Debit card (indiv)'!H79 -> 0 | I46: ='Debit card (indiv)'!I79 -> 0 | J46: ='Debit card (indiv)'!J79 -> -7.61179 | K46: ='Debit card (indiv)'!K79 -> -15.368489 | ... O46: ='Debit card (indiv)'!O79 -> -48.727845 | P46: =SUM(D46:O46) -> -167.17951 | Q46: ='Debit card (indiv)'!Q79 -> -32.640441 | R46: ='Debit card (indiv)'!R79 -> -41.902205 | S46: ='Debit card (indiv)'!S79 -> -51.377787 | T46: ='Debit card (indiv)'!T79 -> -62.1364 | U46: ='Debit card (indiv)'!U79 -> -72.733917 | V46: ='Debit card (indiv)'!V79 -> -84.430379 | W46: ='Debit card (indiv)'!W79 -> -95.7104 | X46: ='Debit card (indiv)'!X79 -> -107.76861 | ... AB46: ='Debit card (indiv)'!AB79 -> -158.76557 | AC46: =SUM(Q46:AB46) -> -1107.9385 | AD46: ='Debit card (indiv)'!AD79 -> -29.391055 | AE46: ='Debit card (indiv)'!AE79 -> -24.218014 | AF46: ='Debit card (indiv)'!AF79 -> -20.637356 | AG46: ='Debit card (indiv)'!AG79 -> -23.926907 | AH46: ='Debit card (indiv)'!AH79 -> -23.481672 | AI46: ='Debit card (indiv)'!AI79 -> -27.130008 | AJ46: ='Debit card (indiv)'!AJ79 -> -26.504715 | AK46: ='Debit card (indiv)'!AK79 -> -28.077746 | ... AO46: ='Debit card (indiv)'!AO79 -> -34.501604 | AP46: =SUM(AD46:AO46) -> -337.4042 | AQ46: ='Debit card (indiv)'!AQ79 -> 167.75833 | AR46: ='Debit card (indiv)'!AR79 -> 190.59273 | AS46: ='Debit card (indiv)'!AS79 -> 211.90819 | AT46: ='Debit card (indiv)'!AT79 -> 212.9929 | AU46: ='Debit card (indiv)'!AU79 -> 225.11976 | AV46: ='Debit card (indiv)'!AV79 -> 226.4622 | AW46: ='Debit card (indiv)'!AW79 -> 239.49872 | AX46: ='Debit card (indiv)'!AX79 -> 247.09309 | ... BB46: ='Debit card (indiv)'!BB79 -> 279.47465 | BC46: =SUM(AQ46:BB46) -> 2777.2622 | BD46: ='Debit card (indiv)'!BD79 -> 465.83906 | BE46: ='Debit card (indiv)'!BE79 -> 486.49448 | BF46: ='Debit card (indiv)'!BF79 -> 520.52938 | BG46: ='Debit card (indiv)'!BG79 -> 519.66162 | BH46: ='Debit card (indiv)'!BH79 -> 537.5951 | BI46: ='Debit card (indiv)'!BI79 -> 537.6402 | BJ46: ='Debit card (indiv)'!BJ79 -> 557.05703 | BK46: ='Debit card (indiv)'!BK79 -> 567.62264 | ... BO46: ='Debit card (indiv)'!BO79 -> 613.92702 | BP46: =SUM(BD46:BO46) -> 6557.437 | CE46: NOI from debit cards | CF46: mln tenge
A47: ЧОД микрозайм 30 | B47: млн тенге | D47: ='Micro_30 (indiv)'!D57 -> 0 | E47: ='Micro_30 (indiv)'!E57 -> 0 | F47: ='Micro_30 (indiv)'!F57 -> 0 | G47: ='Micro_30 (indiv)'!G57 -> 0 | H47: ='Micro_30 (indiv)'!H57 -> 0 | I47: ='Micro_30 (indiv)'!I57 -> 0 | J47: ='Micro_30 (indiv)'!J57 -> -0.66520434 | K47: ='Micro_30 (indiv)'!K57 -> -2.021395 | ... O47: ='Micro_30 (indiv)'!O57 -> -7.9046364 | P47: =SUM(D47:O47) -> -24.975426 | Q47: ='Micro_30 (indiv)'!Q57 -> -9.7678574 | R47: ='Micro_30 (indiv)'!R57 -> -11.928076 | S47: ='Micro_30 (indiv)'!S57 -> -16.811967 | T47: ='Micro_30 (indiv)'!T57 -> -19.916792 | U47: ='Micro_30 (indiv)'!U57 -> -24.507209 | V47: ='Micro_30 (indiv)'!V57 -> -27.664171 | W47: ='Micro_30 (indiv)'!W57 -> -32.812575 | X47: ='Micro_30 (indiv)'!X57 -> -37.180417 | ... AB47: ='Micro_30 (indiv)'!AB57 -> -55.837407 | AC47: =SUM(Q47:AB47) -> -372.51122 | AD47: ='Micro_30 (indiv)'!AD57 -> -56.188686 | AE47: ='Micro_30 (indiv)'!AE57 -> -54.590125 | AF47: ='Micro_30 (indiv)'!AF57 -> -64.885822 | AG47: ='Micro_30 (indiv)'!AG57 -> -67.279188 | AH47: ='Micro_30 (indiv)'!AH57 -> -74.339774 | AI47: ='Micro_30 (indiv)'!AI57 -> -76.773075 | AJ47: ='Micro_30 (indiv)'!AJ57 -> -84.491402 | AK47: ='Micro_30 (indiv)'!AK57 -> -89.809674 | ... AO47: ='Micro_30 (indiv)'!AO57 -> -112.353 | AP47: =SUM(AD47:AO47) -> -977.00739 | AQ47: ='Micro_30 (indiv)'!AQ57 -> -107.98909 | AR47: ='Micro_30 (indiv)'!AR57 -> -100.34966 | AS47: ='Micro_30 (indiv)'!AS57 -> -114.39267 | AT47: ='Micro_30 (indiv)'!AT57 -> -114.05424 | AU47: ='Micro_30 (indiv)'!AU57 -> -121.48459 | AV47: ='Micro_30 (indiv)'!AV57 -> -121.23026 | AW47: ='Micro_30 (indiv)'!AW57 -> -129.20892 | AX47: ='Micro_30 (indiv)'!AX57 -> -133.29033 | ... BB47: ='Micro_30 (indiv)'!BB57 -> -150.73979 | BC47: =SUM(AQ47:BB47) -> -1509.2711 | BD47: ='Micro_30 (indiv)'!BD57 -> -141.29652 | BE47: ='Micro_30 (indiv)'!BE57 -> -129.31149 | BF47: ='Micro_30 (indiv)'!BF57 -> -145.22593 | BG47: ='Micro_30 (indiv)'!BG57 -> -142.71145 | BH47: ='Micro_30 (indiv)'!BH57 -> -149.88696 | BI47: ='Micro_30 (indiv)'!BI57 -> -147.55565 | BJ47: ='Micro_30 (indiv)'!BJ57 -> -155.22296 | BK47: ='Micro_30 (indiv)'!BK57 -> -158.12607 | ... BO47: ='Micro_30 (indiv)'!BO57 -> -170.96066 | BP47: =SUM(BD47:BO47) -> -1822.9201 | CE47: NOI from microloan 30 | CF47: mln tenge
A48: ЧОД карта рассрочки 150 | B48: млн тенге | D48: ='Installment card_150 (indiv)'!D117 -> 0 | E48: ='Installment card_150 (indiv)'!E117 -> 0 | F48: ='Installment card_150 (indiv)'!F117 -> 0 | G48: ='Installment card_150 (indiv)'!G117 -> 0 | H48: ='Installment card_150 (indiv)'!H117 -> 0 | I48: ='Installment card_150 (indiv)'!I117 -> 0 | J48: ='Installment card_150 (indiv)'!J117 -> 0 | K48: ='Installment card_150 (indiv)'!K117 -> 0 | ... O48: ='Installment card_150 (indiv)'!O117 -> -4.6299686 | P48: =SUM(D48:O48) -> -11.735836 | Q48: ='Installment card_150 (indiv)'!Q117 -> -14.239196 | R48: ='Installment card_150 (indiv)'!R117 -> -20.921275 | S48: ='Installment card_150 (indiv)'!S117 -> -30.952895 | T48: ='Installment card_150 (indiv)'!T117 -> -38.736094 | U48: ='Installment card_150 (indiv)'!U117 -> -48.75929 | V48: ='Installment card_150 (indiv)'!V117 -> -56.450077 | W48: ='Installment card_150 (indiv)'!W117 -> -67.409049 | X48: ='Installment card_150 (indiv)'!X117 -> -77.000062 | ... AB48: ='Installment card_150 (indiv)'!AB117 -> -116.04841 | AC48: =SUM(Q48:AB48) -> -755.12541 | AD48: ='Installment card_150 (indiv)'!AD117 -> -132.8246 | AE48: ='Installment card_150 (indiv)'!AE117 -> -127.23054 | AF48: ='Installment card_150 (indiv)'!AF117 -> -148.57064 | AG48: ='Installment card_150 (indiv)'!AG117 -> -153.87041 | AH48: ='Installment card_150 (indiv)'!AH117 -> -168.29926 | AI48: ='Installment card_150 (indiv)'!AI117 -> -173.35215 | AJ48: ='Installment card_150 (indiv)'!AJ117 -> -188.61633 | AK48: ='Installment card_150 (indiv)'!AK117 -> -198.9199 | ... AO48: ='Installment card_150 (indiv)'!AO117 -> -239.46484 | AP48: =SUM(AD48:AO48) -> -2177.7142 | AQ48: ='Installment card_150 (indiv)'!AQ117 -> -258.40068 | AR48: ='Installment card_150 (indiv)'!AR117 -> -231.79461 | AS48: ='Installment card_150 (indiv)'!AS117 -> -258.67865 | AT48: ='Installment card_150 (indiv)'!AT117 -> -256.22631 | AU48: ='Installment card_150 (indiv)'!AU117 -> -269.06336 | AV48: ='Installment card_150 (indiv)'!AV117 -> -266.60134 | AW48: ='Installment card_150 (indiv)'!AW117 -> -279.9161 | AX48: ='Installment card_150 (indiv)'!AX117 -> -285.44461 | ... BB48: ='Installment card_150 (indiv)'!BB117 -> -306.52174 | BC48: =SUM(AQ48:BB48) -> -3285.4956 | BD48: ='Installment card_150 (indiv)'!BD117 -> -324.66332 | BE48: ='Installment card_150 (indiv)'!BE117 -> -280.56695 | BF48: ='Installment card_150 (indiv)'!BF117 -> -306.97638 | BG48: ='Installment card_150 (indiv)'!BG117 -> -298.58708 | BH48: ='Installment card_150 (indiv)'!BH117 -> -307.81174 | BI48: ='Installment card_150 (indiv)'!BI117 -> -299.77906 | BJ48: ='Installment card_150 (indiv)'!BJ117 -> -309.23887 | BK48: ='Installment card_150 (indiv)'!BK117 -> -310.09498 | ... BO48: ='Installment card_150 (indiv)'!BO117 -> -312.57513 | BP48: =SUM(BD48:BO48) -> -3668.7932 | CE48: NOI from Installment card 150 | CF48: mln tenge
A49: ЧОД карта рассрочки 1000 | B49: млн тенге | D49: ='Installment card_1000 (indiv)'!D117 -> 0 | E49: ='Installment card_1000 (indiv)'!E117 -> 0 | F49: ='Installment card_1000 (indiv)'!F117 -> 0 | G49: ='Installment card_1000 (indiv)'!G117 -> 0 | H49: ='Installment card_1000 (indiv)'!H117 -> 0 | I49: ='Installment card_1000 (indiv)'!I117 -> 0 | J49: ='Installment card_1000 (indiv)'!J117 -> 0 | K49: ='Installment card_1000 (indiv)'!K117 -> 0 | ... O49: ='Installment card_1000 (indiv)'!O117 -> 0 | P49: =SUM(D49:O49) -> 0 | Q49: ='Installment card_1000 (indiv)'!Q117 -> 0 | R49: ='Installment card_1000 (indiv)'!R117 -> 0 | S49: ='Installment card_1000 (indiv)'!S117 -> 0 | T49: ='Installment card_1000 (indiv)'!T117 -> 0 | U49: ='Installment card_1000 (indiv)'!U117 -> 0 | V49: ='Installment card_1000 (indiv)'!V117 -> 0 | W49: ='Installment card_1000 (indiv)'!W117 -> -20.378052 | X49: ='Installment card_1000 (indiv)'!X117 -> -38.258053 | ... AB49: ='Installment card_1000 (indiv)'!AB117 -> -111.66134 | AC49: =SUM(Q49:AB49) -> -391.61591 | AD49: ='Installment card_1000 (indiv)'!AD117 -> -129.28714 | AE49: ='Installment card_1000 (indiv)'!AE117 -> -133.59228 | AF49: ='Installment card_1000 (indiv)'!AF117 -> -163.53249 | AG49: ='Installment card_1000 (indiv)'!AG117 -> -176.73674 | AH49: ='Installment card_1000 (indiv)'!AH117 -> -200.46068 | AI49: ='Installment card_1000 (indiv)'!AI117 -> -213.24146 | AJ49: ='Installment card_1000 (indiv)'!AJ117 -> -238.64209 | AK49: ='Installment card_1000 (indiv)'!AK117 -> -258.08162 | ... AO49: ='Installment card_1000 (indiv)'!AO117 -> -335.60848 | AP49: =SUM(AD49:AO49) -> -2724.6079 | AQ49: ='Installment card_1000 (indiv)'!AQ117 -> -345.0084 | AR49: ='Installment card_1000 (indiv)'!AR117 -> -320.08743 | AS49: ='Installment card_1000 (indiv)'!AS117 -> -361.4091 | AT49: ='Installment card_1000 (indiv)'!AT117 -> -361.61479 | AU49: ='Installment card_1000 (indiv)'!AU117 -> -383.73813 | AV49: ='Installment card_1000 (indiv)'!AV117 -> -383.84114 | AW49: ='Installment card_1000 (indiv)'!AW117 -> -407.04216 | AX49: ='Installment card_1000 (indiv)'!AX117 -> -418.9477 | ... BB49: ='Installment card_1000 (indiv)'!BB117 -> -465.69084 | BC49: =SUM(AQ49:BB49) -> -4750.9986 | BD49: ='Installment card_1000 (indiv)'!BD117 -> -465.10359 | BE49: ='Installment card_1000 (indiv)'!BE117 -> -418.70288 | BF49: ='Installment card_1000 (indiv)'!BF117 -> -462.20448 | BG49: ='Installment card_1000 (indiv)'!BG117 -> -452.43282 | BH49: ='Installment card_1000 (indiv)'!BH117 -> -470.03435 | BI49: ='Installment card_1000 (indiv)'!BI117 -> -460.70017 | BJ49: ='Installment card_1000 (indiv)'!BJ117 -> -479.00841 | BK49: ='Installment card_1000 (indiv)'!BK117 -> -483.80995 | ... BO49: ='Installment card_1000 (indiv)'!BO117 -> -502.40231 | BP49: =SUM(BD49:BO49) -> -5647.6624 | CE49: NOI from Installment card 1000 | CF49: mln tenge
A51: Маржа размещения | B51: млн тенге | D51: ='Micro_30 (indiv)'!D37+'Installment card_150 (indiv)'!D97+'Installment card_1000 (indiv)'!D97+'Debit card (indiv)'!D59 -> 0 | E51: ='Micro_30 (indiv)'!E37+'Installment card_150 (indiv)'!E97+'Installment card_1000 (indiv)'!E97+'Debit card (indiv)'!E59 -> 0 | F51: ='Micro_30 (indiv)'!F37+'Installment card_150 (indiv)'!F97+'Installment card_1000 (indiv)'!F97+'Debit card (indiv)'!F59 -> 0 | G51: ='Micro_30 (indiv)'!G37+'Installment card_150 (indiv)'!G97+'Installment card_1000 (indiv)'!G97+'Debit card (indiv)'!G59 -> 0 | H51: ='Micro_30 (indiv)'!H37+'Installment card_150 (indiv)'!H97+'Installment card_1000 (indiv)'!H97+'Debit card (indiv)'!H59 -> 0 | I51: ='Micro_30 (indiv)'!I37+'Installment card_150 (indiv)'!I97+'Installment card_1000 (indiv)'!I97+'Debit card (indiv)'!I59 -> 0 | J51: ='Micro_30 (indiv)'!J37+'Installment card_150 (indiv)'!J97+'Installment card_1000 (indiv)'!J97+'Debit card (indiv)'!J59 -> -0.65296131 | K51: ='Micro_30 (indiv)'!K37+'Installment card_150 (indiv)'!K97+'Installment card_1000 (indiv)'!K97+'Debit card (indiv)'!K59 -> -1.9841914 | ... O51: ='Micro_30 (indiv)'!O37+'Installment card_150 (indiv)'!O97+'Installment card_1000 (indiv)'!O97+'Debit card (indiv)'!O59 -> -9.7808074 | P51: =SUM(D51:O51) -> -29.118646 | Q51: ='Micro_30 (indiv)'!Q37+'Installment card_150 (indiv)'!Q97+'Installment card_1000 (indiv)'!Q97+'Debit card (indiv)'!Q59 -> -13.755284 | R51: ='Micro_30 (indiv)'!R37+'Installment card_150 (indiv)'!R97+'Installment card_1000 (indiv)'!R97+'Debit card (indiv)'!R59 -> -19.181441 | S51: ='Micro_30 (indiv)'!S37+'Installment card_150 (indiv)'!S97+'Installment card_1000 (indiv)'!S97+'Debit card (indiv)'!S59 -> -28.890742 | T51: ='Micro_30 (indiv)'!T37+'Installment card_150 (indiv)'!T97+'Installment card_1000 (indiv)'!T97+'Debit card (indiv)'!T59 -> -35.619142 | U51: ='Micro_30 (indiv)'!U37+'Installment card_150 (indiv)'!U97+'Installment card_1000 (indiv)'!U97+'Debit card (indiv)'!U59 -> -44.967144 | V51: ='Micro_30 (indiv)'!V37+'Installment card_150 (indiv)'!V97+'Installment card_1000 (indiv)'!V97+'Debit card (indiv)'!V59 -> -51.634931 | W51: ='Micro_30 (indiv)'!W37+'Installment card_150 (indiv)'!W97+'Installment card_1000 (indiv)'!W97+'Debit card (indiv)'!W59 -> -65.960504 | X51: ='Micro_30 (indiv)'!X37+'Installment card_150 (indiv)'!X97+'Installment card_1000 (indiv)'!X97+'Debit card (indiv)'!X59 -> -82.81754 | ... AB51: ='Micro_30 (indiv)'!AB37+'Installment card_150 (indiv)'!AB97+'Installment card_1000 (indiv)'!AB97+'Debit card (indiv)'!AB59 -> -152.25624 | AC51: =SUM(Q51:AB51) -> -839.70232 | AD51: ='Micro_30 (indiv)'!AD37+'Installment card_150 (indiv)'!AD97+'Installment card_1000 (indiv)'!AD97+'Debit card (indiv)'!AD59 -> -157.36679 | AE51: ='Micro_30 (indiv)'!AE37+'Installment card_150 (indiv)'!AE97+'Installment card_1000 (indiv)'!AE97+'Debit card (indiv)'!AE59 -> -159.10978 | AF51: ='Micro_30 (indiv)'!AF37+'Installment card_150 (indiv)'!AF97+'Installment card_1000 (indiv)'!AF97+'Debit card (indiv)'!AF59 -> -191.83782 | AG51: ='Micro_30 (indiv)'!AG37+'Installment card_150 (indiv)'!AG97+'Installment card_1000 (indiv)'!AG97+'Debit card (indiv)'!AG59 -> -201.21672 | AH51: ='Micro_30 (indiv)'!AH37+'Installment card_150 (indiv)'!AH97+'Installment card_1000 (indiv)'!AH97+'Debit card (indiv)'!AH59 -> -224.36944 | AI51: ='Micro_30 (indiv)'!AI37+'Installment card_150 (indiv)'!AI97+'Installment card_1000 (indiv)'!AI97+'Debit card (indiv)'!AI59 -> -233.35013 | AJ51: ='Micro_30 (indiv)'!AJ37+'Installment card_150 (indiv)'!AJ97+'Installment card_1000 (indiv)'!AJ97+'Debit card (indiv)'!AJ59 -> -258.1556 | AK51: ='Micro_30 (indiv)'!AK37+'Installment card_150 (indiv)'!AK97+'Installment card_1000 (indiv)'!AK97+'Debit card (indiv)'!AK59 -> -275.40598 | ... AO51: ='Micro_30 (indiv)'!AO37+'Installment card_150 (indiv)'!AO97+'Installment card_1000 (indiv)'!AO97+'Debit card (indiv)'!AO59 -> -345.22077 | AP51: =SUM(AD51:AO51) -> -2957.2971 | AQ51: ='Micro_30 (indiv)'!AQ37+'Installment card_150 (indiv)'!AQ97+'Installment card_1000 (indiv)'!AQ97+'Debit card (indiv)'!AQ59 -> -325.0337 | AR51: ='Micro_30 (indiv)'!AR37+'Installment card_150 (indiv)'!AR97+'Installment card_1000 (indiv)'!AR97+'Debit card (indiv)'!AR59 -> -307.10994 | AS51: ='Micro_30 (indiv)'!AS37+'Installment card_150 (indiv)'!AS97+'Installment card_1000 (indiv)'!AS97+'Debit card (indiv)'!AS59 -> -347.85238 | AT51: ='Micro_30 (indiv)'!AT37+'Installment card_150 (indiv)'!AT97+'Installment card_1000 (indiv)'!AT97+'Debit card (indiv)'!AT59 -> -344.50738 | AU51: ='Micro_30 (indiv)'!AU37+'Installment card_150 (indiv)'!AU97+'Installment card_1000 (indiv)'!AU97+'Debit card (indiv)'!AU59 -> -364.38769 | AV51: ='Micro_30 (indiv)'!AV37+'Installment card_150 (indiv)'!AV97+'Installment card_1000 (indiv)'!AV97+'Debit card (indiv)'!AV59 -> -360.9684 | AW51: ='Micro_30 (indiv)'!AW37+'Installment card_150 (indiv)'!AW97+'Installment card_1000 (indiv)'!AW97+'Debit card (indiv)'!AW59 -> -381.78884 | AX51: ='Micro_30 (indiv)'!AX37+'Installment card_150 (indiv)'!AX97+'Installment card_1000 (indiv)'!AX97+'Debit card (indiv)'!AX59 -> -390.71193 | ... BB51: ='Micro_30 (indiv)'!BB37+'Installment card_150 (indiv)'!BB97+'Installment card_1000 (indiv)'!BB97+'Debit card (indiv)'!BB59 -> -426.48843 | BC51: =SUM(AQ51:BB51) -> -4448.9138 | BD51: ='Micro_30 (indiv)'!BD37+'Installment card_150 (indiv)'!BD97+'Installment card_1000 (indiv)'!BD97+'Debit card (indiv)'!BD59 -> -374.98059 | BE51: ='Micro_30 (indiv)'!BE37+'Installment card_150 (indiv)'!BE97+'Installment card_1000 (indiv)'!BE97+'Debit card (indiv)'!BE59 -> -345.85071 | BF51: ='Micro_30 (indiv)'!BF37+'Installment card_150 (indiv)'!BF97+'Installment card_1000 (indiv)'!BF97+'Debit card (indiv)'!BF59 -> -383.12491 | BG51: ='Micro_30 (indiv)'!BG37+'Installment card_150 (indiv)'!BG97+'Installment card_1000 (indiv)'!BG97+'Debit card (indiv)'!BG59 -> -371.25938 | BH51: ='Micro_30 (indiv)'!BH37+'Installment card_150 (indiv)'!BH97+'Installment card_1000 (indiv)'!BH97+'Debit card (indiv)'!BH59 -> -384.3925 | BI51: ='Micro_30 (indiv)'!BI37+'Installment card_150 (indiv)'!BI97+'Installment card_1000 (indiv)'!BI97+'Debit card (indiv)'!BI59 -> -372.92558 | BJ51: ='Micro_30 (indiv)'!BJ37+'Installment card_150 (indiv)'!BJ97+'Installment card_1000 (indiv)'!BJ97+'Debit card (indiv)'!BJ59 -> -386.48567 | BK51: ='Micro_30 (indiv)'!BK37+'Installment card_150 (indiv)'!BK97+'Installment card_1000 (indiv)'!BK97+'Debit card (indiv)'!BK59 -> -387.74058 | ... BO51: ='Micro_30 (indiv)'!BO37+'Installment card_150 (indiv)'!BO97+'Installment card_1000 (indiv)'!BO97+'Debit card (indiv)'!BO59 -> -392.8578 | BP51: =SUM(BD51:BO51) -> -4545.8645 | BR51: =(D51+E51+F51)/500*1000 -> 0 | BS51: =(G51+H51+I51)/500*1000 -> 0 | BT51: =(J51+K51+L51)/500*1000 -> -12.356939 | BU51: =(M51+N51+O51)/500*1000 -> -45.880353 | BV51: =(SUM(Q51:V51))/500*1000 -> -388.09737 | BW51: =SUM(W51:AB51)/500*1000 -> -1291.3073 | BX51: =SUM(AD51:AI51)/500*1000 -> -2334.5014 | BY51: =SUM(AJ51:AO51)/500*1000 -> -3580.0929 | BZ51: =SUM(AQ51:AV51)/500*1000 -> -4099.719 | CA51: =SUM(AW51:BB51)/500*1000 -> -4798.1085 | CB51: =SUM(BD51:BI51)/500*1000 -> -4465.0673 | CC51: =SUM(BJ51:BO51)/500*1000 -> -4626.6617 | CE51: interest margin on invested funds | CF51: mln tenge
A52: Маржа привлечения | B52: млн тенге | D52: ='Micro_30 (indiv)'!D40+'Installment card_150 (indiv)'!D100+'Installment card_1000 (indiv)'!D100+'Debit card (indiv)'!D62 -> 0 | E52: ='Micro_30 (indiv)'!E40+'Installment card_150 (indiv)'!E100+'Installment card_1000 (indiv)'!E100+'Debit card (indiv)'!E62 -> 0 | F52: ='Micro_30 (indiv)'!F40+'Installment card_150 (indiv)'!F100+'Installment card_1000 (indiv)'!F100+'Debit card (indiv)'!F62 -> 0 | G52: ='Micro_30 (indiv)'!G40+'Installment card_150 (indiv)'!G100+'Installment card_1000 (indiv)'!G100+'Debit card (indiv)'!G62 -> 0 | H52: ='Micro_30 (indiv)'!H40+'Installment card_150 (indiv)'!H100+'Installment card_1000 (indiv)'!H100+'Debit card (indiv)'!H62 -> 0 | I52: ='Micro_30 (indiv)'!I40+'Installment card_150 (indiv)'!I100+'Installment card_1000 (indiv)'!I100+'Debit card (indiv)'!I62 -> 0 | J52: ='Micro_30 (indiv)'!J40+'Installment card_150 (indiv)'!J100+'Installment card_1000 (indiv)'!J100+'Debit card (indiv)'!J62 -> 0.15010855 | K52: ='Micro_30 (indiv)'!K40+'Installment card_150 (indiv)'!K100+'Installment card_1000 (indiv)'!K100+'Debit card (indiv)'!K62 -> 0.45614356 | ... O52: ='Micro_30 (indiv)'!O40+'Installment card_150 (indiv)'!O100+'Installment card_1000 (indiv)'!O100+'Debit card (indiv)'!O62 -> 1.7837429 | P52: =SUM(D52:O52) -> 5.6358998 | Q52: ='Micro_30 (indiv)'!Q40+'Installment card_150 (indiv)'!Q100+'Installment card_1000 (indiv)'!Q100+'Debit card (indiv)'!Q62 -> 3.3877089 | R52: ='Micro_30 (indiv)'!R40+'Installment card_150 (indiv)'!R100+'Installment card_1000 (indiv)'!R100+'Debit card (indiv)'!R62 -> 5.2173805 | S52: ='Micro_30 (indiv)'!S40+'Installment card_150 (indiv)'!S100+'Installment card_1000 (indiv)'!S100+'Debit card (indiv)'!S62 -> 7.3536108 | T52: ='Micro_30 (indiv)'!T40+'Installment card_150 (indiv)'!T100+'Installment card_1000 (indiv)'!T100+'Debit card (indiv)'!T62 -> 8.7116717 | U52: ='Micro_30 (indiv)'!U40+'Installment card_150 (indiv)'!U100+'Installment card_1000 (indiv)'!U100+'Debit card (indiv)'!U62 -> 10.719535 | V52: ='Micro_30 (indiv)'!V40+'Installment card_150 (indiv)'!V100+'Installment card_1000 (indiv)'!V100+'Debit card (indiv)'!V62 -> 12.100401 | W52: ='Micro_30 (indiv)'!W40+'Installment card_150 (indiv)'!W100+'Installment card_1000 (indiv)'!W100+'Debit card (indiv)'!W62 -> 14.35233 | X52: ='Micro_30 (indiv)'!X40+'Installment card_150 (indiv)'!X100+'Installment card_1000 (indiv)'!X100+'Debit card (indiv)'!X62 -> 16.262839 | ... AB52: ='Micro_30 (indiv)'!AB40+'Installment card_150 (indiv)'!AB100+'Installment card_1000 (indiv)'!AB100+'Debit card (indiv)'!AB62 -> 24.423469 | AC52: =SUM(Q52:AB52) -> 162.05287 | AD52: ='Micro_30 (indiv)'!AD40+'Installment card_150 (indiv)'!AD100+'Installment card_1000 (indiv)'!AD100+'Debit card (indiv)'!AD62 -> 35.957888 | AE52: ='Micro_30 (indiv)'!AE40+'Installment card_150 (indiv)'!AE100+'Installment card_1000 (indiv)'!AE100+'Debit card (indiv)'!AE62 -> 46.017153 | AF52: ='Micro_30 (indiv)'!AF40+'Installment card_150 (indiv)'!AF100+'Installment card_1000 (indiv)'!AF100+'Debit card (indiv)'!AF62 -> 54.701351 | AG52: ='Micro_30 (indiv)'!AG40+'Installment card_150 (indiv)'!AG100+'Installment card_1000 (indiv)'!AG100+'Debit card (indiv)'!AG62 -> 56.724617 | AH52: ='Micro_30 (indiv)'!AH40+'Installment card_150 (indiv)'!AH100+'Installment card_1000 (indiv)'!AH100+'Debit card (indiv)'!AH62 -> 62.683706 | AI52: ='Micro_30 (indiv)'!AI40+'Installment card_150 (indiv)'!AI100+'Installment card_1000 (indiv)'!AI100+'Debit card (indiv)'!AI62 -> 64.741829 | AJ52: ='Micro_30 (indiv)'!AJ40+'Installment card_150 (indiv)'!AJ100+'Installment card_1000 (indiv)'!AJ100+'Debit card (indiv)'!AJ62 -> 71.257593 | AK52: ='Micro_30 (indiv)'!AK40+'Installment card_150 (indiv)'!AK100+'Installment card_1000 (indiv)'!AK100+'Debit card (indiv)'!AK62 -> 75.7503 | ... AO52: ='Micro_30 (indiv)'!AO40+'Installment card_150 (indiv)'!AO100+'Installment card_1000 (indiv)'!AO100+'Debit card (indiv)'!AO62 -> 94.80176 | AP52: =SUM(AD52:AO52) -> 812.59865 | AQ52: ='Micro_30 (indiv)'!AQ40+'Installment card_150 (indiv)'!AQ100+'Installment card_1000 (indiv)'!AQ100+'Debit card (indiv)'!AQ62 -> 120.23795 | AR52: ='Micro_30 (indiv)'!AR40+'Installment card_150 (indiv)'!AR100+'Installment card_1000 (indiv)'!AR100+'Debit card (indiv)'!AR62 -> 141.67693 | AS52: ='Micro_30 (indiv)'!AS40+'Installment card_150 (indiv)'!AS100+'Installment card_1000 (indiv)'!AS100+'Debit card (indiv)'!AS62 -> 161.52046 | AT52: ='Micro_30 (indiv)'!AT40+'Installment card_150 (indiv)'!AT100+'Installment card_1000 (indiv)'!AT100+'Debit card (indiv)'!AT62 -> 161.0597 | AU52: ='Micro_30 (indiv)'!AU40+'Installment card_150 (indiv)'!AU100+'Installment card_1000 (indiv)'!AU100+'Debit card (indiv)'!AU62 -> 171.57057 | AV52: ='Micro_30 (indiv)'!AV40+'Installment card_150 (indiv)'!AV100+'Installment card_1000 (indiv)'!AV100+'Debit card (indiv)'!AV62 -> 171.22956 | AW52: ='Micro_30 (indiv)'!AW40+'Installment card_150 (indiv)'!AW100+'Installment card_1000 (indiv)'!AW100+'Debit card (indiv)'!AW62 -> 182.51827 | AX52: ='Micro_30 (indiv)'!AX40+'Installment card_150 (indiv)'!AX100+'Installment card_1000 (indiv)'!AX100+'Debit card (indiv)'!AX62 -> 188.3036 | ... BB52: ='Micro_30 (indiv)'!BB40+'Installment card_150 (indiv)'!BB100+'Installment card_1000 (indiv)'!BB100+'Debit card (indiv)'!BB62 -> 213.04557 | BC52: =SUM(AQ52:BB52) -> 2099.7367 | BD52: ='Micro_30 (indiv)'!BD40+'Installment card_150 (indiv)'!BD100+'Installment card_1000 (indiv)'!BD100+'Debit card (indiv)'!BD62 -> 229.63329 | BE52: ='Micro_30 (indiv)'!BE40+'Installment card_150 (indiv)'!BE100+'Installment card_1000 (indiv)'!BE100+'Debit card (indiv)'!BE62 -> 246.99422 | BF52: ='Micro_30 (indiv)'!BF40+'Installment card_150 (indiv)'!BF100+'Installment card_1000 (indiv)'!BF100+'Debit card (indiv)'!BF62 -> 277.42406 | BG52: ='Micro_30 (indiv)'!BG40+'Installment card_150 (indiv)'!BG100+'Installment card_1000 (indiv)'!BG100+'Debit card (indiv)'!BG62 -> 272.65224 | BH52: ='Micro_30 (indiv)'!BH40+'Installment card_150 (indiv)'!BH100+'Installment card_1000 (indiv)'!BH100+'Debit card (indiv)'!BH62 -> 286.39431 | BI52: ='Micro_30 (indiv)'!BI40+'Installment card_150 (indiv)'!BI100+'Installment card_1000 (indiv)'!BI100+'Debit card (indiv)'!BI62 -> 281.97246 | BJ52: ='Micro_30 (indiv)'!BJ40+'Installment card_150 (indiv)'!BJ100+'Installment card_1000 (indiv)'!BJ100+'Debit card (indiv)'!BJ62 -> 296.6587 | BK52: ='Micro_30 (indiv)'!BK40+'Installment card_150 (indiv)'!BK100+'Installment card_1000 (indiv)'!BK100+'Debit card (indiv)'!BK62 -> 302.24208 | ... BO52: ='Micro_30 (indiv)'!BO40+'Installment card_150 (indiv)'!BO100+'Installment card_1000 (indiv)'!BO100+'Debit card (indiv)'!BO62 -> 326.9256 | BP52: =SUM(BD52:BO52) -> 3443.5964 | BR52: =(D52+E52+F52)/500*1000 -> 0 | BS52: =(G52+H52+I52)/500*1000 -> 0 | BT52: =(J52+K52+L52)/500*1000 -> 2.7098626 | BU52: =(M52+N52+O52)/500*1000 -> 8.561937 | BV52: =(SUM(Q52:V52))/500*1000 -> 94.980617 | BW52: =SUM(W52:AB52)/500*1000 -> 229.12513 | BX52: =SUM(AD52:AI52)/500*1000 -> 641.65309 | BY52: =SUM(AJ52:AO52)/500*1000 -> 983.54422 | BZ52: =SUM(AQ52:AV52)/500*1000 -> 1854.5903 | CA52: =SUM(AW52:BB52)/500*1000 -> 2344.8831 | CB52: =SUM(BD52:BI52)/500*1000 -> 3190.1412 | CC52: =SUM(BJ52:BO52)/500*1000 -> 3697.0516 | CE52: interest margin on borrowed funds | CF52: mln tenge
