Workbook
Name __dol1: #REF!
Name __END1: #REF!
Name __kurs_dol__: #REF!
Name __stroka__: #REF!
Name _dol1: #REF!
Name _END1: #REF!
Name aned110: #REF!
Name aned111: #REF!
Name aned112: #REF!
Name aned113: #REF!
Name aned146: #REF!
Name aned158: #REF!
Name aned161: #REF!
Name aned162: #REF!
Name aned170: #REF!
Name aned184: #REF!
Name aned191: #REF!
Name aned194: #REF!
Name aned213: #REF!
Name aned224: #REF!
Name aned239: #REF!
Name aned34: #REF!
Name aned50: #REF!
Name aned60: #REF!
Name aned61: #REF!
Name aned62: #REF!
Name aned620: #REF!
Name aned624: #REF!
Name aned628: #REF!
Name aned629: #REF!
Name aned63: #REF!
Name aned632: #REF!
Name aned636: #REF!
Name aned637: #REF!
Name aned639: #REF!
Name aned64: #REF!
Name aned647: #REF!
Name aned65: #REF!
Name aned657: #REF!
Name aned662: #REF!
Name aned668: #REF!
Name aned680: #REF!
Name aned681: #REF!
Name aned682: #REF!
Name aned683: #REF!
Name aned716: #REF!
Name aned718: #REF!
Name aned719: #REF!
Name aned72: #REF!
Name aned728: #REF!
Name aned729: #REF!
Name aned731: #REF!
Name aned76: #REF!
Name aned77: #REF!
Name aned79: #REF!
Name aned812: #REF!
Name aned86: #REF!
Name aned87: #REF!
Name aned882: #REF!
Name aned900: #REF!

Sheet Продукты
B1: ЦФО – Владелец продукта | C1: Банковский продукт | D1: Банковский продукт (ФМ) | E1: Канал | F1: Бизнес линия | G1: Вид бизнеса | H1: Лист
C2: Потребительский кредит (ФЛ) | D2: Нецелевые кредиты (потребительские) (залоговые) | E2: Безбумажный офис | F2: Кредиты | G2: Розничный бизнес | H2: РБ.1
E3: DCB 360 | F3: Кредиты | G3: Розничный бизнес | H3: РБ.1
C4: Мобильный кредит | D4: Ипотека | E4: Безбумажный офис | F4: Кредиты | G4: Розничный бизнес | H4: РБ.1
C5: GREEN – ЭКОДОМ (ФЛ) | D5: Нецелевые кредиты (потребительские) (залоговые) | E5: Безбумажный офис | F5: Кредиты | G5: Розничный бизнес | H5: РБ.1
C6: DCB АВТО (ФЛ) | D6: Нецелевые кредиты (потребительские) (без залога) | E6: Безбумажный офис | F6: Кредиты | G6: Розничный бизнес | H6: РБ.1
E7: DCB 360 | F7: Кредиты | G7: Розничный бизнес | H7: РБ.1
C8: ЭКО-Агрокредит (ФЛ) | D8: Ипотека | E8: Безбумажный офис | F8: Кредиты | G8: Розничный бизнес | H8: РБ.1
C9: Универсальный депозит "Бай Бол" | E9: Безбумажный офис | F9: Счета и депозиты | G9: Розничный бизнес | H9: РБ.2
E10: DCB 360 | F10: Счета и депозиты | G10: Розничный бизнес | H10: РБ.2
C11: Депозит «Бай Бол +» | E11: Безбумажный офис | F11: Счета и депозиты | G11: Розничный бизнес | H11: РБ.2
E12: DCB 360 | F12: Счета и депозиты | G12: Розничный бизнес | H12: РБ.2
C13: Депозит «Зеленый» | E13: Безбумажный офис | F13: Счета и депозиты | G13: Розничный бизнес | H13: РБ.2
E14: DCB 360 | F14: Счета и депозиты | G14: Розничный бизнес | H14: РБ.2
C15: Счет до востребования | E15: Безбумажный офис | F15: Счета и депозиты | G15: Розничный бизнес | H15: РБ.2
E16: DCB 360 | F16: Счета и депозиты | G16: Розничный бизнес | H16: РБ.2
C17: Карта социальные выплаты | E17: Безбумажный офис | F17: Выпуск и обслуживание банковских карт | G17: Розничный бизнес | H17: РБ.3
C18: Карта Элкарт DCB | E18: Безбумажный офис | F18: Выпуск и обслуживание банковских карт | G18: Розничный бизнес | H18: РБ.3
E19: DCB 360 | F19: Выпуск и обслуживание банковских карт | G19: Розничный бизнес | H19: РБ.3
C20: Карта пенсионера | E20: Безбумажный офис | F20: Выпуск и обслуживание банковских карт | G20: Розничный бизнес | H20: РБ.3
C21: DCB Kids детская карта | E21: Безбумажный офис | F21: Выпуск и обслуживание банковских карт | G21: Розничный бизнес | H21: РБ.3
C22: Зарплатная карта | E22: Безбумажный офис | F22: Выпуск и обслуживание банковских карт | G22: Розничный бизнес | H22: РБ.3
C23: Открытие и обслуживание банковского счета | E23: Безбумажный офис | F23: РКО | G23: Розничный бизнес | H23: РБ.3
E24: DCB 360 | F24: РКО | G24: Розничный бизнес | H24: РБ.3
C25: Переводы и платежи | E25: Безбумажный офис | F25: РКО | G25: Розничный бизнес | H25: РБ.3
E26: DCB 360 | F26: РКО | G26: Розничный бизнес | H26: РБ.3
C27: Кассовые операции | E27: Безбумажный офис | F27: РКО | G27: Розничный бизнес | H27: РБ.3
C28: Валютные операции | E28: Безбумажный офис | F28: РКО | G28: Розничный бизнес | H28: РБ.3
E29: DCB 360 | F29: РКО | G29: Розничный бизнес | H29: РБ.3
C30: Бизнес-кредит (ИП, ЮЛ) | E30: Безбумажный офис | F30: Кредиты | G30: Малый и средний бизнес | H30: МСБ.1
C31: GREEN - ЭКОАВТО (ИП, ЮЛ) | E31: Безбумажный офис | F31: Кредиты | G31: Малый и средний бизнес | H31: МСБ.1
C32: ЭКО-Агрокредит (ИП, ЮЛ) | E32: Безбумажный офис | F32: Кредиты | G32: Малый и средний бизнес | H32: МСБ.1
C33: Гарантии | E33: Безбумажный офис | F33: Кредиты | G33: Малый и средний бизнес | H33: МСБ.1
C34: Депозит "Срочный" (ЮЛ, ИП) | E34: Безбумажный офис | F34: Депозиты | G34: Малый и средний бизнес | H34: МСБ.2
E35: DCB Бизнес | F35: Депозиты | G35: Малый и средний бизнес | H35: МСБ.2
C36: Депозит «Зеленый» (ЮЛ, ИП) | E36: Безбумажный офис | F36: Депозиты | G36: Малый и средний бизнес | H36: МСБ.2
E37: DCB Бизнес | F37: Депозиты | G37: Малый и средний бизнес | H37: МСБ.2
C38: Расчетный счет | E38: Безбумажный офис | F38: Депозиты | G38: Малый и средний бизнес | H38: МСБ.2
E39: DCB Бизнес | F39: Депозиты | G39: Малый и средний бизнес | H39: МСБ.2
C40: Карточные счета | E40: Безбумажный офис | F40: Депозиты | G40: Малый и средний бизнес | H40: МСБ.2
C41: Открытие и обслуживание банковского счета | E41: Безбумажный офис | F41: РКО | G41: Малый и средний бизнес | H41: МСБ.3
E42: DCB Бизнес | F42: РКО | G42: Малый и средний бизнес | H42: МСБ.3
C43: Межбанковские переводы (Клиринг, Гросс) | E43: Безбумажный офис | F43: РКО | G43: Малый и средний бизнес | H43: МСБ.3
E44: DCB Бизнес | F44: РКО | G44: Малый и средний бизнес | H44: МСБ.3
C45: SWIFT-переводы | E45: Безбумажный офис | F45: РКО | G45: Малый и средний бизнес | H45: МСБ.3
E46: DCB Бизнес | F46: РКО | G46: Малый и средний бизнес | H46: МСБ.3
C47: Кассовые операции | E47: Безбумажный офис | F47: РКО | G47: Малый и средний бизнес | H47: МСБ.3
C48: Валютные операции | E48: Безбумажный офис | F48: РКО | G48: Малый и средний бизнес | H48: МСБ.3
E49: DCB Бизнес | F49: РКО | G49: Малый и средний бизнес | H49: МСБ.3
C50: Сейфовые ячейки | E50: Безбумажный офис | F50: РКО | G50: Малый и средний бизнес | H50: МСБ.3
C51: Зарплатный проект | E51: Безбумажный офис | F51: РКО | G51: Малый и средний бизнес | H51: МСБ.3
C52: Торговый эквайринг | E52: Безбумажный офис | F52: РКО | G52: Малый и средний бизнес | H52: МСБ.3
C53: Элкарт Бизнес | E53: Безбумажный офис | F53: Выпуск и обслуживание банковских карт | G53: Малый и средний бизнес | H53: МСБ.3
E54: DCB Бизнес | F54: Выпуск и обслуживание банковских карт | G54: Малый и средний бизнес | H54: МСБ.3
C55: Продажа карт | E55: Безбумажный офис | F55: Обслуживание проекта Симбанк | G55: Сервисная модель | H55: Симбанк
C56: Выдача карт | E56: Безбумажный офис | F56: Обслуживание проекта Симбанк | G56: Сервисная модель | H56: Симбанк
C57: Прием погашений | E57: Безбумажный офис | F57: Обслуживание проекта Симбанк | G57: Сервисная модель | H57: Симбанк
C58: Снятие наличных | E58: Безбумажный офис | F58: Обслуживание проекта Симбанк | G58: Сервисная модель | H58: Симбанк
C59: Коллекторские услуги | E59: Безбумажный офис | F59: Обслуживание проекта Симбанк | G59: Сервисная модель | H59: Симбанк
E60: Безбумажный офис | F60: Обслуживание проекта Симбанк | G60: Сервисная модель | H60: Симбанк
C61: Выдача денежных переводов | E61: Безбумажный офис | F61: Обслуживание проекта Симбанк | G61: Сервисная модель | H61: Симбанк
E62: Безбумажный офис | F62: Обслуживание проекта Симбанк | G62: Сервисная модель | H62: Симбанк
C63: Продажа страховых полисов | E63: Безбумажный офис | F63: Партнеры | G63: Сервисная модель | H63: Партнеры
C64: Субаренда | E64: Безбумажный офис | F64: Партнеры | G64: Сервисная модель | H64: Партнеры

Sheet 0
A1: Параметры модели
D4: 46023 | E4: 46054 | F4: 46082 | G4: 46113 | H4: 46143 | I4: 46174 | J4: 46204 | K4: 46235 | L4: 46266 | M4: 46296 | N4: 46327 | O4: 46357 | P4: 46388 | Q4: 46419 | R4: 46447 | S4: 46478 | T4: 46508 | U4: 46539 | V4: 46569 | W4: 46600 | X4: 46631 | Y4: 46661 | Z4: 46692 | AA4: 46722 | AB4: 46753 | AC4: 46784 | AD4: 46813 | AE4: 46844 | AF4: 46874 | AG4: 46905 | AH4: 46935 | AI4: 46966 | AJ4: 46997 | AK4: 47027 | AL4: 47058 | AM4: 47088 | AO4: =YEAR(O4) -> 2026 | AP4: =YEAR(AA4) -> 2027 | AQ4: =YEAR(AM4) -> 2028
D5: m1 | E5: m2 | F5: m3 | G5: m4 | H5: m5 | I5: m6 | J5: m7 | K5: m8 | L5: m9 | M5: m10 | N5: m11 | O5: m12 | P5: m13 | Q5: m14 | R5: m15 | S5: m16 | T5: m17 | U5: m18 | V5: m19 | W5: m20 | X5: m21 | Y5: m22 | Z5: m23 | AA5: m24 | AB5: m25 | AC5: m26 | AD5: m27 | AE5: m28 | AF5: m29 | AG5: m30 | AH5: m31 | AI5: m32 | AJ5: m33 | AK5: m34 | AL5: m35 | AM5: m36 | AO5: Y1 | AP5: Y2 | AQ5: Y3
D6: 1 | E6: =D6+1 -> 2 | F6: =E6+1 -> 3 | G6: =F6+1 -> 4 | H6: =G6+1 -> 5 | I6: =H6+1 -> 6 | J6: =I6+1 -> 7 | K6: =J6+1 -> 8 | L6: =K6+1 -> 9 | ... AM6: =AL6+1 -> 36
A8: Показатель | B8: ЕИ | C8: Отв.исп.
A9: количество филиалов | D9: 10 | E9: 10 | F9: 10 | G9: 10 | H9: 10 | I9: 10 | J9: 10 | K9: 10 | L9: 10 | M9: 10 | N9: 10 | O9: 10 | P9: 10 | Q9: 10 | R9: 10 | S9: 10 | T9: 10 | U9: 10 | V9: 10 | W9: 10 | X9: 10 | Y9: 10 | Z9: 10 | AA9: 10 | AB9: 10 | AC9: 10 | AD9: 10 | AE9: 10 | AF9: 10 | AG9: 10 | AH9: 10 | AI9: 10 | AJ9: 10 | AK9: 10 | AL9: 10 | AM9: 10 | AO9: =O9 -> 10 | AP9: =AA9 -> 10 | AQ9: =AM9 -> 10
A10: количество клиентов, в т.ч.: | D10: =SUM(D11:D13) -> 0 | E10: =SUM(E11:E13) -> 0 | F10: =SUM(F11:F13) -> 0 | G10: =SUM(G11:G13) -> 0 | H10: =SUM(H11:H13) -> 0 | I10: =SUM(I11:I13) -> 0 | J10: =SUM(J11:J13) -> 0 | K10: =SUM(K11:K13) -> 0 | ... AM10: =SUM(AM11:AM13) -> 0
A11: ЮЛ
A12: ИП
A13: ФЛ
A14: количество кредитных специалистов | D14: 130 | E14: =D14*(1-5.5%) -> 122.85 | F14: =E14*(1-5.5%) -> 116.09325 | G14: =F14*(1-5.5%) -> 109.70812 | H14: =G14*(1-5.5%) -> 103.67417 | I14: =H14*(1-5.5%) -> 97.972095 | J14: =I14*(1-5.5%) -> 92.58363 | K14: =J14*(1-5.5%) -> 87.49153 | L14: =K14*(1-5.5%) -> 82.679496 | M14: 80 | N14: 80 | O14: 80 | P14: =O14 -> 80 | Q14: =P14 -> 80 | R14: =Q14 -> 80 | S14: =R14 -> 80 | T14: =S14 -> 80 | U14: =T14 -> 80 | V14: =U14 -> 80 | W14: =V14 -> 80 | ... AM14: =AL14 -> 80 | AO14: =O14 -> 80 | AP14: =AA14 -> 80 | AQ14: =AM14 -> 80
A15: курсы валют
A16: RUB | C16: 1.1233 | D16: 1.01 | E16: 1.01 | F16: 1.01 | G16: 1.01 | H16: 1.01 | I16: 1 | J16: 1 | K16: 1 | L16: 1 | M16: 1 | N16: 1 | O16: 1 | P16: 1 | Q16: 1 | R16: 0.97 | S16: 0.97 | T16: 0.97 | U16: 0.97 | V16: 0.97 | W16: 0.97 | X16: 0.97 | Y16: 0.97 | Z16: 0.97 | AA16: 0.97 | AB16: 0.97 | AC16: 0.97 | AD16: 0.97 | AE16: 0.97 | AF16: 0.97 | AG16: 0.97 | AH16: 0.97 | AI16: 0.97 | AJ16: 0.97 | AK16: 0.97 | AL16: 0.97 | AM16: 0.97
A17: USD | C17: 87.4177 | D17: 87.45 | E17: 87.45 | F17: 87.45 | G17: 87.45 | H17: 87.45 | I17: 87.45 | J17: 87.45 | K17: 87.45 | L17: 87.45 | M17: 87.45 | N17: 87.45 | O17: 87.45 | P17: 87.45 | Q17: 87.45 | R17: 87.45 | S17: 87.45 | T17: 87.45 | U17: 87.45 | V17: 87.45 | W17: 87.45 | X17: 87.45 | Y17: 87.45 | Z17: 87.45 | AA17: 87.45 | AB17: 87.45 | AC17: 87.45 | AD17: 87.45 | AE17: 87.45 | AF17: 87.45 | AG17: 87.45 | AH17: 87.45 | AI17: 87.45 | AJ17: 87.45 | AK17: 87.45 | AL17: 87.45 | AM17: 87.45
A18: EUR | C18: 102.86 | D18: 101 | E18: 101 | F18: 101 | G18: 101 | H18: 101 | I18: 101 | J18: 101 | K18: 101 | L18: 101 | M18: 101 | N18: 101 | O18: 101 | P18: 101 | Q18: 101 | R18: 101 | S18: 101 | T18: 101 | U18: 101 | V18: 101 | W18: 101 | X18: 101 | Y18: 101 | Z18: 101 | AA18: 101 | AB18: 101 | AC18: 101 | AD18: 101 | AE18: 101 | AF18: 101 | AG18: 101 | AH18: 101 | AI18: 101 | AJ18: 101 | AK18: 101 | AL18: 101 | AM18: 101
A19: KZT | C19: 0.1739 | D19: 0.17 | E19: 0.17 | F19: 0.17 | G19: 0.17 | H19: 0.17 | I19: 0.17 | J19: 0.17 | K19: 0.17 | L19: 0.17 | M19: 0.17 | N19: 0.17 | O19: 0.17 | P19: 0.17 | Q19: 0.17 | R19: 0.17 | S19: 0.17 | T19: 0.17 | U19: 0.17 | V19: 0.17 | W19: 0.17 | X19: 0.17 | Y19: 0.17 | Z19: 0.17 | AA19: 0.17 | AB19: 0.17 | AC19: 0.17 | AD19: 0.17 | AE19: 0.17 | AF19: 0.17 | AG19: 0.17 | AH19: 0.17 | AI19: 0.17 | AJ19: 0.17 | AK19: 0.17 | AL19: 0.17 | AM19: 0.17
A20: курсы валют
A21: RUB | D21: 1.01 | E21: 1.01 | F21: 1.01 | G21: 1.01 | H21: 1.01 | I21: 1 | J21: 1 | K21: 1 | L21: 1 | M21: 1 | N21: 1 | O21: 1 | P21: 1 | Q21: 1 | R21: 0.97 | S21: 0.97 | T21: 0.97 | U21: 0.97 | V21: 0.97 | W21: 0.97 | X21: 0.97 | Y21: 0.97 | Z21: 0.97 | AA21: 0.97 | AB21: 0.97 | AC21: 0.97 | AD21: 0.97 | AE21: 0.97 | AF21: 0.97 | AG21: 0.97 | AH21: 0.97 | AI21: 0.97 | AJ21: 0.97 | AK21: 0.97 | AL21: 0.97 | AM21: 0.97
A22: USD | D22: 87.45 | E22: 87.45 | F22: 87.45 | G22: 87.45 | H22: 87.45 | I22: 87.45 | J22: 87.45 | K22: 87.45 | L22: 87.45 | M22: 87.45 | N22: 87.45 | O22: 87.45 | P22: 87.45 | Q22: 87.45 | R22: 87.45 | S22: 87.45 | T22: 87.45 | U22: 87.45 | V22: 87.45 | W22: 87.45 | X22: 87.45 | Y22: 87.45 | Z22: 87.45 | AA22: 87.45 | AB22: 87.45 | AC22: 87.45 | AD22: 87.45 | AE22: 87.45 | AF22: 87.45 | AG22: 87.45 | AH22: 87.45 | AI22: 87.45 | AJ22: 87.45 | AK22: 87.45 | AL22: 87.45 | AM22: 87.45
A23: средний ФОТ специалистов
A24: кред.специалист (филиал) | B24: Фил | D24: 40000 | E24: 40000 | F24: 40000 | G24: 40000 | H24: 40000 | I24: 40000 | J24: 40000 | K24: 40000 | L24: 40000 | M24: 40000 | N24: 40000 | O24: 40000 | P24: 40000 | Q24: 40000 | R24: 40000 | S24: 40000 | T24: 40000 | U24: 40000 | V24: 40000 | W24: 40000 | X24: 40000 | Y24: 40000 | Z24: 40000 | AA24: 40000 | AB24: 40000 | AC24: 40000 | AD24: 40000 | AE24: 40000 | AF24: 40000 | AG24: 40000 | AH24: 40000 | AI24: 40000 | AJ24: 40000 | AK24: 40000 | AL24: 40000 | AM24: 40000
A25: нач.кред.отдела (филиал) | B25: Фил | D25: 60000 | E25: 60000 | F25: 60000 | G25: 60000 | H25: 60000 | I25: 60000 | J25: 60000 | K25: 60000 | L25: 60000 | M25: 60000 | N25: 60000 | O25: 60000 | P25: 60000 | Q25: 60000 | R25: 60000 | S25: 60000 | T25: 60000 | U25: 60000 | V25: 60000 | W25: 60000 | X25: 60000 | Y25: 60000 | Z25: 60000 | AA25: 60000 | AB25: 60000 | AC25: 60000 | AD25: 60000 | AE25: 60000 | AF25: 60000 | AG25: 60000 | AH25: 60000 | AI25: 60000 | AJ25: 60000 | AK25: 60000 | AL25: 60000 | AM25: 60000
A26: кред.администратор | B26: Фил | D26: 45000 | E26: 45000 | F26: 45000 | G26: 45000 | H26: 45000 | I26: 45000 | J26: 45000 | K26: 45000 | L26: 45000 | M26: 45000 | N26: 45000 | O26: 45000 | P26: 45000 | Q26: 45000 | R26: 45000 | S26: 45000 | T26: 45000 | U26: 45000 | V26: 45000 | W26: 45000 | X26: 45000 | Y26: 45000 | Z26: 45000 | AA26: 45000 | AB26: 45000 | AC26: 45000 | AD26: 45000 | AE26: 45000 | AF26: 45000 | AG26: 45000 | AH26: 45000 | AI26: 45000 | AJ26: 45000 | AK26: 45000 | AL26: 45000 | AM26: 45000
A27: бухгалтер | B27: Фил | D27: 45000 | E27: 45000 | F27: 45000 | G27: 45000 | H27: 45000 | I27: 45000 | J27: 45000 | K27: 45000 | L27: 45000 | M27: 45000 | N27: 45000 | O27: 45000 | P27: 45000 | Q27: 45000 | R27: 45000 | S27: 45000 | T27: 45000 | U27: 45000 | V27: 45000 | W27: 45000 | X27: 45000 | Y27: 45000 | Z27: 45000 | AA27: 45000 | AB27: 45000 | AC27: 45000 | AD27: 45000 | AE27: 45000 | AF27: 45000 | AG27: 45000 | AH27: 45000 | AI27: 45000 | AJ27: 45000 | AK27: 45000 | AL27: 45000 | AM27: 45000
A28: кассир | B28: Фил | D28: 45000 | E28: 45000 | F28: 45000 | G28: 45000 | H28: 45000 | I28: 45000 | J28: 45000 | K28: 45000 | L28: 45000 | M28: 45000 | N28: 45000 | O28: 45000 | P28: 45000 | Q28: 45000 | R28: 45000 | S28: 45000 | T28: 45000 | U28: 45000 | V28: 45000 | W28: 45000 | X28: 45000 | Y28: 45000 | Z28: 45000 | AA28: 45000 | AB28: 45000 | AC28: 45000 | AD28: 45000 | AE28: 45000 | AF28: 45000 | AG28: 45000 | AH28: 45000 | AI28: 45000 | AJ28: 45000 | AK28: 45000 | AL28: 45000 | AM28: 45000
A29: коллектор | B29: ГО | D29: 35000 | E29: 35000 | F29: 35000 | G29: 35000 | H29: 35000 | I29: 35000 | J29: 35000 | K29: 35000 | L29: 35000 | M29: 35000 | N29: 35000 | O29: 35000 | P29: 35000 | Q29: 35000 | R29: 35000 | S29: 35000 | T29: 35000 | U29: 35000 | V29: 35000 | W29: 35000 | X29: 35000 | Y29: 35000 | Z29: 35000 | AA29: 35000 | AB29: 35000 | AC29: 35000 | AD29: 35000 | AE29: 35000 | AF29: 35000 | AG29: 35000 | AH29: 35000 | AI29: 35000 | AJ29: 35000 | AK29: 35000 | AL29: 35000 | AM29: 35000
A30: операционист | B30: Фил | D30: 25000 | E30: 25000 | F30: 25000 | G30: 25000 | H30: 25000 | I30: 25000 | J30: 25000 | K30: 25000 | L30: 25000 | M30: 25000 | N30: 25000 | O30: 25000 | P30: 25000 | Q30: 25000 | R30: 25000 | S30: 25000 | T30: 25000 | U30: 25000 | V30: 25000 | W30: 25000 | X30: 25000 | Y30: 25000 | Z30: 25000 | AA30: 25000 | AB30: 25000 | AC30: 25000 | AD30: 25000 | AE30: 25000 | AF30: 25000 | AG30: 25000 | AH30: 25000 | AI30: 25000 | AJ30: 25000 | AK30: 25000 | AL30: 25000 | AM30: 25000
A31: верификатор | B31: Фил | D31: 45000 | E31: 45000 | F31: 45000 | G31: 45000 | H31: 45000 | I31: 45000 | J31: 45000 | K31: 45000 | L31: 45000 | M31: 45000 | N31: 45000 | O31: 45000 | P31: 45000 | Q31: 45000 | R31: 45000 | S31: 45000 | T31: 45000 | U31: 45000 | V31: 45000 | W31: 45000 | X31: 45000 | Y31: 45000 | Z31: 45000 | AA31: 45000 | AB31: 45000 | AC31: 45000 | AD31: 45000 | AE31: 45000 | AF31: 45000 | AG31: 45000 | AH31: 45000 | AI31: 45000 | AJ31: 45000 | AK31: 45000 | AL31: 45000 | AM31: 45000
A32: специалист отдела БК | B32: ГО | D32: 35000 | E32: 35000 | F32: 35000 | G32: 35000 | H32: 35000 | I32: 35000 | J32: 35000 | K32: 35000 | L32: 35000 | M32: 35000 | N32: 35000 | O32: 35000 | P32: 35000 | Q32: 35000 | R32: 35000 | S32: 35000 | T32: 35000 | U32: 35000 | V32: 35000 | W32: 35000 | X32: 35000 | Y32: 35000 | Z32: 35000 | AA32: 35000 | AB32: 35000 | AC32: 35000 | AD32: 35000 | AE32: 35000 | AF32: 35000 | AG32: 35000 | AH32: 35000 | AI32: 35000 | AJ32: 35000 | AK32: 35000 | AL32: 35000 | AM32: 35000
A33: курьер | B33: ГО | D33: 25000 | E33: 25000 | F33: 25000 | G33: 25000 | H33: 25000 | I33: 25000 | J33: 25000 | K33: 25000 | L33: 25000 | M33: 25000 | N33: 25000 | O33: 25000 | P33: 25000 | Q33: 25000 | R33: 25000 | S33: 25000 | T33: 25000 | U33: 25000 | V33: 25000 | W33: 25000 | X33: 25000 | Y33: 25000 | Z33: 25000 | AA33: 25000 | AB33: 25000 | AC33: 25000 | AD33: 25000 | AE33: 25000 | AF33: 25000 | AG33: 25000 | AH33: 25000 | AI33: 25000 | AJ33: 25000 | AK33: 25000 | AL33: 25000 | AM33: 25000
A34: комплайнс | B34: ГО | D34: 45000 | E34: 45000 | F34: 45000 | G34: 45000 | H34: 45000 | I34: 45000 | J34: 45000 | K34: 45000 | L34: 45000 | M34: 45000 | N34: 45000 | O34: 45000 | P34: 45000 | Q34: 45000 | R34: 45000 | S34: 45000 | T34: 45000 | U34: 45000 | V34: 45000 | W34: 45000 | X34: 45000 | Y34: 45000 | Z34: 45000 | AA34: 45000 | AB34: 45000 | AC34: 45000 | AD34: 45000 | AE34: 45000 | AF34: 45000 | AG34: 45000 | AH34: 45000 | AI34: 45000 | AJ34: 45000 | AK34: 45000 | AL34: 45000 | AM34: 45000
A35: бэк-офис | B35: ГО | D35: 45000 | E35: 45000 | F35: 45000 | G35: 45000 | H35: 45000 | I35: 45000 | J35: 45000 | K35: 45000 | L35: 45000 | M35: 45000 | N35: 45000 | O35: 45000 | P35: 45000 | Q35: 45000 | R35: 45000 | S35: 45000 | T35: 45000 | U35: 45000 | V35: 45000 | W35: 45000 | X35: 45000 | Y35: 45000 | Z35: 45000 | AA35: 45000 | AB35: 45000 | AC35: 45000 | AD35: 45000 | AE35: 45000 | AF35: 45000 | AG35: 45000 | AH35: 45000 | AI35: 45000 | AJ35: 45000 | AK35: 45000 | AL35: 45000 | AM35: 45000
... A43: юрист | B43: Фил | D43: 30000 | E43: 30000 | F43: 30000 | G43: 30000 | H43: 30000 | I43: 30000 | J43: 30000 | K43: 30000 | L43: 30000 | M43: 30000 | N43: 30000 | O43: 30000 | P43: 30000 | Q43: 30000 | R43: 30000 | S43: 30000 | T43: 30000 | U43: 30000 | V43: 30000 | W43: 30000 | X43: 30000 | Y43: 30000 | Z43: 30000 | AA43: 30000 | AB43: 30000 | AC43: 30000 | AD43: 30000 | AE43: 30000 | AF43: 30000 | AG43: 30000 | AH43: 30000 | AI43: 30000 | AJ43: 30000 | AK43: 30000 | AL43: 30000 | AM43: 30000

Sheet РБ>>>
F5: Розничный бизнес
F7: РБ.1 | G7: Кредиты
F8: РБ.2 | G8: Счета и депозиты
F9: РБ.3 | G9: Обслуживание клиентов

Sheet РБ.1
A1: Розничный бизнес - Кредиты
D3: 46023 | E3: 46054 | F3: 46082 | G3: 46113 | H3: 46143 | I3: 46174 | J3: 46204 | K3: 46235 | L3: 46266 | M3: 46296 | N3: 46327 | O3: 46357 | P3: 46388 | Q3: 46419 | R3: 46447 | S3: 46478 | T3: 46508 | U3: 46539 | V3: 46569 | W3: 46600 | X3: 46631 | Y3: 46661 | Z3: 46692 | AA3: 46722 | AB3: 46753 | AC3: 46784 | AD3: 46813 | AE3: 46844 | AF3: 46874 | AG3: 46905 | AH3: 46935 | AI3: 46966 | AJ3: 46997 | AK3: 47027 | AL3: 47058 | AM3: 47088 | AO3: =YEAR(O3) -> 2026 | AP3: =YEAR(AA3) -> 2027 | AQ3: =YEAR(AM3) -> 2028
D4: m1 | E4: m2 | F4: m3 | G4: m4 | H4: m5 | I4: m6 | J4: m7 | K4: m8 | L4: m9 | M4: m10 | N4: m11 | O4: m12 | P4: m13 | Q4: m14 | R4: m15 | S4: m16 | T4: m17 | U4: m18 | V4: m19 | W4: m20 | X4: m21 | Y4: m22 | Z4: m23 | AA4: m24 | AB4: m25 | AC4: m26 | AD4: m27 | AE4: m28 | AF4: m29 | AG4: m30 | AH4: m31 | AI4: m32 | AJ4: m33 | AK4: m34 | AL4: m35 | AM4: m36 | AO4: Y1 | AP4: Y2 | AQ4: Y3
D5: 1 | E5: =D5+1 -> 2 | F5: =E5+1 -> 3 | G5: =F5+1 -> 4 | H5: =G5+1 -> 5 | I5: =H5+1 -> 6 | J5: =I5+1 -> 7 | K5: =J5+1 -> 8 | L5: =K5+1 -> 9 | ... AM5: =AL5+1 -> 36
A7: сезонность | B7: % | D7: 0.4 | E7: 0.8 | F7: 1 | G7: 1 | H7: 0.4 | I7: 1 | J7: 1 | K7: 0.7 | L7: 1 | M7: 1 | N7: 0.9 | O7: 0.8 | P7: 0.4 | Q7: 0.8 | R7: 1 | S7: 1 | T7: 0.4 | U7: 1 | V7: 1 | W7: 0.7 | X7: 1 | Y7: 1 | Z7: 0.9 | AA7: 0.8 | AB7: 0.4 | AC7: 0.8 | AD7: 1 | AE7: 1 | AF7: 0.4 | AG7: 1 | AH7: 1 | AI7: 0.7 | AJ7: 1 | AK7: 1 | AL7: 0.9 | AM7: 0.8
A8: Итого
A9: количество заявок | B9: шт | D9: =D53+D165+D235+D289 -> 409.5 | E9: =E53+E165+E235+E289 -> 644.9625 | F9: =F53+F165+F235+F289 -> 761.86195 | G9: =G53+G165+G235+G289 -> 760.75725 | H9: =H53+H165+H235+H289 -> 287.43794 | I9: =I53+I165+I235+I289 -> 678.77207 | J9: =J53+J165+J235+J289 -> 641.15888 | K9: =K53+K165+K235+K289 -> 597.12969 | ... AM9: =AM53+AM165+AM235+AM289 -> 684 | AO9: =SUM(D9:O9) -> 7671.5831 | AP9: =SUM(P9:AA9) -> 8020 | AQ9: =SUM(AB9:AM9) -> 8490
A10: количество кредитных специалистов | B10: чел | D10: ='0'!D14 -> 130 | E10: ='0'!E14 -> 122.85 | F10: ='0'!F14 -> 116.09325 | G10: ='0'!G14 -> 109.70812 | H10: ='0'!H14 -> 103.67417 | I10: ='0'!I14 -> 97.972095 | J10: ='0'!J14 -> 92.58363 | K10: ='0'!K14 -> 87.49153 | ... AM10: ='0'!AM14 -> 80
A11: количество заявок на 1 специалиста | B11: шт | D11: =D9/D10 -> 3.15 | E11: =E9/E10 -> 5.25 | F11: =F9/F10 -> 6.5625 | G11: =G9/G10 -> 6.934375 | H11: =H9/H10 -> 2.7725125 | I11: =I9/I10 -> 6.9282184 | J11: =J9/J10 -> 6.9251863 | K11: =K9/K10 -> 6.825 | ... AM11: =AM9/AM10 -> 8.55
A12: выдачи | B12: тыс сом | D12: =D57+D117+D169+D239+D293 -> 54632.5 | E12: =E57+E117+E169+E239+E293 -> 63567.504 | F12: =F57+F117+F169+F239+F293 -> 75008.661 | G12: =G57+G117+G169+G239+G293 -> 91920.784 | H12: =H57+H117+H169+H239+H293 -> 34690.565 | I12: =I57+I117+I169+I239+I293 -> 81827.972 | J12: =J57+J117+J169+J239+J293 -> 77208.428 | K12: =K57+K117+K169+K239+K293 -> 107133.86 | ... AM12: =AM57+AM117+AM169+AM239+AM293 -> 147674.44 | AO12: =SUM(D12:O12) -> 1094810.7 | AP12: =SUM(P12:AA12) -> 1507165.2 | AQ12: =SUM(AB12:AM12) -> 1812602.9
A13: погашения | B13: тыс сом | D13: =D59+D84*'0'!D17+D119+D171+D241+D295 -> 392788.71 | E13: =E59+E84*'0'!E17+E119+E171+E241+E295 -> 391066.53 | F13: =F59+F84*'0'!F17+F119+F171+F241+F295 -> 389988.05 | G13: =G59+G84*'0'!G17+G119+G171+G241+G295 -> 389159.12 | H13: =H59+H84*'0'!H17+H119+H171+H241+H295 -> 388154.03 | I13: =I59+I84*'0'!I17+I119+I171+I241+I295 -> 383953.97 | J13: =J59+J84*'0'!J17+J119+J171+J241+J295 -> 373597.7 | K13: =K59+K84*'0'!K17+K119+K171+K241+K295 -> 363457.06 | ... AM13: =AM59+AM84*'0'!AM17+AM119+AM171+AM241+AM295 -> 241857.18 | AO13: =SUM(D13:O13) -> 4455010.3 | AP13: =SUM(P13:AA13) -> 3432754.3 | AQ13: =SUM(AB13:AM13) -> 2975417.2
A14: кредитный портфель | B14: тыс сом | C14: =C28+C172+C201+C220+C296 -> 5685987.9 | D14: =D28+D172+D201+D220+D296 -> 5527478.6 | E14: =E28+E172+E201+E220+E296 -> 5376030.3 | F14: =F28+F172+F201+F220+F296 -> 5233580.6 | G14: =G28+G172+G201+G220+G296 -> 5105421.4 | H14: =H28+H172+H201+H220+H296 -> 4917655.5 | I14: =I28+I172+I201+I220+I296 -> 4777913.1 | J14: =J28+J172+J201+J220+J296 -> 4640659.7 | ... AM14: =AM28+AM172+AM201+AM220+AM296 -> 3879261.2 | AO14: =O14 -> 4259504.8 | AP14: =AA14 -> 3851332.9 | AQ14: =AM14 -> 3879261.2
A15: просроченная задолженность | B15: тыс сом | D15: =D29+D174+D203+D221+D298 -> 48122.61 | E15: =E29+E174+E203+E221+E298 -> 46738.663 | F15: =F29+F174+F203+F221+F298 -> 45449.791 | G15: =G29+G174+G203+G221+G298 -> 44173.379 | H15: =H29+H174+H203+H221+H298 -> 42319.441 | I15: =I29+I174+I203+I221+I298 -> 40923.175 | J15: =J29+J174+J203+J221+J298 -> 39556.849 | K15: =K29+K174+K203+K221+K298 -> 38621.409 | ... AM15: =AM29+AM174+AM203+AM221+AM298 -> 34510.057 | AO15: =O15 -> 36103.132 | AP15: =AA15 -> 33100.204 | AQ15: =AM15 -> 34510.057
A16: РППУ на конец месяца | B16: тыс сом | D16: =D30+D179+D208+D222+D303 -> -180176.5 | E16: =E30+E179+E208+E222+E303 -> -173027.53 | F16: =F30+F179+F208+F222+F303 -> -166079.33 | G16: =G30+G179+G208+G222+G303 -> -159707.08 | H16: =H30+H179+H208+H222+H303 -> -152225.47 | I16: =I30+I179+I208+I222+I303 -> -145741.96 | J16: =J30+J179+J208+J222+J303 -> -139527.34 | K16: =K30+K179+K208+K222+K303 -> -135145.82 | ... AM16: =AM30+AM179+AM208+AM222+AM303 -> -119122.93 | AO16: =O16 -> -121758.11 | AP16: =AA16 -> -115906.67 | AQ16: =AM16 -> -119122.93
A17: % доход | B17: тыс сом | D17: =D31+D180+D209+D223+D304 -> 109670.06 | E17: =E31+E180+E209+E223+E304 -> 106890.47 | F17: =F31+F180+F209+F223+F304 -> 104308.46 | G17: =G31+G180+G209+G223+G304 -> 101934.03 | H17: =H31+H180+H209+H223+H304 -> 99047.58 | I17: =I31+I180+I209+I223+I304 -> 96034.878 | J17: =J31+J180+J209+J223+J304 -> 93544.204 | K17: =K31+K180+K209+K223+K304 -> 91426.291 | ... AM17: =AM31+AM180+AM209+AM223+AM304 -> 79677.03 | AO17: =SUM(D17:O17) -> 1156614.5 | AP17: =SUM(P17:AA17) -> 972895.92 | AQ17: =SUM(AB17:AM17) -> 939147.16
A18: трансфертный расход | B18: тыс сом | D18: =D32+D181+D210+D224+D305 -> -70017.426 | E18: =E32+E181+E210+E224+E305 -> -68081.506 | F18: =F32+F181+F210+F224+F305 -> -66245.952 | G18: =G32+G181+G210+G224+G305 -> -64555.929 | H18: =H32+H181+H210+H224+H305 -> -62582.654 | I18: =I32+I181+I210+I224+I305 -> -60536.958 | J18: =J32+J181+J210+J224+J305 -> -58806.942 | K18: =K32+K181+K210+K224+K305 -> -57322.979 | ... AM18: =AM32+AM181+AM210+AM224+AM305 -> -48492.879 | AO18: =SUM(D18:O18) -> -728436.13 | AP18: =SUM(P18:AA18) -> -594559.87 | AQ18: =SUM(AB18:AM18) -> -571188.68
A19: расходы на провизии | B19: тыс сом | D19: =D33+D182+D211+D225+D306 -> 15693.32 | E19: =E33+E182+E211+E225+E306 -> 7148.9765 | F19: =F33+F182+F211+F225+F306 -> 6948.1988 | G19: =G33+G182+G211+G225+G306 -> 6372.2512 | H19: =H33+H182+H211+H225+H306 -> 7481.6099 | I19: =I33+I182+I211+I225+I306 -> 6483.5012 | J19: =J33+J182+J211+J225+J306 -> 6214.6232 | K19: =K33+K182+K211+K225+K306 -> 4381.5239 | ... AM19: =AM33+AM182+AM211+AM225+AM306 -> -7.4729162 | AO19: =SUM(D19:O19) -> 74111.708 | AP19: =SUM(P19:AA19) -> 5851.4416 | AQ19: =SUM(AB19:AM19) -> -3216.2606
A20: комиссии | B20: тыс сом | D20: =D34+D183+D212+D226+D307 -> 0 | E20: =E34+E183+E212+E226+E307 -> 0 | F20: =F34+F183+F212+F226+F307 -> 0 | G20: =G34+G183+G212+G226+G307 -> 0 | H20: =H34+H183+H212+H226+H307 -> 0 | I20: =I34+I183+I212+I226+I307 -> 0 | J20: =J34+J183+J212+J226+J307 -> 0 | K20: =K34+K183+K212+K226+K307 -> 0 | ... AM20: =AM34+AM183+AM212+AM226+AM307 -> 0 | AO20: =SUM(D20:O20) -> 0 | AP20: =SUM(P20:AA20) -> 0 | AQ20: =SUM(AB20:AM20) -> 0
A21: операционные доходы | B21: тыс сом | D21: =D35+D184+D213+D227+D308 -> 55345.955 | E21: =E35+E184+E213+E227+E308 -> 45957.944 | F21: =F35+F184+F213+F227+F308 -> 45010.71 | G21: =G35+G184+G213+G227+G308 -> 43750.351 | H21: =H35+H184+H213+H227+H308 -> 43946.536 | I21: =I35+I184+I213+I227+I308 -> 41981.421 | J21: =J35+J184+J213+J227+J308 -> 40951.885 | K21: =K35+K184+K213+K227+K308 -> 38484.836 | ... AM21: =AM35+AM184+AM213+AM227+AM308 -> 31176.679 | AO21: =SUM(D21:O21) -> 502290.09 | AP21: =SUM(P21:AA21) -> 384187.49 | AQ21: =SUM(AB21:AM21) -> 364742.22
A22: операционные расходы | B22: тыс сом | D22: =D36+D185+D214+D228+D309 -> -803.65559 | E22: =E36+E185+E214+E228+E309 -> -999.82289 | F22: =F36+F185+F214+F228+F309 -> -1094.9488 | G22: =G36+G185+G214+G228+G309 -> -1089.4638 | H22: =H36+H185+H214+H228+H309 -> -678.92394 | I22: =I36+I185+I214+I228+I309 -> -999.89602 | J22: =J36+J185+J214+J228+J309 -> -962.0376 | K22: =K36+K185+K214+K228+K309 -> -835.15488 | ... AM22: =AM36+AM185+AM214+AM228+AM309 -> -886.25094 | AO22: =SUM(D22:O22) -> -11198.644 | AP22: =SUM(P22:AA22) -> -10487.985 | AQ22: =SUM(AB22:AM22) -> -10792.926
A23: прибыль | B23: тыс сом | D23: =D37+D186+D215+D229+D310 -> 54542.299 | E23: =E37+E186+E215+E229+E310 -> 44958.122 | F23: =F37+F186+F215+F229+F310 -> 43915.761 | G23: =G37+G186+G215+G229+G310 -> 42660.887 | H23: =H37+H186+H215+H229+H310 -> 43267.612 | I23: =I37+I186+I215+I229+I310 -> 40981.525 | J23: =J37+J186+J215+J229+J310 -> 39989.847 | K23: =K37+K186+K215+K229+K310 -> 37649.681 | ... AM23: =AM37+AM186+AM215+AM229+AM310 -> 30290.428 | AO23: =SUM(D23:O23) -> 491091.44 | AP23: =SUM(P23:AA23) -> 373699.5 | AQ23: =SUM(AB23:AM23) -> 353949.29
A25: Потребительский кредит
A26: Итого
A27: количество кредитов | B27: шт | D27: =D39+D101 -> 9409 | E27: =E39+E101 -> 9022 | F27: =F39+F101 -> 8634 | G27: =G39+G101 -> 8243 | H27: =H39+H101 -> 7839 | I27: =I39+I101 -> 7444 | J27: =J39+J101 -> 7068 | K27: =K39+K101 -> 4670 | ... AM27: =AM39+AM101 -> 3560 | AO27: =O27 -> 4211 | AP27: =AA27 -> 3671 | AQ27: =AM27 -> 3560
A28: кредитный портфель | B28: тыс сом | C28: =C40+C102 -> 3770987.9 | D28: =D40+D102 -> 3628621.3 | E28: =E40+E102 -> 3476492.3 | F28: =F40+F102 -> 3324180.2 | G28: =G40+G102 -> 3170250.9 | H28: =H40+H102 -> 3011065.7 | I28: =I40+I102 -> 2855528.7 | J28: =J40+J102 -> 2707894.6 | ... AM28: =AM40+AM102 -> 2203541.7 | AO28: =O28 -> 2360876.5 | AP28: =AA28 -> 2072616.9 | AQ28: =AM28 -> 2203541.7
A29: просроченная задолженность | B29: тыс сом | D29: =D41+D103 -> 39300.794 | E29: =E41+E103 -> 37651.021 | F29: =F41+F103 -> 35999.222 | G29: =G41+G103 -> 34329.826 | H29: =H41+H103 -> 32603.331 | I29: =I41+I103 -> 30916.409 | J29: =J41+J103 -> 29315.253 | K29: =K41+K103 -> 28387.433 | ... AM29: =AM41+AM103 -> 23876.997 | AO29: =O29 -> 25555.771 | AP29: =AA29 -> 22442.586 | AQ29: =AM29 -> 23876.997
A30: РППУ на конец месяца | B30: тыс сом | D30: =D42+D104 -> -142466.61 | E30: =E42+E104 -> -135803.5 | F30: =F42+F104 -> -129194.12 | G30: =G42+G104 -> -122583.2 | H30: =H42+H104 -> -115831.92 | I30: =I42+I104 -> -109283.75 | J30: =J42+J104 -> -103098.24 | K30: =K42+K104 -> -99186.686 | ... AM30: =AM42+AM104 -> -86497.895 | AO30: =O30 -> -86948.494 | AP30: =AA30 -> -81383.596 | AQ30: =AM30 -> -86497.895
A31: % доход | B31: тыс сом | D31: =D43+D105 -> 73965.676 | E31: =E43+E105 -> 71020.1 | F31: =F43+F105 -> 67974.983 | G31: =G43+G105 -> 64911.812 | H31: =H43+H105 -> 61779.82 | I31: =I43+I105 -> 58631.705 | J31: =J43+J105 -> 55599.16 | K31: =K43+K105 -> 53266.391 | ... AM31: =AM43+AM105 -> 44010.099 | AO31: =SUM(D31:O31) -> 706626.92 | AP31: =SUM(P31:AA31) -> 514499.52 | AQ31: =SUM(AB31:AM31) -> 503889.33
A32: трансфертный расход | B32: тыс сом | D32: =D44+D106 -> -46180.819 | E32: =E44+E106 -> -44341.536 | F32: =F44+F106 -> -42440.088 | G32: =G44+G106 -> -40527.361 | H32: =H44+H106 -> -38571.652 | I32: =I44+I106 -> -36605.87 | J32: =J44+J106 -> -34712.257 | K32: =K44+K106 -> -33255.644 | ... AM32: =AM44+AM106 -> -27478.931 | AO32: =SUM(D32:O32) -> -441173.76 | AP32: =SUM(P32:AA32) -> -321215.31 | AQ32: =SUM(AB32:AM32) -> -314607.52
A33: расходы на провизии | B33: тыс сом | D33: =D45+D107 -> 18800.208 | E33: =E45+E107 -> 6663.1133 | F33: =F45+F107 -> 6609.3772 | G33: =G45+G107 -> 6610.9187 | H33: =H45+H107 -> 6751.2799 | I33: =I45+I107 -> 6548.1791 | J33: =J45+J107 -> 6185.5042 | K33: =K45+K107 -> 3911.5553 | ... AM33: =AM45+AM107 -> -201.92895 | AO33: =SUM(D33:O33) -> 74318.328 | AP33: =SUM(P33:AA33) -> 5564.8975 | AQ33: =SUM(AB33:AM33) -> -5114.2988
A34: комиссии | B34: тыс сом | D34: =D46+D108 -> 0 | E34: =E46+E108 -> 0 | F34: =F46+F108 -> 0 | G34: =G46+G108 -> 0 | H34: =H46+H108 -> 0 | I34: =I46+I108 -> 0 | J34: =J46+J108 -> 0 | K34: =K46+K108 -> 0 | ... AM34: =AM46+AM108 -> 0 | AO34: =SUM(D34:O34) -> 0 | AP34: =SUM(P34:AA34) -> 0 | AQ34: =SUM(AB34:AM34) -> 0
A35: операционные доходы | B35: тыс сом | D35: =D47+D109 -> 46585.066 | E35: =E47+E109 -> 33341.677 | F35: =F47+F109 -> 32144.273 | G35: =G47+G109 -> 30995.37 | H35: =H47+H109 -> 29959.448 | I35: =I47+I109 -> 28574.014 | J35: =J47+J109 -> 27072.407 | K35: =K47+K109 -> 23922.302 | ... AM35: =AM47+AM109 -> 16329.239 | AO35: =SUM(D35:O35) -> 339771.5 | AP35: =SUM(P35:AA35) -> 198849.11 | AQ35: =SUM(AB35:AM35) -> 184167.51
A36: операционные расходы | B36: тыс сом | D36: =D48+D110 -> -347.31558 | E36: =E48+E110 -> -308.76901 | F36: =F48+F110 -> -300.67668 | G36: =G48+G110 -> -286.46425 | H36: =H48+H110 -> -257.53088 | I36: =I48+I110 -> -257.86527 | J36: =J48+J110 -> -244.47459 | K36: =K48+K110 -> -291.59112 | ... AM36: =AM48+AM110 -> -313.64971 | AO36: =SUM(D36:O36) -> -3531.0185 | AP36: =SUM(P36:AA36) -> -3509.5309 | AQ36: =SUM(AB36:AM36) -> -3784.4908
A37: прибыль | B37: тыс сом | D37: =D49+D111 -> 46237.75 | E37: =E49+E111 -> 33032.908 | F37: =F49+F111 -> 31843.596 | G37: =G49+G111 -> 30708.906 | H37: =H49+H111 -> 29701.918 | I37: =I49+I111 -> 28316.149 | J37: =J49+J111 -> 26827.932 | K37: =K49+K111 -> 23630.711 | ... AM37: =AM49+AM111 -> 16015.589 | AO37: =SUM(D37:O37) -> 336240.48 | AP37: =SUM(P37:AA37) -> 195339.58 | AQ37: =SUM(AB37:AM37) -> 180383.02
A38: Безбумажный офис
A39: количество кредитов | B39: шт | D39: =INT(D60/D56+D85/D81) -> 9409 | E39: =INT(E60/E56+E85/E81) -> 9022 | F39: =INT(F60/F56+F85/F81) -> 8634 | G39: =INT(G60/G56+G85/G81) -> 8243 | H39: =INT(H60/H56+H85/H81) -> 7839 | I39: =INT(I60/I56+I85/I81) -> 7444 | J39: =INT(J60/J56+J85/J81) -> 7068 | K39: =INT(K60/K56+K85/K81) -> 4670 | ... AM39: =INT(AM60/AM56+AM85/AM81) -> 3560 | AO39: =O39 -> 4211 | AP39: =AA39 -> 3671 | AQ39: =AM39 -> 3560
A40: кредитный портфель | B40: тыс сом | C40: =C60+C85*'0'!C17/1000 -> 3770987.9 | D40: =D60+D85*'0'!D17/1000 -> 3628621.3 | E40: =E60+E85*'0'!E17/1000 -> 3476492.3 | F40: =F60+F85*'0'!F17/1000 -> 3324180.2 | G40: =G60+G85*'0'!G17/1000 -> 3170250.9 | H40: =H60+H85*'0'!H17/1000 -> 3011065.7 | I40: =I60+I85*'0'!I17/1000 -> 2855528.7 | J40: =J60+J85*'0'!J17/1000 -> 2707894.6 | ... AM40: =AM60+AM85*'0'!AM17/1000 -> 2203541.7 | AO40: =O40 -> 2360876.5 | AP40: =AA40 -> 2072616.9 | AQ40: =AM40 -> 2203541.7
A41: просроченная задолженность | B41: тыс сом | D41: =D62+D87*'0'!D17/1000 -> 39300.794 | E41: =E62+E87*'0'!E17/1000 -> 37651.021 | F41: =F62+F87*'0'!F17/1000 -> 35999.222 | G41: =G62+G87*'0'!G17/1000 -> 34329.826 | H41: =H62+H87*'0'!H17/1000 -> 32603.331 | I41: =I62+I87*'0'!I17/1000 -> 30916.409 | J41: =J62+J87*'0'!J17/1000 -> 29315.253 | K41: =K62+K87*'0'!K17/1000 -> 28387.433 | ... AM41: =AM62+AM87*'0'!AM17/1000 -> 23876.997 | AO41: =O41 -> 25555.771 | AP41: =AA41 -> 22442.586 | AQ41: =AM41 -> 23876.997
A42: РППУ на конец месяца | B42: тыс сом | D42: =D67+D92*'0'!D$17/1000 -> -142466.61 | E42: =E67+E92*'0'!E$17/1000 -> -135803.5 | F42: =F67+F92*'0'!F$17/1000 -> -129194.12 | G42: =G67+G92*'0'!G$17/1000 -> -122583.2 | H42: =H67+H92*'0'!H$17/1000 -> -115831.92 | I42: =I67+I92*'0'!I$17/1000 -> -109283.75 | J42: =J67+J92*'0'!J$17/1000 -> -103098.24 | K42: =K67+K92*'0'!K$17/1000 -> -99186.686 | ... AM42: =AM67+AM92*'0'!AM$17/1000 -> -86497.895 | AO42: =O42 -> -86948.494 | AP42: =AA42 -> -81383.596 | AQ42: =AM42 -> -86497.895
A43: % доход | B43: тыс сом | D43: =D68+D93*'0'!D$17/1000 -> 73965.676 | E43: =E68+E93*'0'!E$17/1000 -> 71020.1 | F43: =F68+F93*'0'!F$17/1000 -> 67974.983 | G43: =G68+G93*'0'!G$17/1000 -> 64911.812 | H43: =H68+H93*'0'!H$17/1000 -> 61779.82 | I43: =I68+I93*'0'!I$17/1000 -> 58631.705 | J43: =J68+J93*'0'!J$17/1000 -> 55599.16 | K43: =K68+K93*'0'!K$17/1000 -> 53266.391 | ... AM43: =AM68+AM93*'0'!AM$17/1000 -> 44010.099 | AO43: =SUM(D43:O43) -> 706626.92 | AP43: =SUM(P43:AA43) -> 514499.52 | AQ43: =SUM(AB43:AM43) -> 503889.33
A44: трансфертный расход | B44: тыс сом | D44: =D69+D94*'0'!D$17/1000 -> -46180.819 | E44: =E69+E94*'0'!E$17/1000 -> -44341.536 | F44: =F69+F94*'0'!F$17/1000 -> -42440.088 | G44: =G69+G94*'0'!G$17/1000 -> -40527.361 | H44: =H69+H94*'0'!H$17/1000 -> -38571.652 | I44: =I69+I94*'0'!I$17/1000 -> -36605.87 | J44: =J69+J94*'0'!J$17/1000 -> -34712.257 | K44: =K69+K94*'0'!K$17/1000 -> -33255.644 | ... AM44: =AM69+AM94*'0'!AM$17/1000 -> -27478.931 | AO44: =SUM(D44:O44) -> -441173.76 | AP44: =SUM(P44:AA44) -> -321215.31 | AQ44: =SUM(AB44:AM44) -> -314607.52
A45: расходы на провизии | B45: тыс сом | D45: =D70+D95*'0'!D$17/1000 -> 18800.208 | E45: =E70+E95*'0'!E$17/1000 -> 6663.1133 | F45: =F70+F95*'0'!F$17/1000 -> 6609.3772 | G45: =G70+G95*'0'!G$17/1000 -> 6610.9187 | H45: =H70+H95*'0'!H$17/1000 -> 6751.2799 | I45: =I70+I95*'0'!I$17/1000 -> 6548.1791 | J45: =J70+J95*'0'!J$17/1000 -> 6185.5042 | K45: =K70+K95*'0'!K$17/1000 -> 3911.5553 | ... AM45: =AM70+AM95*'0'!AM$17/1000 -> -201.92895 | AO45: =SUM(D45:O45) -> 74318.328 | AP45: =SUM(P45:AA45) -> 5564.8975 | AQ45: =SUM(AB45:AM45) -> -5114.2988
A46: комиссии | B46: тыс сом | D46: =D71+D96*'0'!D$17/1000 -> 0 | E46: =E71+E96*'0'!E$17/1000 -> 0 | F46: =F71+F96*'0'!F$17/1000 -> 0 | G46: =G71+G96*'0'!G$17/1000 -> 0 | H46: =H71+H96*'0'!H$17/1000 -> 0 | I46: =I71+I96*'0'!I$17/1000 -> 0 | J46: =J71+J96*'0'!J$17/1000 -> 0 | K46: =K71+K96*'0'!K$17/1000 -> 0 | ... AM46: =AM71+AM96*'0'!AM$17/1000 -> 0 | AO46: =SUM(D46:O46) -> 0 | AP46: =SUM(P46:AA46) -> 0 | AQ46: =SUM(AB46:AM46) -> 0
A47: операционные доходы | B47: тыс сом | D47: =D72+D97*'0'!D$17/1000 -> 46585.066 | E47: =E72+E97*'0'!E$17/1000 -> 33341.677 | F47: =F72+F97*'0'!F$17/1000 -> 32144.273 | G47: =G72+G97*'0'!G$17/1000 -> 30995.37 | H47: =H72+H97*'0'!H$17/1000 -> 29959.448 | I47: =I72+I97*'0'!I$17/1000 -> 28574.014 | J47: =J72+J97*'0'!J$17/1000 -> 27072.407 | K47: =K72+K97*'0'!K$17/1000 -> 23922.302 | ... AM47: =AM72+AM97*'0'!AM$17/1000 -> 16329.239 | AO47: =SUM(D47:O47) -> 339771.5 | AP47: =SUM(P47:AA47) -> 198849.11 | AQ47: =SUM(AB47:AM47) -> 184167.51
A48: операционные расходы | B48: тыс сом | D48: =-'OPEX+CAPEX'!I25 -> -347.31558 | E48: =-'OPEX+CAPEX'!J25 -> -308.76901 | F48: =-'OPEX+CAPEX'!K25 -> -300.67668 | G48: =-'OPEX+CAPEX'!L25 -> -286.46425 | H48: =-'OPEX+CAPEX'!M25 -> -257.53088 | I48: =-'OPEX+CAPEX'!N25 -> -257.86527 | J48: =-'OPEX+CAPEX'!O25 -> -244.47459 | K48: =-'OPEX+CAPEX'!P25 -> -291.59112 | ... AM48: =-'OPEX+CAPEX'!AR25 -> -313.64971 | AO48: =SUM(D48:O48) -> -3531.0185 | AP48: =SUM(P48:AA48) -> -3509.5309 | AQ48: =SUM(AB48:AM48) -> -3784.4908
A49: прибыль | B49: тыс сом | D49: =D47+D48 -> 46237.75 | E49: =E47+E48 -> 33032.908 | F49: =F47+F48 -> 31843.596 | G49: =G47+G48 -> 30708.906 | H49: =H47+H48 -> 29701.918 | I49: =I47+I48 -> 28316.149 | J49: =J47+J48 -> 26827.932 | K49: =K47+K48 -> 23630.711 | ... AM49: =AM47+AM48 -> 16015.589 | AO49: =SUM(D49:O49) -> 336240.48 | AP49: =SUM(P49:AA49) -> 195339.58 | AQ49: =SUM(AB49:AM49) -> 180383.02
A50: KGS
A51: количество кредитных специалистов | B51: шт | D51: ='0'!D14 -> 130 | E51: ='0'!E14 -> 122.85 | F51: ='0'!F14 -> 116.09325 | G51: ='0'!G14 -> 109.70812 | H51: ='0'!H14 -> 103.67417 | I51: ='0'!I14 -> 97.972095 | J51: ='0'!J14 -> 92.58363 | K51: ='0'!K14 -> 87.49153 | ... AM51: ='0'!AM14 -> 80 | AO51: =O51 -> 80 | AP51: =AA51 -> 80 | AQ51: =AM51 -> 80
A52: среднее количество заявок на 1 специалиста | B52: шт | D52: =200/160 -> 1.25 | E52: =50/160 -> 0.3125 | F52: =50/160 -> 0.3125 | G52: =F52*(1-1%) -> 0.309375 | H52: =G52*(1-1%) -> 0.30628125 | I52: =H52*(1-1%) -> 0.30321844 | J52: =I52*(1-1%) -> 0.30018625 | K52: =500/160 -> 3.125 | L52: =K52*(1-1%) -> 3.09375 | M52: =L52*(1-1%) -> 3.0628125 | N52: =M52*(1-1%) -> 3.0321844 | O52: =N52*(1-1%) -> 3.0018625 | P52: =500/160 -> 3.125 | Q52: =500/160 -> 3.125 | R52: =550/160 -> 3.4375 | S52: =550/160 -> 3.4375 | T52: =550/160 -> 3.4375 | U52: =550/160 -> 3.4375 | V52: =550/160 -> 3.4375 | W52: =550/160 -> 3.4375 | X52: =550/160 -> 3.4375 | Y52: =550/160 -> 3.4375 | ... AC52: =550/160 -> 3.4375 | AD52: =650/160 -> 4.0625 | AE52: =650/160 -> 4.0625 | AF52: =650/160 -> 4.0625 | AG52: =650/160 -> 4.0625 | AH52: =650/160 -> 4.0625 | AI52: =650/160 -> 4.0625 | AJ52: =650/160 -> 4.0625 | AK52: =650/160 -> 4.0625 | ... AM52: =650/160 -> 4.0625 | AO52: =AVERAGE(D52:O52) -> 1.5341392 | AP52: =AVERAGE(P52:AA52) -> 3.3854167 | AQ52: =AVERAGE(AB52:AM52) -> 3.9583333
A53: количество заявок | B53: шт | D53: =D51*D52*D7 -> 65 | E53: =E51*E52*E7 -> 30.7125 | F53: =F51*F52*F7 -> 36.279141 | G53: =G51*G52*G7 -> 33.94095 | H53: =H51*H52*H7 -> 12.701382 | I53: =I51*I52*I7 -> 29.706946 | J53: =J51*J52*J7 -> 27.792333 | K53: =K51*K52*K7 -> 191.38772 | ... AM53: =AM51*AM52*AM7 -> 260 | AO53: =SUM(D53:O53) -> 1338.7721 | AP53: =SUM(P53:AA53) -> 2720 | AQ53: =SUM(AB53:AM53) -> 3190
A54: APR, % | B54: % | D54: 0.56 | E54: =D54*(1-1%) -> 0.5544 | F54: =E54*(1-1%) -> 0.548856 | G54: =F54*(1-1%) -> 0.54336744 | H54: =G54*(1-1%) -> 0.53793377 | I54: =H54*(1-1%) -> 0.53255443 | J54: =I54*(1-1%) -> 0.52722888 | K54: =J54*(1-1%) -> 0.52195659 | L54: =K54*(1-1%) -> 0.51673703 | ... O54: =N54*(1-1%) -> 0.50138942 | P54: =O54*(1+1%) -> 0.50640332 | Q54: =P54*(1+1%) -> 0.51146735 | R54: =Q54*(1+1.5%) -> 0.51913936 | S54: =R54*(1+1.3%) -> 0.52588817 | T54: =S54*(1+1.3%) -> 0.53272472 | U54: =T54*(1+1.3%) -> 0.53965014 | V54: =U54*(1+1.3%) -> 0.54666559 | W54: =V54*(1+1.3%) -> 0.55377224 | X54: =W54*(1+1.3%) -> 0.56097128 | Y54: =X54*(1+1.3%) -> 0.56826391 | Z54: =Y54*(1+1.5%) -> 0.57678787 | AA54: =Z54 -> 0.57678787 | AB54: =AA54 -> 0.57678787 | AC54: =AB54 -> 0.57678787 | AD54: =AC54*(1+0.9%) -> 0.58197896 | AE54: =AD54 -> 0.58197896 | AF54: =AE54 -> 0.58197896 | AG54: =AF54 -> 0.58197896 | AH54: =AG54 -> 0.58197896 | AI54: =AH54 -> 0.58197896 | AJ54: =AI54 -> 0.58197896 | AK54: =AJ54 -> 0.58197896 | AL54: =AK54 -> 0.58197896 | AM54: =AL54 -> 0.58197896 | AO54: =AVERAGE(D54:O54) -> 0.53020393 | AP54: =AVERAGE(P54:AA54) -> 0.54321015 | AQ54: =AVERAGE(AB54:AM54) -> 0.58111378
A55: количество выдач | B55: шт | D55: =D53*D54 -> 36.4 | E55: =E53*E54 -> 17.02701 | F55: =F53*F54 -> 19.912024 | G55: =G53*G54 -> 18.442407 | H55: =H53*H54 -> 6.8325024 | I55: =I53*I54 -> 15.820565 | J55: =J53*J54 -> 14.652921 | K55: =K53*K54 -> 99.896084 | ... AM55: =AM53*AM54 -> 151.31453 | AO55: =SUM(D55:O55) -> 693.40106 | AP55: =SUM(P55:AA55) -> 1484.4421 | AQ55: =SUM(AB55:AM55) -> 1854.7998
A56: ср. сумма выдачи | B56: тыс сом | D56: 400 | E56: 400 | F56: 400 | G56: 400 | H56: 400 | I56: 400 | J56: 400 | K56: 600 | L56: 600 | M56: 600 | N56: 600 | O56: 600 | P56: 600 | Q56: 600 | R56: 600 | S56: 600 | T56: 600 | U56: 600 | V56: 600 | W56: 600 | X56: 600 | Y56: 600 | Z56: 600 | AA56: 600 | AB56: 600 | AC56: 600 | AD56: 650 | AE56: 650 | AF56: 650 | AG56: 650 | AH56: 650 | AI56: 650 | AJ56: 650 | AK56: 650 | AL56: 650 | AM56: 650 | AO56: =AVERAGE(D56:O56) -> 483.33333 | AP56: =AVERAGE(P56:AA56) -> 600 | AQ56: =AVERAGE(AB56:AM56) -> 641.66667
A57: выдачи | B57: тыс сом | D57: =D55*D56 -> 14560 | E57: =E55*E56 -> 6810.804 | F57: =F55*F56 -> 7964.8096 | G57: =G55*G56 -> 7376.9628 | H57: =H55*H56 -> 2733.001 | I57: =I55*I56 -> 6328.2262 | J57: =J55*J56 -> 5861.1683 | K57: =K55*K56 -> 59937.65 | ... AM57: =AM55*AM56 -> 98354.444 | AO57: =SUM(D57:O57) -> 390223.15 | AP57: =SUM(P57:AA57) -> 890665.25 | AQ57: =SUM(AB57:AM57) -> 1196102.9
A58: cр. срок портфеля | B58: мес | D58: 24 | E58: =D58*(1-5%) -> 22.8 | F58: =E58*(1-5%) -> 21.66 | G58: =F58*(1-5%) -> 20.577 | H58: =G58*(1-5%) -> 19.54815 | I58: =H58*(1-5%) -> 18.570742 | J58: =I58 -> 18.570742 | K58: =J58 -> 18.570742 | L58: =K58 -> 18.570742 | M58: =L58 -> 18.570742 | N58: =M58 -> 18.570742 | O58: =N58+0.5 -> 19.070742 | P58: =O58+0.5 -> 19.570742 | Q58: =P58+0.5 -> 20.070742 | R58: =Q58+0.5 -> 20.570742 | S58: =R58+0.5 -> 21.070742 | T58: =S58+0.5 -> 21.570742 | U58: =T58+0.5 -> 22.070742 | V58: =U58+0.5 -> 22.570742 | ... X58: =W58+0.5 -> 23.570742 | Y58: =X58 -> 23.570742 | Z58: =Y58 -> 23.570742 | AA58: =Z58 -> 23.570742 | AB58: =AA58 -> 23.570742 | AC58: =AB58 -> 23.570742 | AD58: =AC58 -> 23.570742 | AE58: =AD58 -> 23.570742 | AF58: =AE58 -> 23.570742 | ... AM58: =AL58 -> 23.570742 | AO58: =AVERAGE(D58:O58) -> 19.923362 | AP58: =AVERAGE(P58:AA58) -> 22.070742 | AQ58: =AVERAGE(AB58:AM58) -> 23.570742
A59: погашения | B59: тыс сом | D59: =C60/D58 -> 156750 | E59: =D60/E58 -> 158763.6 | F59: =E60/F58 -> 160104.21 | G59: =F60/G58 -> 161137.09 | H59: =G60/H58 -> 161752.27 | I59: =H60/I58 -> 161702.66 | J59: =I60/J58 -> 153336.03 | K59: =J60/K58 -> 145394.79 | ... AM59: =AL60/AM58 -> 93078.135 | AO59: =SUM(D59:O59) -> 1798402.2 | AP59: =SUM(P59:AA59) -> 1177405.9 | AQ59: =SUM(AB59:AM59) -> 1063986.1
A60: кредитный портфель | B60: тыс сом | C60: 3762000 | D60: =C60+D57-D59 -> 3619810 | E60: =D60+E57-E59 -> 3467857.2 | F60: =E60+F57-F59 -> 3315717.8 | G60: =F60+G57-G59 -> 3161957.7 | H60: =G60+H57-H59 -> 3002938.4 | I60: =H60+I57-I59 -> 2847564 | J60: =I60+J57-J59 -> 2700089.1 | K60: =J60+K57-K59 -> 2614632 | ... AM60: =AL60+AM57-AM59 -> 2199197.1 | AO60: =O60 -> 2353821 | AP60: =AA60 -> 2067080.3 | AQ60: =AM60 -> 2199197.1
A61: доля просроченной задолженности, % | B61: % | D61: 0.010857143 | E61: 0.010857143 | F61: 0.010857143 | G61: 0.010857143 | H61: 0.010857143 | I61: 0.010857143 | J61: 0.010857143 | K61: 0.010857143 | L61: 0.010857143 | M61: 0.010857143 | N61: 0.010857143 | O61: 0.010857143 | P61: 0.010857143 | Q61: 0.010857143 | R61: 0.010857143 | S61: 0.010857143 | T61: 0.010857143 | U61: 0.010857143 | V61: 0.010857143 | W61: 0.010857143 | X61: 0.010857143 | Y61: 0.010857143 | Z61: 0.010857143 | AA61: 0.010857143 | AB61: 0.010857143 | AC61: 0.010857143 | AD61: 0.010857143 | AE61: 0.010857143 | AF61: 0.010857143 | AG61: 0.010857143 | AH61: 0.010857143 | AI61: 0.010857143 | AJ61: 0.010857143 | AK61: 0.010857143 | AL61: 0.010857143 | AM61: 0.010857143 | AO61: =O61 -> 0.010857143 | AP61: =AA61 -> 0.010857143 | AQ61: =AM61 -> 0.010857143
A62: просроченная задолженность | B62: тыс сом | D62: =D60*D61 -> 39300.794 | E62: =E60*E61 -> 37651.021 | F62: =F60*F61 -> 35999.222 | G62: =G60*G61 -> 34329.826 | H62: =H60*H61 -> 32603.331 | I62: =I60*I61 -> 30916.409 | J62: =J60*J61 -> 29315.253 | K62: =K60*K61 -> 28387.433 | ... AM62: =AM60*AM61 -> 23876.997 | AO62: =O62 -> 25555.771 | AP62: =AA62 -> 22442.586 | AQ62: =AM62 -> 23876.997
A63: ср. % ставка портфеля | B63: % | D63: 0.245 | E63: 0.245 | F63: 0.245 | G63: 0.245 | H63: 0.245 | I63: 0.245 | J63: 0.245 | K63: 0.245 | L63: 0.245 | M63: 0.245 | N63: 0.245 | O63: 0.245 | P63: 0.245 | Q63: 0.245 | R63: 0.245 | S63: 0.245 | T63: 0.245 | U63: 0.245 | V63: 0.245 | W63: 0.245 | X63: 0.245 | Y63: 0.245 | Z63: 0.245 | AA63: 0.245 | AB63: 0.245 | AC63: 0.245 | AD63: 0.245 | AE63: 0.245 | AF63: 0.245 | AG63: 0.245 | AH63: 0.245 | AI63: 0.245 | AJ63: 0.245 | AK63: 0.245 | AL63: 0.245 | AM63: 0.245 | AO63: =AVERAGE(D63:O63) -> 0.245 | AP63: =AVERAGE(P63:AA63) -> 0.245 | AQ63: =AVERAGE(AB63:AM63) -> 0.245
A64: ср. % ставка фондирования | B64: % | D64: 0.15 | E64: 0.15 | F64: 0.15 | G64: 0.15 | H64: 0.15 | I64: 0.15 | J64: 0.15 | K64: 0.15 | L64: 0.15 | M64: 0.15 | N64: 0.15 | O64: 0.15 | P64: 0.15 | Q64: 0.15 | R64: 0.15 | S64: 0.15 | T64: 0.15 | U64: 0.15 | V64: 0.15 | W64: 0.15 | X64: 0.15 | Y64: 0.15 | Z64: 0.15 | AA64: 0.15 | AB64: 0.15 | AC64: 0.15 | AD64: 0.15 | AE64: 0.15 | AF64: 0.15 | AG64: 0.15 | AH64: 0.15 | AI64: 0.15 | AJ64: 0.15 | AK64: 0.15 | AL64: 0.15 | AM64: 0.15 | AO64: =AVERAGE(D64:O64) -> 0.15 | AP64: =AVERAGE(P64:AA64) -> 0.15 | AQ64: =AVERAGE(AB64:AM64) -> 0.15
A65: ср. % резервирования | B65: % | D65: 0.03922 | E65: =D65-0.02% -> 0.03902 | F65: =E65-0.02% -> 0.03882 | G65: =F65-0.02% -> 0.03862 | H65: =G65-0.02% -> 0.03842 | I65: =H65-0.02% -> 0.03822 | J65: =I65-0.02% -> 0.03802 | K65: =J65-0.025% -> 0.03777 | L65: =K65-0.025% -> 0.03752 | M65: =L65-0.025% -> 0.03727 | N65: =M65-0.025% -> 0.03702 | O65: =N65-0.025% -> 0.03677 | P65: 0.03922 | Q65: 0.03922 | R65: 0.03922 | S65: 0.03922 | T65: 0.03922 | U65: 0.03922 | V65: 0.03922 | W65: 0.03922 | X65: 0.03922 | Y65: 0.03922 | Z65: 0.03922 | AA65: 0.03922 | AB65: 0.03922 | AC65: 0.03922 | AD65: 0.03922 | AE65: 0.03922 | AF65: 0.03922 | AG65: 0.03922 | AH65: 0.03922 | AI65: 0.03922 | AJ65: 0.03922 | AK65: 0.03922 | AL65: 0.03922 | AM65: 0.03922 | AO65: =AVERAGE(D65:O65) -> 0.0380575 | AP65: =AVERAGE(P65:AA65) -> 0.03922 | AQ65: =AVERAGE(AB65:AM65) -> 0.03922
A66: ср. комиссия на 1 клиента | B66: тыс сом | AO66: =AVERAGE(D66:O66) -> #DIV/0! | AP66: =AVERAGE(P66:AA66) -> #DIV/0! | AQ66: =AVERAGE(AB66:AM66) -> #DIV/0!
A67: РППУ на конец месяца | B67: тыс сом | C67: =-160759 -> -160759 | D67: =-D60*D65 -> -141968.95 | E67: =-E60*E65 -> -135315.79 | F67: =-F60*F65 -> -128716.17 | G67: =-G60*G65 -> -122114.81 | H67: =-H60*H65 -> -115372.89 | I67: =-I60*I65 -> -108833.9 | J67: =-J60*J65 -> -102657.39 | K67: =-K60*K65 -> -98754.65 | ... AM67: =-AM60*AM65 -> -86252.509 | AO67: =O67 -> -86549.997 | AP67: =AA67 -> -81070.89 | AQ67: =AM67 -> -86252.509
A68: % доход | B68: тыс сом | D68: =(C60+D60)/2*D63/12*(1-2/102) -> 73878.409 | E68: =(D60+E60)/2*E63/12*(1-2/102) -> 70934.578 | F68: =(E60+F60)/2*F63/12*(1-2/102) -> 67891.172 | G68: =(F60+G60)/2*G63/12*(1-2/102) -> 64829.677 | H68: =(G60+H60)/2*H63/12*(1-2/102) -> 61699.328 | I68: =(H60+I60)/2*I63/12*(1-2/102) -> 58552.822 | J68: =(I60+J60)/2*J63/12*(1-2/102) -> 55521.855 | K68: =(J60+K60)/2*K63/12*(1-2/102) -> 53190.632 | ... AM68: =(AL60+AM60)/2*AM63/12*(1-2/102) -> 43967.07 | AO68: =SUM(D68:O68) -> 705687.56 | AP68: =SUM(P68:AA68) -> 513762.39 | AQ68: =SUM(AB68:AM68) -> 503310.89
A69: трансфертный расход | B69: тыс сом | D69: =-(C60+D60)/2*D64/12 -> -46136.312 | E69: =-(D60+E60)/2*E64/12 -> -44297.92 | F69: =-(E60+F60)/2*F64/12 -> -42397.344 | G69: =-(F60+G60)/2*G64/12 -> -40485.472 | H69: =-(G60+H60)/2*H64/12 -> -38530.601 | I69: =-(H60+I60)/2*I64/12 -> -36565.64 | J69: =-(I60+J60)/2*J64/12 -> -34672.832 | K69: =-(J60+K60)/2*K64/12 -> -33217.007 | ... AM69: =-(AL60+AM60)/2*AM64/12 -> -27456.986 | AO69: =SUM(D69:O69) -> -440694.68 | AP69: =SUM(P69:AA69) -> -320839.37 | AQ69: =SUM(AB69:AM69) -> -314312.52
A70: расходы на провизии | B70: тыс сом | D70: =(D67-C67) -> 18790.052 | E70: =(E67-D67) -> 6653.16 | F70: =(F67-E67) -> 6599.623 | G70: =(G67-F67) -> 6601.3595 | H70: =(H67-G67) -> 6741.9119 | I70: =(I67-H67) -> 6538.9984 | J70: =(J67-I67) -> 6176.5071 | K70: =(K67-J67) -> 3902.7383 | ... AM70: =(AM67-AL67) -> -206.93683 | AO70: =SUM(D70:O70) -> 74209.003 | AP70: =SUM(P70:AA70) -> 5479.1078 | AQ70: =SUM(AB70:AM70) -> -5181.6194
A71: комиссии | B71: тыс сом | D71: =D66*(AVERAGE(C60:D60)/D56)*(1-2/102) -> 0 | E71: =E66*(AVERAGE(D60:E60)/E56)*(1-2/102) -> 0 | F71: =F66*(AVERAGE(E60:F60)/F56)*(1-2/102) -> 0 | G71: =G66*(AVERAGE(F60:G60)/G56)*(1-2/102) -> 0 | H71: =H66*(AVERAGE(G60:H60)/H56)*(1-2/102) -> 0 | I71: =I66*(AVERAGE(H60:I60)/I56)*(1-2/102) -> 0 | J71: =J66*(AVERAGE(I60:J60)/J56)*(1-2/102) -> 0 | K71: =K66*(AVERAGE(J60:K60)/K56)*(1-2/102) -> 0 | ... AM71: =AM66*(AVERAGE(AL60:AM60)/AM56)*(1-2/102) -> 0 | AO71: =SUM(D71:O71) -> 0 | AP71: =SUM(P71:AA71) -> 0 | AQ71: =SUM(AB71:AM71) -> 0
A72: операционные доходы | B72: тыс сом | D72: =SUM(D68:D71) -> 46532.148 | E72: =SUM(E68:E71) -> 33289.818 | F72: =SUM(F68:F71) -> 32093.451 | G72: =SUM(G68:G71) -> 30945.565 | H72: =SUM(H68:H71) -> 29910.639 | I72: =SUM(I68:I71) -> 28526.181 | J72: =SUM(J68:J71) -> 27025.53 | K72: =SUM(K68:K71) -> 23876.363 | ... AM72: =SUM(AM68:AM71) -> 16303.146 | AO72: =SUM(D72:O72) -> 339201.88 | AP72: =SUM(P72:AA72) -> 198402.13 | AQ72: =SUM(AB72:AM72) -> 183816.76
A73: операционные расходы | B73: тыс сом | AO73: =SUM(D73:O73) -> 0 | AP73: =SUM(P73:AA73) -> 0 | AQ73: =SUM(AB73:AM73) -> 0
A74: прибыль | B74: тыс сом | D74: =D72+D73 -> 46532.148 | E74: =E72+E73 -> 33289.818 | F74: =F72+F73 -> 32093.451 | G74: =G72+G73 -> 30945.565 | H74: =H72+H73 -> 29910.639 | I74: =I72+I73 -> 28526.181 | J74: =J72+J73 -> 27025.53 | K74: =K72+K73 -> 23876.363 | ... AM74: =AM72+AM73 -> 16303.146 | AO74: =SUM(D74:O74) -> 339201.88 | AP74: =SUM(P74:AA74) -> 198402.13 | AQ74: =SUM(AB74:AM74) -> 183816.76
A75: USD
A76: количество кредитных специалистов | B76: шт | D76: ='0'!D14 -> 130 | E76: ='0'!E14 -> 122.85 | F76: ='0'!F14 -> 116.09325 | G76: ='0'!G14 -> 109.70812 | H76: ='0'!H14 -> 103.67417 | I76: ='0'!I14 -> 97.972095 | J76: ='0'!J14 -> 92.58363 | K76: ='0'!K14 -> 87.49153 | ... AM76: ='0'!AM14 -> 80 | AO76: =O76 -> 80 | AP76: =AA76 -> 80 | AQ76: =AM76 -> 80
A77: среднее количество заявок на 1 специалиста | B77: шт | D77: 0 | E77: 0 | F77: 0 | G77: 0 | H77: 0 | I77: 0 | J77: 0 | K77: 0 | L77: 0 | M77: 0 | N77: 0 | O77: 0 | P77: 0 | Q77: 0 | R77: 0 | S77: 0 | T77: 0 | U77: 0 | V77: 0 | W77: 0 | X77: 0 | Y77: 0 | Z77: 0 | AA77: 0 | AB77: 0 | AC77: 0 | AD77: 0 | AE77: 0 | AF77: 0 | AG77: 0 | AH77: 0 | AI77: 0 | AJ77: 0 | AK77: 0 | AL77: 0 | AM77: 0 | AO77: =AVERAGE(D77:O77) -> 0 | AP77: =AVERAGE(P77:AA77) -> 0 | AQ77: =AVERAGE(AB77:AM77) -> 0
A78: количество заявок | B78: шт | D78: =D76*D77 -> 0 | E78: =E76*E77 -> 0 | F78: =F76*F77 -> 0 | G78: =G76*G77 -> 0 | H78: =H76*H77 -> 0 | I78: =I76*I77 -> 0 | J78: =J76*J77 -> 0 | K78: =K76*K77 -> 0 | ... AM78: =AM76*AM77 -> 0 | AO78: =SUM(D78:O78) -> 0 | AP78: =SUM(P78:AA78) -> 0 | AQ78: =SUM(AB78:AM78) -> 0
A79: APR, % | B79: % | D79: 0.7 | E79: 0.7 | F79: 0.7 | G79: 0.7 | H79: 0.7 | I79: 0.7 | J79: 0.7 | K79: 0.7 | L79: 0.7 | M79: 0.7 | N79: 0.7 | O79: 0.7 | P79: 0.7 | Q79: 0.7 | R79: 0.7 | S79: 0.7 | T79: 0.7 | U79: 0.7 | V79: 0.7 | W79: 0.7 | X79: 0.7 | Y79: 0.7 | Z79: 0.7 | AA79: 0.7 | AB79: 0.7 | AC79: 0.7 | AD79: 0.7 | AE79: 0.7 | AF79: 0.7 | AG79: 0.7 | AH79: 0.7 | AI79: 0.7 | AJ79: 0.7 | AK79: 0.7 | AL79: 0.7 | AM79: 0.7 | AO79: =AVERAGE(D79:O79) -> 0.7 | AP79: =AVERAGE(P79:AA79) -> 0.7 | AQ79: =AVERAGE(AB79:AM79) -> 0.7
A80: количество выдач | B80: шт | D80: =D78*D79 -> 0 | E80: =E78*E79 -> 0 | F80: =F78*F79 -> 0 | G80: =G78*G79 -> 0 | H80: =H78*H79 -> 0 | I80: =I78*I79 -> 0 | J80: =J78*J79 -> 0 | K80: =K78*K79 -> 0 | ... AM80: =AM78*AM79 -> 0 | AO80: =SUM(D80:O80) -> 0 | AP80: =SUM(P80:AA80) -> 0 | AQ80: =SUM(AB80:AM80) -> 0
A81: ср. сумма выдачи | B81: usd | D81: 280 | E81: 280 | F81: 280 | G81: 280 | H81: 280 | I81: 280 | J81: 280 | K81: 280 | L81: 280 | M81: 280 | N81: 280 | O81: 280 | P81: 280 | Q81: 280 | R81: 280 | S81: 280 | T81: 280 | U81: 280 | V81: 280 | W81: 280 | X81: 280 | Y81: 280 | Z81: 280 | AA81: 280 | AB81: 280 | AC81: 280 | AD81: 280 | AE81: 280 | AF81: 280 | AG81: 280 | AH81: 280 | AI81: 280 | AJ81: 280 | AK81: 280 | AL81: 280 | AM81: 280 | AO81: =AVERAGE(D81:O81) -> 280 | AP81: =AVERAGE(P81:AA81) -> 280 | AQ81: =AVERAGE(AB81:AM81) -> 280
A82: выдачи | B82: usd | D82: =D80*D81 -> 0 | E82: =E80*E81 -> 0 | F82: =F80*F81 -> 0 | G82: =G80*G81 -> 0 | H82: =H80*H81 -> 0 | I82: =I80*I81 -> 0 | J82: =J80*J81 -> 0 | K82: =K80*K81 -> 0 | ... AM82: =AM80*AM81 -> 0 | AO82: =SUM(D82:O82) -> 0 | AP82: =SUM(P82:AA82) -> 0 | AQ82: =SUM(AB82:AM82) -> 0
A83: cр. срок портфеля | B83: мес | D83: 50 | E83: 50 | F83: 50 | G83: 50 | H83: 50 | I83: 50 | J83: 50 | K83: 50 | L83: 50 | M83: 50 | N83: 50 | O83: 50 | P83: 50 | Q83: 50 | R83: 50 | S83: 50 | T83: 50 | U83: 50 | V83: 50 | W83: 50 | X83: 50 | Y83: 50 | Z83: 50 | AA83: 50 | AB83: 50 | AC83: 50 | AD83: 50 | AE83: 50 | AF83: 50 | AG83: 50 | AH83: 50 | AI83: 50 | AJ83: 50 | AK83: 50 | AL83: 50 | AM83: 50 | AO83: =AVERAGE(D83:O83) -> 50 | AP83: =AVERAGE(P83:AA83) -> 50 | AQ83: =AVERAGE(AB83:AM83) -> 50
A84: погашения | B84: usd | D84: =C85/D83 -> 2056.3 | E84: =D85/E83 -> 2015.174 | F84: =E85/F83 -> 1974.8705 | G84: =F85/G83 -> 1935.3731 | H84: =G85/H83 -> 1896.6656 | I84: =H85/I83 -> 1858.7323 | J84: =I85/J83 -> 1821.5577 | K84: =J85/K83 -> 1785.1265 | ... AM84: =AL85/AM83 -> 1013.9093 | AO84: =SUM(D84:O84) -> 22134.35 | AP84: =SUM(P84:AA84) -> 17369.195 | AQ84: =SUM(AB84:AM84) -> 13629.898
A85: кредитный портфель | B85: usd | C85: 102815 | D85: =C85+D82-D84 -> 100758.7 | E85: =D85+E82-E84 -> 98743.526 | F85: =E85+F82-F84 -> 96768.655 | G85: =F85+G82-G84 -> 94833.282 | H85: =G85+H82-H84 -> 92936.617 | I85: =H85+I82-I84 -> 91077.884 | J85: =I85+J82-J84 -> 89256.327 | K85: =J85+K82-K84 -> 87471.2 | ... AM85: =AL85+AM82-AM84 -> 49681.558 | AO85: =O85 -> 80680.65 | AP85: =AA85 -> 63311.455 | AQ85: =AM85 -> 49681.558
A86: доля просроченной задолженности, % | B86: % | D86: 0 | E86: 0 | F86: 0 | G86: 0 | H86: 0 | I86: 0 | J86: 0 | K86: 0 | L86: 0 | M86: 0 | N86: 0 | O86: 0 | P86: 0 | Q86: 0 | R86: 0 | S86: 0 | T86: 0 | U86: 0 | V86: 0 | W86: 0 | X86: 0 | Y86: 0 | Z86: 0 | AA86: 0 | AB86: 0 | AC86: 0 | AD86: 0 | AE86: 0 | AF86: 0 | AG86: 0 | AH86: 0 | AI86: 0 | AJ86: 0 | AK86: 0 | AL86: 0 | AM86: 0 | AO86: =O86 -> 0 | AP86: =AA86 -> 0 | AQ86: =AM86 -> 0
A87: просроченная задолженность | B87: usd | D87: =D85*D86 -> 0 | E87: =E85*E86 -> 0 | F87: =F85*F86 -> 0 | G87: =G85*G86 -> 0 | H87: =H85*H86 -> 0 | I87: =I85*I86 -> 0 | J87: =J85*J86 -> 0 | K87: =K85*K86 -> 0 | ... AM87: =AM85*AM86 -> 0 | AO87: =O87 -> 0 | AP87: =AA87 -> 0 | AQ87: =AM87 -> 0
A88: ср. % ставка портфеля | B88: % | D88: 0.12 | E88: 0.12 | F88: 0.12 | G88: 0.12 | H88: 0.12 | I88: 0.12 | J88: 0.12 | K88: 0.12 | L88: 0.12 | M88: 0.12 | N88: 0.12 | O88: 0.12 | P88: 0.12 | Q88: 0.12 | R88: 0.12 | S88: 0.12 | T88: 0.12 | U88: 0.12 | V88: 0.12 | W88: 0.12 | X88: 0.12 | Y88: 0.12 | Z88: 0.12 | AA88: 0.12 | AB88: 0.12 | AC88: 0.12 | AD88: 0.12 | AE88: 0.12 | AF88: 0.12 | AG88: 0.12 | AH88: 0.12 | AI88: 0.12 | AJ88: 0.12 | AK88: 0.12 | AL88: 0.12 | AM88: 0.12 | AO88: =AVERAGE(D88:O88) -> 0.12 | AP88: =AVERAGE(P88:AA88) -> 0.12 | AQ88: =AVERAGE(AB88:AM88) -> 0.12
A89: ср. % ставка фондирования | B89: % | D89: 0.06 | E89: 0.06 | F89: 0.06 | G89: 0.06 | H89: 0.06 | I89: 0.06 | J89: 0.06 | K89: 0.06 | L89: 0.06 | M89: 0.06 | N89: 0.06 | O89: 0.06 | P89: 0.06 | Q89: 0.06 | R89: 0.06 | S89: 0.06 | T89: 0.06 | U89: 0.06 | V89: 0.06 | W89: 0.06 | X89: 0.06 | Y89: 0.06 | Z89: 0.06 | AA89: 0.06 | AB89: 0.06 | AC89: 0.06 | AD89: 0.06 | AE89: 0.06 | AF89: 0.06 | AG89: 0.06 | AH89: 0.06 | AI89: 0.06 | AJ89: 0.06 | AK89: 0.06 | AL89: 0.06 | AM89: 0.06 | AO89: =AVERAGE(D89:O89) -> 0.06 | AP89: =AVERAGE(P89:AA89) -> 0.06 | AQ89: =AVERAGE(AB89:AM89) -> 0.06
A90: ср. % резервирования | B90: % | D90: 0.056480086 | E90: 0.056480086 | F90: 0.056480086 | G90: 0.056480086 | H90: 0.056480086 | I90: 0.056480086 | J90: 0.056480086 | K90: 0.056480086 | L90: 0.056480086 | M90: 0.056480086 | N90: 0.056480086 | O90: 0.056480086 | P90: 0.056480086 | Q90: 0.056480086 | R90: 0.056480086 | S90: 0.056480086 | T90: 0.056480086 | U90: 0.056480086 | V90: 0.056480086 | W90: 0.056480086 | X90: 0.056480086 | Y90: 0.056480086 | Z90: 0.056480086 | AA90: 0.056480086 | AB90: 0.056480086 | AC90: 0.056480086 | AD90: 0.056480086 | AE90: 0.056480086 | AF90: 0.056480086 | AG90: 0.056480086 | AH90: 0.056480086 | AI90: 0.056480086 | AJ90: 0.056480086 | AK90: 0.056480086 | AL90: 0.056480086 | AM90: 0.056480086 | AO90: =AVERAGE(D90:O90) -> 0.056480086 | AP90: =AVERAGE(P90:AA90) -> 0.056480086 | AQ90: =AVERAGE(AB90:AM90) -> 0.056480086
A91: ср. комиссия на 1 клиента | B91: usd | AO91: =AVERAGE(D91:O91) -> #DIV/0! | AP91: =AVERAGE(P91:AA91) -> #DIV/0! | AQ91: =AVERAGE(AB91:AM91) -> #DIV/0!
A92: РППУ на конец месяца | B92: usd | C92: =-5807 -> -5807 | D92: =-D85*D90 -> -5690.86 | E92: =-E85*E90 -> -5577.0428 | F92: =-F85*F90 -> -5465.5019 | G92: =-G85*G90 -> -5356.1919 | H92: =-H85*H90 -> -5249.0681 | I92: =-I85*I90 -> -5144.0867 | J92: =-J85*J90 -> -5041.205 | K92: =-K85*K90 -> -4940.3809 | ... AM92: =-AM85*AM90 -> -2806.0186 | AO92: =O92 -> -4556.85 | AP92: =AA92 -> -3575.8364 | AQ92: =AM92 -> -2806.0186
A93: % доход | B93: usd | D93: =(C85+D85)/2*D88/12*(1-2/102) -> 997.91029 | E93: =(D85+E85)/2*E88/12*(1-2/102) -> 977.95209 | F93: =(E85+F85)/2*F88/12*(1-2/102) -> 958.39305 | G93: =(F85+G85)/2*G88/12*(1-2/102) -> 939.22519 | H93: =(G85+H85)/2*H88/12*(1-2/102) -> 920.44068 | I93: =(H85+I85)/2*I88/12*(1-2/102) -> 902.03187 | J93: =(I85+J85)/2*J88/12*(1-2/102) -> 883.99123 | K93: =(J85+K85)/2*K88/12*(1-2/102) -> 866.31141 | ... AM93: =(AL85+AM85)/2*AM88/12*(1-2/102) -> 492.04424 | AO93: =SUM(D93:O93) -> 10741.67 | AP93: =SUM(P93:AA93) -> 8429.168 | AQ93: =SUM(AB93:AM93) -> 6614.5091
A94: трансфертный расход | B94: usd | D94: =-(C85+D85)/2*D89/12 -> -508.93425 | E94: =-(D85+E85)/2*E89/12 -> -498.75556 | F94: =-(E85+F85)/2*F89/12 -> -488.78045 | G94: =-(F85+G85)/2*G89/12 -> -479.00484 | H94: =-(G85+H85)/2*H89/12 -> -469.42475 | I94: =-(H85+I85)/2*I89/12 -> -460.03625 | J94: =-(I85+J85)/2*J89/12 -> -450.83553 | K94: =-(J85+K85)/2*K89/12 -> -441.81882 | ... AM94: =-(AL85+AM85)/2*AM89/12 -> -250.94256 | AO94: =SUM(D94:O94) -> -5478.2516 | AP94: =SUM(P94:AA94) -> -4298.8757 | AQ94: =SUM(AB94:AM94) -> -3373.3996
A95: расходы на провизии | B95: usd | D95: =(D92-C92) -> 116.14 | E95: =(E92-D92) -> 113.8172 | F95: =(F92-E92) -> 111.54086 | G95: =(G92-F92) -> 109.31004 | H95: =(H92-G92) -> 107.12384 | I95: =(I92-H92) -> 104.98136 | J95: =(J92-I92) -> 102.88173 | K95: =(K92-J92) -> 100.8241 | ... AM95: =(AM92-AL92) -> 57.265686 | AO95: =SUM(D95:O95) -> 1250.15 | AP95: =SUM(P95:AA95) -> 981.0136 | AQ95: =SUM(AB95:AM95) -> 769.81778
A96: комиссии | B96: usd | D96: =D91*(AVERAGE(C85:D85)/D81)*(1-2/102) -> 0 | E96: =E91*(AVERAGE(D85:E85)/E81)*(1-2/102) -> 0 | F96: =F91*(AVERAGE(E85:F85)/F81)*(1-2/102) -> 0 | G96: =G91*(AVERAGE(F85:G85)/G81)*(1-2/102) -> 0 | H96: =H91*(AVERAGE(G85:H85)/H81)*(1-2/102) -> 0 | I96: =I91*(AVERAGE(H85:I85)/I81)*(1-2/102) -> 0 | J96: =J91*(AVERAGE(I85:J85)/J81)*(1-2/102) -> 0 | K96: =K91*(AVERAGE(J85:K85)/K81)*(1-2/102) -> 0 | ... AM96: =AM91*(AVERAGE(AL85:AM85)/AM81)*(1-2/102) -> 0 | AO96: =SUM(D96:O96) -> 0 | AP96: =SUM(P96:AA96) -> 0 | AQ96: =SUM(AB96:AM96) -> 0
A97: операционные доходы | B97: usd | D97: =SUM(D93:D96) -> 605.11604 | E97: =SUM(E93:E96) -> 593.01372 | F97: =SUM(F93:F96) -> 581.15345 | G97: =SUM(G93:G96) -> 569.53038 | H97: =SUM(H93:H96) -> 558.13977 | I97: =SUM(I93:I96) -> 546.97698 | J97: =SUM(J93:J96) -> 536.03744 | K97: =SUM(K93:K96) -> 525.31669 | ... AM97: =SUM(AM93:AM96) -> 298.36736 | AO97: =SUM(D97:O97) -> 6513.5682 | AP97: =SUM(P97:AA97) -> 5111.3059 | AQ97: =SUM(AB97:AM97) -> 4010.9272
A98: операционные расходы | B98: usd | AO98: =SUM(D98:O98) -> 0 | AP98: =SUM(P98:AA98) -> 0 | AQ98: =SUM(AB98:AM98) -> 0
A99: прибыль | B99: usd | D99: =D97+D98 -> 605.11604 | E99: =E97+E98 -> 593.01372 | F99: =F97+F98 -> 581.15345 | G99: =G97+G98 -> 569.53038 | H99: =H97+H98 -> 558.13977 | I99: =I97+I98 -> 546.97698 | J99: =J97+J98 -> 536.03744 | K99: =K97+K98 -> 525.31669 | ... AM99: =AM97+AM98 -> 298.36736 | AO99: =SUM(D99:O99) -> 6513.5682 | AP99: =SUM(P99:AA99) -> 5111.3059 | AQ99: =SUM(AB99:AM99) -> 4010.9272
A100: DCB 360
A101: количество кредитов | B101: шт | D101: =INT(D120/D116+D143/D139) -> 0 | E101: =INT(E120/E116+E143/E139) -> 0 | F101: =INT(F120/F116+F143/F139) -> 0 | G101: =INT(G120/G116+G143/G139) -> 0 | H101: =INT(H120/H116+H143/H139) -> 0 | I101: =INT(I120/I116+I143/I139) -> 0 | J101: =INT(J120/J116+J143/J139) -> 0 | K101: =INT(K120/K116+K143/K139) -> 0 | ... AM101: =INT(AM120/AM116+AM143/AM139) -> 0 | AO101: =O101 -> 0 | AP101: =AA101 -> 0 | AQ101: =AM101 -> 0
A102: кредитный портфель | B102: тыс сом | D102: =D120+D143*'0'!D17/1000 -> 0 | E102: =E120+E143*'0'!E17/1000 -> 0 | F102: =F120+F143*'0'!F17/1000 -> 0 | G102: =G120+G143*'0'!G17/1000 -> 0 | H102: =H120+H143*'0'!H17/1000 -> 0 | I102: =I120+I143*'0'!I17/1000 -> 0 | J102: =J120+J143*'0'!J17/1000 -> 0 | K102: =K120+K143*'0'!K17/1000 -> 0 | ... AM102: =AM120+AM143*'0'!AM17/1000 -> 0 | AO102: =O102 -> 0 | AP102: =AA102 -> 0 | AQ102: =AM102 -> 0
A103: просроченная задолженность | B103: тыс сом | D103: =D122+D145*'0'!D17/1000 -> 0 | E103: =E122+E145*'0'!E17/1000 -> 0 | F103: =F122+F145*'0'!F17/1000 -> 0 | G103: =G122+G145*'0'!G17/1000 -> 0 | H103: =H122+H145*'0'!H17/1000 -> 0 | I103: =I122+I145*'0'!I17/1000 -> 0 | J103: =J122+J145*'0'!J17/1000 -> 0 | K103: =K122+K145*'0'!K17/1000 -> 0 | ... AM103: =AM122+AM145*'0'!AM17/1000 -> 0 | AO103: =O103 -> 0 | AP103: =AA103 -> 0 | AQ103: =AM103 -> 0
...

Sheet РБ.2
A1: Розничный бизнес - Счета и депозиты
D3: 46023 | E3: 46054 | F3: 46082 | G3: 46113 | H3: 46143 | I3: 46174 | J3: 46204 | K3: 46235 | L3: 46266 | M3: 46296 | N3: 46327 | O3: 46357 | P3: 46388 | Q3: 46419 | R3: 46447 | S3: 46478 | T3: 46508 | U3: 46539 | V3: 46569 | W3: 46600 | X3: 46631 | Y3: 46661 | Z3: 46692 | AA3: 46722 | AB3: 46753 | AC3: 46784 | AD3: 46813 | AE3: 46844 | AF3: 46874 | AG3: 46905 | AH3: 46935 | AI3: 46966 | AJ3: 46997 | AK3: 47027 | AL3: 47058 | AM3: 47088 | AO3: =YEAR(O3) -> 2026 | AP3: =YEAR(AA3) -> 2027 | AQ3: =YEAR(AM3) -> 2028
D4: m1 | E4: m2 | F4: m3 | G4: m4 | H4: m5 | I4: m6 | J4: m7 | K4: m8 | L4: m9 | M4: m10 | N4: m11 | O4: m12 | P4: m13 | Q4: m14 | R4: m15 | S4: m16 | T4: m17 | U4: m18 | V4: m19 | W4: m20 | X4: m21 | Y4: m22 | Z4: m23 | AA4: m24 | AB4: m25 | AC4: m26 | AD4: m27 | AE4: m28 | AF4: m29 | AG4: m30 | AH4: m31 | AI4: m32 | AJ4: m33 | AK4: m34 | AL4: m35 | AM4: m36 | AO4: Y1 | AP4: Y2 | AQ4: Y3
D5: 1 | E5: =D5+1 -> 2 | F5: =E5+1 -> 3 | G5: =F5+1 -> 4 | H5: =G5+1 -> 5 | I5: =H5+1 -> 6 | J5: =I5+1 -> 7 | K5: =J5+1 -> 8 | L5: =K5+1 -> 9 | ... AM5: =AL5+1 -> 36
A6: сезонность | B6: % | D6: 0.4 | E6: 0.8 | F6: 1 | G6: 1 | H6: 1 | I6: 1 | J6: 1 | K6: 0.7 | L6: 1 | M6: 1 | N6: 0.9 | O6: 0.8 | P6: 0.4 | Q6: 0.8 | R6: 1 | S6: 1 | T6: 1 | U6: 1 | V6: 1 | W6: 0.7 | X6: 1 | Y6: 1 | Z6: 0.9 | AA6: 0.8 | AB6: 0.4 | AC6: 0.8 | AD6: 1 | AE6: 1 | AF6: 1 | AG6: 1 | AH6: 1 | AI6: 0.7 | AJ6: 1 | AK6: 1 | AL6: 0.9 | AM6: 0.8
A7: Итого
A8: портфель | B8: тыс сом | C8: =C18+C160+C204+C246+C378 -> 7154435.2 | D8: =D18+D160+D204+D246+D378 -> 7432358 | E8: =E18+E160+E204+E246+E378 -> 7486074.6 | F8: =F18+F160+F204+F246+F378 -> 7551198.3 | G8: =G18+G160+G204+G246+G378 -> 7625873.6 | H8: =H18+H160+H204+H246+H378 -> 7710566.2 | I8: =I18+I160+I204+I246+I378 -> 7802758 | J8: =J18+J160+J204+J246+J378 -> 7906893.5 | ... AM8: =AM18+AM160+AM204+AM246+AM378 -> 16073930 | AO8: =O8 -> 8568555.8 | AP8: =AA8 -> 11071363 | AQ8: =AM8 -> 16073930
A9: % расход | B9: тыс сом | D9: =D19+D161+D205+D247+D379 -> -67435.52 | E9: =E19+E161+E205+E247+E379 -> -67604.099 | F9: =F19+F161+F205+F247+F379 -> -68153.559 | G9: =G19+G161+G205+G247+G379 -> -68795.023 | H9: =H19+H161+H205+H247+H379 -> -69529.765 | I9: =I19+I161+I205+I247+I379 -> -70341.068 | J9: =J19+J161+J205+J247+J379 -> -71262.826 | K9: =K19+K161+K205+K247+K379 -> -72275.84 | ... AM9: =AM19+AM161+AM205+AM247+AM379 -> -141740.01 | AO9: =SUM(D9:O9) -> -856526.77 | AP9: =SUM(P9:AA9) -> -1060691.3 | AQ9: =SUM(AB9:AM9) -> -1447193.9
A10: трансфертный доход | B10: тыс сом | D10: =D20+D162+D206+D248+D380 -> 81475.629 | E10: =E20+E162+E206+E248+E380 -> 82492.427 | F10: =F20+F162+F206+F248+F380 -> 83198.783 | G10: =G20+G162+G206+G248+G380 -> 84017.909 | H10: =H20+H162+H206+H248+H380 -> 84948.685 | I10: =I20+I162+I206+I248+I380 -> 85973.63 | J10: =J20+J162+J206+J248+J380 -> 87126.21 | K10: =K20+K162+K206+K248+K380 -> 88375.472 | ... AM10: =AM20+AM162+AM206+AM248+AM380 -> 176292.38 | AO10: =SUM(D10:O10) -> 1045965.4 | AP10: =SUM(P10:AA10) -> 1299529.3 | AQ10: =SUM(AB10:AM10) -> 1786557.9
A11: операционные доходы | B11: тыс сом | D11: =D21+D163+D207+D249+D381 -> 14040.109 | E11: =E21+E163+E207+E249+E381 -> 14888.328 | F11: =F21+F163+F207+F249+F381 -> 15045.224 | G11: =G21+G163+G207+G249+G381 -> 15222.886 | H11: =H21+H163+H207+H249+H381 -> 15418.92 | I11: =I21+I163+I207+I249+I381 -> 15632.562 | J11: =J21+J163+J207+J249+J381 -> 15863.385 | K11: =K21+K163+K207+K249+K381 -> 16099.632 | ... AM11: =AM21+AM163+AM207+AM249+AM381 -> 34552.368 | AO11: =SUM(D11:O11) -> 189438.62 | AP11: =SUM(P11:AA11) -> 238838.06 | AQ11: =SUM(AB11:AM11) -> 339363.99
A12: начисление расходов в ФЗД | B12: тыс сом | D12: =D22+D164+D208+D250+D382 -> -1215.5661 | E12: =E22+E164+E208+E250+E382 -> -1243.2027 | F12: =F22+F164+F208+F250+F382 -> -1253.1061 | G12: =G22+G164+G208+G250+G382 -> -1264.756 | H12: =H22+H164+H208+H250+H382 -> -1278.0366 | I12: =I22+I164+I208+I250+I382 -> -1292.777 | J12: =J22+J164+J208+J250+J382 -> -1309.1376 | K12: =K22+K164+K208+K250+K382 -> -1326.8376 | ... AM12: =AM22+AM164+AM208+AM250+AM382 -> -2632.9423 | AO12: =SUM(D12:O12) -> -15703.491 | AP12: =SUM(P12:AA12) -> -19357.025 | AQ12: =SUM(AB12:AM12) -> -26557.707
A13: операционные расходы | B13: тыс сом | D13: =D23+D165+D209+D251+D383 -> -1645.2759 | E13: =E23+E165+E209+E251+E383 -> -1622.242 | F13: =F23+F165+F209+F251+F383 -> -1639.4697 | G13: =G23+G165+G209+G251+G383 -> -1658.6417 | H13: =H23+H165+H209+H251+H383 -> -1679.8174 | I13: =I23+I165+I209+I251+I383 -> -1702.647 | J13: =J23+J165+J209+J251+J383 -> -1727.5056 | K13: =K23+K165+K209+K251+K383 -> -1754.0996 | ... AM13: =AM23+AM165+AM209+AM251+AM383 -> -3395.1994 | AO13: =SUM(D13:O13) -> -20760.379 | AP13: =SUM(P13:AA13) -> -25768.799 | AQ13: =SUM(AB13:AM13) -> -34732.723
A14: прибыль | B14: тыс сом | D14: =D24+D166+D210+D252+D384 -> 12154.963 | E14: =E24+E166+E210+E252+E384 -> 13021.748 | F14: =F24+F166+F210+F252+F384 -> 13155.649 | G14: =G24+G166+G210+G252+G384 -> 13308.486 | H14: =H24+H166+H210+H252+H384 -> 13477.819 | I14: =I24+I166+I210+I252+I384 -> 13663.254 | J14: =J24+J166+J210+J252+J384 -> 13863.933 | K14: =K24+K166+K210+K252+K384 -> 14068.49 | ... AM14: =AM24+AM166+AM210+AM252+AM384 -> 30783.902 | AO14: =SUM(D14:O14) -> 165456.05 | AP14: =SUM(P14:AA14) -> 209291.89 | AQ14: =SUM(AB14:AM14) -> 300436
A16: Универсальный депозит "Бай Бол"
A17: Итого
A18: портфель | B18: тыс сом | C18: =C26+C92 -> 4767893.2 | D18: =D26+D92 -> 4707639.8 | E18: =E26+E92 -> 4713311.7 | F18: =F26+F92 -> 4728678.6 | G18: =G26+G92 -> 4753302.3 | H18: =H26+H92 -> 4788626.7 | I18: =I26+I92 -> 4831453.5 | J18: =J26+J92 -> 4885880 | ... AM18: =AM26+AM92 -> 11047443 | AO18: =O18 -> 5313921.6 | AP18: =AA18 -> 7278477.1 | AQ18: =AM18 -> 11047443
A19: % расход | B19: тыс сом | D19: =D27+D93 -> -50644.593 | E19: =E27+E93 -> -50500.482 | F19: =F27+F93 -> -50646.215 | G19: =G27+G93 -> -50891.945 | H19: =H27+H93 -> -51239.932 | I19: =I27+I93 -> -51674.794 | J19: =J27+J93 -> -52226.572 | K19: =K27+K93 -> -52882.872 | ... AM19: =AM27+AM93 -> -115611.34 | AO19: =SUM(D19:O19) -> -630972.97 | AP19: =SUM(P19:AA19) -> -796275.44 | AQ19: =SUM(AB19:AM19) -> -1153524.9
A20: трансфертный доход | B20: тыс сом | D20: =D28+D94 -> 58141.36 | E20: =E28+E94 -> 58059.124 | F20: =F28+F94 -> 58256.004 | G20: =G28+G94 -> 58565.718 | H20: =H28+H94 -> 58993.718 | I20: =I28+I94 -> 59524.481 | J20: =J28+J94 -> 60185.464 | K20: =K28+K94 -> 60964.999 | ... AM20: =AM28+AM94 -> 134824.74 | AO20: =SUM(D20:O20) -> 726864.26 | AP20: =SUM(P20:AA20) -> 921530.97 | AQ20: =SUM(AB20:AM20) -> 1341523.7
A21: операционные доходы | B21: тыс сом | D21: =D29+D95 -> 7496.7671 | E21: =E29+E95 -> 7558.6425 | F21: =F29+F95 -> 7609.7893 | G21: =G29+G95 -> 7673.7731 | H21: =H29+H95 -> 7753.7854 | I21: =I29+I95 -> 7849.6876 | J21: =J29+J95 -> 7958.8921 | K21: =K29+K95 -> 8082.127 | ... AM21: =AM29+AM95 -> 19213.399 | AO21: =SUM(D21:O21) -> 95891.293 | AP21: =SUM(P21:AA21) -> 125255.52 | AQ21: =SUM(AB21:AM21) -> 187998.83
A22: начисление расходов в ФЗД | B22: тыс сом | D22: =-0.2%*(C18+D18)/2/12 -> -789.62775 | E22: =-0.2%*(D18+E18)/2/12 -> -785.07929 | F22: =-0.2%*(E18+F18)/2/12 -> -786.83253 | G22: =-0.2%*(F18+G18)/2/12 -> -790.16507 | H22: =-0.2%*(G18+H18)/2/12 -> -795.16075 | I22: =-0.2%*(H18+I18)/2/12 -> -801.67335 | J22: =-0.2%*(I18+J18)/2/12 -> -809.77779 | K22: =-0.2%*(J18+K18)/2/12 -> -819.65127 | ... AM22: =-0.2%*(AL18+AM18)/2/12 -> -1807.7453 | AO22: =SUM(D22:O22) -> -9790.073 | AP22: =SUM(P22:AA22) -> -12340.031 | AQ22: =SUM(AB22:AM22) -> -17968.873
A23: операционные расходы | B23: тыс сом | D23: =D22+D30+D96 -> -1135.88 | E23: =E22+E30+E96 -> -1137.7614 | F23: =F22+F30+F96 -> -1146.1962 | G23: =G22+G30+G96 -> -1156.3678 | H23: =H22+H30+H96 -> -1168.6156 | I23: =I22+I30+I96 -> -1182.5344 | J23: =J22+J30+J96 -> -1198.4538 | K23: =K22+K30+K96 -> -1216.4981 | ... AM23: =AM22+AM30+AM96 -> -2510.9399 | AO23: =SUM(D23:O23) -> -14435.887 | AP23: =SUM(P23:AA23) -> -18282.238 | AQ23: =SUM(AB23:AM23) -> -25519.796
A24: прибыль | B24: тыс сом | D24: =D21+D23 -> 6360.8871 | E24: =E21+E23 -> 6420.8811 | F24: =F21+F23 -> 6463.5931 | G24: =G21+G23 -> 6517.4053 | H24: =H21+H23 -> 6585.1698 | I24: =I21+I23 -> 6667.1532 | J24: =J21+J23 -> 6760.4384 | K24: =K21+K23 -> 6865.629 | ... AM24: =AM21+AM23 -> 16702.459 | AO24: =SUM(D24:O24) -> 81455.406 | AP24: =SUM(P24:AA24) -> 106973.29 | AQ24: =SUM(AB24:AM24) -> 162479.03
A25: Безбумажный офис
A26: портфель | B26: тыс сом | C26: =C40+C55*'0'!C$16+C70*'0'!C$19+C85*'0'!C$17 -> 4766780.9 | D26: =D40+D55*'0'!D$16+D70*'0'!D$19+D85*'0'!D$17 -> 4706310.3 | E26: =E40+E55*'0'!E$16+E70*'0'!E$19+E85*'0'!E$17 -> 4711666.5 | F26: =F40+F55*'0'!F$16+F70*'0'!F$19+F85*'0'!F$17 -> 4726522.3 | G26: =G40+G55*'0'!G$16+G70*'0'!G$19+G85*'0'!G$17 -> 4750475.2 | H26: =H40+H55*'0'!H$16+H70*'0'!H$19+H85*'0'!H$17 -> 4784861.5 | I26: =I40+I55*'0'!I$16+I70*'0'!I$19+I85*'0'!I$17 -> 4826406.7 | J26: =J40+J55*'0'!J$16+J70*'0'!J$19+J85*'0'!J$17 -> 4879030.4 | ... AM26: =AM40+AM55*'0'!AM$16+AM70*'0'!AM$19+AM85*'0'!AM$17 -> 11011974 | AO26: =O26 -> 5281028.4 | AP26: =AA26 -> 7250520.6 | AQ26: =AM26 -> 11011974
A27: % расход | B27: тыс сом | D27: =D43+D58*'0'!D$16+D73*'0'!D$19+D88*'0'!D$17 -> -50631.873 | E27: =E43+E58*'0'!E$16+E73*'0'!E$19+E88*'0'!E$17 -> -50484.862 | F27: =F43+F58*'0'!F$16+F73*'0'!F$19+F88*'0'!F$17 -> -50626.203 | G27: =G43+G58*'0'!G$16+G73*'0'!G$19+G88*'0'!G$17 -> -50865.653 | H27: =H43+H58*'0'!H$16+H73*'0'!H$19+H88*'0'!H$17 -> -51205.08 | I27: =I43+I58*'0'!I$16+I73*'0'!I$19+I88*'0'!I$17 -> -51628.145 | J27: =J43+J58*'0'!J$16+J73*'0'!J$19+J88*'0'!J$17 -> -52163.494 | K27: =K43+K58*'0'!K$16+K73*'0'!K$19+K88*'0'!K$17 -> -52796.941 | ... AM27: =AM43+AM58*'0'!AM$16+AM73*'0'!AM$19+AM88*'0'!AM$17 -> -115234.24 | AO27: =SUM(D27:O27) -> -629865.33 | AP27: =SUM(P27:AA27) -> -792532.93 | AQ27: =SUM(AB27:AM27) -> -1149531.9
A28: трансфертный доход | B28: тыс сом | D28: =D44+D59*'0'!D$16+D74*'0'!D$19+D89*'0'!D$17 -> 58126.526 | E28: =E44+E59*'0'!E$16+E74*'0'!E$19+E89*'0'!E$17 -> 58040.927 | F28: =F44+F59*'0'!F$16+F74*'0'!F$19+F89*'0'!F$17 -> 58232.708 | G28: =G44+G59*'0'!G$16+G74*'0'!G$19+G89*'0'!G$17 -> 58535.133 | H28: =H44+H59*'0'!H$16+H74*'0'!H$19+H89*'0'!H$17 -> 58953.201 | I28: =I44+I59*'0'!I$16+I74*'0'!I$19+I89*'0'!I$17 -> 59470.277 | J28: =J44+J59*'0'!J$16+J74*'0'!J$19+J89*'0'!J$17 -> 60112.2 | K28: =K44+K59*'0'!K$16+K74*'0'!K$19+K89*'0'!K$17 -> 60865.243 | ... AM28: =AM44+AM59*'0'!AM$16+AM74*'0'!AM$19+AM89*'0'!AM$17 -> 134389.08 | AO28: =SUM(D28:O28) -> 725579.14 | AP28: =SUM(P28:AA28) -> 917198 | AQ28: =SUM(AB28:AM28) -> 1336908.3
A29: операционные доходы | B29: тыс сом | D29: =D45+D60*'0'!D$16+D75*'0'!D$19+D90*'0'!D$17 -> 7494.6527 | E29: =E45+E60*'0'!E$16+E75*'0'!E$19+E90*'0'!E$17 -> 7556.065 | F29: =F45+F60*'0'!F$16+F75*'0'!F$19+F90*'0'!F$17 -> 7606.5054 | G29: =G45+G60*'0'!G$16+G75*'0'!G$19+G90*'0'!G$17 -> 7669.4799 | H29: =H45+H60*'0'!H$16+H75*'0'!H$19+H90*'0'!H$17 -> 7748.1207 | I29: =I45+I60*'0'!I$16+I75*'0'!I$19+I90*'0'!I$17 -> 7842.132 | J29: =J45+J60*'0'!J$16+J75*'0'!J$19+J90*'0'!J$17 -> 7948.7066 | K29: =K45+K60*'0'!K$16+K75*'0'!K$19+K90*'0'!K$17 -> 8068.3021 | ... AM29: =AM45+AM60*'0'!AM$16+AM75*'0'!AM$19+AM90*'0'!AM$17 -> 19154.834 | AO29: =SUM(D29:O29) -> 95713.806 | AP29: =SUM(P29:AA29) -> 124665.07 | AQ29: =SUM(AB29:AM29) -> 187376.43
A30: операционные расходы | B30: тыс сом | D30: =-'OPEX+CAPEX'!I190 -> -346.25223 | E30: =-'OPEX+CAPEX'!J190 -> -352.68214 | F30: =-'OPEX+CAPEX'!K190 -> -359.36367 | G30: =-'OPEX+CAPEX'!L190 -> -366.20273 | H30: =-'OPEX+CAPEX'!M190 -> -373.45483 | I30: =-'OPEX+CAPEX'!N190 -> -380.86103 | J30: =-'OPEX+CAPEX'!O190 -> -388.67599 | K30: =-'OPEX+CAPEX'!P190 -> -396.84681 | ... AM30: =-'OPEX+CAPEX'!AR190 -> -703.1946 | AO30: =SUM(D30:O30) -> -4645.8139 | AP30: =SUM(P30:AA30) -> -5942.2066 | AQ30: =SUM(AB30:AM30) -> -7550.9225
A31: KGS
A32: количество депозитов на конец периода | B32: шт | C32: 9000 | D32: =C32+D34 -> 9360 | E32: =D32+E34 -> 9734 | F32: =E32+F34 -> 10123 | G32: =F32+G34 -> 10527 | H32: =G32+H34 -> 10948 | I32: =H32+I34 -> 11385 | J32: =I32+J34 -> 11840 | K32: =J32+K34 -> 12313 | ... AM32: =AL32+AM34 -> 36899 | AO32: =AVERAGE(D32:O32) -> 11716.917 | AP32: =AVERAGE(P32:AA32) -> 18751.917 | AQ32: =AVERAGE(AB32:AM32) -> 30014.667
A33: индекс прироста депозитов | B33: % | D33: 0.04 | E33: 0.04 | F33: 0.04 | G33: 0.04 | H33: 0.04 | I33: 0.04 | J33: 0.04 | K33: 0.04 | L33: 0.04 | M33: 0.04 | N33: 0.04 | O33: 0.04 | P33: 0.04 | Q33: 0.04 | R33: 0.04 | S33: 0.04 | T33: 0.04 | U33: 0.04 | V33: 0.04 | W33: 0.04 | X33: 0.04 | Y33: 0.04 | Z33: 0.04 | AA33: 0.04 | AB33: 0.04 | AC33: 0.04 | AD33: 0.04 | AE33: 0.04 | AF33: 0.04 | AG33: 0.04 | AH33: 0.04 | AI33: 0.04 | AJ33: 0.04 | AK33: 0.04 | AL33: 0.04 | AM33: 0.04 | AO33: =O33 -> 0.04 | AP33: =AA33 -> 0.04 | AQ33: =AM33 -> 0.04
A34: количество новых депозитов | B34: шт | D34: =INT(C32*D33) -> 360 | E34: =INT(D32*E33) -> 374 | F34: =INT(E32*F33) -> 389 | G34: =INT(F32*G33) -> 404 | H34: =INT(G32*H33) -> 421 | I34: =INT(H32*I33) -> 437 | J34: =INT(I32*J33) -> 455 | K34: =INT(J32*K33) -> 473 | ... AM34: =INT(AL32*AM33) -> 1419 | AO34: =SUM(D34:O34) -> 5402 | AP34: =SUM(P34:AA34) -> 8649 | AQ34: =SUM(AB34:AM34) -> 13848
A35: ср. сумма нового депозита | B35: тыс сом | D35: 600 | E35: 600 | F35: 600 | G35: 600 | H35: 600 | I35: 600 | J35: 600 | K35: 600 | L35: 600 | M35: 600 | N35: 600 | O35: 600 | P35: 600 | Q35: 600 | R35: 600 | S35: 600 | T35: 600 | U35: 600 | V35: 600 | W35: 600 | X35: 600 | Y35: 600 | Z35: 600 | AA35: 600 | AB35: 600 | AC35: 600 | AD35: 600 | AE35: 600 | AF35: 600 | AG35: 600 | AH35: 600 | AI35: 600 | AJ35: 600 | AK35: 600 | AL35: 600 | AM35: 600 | AO35: =AVERAGE(D35:O35) -> 600 | AP35: =AVERAGE(P35:AA35) -> 600 | AQ35: =AVERAGE(AB35:AM35) -> 600
A36: привлечение депозитов | B36: тыс сом | D36: =D34*D35 -> 216000 | E36: =E34*E35 -> 224400 | F36: =F34*F35 -> 233400 | G36: =G34*G35 -> 242400 | H36: =H34*H35 -> 252600 | I36: =I34*I35 -> 262200 | J36: =J34*J35 -> 273000 | K36: =K34*K35 -> 283800 | ... AM36: =AM34*AM35 -> 851400 | AO36: =SUM(D36:O36) -> 3241200 | AP36: =SUM(P36:AA36) -> 5189400 | AQ36: =SUM(AB36:AM36) -> 8308800
A37: капитализация % | B37: тыс сом | E37: =-D43/2 -> 24139.375 | F37: =-E43/2 -> 24190.534 | G37: =-F43/2 -> 24351.776 | H37: =-G43/2 -> 24554.281 | I37: =-H43/2 -> 24799.645 | J37: =-I43/2 -> 25087.58 | K37: =-J43/2 -> 25417.812 | L37: =-K43/2 -> 25791.707 | ... AM37: =-AL43/2 -> 55528.386 | AO37: =SUM(D37:O37) -> 278389.48 | AP37: =SUM(P37:AA37) -> 382895.24 | AQ37: =SUM(AB37:AM37) -> 554416.99
A38: cр. срок портфеля | B38: мес | D38: 20 | E38: 20 | F38: 20 | G38: 20 | H38: 20 | I38: 20 | J38: 20 | K38: 20 | L38: 20 | M38: 20 | N38: 20 | O38: 20 | P38: 20 | Q38: 20 | R38: 20 | S38: 20 | T38: 20 | U38: 20 | V38: 20 | W38: 20 | X38: 20 | Y38: 20 | Z38: 20 | AA38: 20 | AB38: 20 | AC38: 20 | AD38: 20 | AE38: 20 | AF38: 20 | AG38: 20 | AH38: 20 | AI38: 20 | AJ38: 20 | AK38: 20 | AL38: 20 | AM38: 20 | AO38: =AVERAGE(D38:O38) -> 20 | AP38: =AVERAGE(P38:AA38) -> 20 | AQ38: =AVERAGE(AB38:AM38) -> 20
A39: возвраты | B39: тыс сом | D39: =C40/D38 -> 223000 | E39: =D40/E38 -> 222650 | F39: =E40/F38 -> 223944.47 | G39: =F40/G38 -> 225626.77 | H39: =G40/H38 -> 227683.02 | I39: =H40/I38 -> 230156.59 | J39: =I40/J38 -> 232998.74 | K39: =J40/K38 -> 236253.18 | ... AM39: =AL40/AM38 -> 521785.2 | AO39: =SUM(D39:O39) -> 2807899.4 | AP39: =SUM(P39:AA39) -> 3581295.2 | AQ39: =SUM(AB39:AM39) -> 5205060
A40: портфель | B40: тыс сом | C40: 4460000 | D40: =C40+D36-D39+D37 -> 4453000 | E40: =D40+E36-E39+E37 -> 4478889.4 | F40: =E40+F36-F39+F37 -> 4512535.4 | G40: =F40+G36-G39+G37 -> 4553660.4 | H40: =G40+H36-H39+H37 -> 4603131.7 | I40: =H40+I36-I39+I37 -> 4659974.8 | J40: =I40+J36-J39+J37 -> 4725063.6 | K40: =J40+K36-K39+K37 -> 4798028.2 | ... AM40: =AL40+AM36-AM39+AM37 -> 10820847 | AO40: =O40 -> 5171690.1 | AP40: =AA40 -> 7162690.1 | AQ40: =AM40 -> 10820847
A41: ср. % ставка портфеля | B41: % | D41: 0.13 | E41: 0.13 | F41: 0.13 | G41: 0.13 | H41: 0.13 | I41: 0.13 | J41: 0.13 | K41: 0.13 | L41: 0.13 | M41: 0.13 | N41: 0.13 | O41: 0.13 | P41: 0.13 | Q41: 0.13 | R41: 0.13 | S41: 0.13 | T41: 0.13 | U41: 0.13 | V41: 0.13 | W41: 0.13 | X41: 0.13 | Y41: 0.13 | Z41: 0.13 | AA41: 0.13 | AB41: 0.13 | AC41: 0.13 | AD41: 0.13 | AE41: 0.13 | AF41: 0.13 | AG41: 0.13 | AH41: 0.13 | AI41: 0.13 | AJ41: 0.13 | AK41: 0.13 | AL41: 0.13 | AM41: 0.13 | AO41: =AVERAGE(D41:O41) -> 0.13 | AP41: =AVERAGE(P41:AA41) -> 0.13 | AQ41: =AVERAGE(AB41:AM41) -> 0.13
A42: ср. % ставка фондирования | B42: % | D42: 0.15 | E42: 0.15 | F42: 0.15 | G42: 0.15 | H42: 0.15 | I42: 0.15 | J42: 0.15 | K42: 0.15 | L42: 0.15 | M42: 0.15 | N42: 0.15 | O42: 0.15 | P42: 0.15 | Q42: 0.15 | R42: 0.15 | S42: 0.15 | T42: 0.15 | U42: 0.15 | V42: 0.15 | W42: 0.15 | X42: 0.15 | Y42: 0.15 | Z42: 0.15 | AA42: 0.15 | AB42: 0.15 | AC42: 0.15 | AD42: 0.15 | AE42: 0.15 | AF42: 0.15 | AG42: 0.15 | AH42: 0.15 | AI42: 0.15 | AJ42: 0.15 | AK42: 0.15 | AL42: 0.15 | AM42: 0.15 | AO42: =AVERAGE(D42:O42) -> 0.15 | AP42: =AVERAGE(P42:AA42) -> 0.15 | AQ42: =AVERAGE(AB42:AM42) -> 0.15
A43: % расход | B43: тыс сом | D43: =-(C40+D40)/2*D41/12 -> -48278.75 | E43: =-(D40+E40)/2*E41/12 -> -48381.067 | F43: =-(E40+F40)/2*F41/12 -> -48703.551 | G43: =-(F40+G40)/2*G41/12 -> -49108.561 | H43: =-(G40+H40)/2*H41/12 -> -49599.291 | I43: =-(H40+I40)/2*I41/12 -> -50175.16 | J43: =-(I40+J40)/2*J41/12 -> -50835.624 | K43: =-(J40+K40)/2*K41/12 -> -51583.414 | ... AM43: =-(AL40+AM40)/2*AM41/12 -> -115139.65 | AO43: =SUM(D43:O43) -> -612233.19 | AP43: =SUM(P43:AA43) -> -786731.88 | AQ43: =SUM(AB43:AM43) -> -1147578
A44: трансфертный доход | B44: тыс сом | D44: =(C40+D40)/2*D42/12 -> 55706.25 | E44: =(D40+E40)/2*E42/12 -> 55824.309 | F44: =(E40+F40)/2*F42/12 -> 56196.405 | G44: =(F40+G40)/2*G42/12 -> 56663.724 | H44: =(G40+H40)/2*H42/12 -> 57229.951 | I44: =(H40+I40)/2*I42/12 -> 57894.415 | J44: =(I40+J40)/2*J42/12 -> 58656.49 | K44: =(J40+K40)/2*K42/12 -> 59519.324 | ... AM44: =(AL40+AM40)/2*AM42/12 -> 132853.44 | AO44: =SUM(D44:O44) -> 706422.91 | AP44: =SUM(P44:AA44) -> 907767.56 | AQ44: =SUM(AB44:AM44) -> 1324128.5
A45: операционные доходы | B45: тыс сом | D45: =SUM(D43:D44) -> 7427.5 | E45: =SUM(E43:E44) -> 7443.2411 | F45: =SUM(F43:F44) -> 7492.854 | G45: =SUM(G43:G44) -> 7555.1632 | H45: =SUM(H43:H44) -> 7630.6601 | I45: =SUM(I43:I44) -> 7719.2554 | J45: =SUM(J43:J44) -> 7820.8653 | K45: =SUM(K43:K44) -> 7935.9099 | ... AM45: =SUM(AM43:AM44) -> 17713.793 | AO45: =SUM(D45:O45) -> 94189.721 | AP45: =SUM(P45:AA45) -> 121035.67 | AQ45: =SUM(AB45:AM45) -> 176550.46
A46: RUB
A47: количество депозитов на конец периода | B47: шт | C47: 504 | D47: =C47+D49 -> 504 | E47: =D47+E49 -> 504 | F47: =E47+F49 -> 504 | G47: =F47+G49 -> 504 | H47: =G47+H49 -> 504 | I47: =H47+I49 -> 504 | J47: =I47+J49 -> 504 | K47: =J47+K49 -> 504 | ... AM47: =AL47+AM49 -> 504 | AO47: =AVERAGE(D47:O47) -> 504 | AP47: =AVERAGE(P47:AA47) -> 504 | AQ47: =AVERAGE(AB47:AM47) -> 504
A48: индекс прироста депозитов | B48: % | D48: 0 | E48: 0 | F48: 0 | G48: 0 | H48: 0 | I48: 0 | J48: 0 | K48: 0 | L48: 0 | M48: 0 | N48: 0 | O48: 0 | P48: 0 | Q48: 0 | R48: 0 | S48: 0 | T48: 0 | U48: 0 | V48: 0 | W48: 0 | X48: 0 | Y48: 0 | Z48: 0 | AA48: 0 | AB48: 0 | AC48: 0 | AD48: 0 | AE48: 0 | AF48: 0 | AG48: 0 | AH48: 0 | AI48: 0 | AJ48: 0 | AK48: 0 | AL48: 0 | AM48: 0 | AO48: =O48 -> 0 | AP48: =AA48 -> 0 | AQ48: =AM48 -> 0
A49: количество новых депозитов | B49: шт | D49: =INT(C47*D48) -> 0 | E49: =INT(D47*E48) -> 0 | F49: =INT(E47*F48) -> 0 | G49: =INT(F47*G48) -> 0 | H49: =INT(G47*H48) -> 0 | I49: =INT(H47*I48) -> 0 | J49: =INT(I47*J48) -> 0 | K49: =INT(J47*K48) -> 0 | ... AM49: =INT(AL47*AM48) -> 0 | AO49: =SUM(D49:O49) -> 0 | AP49: =SUM(P49:AA49) -> 0 | AQ49: =SUM(AB49:AM49) -> 0
A50: ср. сумма нового депозита | B50: тыс руб | D50: 518.25397 | E50: 518.25397 | F50: 518.25397 | G50: 518.25397 | H50: 518.25397 | I50: 518.25397 | J50: 518.25397 | K50: 518.25397 | L50: 518.25397 | M50: 518.25397 | N50: 518.25397 | O50: 518.25397 | P50: 518.25397 | Q50: 518.25397 | R50: 518.25397 | S50: 518.25397 | T50: 518.25397 | U50: 518.25397 | V50: 518.25397 | W50: 518.25397 | X50: 518.25397 | Y50: 518.25397 | Z50: 518.25397 | AA50: 518.25397 | AB50: 518.25397 | AC50: 518.25397 | AD50: 518.25397 | AE50: 518.25397 | AF50: 518.25397 | AG50: 518.25397 | AH50: 518.25397 | AI50: 518.25397 | AJ50: 518.25397 | AK50: 518.25397 | AL50: 518.25397 | AM50: 518.25397 | AO50: =AVERAGE(D50:O50) -> 518.25397 | AP50: =AVERAGE(P50:AA50) -> 518.25397 | AQ50: =AVERAGE(AB50:AM50) -> 518.25397
A51: привлечение депозитов | B51: тыс руб | D51: =D49*D50 -> 0 | E51: =E49*E50 -> 0 | F51: =F49*F50 -> 0 | G51: =G49*G50 -> 0 | H51: =H49*H50 -> 0 | I51: =I49*I50 -> 0 | J51: =J49*J50 -> 0 | K51: =K49*K50 -> 0 | ... AM51: =AM49*AM50 -> 0 | AO51: =SUM(D51:O51) -> 0 | AP51: =SUM(P51:AA51) -> 0 | AQ51: =SUM(AB51:AM51) -> 0
A52: капитализация % | B52: тыс руб | E52: =-D58/2 -> 1142.75 | F52: =-E58/2 -> 1041.4824 | G52: =-F58/2 -> 951.80775 | H52: =-G58/2 -> 869.84773 | I52: =-H58/2 -> 794.94529 | J52: =-I58/2 -> 726.49269 | K52: =-J58/2 -> 663.93453 | L52: =-K58/2 -> 606.76324 | ... AM52: =-AL58/2 -> 53.352827 | AO52: =SUM(D52:O52) -> 8322.4326 | AP52: =SUM(P52:AA52) -> 3246.9289 | AQ52: =SUM(AB52:AM52) -> 1102.0489
A53: cр. срок портфеля | B53: мес | D53: 11 | E53: 11 | F53: 11 | G53: 11 | H53: 11 | I53: 11 | J53: 11 | K53: 11 | L53: 11 | M53: 11 | N53: 11 | O53: 11 | P53: 11 | Q53: 11 | R53: 11 | S53: 11 | T53: 11 | U53: 11 | V53: 11 | W53: 11 | X53: 11 | Y53: 11 | Z53: 11 | AA53: 11 | AB53: 11 | AC53: 11 | AD53: 11 | AE53: 11 | AF53: 11 | AG53: 11 | AH53: 11 | AI53: 11 | AJ53: 11 | AK53: 11 | AL53: 11 | AM53: 11 | AO53: =AVERAGE(D53:O53) -> 11 | AP53: =AVERAGE(P53:AA53) -> 11 | AQ53: =AVERAGE(AB53:AM53) -> 11
A54: возвраты | B54: тыс руб | D54: =C55/D53 -> 23745.455 | E54: =D55/E53 -> 21586.777 | F54: =E55/F53 -> 19728.229 | G54: =F55/G53 -> 18029.434 | H54: =G55/H53 -> 16476.922 | I54: =H55/I53 -> 15058.097 | J54: =I55/J53 -> 13761.447 | K54: =J55/K53 -> 12576.451 | ... AM54: =AL55/AM53 -> 1010.6256 | AO54: =SUM(D54:O54) -> 181332.13 | AP54: =SUM(P54:AA54) -> 61504.324 | AQ54: =SUM(AB54:AM54) -> 20875.348
A55: портфель | B55: тыс руб | C55: 261200 | D55: =C55+D51-D54+D52 -> 237454.55 | E55: =D55+E51-E54+E52 -> 217010.52 | F55: =E55+F51-F54+F52 -> 198323.77 | G55: =F55+G51-G54+G52 -> 181246.15 | H55: =G55+H51-H54+H52 -> 165639.07 | I55: =H55+I51-I54+I52 -> 151375.92 | J55: =I55+J51-J54+J52 -> 138340.96 | K55: =J55+K51-K54+K52 -> 126428.45 | ... AM55: =AL55+AM51-AM54+AM52 -> 10159.609 | AO55: =O55 -> 88190.303 | AP55: =AA55 -> 29932.908 | AQ55: =AM55 -> 10159.609
A56: ср. % ставка портфеля | B56: % | D56: 0.11 | E56: 0.11 | F56: 0.11 | G56: 0.11 | H56: 0.11 | I56: 0.11 | J56: 0.11 | K56: 0.11 | L56: 0.11 | M56: 0.11 | N56: 0.11 | O56: 0.11 | P56: 0.11 | Q56: 0.11 | R56: 0.11 | S56: 0.11 | T56: 0.11 | U56: 0.11 | V56: 0.11 | W56: 0.11 | X56: 0.11 | Y56: 0.11 | Z56: 0.11 | AA56: 0.11 | AB56: 0.11 | AC56: 0.11 | AD56: 0.11 | AE56: 0.11 | AF56: 0.11 | AG56: 0.11 | AH56: 0.11 | AI56: 0.11 | AJ56: 0.11 | AK56: 0.11 | AL56: 0.11 | AM56: 0.11 | AO56: =AVERAGE(D56:O56) -> 0.11 | AP56: =AVERAGE(P56:AA56) -> 0.11 | AQ56: =AVERAGE(AB56:AM56) -> 0.11
A57: ср. % ставка фондирования | B57: % | D57: 0.11 | E57: 0.11 | F57: 0.11 | G57: 0.11 | H57: 0.11 | I57: 0.11 | J57: 0.11 | K57: 0.11 | L57: 0.11 | M57: 0.11 | N57: 0.11 | O57: 0.11 | P57: 0.11 | Q57: 0.11 | R57: 0.11 | S57: 0.11 | T57: 0.11 | U57: 0.11 | V57: 0.11 | W57: 0.11 | X57: 0.11 | Y57: 0.11 | Z57: 0.11 | AA57: 0.11 | AB57: 0.11 | AC57: 0.11 | AD57: 0.11 | AE57: 0.11 | AF57: 0.11 | AG57: 0.11 | AH57: 0.11 | AI57: 0.11 | AJ57: 0.11 | AK57: 0.11 | AL57: 0.11 | AM57: 0.11 | AO57: =AVERAGE(D57:O57) -> 0.11 | AP57: =AVERAGE(P57:AA57) -> 0.11 | AQ57: =AVERAGE(AB57:AM57) -> 0.11
A58: % расход | B58: тыс руб | D58: =-(C55+D55)/2*D56/12 -> -2285.5 | E58: =-(D55+E55)/2*E56/12 -> -2082.9649 | F58: =-(E55+F55)/2*F56/12 -> -1903.6155 | G58: =-(F55+G55)/2*G56/12 -> -1739.6955 | H58: =-(G55+H55)/2*H56/12 -> -1589.8906 | I58: =-(H55+I55)/2*I56/12 -> -1452.9854 | J58: =-(I55+J55)/2*J56/12 -> -1327.8691 | K58: =-(J55+K55)/2*K56/12 -> -1213.5265 | ... AM58: =-(AL55+AM55)/2*AM56/12 -> -97.517248 | AO58: =SUM(D58:O58) -> -17491.362 | AP58: =SUM(P58:AA58) -> -5934.6729 | AQ58: =SUM(AB58:AM58) -> -2014.3033
A59: трансфертный доход | B59: тыс руб | D59: =(C55+D55)/2*D57/12 -> 2285.5 | E59: =(D55+E55)/2*E57/12 -> 2082.9649 | F59: =(E55+F55)/2*F57/12 -> 1903.6155 | G59: =(F55+G55)/2*G57/12 -> 1739.6955 | H59: =(G55+H55)/2*H57/12 -> 1589.8906 | I59: =(H55+I55)/2*I57/12 -> 1452.9854 | J59: =(I55+J55)/2*J57/12 -> 1327.8691 | K59: =(J55+K55)/2*K57/12 -> 1213.5265 | ... AM59: =(AL55+AM55)/2*AM57/12 -> 97.517248 | AO59: =SUM(D59:O59) -> 17491.362 | AP59: =SUM(P59:AA59) -> 5934.6729 | AQ59: =SUM(AB59:AM59) -> 2014.3033
A60: операционные доходы | B60: тыс руб | D60: =SUM(D58:D59) -> 0 | E60: =SUM(E58:E59) -> 0 | F60: =SUM(F58:F59) -> 0 | G60: =SUM(G58:G59) -> 0 | H60: =SUM(H58:H59) -> 0 | I60: =SUM(I58:I59) -> 0 | J60: =SUM(J58:J59) -> 0 | K60: =SUM(K58:K59) -> 0 | ... AM60: =SUM(AM58:AM59) -> 0 | AO60: =SUM(D60:O60) -> 0 | AP60: =SUM(P60:AA60) -> 0 | AQ60: =SUM(AB60:AM60) -> 0
A61: KZT
A62: количество депозитов на конец периода | B62: шт | C62: 0 | D62: =C62+D64 -> 0 | E62: =D62+E64 -> 0 | F62: =E62+F64 -> 0 | G62: =F62+G64 -> 0 | H62: =G62+H64 -> 0 | I62: =H62+I64 -> 0 | J62: =I62+J64 -> 0 | K62: =J62+K64 -> 0 | ... AM62: =AL62+AM64 -> 0 | AO62: =AVERAGE(D62:O62) -> 0 | AP62: =AVERAGE(P62:AA62) -> 0 | AQ62: =AVERAGE(AB62:AM62) -> 0
A63: индекс прироста депозитов | B63: % | D63: 0.01 | E63: 0.01 | F63: 0.01 | G63: 0.01 | H63: 0.01 | I63: 0.01 | J63: 0.01 | K63: 0.01 | L63: 0.01 | M63: 0.01 | N63: 0.01 | O63: 0.01 | P63: 0.01 | Q63: 0.01 | R63: 0.01 | S63: 0.01 | T63: 0.01 | U63: 0.01 | V63: 0.01 | W63: 0.01 | X63: 0.01 | Y63: 0.01 | Z63: 0.01 | AA63: 0.01 | AB63: 0.01 | AC63: 0.01 | AD63: 0.01 | AE63: 0.01 | AF63: 0.01 | AG63: 0.01 | AH63: 0.01 | AI63: 0.01 | AJ63: 0.01 | AK63: 0.01 | AL63: 0.01 | AM63: 0.01 | AO63: =O63 -> 0.01 | AP63: =AA63 -> 0.01 | AQ63: =AM63 -> 0.01
A64: количество новых депозитов | B64: шт | D64: =INT(C62*D63) -> 0 | E64: =INT(D62*E63) -> 0 | F64: =INT(E62*F63) -> 0 | G64: =INT(F62*G63) -> 0 | H64: =INT(G62*H63) -> 0 | I64: =INT(H62*I63) -> 0 | J64: =INT(I62*J63) -> 0 | K64: =INT(J62*K63) -> 0 | ... AM64: =INT(AL62*AM63) -> 0 | AO64: =SUM(D64:O64) -> 0 | AP64: =SUM(P64:AA64) -> 0 | AQ64: =SUM(AB64:AM64) -> 0
A65: ср. сумма нового депозита | B65: тыс. тенге | D65: 50 | E65: 50 | F65: 50 | G65: 50 | H65: 50 | I65: 50 | J65: 50 | K65: 50 | L65: 50 | M65: 50 | N65: 50 | O65: 50 | P65: 50 | Q65: 50 | R65: 50 | S65: 50 | T65: 50 | U65: 50 | V65: 50 | W65: 50 | X65: 50 | Y65: 50 | Z65: 50 | AA65: 50 | AB65: 50 | AC65: 50 | AD65: 50 | AE65: 50 | AF65: 50 | AG65: 50 | AH65: 50 | AI65: 50 | AJ65: 50 | AK65: 50 | AL65: 50 | AM65: 50 | AO65: =AVERAGE(D65:O65) -> 50 | AP65: =AVERAGE(P65:AA65) -> 50 | AQ65: =AVERAGE(AB65:AM65) -> 50
A66: привлечение депозитов | B66: тыс. тенге | D66: =D64*D65 -> 0 | E66: =E64*E65 -> 0 | F66: =F64*F65 -> 0 | G66: =G64*G65 -> 0 | H66: =H64*H65 -> 0 | I66: =I64*I65 -> 0 | J66: =J64*J65 -> 0 | K66: =K64*K65 -> 0 | ... AM66: =AM64*AM65 -> 0 | AO66: =SUM(D66:O66) -> 0 | AP66: =SUM(P66:AA66) -> 0 | AQ66: =SUM(AB66:AM66) -> 0
A67: капитализация % | B67: тыс. тенге | E67: =-D73/2 -> 0 | F67: =-E73/2 -> 0 | G67: =-F73/2 -> 0 | H67: =-G73/2 -> 0 | I67: =-H73/2 -> 0 | J67: =-I73/2 -> 0 | K67: =-J73/2 -> 0 | L67: =-K73/2 -> 0 | ... AM67: =-AL73/2 -> 0 | AO67: =SUM(D67:O67) -> 0 | AP67: =SUM(P67:AA67) -> 0 | AQ67: =SUM(AB67:AM67) -> 0
A68: cр. срок портфеля | B68: мес | D68: 12 | E68: 12 | F68: 12 | G68: 12 | H68: 12 | I68: 12 | J68: 12 | K68: 12 | L68: 12 | M68: 12 | N68: 12 | O68: 12 | P68: 12 | Q68: 12 | R68: 12 | S68: 12 | T68: 12 | U68: 12 | V68: 12 | W68: 12 | X68: 12 | Y68: 12 | Z68: 12 | AA68: 12 | AB68: 12 | AC68: 12 | AD68: 12 | AE68: 12 | AF68: 12 | AG68: 12 | AH68: 12 | AI68: 12 | AJ68: 12 | AK68: 12 | AL68: 12 | AM68: 12 | AO68: =AVERAGE(D68:O68) -> 12 | AP68: =AVERAGE(P68:AA68) -> 12 | AQ68: =AVERAGE(AB68:AM68) -> 12
A69: возвраты | B69: тыс. тенге | D69: =C70/D68 -> 0 | E69: =D70/E68 -> 0 | F69: =E70/F68 -> 0 | G69: =F70/G68 -> 0 | H69: =G70/H68 -> 0 | I69: =H70/I68 -> 0 | J69: =I70/J68 -> 0 | K69: =J70/K68 -> 0 | ... AM69: =AL70/AM68 -> 0 | AO69: =SUM(D69:O69) -> 0 | AP69: =SUM(P69:AA69) -> 0 | AQ69: =SUM(AB69:AM69) -> 0
A70: портфель | B70: тыс. тенге | C70: 0 | D70: =C70+D66-D69+D67 -> 0 | E70: =D70+E66-E69+E67 -> 0 | F70: =E70+F66-F69+F67 -> 0 | G70: =F70+G66-G69+G67 -> 0 | H70: =G70+H66-H69+H67 -> 0 | I70: =H70+I66-I69+I67 -> 0 | J70: =I70+J66-J69+J67 -> 0 | K70: =J70+K66-K69+K67 -> 0 | ... AM70: =AL70+AM66-AM69+AM67 -> 0 | AO70: =O70 -> 0 | AP70: =AA70 -> 0 | AQ70: =AM70 -> 0
A71: ср. % ставка портфеля | B71: % | D71: 0.14 | E71: 0.14 | F71: 0.14 | G71: 0.14 | H71: 0.14 | I71: 0.14 | J71: 0.14 | K71: 0.14 | L71: 0.14 | M71: 0.14 | N71: 0.14 | O71: 0.14 | P71: 0.14 | Q71: 0.14 | R71: 0.14 | S71: 0.14 | T71: 0.14 | U71: 0.14 | V71: 0.14 | W71: 0.14 | X71: 0.14 | Y71: 0.14 | Z71: 0.14 | AA71: 0.14 | AB71: 0.14 | AC71: 0.14 | AD71: 0.14 | AE71: 0.14 | AF71: 0.14 | AG71: 0.14 | AH71: 0.14 | AI71: 0.14 | AJ71: 0.14 | AK71: 0.14 | AL71: 0.14 | AM71: 0.14 | AO71: =AVERAGE(D71:O71) -> 0.14 | AP71: =AVERAGE(P71:AA71) -> 0.14 | AQ71: =AVERAGE(AB71:AM71) -> 0.14
A72: ср. % ставка фондирования | B72: % | D72: 0.16 | E72: 0.16 | F72: 0.16 | G72: 0.16 | H72: 0.16 | I72: 0.16 | J72: 0.16 | K72: 0.16 | L72: 0.16 | M72: 0.16 | N72: 0.16 | O72: 0.16 | P72: 0.16 | Q72: 0.16 | R72: 0.16 | S72: 0.16 | T72: 0.16 | U72: 0.16 | V72: 0.16 | W72: 0.16 | X72: 0.16 | Y72: 0.16 | Z72: 0.16 | AA72: 0.16 | AB72: 0.16 | AC72: 0.16 | AD72: 0.16 | AE72: 0.16 | AF72: 0.16 | AG72: 0.16 | AH72: 0.16 | AI72: 0.16 | AJ72: 0.16 | AK72: 0.16 | AL72: 0.16 | AM72: 0.16 | AO72: =AVERAGE(D72:O72) -> 0.16 | AP72: =AVERAGE(P72:AA72) -> 0.16 | AQ72: =AVERAGE(AB72:AM72) -> 0.16
A73: % расход | B73: тыс. тенге | D73: =-(C70+D70)/2*D71/12 -> 0 | E73: =-(D70+E70)/2*E71/12 -> 0 | F73: =-(E70+F70)/2*F71/12 -> 0 | G73: =-(F70+G70)/2*G71/12 -> 0 | H73: =-(G70+H70)/2*H71/12 -> 0 | I73: =-(H70+I70)/2*I71/12 -> 0 | J73: =-(I70+J70)/2*J71/12 -> 0 | K73: =-(J70+K70)/2*K71/12 -> 0 | ... AM73: =-(AL70+AM70)/2*AM71/12 -> 0 | AO73: =SUM(D73:O73) -> 0 | AP73: =SUM(P73:AA73) -> 0 | AQ73: =SUM(AB73:AM73) -> 0
A74: трансфертный доход | B74: тыс. тенге | D74: =(C70+D70)/2*D72/12 -> 0 | E74: =(D70+E70)/2*E72/12 -> 0 | F74: =(E70+F70)/2*F72/12 -> 0 | G74: =(F70+G70)/2*G72/12 -> 0 | H74: =(G70+H70)/2*H72/12 -> 0 | I74: =(H70+I70)/2*I72/12 -> 0 | J74: =(I70+J70)/2*J72/12 -> 0 | K74: =(J70+K70)/2*K72/12 -> 0 | ... AM74: =(AL70+AM70)/2*AM72/12 -> 0 | AO74: =SUM(D74:O74) -> 0 | AP74: =SUM(P74:AA74) -> 0 | AQ74: =SUM(AB74:AM74) -> 0
A75: операционные доходы | B75: тыс. тенге | D75: =SUM(D73:D74) -> 0 | E75: =SUM(E73:E74) -> 0 | F75: =SUM(F73:F74) -> 0 | G75: =SUM(G73:G74) -> 0 | H75: =SUM(H73:H74) -> 0 | I75: =SUM(I73:I74) -> 0 | J75: =SUM(J73:J74) -> 0 | K75: =SUM(K73:K74) -> 0 | ... AM75: =SUM(AM73:AM74) -> 0 | AO75: =SUM(D75:O75) -> 0 | AP75: =SUM(P75:AA75) -> 0 | AQ75: =SUM(AB75:AM75) -> 0
A76: USD
A77: количество депозитов на конец периода | B77: шт | C77: 22 | D77: =C77+D79 -> 24 | E77: =D77+E79 -> 26 | F77: =E77+F79 -> 28 | G77: =F77+G79 -> 30 | H77: =G77+H79 -> 33 | I77: =H77+I79 -> 36 | J77: =I77+J79 -> 39 | K77: =J77+K79 -> 42 | ... AM77: =AL77+AM79 -> 550 | AO77: =AVERAGE(D77:O77) -> 39.083333 | AP77: =AVERAGE(P77:AA77) -> 113.66667 | AQ77: =AVERAGE(AB77:AM77) -> 345.08333
A78: индекс прироста депозитов | B78: % | D78: 0.1 | E78: 0.1 | F78: 0.1 | G78: 0.1 | H78: 0.1 | I78: 0.1 | J78: 0.1 | K78: 0.1 | L78: 0.1 | M78: 0.1 | N78: 0.1 | O78: 0.1 | P78: 0.1 | Q78: 0.1 | R78: 0.1 | S78: 0.1 | T78: 0.1 | U78: 0.1 | V78: 0.1 | W78: 0.1 | X78: 0.1 | Y78: 0.1 | Z78: 0.1 | AA78: 0.1 | AB78: 0.1 | AC78: 0.1 | AD78: 0.1 | AE78: 0.1 | AF78: 0.1 | AG78: 0.1 | AH78: 0.1 | AI78: 0.1 | AJ78: 0.1 | AK78: 0.1 | AL78: 0.1 | AM78: 0.1 | AO78: =O78 -> 0.1 | AP78: =AA78 -> 0.1 | AQ78: =AM78 -> 0.1
A79: количество новых депозитов | B79: шт | D79: =INT(C77*D78) -> 2 | E79: =INT(D77*E78) -> 2 | F79: =INT(E77*F78) -> 2 | G79: =INT(F77*G78) -> 2 | H79: =INT(G77*H78) -> 3 | I79: =INT(H77*I78) -> 3 | J79: =INT(I77*J78) -> 3 | K79: =INT(J77*K78) -> 3 | ... AM79: =INT(AL77*AM78) -> 50 | AO79: =SUM(D79:O79) -> 38 | AP79: =SUM(P79:AA79) -> 119 | AQ79: =SUM(AB79:AM79) -> 371
A80: ср. сумма нового депозита | B80: тыс. долл | D80: 6.9545455 | E80: 6.9545455 | F80: 6.9545455 | G80: 6.9545455 | H80: 6.9545455 | I80: 6.9545455 | J80: 6.9545455 | K80: 6.9545455 | L80: 6.9545455 | M80: 6.9545455 | N80: 6.9545455 | O80: 6.9545455 | P80: 6.9545455 | Q80: 6.9545455 | R80: 6.9545455 | S80: 6.9545455 | T80: 6.9545455 | U80: 6.9545455 | V80: 6.9545455 | W80: 6.9545455 | X80: 6.9545455 | Y80: 6.9545455 | Z80: 6.9545455 | AA80: 6.9545455 | AB80: 6.9545455 | AC80: 6.9545455 | AD80: 6.9545455 | AE80: 6.9545455 | AF80: 6.9545455 | AG80: 6.9545455 | AH80: 6.9545455 | AI80: 6.9545455 | AJ80: 6.9545455 | AK80: 6.9545455 | AL80: 6.9545455 | AM80: 6.9545455 | AO80: =AVERAGE(D80:O80) -> 6.9545455 | AP80: =AVERAGE(P80:AA80) -> 6.9545455 | AQ80: =AVERAGE(AB80:AM80) -> 6.9545455
A81: привлечение депозитов | B81: тыс. долл | D81: =D79*D80 -> 13.909091 | E81: =E79*E80 -> 13.909091 | F81: =F79*F80 -> 13.909091 | G81: =G79*G80 -> 13.909091 | H81: =H79*H80 -> 20.863636 | I81: =I79*I80 -> 20.863636 | J81: =J79*J80 -> 20.863636 | K81: =K79*K80 -> 20.863636 | ... AM81: =AM79*AM80 -> 347.72727 | AO81: =SUM(D81:O81) -> 264.27273 | AP81: =SUM(P81:AA81) -> 827.59091 | AQ81: =SUM(AB81:AM81) -> 2580.1364
A82: капитализация % | B82: тыс. долл | E82: =-D88/2 -> 0.25596591 | F82: =-E88/2 -> 0 | G82: =-F88/2 -> 0 | H82: =-G88/2 -> 0 | I82: =-H88/2 -> 0 | J82: =-I88/2 -> 0 | K82: =-J88/2 -> 0 | L82: =-K88/2 -> 0 | ... AM82: =-AL88/2 -> 0 | AO82: =SUM(D82:O82) -> 0.25596591 | AP82: =SUM(P82:AA82) -> 0 | AQ82: =SUM(AB82:AM82) -> 0
A83: cр. срок портфеля | B83: мес | D83: 12 | E83: 12 | F83: 12 | G83: 12 | H83: 12 | I83: 12 | J83: 12 | K83: 12 | L83: 12 | M83: 12 | N83: 12 | O83: 12 | P83: 12 | Q83: 12 | R83: 12 | S83: 12 | T83: 12 | U83: 12 | V83: 12 | W83: 12 | X83: 12 | Y83: 12 | Z83: 12 | AA83: 12 | AB83: 12 | AC83: 12 | AD83: 12 | AE83: 12 | AF83: 12 | AG83: 12 | AH83: 12 | AI83: 12 | AJ83: 12 | AK83: 12 | AL83: 12 | AM83: 12 | AO83: =AVERAGE(D83:O83) -> 12 | AP83: =AVERAGE(P83:AA83) -> 12 | AQ83: =AVERAGE(AB83:AM83) -> 12
A84: возвраты | B84: тыс. долл | D84: =C85/D83 -> 12.75 | E84: =D85/E83 -> 12.846591 | F84: =E85/F83 -> 12.956463 | G84: =F85/G83 -> 13.035849 | H84: =G85/H83 -> 13.108619 | I84: =H85/I83 -> 13.75487 | J84: =I85/J83 -> 14.347268 | K84: =J85/K83 -> 14.890298 | ... AM84: =AL85/AM83 -> 156.83063 | AO84: =SUM(D84:O84) -> 175.69877 | AP84: =SUM(P84:AA84) -> 397.0875 | AQ84: =SUM(AB84:AM84) -> 1179.6054
A85: портфель | B85: тыс. долл | C85: 153 | D85: =C85+D81-D84+D82 -> 154.15909 | E85: =D85+E81-E84+E82 -> 155.47756 | F85: =E85+F81-F84+F82 -> 156.43018 | G85: =F85+G81-G84+G82 -> 157.30343 | H85: =G85+H81-H84+H82 -> 165.05844 | I85: =H85+I81-I84+I82 -> 172.16721 | J85: =I85+J81-J84+J82 -> 178.68358 | K85: =J85+K81-K84+K82 -> 184.65692 | ... AM85: =AL85+AM81-AM84+AM82 -> 2072.8642 | AO85: =O85 -> 241.82992 | AP85: =AA85 -> 672.33332 | AQ85: =AM85 -> 2072.8642
A86: ср. % ставка портфеля | B86: % | D86: 0.04 | E86: 0 | F86: 0 | G86: 0 | H86: 0 | I86: 0 | J86: 0 | K86: 0 | L86: 0 | M86: 0 | N86: 0 | O86: 0 | P86: 0 | Q86: 0 | R86: 0 | S86: 0 | T86: 0 | U86: 0 | V86: 0 | W86: 0 | X86: 0 | Y86: 0 | Z86: 0 | AA86: 0 | AB86: 0 | AC86: 0 | AD86: 0 | AE86: 0 | AF86: 0 | AG86: 0 | AH86: 0 | AI86: 0 | AJ86: 0 | AK86: 0 | AL86: 0 | AM86: 0 | AO86: =AVERAGE(D86:O86) -> 0.0033333333 | AP86: =AVERAGE(P86:AA86) -> 0 | AQ86: =AVERAGE(AB86:AM86) -> 0
A87: ср. % ставка фондирования | B87: % | D87: 0.1 | E87: 0.1 | F87: 0.1 | G87: 0.1 | H87: 0.1 | I87: 0.1 | J87: 0.1 | K87: 0.1 | L87: 0.1 | M87: 0.1 | N87: 0.1 | O87: 0.1 | P87: 0.1 | Q87: 0.1 | R87: 0.1 | S87: 0.1 | T87: 0.1 | U87: 0.1 | V87: 0.1 | W87: 0.1 | X87: 0.1 | Y87: 0.1 | Z87: 0.1 | AA87: 0.1 | AB87: 0.1 | AC87: 0.1 | AD87: 0.1 | AE87: 0.1 | AF87: 0.1 | AG87: 0.1 | AH87: 0.1 | AI87: 0.1 | AJ87: 0.1 | AK87: 0.1 | AL87: 0.1 | AM87: 0.1 | AO87: =AVERAGE(D87:O87) -> 0.1 | AP87: =AVERAGE(P87:AA87) -> 0.1 | AQ87: =AVERAGE(AB87:AM87) -> 0.1
A88: % расход | B88: тыс. долл | D88: =-(C85+D85)/2*D86/12 -> -0.51193182 | E88: =-(D85+E85)/2*E86/12 -> 0 | F88: =-(E85+F85)/2*F86/12 -> 0 | G88: =-(F85+G85)/2*G86/12 -> 0 | H88: =-(G85+H85)/2*H86/12 -> 0 | I88: =-(H85+I85)/2*I86/12 -> 0 | J88: =-(I85+J85)/2*J86/12 -> 0 | K88: =-(J85+K85)/2*K86/12 -> 0 | ... AM88: =-(AL85+AM85)/2*AM86/12 -> 0 | AO88: =SUM(D88:O88) -> -0.51193182 | AP88: =SUM(P88:AA88) -> 0 | AQ88: =SUM(AB88:AM88) -> 0
A89: трансфертный доход | B89: тыс. долл | D89: =(C85+D85)/2*D87/12 -> 1.2798295 | E89: =(D85+E85)/2*E87/12 -> 1.2901527 | F89: =(E85+F85)/2*F87/12 -> 1.2996156 | G89: =(F85+G85)/2*G87/12 -> 1.3072234 | H89: =(G85+H85)/2*H87/12 -> 1.3431745 | I89: =(H85+I85)/2*I87/12 -> 1.4051069 | J89: =(I85+J85)/2*J87/12 -> 1.4618783 | K89: =(J85+K85)/2*K87/12 -> 1.5139187 | ... AM89: =(AL85+AM85)/2*AM87/12 -> 16.478466 | AO89: =SUM(D89:O89) -> 17.940002 | AP89: =SUM(P89:AA89) -> 41.502515 | AQ89: =SUM(AB89:AM89) -> 123.79609
A90: операционные доходы | B90: тыс. долл | D90: =SUM(D88:D89) -> 0.76789773 | E90: =SUM(E88:E89) -> 1.2901527 | F90: =SUM(F88:F89) -> 1.2996156 | G90: =SUM(G88:G89) -> 1.3072234 | H90: =SUM(H88:H89) -> 1.3431745 | I90: =SUM(I88:I89) -> 1.4051069 | J90: =SUM(J88:J89) -> 1.4618783 | K90: =SUM(K88:K89) -> 1.5139187 | ... AM90: =SUM(AM88:AM89) -> 16.478466 | AO90: =SUM(D90:O90) -> 17.42807 | AP90: =SUM(P90:AA90) -> 41.502515 | AQ90: =SUM(AB90:AM90) -> 123.79609
A91: DCB 360
A92: портфель | B92: тыс сом | C92: =C106+C121*'0'!C$16+C136*'0'!C$19+C151*'0'!C$17 -> 1112.33 | D92: =D106+D121*'0'!D$16+D136*'0'!D$19+D151*'0'!D$17 -> 1329.45 | E92: =E106+E121*'0'!E$16+E136*'0'!E$19+E151*'0'!E$17 -> 1645.2223 | F92: =F106+F121*'0'!F$16+F136*'0'!F$19+F151*'0'!F$17 -> 2156.3302 | G92: =G106+G121*'0'!G$16+G136*'0'!G$19+G151*'0'!G$17 -> 2827.042 | H92: =H106+H121*'0'!H$16+H136*'0'!H$19+H151*'0'!H$17 -> 3765.2009 | I92: =I106+I121*'0'!I$16+I136*'0'!I$19+I151*'0'!I$17 -> 5046.7809 | J92: =J106+J121*'0'!J$16+J136*'0'!J$19+J151*'0'!J$17 -> 6849.54 | ... AM92: =AM106+AM121*'0'!AM$16+AM136*'0'!AM$19+AM151*'0'!AM$17 -> 35468.774 | AO92: =O92 -> 32893.199 | AP92: =AA92 -> 27956.536 | AQ92: =AM92 -> 35468.774
A93: % расход | B93: тыс сом | D93: =D109+D124*'0'!D$16+D139*'0'!D$19+D154*'0'!D$17 -> -12.719556 | E93: =E109+E124*'0'!E$16+E139*'0'!E$19+E154*'0'!E$17 -> -15.619632 | F93: =F109+F124*'0'!F$16+F139*'0'!F$19+F154*'0'!F$17 -> -20.011851 | G93: =G109+G124*'0'!G$16+G139*'0'!G$19+G154*'0'!G$17 -> -26.291577 | H93: =H109+H124*'0'!H$16+H139*'0'!H$19+H154*'0'!H$17 -> -34.852214 | I93: =I109+I124*'0'!I$16+I139*'0'!I$19+I154*'0'!I$17 -> -46.648397 | J93: =J109+J124*'0'!J$16+J139*'0'!J$19+J154*'0'!J$17 -> -63.078528 | K93: =K109+K124*'0'!K$16+K139*'0'!K$19+K154*'0'!K$17 -> -85.931776 | ... AM93: =AM109+AM124*'0'!AM$16+AM139*'0'!AM$19+AM154*'0'!AM$17 -> -377.09663 | AO93: =SUM(D93:O93) -> -1107.6341 | AP93: =SUM(P93:AA93) -> -3742.5101 | AQ93: =SUM(AB93:AM93) -> -3993.0297
A94: трансфертный доход | B94: тыс сом | D94: =D110+D125*'0'!D$16+D140*'0'!D$19+D155*'0'!D$17 -> 14.834007 | E94: =E110+E125*'0'!E$16+E140*'0'!E$19+E155*'0'!E$17 -> 18.197161 | F94: =F110+F125*'0'!F$16+F140*'0'!F$19+F155*'0'!F$17 -> 23.29579 | G94: =G110+G125*'0'!G$16+G140*'0'!G$19+G155*'0'!G$17 -> 30.584725 | H94: =H110+H125*'0'!H$16+H140*'0'!H$19+H155*'0'!H$17 -> 40.516904 | I94: =I110+I125*'0'!I$16+I140*'0'!I$19+I155*'0'!I$17 -> 54.204016 | J94: =J110+J125*'0'!J$16+J140*'0'!J$19+J155*'0'!J$17 -> 73.264104 | K94: =K110+K125*'0'!K$16+K140*'0'!K$19+K155*'0'!K$17 -> 99.756751 | ... AM94: =AM110+AM125*'0'!AM$16+AM140*'0'!AM$19+AM155*'0'!AM$17 -> 435.66096 | AO94: =SUM(D94:O94) -> 1285.1216 | AP94: =SUM(P94:AA94) -> 4332.9656 | AQ94: =SUM(AB94:AM94) -> 4615.4244
A95: операционные доходы | B95: тыс сом | D95: =D111+D126*'0'!D$16+D141*'0'!D$19+D156*'0'!D$17 -> 2.1144514 | E95: =E111+E126*'0'!E$16+E141*'0'!E$19+E156*'0'!E$17 -> 2.5775287 | F95: =F111+F126*'0'!F$16+F141*'0'!F$19+F156*'0'!F$17 -> 3.2839388 | G95: =G111+G126*'0'!G$16+G141*'0'!G$19+G156*'0'!G$17 -> 4.2931481 | H95: =H111+H126*'0'!H$16+H141*'0'!H$19+H156*'0'!H$17 -> 5.6646894 | I95: =I111+I126*'0'!I$16+I141*'0'!I$19+I156*'0'!I$17 -> 7.5556188 | J95: =J111+J126*'0'!J$16+J141*'0'!J$19+J156*'0'!J$17 -> 10.185576 | K95: =K111+K126*'0'!K$16+K141*'0'!K$19+K156*'0'!K$17 -> 13.824975 | ... AM95: =AM111+AM126*'0'!AM$16+AM141*'0'!AM$19+AM156*'0'!AM$17 -> 58.564322 | AO95: =SUM(D95:O95) -> 177.48744 | AP95: =SUM(P95:AA95) -> 590.45545 | AQ95: =SUM(AB95:AM95) -> 622.3947
A96: операционные расходы | B96: тыс сом | D96: =-'OPEX+CAPEX'!I201 -> 0 | E96: =-'OPEX+CAPEX'!J201 -> 0 | F96: =-'OPEX+CAPEX'!K201 -> 0 | G96: =-'OPEX+CAPEX'!L201 -> 0 | H96: =-'OPEX+CAPEX'!M201 -> 0 | I96: =-'OPEX+CAPEX'!N201 -> 0 | J96: =-'OPEX+CAPEX'!O201 -> 0 | K96: =-'OPEX+CAPEX'!P201 -> 0 | ... AM96: =-'OPEX+CAPEX'!AR201 -> 0 | AO96: =SUM(D96:O96) -> 0 | AP96: =SUM(P96:AA96) -> 0 | AQ96: =SUM(AB96:AM96) -> 0
A97: KGS
A98: количество депозитов на конец периода | B98: шт | C98: 10 | D98: =C98+D100 -> 13 | E98: =D98+E100 -> 17 | F98: =E98+F100 -> 23 | G98: =F98+G100 -> 31 | H98: =G98+H100 -> 42 | I98: =H98+I100 -> 57 | J98: =I98+J100 -> 78 | K98: =J98+K100 -> 107 | ... AM98: =AL98+AM100 -> 965 | AO98: =O98 -> 383 | AP98: =AA98 -> 606 | AQ98: =AM98 -> 965
A99: индекс прироста депозитов | B99: % | D99: 0.38 | E99: 0.38 | F99: 0.38 | G99: 0.38 | H99: 0.38 | I99: 0.38 | J99: 0.38 | K99: 0.38 | L99: 0.38 | M99: 0.38 | N99: 0.38 | O99: 0.38 | P99: 0.04 | Q99: 0.04 | R99: 0.04 | S99: 0.04 | T99: 0.04 | U99: 0.04 | V99: 0.04 | W99: 0.04 | X99: 0.04 | Y99: 0.04 | Z99: 0.04 | AA99: 0.04 | AB99: 0.04 | AC99: 0.04 | AD99: 0.04 | AE99: 0.04 | AF99: 0.04 | AG99: 0.04 | AH99: 0.04 | AI99: 0.04 | AJ99: 0.04 | AK99: 0.04 | AL99: 0.04 | AM99: 0.04 | AO99: =O99 -> 0.38 | AP99: =AA99 -> 0.04 | AQ99: =AM99 -> 0.04
A100: количество новых депозитов | B100: шт | D100: =INT(C98*D99) -> 3 | E100: =INT(D98*E99) -> 4 | F100: =INT(E98*F99) -> 6 | G100: =INT(F98*G99) -> 8 | H100: =INT(G98*H99) -> 11 | I100: =INT(H98*I99) -> 15 | J100: =INT(I98*J99) -> 21 | K100: =INT(J98*K99) -> 29 | ... AM100: =INT(AL98*AM99) -> 37 | AO100: =SUM(D100:O100) -> 373 | AP100: =SUM(P100:AA100) -> 223 | AQ100: =SUM(AB100:AM100) -> 359
A101: ср. сумма нового депозита | B101: тыс сом | D101: 100 | E101: 100 | F101: 100 | G101: 100 | H101: 100 | I101: 100 | J101: 100 | K101: 100 | L101: 100 | M101: 100 | N101: 100 | O101: 100 | P101: 100 | Q101: 100 | R101: 100 | S101: 100 | T101: 100 | U101: 100 | V101: 100 | W101: 100 | X101: 100 | Y101: 100 | Z101: 100 | AA101: 100 | AB101: 100 | AC101: 100 | AD101: 100 | AE101: 100 | AF101: 100 | AG101: 100 | AH101: 100 | AI101: 100 | AJ101: 100 | AK101: 100 | AL101: 100 | AM101: 100 | AO101: =AVERAGE(D101:O101) -> 100 | AP101: =AVERAGE(P101:AA101) -> 100 | AQ101: =AVERAGE(AB101:AM101) -> 100
A102: привлечение депозитов | B102: тыс сом | D102: =D100*D101 -> 300 | E102: =E100*E101 -> 400 | F102: =F100*F101 -> 600 | G102: =G100*G101 -> 800 | H102: =H100*H101 -> 1100 | I102: =I100*I101 -> 1500 | J102: =J100*J101 -> 2100 | K102: =K100*K101 -> 2900 | ... AM102: =AM100*AM101 -> 3700 | AO102: =SUM(D102:O102) -> 37300 | AP102: =SUM(P102:AA102) -> 22300 | AQ102: =SUM(AB102:AM102) -> 35900
...

Sheet РБ.3
A1: Розничный бизнес - обслуживание клиентов
D3: 46023 | E3: 46054 | F3: 46082 | G3: 46113 | H3: 46143 | I3: 46174 | J3: 46204 | K3: 46235 | L3: 46266 | M3: 46296 | N3: 46327 | O3: 46357 | P3: 46388 | Q3: 46419 | R3: 46447 | S3: 46478 | T3: 46508 | U3: 46539 | V3: 46569 | W3: 46600 | X3: 46631 | Y3: 46661 | Z3: 46692 | AA3: 46722 | AB3: 46753 | AC3: 46784 | AD3: 46813 | AE3: 46844 | AF3: 46874 | AG3: 46905 | AH3: 46935 | AI3: 46966 | AJ3: 46997 | AK3: 47027 | AL3: 47058 | AM3: 47088 | AO3: =YEAR(O3) -> 2026 | AP3: =YEAR(AA3) -> 2027 | AQ3: =YEAR(AM3) -> 2028
D4: m1 | E4: m2 | F4: m3 | G4: m4 | H4: m5 | I4: m6 | J4: m7 | K4: m8 | L4: m9 | M4: m10 | N4: m11 | O4: m12 | P4: m13 | Q4: m14 | R4: m15 | S4: m16 | T4: m17 | U4: m18 | V4: m19 | W4: m20 | X4: m21 | Y4: m22 | Z4: m23 | AA4: m24 | AB4: m25 | AC4: m26 | AD4: m27 | AE4: m28 | AF4: m29 | AG4: m30 | AH4: m31 | AI4: m32 | AJ4: m33 | AK4: m34 | AL4: m35 | AM4: m36 | AO4: Y1 | AP4: Y2 | AQ4: Y3
D5: 1 | E5: =D5+1 -> 2 | F5: =E5+1 -> 3 | G5: =F5+1 -> 4 | H5: =G5+1 -> 5 | I5: =H5+1 -> 6 | J5: =I5+1 -> 7 | K5: =J5+1 -> 8 | L5: =K5+1 -> 9 | ... AM5: =AL5+1 -> 36
A7: Выпуск и обслуживание банковских карт (ФЛ)
A8: количество новых карт, в т.ч. заказанных через: | B8: шт | D8: =SUM(D9:D10) -> 641 | E8: =SUM(E9:E10) -> 656 | F8: =SUM(F9:F10) -> 672 | G8: =SUM(G9:G10) -> 689 | H8: =SUM(H9:H10) -> 705 | I8: =SUM(I9:I10) -> 722 | J8: =SUM(J9:J10) -> 739 | K8: =SUM(K9:K10) -> 757 | ... AM8: =SUM(AM9:AM10) -> 1470 | AO8: =SUM(D8:O8) -> 8795 | AP8: =SUM(P8:AA8) -> 11687 | AQ8: =SUM(AB8:AM8) -> 15533
A9: Безбумажный офис | B9: шт | D9: =РБ.2!D398 -> 641 | E9: =РБ.2!E398 -> 656 | F9: =РБ.2!F398 -> 672 | G9: =РБ.2!G398 -> 689 | H9: =РБ.2!H398 -> 705 | I9: =РБ.2!I398 -> 722 | J9: =РБ.2!J398 -> 739 | K9: =РБ.2!K398 -> 757 | ... AM9: =РБ.2!AM398 -> 1470 | AO9: =SUM(D9:O9) -> 8795 | AP9: =SUM(P9:AA9) -> 11687 | AQ9: =SUM(AB9:AM9) -> 15533
A10: DCB 360 | B10: шт | D10: =РБ.2!D445 -> 0 | E10: =РБ.2!E445 -> 0 | F10: =РБ.2!F445 -> 0 | G10: =РБ.2!G445 -> 0 | H10: =РБ.2!H445 -> 0 | I10: =РБ.2!I445 -> 0 | J10: =РБ.2!J445 -> 0 | K10: =РБ.2!K445 -> 0 | ... AM10: =РБ.2!AM445 -> 0 | AO10: =SUM(D10:O10) -> 0 | AP10: =SUM(P10:AA10) -> 0 | AQ10: =SUM(AB10:AM10) -> 0
A11: количество карт на конец периода, в т.ч. заказанных через: | B11: шт | C11: =SUM(C12:C13) -> 26807 | D11: =SUM(D12:D13) -> 27448 | E11: =SUM(E12:E13) -> 28104 | F11: =SUM(F12:F13) -> 28776 | G11: =SUM(G12:G13) -> 29465 | H11: =SUM(H12:H13) -> 30170 | I11: =SUM(I12:I13) -> 30892 | J11: =SUM(J12:J13) -> 31631 | ... AM11: =SUM(AM12:AM13) -> 62822 | AO11: =O11 -> 35602 | AP11: =AA11 -> 47289 | AQ11: =AM11 -> 62822
A12: Безбумажный офис | B12: шт | C12: =РБ.2!C386 -> 26807 | D12: =РБ.2!D386 -> 27448 | E12: =РБ.2!E386 -> 28104 | F12: =РБ.2!F386 -> 28776 | G12: =РБ.2!G386 -> 29465 | H12: =РБ.2!H386 -> 30170 | I12: =РБ.2!I386 -> 30892 | J12: =РБ.2!J386 -> 31631 | ... AM12: =РБ.2!AM386 -> 62822 | AO12: =O12 -> 35602 | AP12: =AA12 -> 47289 | AQ12: =AM12 -> 62822
A13: DCB 360 | B13: шт | C13: =РБ.2!C433 -> 0 | D13: =РБ.2!D433 -> 0 | E13: =РБ.2!E433 -> 0 | F13: =РБ.2!F433 -> 0 | G13: =РБ.2!G433 -> 0 | H13: =РБ.2!H433 -> 0 | I13: =РБ.2!I433 -> 0 | J13: =РБ.2!J433 -> 0 | ... AM13: =РБ.2!AM433 -> 0 | AO13: =O13 -> 0 | AP13: =AA13 -> 0 | AQ13: =AM13 -> 0
A14: доля перевыпускаемых карт | B14: % | D14: 0.0147 | E14: 0.0147 | F14: 0.0147 | G14: 0.0147 | H14: 0.0147 | I14: 0.0147 | J14: 0.0147 | K14: 0.0147 | L14: 0.0147 | M14: 0.0147 | N14: 0.0147 | O14: 0.0147 | P14: 0.0147 | Q14: 0.0147 | R14: 0.0147 | S14: 0.0147 | T14: 0.0147 | U14: 0.0147 | V14: 0.0147 | W14: 0.0147 | X14: 0.0147 | Y14: 0.0147 | Z14: 0.0147 | AA14: 0.0147 | AB14: 0.0147 | AC14: 0.0147 | AD14: 0.0147 | AE14: 0.0147 | AF14: 0.0147 | AG14: 0.0147 | AH14: 0.0147 | AI14: 0.0147 | AJ14: 0.0147 | AK14: 0.0147 | AL14: 0.0147 | AM14: 0.0147
A15: количество перевыпускаемых карт | B15: шт | D15: =C11*D14 -> 394.0629 | E15: =D11*E14 -> 403.4856 | F15: =E11*F14 -> 413.1288 | G15: =F11*G14 -> 423.0072 | H15: =G11*H14 -> 433.1355 | I15: =H11*I14 -> 443.499 | J15: =I11*J14 -> 454.1124 | K15: =J11*K14 -> 464.9757 | ... AM15: =AL11*AM14 -> 901.8744 | AO15: =SUM(D15:O15) -> 5403.279 | AP15: =SUM(P15:AA15) -> 7176.4077 | AQ15: =SUM(AB15:AM15) -> 9533.244
A16: доля карт для оплаты годового обслуживания | B16: % | D16: =1/12 -> 0.083333333 | E16: =1/12 -> 0.083333333 | F16: =1/12 -> 0.083333333 | G16: =1/12 -> 0.083333333 | H16: =1/12 -> 0.083333333 | I16: =1/12 -> 0.083333333 | J16: =1/12 -> 0.083333333 | K16: =1/12 -> 0.083333333 | ... AM16: =1/12 -> 0.083333333
A17: ср.комиссия за выпуск (перевыпуск) 1 карты | B17: сом | D17: 200 | E17: 100 | F17: 100 | G17: 100 | H17: 100 | I17: 100 | J17: 100 | K17: 100 | L17: 100 | M17: 100 | N17: 100 | O17: 100 | P17: 100 | Q17: 100 | R17: 100 | S17: 100 | T17: 100 | U17: 100 | V17: 100 | W17: 100 | X17: 100 | Y17: 100 | Z17: 100 | AA17: 100 | AB17: 100 | AC17: 100 | AD17: 100 | AE17: 100 | AF17: 100 | AG17: 100 | AH17: 100 | AI17: 100 | AJ17: 100 | AK17: 100 | AL17: 100 | AM17: 100
A18: ср.комиссия за годовое обслуживание 1 карты | B18: сом | D18: 200 | E18: 450 | F18: 450 | G18: 450 | H18: 450 | I18: 450 | J18: 450 | K18: 450 | L18: 450 | M18: 450 | N18: 450 | O18: 450 | P18: 450 | Q18: 450 | R18: 450 | S18: 450 | T18: 450 | U18: 450 | V18: 450 | W18: 450 | X18: 450 | Y18: 450 | Z18: 450 | AA18: 450 | AB18: 450 | AC18: 450 | AD18: 450 | AE18: 450 | AF18: 450 | AG18: 450 | AH18: 450 | AI18: 450 | AJ18: 450 | AK18: 450 | AL18: 450 | AM18: 450
A19: комиссионный доход | B19: тыс.сом | D19: =D20+D21 -> 664.47925 | E19: =E20+E21 -> 1159.8486 | F19: =F20+F21 -> 1187.6129 | G19: =G20+G21 -> 1216.1382 | H19: =H20+H21 -> 1245.1886 | I19: =I20+I21 -> 1274.9999 | J19: =J20+J21 -> 1305.4737 | K19: =K20+K21 -> 1336.7476 | ... AM19: =AM20+AM21 -> 2593.0124 | AO19: =SUM(D19:O19) -> 15065.188 | AP19: =SUM(P19:AA19) -> 20631.766 | AQ19: =SUM(AB19:AM19) -> 27408.612
A20: комиссионный доход за выпуск (перевыпуск) | B20: тыс.сом | D20: =(D8+C11*D14)*D17/1000 -> 207.01258 | E20: =(E8+D11*E14)*E17/1000 -> 105.94856 | F20: =(F8+E11*F14)*F17/1000 -> 108.51288 | G20: =(G8+F11*G14)*G17/1000 -> 111.20072 | H20: =(H8+G11*H14)*H17/1000 -> 113.81355 | I20: =(I8+H11*I14)*I17/1000 -> 116.5499 | J20: =(J8+I11*J14)*J17/1000 -> 119.31124 | K20: =(K8+J11*K14)*K17/1000 -> 122.19757 | ... AM20: =(AM8+AL11*AM14)*AM17/1000 -> 237.18744 | AO20: =SUM(D20:O20) -> 1523.3342 | AP20: =SUM(P20:AA20) -> 1886.3408 | AQ20: =SUM(AB20:AM20) -> 2506.6244
A21: комиссионный доход за годовое обслуживание | B21: тыс.сом | D21: =D11*D16*D18/1000 -> 457.46667 | E21: =E11*E16*E18/1000 -> 1053.9 | F21: =F11*F16*F18/1000 -> 1079.1 | G21: =G11*G16*G18/1000 -> 1104.9375 | H21: =H11*H16*H18/1000 -> 1131.375 | I21: =I11*I16*I18/1000 -> 1158.45 | J21: =J11*J16*J18/1000 -> 1186.1625 | K21: =K11*K16*K18/1000 -> 1214.55 | ... AM21: =AM11*AM16*AM18/1000 -> 2355.825 | AO21: =SUM(D21:O21) -> 13541.854 | AP21: =SUM(P21:AA21) -> 18745.425 | AQ21: =SUM(AB21:AM21) -> 24901.987
A22: операционные расходы, в т.ч.: | B22: тыс.сом | D22: =-'OPEX+CAPEX'!I284 -> -297.80072 | E22: =-'OPEX+CAPEX'!J284 -> -303.57828 | F22: =-'OPEX+CAPEX'!K284 -> -309.58677 | G22: =-'OPEX+CAPEX'!L284 -> -315.83177 | H22: =-'OPEX+CAPEX'!M284 -> -322.02378 | I22: =-'OPEX+CAPEX'!N284 -> -328.4523 | J22: =-'OPEX+CAPEX'!O284 -> -334.97535 | K22: =-'OPEX+CAPEX'!P284 -> -341.74047 | ... AM22: =-'OPEX+CAPEX'!AR284 -> -612.20786 | AO22: =SUM(D22:O22) -> -3991.5063 | AP22: =SUM(P22:AA22) -> -5088.9366 | AQ22: =SUM(AB22:AM22) -> -6547.9266
A23: прибыль | B23: тыс.сом | D23: =D20+D21+D22 -> 366.67852 | E23: =E20+E21+E22 -> 856.27028 | F23: =F20+F21+F22 -> 878.02611 | G23: =G20+G21+G22 -> 900.30645 | H23: =H20+H21+H22 -> 923.16477 | I23: =I20+I21+I22 -> 946.5476 | J23: =J20+J21+J22 -> 970.49839 | K23: =K20+K21+K22 -> 995.0071 | ... AM23: =AM20+AM21+AM22 -> 1980.8046 | AO23: =SUM(D23:O23) -> 11073.682 | AP23: =SUM(P23:AA23) -> 15542.829 | AQ23: =SUM(AB23:AM23) -> 20860.685
A25: Открытие и обслуживание банковского счета (ФЛ)
A26: количество новых счетов, в т.ч. открытых через: | B26: шт | D26: =SUM(D27:D28) -> 344.8 | E26: =SUM(E27:E28) -> 744 | F26: =SUM(F27:F28) -> 948 | G26: =SUM(G27:G28) -> 974 | H26: =SUM(H27:H28) -> 1006 | I26: =SUM(I27:I28) -> 1042 | J26: =SUM(J27:J28) -> 1084 | K26: =SUM(K27:K28) -> 793.8 | ... AM26: =SUM(AM27:AM28) -> 5932 | AO26: =SUM(D26:O26) -> 11689 | AP26: =SUM(P26:AA26) -> 18893.6 | AQ26: =SUM(AB26:AM26) -> 48027.6
A27: Безбумажный офис | B27: шт | D27: =РБ.2!D262+РБ.2!D273+РБ.2!D284+РБ.2!D295+РБ.2!D306 -> 344.8 | E27: =РБ.2!E262+РБ.2!E273+РБ.2!E284+РБ.2!E295+РБ.2!E306 -> 692 | F27: =РБ.2!F262+РБ.2!F273+РБ.2!F284+РБ.2!F295+РБ.2!F306 -> 872 | G27: =РБ.2!G262+РБ.2!G273+РБ.2!G284+РБ.2!G295+РБ.2!G306 -> 881 | H27: =РБ.2!H262+РБ.2!H273+РБ.2!H284+РБ.2!H295+РБ.2!H306 -> 892 | I27: =РБ.2!I262+РБ.2!I273+РБ.2!I284+РБ.2!I295+РБ.2!I306 -> 901 | J27: =РБ.2!J262+РБ.2!J273+РБ.2!J284+РБ.2!J295+РБ.2!J306 -> 911 | K27: =РБ.2!K262+РБ.2!K273+РБ.2!K284+РБ.2!K295+РБ.2!K306 -> 644.7 | ... AM27: =РБ.2!AM262+РБ.2!AM273+РБ.2!AM284+РБ.2!AM295+РБ.2!AM306 -> 966.4 | AO27: =SUM(D27:O27) -> 9624.1 | AP27: =SUM(P27:AA27) -> 10802.6 | AQ27: =SUM(AB27:AM27) -> 12131
A28: DCB 360 | B28: шт | D28: =РБ.2!D323+РБ.2!D334+РБ.2!D345+РБ.2!D356+РБ.2!D367 -> 0 | E28: =РБ.2!E323+РБ.2!E334+РБ.2!E345+РБ.2!E356+РБ.2!E367 -> 52 | F28: =РБ.2!F323+РБ.2!F334+РБ.2!F345+РБ.2!F356+РБ.2!F367 -> 76 | G28: =РБ.2!G323+РБ.2!G334+РБ.2!G345+РБ.2!G356+РБ.2!G367 -> 93 | H28: =РБ.2!H323+РБ.2!H334+РБ.2!H345+РБ.2!H356+РБ.2!H367 -> 114 | I28: =РБ.2!I323+РБ.2!I334+РБ.2!I345+РБ.2!I356+РБ.2!I367 -> 141 | J28: =РБ.2!J323+РБ.2!J334+РБ.2!J345+РБ.2!J356+РБ.2!J367 -> 173 | K28: =РБ.2!K323+РБ.2!K334+РБ.2!K345+РБ.2!K356+РБ.2!K367 -> 149.1 | ... AM28: =РБ.2!AM323+РБ.2!AM334+РБ.2!AM345+РБ.2!AM356+РБ.2!AM367 -> 4965.6 | AO28: =SUM(D28:O28) -> 2064.9 | AP28: =SUM(P28:AA28) -> 8091 | AQ28: =SUM(AB28:AM28) -> 35896.6
A29: общее количество счетов, в т.ч. открытых через: | C29: =SUM(C30:C31) -> 82763 | D29: =SUM(D30:D31) -> 83407.8 | E29: =SUM(E30:E31) -> 84151.8 | F29: =SUM(F30:F31) -> 85099.8 | G29: =SUM(G30:G31) -> 86073.8 | H29: =SUM(H30:H31) -> 87079.8 | I29: =SUM(I30:I31) -> 88121.8 | J29: =SUM(J30:J31) -> 89205.8 | ... AM29: =SUM(AM30:AM31) -> 161673.2 | AO29: =O29 -> 94752 | AP29: =AA29 -> 113645.6 | AQ29: =AM29 -> 161673.2
A30: Безбумажный офис | B30: шт | C30: =РБ.2!C260+РБ.2!C271+РБ.2!C282+РБ.2!C293+РБ.2!C304 -> 82763 | D30: =РБ.2!D260+РБ.2!D271+РБ.2!D282+РБ.2!D293+РБ.2!D304 -> 83107.8 | E30: =РБ.2!E260+РБ.2!E271+РБ.2!E282+РБ.2!E293+РБ.2!E304 -> 83799.8 | F30: =РБ.2!F260+РБ.2!F271+РБ.2!F282+РБ.2!F293+РБ.2!F304 -> 84671.8 | G30: =РБ.2!G260+РБ.2!G271+РБ.2!G282+РБ.2!G293+РБ.2!G304 -> 85552.8 | H30: =РБ.2!H260+РБ.2!H271+РБ.2!H282+РБ.2!H293+РБ.2!H304 -> 86444.8 | I30: =РБ.2!I260+РБ.2!I271+РБ.2!I282+РБ.2!I293+РБ.2!I304 -> 87345.8 | J30: =РБ.2!J260+РБ.2!J271+РБ.2!J282+РБ.2!J293+РБ.2!J304 -> 88256.8 | ... AM30: =РБ.2!AM260+РБ.2!AM271+РБ.2!AM282+РБ.2!AM293+РБ.2!AM304 -> 115320.7 | AO30: =O30 -> 92387.1 | AP30: =AA30 -> 103189.7 | AQ30: =AM30 -> 115320.7
A31: DCB 360 | B31: шт | C31: =РБ.2!C321+РБ.2!C332+РБ.2!C343+РБ.2!C354+РБ.2!C365 -> 0 | D31: =РБ.2!D321+РБ.2!D332+РБ.2!D343+РБ.2!D354+РБ.2!D365 -> 300 | E31: =РБ.2!E321+РБ.2!E332+РБ.2!E343+РБ.2!E354+РБ.2!E365 -> 352 | F31: =РБ.2!F321+РБ.2!F332+РБ.2!F343+РБ.2!F354+РБ.2!F365 -> 428 | G31: =РБ.2!G321+РБ.2!G332+РБ.2!G343+РБ.2!G354+РБ.2!G365 -> 521 | H31: =РБ.2!H321+РБ.2!H332+РБ.2!H343+РБ.2!H354+РБ.2!H365 -> 635 | I31: =РБ.2!I321+РБ.2!I332+РБ.2!I343+РБ.2!I354+РБ.2!I365 -> 776 | J31: =РБ.2!J321+РБ.2!J332+РБ.2!J343+РБ.2!J354+РБ.2!J365 -> 949 | ... AM31: =РБ.2!AM321+РБ.2!AM332+РБ.2!AM343+РБ.2!AM354+РБ.2!AM365 -> 46352.5 | AO31: =O31 -> 2364.9 | AP31: =AA31 -> 10455.9 | AQ31: =AM31 -> 46352.5
A32: ср.комиссия за открытие 1 счета | B32: сом | D32: 0 | E32: 0 | F32: 0 | G32: 0 | H32: 0 | I32: 0 | J32: 0 | K32: 0 | L32: 0 | M32: 0 | N32: 0 | O32: 0 | P32: 0 | Q32: 0 | R32: 0 | S32: 0 | T32: 0 | U32: 0 | V32: 0 | W32: 0 | X32: 0 | Y32: 0 | Z32: 0 | AA32: 0 | AB32: 0 | AC32: 0 | AD32: 0 | AE32: 0 | AF32: 0 | AG32: 0 | AH32: 0 | AI32: 0 | AJ32: 0 | AK32: 0 | AL32: 0 | AM32: 0
A33: ср.комиссия за обслуживание 1 счета | B33: сом | D33: 0.57996931 | E33: 0.57996931 | F33: 0.57996931 | G33: 0.57996931 | H33: 0.57996931 | I33: 0.57996931 | J33: 0.57996931 | K33: 0.57996931 | L33: 0.57996931 | M33: 0.57996931 | N33: 0.57996931 | O33: 0.57996931 | P33: 0.57996931 | Q33: 0.57996931 | R33: 0.57996931 | S33: 0.57996931 | T33: 0.57996931 | U33: 0.57996931 | V33: 0.57996931 | W33: 0.57996931 | X33: 0.57996931 | Y33: 0.57996931 | Z33: 0.57996931 | AA33: 0.57996931 | AB33: 0.57996931 | AC33: 0.57996931 | AD33: 0.57996931 | AE33: 0.57996931 | AF33: 0.57996931 | AG33: 0.57996931 | AH33: 0.57996931 | AI33: 0.57996931 | AJ33: 0.57996931 | AK33: 0.57996931 | AL33: 0.57996931 | AM33: 0.57996931
A34: комиссионный доход | B34: тыс.сом | D34: =D35+D36 -> 48.373964 | E34: =E35+E36 -> 48.805461 | F34: =F35+F36 -> 49.355272 | G34: =G35+G36 -> 49.920162 | H34: =H35+H36 -> 50.503612 | I34: =I35+I36 -> 51.10794 | J34: =J35+J36 -> 51.736626 | K34: =K35+K36 -> 52.197006 | ... AM34: =AM35+AM36 -> 93.765494 | AO34: =SUM(D34:O34) -> 617.72891 | AP34: =SUM(P34:AA34) -> 721.42614 | AQ34: =SUM(AB34:AM34) -> 937.5136
A35: комиссионный доход за открытие счета | B35: тыс.сом | D35: =D26*D32/1000 -> 0 | E35: =E26*E32/1000 -> 0 | F35: =F26*F32/1000 -> 0 | G35: =G26*G32/1000 -> 0 | H35: =H26*H32/1000 -> 0 | I35: =I26*I32/1000 -> 0 | J35: =J26*J32/1000 -> 0 | K35: =K26*K32/1000 -> 0 | ... AM35: =AM26*AM32/1000 -> 0 | AO35: =SUM(D35:O35) -> 0 | AP35: =SUM(P35:AA35) -> 0 | AQ35: =SUM(AB35:AM35) -> 0
A36: комиссионный доход от обслуживания счета | B36: тыс.сом | D36: =D29*D33/1000 -> 48.373964 | E36: =E29*E33/1000 -> 48.805461 | F36: =F29*F33/1000 -> 49.355272 | G36: =G29*G33/1000 -> 49.920162 | H36: =H29*H33/1000 -> 50.503612 | I36: =I29*I33/1000 -> 51.10794 | J36: =J29*J33/1000 -> 51.736626 | K36: =K29*K33/1000 -> 52.197006 | ... AM36: =AM29*AM33/1000 -> 93.765494 | AO36: =SUM(D36:O36) -> 617.72891 | AP36: =SUM(P36:AA36) -> 721.42614 | AQ36: =SUM(AB36:AM36) -> 937.5136
A37: операционные расходы, в т.ч.: | B37: тыс.сом | D37: =-'OPEX+CAPEX'!I222 -> -13.853571 | E37: =-'OPEX+CAPEX'!J222 -> -27.803571 | F37: =-'OPEX+CAPEX'!K222 -> -35.035714 | G37: =-'OPEX+CAPEX'!L222 -> -35.397321 | H37: =-'OPEX+CAPEX'!M222 -> -35.839286 | I37: =-'OPEX+CAPEX'!N222 -> -36.200893 | J37: =-'OPEX+CAPEX'!O222 -> -36.602679 | K37: =-'OPEX+CAPEX'!P222 -> -25.903125 | ... AM37: =-'OPEX+CAPEX'!AR222 -> -38.828571 | AO37: =SUM(D37:O37) -> -386.68259 | AP37: =SUM(P37:AA37) -> -434.03304 | AQ37: =SUM(AB37:AM37) -> -487.40625
A38: прибыль | B38: тыс.сом | D38: =D35+D36+D37 -> 34.520393 | E38: =E35+E36+E37 -> 21.00189 | F38: =F35+F36+F37 -> 14.319558 | G38: =G35+G36+G37 -> 14.522841 | H38: =H35+H36+H37 -> 14.664326 | I38: =I35+I36+I37 -> 14.907047 | J38: =J35+J36+J37 -> 15.133948 | K38: =K35+K36+K37 -> 26.293881 | ... AM38: =AM35+AM36+AM37 -> 54.936923 | AO38: =SUM(D38:O38) -> 231.04632 | AP38: =SUM(P38:AA38) -> 287.39311 | AQ38: =SUM(AB38:AM38) -> 450.10735
A40: Переводы и платежи (ФЛ)
A41: Межбанковские переводы (Клиринг, Гросс)
A42: ср.количество переводов на 1 счет, в т.ч. через: | B42: шт | D42: =SUM(D43:D44) -> 0.00047957145 | E42: =SUM(E43:E44) -> 0.00047957145 | F42: =SUM(F43:F44) -> 0.00047957145 | G42: =SUM(G43:G44) -> 0.00047957145 | H42: =SUM(H43:H44) -> 0.00047957145 | I42: =SUM(I43:I44) -> 0.00047957145 | J42: =SUM(J43:J44) -> 0.00047957145 | K42: =SUM(K43:K44) -> 0.00047957145 | ... AM42: =SUM(AM43:AM44) -> 0.00047957145 | AO42: =РБ.2!AO443 -> 0.01 | AP42: =РБ.2!AP443 -> 0.01 | AQ42: =РБ.2!AQ443 -> 0.01
A43: Безбумажный офис | B43: шт | D43: 0.00047957145 | E43: 0.00047957145 | F43: 0.00047957145 | G43: 0.00047957145 | H43: 0.00047957145 | I43: 0.00047957145 | J43: 0.00047957145 | K43: 0.00047957145 | L43: 0.00047957145 | M43: 0.00047957145 | N43: 0.00047957145 | O43: 0.00047957145 | P43: 0.00047957145 | Q43: 0.00047957145 | R43: 0.00047957145 | S43: 0.00047957145 | T43: 0.00047957145 | U43: 0.00047957145 | V43: 0.00047957145 | W43: 0.00047957145 | X43: 0.00047957145 | Y43: 0.00047957145 | Z43: 0.00047957145 | AA43: 0.00047957145 | AB43: 0.00047957145 | AC43: 0.00047957145 | AD43: 0.00047957145 | AE43: 0.00047957145 | AF43: 0.00047957145 | AG43: 0.00047957145 | AH43: 0.00047957145 | AI43: 0.00047957145 | AJ43: 0.00047957145 | AK43: 0.00047957145 | AL43: 0.00047957145 | AM43: 0.00047957145
A44: DCB 360 | B44: шт | D44: 0 | E44: 0 | F44: 0 | G44: 0 | H44: 0 | I44: 0 | J44: 0 | K44: 0 | L44: 0 | M44: 0 | N44: 0 | O44: 0 | P44: 0 | Q44: 0 | R44: 0 | S44: 0 | T44: 0 | U44: 0 | V44: 0 | W44: 0 | X44: 0 | Y44: 0 | Z44: 0 | AA44: 0 | AB44: 0 | AC44: 0 | AD44: 0 | AE44: 0 | AF44: 0 | AG44: 0 | AH44: 0 | AI44: 0 | AJ44: 0 | AK44: 0 | AL44: 0 | AM44: 0
A45: общее количество переводов, в т.ч. через: | B45: шт | D45: =SUM(D46:D47) -> 40 | E45: =SUM(E46:E47) -> 40.356801 | F45: =SUM(F46:F47) -> 40.811435 | G45: =SUM(G46:G47) -> 41.278537 | H45: =SUM(H46:H47) -> 41.760986 | I45: =SUM(I46:I47) -> 42.2607 | J45: =SUM(J46:J47) -> 42.780555 | K45: =SUM(K46:K47) -> 43.161239 | ... AM45: =SUM(AM46:AM47) -> 77.533852 | AO45: =SUM(D45:O45) -> 510.79453 | AP45: =SUM(P45:AA45) -> 596.54085 | AQ45: =SUM(AB45:AM45) -> 775.22165
A46: Безбумажный офис | B46: шт | D46: =D43*D29 -> 40 | E46: =E43*E29 -> 40.356801 | F46: =F43*F29 -> 40.811435 | G46: =G43*G29 -> 41.278537 | H46: =H43*H29 -> 41.760986 | I46: =I43*I29 -> 42.2607 | J46: =J43*J29 -> 42.780555 | K46: =K43*K29 -> 43.161239 | ... AM46: =AM43*AM29 -> 77.533852 | AO46: =SUM(D46:O46) -> 510.79453 | AP46: =SUM(P46:AA46) -> 596.54085 | AQ46: =SUM(AB46:AM46) -> 775.22165
A47: DCB 360 | B47: шт | D47: =D44*D30 -> 0 | E47: =E44*E30 -> 0 | F47: =F44*F30 -> 0 | G47: =G44*G30 -> 0 | H47: =H44*H30 -> 0 | I47: =I44*I30 -> 0 | J47: =J44*J30 -> 0 | K47: =K44*K30 -> 0 | ... AM47: =AM44*AM30 -> 0 | AO47: =SUM(D47:O47) -> 0 | AP47: =SUM(P47:AA47) -> 0 | AQ47: =SUM(AB47:AM47) -> 0
A48: ср.комиссия за 1 перевод | B48: сом | D48: 60 | E48: 60 | F48: 60 | G48: 60 | H48: 60 | I48: 60 | J48: 60 | K48: 60 | L48: 60 | M48: 60 | N48: 60 | O48: 60 | P48: 60 | Q48: 60 | R48: 60 | S48: 60 | T48: 60 | U48: 60 | V48: 60 | W48: 60 | X48: 60 | Y48: 60 | Z48: 60 | AA48: 60 | AB48: 60 | AC48: 60 | AD48: 60 | AE48: 60 | AF48: 60 | AG48: 60 | AH48: 60 | AI48: 60 | AJ48: 60 | AK48: 60 | AL48: 60 | AM48: 60
A49: комиссионный доход | B49: тыс.сом | D49: =D48*D45/1000 -> 2.4 | E49: =E48*E45/1000 -> 2.4214081 | F49: =F48*F45/1000 -> 2.4486861 | G49: =G48*G45/1000 -> 2.4767122 | H49: =H48*H45/1000 -> 2.5056592 | I49: =I48*I45/1000 -> 2.535642 | J49: =J48*J45/1000 -> 2.5668333 | K49: =K48*K45/1000 -> 2.5896743 | ... AM49: =AM48*AM45/1000 -> 4.6520311 | AO49: =SUM(D49:O49) -> 30.647672 | AP49: =SUM(P49:AA49) -> 35.792451 | AQ49: =SUM(AB49:AM49) -> 46.513299
A50: операционные расходы | B50: тыс.сом | D50: =D52+D53 -> -1.5770422 | E50: =E52+E53 -> -1.5911095 | F50: =F52+F53 -> -1.6090339 | G50: =G52+G53 -> -1.6274499 | H50: =H52+H53 -> -1.6464709 | I50: =I52+I53 -> -1.6661727 | J50: =J52+J53 -> -1.6866685 | K50: =K52+K53 -> -1.7016774 | ... AM50: =AM52+AM53 -> -3.0568539 | AO50: =SUM(D50:O50) -> -20.138613 | AP50: =SUM(P50:AA50) -> -23.519252 | AQ50: =SUM(AB50:AM50) -> -30.563931
A51: ср.комиссия за 1 перевод | B51: сом | D51: 22.560976 | E51: 22.560976 | F51: 22.560976 | G51: 22.560976 | H51: 22.560976 | I51: 22.560976 | J51: 22.560976 | K51: 22.560976 | L51: 22.560976 | M51: 22.560976 | N51: 22.560976 | O51: 22.560976 | P51: 22.560976 | Q51: 22.560976 | R51: 22.560976 | S51: 22.560976 | T51: 22.560976 | U51: 22.560976 | V51: 22.560976 | W51: 22.560976 | X51: 22.560976 | Y51: 22.560976 | Z51: 22.560976 | AA51: 22.560976 | AB51: 22.560976 | AC51: 22.560976 | AD51: 22.560976 | AE51: 22.560976 | AF51: 22.560976 | AG51: 22.560976 | AH51: 22.560976 | AI51: 22.560976 | AJ51: 22.560976 | AK51: 22.560976 | AL51: 22.560976 | AM51: 22.560976
A52: комиссия оператору (нац.банк) | B52: тыс.сом | D52: =-D45*D51/1000 -> -0.90243902 | E52: =-E45*E51/1000 -> -0.91048881 | F52: =-F45*F51/1000 -> -0.92074579 | G52: =-G45*G51/1000 -> -0.93128408 | H52: =-H45*H51/1000 -> -0.9421686 | I52: =-I45*I51/1000 -> -0.95344262 | J52: =-J45*J51/1000 -> -0.96517106 | K52: =-K45*K51/1000 -> -0.97375966 | ... AM52: =-AM45*AM51/1000 -> -1.7492393 | AO52: =SUM(D52:O52) -> -11.524023 | AP52: =SUM(P52:AA52) -> -13.458544 | AQ52: =SUM(AB52:AM52) -> -17.489757
A53: операционист+верификатор | B53: тыс.сом | D53: =-'OPEX+CAPEX'!I307 -> -0.67460317 | E53: =-'OPEX+CAPEX'!J307 -> -0.68062065 | F53: =-'OPEX+CAPEX'!K307 -> -0.68828809 | G53: =-'OPEX+CAPEX'!L307 -> -0.69616581 | H53: =-'OPEX+CAPEX'!M307 -> -0.70430235 | I53: =-'OPEX+CAPEX'!N307 -> -0.71273006 | J53: =-'OPEX+CAPEX'!O307 -> -0.72149746 | K53: =-'OPEX+CAPEX'!P307 -> -0.72791772 | ... AM53: =-'OPEX+CAPEX'!AR307 -> -1.3076146 | AO53: =SUM(D53:O53) -> -8.6145903 | AP53: =SUM(P53:AA53) -> -10.060709 | AQ53: =SUM(AB53:AM53) -> -13.074175
A54: прибыль | B54: тыс.сом | D54: =D49+D50 -> 0.8229578 | E54: =E49+E50 -> 0.83029861 | F54: =F49+F50 -> 0.83965222 | G54: =G49+G50 -> 0.84926236 | H54: =H49+H50 -> 0.85918824 | I54: =I49+I50 -> 0.86946932 | J54: =J49+J50 -> 0.88016479 | K54: =K49+K50 -> 0.88799696 | ... AM54: =AM49+AM50 -> 1.5951772 | AO54: =SUM(D54:O54) -> 10.509059 | AP54: =SUM(P54:AA54) -> 12.273199 | AQ54: =SUM(AB54:AM54) -> 15.949368
A56: Переводы без открытия счета (Аманат)
A57: общее количество переводов | B57: шт | D57: 2300 | E57: 2300 | F57: 2300 | G57: 2300 | H57: 2300 | I57: 2300 | J57: 2300 | K57: 2300 | L57: 2300 | M57: 2300 | N57: 2300 | O57: 2300 | P57: 2300 | Q57: 2300 | R57: 2300 | S57: 2300 | T57: 2300 | U57: 2300 | V57: 2300 | W57: 2300 | X57: 2300 | Y57: 2300 | Z57: 2300 | AA57: 2300 | AB57: 2300 | AC57: 2300 | AD57: 2300 | AE57: 2300 | AF57: 2300 | AG57: 2300 | AH57: 2300 | AI57: 2300 | AJ57: 2300 | AK57: 2300 | AL57: 2300 | AM57: 2300 | AO57: =SUM(D57:O57) -> 27600 | AP57: =SUM(P57:AA57) -> 27600 | AQ57: =SUM(AB57:AM57) -> 27600
A58: ср.сумма перевода | B58: тыс.сом | D58: 250 | E58: =D58*(1+0.5%) -> 251.25 | F58: =E58*(1+0.5%) -> 252.50625 | G58: =F58*(1+0.5%) -> 253.76878 | H58: =G58*(1+0.5%) -> 255.03763 | I58: =H58*(1+0.5%) -> 256.31281 | J58: =I58*(1+0.5%) -> 257.59438 | K58: =J58*(1+0.5%) -> 258.88235 | L58: =K58*(1+0.5%) -> 260.17676 | ... AM58: =AL58*(1+0.5%) -> 297.68172
A59: ср.комиссия за 1 перевод | B59: % | D59: 0.00125 | E59: 0.00125 | F59: 0.00125 | G59: 0.00125 | H59: 0.00125 | I59: 0.00125 | J59: 0.00125 | K59: 0.00125 | L59: 0.00125 | M59: 0.00125 | N59: 0.00125 | O59: 0.00125 | P59: 0.00125 | Q59: 0.00125 | R59: 0.00125 | S59: 0.00125 | T59: 0.00125 | U59: 0.00125 | V59: 0.00125 | W59: 0.00125 | X59: 0.00125 | Y59: 0.00125 | Z59: 0.00125 | AA59: 0.00125 | AB59: 0.00125 | AC59: 0.00125 | AD59: 0.00125 | AE59: 0.00125 | AF59: 0.00125 | AG59: 0.00125 | AH59: 0.00125 | AI59: 0.00125 | AJ59: 0.00125 | AK59: 0.00125 | AL59: 0.00125 | AM59: 0.00125
A60: комиссионный доход | B60: тыс.сом | D60: =D57*D58*D59 -> 718.75 | E60: =E57*E58*E59 -> 722.34375 | F60: =F57*F58*F59 -> 725.95547 | G60: =G57*G58*G59 -> 729.58525 | H60: =H57*H58*H59 -> 733.23317 | I60: =I57*I58*I59 -> 736.89934 | J60: =J57*J58*J59 -> 740.58383 | K60: =K57*K58*K59 -> 744.28675 | ... AM60: =AM57*AM58*AM59 -> 855.83495 | AO60: =SUM(D60:O60) -> 8866.1855 | AP60: =SUM(P60:AA60) -> 9413.0324 | AQ60: =SUM(AB60:AM60) -> 9993.6076
A61: операционные расходы | B61: тыс.сом | D61: =-'OPEX+CAPEX'!I312 -> -100.39683 | E61: =-'OPEX+CAPEX'!J312 -> -100.39683 | F61: =-'OPEX+CAPEX'!K312 -> -100.39683 | G61: =-'OPEX+CAPEX'!L312 -> -100.39683 | H61: =-'OPEX+CAPEX'!M312 -> -100.39683 | I61: =-'OPEX+CAPEX'!N312 -> -100.39683 | J61: =-'OPEX+CAPEX'!O312 -> -100.39683 | K61: =-'OPEX+CAPEX'!P312 -> -100.39683 | ... AM61: =-'OPEX+CAPEX'!AR312 -> -100.39683 | AO61: =SUM(D61:O61) -> -1204.7619 | AP61: =SUM(P61:AA61) -> -1204.7619 | AQ61: =SUM(AB61:AM61) -> -1204.7619
A62: прибыль | D62: =D60+D61 -> 618.35317 | E62: =E60+E61 -> 621.94692 | F62: =F60+F61 -> 625.55864 | G62: =G60+G61 -> 629.18842 | H62: =H60+H61 -> 632.83635 | I62: =I60+I61 -> 636.50251 | J62: =J60+J61 -> 640.18701 | K62: =K60+K61 -> 643.88993 | ... AM62: =AM60+AM61 -> 755.43813 | AO62: =SUM(D62:O62) -> 7661.4236 | AP62: =SUM(P62:AA62) -> 8208.2705 | AQ62: =SUM(AB62:AM62) -> 8788.8457
A64: SWIFT-переводы
A65: ср.количество переводов на 1 счет, в т.ч. через: | B65: шт | D65: 0.0024165388 | E65: 0.0024165388 | F65: 0.0024165388 | G65: 0.0024165388 | H65: 0.0024165388 | I65: 0.0024165388 | J65: 0.0024165388 | K65: 0.0024165388 | L65: 0.0024165388 | M65: 0.0024165388 | N65: 0.0024165388 | O65: 0.0024165388 | P65: 0.0024165388 | Q65: 0.0024165388 | R65: 0.0024165388 | S65: 0.0024165388 | T65: 0.0024165388 | U65: 0.0024165388 | V65: 0.0024165388 | W65: 0.0024165388 | X65: 0.0024165388 | Y65: 0.0024165388 | Z65: 0.0024165388 | AA65: 0.0024165388 | AB65: 0.0024165388 | AC65: 0.0024165388 | AD65: 0.0024165388 | AE65: 0.0024165388 | AF65: 0.0024165388 | AG65: 0.0024165388 | AH65: 0.0024165388 | AI65: 0.0024165388 | AJ65: 0.0024165388 | AK65: 0.0024165388 | AL65: 0.0024165388 | AM65: 0.0024165388 | AO65: =РБ.2!AO458 -> 0 | AP65: =РБ.2!AP458 -> 0 | AQ65: =РБ.2!AQ458 -> 0
A66: общее количество переводов, в т.ч. через: | B66: шт | D66: =D65*D29 -> 201.55818 | E66: =E65*E29 -> 203.35609 | F66: =F65*F29 -> 205.64697 | G66: =G65*G29 -> 208.00068 | H66: =H65*H29 -> 210.43171 | I66: =I65*I29 -> 212.94975 | J66: =J65*J29 -> 215.56928 | K66: =K65*K29 -> 217.48752 | ... AM66: =AM65*AM29 -> 390.68956 | AO66: =SUM(D66:O66) -> 2573.8704 | AP66: =SUM(P66:AA66) -> 3005.9423 | AQ66: =SUM(AB66:AM66) -> 3906.3067
A67: в т.ч. Доля Безбумажный офис | B67: % | D67: =1-D68 -> 0.97 | E67: =1-E68 -> 0.9664 | F67: =1-F68 -> 0.962368 | G67: =1-G68 -> 0.95785216 | H67: =1-H68 -> 0.95279442 | I67: =1-I68 -> 0.94712975 | J67: =1-J68 -> 0.94078532 | K67: =1-K68 -> 0.93367956 | ... AM67: =1-AM68 -> 0.18190044
A68: в т.ч. Доля Интернет Банкинга | B68: % | D68: 0.03 | E68: =D68*(1+12%) -> 0.0336 | F68: =E68*(1+12%) -> 0.037632 | G68: =F68*(1+12%) -> 0.04214784 | H68: =G68*(1+12%) -> 0.047205581 | I68: =H68*(1+12%) -> 0.05287025 | J68: =I68*(1+12%) -> 0.059214681 | K68: =J68*(1+12%) -> 0.066320442 | L68: =K68*(1+12%) -> 0.074278895 | ... AA68: =Z68*(1+12%) -> 0.40657042 | AB68: =AA68*(1+6%) -> 0.43096464 | AC68: =AB68*(1+6%) -> 0.45682252 | AD68: =AC68*(1+6%) -> 0.48423187 | AE68: =AD68*(1+6%) -> 0.51328579 | AF68: =AE68*(1+6%) -> 0.54408293 | AG68: =AF68*(1+6%) -> 0.57672791 | AH68: =AG68*(1+6%) -> 0.61133158 | AI68: =AH68*(1+6%) -> 0.64801148 | ... AM68: =AL68*(1+6%) -> 0.81809956
A69: Безбумажный офис | B69: шт | D69: =D66*D67 -> 195.51144 | E69: =E66*E67 -> 196.52332 | F69: =F66*F67 -> 197.90806 | G69: =G66*G67 -> 199.2339 | H69: =H66*H67 -> 200.49816 | I69: =I66*I67 -> 201.69104 | J69: =J66*J67 -> 202.80441 | K69: =K66*K67 -> 203.06366 | ... AM69: =AM66*AM67 -> 71.066603 | AO69: =SUM(D69:O69) -> 2416.1846 | AP69: =SUM(P69:AA69) -> 2284.193 | AQ69: =SUM(AB69:AM69) -> 1487.4445
A70: Интернет Банкинг | B70: шт | D70: =D66*D68 -> 6.0467455 | E70: =E66*E68 -> 6.8327646 | F70: =F66*F68 -> 7.7389067 | G70: =G66*G68 -> 8.7667792 | H70: =H66*H68 -> 9.9335513 | I70: =I66*I68 -> 11.258707 | J70: =J66*J68 -> 12.764866 | K70: =K66*K68 -> 14.423869 | ... AM70: =AM66*AM68 -> 319.62296 | AO70: =SUM(D70:O70) -> 157.68588 | AP70: =SUM(P70:AA70) -> 721.74926 | AQ70: =SUM(AB70:AM70) -> 2418.8622
A71: ср.комиссия за 1 перевод | B71: сом | D71: 5100 | E71: 5100 | F71: 5100 | G71: 5100 | H71: 5100 | I71: 5100 | J71: 5100 | K71: 5100 | L71: 5100 | M71: 5100 | N71: 5100 | O71: 5100 | P71: 5100 | Q71: 5100 | R71: 5100 | S71: 5100 | T71: 5100 | U71: 5100 | V71: 5100 | W71: 5100 | X71: 5100 | Y71: 5100 | Z71: 5100 | AA71: 5100 | AB71: 5100 | AC71: 5100 | AD71: 5100 | AE71: 5100 | AF71: 5100 | AG71: 5100 | AH71: 5100 | AI71: 5100 | AJ71: 5100 | AK71: 5100 | AL71: 5100 | AM71: 5100
A72: комиссионный доход | B72: тыс.сом | D72: =D71*D66/1000 -> 1027.9467 | E72: =E71*E66/1000 -> 1037.1161 | F72: =F71*F66/1000 -> 1048.7995 | G72: =G71*G66/1000 -> 1060.8035 | H72: =H71*H66/1000 -> 1073.2017 | I72: =I71*I66/1000 -> 1086.0437 | J72: =J71*J66/1000 -> 1099.4033 | K72: =K71*K66/1000 -> 1109.1864 | ... AM72: =AM71*AM66/1000 -> 1992.5168 | AO72: =SUM(D72:O72) -> 13126.739 | AP72: =SUM(P72:AA72) -> 15330.306 | AQ72: =SUM(AB72:AM72) -> 19922.164
A73: операционные расходы | B73: тыс.сом | D73: =D75+D76 -> -176.79334 | E73: =E75+E76 -> -178.29299 | F73: =F75+F76 -> -180.21392 | G73: =G75+G76 -> -182.17729 | H73: =H75+H76 -> -184.19407 | I73: =I75+I76 -> -186.27069 | J73: =J75+J76 -> -188.41754 | K73: =K75+K76 -> -189.93089 | ... AM73: =AM75+AM76 -> -310.15537 | AO73: =SUM(D73:O73) -> -2249.1247 | AP73: =SUM(P73:AA73) -> -2569.8827 | AQ73: =SUM(AB73:AM73) -> -3183.1678
A74: ср.комиссия за 1 перевод | B74: сом | D74: =-0.774647887323944*1000 -> -774.64789 | E74: =-0.774647887323944*1000 -> -774.64789 | F74: =-0.774647887323944*1000 -> -774.64789 | G74: =-0.774647887323944*1000 -> -774.64789 | H74: =-0.774647887323944*1000 -> -774.64789 | I74: =-0.774647887323944*1000 -> -774.64789 | J74: =-0.774647887323944*1000 -> -774.64789 | K74: =-0.774647887323944*1000 -> -774.64789 | ... AM74: =-0.774647887323944*1000 -> -774.64789
A75: комиссия за перевод | B75: тыс.сом | D75: =D74*D66/1000 -> -156.13662 | E75: =E74*E66/1000 -> -157.52936 | F75: =F74*F66/1000 -> -159.30399 | G75: =G74*G66/1000 -> -161.12728 | H75: =H74*H66/1000 -> -163.01048 | I75: =I74*I66/1000 -> -164.96107 | J75: =J74*J66/1000 -> -166.99028 | K75: =K74*K66/1000 -> -168.47625 | ... AM75: =AM74*AM66/1000 -> -302.64684
A76: сотрудники | B76: тыс.сом | D76: =-'OPEX+CAPEX'!I317 -> -20.656715 | E76: =-'OPEX+CAPEX'!J317 -> -20.763625 | F76: =-'OPEX+CAPEX'!K317 -> -20.909929 | G76: =-'OPEX+CAPEX'!L317 -> -21.05001 | H76: =-'OPEX+CAPEX'!M317 -> -21.183586 | I76: =-'OPEX+CAPEX'!N317 -> -21.309619 | J76: =-'OPEX+CAPEX'!O317 -> -21.427252 | K76: =-'OPEX+CAPEX'!P317 -> -21.454642 | ... AM76: =-'OPEX+CAPEX'!AR317 -> -7.508525 | AO76: =SUM(D76:O76) -> -255.28141 | AP76: =SUM(P76:AA76) -> -241.33587 | AQ76: =SUM(AB76:AM76) -> -157.15559
A77: прибыль | B77: тыс.сом | D77: =D72+D73 -> 851.1534 | E77: =E72+E73 -> 858.82306 | F77: =F72+F73 -> 868.58562 | G77: =G72+G73 -> 878.62616 | H77: =H72+H73 -> 889.00768 | I77: =I72+I73 -> 899.77302 | J77: =J72+J73 -> 910.98577 | K77: =K72+K73 -> 919.25548 | ... AM77: =AM72+AM73 -> 1682.3614 | AO77: =SUM(D77:O77) -> 10877.615 | AP77: =SUM(P77:AA77) -> 12760.423 | AQ77: =SUM(AB77:AM77) -> 16738.996
A79: Переводы по МСДП
A80: общее количество переводов (входящие + исходящие) | B80: шт | D80: 117300 | E80: =D80*(1+3%) -> 120819 | F80: =E80*(1+3%) -> 124443.57 | G80: =F80*(1+3%) -> 128176.88 | H80: =G80*(1+3%) -> 132022.18 | I80: =H80*(1+3%) -> 135982.85 | J80: =I80*(1+3%) -> 140062.33 | K80: =J80*(1+3%) -> 144264.2 | L80: =K80*(1+3%) -> 148592.13 | ... O80: =N80*(1+3%) -> 162370.63 | P80: =O80*(1+0.8%) -> 163669.6 | Q80: =P80*(1+0.8%) -> 164978.95 | R80: =Q80*(1+0.8%) -> 166298.79 | S80: =R80*(1+0.8%) -> 167629.18 | T80: =S80*(1+0.8%) -> 168970.21 | U80: =T80*(1+0.8%) -> 170321.97 | V80: =U80*(1+0.8%) -> 171684.55 | W80: =V80*(1+0.8%) -> 173058.02 | ... AA80: =Z80*(1+0.8%) -> 178662.69 | AB80: =AA80*(1+1.7%) -> 181699.96 | AC80: =AB80*(1+1.7%) -> 184788.86 | AD80: =AC80*(1+1.7%) -> 187930.27 | AE80: =AD80*(1+1.7%) -> 191125.08 | AF80: =AE80*(1+1.7%) -> 194374.21 | AG80: =AF80*(1+1.7%) -> 197678.57 | AH80: =AG80*(1+1.7%) -> 201039.1 | AI80: =AH80*(1+1.7%) -> 204456.77 | ... AM80: =AL80*(1+1.7%) -> 218718.39 | AO80: =SUM(D80:O80) -> 1664725.1 | AP80: =SUM(P80:AA80) -> 2052799.2 | AQ80: =SUM(AB80:AM80) -> 2396273.4
A81: в т.ч. Доля Безбумажный офис | B81: % | D81: =1-D82 -> 1 | E81: =1-E82 -> 1 | F81: =1-F82 -> 0.95 | G81: =1-G82 -> 0.94 | H81: =1-H82 -> 0.928 | I81: =1-I82 -> 0.9136 | J81: =1-J82 -> 0.89632 | K81: =1-K82 -> 0.875584 | ... AM81: =1-AM82 -> 0.30183514
A82: в т.ч. Доля DCB 360 | B82: % | D82: 0 | E82: =D82*(1+12%) -> 0 | F82: 0.05 | G82: =F82*(1+20%) -> 0.06 | H82: =G82*(1+20%) -> 0.072 | I82: =H82*(1+20%) -> 0.0864 | J82: =I82*(1+20%) -> 0.10368 | K82: =J82*(1+20%) -> 0.124416 | L82: =K82*(1+20%) -> 0.1492992 | M82: =L82*(1+20%) -> 0.17915904 | N82: =M82*(1+20%) -> 0.21499085 | O82: =N82*(1+20%) -> 0.25798902 | P82: =O82*(1+6%) -> 0.27346836 | Q82: =P82*(1+6%) -> 0.28987646 | R82: =Q82*(1+6%) -> 0.30726905 | S82: =R82*(1+6%) -> 0.32570519 | T82: =S82*(1+6%) -> 0.3452475 | U82: =T82*(1+6%) -> 0.36596235 | V82: =U82*(1+6%) -> 0.38792009 | W82: =V82*(1+6%) -> 0.4111953 | ... AA82: =Z82*(1+6%) -> 0.51912459 | AB82: =AA82*(1+2.5%) -> 0.53210271 | AC82: =AB82*(1+2.5%) -> 0.54540527 | AD82: =AC82*(1+2.5%) -> 0.55904041 | AE82: =AD82*(1+2.5%) -> 0.57301642 | AF82: =AE82*(1+2.5%) -> 0.58734183 | AG82: =AF82*(1+2.5%) -> 0.60202537 | AH82: =AG82*(1+2.5%) -> 0.61707601 | AI82: =AH82*(1+2.5%) -> 0.63250291 | ... AM82: =AL82*(1+2.5%) -> 0.69816486
A83: Безбумажный офис | B83: шт | D83: =D80*D81 -> 117300 | E83: =E80*E81 -> 120819 | F83: =F80*F81 -> 118221.39 | G83: =G80*G81 -> 120486.26 | H83: =H80*H81 -> 122516.59 | I83: =I80*I81 -> 124233.93 | J83: =J80*J81 -> 125540.67 | K83: =K80*K81 -> 126315.43 | ... AM83: =AM80*AM81 -> 66016.896 | AO83: =SUM(D83:O83) -> 1471701.1 | AP83: =SUM(P83:AA83) -> 1259266.3 | AQ83: =SUM(AB83:AM83) -> 923160.46
A84: DCB 360 | B84: шт | D84: =D80*D82 -> 0 | E84: =E80*E82 -> 0 | F84: =F80*F82 -> 6222.1785 | G84: =G80*G82 -> 7690.6126 | H84: =H80*H82 -> 9505.5972 | I84: =I80*I82 -> 11748.918 | J84: =J80*J82 -> 14521.663 | K84: =K80*K82 -> 17948.775 | ... AM84: =AM80*AM82 -> 152701.5 | AO84: =SUM(D84:O84) -> 193024 | AP84: =SUM(P84:AA84) -> 793532.95 | AQ84: =SUM(AB84:AM84) -> 1473113
A85: ср.сумма 1 перевода | B85: сом | D85: 46300 | E85: 46300 | F85: 46300 | G85: 46300 | H85: 46300 | I85: 46300 | J85: 46300 | K85: 46300 | L85: 46300 | M85: 46300 | N85: 46300 | O85: 46300 | P85: 46300 | Q85: 46300 | R85: 46300 | S85: 46300 | T85: 46300 | U85: 46300 | V85: 46300 | W85: 46300 | X85: 46300 | Y85: 46300 | Z85: 46300 | AA85: 46300 | AB85: 46300 | AC85: 46300 | AD85: 46300 | AE85: 46300 | AF85: 46300 | AG85: 46300 | AH85: 46300 | AI85: 46300 | AJ85: 46300 | AK85: 46300 | AL85: 46300 | AM85: 46300
A86: общая сумма переводов | B86: тыс.сом | D86: =D80*D85/1000 -> 5430990 | E86: =E80*E85/1000 -> 5593919.7 | F86: =F80*F85/1000 -> 5761737.3 | G86: =G80*G85/1000 -> 5934589.4 | H86: =H80*H85/1000 -> 6112627.1 | I86: =I80*I85/1000 -> 6296005.9 | J86: =J80*J85/1000 -> 6484886.1 | K86: =K80*K85/1000 -> 6679432.7 | ... AM86: =AM80*AM85/1000 -> 10126662 | AO86: =SUM(D86:O86) -> 77076771 | AP86: =SUM(P86:AA86) -> 95044603 | AQ86: =SUM(AB86:AM86) -> 1.1094746e+08
A87: ср.% комиссии | B87: % | D87: 0.0028539916 | E87: 0.0028539916 | F87: 0.0028539916 | G87: 0.0028539916 | H87: 0.0028539916 | I87: 0.0028539916 | J87: 0.0028539916 | K87: 0.0028539916 | L87: 0.0028539916 | M87: 0.0028539916 | N87: 0.0028539916 | O87: 0.0028539916 | P87: 0.0028539916 | Q87: 0.0028539916 | R87: 0.0028539916 | S87: 0.0028539916 | T87: 0.0028539916 | U87: 0.0028539916 | V87: 0.0028539916 | W87: 0.0028539916 | X87: 0.0028539916 | Y87: 0.0028539916 | Z87: 0.0028539916 | AA87: 0.0028539916 | AB87: 0.0028539916 | AC87: 0.0028539916 | AD87: 0.0028539916 | AE87: 0.0028539916 | AF87: 0.0028539916 | AG87: 0.0028539916 | AH87: 0.0028539916 | AI87: 0.0028539916 | AJ87: 0.0028539916 | AK87: 0.0028539916 | AL87: 0.0028539916 | AM87: 0.0028539916
A88: комиссионный доход | B88: тыс.сом | D88: =D86*D87 -> 15500 | E88: =E86*E87 -> 15965 | F88: =F86*F87 -> 16443.95 | G88: =G86*G87 -> 16937.269 | H88: =H86*H87 -> 17445.387 | I88: =I86*I87 -> 17968.748 | J88: =J86*J87 -> 18507.811 | K88: =K86*K87 -> 19063.045 | ... AM88: =AM86*AM87 -> 28901.407 | AO88: =SUM(D88:O88) -> 219976.46 | AP88: =SUM(P88:AA88) -> 271256.5 | AQ88: =SUM(AB88:AM88) -> 316643.12
A89: операционные расходы | B89: тыс.сом | D89: =D91+D92 -> -4654.7619 | E89: =E91+E92 -> -4794.4048 | F89: =F91+F92 -> -4691.3251 | G89: =G91+G92 -> -4781.201 | H89: =H91+H92 -> -4861.7693 | I89: =I91+I92 -> -4929.9179 | J89: =J91+J92 -> -4981.7727 | K89: =K91+K92 -> -5012.517 | ... AM89: =AM91+AM92 -> -2619.7181 | AO89: =SUM(D89:O89) -> -58400.836 | AP89: =SUM(P89:AA89) -> -49970.883 | AQ89: =SUM(AB89:AM89) -> -36633.352
A90: ср.% комиссии МСДП | B90: % | D90: 0 | E90: 0 | F90: 0 | G90: 0 | H90: 0 | I90: 0 | J90: 0 | K90: 0 | L90: 0 | M90: 0 | N90: 0 | O90: 0 | P90: 0 | Q90: 0 | R90: 0 | S90: 0 | T90: 0 | U90: 0 | V90: 0 | W90: 0 | X90: 0 | Y90: 0 | Z90: 0 | AA90: 0 | AB90: 0 | AC90: 0 | AD90: 0 | AE90: 0 | AF90: 0 | AG90: 0 | AH90: 0 | AI90: 0 | AJ90: 0 | AK90: 0 | AL90: 0 | AM90: 0
A91: комиссия МСДП | B91: тыс.сом | D91: =-D90*D86 -> 0 | E91: =-E90*E86 -> 0 | F91: =-F90*F86 -> 0 | G91: =-G90*G86 -> 0 | H91: =-H90*H86 -> 0 | I91: =-I90*I86 -> 0 | J91: =-J90*J86 -> 0 | K91: =-K90*K86 -> 0 | ... AM91: =-AM90*AM86 -> 0 | AO91: =SUM(D91:O91) -> 0 | AP91: =SUM(P91:AA91) -> 0 | AQ91: =SUM(AB91:AM91) -> 0
A92: сотрудники | B92: тыс.сом | D92: =-'OPEX+CAPEX'!I325 -> -4654.7619 | E92: =-'OPEX+CAPEX'!J325 -> -4794.4048 | F92: =-'OPEX+CAPEX'!K325 -> -4691.3251 | G92: =-'OPEX+CAPEX'!L325 -> -4781.201 | H92: =-'OPEX+CAPEX'!M325 -> -4861.7693 | I92: =-'OPEX+CAPEX'!N325 -> -4929.9179 | J92: =-'OPEX+CAPEX'!O325 -> -4981.7727 | K92: =-'OPEX+CAPEX'!P325 -> -5012.517 | ... AM92: =-'OPEX+CAPEX'!AR325 -> -2619.7181 | AO92: =SUM(D92:O92) -> -58400.836 | AP92: =SUM(P92:AA92) -> -49970.883 | AQ92: =SUM(AB92:AM92) -> -36633.352
A93: прибыль | B93: тыс.сом | D93: =D88+D89 -> 10845.238 | E93: =E88+E89 -> 11170.595 | F93: =F88+F89 -> 11752.625 | G93: =G88+G89 -> 12156.068 | H93: =H88+H89 -> 12583.617 | I93: =I88+I89 -> 13038.83 | J93: =J88+J89 -> 13526.038 | K93: =K88+K89 -> 14050.528 | ... AM93: =AM88+AM89 -> 26281.689 | AO93: =SUM(D93:O93) -> 161575.62 | AP93: =SUM(P93:AA93) -> 221285.62 | AQ93: =SUM(AB93:AM93) -> 280009.77
A95: Карточные переводы
A96: ср. сумма переводов на 1 карту | B96: тыс.сом | D96: 10 | E96: 10 | F96: 10 | G96: 10 | H96: 10 | I96: 10 | J96: 10 | K96: 10 | L96: 10 | M96: 10 | N96: 10 | O96: 10 | P96: 10 | Q96: 10 | R96: 10 | S96: 10 | T96: 10 | U96: 10 | V96: 10 | W96: 10 | X96: 10 | Y96: 10 | Z96: 10 | AA96: 10 | AB96: 10 | AC96: 10 | AD96: 10 | AE96: 10 | AF96: 10 | AG96: 10 | AH96: 10 | AI96: 10 | AJ96: 10 | AK96: 10 | AL96: 10 | AM96: 10 | AO96: =РБ.2!AO485 -> 0 | AP96: =РБ.2!AP485 -> 0 | AQ96: =РБ.2!AQ485 -> 0
A97: общая сумма переводов | B97: тыс.сом | D97: =D96*D11 -> 274480 | E97: =E96*E11 -> 281040 | F97: =F96*F11 -> 287760 | G97: =G96*G11 -> 294650 | H97: =H96*H11 -> 301700 | I97: =I96*I11 -> 308920 | J97: =J96*J11 -> 316310 | K97: =K96*K11 -> 323880 | ... AM97: =AM96*AM11 -> 628220 | AO97: =SUM(D97:O97) -> 3763650 | AP97: =SUM(P97:AA97) -> 4998780 | AQ97: =SUM(AB97:AM97) -> 6640530
A98: ср.% комиссии | B98: % | D98: 0 | E98: 0 | F98: 0 | G98: 0 | H98: 0 | I98: 0 | J98: 0 | K98: 0 | L98: 0 | M98: 0 | N98: 0 | O98: 0 | P98: 0 | Q98: 0 | R98: 0 | S98: 0 | T98: 0 | U98: 0 | V98: 0 | W98: 0 | X98: 0 | Y98: 0 | Z98: 0 | AA98: 0 | AB98: 0 | AC98: 0 | AD98: 0 | AE98: 0 | AF98: 0 | AG98: 0 | AH98: 0 | AI98: 0 | AJ98: 0 | AK98: 0 | AL98: 0 | AM98: 0
A99: комиссионный доход | B99: тыс.сом | D99: =D97*D98 -> 0 | E99: =E97*E98 -> 0 | F99: =F97*F98 -> 0 | G99: =G97*G98 -> 0 | H99: =H97*H98 -> 0 | I99: =I97*I98 -> 0 | J99: =J97*J98 -> 0 | K99: =K97*K98 -> 0 | ... AM99: =AM97*AM98 -> 0 | AO99: =SUM(D99:O99) -> 0 | AP99: =SUM(P99:AA99) -> 0 | AQ99: =SUM(AB99:AM99) -> 0
A100: операционные расходы | B100: тыс.сом | D100: =D102 -> 0 | E100: =E102 -> 0 | F100: =F102 -> 0 | G100: =G102 -> 0 | H100: =H102 -> 0 | I100: =I102 -> 0 | J100: =J102 -> 0 | K100: =K102 -> 0 | ... AM100: =AM102 -> 0 | AO100: =SUM(D100:O100) -> 0 | AP100: =SUM(P100:AA100) -> 0 | AQ100: =SUM(AB100:AM100) -> 0
A101: ср.% комиссии провайдерам | B101: %
A102: комиссия провайдерам | B102: тыс.сом | D102: =-D97*D101 -> 0 | E102: =-E97*E101 -> 0 | F102: =-F97*F101 -> 0 | G102: =-G97*G101 -> 0 | H102: =-H97*H101 -> 0 | I102: =-I97*I101 -> 0 | J102: =-J97*J101 -> 0 | K102: =-K97*K101 -> 0 | ... AM102: =-AM97*AM101 -> 0 | AO102: =SUM(D102:O102) -> 0 | AP102: =SUM(P102:AA102) -> 0 | AQ102: =SUM(AB102:AM102) -> 0
A103: прибыль | B103: тыс.сом | D103: =D99+D100 -> 0 | E103: =E99+E100 -> 0 | F103: =F99+F100 -> 0 | G103: =G99+G100 -> 0 | H103: =H99+H100 -> 0 | I103: =I99+I100 -> 0 | J103: =J99+J100 -> 0 | K103: =K99+K100 -> 0 | ... AM103: =AM99+AM100 -> 0 | AO103: =SUM(D103:O103) -> 0 | AP103: =SUM(P103:AA103) -> 0 | AQ103: =SUM(AB103:AM103) -> 0
A105: Прием платежей
A106: общее количество платежей | B106: шт | C106: 11000 | D106: 11000 | E106: =D106*(1+1%) -> 11110 | F106: =E106*(1+1%) -> 11221.1 | G106: =F106*(1+1%) -> 11333.311 | H106: =G106*(1+1%) -> 11446.644 | I106: =H106*(1+1%) -> 11561.111 | J106: =I106*(1+1%) -> 11676.722 | K106: =J106*(1+1%) -> 11793.489 | L106: =K106*(1+1%) -> 11911.424 | ... AM106: =AL106*(1+1%) -> 15582.63 | AO106: =SUM(D106:O106) -> 139507.53 | AP106: =SUM(P106:AA106) -> 157200.58 | AQ106: =SUM(AB106:AM106) -> 177137.55
A107: доля платежей через операционистов | B107: % | D107: 0 | E107: 0 | F107: 0 | G107: 0 | H107: 0 | I107: 0 | J107: 0 | K107: 0 | L107: 0 | M107: 0 | N107: 0 | O107: 0 | P107: 0 | Q107: 0 | R107: 0 | S107: 0 | T107: 0 | U107: 0 | V107: 0 | W107: 0 | X107: 0 | Y107: 0 | Z107: 0 | AA107: 0 | AB107: 0 | AC107: 0 | AD107: 0 | AE107: 0 | AF107: 0 | AG107: 0 | AH107: 0 | AI107: 0 | AJ107: 0 | AK107: 0 | AL107: 0 | AM107: 0
A108: количество платежей через операционистов | B108: шт | D108: =D106*D107 -> 0 | E108: =E106*E107 -> 0 | F108: =F106*F107 -> 0 | G108: =G106*G107 -> 0 | H108: =H106*H107 -> 0 | I108: =I106*I107 -> 0 | J108: =J106*J107 -> 0 | K108: =K106*K107 -> 0 | ... AM108: =AM106*AM107 -> 0
A109: в т.ч. DCB 360 | B109: шт. | D109: =D106-D108 -> 11000 | E109: =E106-E108 -> 11110 | F109: =F106-F108 -> 11221.1 | G109: =G106-G108 -> 11333.311 | H109: =H106-H108 -> 11446.644 | I109: =I106-I108 -> 11561.111 | J109: =J106-J108 -> 11676.722 | K109: =K106-K108 -> 11793.489 | ... AM109: =AM106-AM108 -> 15582.63
...

Sheet МСБ>>>
F5: Бизнес-клиенты
F7: МСБ.1 | G7: Кредиты
F8: МСБ.2 | G8: Счета и депозиты
F9: МСБ.3 | G9: Обслуживание клиентов

Sheet МСБ.1
A1: Малый и средний бизнес - Кредиты
D3: 46023 | E3: 46054 | F3: 46082 | G3: 46113 | H3: 46143 | I3: 46174 | J3: 46204 | K3: 46235 | L3: 46266 | M3: 46296 | N3: 46327 | O3: 46357 | P3: 46388 | Q3: 46419 | R3: 46447 | S3: 46478 | T3: 46508 | U3: 46539 | V3: 46569 | W3: 46600 | X3: 46631 | Y3: 46661 | Z3: 46692 | AA3: 46722 | AB3: 46753 | AC3: 46784 | AD3: 46813 | AE3: 46844 | AF3: 46874 | AG3: 46905 | AH3: 46935 | AI3: 46966 | AJ3: 46997 | AK3: 47027 | AL3: 47058 | AM3: 47088 | AO3: =YEAR(O3) -> 2026 | AP3: =YEAR(AA3) -> 2027 | AQ3: =YEAR(AM3) -> 2028
D4: m1 | E4: m2 | F4: m3 | G4: m4 | H4: m5 | I4: m6 | J4: m7 | K4: m8 | L4: m9 | M4: m10 | N4: m11 | O4: m12 | P4: m13 | Q4: m14 | R4: m15 | S4: m16 | T4: m17 | U4: m18 | V4: m19 | W4: m20 | X4: m21 | Y4: m22 | Z4: m23 | AA4: m24 | AB4: m25 | AC4: m26 | AD4: m27 | AE4: m28 | AF4: m29 | AG4: m30 | AH4: m31 | AI4: m32 | AJ4: m33 | AK4: m34 | AL4: m35 | AM4: m36 | AO4: Y1 | AP4: Y2 | AQ4: Y3
D5: 1 | E5: =D5+1 -> 2 | F5: =E5+1 -> 3 | G5: =F5+1 -> 4 | H5: =G5+1 -> 5 | I5: =H5+1 -> 6 | J5: =I5+1 -> 7 | K5: =J5+1 -> 8 | L5: =K5+1 -> 9 | ... AM5: =AL5+1 -> 36
A7: сезонность | B7: % | D7: 0.4 | E7: 0.8 | F7: 1 | G7: 1 | H7: 0.4 | I7: 1 | J7: 1 | K7: 0.7 | L7: 1 | M7: 1 | N7: 0.9 | O7: 0.8 | P7: 0.4 | Q7: 0.8 | R7: 1 | S7: 1 | T7: 0.4 | U7: 1 | V7: 1 | W7: 0.7 | X7: 1 | Y7: 1 | Z7: 0.9 | AA7: 0.8 | AB7: 0.4 | AC7: 0.8 | AD7: 1 | AE7: 1 | AF7: 0.4 | AG7: 1 | AH7: 1 | AI7: 0.7 | AJ7: 1 | AK7: 1 | AL7: 0.9 | AM7: 0.8
A8: Итого
A9: количество заявок | B9: шт | D9: =D30+D58+D86+D110 -> 60.375 | E9: =E30+E58+E86+E110 -> 65.2825 | F9: =F30+F58+F86+F110 -> 75.302453 | G9: =G30+G58+G86+G110 -> 116.27974 | H9: =H30+H58+H86+H110 -> 50.173743 | I9: =I30+I58+I86+I110 -> 104.91047 | J9: =J30+J58+J86+J110 -> 99.690391 | K9: =K30+K58+K86+K110 -> 69.330194 | ... AM9: =AM30+AM58+AM86+AM110 -> 72 | AO9: =SUM(D9:O9) -> 970.69025 | AP9: =SUM(P9:AA9) -> 895 | AQ9: =SUM(AB9:AM9) -> 895
A10: количество кредитных специалистов | B10: чел | D10: ='0'!D14 -> 130 | E10: ='0'!E14 -> 122.85 | F10: ='0'!F14 -> 116.09325 | G10: ='0'!G14 -> 109.70812 | H10: ='0'!H14 -> 103.67417 | I10: ='0'!I14 -> 97.972095 | J10: ='0'!J14 -> 92.58363 | K10: ='0'!K14 -> 87.49153 | ... AM10: ='0'!AM14 -> 80
A11: количество заявок на 1 специалиста | B11: шт | D11: =D9/D10 -> 0.46442308 | E11: =E9/E10 -> 0.53140008 | F11: =F9/F10 -> 0.64863765 | G11: =G9/G10 -> 1.059901 | H11: =H9/H10 -> 0.48395604 | I11: =I9/I10 -> 1.0708199 | J11: =J9/J10 -> 1.0767605 | K11: =K9/K10 -> 0.79242178 | ... AM11: =AM9/AM10 -> 0.9
A12: выдачи | B12: тыс сом | D12: =D34+D62+D90 -> 29575 | E12: =E34+E62+E90 -> 31326.75 | F12: =F34+F62+F90 -> 37004.723 | G12: =G34+G62+G90 -> 62396.494 | H12: =H34+H62+H90 -> 23585.875 | I12: =I34+I62+I90 -> 55721.629 | J12: =J34+J62+J90 -> 52656.939 | K12: =K34+K62+K90 -> 34832.565 | ... AM12: =AM34+AM62+AM90 -> 36400 | AO12: =SUM(D12:O12) -> 496973.94 | AP12: =SUM(P12:AA12) -> 455000 | AQ12: =SUM(AB12:AM12) -> 455000
A13: погашения | B13: тыс сом | D13: =D36+D64+D92 -> 49152.778 | E13: =E36+E64+E92 -> 48230.826 | F13: =F36+F64+F92 -> 47266.551 | G13: =G36+G64+G92 -> 46525.952 | H13: =H36+H64+H92 -> 46904.513 | I13: =I36+I64+I92 -> 45889.06 | J13: =J36+J64+J92 -> 46064.841 | K13: =K36+K64+K92 -> 46130.342 | ... AM13: =AM36+AM64+AM92 -> 39672.926 | AO13: =SUM(D13:O13) -> 557488.86 | AP13: =SUM(P13:AA13) -> 509556.67 | AQ13: =SUM(AB13:AM13) -> 479331.66
A14: кредитный портфель | B14: тыс сом | C14: =C37+C65+C93 -> 1240000 | D14: =D37+D65+D93 -> 1220422.2 | E14: =E37+E65+E93 -> 1203518.1 | F14: =F37+F65+F93 -> 1193256.3 | G14: =G37+G65+G93 -> 1209126.9 | H14: =H37+H65+H93 -> 1185808.2 | I14: =I37+I65+I93 -> 1195640.8 | J14: =J37+J65+J93 -> 1202232.9 | ... AM14: =AM37+AM65+AM93 -> 1100596.7 | AO14: =O14 -> 1179485.1 | AP14: =AA14 -> 1124928.4 | AQ14: =AM14 -> 1100596.7
A15: просроченная задолженность | B15: тыс сом | D15: =D39+D67+D95 -> 12274.664 | E15: =E39+E67+E95 -> 11930.199 | F15: =F39+F67+F95 -> 11629.834 | G15: =G39+G67+G95 -> 11628.093 | H15: =H39+H67+H95 -> 11331.566 | I15: =I39+I67+I95 -> 11292.211 | J15: =J39+J67+J95 -> 11231.721 | K15: =K39+K67+K95 -> 11038.525 | ... AM15: =AM39+AM67+AM95 -> 8499.3398 | AO15: =O15 -> 10558.901 | AP15: =AA15 -> 9259.0736 | AQ15: =AM15 -> 8499.3398
A16: РППУ на конец месяца | B16: тыс сом | D16: =D44+D72+D100 -> -34509.538 | E16: =E44+E72+E100 -> -33772.866 | F16: =F44+F72+F100 -> -33190.186 | G16: =G44+G72+G100 -> -33414.839 | H16: =H44+H72+H100 -> -32670.329 | I16: =I44+I72+I100 -> -32756.484 | J16: =J44+J72+J100 -> -32766.999 | K16: =K44+K72+K100 -> -32337.675 | ... AM16: =AM44+AM72+AM100 -> -27527.962 | AO16: =O16 -> -31509.382 | AP16: =AA16 -> -28928.218 | AQ16: =AM16 -> -27527.962
A17: % доход | B17: тыс сом | D17: =D45+D73+D101 -> 23087.725 | E17: =E45+E73+E101 -> 22758.627 | F17: =F45+F73+F101 -> 22521.054 | G17: =G45+G73+G101 -> 22591.699 | H17: =H45+H73+H101 -> 22534.021 | I17: =I45+I73+I101 -> 22418.426 | J17: =J45+J73+J101 -> 22587.029 | K17: =K45+K73+K101 -> 22554.157 | ... AM17: =AM45+AM73+AM101 -> 20964.62 | AO17: =SUM(D17:O17) -> 270843.7 | AP17: =SUM(P17:AA17) -> 258364.96 | AQ17: =SUM(AB17:AM17) -> 250658.28
A18: трансфертный расход | B18: тыс сом | D18: =D46+D74+D102 -> -15377.639 | E18: =E46+E74+E102 -> -15149.627 | F18: =F46+F74+F102 -> -14979.84 | G18: =G46+G74+G102 -> -15014.895 | H18: =H46+H74+H102 -> -14968.344 | I18: =I46+I74+I102 -> -14884.056 | J18: =J46+J74+J102 -> -14986.711 | K18: =K46+K74+K102 -> -14957.3 | ... AM18: =AM46+AM74+AM102 -> -13777.915 | AO18: =SUM(D18:O18) -> -179795.08 | AP18: =SUM(P18:AA18) -> -170626.86 | AQ18: =SUM(AB18:AM18) -> -164946.3
A19: расходы на провизии | B19: тыс сом | D19: =D47+D75+D103+D115 -> 10246.462 | E19: =E47+E75+E103+E115 -> 736.67144 | F19: =F47+F75+F103+F115 -> 582.67989 | G19: =G47+G75+G103+G115 -> -224.65247 | H19: =H47+H75+H103+H115 -> 744.50958 | I19: =I47+I75+I103+I115 -> -86.154925 | J19: =J47+J75+J103+J115 -> -10.514912 | K19: =K47+K75+K103+K115 -> 429.32431 | ... AM19: =AM47+AM75+AM103+AM115 -> 136.02867 | AO19: =SUM(D19:O19) -> 13246.618 | AP19: =SUM(P19:AA19) -> 2581.1644 | AQ19: =SUM(AB19:AM19) -> 1400.2559
A20: комиссии | B20: тыс сом | D20: =D48+D76+D104+D116 -> 147.05882 | E20: =E48+E76+E104+E116 -> 147.05882 | F20: =F48+F76+F104+F116 -> 147.05882 | G20: =G48+G76+G104+G116 -> 147.05882 | H20: =H48+H76+H104+H116 -> 147.05882 | I20: =I48+I76+I104+I116 -> 147.05882 | J20: =J48+J76+J104+J116 -> 147.05882 | K20: =K48+K76+K104+K116 -> 147.05882 | ... AM20: =AM48+AM76+AM104+AM116 -> 147.05882 | AO20: =SUM(D20:O20) -> 1764.7059 | AP20: =SUM(P20:AA20) -> 1764.7059 | AQ20: =SUM(AB20:AM20) -> 1764.7059
A21: операционные доходы | B21: тыс сом | D21: =D49+D77+D105++D117 -> 18103.607 | E21: =E49+E77+E105++E117 -> 8492.7295 | F21: =F49+F77+F105++F117 -> 8270.9525 | G21: =G49+G77+G105++G117 -> 7499.2106 | H21: =H49+H77+H105++H117 -> 8457.2453 | I21: =I49+I77+I105++I117 -> 7595.2734 | J21: =J49+J77+J105++J117 -> 7736.8619 | K21: =K49+K77+K105++K117 -> 8173.2396 | ... AM21: =AM49+AM77+AM105++AM117 -> 7469.7923 | AO21: =SUM(D21:O21) -> 106059.94 | AP21: =SUM(P21:AA21) -> 92083.967 | AQ21: =SUM(AB21:AM21) -> 88876.939
A22: операционные расходы | B22: тыс сом | D22: =D50+D78+D106+D118 -> -92.655875 | E22: =E50+E78+E106+E118 -> -96.313753 | F22: =F50+F78+F106+F118 -> -103.97786 | G22: =G50+G78+G106+G118 -> -136.64164 | H22: =H50+H78+H106+H118 -> -83.295292 | I22: =I50+I78+I106+I118 -> -127.01826 | J22: =J50+J78+J106+J118 -> -123.0338 | K22: =K50+K78+K106+K118 -> -98.497599 | ... AM22: =AM50+AM78+AM106+AM118 -> -96.599946 | AO22: =SUM(D22:O22) -> -1295.8569 | AP22: =SUM(P22:AA22) -> -1203.661 | AQ22: =SUM(AB22:AM22) -> -1184.3698
A23: прибыль | B23: тыс сом | D23: =D51+D79+D107+D119 -> 18010.951 | E23: =E51+E79+E107+E119 -> 8396.4158 | F23: =F51+F79+F107+F119 -> 8166.9746 | G23: =G51+G79+G107+G119 -> 7362.569 | H23: =H51+H79+H107+H119 -> 8373.95 | I23: =I51+I79+I107+I119 -> 7468.2551 | J23: =J51+J79+J107+J119 -> 7613.8281 | K23: =K51+K79+K107+K119 -> 8074.742 | ... AM23: =AM51+AM79+AM107+AM119 -> 7373.1923 | AO23: =SUM(D23:O23) -> 104764.08 | AP23: =SUM(P23:AA23) -> 90880.306 | AQ23: =SUM(AB23:AM23) -> 87692.569
A25: Бизнес-кредит (ИП, ЮЛ)
A26: Безбумажный офис
A27: количество кредитов | B27: шт | D27: =INT(D37/D33) -> 814 | E27: =INT(E37/E33) -> 780 | F27: =INT(F37/F33) -> 747 | G27: =INT(G37/G33) -> 744 | H27: =INT(H37/H33) -> 723 | I27: =INT(I37/I33) -> 717 | J27: =INT(J37/J33) -> 710 | K27: =INT(K37/K33) -> 696 | ... AM27: =INT(AM37/AM33) -> 495 | AO27: =O27 -> 657 | AP27: =AA27 -> 556 | AQ27: =AM27 -> 495
A28: количество кредитных специалистов | B28: шт | D28: ='0'!D14 -> 130 | E28: ='0'!E14 -> 122.85 | F28: ='0'!F14 -> 116.09325 | G28: ='0'!G14 -> 109.70812 | H28: ='0'!H14 -> 103.67417 | I28: ='0'!I14 -> 97.972095 | J28: ='0'!J14 -> 92.58363 | K28: ='0'!K14 -> 87.49153 | ... AM28: ='0'!AM14 -> 80 | AO28: =O28 -> 80 | AP28: =AA28 -> 80 | AQ28: =AM28 -> 80
A29: среднее количество заявок на 1 специалиста | B29: шт | D29: 0.40625 | G29: 0.40625 | H29: 0.40625 | I29: 0.40625 | J29: 0.40625 | K29: 0.40625 | L29: 0.40625 | M29: 0.40625 | N29: 0.40625 | O29: 0.40625 | P29: 0.40625 | Q29: 0.40625 | R29: 0.40625 | S29: 0.40625 | T29: 0.40625 | U29: 0.40625 | V29: 0.40625 | W29: 0.40625 | X29: 0.40625 | Y29: 0.40625 | Z29: 0.40625 | AA29: 0.40625 | AB29: 0.40625 | AC29: 0.40625 | AD29: 0.40625 | AE29: 0.40625 | AF29: 0.40625 | AG29: 0.40625 | AH29: 0.40625 | AI29: 0.40625 | AJ29: 0.40625 | AK29: 0.40625 | AL29: 0.40625 | AM29: 0.40625 | AO29: =AVERAGE(D29:O29) -> 0.40625 | AP29: =AVERAGE(P29:AA29) -> 0.40625 | AQ29: =AVERAGE(AB29:AM29) -> 0.40625
A30: количество заявок | B30: шт | D30: =D28*D29*D7 -> 21.125 | E30: =E28*E29*E7 -> 0 | F30: =F28*F29*F7 -> 0 | G30: =G28*G29*G7 -> 44.568924 | H30: =H28*H29*H7 -> 16.847053 | I30: =I28*I29*I7 -> 39.801164 | J30: =J28*J29*J7 -> 37.6121 | K30: =K28*K29*K7 -> 24.880404 | ... AM30: =AM28*AM29*AM7 -> 26 | AO30: =SUM(D30:O30) -> 306.17319 | AP30: =SUM(P30:AA30) -> 325 | AQ30: =SUM(AB30:AM30) -> 325
A31: APR, % | B31: % | D31: 0.61538462 | E31: 0.61538462 | F31: 0.61538462 | G31: 0.61538462 | H31: 0.61538462 | I31: 0.61538462 | J31: 0.61538462 | K31: 0.61538462 | L31: 0.61538462 | M31: 0.61538462 | N31: 0.61538462 | O31: 0.61538462 | P31: 0.61538462 | Q31: 0.61538462 | R31: 0.61538462 | S31: 0.61538462 | T31: 0.61538462 | U31: 0.61538462 | V31: 0.61538462 | W31: 0.61538462 | X31: 0.61538462 | Y31: 0.61538462 | Z31: 0.61538462 | AA31: 0.61538462 | AB31: 0.61538462 | AC31: 0.61538462 | AD31: 0.61538462 | AE31: 0.61538462 | AF31: 0.61538462 | AG31: 0.61538462 | AH31: 0.61538462 | AI31: 0.61538462 | AJ31: 0.61538462 | AK31: 0.61538462 | AL31: 0.61538462 | AM31: 0.61538462 | AO31: =AVERAGE(D31:O31) -> 0.61538462 | AP31: =AVERAGE(P31:AA31) -> 0.61538462 | AQ31: =AVERAGE(AB31:AM31) -> 0.61538462
A32: количество выдач | B32: шт | D32: =D30*D31 -> 13 | E32: =E30*E31 -> 0 | F32: =F30*F31 -> 0 | G32: =G30*G31 -> 27.42703 | H32: =H30*H31 -> 10.367417 | I32: =I30*I31 -> 24.493024 | J32: =J30*J31 -> 23.145907 | K32: =K30*K31 -> 15.311018 | ... AM32: =AM30*AM31 -> 16 | AO32: =SUM(D32:O32) -> 188.41427 | AP32: =SUM(P32:AA32) -> 200 | AQ32: =SUM(AB32:AM32) -> 200
A33: ср. сумма выдачи | B33: тыс сом | D33: 1000 | E33: 1000 | F33: 1000 | G33: 1000 | H33: 1000 | I33: 1000 | J33: 1000 | K33: 1000 | L33: 1000 | M33: 1000 | N33: 1000 | O33: 1000 | P33: 1000 | Q33: 1000 | R33: 1000 | S33: 1000 | T33: 1000 | U33: 1000 | V33: 1000 | W33: 1000 | X33: 1000 | Y33: 1000 | Z33: 1000 | AA33: 1000 | AB33: 1000 | AC33: 1000 | AD33: 1000 | AE33: 1000 | AF33: 1000 | AG33: 1000 | AH33: 1000 | AI33: 1000 | AJ33: 1000 | AK33: 1000 | AL33: 1000 | AM33: 1000 | AO33: =AVERAGE(D33:O33) -> 1000 | AP33: =AVERAGE(P33:AA33) -> 1000 | AQ33: =AVERAGE(AB33:AM33) -> 1000
A34: выдачи | B34: тыс сом | D34: =D32*D33 -> 13000 | E34: =E32*E33 -> 0 | F34: =F32*F33 -> 0 | G34: =G32*G33 -> 27427.03 | H34: =H32*H33 -> 10367.417 | I34: =I32*I33 -> 24493.024 | J34: =J32*J33 -> 23145.907 | K34: =K32*K33 -> 15311.018 | ... AM34: =AM32*AM33 -> 16000 | AO34: =SUM(D34:O34) -> 188414.27 | AP34: =SUM(P34:AA34) -> 200000 | AQ34: =SUM(AB34:AM34) -> 200000
A35: cр. срок портфеля | B35: мес | D35: 24 | E35: 24 | F35: 24 | G35: 24 | H35: 24 | I35: 24 | J35: 24 | K35: 24 | L35: 24 | M35: 24 | N35: 24 | O35: 24 | P35: 24 | Q35: 24 | R35: 24 | S35: 24 | T35: 24 | U35: 24 | V35: 24 | W35: 24 | X35: 24 | Y35: 24 | Z35: 24 | AA35: 24 | AB35: 24 | AC35: 24 | AD35: 24 | AE35: 24 | AF35: 24 | AG35: 24 | AH35: 24 | AI35: 24 | AJ35: 24 | AK35: 24 | AL35: 24 | AM35: 24 | AO35: =AVERAGE(D35:O35) -> 24 | AP35: =AVERAGE(P35:AA35) -> 24 | AQ35: =AVERAGE(AB35:AM35) -> 24
A36: погашения | B36: тыс сом | D36: =C37/D35 -> 34833.333 | E36: =D37/E35 -> 33923.611 | F36: =E37/F35 -> 32510.127 | G36: =F37/G35 -> 31155.539 | H36: =G37/H35 -> 31000.184 | I36: =H37/I35 -> 30140.486 | J36: =I37/J35 -> 29905.175 | K36: =J37/K35 -> 29623.539 | ... AM36: =AL37/AM35 -> 20863.438 | AO36: =SUM(D36:O36) -> 367002.93 | AP36: =SUM(P36:AA36) -> 300965.99 | AQ36: =SUM(AB36:AM36) -> 260586.28
A37: кредитный портфель | B37: тыс сом | C37: 836000 | D37: =C37+D34-D36 -> 814166.67 | E37: =D37+E34-E36 -> 780243.06 | F37: =E37+F34-F36 -> 747732.93 | G37: =F37+G34-G36 -> 744004.42 | H37: =G37+H34-H36 -> 723371.65 | I37: =H37+I34-I36 -> 717724.19 | J37: =I37+J34-J36 -> 710964.92 | K37: =J37+K34-K36 -> 696652.4 | ... AM37: =AL37+AM34-AM36 -> 495859.07 | AO37: =O37 -> 657411.34 | AP37: =AA37 -> 556445.35 | AQ37: =AM37 -> 495859.07
A38: доля просроченной задолженности, % | B38: % | D38: 0.010784717 | E38: 0.010784717 | F38: 0.010784717 | G38: 0.010784717 | H38: 0.010784717 | I38: 0.010784717 | J38: 0.010784717 | K38: 0.010784717 | L38: 0.010784717 | M38: 0.010784717 | N38: 0.010784717 | O38: 0.010784717 | P38: 0.010784717 | Q38: 0.010784717 | R38: 0.010784717 | S38: 0.010784717 | T38: 0.010784717 | U38: 0.010784717 | V38: 0.010784717 | W38: 0.010784717 | X38: 0.010784717 | Y38: 0.010784717 | Z38: 0.010784717 | AA38: 0.010784717 | AB38: 0.010784717 | AC38: 0.010784717 | AD38: 0.010784717 | AE38: 0.010784717 | AF38: 0.010784717 | AG38: 0.010784717 | AH38: 0.010784717 | AI38: 0.010784717 | AJ38: 0.010784717 | AK38: 0.010784717 | AL38: 0.010784717 | AM38: 0.010784717 | AO38: =O38 -> 0.010784717 | AP38: =AA38 -> 0.010784717 | AQ38: =AM38 -> 0.010784717
A39: просроченная задолженность | B39: тыс сом | D39: =D37*D38 -> 8780.5567 | E39: =E37*E38 -> 8414.7002 | F39: =F37*F38 -> 8064.0877 | G39: =G37*G38 -> 8023.8768 | H39: =H37*H38 -> 7801.3582 | I39: =I37*I38 -> 7740.4519 | J39: =J37*J38 -> 7667.5552 | K39: =K37*K38 -> 7513.1987 | ... AM39: =AM37*AM38 -> 5347.6995 | AO39: =O39 -> 7089.995 | AP39: =AA39 -> 6001.1053 | AQ39: =AM39 -> 5347.6995
A40: ср. % ставка портфеля | B40: % | D40: 0.23 | E40: 0.23 | F40: 0.23 | G40: 0.23 | H40: 0.23 | I40: 0.23 | J40: 0.23 | K40: 0.23 | L40: 0.23 | M40: 0.23 | N40: 0.23 | O40: 0.23 | P40: 0.23 | Q40: 0.23 | R40: 0.23 | S40: 0.23 | T40: 0.23 | U40: 0.23 | V40: 0.23 | W40: 0.23 | X40: 0.23 | Y40: 0.23 | Z40: 0.23 | AA40: 0.23 | AB40: 0.23 | AC40: 0.23 | AD40: 0.23 | AE40: 0.23 | AF40: 0.23 | AG40: 0.23 | AH40: 0.23 | AI40: 0.23 | AJ40: 0.23 | AK40: 0.23 | AL40: 0.23 | AM40: 0.23 | AO40: =AVERAGE(D40:O40) -> 0.23 | AP40: =AVERAGE(P40:AA40) -> 0.23 | AQ40: =AVERAGE(AB40:AM40) -> 0.23
A41: ср. % ставка фондирования | B41: % | D41: 0.15 | E41: 0.15 | F41: 0.15 | G41: 0.15 | H41: 0.15 | I41: 0.15 | J41: 0.15 | K41: 0.15 | L41: 0.15 | M41: 0.15 | N41: 0.15 | O41: 0.15 | P41: 0.15 | Q41: 0.15 | R41: 0.15 | S41: 0.15 | T41: 0.15 | U41: 0.15 | V41: 0.15 | W41: 0.15 | X41: 0.15 | Y41: 0.15 | Z41: 0.15 | AA41: 0.15 | AB41: 0.15 | AC41: 0.15 | AD41: 0.15 | AE41: 0.15 | AF41: 0.15 | AG41: 0.15 | AH41: 0.15 | AI41: 0.15 | AJ41: 0.15 | AK41: 0.15 | AL41: 0.15 | AM41: 0.15 | AO41: =AVERAGE(D41:O41) -> 0.15 | AP41: =AVERAGE(P41:AA41) -> 0.15 | AQ41: =AVERAGE(AB41:AM41) -> 0.15
A42: ср. % резервирования | B42: % | D42: 0.0299 | E42: 0.0299 | F42: 0.0299 | G42: 0.0299 | H42: 0.0299 | I42: 0.0299 | J42: 0.0299 | K42: 0.0299 | L42: 0.0299 | M42: 0.0299 | N42: 0.0299 | O42: 0.0299 | P42: 0.0299 | Q42: 0.0299 | R42: 0.0299 | S42: 0.0299 | T42: 0.0299 | U42: 0.0299 | V42: 0.0299 | W42: 0.0299 | X42: 0.0299 | Y42: 0.0299 | Z42: 0.0299 | AA42: 0.0299 | AB42: 0.0299 | AC42: 0.0299 | AD42: 0.0299 | AE42: 0.0299 | AF42: 0.0299 | AG42: 0.0299 | AH42: 0.0299 | AI42: 0.0299 | AJ42: 0.0299 | AK42: 0.0299 | AL42: 0.0299 | AM42: 0.0299 | AO42: =AVERAGE(D42:O42) -> 0.0299 | AP42: =AVERAGE(P42:AA42) -> 0.0299 | AQ42: =AVERAGE(AB42:AM42) -> 0.0299
A43: ср. комиссия на 1 клиента | B43: тыс сом | AO43: =AVERAGE(D43:O43) -> #DIV/0! | AP43: =AVERAGE(P43:AA43) -> #DIV/0! | AQ43: =AVERAGE(AB43:AM43) -> #DIV/0!
A44: РППУ на конец месяца | B44: тыс сом | C44: -34556 | D44: =-D37*D42 -> -24343.583 | E44: =-E37*E42 -> -23329.267 | F44: =-F37*F42 -> -22357.215 | G44: =-G37*G42 -> -22245.732 | H44: =-H37*H42 -> -21628.812 | I44: =-I37*I42 -> -21459.953 | J44: =-J37*J42 -> -21257.851 | K44: =-K37*K42 -> -20829.907 | ... AM44: =-AM37*AM42 -> -14826.186 | AO44: =O44 -> -19656.599 | AP44: =AA44 -> -16637.716 | AQ44: =AM44 -> -14826.186
A45: % доход | B45: тыс сом | D45: =(C37+D37)/2*D40/12*(1-2/102) -> 15504.017 | E45: =(D37+E37)/2*E40/12*(1-2/102) -> 14980.157 | F45: =(E37+F37)/2*F40/12*(1-2/102) -> 14355.984 | G45: =(F37+G37)/2*G40/12*(1-2/102) -> 14015.506 | H45: =(G37+H37)/2*H40/12*(1-2/102) -> 13786.622 | I45: =(H37+I37)/2*I40/12*(1-2/102) -> 13539.708 | J45: =(I37+J37)/2*J40/12*(1-2/102) -> 13423.141 | K45: =(J37+K37)/2*K40/12*(1-2/102) -> 13225.163 | ... AM45: =(AL37+AM37)/2*AM40/12*(1-2/102) -> 9363.3074 | AO45: =SUM(D45:O45) -> 163833.21 | AP45: =SUM(P45:AA45) -> 134781.14 | AQ45: =SUM(AB45:AM45) -> 116950.07
A46: трансфертный расход | B46: тыс сом | D46: =-(C37+D37)/2*D41/12 -> -10313.542 | E46: =-(D37+E37)/2*E41/12 -> -9965.0608 | F46: =-(E37+F37)/2*F41/12 -> -9549.8499 | G46: =-(F37+G37)/2*G41/12 -> -9323.3584 | H46: =-(G37+H37)/2*H41/12 -> -9171.1005 | I46: =-(H37+I37)/2*I41/12 -> -9006.849 | J46: =-(I37+J37)/2*J41/12 -> -8929.307 | K46: =-(J37+K37)/2*K41/12 -> -8797.6083 | ... AM46: =-(AL37+AM37)/2*AM41/12 -> -6228.6349 | AO46: =SUM(D46:O46) -> -108984.7 | AP46: =SUM(P46:AA46) -> -89658.761 | AQ46: =SUM(AB46:AM46) -> -77797.219
A47: расходы на провизии | B47: тыс сом | D47: =(D44-C44) -> 10212.417 | E47: =(E44-D44) -> 1014.316 | F47: =(F44-E44) -> 972.05281 | G47: =(G44-F44) -> 111.4824 | H47: =(H44-G44) -> 616.91972 | I47: =(I44-H44) -> 168.85911 | J47: =(J44-I44) -> 202.10209 | K47: =(K44-J44) -> 427.94437 | ... AM47: =(AM44-AL44) -> 145.41679 | AO47: =SUM(D47:O47) -> 14899.401 | AP47: =SUM(P47:AA47) -> 3018.8832 | AQ47: =SUM(AB47:AM47) -> 1811.5297
A48: комиссии | B48: тыс сом | D48: =D43*(AVERAGE(C37:D37)/D33)*(1-2/102) -> 0 | E48: =E43*(AVERAGE(D37:E37)/E33)*(1-2/102) -> 0 | F48: =F43*(AVERAGE(E37:F37)/F33)*(1-2/102) -> 0 | G48: =G43*(AVERAGE(F37:G37)/G33)*(1-2/102) -> 0 | H48: =H43*(AVERAGE(G37:H37)/H33)*(1-2/102) -> 0 | I48: =I43*(AVERAGE(H37:I37)/I33)*(1-2/102) -> 0 | J48: =J43*(AVERAGE(I37:J37)/J33)*(1-2/102) -> 0 | K48: =K43*(AVERAGE(J37:K37)/K33)*(1-2/102) -> 0 | ... AM48: =AM43*(AVERAGE(AL37:AM37)/AM33)*(1-2/102) -> 0 | AO48: =SUM(D48:O48) -> 0 | AP48: =SUM(P48:AA48) -> 0 | AQ48: =SUM(AB48:AM48) -> 0
A49: операционные доходы | B49: тыс сом | D49: =SUM(D45:D48) -> 15402.892 | E49: =SUM(E45:E48) -> 6029.4119 | F49: =SUM(F45:F48) -> 5778.1864 | G49: =SUM(G45:G48) -> 4803.6301 | H49: =SUM(H45:H48) -> 5232.4409 | I49: =SUM(I45:I48) -> 4701.7178 | J49: =SUM(J45:J48) -> 4695.9363 | K49: =SUM(K45:K48) -> 4855.4989 | ... AM49: =SUM(AM45:AM48) -> 3280.0893 | AO49: =SUM(D49:O49) -> 69747.91 | AP49: =SUM(P49:AA49) -> 48141.266 | AQ49: =SUM(AB49:AM49) -> 40964.378
A50: операционные расходы | B50: тыс сом | D50: =-'OPEX+CAPEX'!I130 -> -42.331292 | E50: =-'OPEX+CAPEX'!J130 -> -24.6675 | F50: =-'OPEX+CAPEX'!K130 -> -23.623875 | G50: =-'OPEX+CAPEX'!L130 -> -58.527033 | H50: =-'OPEX+CAPEX'!M130 -> -36.094132 | I50: =-'OPEX+CAPEX'!N130 -> -53.929244 | J50: =-'OPEX+CAPEX'!O130 -> -51.988892 | K50: =-'OPEX+CAPEX'!P130 -> -41.548497 | ... AM50: =-'OPEX+CAPEX'!AR130 -> -36.071042 | AO50: =SUM(D50:O50) -> -513.15846 | AP50: =SUM(P50:AA50) -> -480.25183 | AQ50: =SUM(AB50:AM50) -> -450.87221
A51: прибыль | B51: тыс сом | D51: =D49+D50 -> 15360.561 | E51: =E49+E50 -> 6004.7444 | F51: =F49+F50 -> 5754.5625 | G51: =G49+G50 -> 4745.1031 | H51: =H49+H50 -> 5196.3467 | I51: =I49+I50 -> 4647.7885 | J51: =J49+J50 -> 4643.9474 | K51: =K49+K50 -> 4813.9504 | ... AM51: =AM49+AM50 -> 3244.0182 | AO51: =SUM(D51:O51) -> 69234.751 | AP51: =SUM(P51:AA51) -> 47661.014 | AQ51: =SUM(AB51:AM51) -> 40513.506
A53: GREEN - ЭКОАВТО (ИП, ЮЛ)
A54: Безбумажный офис
A55: количество кредитов | B55: шт | D55: =INT(D65/D61) -> 188 | E55: =INT(E65/E61) -> 207 | F55: =INT(F65/F61) -> 229 | G55: =INT(G65/G61) -> 250 | H55: =INT(H65/H61) -> 253 | I55: =INT(I65/I61) -> 270 | J55: =INT(J65/J61) -> 285 | K55: =INT(K65/K61) -> 292 | ... AM55: =INT(AM65/AM61) -> 458 | AO55: =O55 -> 330 | AP55: =AA55 -> 405 | AQ55: =AM55 -> 458
A56: количество кредитных специалистов | B56: шт | D56: ='0'!D14 -> 130 | E56: ='0'!E14 -> 122.85 | F56: ='0'!F14 -> 116.09325 | G56: ='0'!G14 -> 109.70812 | H56: ='0'!H14 -> 103.67417 | I56: ='0'!I14 -> 97.972095 | J56: ='0'!J14 -> 92.58363 | K56: ='0'!K14 -> 87.49153 | ... AM56: ='0'!AM14 -> 80 | AO56: =O56 -> 80 | AP56: =AA56 -> 80 | AQ56: =AM56 -> 80
A57: среднее количество заявок на 1 специалиста | B57: шт | D57: 0.375 | E57: 0.375 | F57: 0.375 | G57: 0.375 | H57: 0.375 | I57: 0.375 | J57: 0.375 | K57: 0.375 | L57: 0.375 | M57: 0.375 | N57: 0.375 | O57: 0.375 | P57: 0.375 | Q57: 0.375 | R57: 0.375 | S57: 0.375 | T57: 0.375 | U57: 0.375 | V57: 0.375 | W57: 0.375 | X57: 0.375 | Y57: 0.375 | Z57: 0.375 | AA57: 0.375 | AB57: 0.375 | AC57: 0.375 | AD57: 0.375 | AE57: 0.375 | AF57: 0.375 | AG57: 0.375 | AH57: 0.375 | AI57: 0.375 | AJ57: 0.375 | AK57: 0.375 | AL57: 0.375 | AM57: 0.375 | AO57: =AVERAGE(D57:O57) -> 0.375 | AP57: =AVERAGE(P57:AA57) -> 0.375 | AQ57: =AVERAGE(AB57:AM57) -> 0.375
A58: количество заявок | B58: шт | D58: =D56*D57*D7 -> 19.5 | E58: =E56*E57*E7 -> 36.855 | F58: =F56*F57*F7 -> 43.534969 | G58: =G56*G57*G7 -> 41.140545 | H58: =H56*H57*H7 -> 15.551126 | I58: =I56*I57*I7 -> 36.739536 | J58: =J56*J57*J7 -> 34.718861 | K58: =K56*K57*K7 -> 22.966527 | ... AM58: =AM56*AM57*AM7 -> 24 | AO58: =SUM(D58:O58) -> 363.01137 | AP58: =SUM(P58:AA58) -> 300 | AQ58: =SUM(AB58:AM58) -> 300
A59: APR, % | B59: % | D59: 0.65 | E59: 0.65 | F59: 0.65 | G59: 0.65 | H59: 0.65 | I59: 0.65 | J59: 0.65 | K59: 0.65 | L59: 0.65 | M59: 0.65 | N59: 0.65 | O59: 0.65 | P59: 0.65 | Q59: 0.65 | R59: 0.65 | S59: 0.65 | T59: 0.65 | U59: 0.65 | V59: 0.65 | W59: 0.65 | X59: 0.65 | Y59: 0.65 | Z59: 0.65 | AA59: 0.65 | AB59: 0.65 | AC59: 0.65 | AD59: 0.65 | AE59: 0.65 | AF59: 0.65 | AG59: 0.65 | AH59: 0.65 | AI59: 0.65 | AJ59: 0.65 | AK59: 0.65 | AL59: 0.65 | AM59: 0.65 | AO59: =AVERAGE(D59:O59) -> 0.65 | AP59: =AVERAGE(P59:AA59) -> 0.65 | AQ59: =AVERAGE(AB59:AM59) -> 0.65
A60: количество выдач | B60: шт | D60: =D58*D59 -> 12.675 | E60: =E58*E59 -> 23.95575 | F60: =F58*F59 -> 28.29773 | G60: =G58*G59 -> 26.741355 | H60: =H58*H59 -> 10.108232 | I60: =I58*I59 -> 23.880698 | J60: =J58*J59 -> 22.56726 | K60: =K58*K59 -> 14.928242 | ... AM60: =AM58*AM59 -> 15.6 | AO60: =SUM(D60:O60) -> 235.95739 | AP60: =SUM(P60:AA60) -> 195 | AQ60: =SUM(AB60:AM60) -> 195
A61: ср. сумма выдачи | B61: тыс сом | D61: 1000 | E61: 1000 | F61: 1000 | G61: 1000 | H61: 1000 | I61: 1000 | J61: 1000 | K61: 1000 | L61: 1000 | M61: 1000 | N61: 1000 | O61: 1000 | P61: 1000 | Q61: 1000 | R61: 1000 | S61: 1000 | T61: 1000 | U61: 1000 | V61: 1000 | W61: 1000 | X61: 1000 | Y61: 1000 | Z61: 1000 | AA61: 1000 | AB61: 1000 | AC61: 1000 | AD61: 1000 | AE61: 1000 | AF61: 1000 | AG61: 1000 | AH61: 1000 | AI61: 1000 | AJ61: 1000 | AK61: 1000 | AL61: 1000 | AM61: 1000 | AO61: =AVERAGE(D61:O61) -> 1000 | AP61: =AVERAGE(P61:AA61) -> 1000 | AQ61: =AVERAGE(AB61:AM61) -> 1000
A62: выдачи | B62: тыс сом | D62: =D60*D61 -> 12675 | E62: =E60*E61 -> 23955.75 | F62: =F60*F61 -> 28297.73 | G62: =G60*G61 -> 26741.355 | H62: =H60*H61 -> 10108.232 | I62: =I60*I61 -> 23880.698 | J62: =J60*J61 -> 22567.26 | K62: =K60*K61 -> 14928.242 | ... AM62: =AM60*AM61 -> 15600 | AO62: =SUM(D62:O62) -> 235957.39 | AP62: =SUM(P62:AA62) -> 195000 | AQ62: =SUM(AB62:AM62) -> 195000
A63: cр. срок портфеля | B63: мес | D63: 36 | E63: 36 | F63: 36 | G63: 36 | H63: 36 | I63: 36 | J63: 36 | K63: 36 | L63: 36 | M63: 36 | N63: 36 | O63: 36 | P63: 36 | Q63: 36 | R63: 36 | S63: 36 | T63: 36 | U63: 36 | V63: 36 | W63: 36 | X63: 36 | Y63: 36 | Z63: 36 | AA63: 36 | AB63: 36 | AC63: 36 | AD63: 36 | AE63: 36 | AF63: 36 | AG63: 36 | AH63: 36 | AI63: 36 | AJ63: 36 | AK63: 36 | AL63: 36 | AM63: 36 | AO63: =AVERAGE(D63:O63) -> 36 | AP63: =AVERAGE(P63:AA63) -> 36 | AQ63: =AVERAGE(AB63:AM63) -> 36
A64: погашения | B64: тыс сом | D64: =C65/D63 -> 5027.7778 | E64: =D65/E63 -> 5240.2006 | F64: =E65/F63 -> 5760.077 | G64: =F65/G63 -> 6386.1229 | H64: =G65/H63 -> 6951.546 | I64: =H65/I63 -> 7039.2317 | J64: =I65/J63 -> 7507.0502 | K64: =J65/K63 -> 7925.3894 | ... AM64: =AL65/AM63 -> 12643.286 | AO64: =SUM(D64:O64) -> 86177.612 | AP64: =SUM(P64:AA64) -> 120672.27 | AQ64: =SUM(AB64:AM64) -> 141992.49
A65: кредитный портфель | B65: тыс сом | C65: 181000 | D65: =C65+D62-D64 -> 188647.22 | E65: =D65+E62-E64 -> 207362.77 | F65: =E65+F62-F64 -> 229900.42 | G65: =F65+G62-G64 -> 250255.66 | H65: =G65+H62-H64 -> 253412.34 | I65: =H65+I62-I64 -> 270253.81 | J65: =I65+J62-J64 -> 285314.02 | K65: =J65+K62-K64 -> 292316.87 | ... AM65: =AL65+AM62-AM64 -> 458115.02 | AO65: =O65 -> 330779.78 | AP65: =AA65 -> 405107.51 | AQ65: =AM65 -> 458115.02
A66: доля просроченной задолженности, % | B66: % | D66: 0.0024088398 | E66: 0.0024088398 | F66: 0.0024088398 | G66: 0.0024088398 | H66: 0.0024088398 | I66: 0.0024088398 | J66: 0.0024088398 | K66: 0.0024088398 | L66: 0.0024088398 | M66: 0.0024088398 | N66: 0.0024088398 | O66: 0.0024088398 | P66: 0.0024088398 | Q66: 0.0024088398 | R66: 0.0024088398 | S66: 0.0024088398 | T66: 0.0024088398 | U66: 0.0024088398 | V66: 0.0024088398 | W66: 0.0024088398 | X66: 0.0024088398 | Y66: 0.0024088398 | Z66: 0.0024088398 | AA66: 0.0024088398 | AB66: 0.0024088398 | AC66: 0.0024088398 | AD66: 0.0024088398 | AE66: 0.0024088398 | AF66: 0.0024088398 | AG66: 0.0024088398 | AH66: 0.0024088398 | AI66: 0.0024088398 | AJ66: 0.0024088398 | AK66: 0.0024088398 | AL66: 0.0024088398 | AM66: 0.0024088398 | AO66: =O66 -> 0.0024088398 | AP66: =AA66 -> 0.0024088398 | AQ66: =AM66 -> 0.0024088398
A67: просроченная задолженность | B67: тыс сом | D67: =D65*D66 -> 454.42093 | E67: =E65*E66 -> 499.50369 | F67: =F65*F66 -> 553.79329 | G67: =G65*G66 -> 602.82578 | H67: =H65*H66 -> 610.42973 | I67: =I65*I66 -> 650.99812 | J67: =J65*J66 -> 687.27576 | K67: =K65*K66 -> 704.14451 | ... AM67: =AM65*AM66 -> 1103.5257 | AO67: =O67 -> 796.7955 | AP67: =AA67 -> 975.8391 | AQ67: =AM67 -> 1103.5257
A68: ср. % ставка портфеля | B68: % | D68: 0.24 | E68: 0.24 | F68: 0.24 | G68: 0.24 | H68: 0.24 | I68: 0.24 | J68: 0.24 | K68: 0.24 | L68: 0.24 | M68: 0.24 | N68: 0.24 | O68: 0.24 | P68: 0.24 | Q68: 0.24 | R68: 0.24 | S68: 0.24 | T68: 0.24 | U68: 0.24 | V68: 0.24 | W68: 0.24 | X68: 0.24 | Y68: 0.24 | Z68: 0.24 | AA68: 0.24 | AB68: 0.24 | AC68: 0.24 | AD68: 0.24 | AE68: 0.24 | AF68: 0.24 | AG68: 0.24 | AH68: 0.24 | AI68: 0.24 | AJ68: 0.24 | AK68: 0.24 | AL68: 0.24 | AM68: 0.24 | AO68: =AVERAGE(D68:O68) -> 0.24 | AP68: =AVERAGE(P68:AA68) -> 0.24 | AQ68: =AVERAGE(AB68:AM68) -> 0.24
A69: ср. % ставка фондирования | B69: % | D69: 0.15 | E69: 0.15 | F69: 0.15 | G69: 0.15 | H69: 0.15 | I69: 0.15 | J69: 0.15 | K69: 0.15 | L69: 0.15 | M69: 0.15 | N69: 0.15 | O69: 0.15 | P69: 0.15 | Q69: 0.15 | R69: 0.15 | S69: 0.15 | T69: 0.15 | U69: 0.15 | V69: 0.15 | W69: 0.15 | X69: 0.15 | Y69: 0.15 | Z69: 0.15 | AA69: 0.15 | AB69: 0.15 | AC69: 0.15 | AD69: 0.15 | AE69: 0.15 | AF69: 0.15 | AG69: 0.15 | AH69: 0.15 | AI69: 0.15 | AJ69: 0.15 | AK69: 0.15 | AL69: 0.15 | AM69: 0.15 | AO69: =AVERAGE(D69:O69) -> 0.15 | AP69: =AVERAGE(P69:AA69) -> 0.15 | AQ69: =AVERAGE(AB69:AM69) -> 0.15
A70: ср. % резервирования | B70: % | D70: 0.017679558 | E70: 0.017679558 | F70: 0.017679558 | G70: 0.017679558 | H70: 0.017679558 | I70: 0.017679558 | J70: 0.017679558 | K70: 0.017679558 | L70: 0.017679558 | M70: 0.017679558 | N70: 0.017679558 | O70: 0.017679558 | P70: 0.017679558 | Q70: 0.017679558 | R70: 0.017679558 | S70: 0.017679558 | T70: 0.017679558 | U70: 0.017679558 | V70: 0.017679558 | W70: 0.017679558 | X70: 0.017679558 | Y70: 0.017679558 | Z70: 0.017679558 | AA70: 0.017679558 | AB70: 0.017679558 | AC70: 0.017679558 | AD70: 0.017679558 | AE70: 0.017679558 | AF70: 0.017679558 | AG70: 0.017679558 | AH70: 0.017679558 | AI70: 0.017679558 | AJ70: 0.017679558 | AK70: 0.017679558 | AL70: 0.017679558 | AM70: 0.017679558 | AO70: =AVERAGE(D70:O70) -> 0.017679558 | AP70: =AVERAGE(P70:AA70) -> 0.017679558 | AQ70: =AVERAGE(AB70:AM70) -> 0.017679558
A71: ср. комиссия на 1 клиента | B71: тыс сом | AO71: =AVERAGE(D71:O71) -> #DIV/0! | AP71: =AVERAGE(P71:AA71) -> #DIV/0! | AQ71: =AVERAGE(AB71:AM71) -> #DIV/0!
A72: РППУ на конец месяца | B72: тыс сом | C72: -3200 | D72: =-D65*D70 -> -3335.1995 | E72: =-E65*E70 -> -3666.0821 | F72: =-F65*F70 -> -4064.5379 | G72: =-G65*G70 -> -4424.4094 | H72: =-H65*H70 -> -4480.2182 | I72: =-I65*I70 -> -4777.9679 | J72: =-J65*J70 -> -5044.2257 | K72: =-K65*K70 -> -5168.0331 | ... AM72: =-AM65*AM70 -> -8099.2712 | AO72: =O72 -> -5848.0403 | AP72: =AA72 -> -7162.1218 | AQ72: =AM72 -> -8099.2712
A73: % доход | B73: тыс сом | D73: =(C65+D65)/2*D68/12*(1-2/102) -> 3623.9924 | E73: =(D65+E65)/2*E68/12*(1-2/102) -> 3882.4509 | F73: =(E65+F65)/2*F68/12*(1-2/102) -> 4286.8941 | G73: =(F65+G65)/2*G68/12*(1-2/102) -> 4707.4126 | H73: =(G65+H65)/2*H68/12*(1-2/102) -> 4937.9215 | I73: =(H65+I65)/2*I68/12*(1-2/102) -> 5133.9819 | J73: =(I65+J65)/2*J68/12*(1-2/102) -> 5446.7434 | K73: =(J65+K65)/2*K68/12*(1-2/102) -> 5663.0479 | ... AM73: =(AL65+AM65)/2*AM68/12*(1-2/102) -> 8953.6602 | AO73: =SUM(D73:O73) -> 62299.685 | AP73: =SUM(P73:AA73) -> 85909.127 | AQ73: =SUM(AB73:AM73) -> 100749.67
A74: трансфертный расход | B74: тыс сом | D74: =-(C65+D65)/2*D69/12 -> -2310.2951 | E74: =-(D65+E65)/2*E69/12 -> -2475.0625 | F74: =-(E65+F65)/2*F69/12 -> -2732.895 | G74: =-(F65+G65)/2*G69/12 -> -3000.9755 | H74: =-(G65+H65)/2*H69/12 -> -3147.925 | I74: =-(H65+I65)/2*I69/12 -> -3272.9134 | J74: =-(I65+J65)/2*J69/12 -> -3472.2989 | K74: =-(J65+K65)/2*K69/12 -> -3610.1931 | ... AM74: =-(AL65+AM65)/2*AM69/12 -> -5707.9583 | AO74: =SUM(D74:O74) -> -39716.049 | AP74: =SUM(P74:AA74) -> -54767.069 | AQ74: =SUM(AB74:AM74) -> -64227.917
A75: расходы на провизии | B75: тыс сом | D75: =(D72-C72) -> -135.19951 | E75: =(E72-D72) -> -330.88264 | F75: =(F72-E72) -> -398.45574 | G75: =(G72-F72) -> -359.8715 | H75: =(H72-G72) -> -55.808814 | I75: =(I72-H72) -> -297.74968 | J75: =(J72-I72) -> -266.25785 | K75: =(K72-J72) -> -123.80734 | ... AM75: =(AM72-AL72) -> -52.273389 | AO75: =SUM(D75:O75) -> -2648.0403 | AP75: =SUM(P75:AA75) -> -1314.0815 | AQ75: =SUM(AB75:AM75) -> -937.14936
A76: комиссии | B76: тыс сом | D76: =D71*(AVERAGE(C65:D65)/D61)*(1-2/102) -> 0 | E76: =E71*(AVERAGE(D65:E65)/E61)*(1-2/102) -> 0 | F76: =F71*(AVERAGE(E65:F65)/F61)*(1-2/102) -> 0 | G76: =G71*(AVERAGE(F65:G65)/G61)*(1-2/102) -> 0 | H76: =H71*(AVERAGE(G65:H65)/H61)*(1-2/102) -> 0 | I76: =I71*(AVERAGE(H65:I65)/I61)*(1-2/102) -> 0 | J76: =J71*(AVERAGE(I65:J65)/J61)*(1-2/102) -> 0 | K76: =K71*(AVERAGE(J65:K65)/K61)*(1-2/102) -> 0 | ... AM76: =AM71*(AVERAGE(AL65:AM65)/AM61)*(1-2/102) -> 0 | AO76: =SUM(D76:O76) -> 0 | AP76: =SUM(P76:AA76) -> 0 | AQ76: =SUM(AB76:AM76) -> 0
A77: операционные доходы | B77: тыс сом | D77: =SUM(D73:D76) -> 1178.4977 | E77: =SUM(E73:E76) -> 1076.5058 | F77: =SUM(F73:F76) -> 1155.5434 | G77: =SUM(G73:G76) -> 1346.5656 | H77: =SUM(H73:H76) -> 1734.1877 | I77: =SUM(I73:I76) -> 1563.3187 | J77: =SUM(J73:J76) -> 1708.1866 | K77: =SUM(K73:K76) -> 1929.0475 | ... AM77: =SUM(AM73:AM76) -> 3193.4284 | AO77: =SUM(D77:O77) -> 19935.595 | AP77: =SUM(P77:AA77) -> 29827.977 | AQ77: =SUM(AB77:AM77) -> 35584.608
A78: операционные расходы | B78: тыс сом | D78: =-'OPEX+CAPEX'!I145 -> -21.499071 | E78: =-'OPEX+CAPEX'!J145 -> -35.942625 | F78: =-'OPEX+CAPEX'!K145 -> -41.966445 | G78: =-'OPEX+CAPEX'!L145 -> -40.720733 | H78: =-'OPEX+CAPEX'!M145 -> -20.404999 | I78: =-'OPEX+CAPEX'!N145 -> -37.842903 | J78: =-'OPEX+CAPEX'!O145 -> -36.70555 | K78: =-'OPEX+CAPEX'!P145 -> -27.553039 | ... AM78: =-'OPEX+CAPEX'!AR145 -> -33.627107 | AO78: =SUM(D78:O78) -> -392.23116 | AP78: =SUM(P78:AA78) -> -378.84684 | AQ78: =SUM(AB78:AM78) -> -402.47071
A79: прибыль | B79: тыс сом | D79: =D77+D78 -> 1156.9987 | E79: =E77+E78 -> 1040.5632 | F79: =F77+F78 -> 1113.5769 | G79: =G77+G78 -> 1305.8448 | H79: =H77+H78 -> 1713.7827 | I79: =I77+I78 -> 1525.4758 | J79: =J77+J78 -> 1671.4811 | K79: =K77+K78 -> 1901.4945 | ... AM79: =AM77+AM78 -> 3159.8013 | AO79: =SUM(D79:O79) -> 19543.364 | AP79: =SUM(P79:AA79) -> 29449.13 | AQ79: =SUM(AB79:AM79) -> 35182.137
A81: ЭКО-Агрокредит (ИП, ЮЛ)
A82: Безбумажный офис
A83: количество кредитов | B83: шт | D83: =INT(D93/D89) -> 362 | E83: =INT(E93/E89) -> 359 | F83: =INT(F93/F89) -> 359 | G83: =INT(G93/G89) -> 358 | H83: =INT(H93/H89) -> 348 | I83: =INT(I93/I89) -> 346 | J83: =INT(J93/J89) -> 343 | K83: =INT(K93/K89) -> 336 | ... AM83: =INT(AM93/AM89) -> 244 | AO83: =O83 -> 318 | AP83: =AA83 -> 272 | AQ83: =AM83 -> 244
A84: количество кредитных специалистов | B84: шт | D84: ='0'!D14 -> 130 | E84: ='0'!E14 -> 122.85 | F84: ='0'!F14 -> 116.09325 | G84: ='0'!G14 -> 109.70812 | H84: ='0'!H14 -> 103.67417 | I84: ='0'!I14 -> 97.972095 | J84: ='0'!J14 -> 92.58363 | K84: ='0'!K14 -> 87.49153 | ... AM84: ='0'!AM14 -> 80 | AO84: =O84 -> 80 | AP84: =AA84 -> 80 | AQ84: =AM84 -> 80
A85: среднее количество заявок на 1 специалиста | B85: шт | D85: 0.1875 | E85: 0.1875 | F85: 0.1875 | G85: 0.1875 | H85: 0.1875 | I85: 0.1875 | J85: 0.1875 | K85: 0.1875 | L85: 0.1875 | M85: 0.1875 | N85: 0.1875 | O85: 0.1875 | P85: 0.1875 | Q85: 0.1875 | R85: 0.1875 | S85: 0.1875 | T85: 0.1875 | U85: 0.1875 | V85: 0.1875 | W85: 0.1875 | X85: 0.1875 | Y85: 0.1875 | Z85: 0.1875 | AA85: 0.1875 | AB85: 0.1875 | AC85: 0.1875 | AD85: 0.1875 | AE85: 0.1875 | AF85: 0.1875 | AG85: 0.1875 | AH85: 0.1875 | AI85: 0.1875 | AJ85: 0.1875 | AK85: 0.1875 | AL85: 0.1875 | AM85: 0.1875 | AO85: =AVERAGE(D85:O85) -> 0.1875 | AP85: =AVERAGE(P85:AA85) -> 0.1875 | AQ85: =AVERAGE(AB85:AM85) -> 0.1875
A86: количество заявок | B86: шт | D86: =D84*D85*D7 -> 9.75 | E86: =E84*E85*E7 -> 18.4275 | F86: =F84*F85*F7 -> 21.767484 | G86: =G84*G85*G7 -> 20.570273 | H86: =H84*H85*H7 -> 7.7755631 | I86: =I84*I85*I7 -> 18.369768 | J86: =J84*J85*J7 -> 17.359431 | K86: =K84*K85*K7 -> 11.483263 | ... AM86: =AM84*AM85*AM7 -> 12 | AO86: =SUM(D86:O86) -> 181.50569 | AP86: =SUM(P86:AA86) -> 150 | AQ86: =SUM(AB86:AM86) -> 150
A87: APR, % | B87: % | D87: 0.66666667 | E87: 0.66666667 | F87: 0.66666667 | G87: 0.66666667 | H87: 0.66666667 | I87: 0.66666667 | J87: 0.66666667 | K87: 0.66666667 | L87: 0.66666667 | M87: 0.66666667 | N87: 0.66666667 | O87: 0.66666667 | P87: 0.66666667 | Q87: 0.66666667 | R87: 0.66666667 | S87: 0.66666667 | T87: 0.66666667 | U87: 0.66666667 | V87: 0.66666667 | W87: 0.66666667 | X87: 0.66666667 | Y87: 0.66666667 | Z87: 0.66666667 | AA87: 0.66666667 | AB87: 0.66666667 | AC87: 0.66666667 | AD87: 0.66666667 | AE87: 0.66666667 | AF87: 0.66666667 | AG87: 0.66666667 | AH87: 0.66666667 | AI87: 0.66666667 | AJ87: 0.66666667 | AK87: 0.66666667 | AL87: 0.66666667 | AM87: 0.66666667 | AO87: =AVERAGE(D87:O87) -> 0.66666667 | AP87: =AVERAGE(P87:AA87) -> 0.66666667 | AQ87: =AVERAGE(AB87:AM87) -> 0.66666667
A88: количество выдач | B88: шт | D88: =D86*D87 -> 6.5 | E88: =E86*E87 -> 12.285 | F88: =F86*F87 -> 14.511656 | G88: =G86*G87 -> 13.713515 | H88: =H86*H87 -> 5.1837087 | I88: =I86*I87 -> 12.246512 | J88: =J86*J87 -> 11.572954 | K88: =K86*K87 -> 7.6555089 | ... AM88: =AM86*AM87 -> 8 | AO88: =SUM(D88:O88) -> 121.00379 | AP88: =SUM(P88:AA88) -> 100 | AQ88: =SUM(AB88:AM88) -> 100
A89: ср. сумма выдачи | B89: тыс сом | D89: 600 | E89: 600 | F89: 600 | G89: 600 | H89: 600 | I89: 600 | J89: 600 | K89: 600 | L89: 600 | M89: 600 | N89: 600 | O89: 600 | P89: 600 | Q89: 600 | R89: 600 | S89: 600 | T89: 600 | U89: 600 | V89: 600 | W89: 600 | X89: 600 | Y89: 600 | Z89: 600 | AA89: 600 | AB89: 600 | AC89: 600 | AD89: 600 | AE89: 600 | AF89: 600 | AG89: 600 | AH89: 600 | AI89: 600 | AJ89: 600 | AK89: 600 | AL89: 600 | AM89: 600 | AO89: =AVERAGE(D89:O89) -> 600 | AP89: =AVERAGE(P89:AA89) -> 600 | AQ89: =AVERAGE(AB89:AM89) -> 600
A90: выдачи | B90: тыс сом | D90: =D88*D89 -> 3900 | E90: =E88*E89 -> 7371 | F90: =F88*F89 -> 8706.9937 | G90: =G88*G89 -> 8228.1091 | H90: =H88*H89 -> 3110.2252 | I90: =I88*I89 -> 7347.9071 | J90: =J88*J89 -> 6943.7722 | K90: =K88*K89 -> 4593.3053 | ... AM90: =AM88*AM89 -> 4800 | AO90: =SUM(D90:O90) -> 72602.275 | AP90: =SUM(P90:AA90) -> 60000 | AQ90: =SUM(AB90:AM90) -> 60000
A91: cр. срок портфеля | B91: мес | D91: 24 | E91: 24 | F91: 24 | G91: 24 | H91: 24 | I91: 24 | J91: 24 | K91: 24 | L91: 24 | M91: 24 | N91: 24 | O91: 24 | P91: 24 | Q91: 24 | R91: 24 | S91: 24 | T91: 24 | U91: 24 | V91: 24 | W91: 24 | X91: 24 | Y91: 24 | Z91: 24 | AA91: 24 | AB91: 24 | AC91: 24 | AD91: 24 | AE91: 24 | AF91: 24 | AG91: 24 | AH91: 24 | AI91: 24 | AJ91: 24 | AK91: 24 | AL91: 24 | AM91: 24 | AO91: =AVERAGE(D91:O91) -> 24 | AP91: =AVERAGE(P91:AA91) -> 24 | AQ91: =AVERAGE(AB91:AM91) -> 24
A92: погашения | B92: тыс сом | D92: =C93/D91 -> 9291.6667 | E92: =D93/E91 -> 9067.0139 | F92: =E93/F91 -> 8996.3466 | G92: =F93/G91 -> 8984.2903 | H92: =G93/H91 -> 8952.7827 | I92: =H93/I91 -> 8709.3428 | J92: =I93/J91 -> 8652.6163 | K92: =J93/K91 -> 8581.4145 | ... AM92: =AL93/AM91 -> 6166.2021 | AO92: =SUM(D92:O92) -> 104308.32 | AP92: =SUM(P92:AA92) -> 87918.411 | AQ92: =SUM(AB92:AM92) -> 76752.893
A93: кредитный портфель | B93: тыс сом | C93: 223000 | D93: =C93+D90-D92 -> 217608.33 | E93: =D93+E90-E92 -> 215912.32 | F93: =E93+F90-F92 -> 215622.97 | G93: =F93+G90-G92 -> 214866.79 | H93: =G93+H90-H92 -> 209024.23 | I93: =H93+I90-I92 -> 207662.79 | J93: =I93+J90-J92 -> 205953.95 | K93: =J93+K90-K92 -> 201965.84 | ... AM93: =AL93+AM90-AM92 -> 146622.65 | AO93: =O93 -> 191293.95 | AP93: =AA93 -> 163375.54 | AQ93: =AM93 -> 146622.65
A94: доля просроченной задолженности, % | B94: % | D94: 0.01396861 | E94: 0.01396861 | F94: 0.01396861 | G94: 0.01396861 | H94: 0.01396861 | I94: 0.01396861 | J94: 0.01396861 | K94: 0.01396861 | L94: 0.01396861 | M94: 0.01396861 | N94: 0.01396861 | O94: 0.01396861 | P94: 0.01396861 | Q94: 0.01396861 | R94: 0.01396861 | S94: 0.01396861 | T94: 0.01396861 | U94: 0.01396861 | V94: 0.01396861 | W94: 0.01396861 | X94: 0.01396861 | Y94: 0.01396861 | Z94: 0.01396861 | AA94: 0.01396861 | AB94: 0.01396861 | AC94: 0.01396861 | AD94: 0.01396861 | AE94: 0.01396861 | AF94: 0.01396861 | AG94: 0.01396861 | AH94: 0.01396861 | AI94: 0.01396861 | AJ94: 0.01396861 | AK94: 0.01396861 | AL94: 0.01396861 | AM94: 0.01396861 | AO94: =O94 -> 0.01396861 | AP94: =AA94 -> 0.01396861 | AQ94: =AM94 -> 0.01396861
A95: просроченная задолженность | B95: тыс сом | D95: =D93*D94 -> 3039.6859 | E95: =E93*E94 -> 3015.995 | F95: =F93*F94 -> 3011.9531 | G95: =G93*G94 -> 3001.3903 | H95: =H93*H94 -> 2919.7779 | I95: =I93*I94 -> 2900.7605 | J95: =J93*J94 -> 2876.8904 | K95: =K93*K94 -> 2821.182 | ... AM95: =AM93*AM94 -> 2048.1146 | AO95: =O95 -> 2672.1106 | AP95: =AA95 -> 2282.1292 | AQ95: =AM95 -> 2048.1146
A96: ср. % ставка портфеля | B96: % | D96: 0.22 | E96: 0.22 | F96: 0.22 | G96: 0.22 | H96: 0.22 | I96: 0.22 | J96: 0.22 | K96: 0.22 | L96: 0.22 | M96: 0.22 | N96: 0.22 | O96: 0.22 | P96: 0.22 | Q96: 0.22 | R96: 0.22 | S96: 0.22 | T96: 0.22 | U96: 0.22 | V96: 0.22 | W96: 0.22 | X96: 0.22 | Y96: 0.22 | Z96: 0.22 | AA96: 0.22 | AB96: 0.22 | AC96: 0.22 | AD96: 0.22 | AE96: 0.22 | AF96: 0.22 | AG96: 0.22 | AH96: 0.22 | AI96: 0.22 | AJ96: 0.22 | AK96: 0.22 | AL96: 0.22 | AM96: 0.22 | AO96: =AVERAGE(D96:O96) -> 0.22 | AP96: =AVERAGE(P96:AA96) -> 0.22 | AQ96: =AVERAGE(AB96:AM96) -> 0.22
A97: ср. % ставка фондирования | B97: % | D97: 0.15 | E97: 0.15 | F97: 0.15 | G97: 0.15 | H97: 0.15 | I97: 0.15 | J97: 0.15 | K97: 0.15 | L97: 0.15 | M97: 0.15 | N97: 0.15 | O97: 0.15 | P97: 0.15 | Q97: 0.15 | R97: 0.15 | S97: 0.15 | T97: 0.15 | U97: 0.15 | V97: 0.15 | W97: 0.15 | X97: 0.15 | Y97: 0.15 | Z97: 0.15 | AA97: 0.15 | AB97: 0.15 | AC97: 0.15 | AD97: 0.15 | AE97: 0.15 | AF97: 0.15 | AG97: 0.15 | AH97: 0.15 | AI97: 0.15 | AJ97: 0.15 | AK97: 0.15 | AL97: 0.15 | AM97: 0.15 | AO97: =AVERAGE(D97:O97) -> 0.15 | AP97: =AVERAGE(P97:AA97) -> 0.15 | AQ97: =AVERAGE(AB97:AM97) -> 0.15
A98: ср. % резервирования | B98: % | D98: 0.031390135 | E98: 0.031390135 | F98: 0.031390135 | G98: 0.031390135 | H98: 0.031390135 | I98: 0.031390135 | J98: 0.031390135 | K98: 0.031390135 | L98: 0.031390135 | M98: 0.031390135 | N98: 0.031390135 | O98: 0.031390135 | P98: 0.031390135 | Q98: 0.031390135 | R98: 0.031390135 | S98: 0.031390135 | T98: 0.031390135 | U98: 0.031390135 | V98: 0.031390135 | W98: 0.031390135 | X98: 0.031390135 | Y98: 0.031390135 | Z98: 0.031390135 | AA98: 0.031390135 | AB98: 0.031390135 | AC98: 0.031390135 | AD98: 0.031390135 | AE98: 0.031390135 | AF98: 0.031390135 | AG98: 0.031390135 | AH98: 0.031390135 | AI98: 0.031390135 | AJ98: 0.031390135 | AK98: 0.031390135 | AL98: 0.031390135 | AM98: 0.031390135 | AO98: =AVERAGE(D98:O98) -> 0.031390135 | AP98: =AVERAGE(P98:AA98) -> 0.031390135 | AQ98: =AVERAGE(AB98:AM98) -> 0.031390135
A99: ср. комиссия на 1 клиента | B99: тыс сом | AO99: =AVERAGE(D99:O99) -> #DIV/0! | AP99: =AVERAGE(P99:AA99) -> #DIV/0! | AQ99: =AVERAGE(AB99:AM99) -> #DIV/0!
A100: РППУ на конец месяца | B100: тыс сом | C100: -7000 | D100: =-D93*D98 -> -6830.7549 | E100: =-E93*E98 -> -6777.5168 | F100: =-F93*F98 -> -6768.4339 | G100: =-G93*G98 -> -6744.6973 | H100: =-H93*H98 -> -6561.2986 | I100: =-I93*I98 -> -6518.563 | J100: =-J93*J98 -> -6464.9221 | K100: =-K93*K98 -> -6339.7349 | ... AM100: =-AM93*AM98 -> -4602.5047 | AO100: =O100 -> -6004.7429 | AP100: =AA100 -> -5128.3802 | AQ100: =AM100 -> -4602.5047
A101: % доход | B101: тыс сом | D101: =(C93+D93)/2*D96/12*(1-2/102) -> 3959.7154 | E101: =(D93+E93)/2*E96/12*(1-2/102) -> 3896.0189 | F101: =(E93+F93)/2*F96/12*(1-2/102) -> 3878.1766 | G101: =(F93+G93)/2*G96/12*(1-2/102) -> 3868.7805 | H101: =(G93+H93)/2*H96/12*(1-2/102) -> 3809.4781 | I101: =(H93+I93)/2*I96/12*(1-2/102) -> 3744.7363 | J101: =(I93+J93)/2*J96/12*(1-2/102) -> 3717.1439 | K101: =(J93+K93)/2*K96/12*(1-2/102) -> 3665.9458 | ... AM101: =(AL93+AM93)/2*AM96/12*(1-2/102) -> 2647.6524 | AO101: =SUM(D101:O101) -> 44710.807 | AP101: =SUM(P101:AA101) -> 37674.688 | AQ101: =SUM(AB101:AM101) -> 32958.534
A102: трансфертный расход | B102: тыс сом | D102: =-(C93+D93)/2*D97/12 -> -2753.8021 | E102: =-(D93+E93)/2*E97/12 -> -2709.5041 | F102: =-(E93+F93)/2*F97/12 -> -2697.0955 | G102: =-(F93+G93)/2*G97/12 -> -2690.5609 | H102: =-(G93+H93)/2*H97/12 -> -2649.3188 | I102: =-(H93+I93)/2*I97/12 -> -2604.2939 | J102: =-(I93+J93)/2*J97/12 -> -2585.1046 | K102: =-(J93+K93)/2*K97/12 -> -2549.4987 | ... AM102: =-(AL93+AM93)/2*AM97/12 -> -1841.3219 | AO102: =SUM(D102:O102) -> -31094.334 | AP102: =SUM(P102:AA102) -> -26201.033 | AQ102: =SUM(AB102:AM102) -> -22921.162
A103: расходы на провизии | B103: тыс сом | D103: =(D100-C100) -> 169.24514 | E103: =(E100-D100) -> 53.238104 | F103: =(F100-E100) -> 9.0828263 | G103: =(G100-F100) -> 23.736629 | H103: =(H100-G100) -> 183.39867 | I103: =(I100-H100) -> 42.73565 | J103: =(J100-I100) -> 53.640846 | K103: =(K100-J100) -> 125.18728 | ... AM103: =(AM100-AL100) -> 42.885269 | AO103: =SUM(D103:O103) -> 995.25709 | AP103: =SUM(P103:AA103) -> 876.36266 | AQ103: =SUM(AB103:AM103) -> 525.87557
A104: комиссии | B104: тыс сом | D104: =D99*(AVERAGE(C93:D93)/D89)*(1-2/102) -> 0 | E104: =E99*(AVERAGE(D93:E93)/E89)*(1-2/102) -> 0 | F104: =F99*(AVERAGE(E93:F93)/F89)*(1-2/102) -> 0 | G104: =G99*(AVERAGE(F93:G93)/G89)*(1-2/102) -> 0 | H104: =H99*(AVERAGE(G93:H93)/H89)*(1-2/102) -> 0 | I104: =I99*(AVERAGE(H93:I93)/I89)*(1-2/102) -> 0 | J104: =J99*(AVERAGE(I93:J93)/J89)*(1-2/102) -> 0 | K104: =K99*(AVERAGE(J93:K93)/K89)*(1-2/102) -> 0 | ... AM104: =AM99*(AVERAGE(AL93:AM93)/AM89)*(1-2/102) -> 0 | AO104: =SUM(D104:O104) -> 0 | AP104: =SUM(P104:AA104) -> 0 | AQ104: =SUM(AB104:AM104) -> 0
A105: операционные доходы | B105: тыс сом | D105: =SUM(D101:D104) -> 1375.1585 | E105: =SUM(E101:E104) -> 1239.753 | F105: =SUM(F101:F104) -> 1190.1639 | G105: =SUM(G101:G104) -> 1201.9561 | H105: =SUM(H101:H104) -> 1343.5579 | I105: =SUM(I101:I104) -> 1183.1781 | J105: =SUM(J101:J104) -> 1185.6801 | K105: =SUM(K101:K104) -> 1241.6344 | ... AM105: =SUM(AM101:AM104) -> 849.21576 | AO105: =SUM(D105:O105) -> 14611.73 | AP105: =SUM(P105:AA105) -> 12350.018 | AQ105: =SUM(AB105:AM105) -> 10563.247
...

Sheet МСБ.2
A1: Малый и средний бизнес - Счета и депозиты
D3: 46023 | E3: 46054 | F3: 46082 | G3: 46113 | H3: 46143 | I3: 46174 | J3: 46204 | K3: 46235 | L3: 46266 | M3: 46296 | N3: 46327 | O3: 46357 | P3: 46388 | Q3: 46419 | R3: 46447 | S3: 46478 | T3: 46508 | U3: 46539 | V3: 46569 | W3: 46600 | X3: 46631 | Y3: 46661 | Z3: 46692 | AA3: 46722 | AB3: 46753 | AC3: 46784 | AD3: 46813 | AE3: 46844 | AF3: 46874 | AG3: 46905 | AH3: 46935 | AI3: 46966 | AJ3: 46997 | AK3: 47027 | AL3: 47058 | AM3: 47088 | AO3: =YEAR(O3) -> 2026 | AP3: =YEAR(AA3) -> 2027 | AQ3: =YEAR(AM3) -> 2028
D4: m1 | E4: m2 | F4: m3 | G4: m4 | H4: m5 | I4: m6 | J4: m7 | K4: m8 | L4: m9 | M4: m10 | N4: m11 | O4: m12 | P4: m13 | Q4: m14 | R4: m15 | S4: m16 | T4: m17 | U4: m18 | V4: m19 | W4: m20 | X4: m21 | Y4: m22 | Z4: m23 | AA4: m24 | AB4: m25 | AC4: m26 | AD4: m27 | AE4: m28 | AF4: m29 | AG4: m30 | AH4: m31 | AI4: m32 | AJ4: m33 | AK4: m34 | AL4: m35 | AM4: m36 | AO4: Y1 | AP4: Y2 | AQ4: Y3
D5: 1 | E5: =D5+1 -> 2 | F5: =E5+1 -> 3 | G5: =F5+1 -> 4 | H5: =G5+1 -> 5 | I5: =H5+1 -> 6 | J5: =I5+1 -> 7 | K5: =J5+1 -> 8 | L5: =K5+1 -> 9 | ... AM5: =AL5+1 -> 36
A7: Итого
A8: портфель | B8: тыс сом | C8: =C18+C160+C296+C428 -> 3292238.3 | D8: =D18+D160+D296+D428 -> 3463787.1 | E8: =E18+E160+E296+E428 -> 3482601.4 | F8: =F18+F160+F296+F428 -> 3505955.3 | G8: =G18+G160+G296+G428 -> 3626888.7 | H8: =H18+H160+H296+H428 -> 3414303.8 | I8: =I18+I160+I296+I428 -> 3512341.1 | J8: =J18+J160+J296+J428 -> 3533929.9 | ... AM8: =AM18+AM160+AM296+AM428 -> 5799594.7 | AO8: =O8 -> 3603006.9 | AP8: =AA8 -> 4671271.3 | AQ8: =AM8 -> 5799594.7
A9: % расход | B9: тыс сом | D9: =D19+D161+D297+D429 -> -16426.849 | E9: =E19+E161+E297+E429 -> -17016.382 | F9: =F19+F161+F297+F429 -> -17035.616 | G9: =G19+G161+G297+G429 -> -17647.723 | H9: =H19+H161+H297+H429 -> -16880.699 | I9: =I19+I161+I297+I429 -> -15979.445 | J9: =J19+J161+J297+J429 -> -16441.408 | K9: =K19+K161+K297+K429 -> -16186.533 | ... AM9: =AM19+AM161+AM297+AM429 -> -34275.812 | AO9: =SUM(D9:O9) -> -201107.3 | AP9: =SUM(P9:AA9) -> -235695.88 | AQ9: =SUM(AB9:AM9) -> -354442.17
A10: трансфертный доход | B10: тыс сом | D10: =D20+D162+D298+D430 -> 31712.893 | E10: =E20+E162+E298+E430 -> 32664.534 | F10: =F20+F162+F298+F430 -> 32817.906 | G10: =G20+G162+G298+G430 -> 33605.18 | H10: =H20+H162+H298+H430 -> 32912.094 | I10: =I20+I162+I298+I430 -> 32067.072 | J10: =J20+J162+J298+J430 -> 32676.697 | K10: =K20+K162+K298+K430 -> 32503.068 | ... AM10: =AM20+AM162+AM298+AM430 -> 48790.211 | AO10: =SUM(D10:O10) -> 394266.73 | AP10: =SUM(P10:AA10) -> 429279.75 | AQ10: =SUM(AB10:AM10) -> 533621.34
A11: операционные доходы | B11: тыс сом | D11: =D21+D163+D299+D431 -> 15286.044 | E11: =E21+E163+E299+E431 -> 15648.152 | F11: =F21+F163+F299+F431 -> 15782.29 | G11: =G21+G163+G299+G431 -> 15957.457 | H11: =H21+H163+H299+H431 -> 16031.394 | I11: =I21+I163+I299+I431 -> 16087.626 | J11: =J21+J163+J299+J431 -> 16235.289 | K11: =K21+K163+K299+K431 -> 16316.535 | ... AM11: =AM21+AM163+AM299+AM431 -> 14514.399 | AO11: =SUM(D11:O11) -> 193159.43 | AP11: =SUM(P11:AA11) -> 193583.87 | AQ11: =SUM(AB11:AM11) -> 179179.16
A12: начисление расходов в ФЗД | B12: тыс сом | D12: =D22+D164+D300+D432 -> -563.00211 | E12: =E22+E164+E300+E432 -> -578.8657 | F12: =F22+F164+F300+F432 -> -582.37973 | G12: =G22+G164+G300+G432 -> -594.40367 | H12: =H22+H164+H300+H432 -> -586.76605 | I12: =I22+I164+I300+I432 -> -577.22041 | J12: =J22+J164+J300+J432 -> -587.18925 | K12: =K22+K164+K300+K432 -> -586.94943 | ... AM12: =AM22+AM164+AM300+AM432 -> -956.15748 | AO12: =SUM(D12:O12) -> -7078.6106 | AP12: =SUM(P12:AA12) -> -8093.0866 | AQ12: =SUM(AB12:AM12) -> -10372.435
A13: операционные расходы | B13: тыс сом | D13: =D23+D165+D301+D433 -> -572.91952 | E13: =E23+E165+E301+E433 -> -588.80187 | F13: =F23+F165+F301+F433 -> -592.47894 | G13: =G23+G165+G301+G433 -> -604.66973 | H13: =H23+H165+H301+H433 -> -597.22032 | I13: =I23+I165+I301+I433 -> -587.81554 | J13: =J23+J165+J301+J433 -> -598.13353 | K13: =K23+K165+K301+K433 -> -598.11067 | ... AM13: =AM23+AM165+AM301+AM433 -> -977.07387 | AO13: =SUM(D13:O13) -> -7211.05 | AP13: =SUM(P13:AA13) -> -8274.3286 | AQ13: =SUM(AB13:AM13) -> -10600.333
A14: прибыль | B14: тыс сом | D14: =D24+D166+D302+D434 -> 14713.125 | E14: =E24+E166+E302+E434 -> 15059.35 | F14: =F24+F166+F302+F434 -> 15189.812 | G14: =G24+G166+G302+G434 -> 15352.787 | H14: =H24+H166+H302+H434 -> 15434.174 | I14: =I24+I166+I302+I434 -> 15499.811 | J14: =J24+J166+J302+J434 -> 15637.156 | K14: =K24+K166+K302+K434 -> 15718.424 | ... AM14: =AM24+AM166+AM302+AM434 -> 13537.325 | AO14: =SUM(D14:O14) -> 185948.38 | AP14: =SUM(P14:AA14) -> 185309.54 | AQ14: =SUM(AB14:AM14) -> 168578.83
A16: Депозит "Срочный" (ЮЛ, ИП)
A17: Итого
